Workbook

Sheet Key
A1: Guide to interpreting this cost-effectiveness analysis
A2: Sheet descriptions
E4: Main CEA | F4: This sheet contains the primary calculations that result in final cost-effectiveness estimates. This sheet draws on inputs from the "Inputs" sheet and inputs calculated in the other supplemental sheets listed below.
E5: Counterfactual mortality | F5: This sheet contains our calculations of how high mortality rates would be in the absence of VAS campaigns.
E6: External validity | F6: This sheet contains our calculations of the external validity adjustments we apply to the effect of VAS on mortality, based on differences between the populations treated in studies and the populations treated by grantee programs.
E7: Leverage/Funging | F7: This sheet contains our calculations of the impact that crowding in and crowding out funding by other contributors has on the benefits of the program.
E8: Inputs | F8: This sheet contains all of the manually entered input values informing the CEA, along with the sources and reasoning supporting them. This sheet also contains inputs sourced from the "GBD estimates" sheet.
E9: GBD estimates | F9: This sheet contains disease burden and population datasets downloaded from the Institute of Health Metrics (IHME)'s Global Burden of Disease (GBD) project.
E10: Simple CEA | F10: This sheet contains a simplified version of the CEA that is designed to be comparable to our CEAs of other programs.
E11: Confidence intervals | F11: This sheet contains our best guesses of the 25th and 75th percentile values for each of the parameters of our simple CEA.
E12: Sensitivity analysis | F12: This sheet contains the outputs of our sensitivity analysis that tests the cost-effectiveness ranges that would result from updating certain inputs to their 25th or 75th percentile values.
A14: Terminology key
C16: Terms specific to this CEA
E17: VAS | F17: Stands for vitamin A supplementation; describes an intervention in which vitamin A supplements are delivered to a population in an effort to reduce rates of vitamin A deficiency.
E18: VAD | F18: Stands for vitamin A deficiency; describes a condition resulting from insufficient dietary intake of vitamin A that is associated with increased morbidity and mortality.
E19: Stunting | F19: Describes a condition in which a child has a height-for-age measurement more than two standard deviations below average. We use rates of stunting as one of several proxies for rates of vitamin A deficiency.
E20: Wasting | F20: Describes a condition in which a child has a weight-for-age measurement more than two standard deviations below average. We use rates of wasting as one of several proxies for rates of vitamin A deficiency.
E21: Anemia | F21: Describes a condition in which a person does not have enough healthy red blood cells or hemoglobin in their blood to transport oxygen through their body. We use anemia rates as one of several proxies for rates of vitamin A deficiency.
E22: Poverty headcount | F22: Refers to the percentage of a population that has income or consumption levels lower than a given poverty benchmark.
E23: Fixed-effects | F23: A fixed-effect meta-analysis assumes that the true impact of the intervention is consistent in every study in the analysis. Differences between study results are assumed to be solely down to chance. The main estimate from the analysis can be interpreted as the typical intervention effect.
E24: Random-effects | F24: A random-effects meta-analysis assumes that the true impact of the intervention varies and follows some distribution. The main estimate from the analysis can be interpreted as the average impact of the intervention across heterogenous studies with different findings.
C26: Terms used across GiveWell's CEAs
E27: Internal validity | F27: Describes an adjustment we make to the treatment effect of an intervention to account for the possibility that the treatment effects found in studies may not represent the true effect the intervention had on the populations studied.
E28: External validity | F28: Describes an adjustment we make to the treatment effect of an intervention to account for differences in the program implementation or populations treated in studies from the program implementation or populations treated by grantee programs.
E29: Leverage | F29: Describes a situation where a grantee's spending on a program causes other organizations or governments to contribute more to the program than they otherwise would have. In most cases, accounting for leverage increases cost-effectiveness
E30: Funging | F30: Describes a situation where a grantee's spending on a program causes other organizations or governments to contribute less to the program than they otherwise would have. In most cases, accounting for funging decreases cost-effectiveness.
E31: In-kind contributions | F31: Describes non-financial (e.g., staff time, office space) contributions to a program that might otherwise have been used for other activities or programs.
E32: Counterfactual | F32: In most cases, describes the state of the world that would exist if we did not provide funding to a grantee for a program. When discussing the "counterfactual value of other actors' spending," we are referring to how much benefit another organization's or government's spending would generate if it were spent on something other than the grantee program.
E33: Moral weights | F33: To compare cost-effectiveness across different programs, we use ‘moral weights’ to quantify the benefits of different program impacts (e.g. increased income vs reduced deaths). We benchmark the value of each benefit to a value of 1, which we define as the value of doubling someone’s consumption for one year.
E34: Philanthropic actors | F34: Non-governmental organizations (NGOs) providing funding to philanthropic programs.
A36: Unit and source key
C38: Unit labels used in the CEA
E39: # | F39: Number
E40: per 1k | F40: Rate per 1,000
E41: per 100k | F41: Rate per 100,000
E42: $ | F42: U.S. dollars
E43: ln($) | F43: The natural logarithm of a monetary value
E44: % | F44: Percentage
E45: ppt | F45: Percentage points
E46: UoV | F46: Units of value: an arbitrary unit GiveWell uses to compare the moral value of different types of outcomes, such as saving lives or increasing income
E47: xbenchmark | F47: Cost-effectiveness in terms of multiples of GiveWell's benchmark
C49: Source labels used in the CEA
E51: Input | F51: A value pulled from the "Inputs" sheet
E52: Calc | F52: A value calculated using other values in the same sheet
E53: Supp | F53: A value pulled from one of the sheets hosting supplemental calculations
E54: Main | F54: A value pulled from the "Main CEA" sheet
E55: Feed | F55: A value pulled from an earlier section within the same sheet
A57: GiveWell analyses informing this model
C59: Analyses specific to this CEA
E60: GiveWell's analysis of Helen Keller International's cost per supplement
E61: GiveWell's analysis of coverage estimates from RCTs of VAS from Imdad et al. 2017
E62: GiveWell's analysis of baseline VAS coverage in regions of Madagascar
E63: GW's analysis of baseline mortality for Imdad et al. 2017
E64: GW's analysis of recent vitamin A deficiency surveys
E65: GW's analysis of disease-specific mortality effects of VAS
E66: GW's analysis of baseline VAS coverage
E67: GW's analysis of subnational mortality rates for VAS
E68: GiveWell, VAS supplementary analysis, 2024
C70: Analyses referenced across GiveWell's CEAs
E71: GW's moral weights and discount rate
E72: GW's supplemental intervention-level adjustments
E73: GWs benchmark for evaluating cost effectiveness
E74: GW's analysis of the counterfactual value of other actors' spending
E75: GW's analysis of the counterfactual value of Global Fund spending

Sheet Main CEA
I1: Helen Keller International | Q1: Helen Keller International | Y1: Helen Keller International | AG1: Nutrition International
I2: Burkina Faso | J2: Cameroon | K2: Côte d'Ivoire | L2: DRC | M2: Guinea | N2: Kenya | O2: Madagascar | P2: Mali | Q2: Niger | R2: Nigeria | S2: Nigeria | T2: Nigeria | U2: Nigeria | V2: Nigeria | W2: Nigeria | X2: Nigeria | Y2: Nigeria | Z2: Nigeria | AA2: Nigeria | AB2: Nigeria | AC2: Nigeria | AD2: Nigeria | AE2: Nigeria | AF2: Nigeria | AG2: Angola | AH2: Chad | AI2: Togo | AJ2: Uganda
A3: Main calculations | F3: unit | G3: type | H3: Overall | R3: Adamawa | S3: Akwa Ibom | T3: Anambra | U3: Benue | V3: Delta | W3: Ebonyi | X3: Edo | Y3: Ekiti | Z3: Imo | AA3: Kogi | AB3: Nasarawa | AC3: Ogun | AD3: Osun | AE3: Rivers | AF3: Taraba
E4: Final cost-effectiveness estimate (pulled from below for visibility) | F4: =F149 -> xbenchmark | G4: feed | H4: =H149 -> - | I4: =I149 -> 22.604158 | J4: =J149 -> 15.907951 | K4: =K149 -> 8.5391703 | L4: =L149 -> 16.914533 | M4: =M149 -> 10.932207 | N4: =N149 -> 4.7974496 | O4: =O149 -> 15.912911 | ... AJ4: =AJ149 -> 6.3105992
A5: Costs
C7: GiveWell costs
E8: Grant size | F8: =Inputs!F8 -> $ | G8: =Inputs!G8 -> input | H8: =Inputs!H8 -> 1000000 | I8: =Inputs!I8 -> - | J8: =Inputs!J8 -> - | K8: =Inputs!K8 -> - | L8: =Inputs!L8 -> - | M8: =Inputs!M8 -> - | ... AJ8: =Inputs!AJ8 -> -
C10: Cost breakdown
E11: Percentage of total costs covered by the grantee | F11: =Inputs!F11 -> % | G11: =Inputs!G11 -> input | H11: =Inputs!H11 -> - | I11: =Inputs!I11 -> 0.4310638 | J11: =Inputs!J11 -> 0.6403403 | K11: =Inputs!K11 -> 0.4659904 | L11: =Inputs!L11 -> 0.4659904 | M11: =Inputs!M11 -> 0.5527665 | ... AJ11: =Inputs!AJ11 -> 0.7
E12: Percentage of total costs covered by Nutrition International (vitamin A capsule procurement) | F12: =Inputs!F12 -> % | G12: =Inputs!G12 -> input | H12: =Inputs!H12 -> - | I12: =Inputs!I12 -> 0.0642112 | J12: =Inputs!J12 -> 0.0596597 | K12: =Inputs!K12 -> 0.0697078 | L12: =Inputs!L12 -> 0.0697078 | M12: =Inputs!M12 -> 0.0486625 | ... AJ12: =Inputs!AJ12 -> 0
E13: Percentage of total costs covered by other philanthropic actors | F13: =Inputs!F13 -> % | G13: =Inputs!G13 -> input | H13: =Inputs!H13 -> - | I13: =Inputs!I13 -> 0.0565391 | J13: =Inputs!J13 -> 0 | K13: =Inputs!K13 -> 0.1323195 | L13: =Inputs!L13 -> 0.1323195 | M13: =Inputs!M13 -> 0.098571 | ... AJ13: =Inputs!AJ13 -> 0
E14: Percentage of total costs covered by domestic governments (financial contributions) | F14: =Inputs!F14 -> % | G14: =Inputs!G14 -> input | H14: =Inputs!H14 -> - | I14: =Inputs!I14 -> 0.1481859 | J14: =Inputs!J14 -> 0 | K14: =Inputs!K14 -> 0.0319823 | L14: =Inputs!L14 -> 0.0319823 | M14: =Inputs!M14 -> 0 | ... AJ14: =Inputs!AJ14 -> 0
E15: Percentage of total costs covered by domestic governments (in-kind contributions) | F15: =Inputs!F15 -> % | G15: =Inputs!G15 -> input | H15: =Inputs!H15 -> - | I15: =Inputs!I15 -> 0.3 | J15: =Inputs!J15 -> 0.3 | K15: =Inputs!K15 -> 0.3 | L15: =Inputs!L15 -> 0.3 | M15: =Inputs!M15 -> 0.3 | ... AJ15: =Inputs!AJ15 -> 0.3
C17: Total costs
E18: Total spending by all contributors | F18: $ | G18: calc | H18: - | I18: =IF(I8="-",$H8/I11,I8/I11) -> 2319842.2 | J18: =IF(J8="-",$H8/J11,J8/J11) -> 1561669.6 | K18: =IF(K8="-",$H8/K11,K8/K11) -> 2145967 | L18: =IF(L8="-",$H8/L11,L8/L11) -> 2145967 | M18: =IF(M8="-",$H8/M11,M8/M11) -> 1809082.1 | N18: =IF(N8="-",$H8/N11,N8/N11) -> 2145967 | O18: =IF(O8="-",$H8/O11,O8/O11) -> 1671374.6 | P18: =IF(P8="-",$H8/P11,P8/P11) -> 2312316.8 | ... AJ18: =IF(AJ8="-",$H8/AJ11,AJ8/AJ11) -> 1428571.4
C20: Total spending attributable to different actors
E21: Total spending contributed by grantee | F21: $ | G21: calc | H21: - | I21: =I$18*I11 -> 1000000 | J21: =J$18*J11 -> 1000000 | K21: =K$18*K11 -> 1000000 | L21: =L$18*L11 -> 1000000 | M21: =M$18*M11 -> 1000000 | N21: =N$18*N11 -> 1000000 | O21: =O$18*O11 -> 1000000 | P21: =P$18*P11 -> 1000000 | ... AJ21: =AJ$18*AJ11 -> 1000000
E22: Total spending contributed by Nutrition International (vitamin A capsule procurement) | F22: $ | G22: calc | H22: - | I22: =I$18*I12 -> 148959.85 | J22: =J$18*J12 -> 93168.742 | K22: =K$18*K12 -> 149590.64 | L22: =L$18*L12 -> 149590.64 | M22: =M$18*M12 -> 88034.459 | N22: =N$18*N12 -> 149590.64 | O22: =O$18*O12 -> 116507.85 | P22: =P$18*P12 -> 195582.46 | ... AJ22: =AJ$18*AJ12 -> 0
E23: Total spending contributed by other philanthropic actors | F23: $ | G23: calc | H23: - | I23: =I$18*I13 -> 131161.79 | J23: =J$18*J13 -> 0 | K23: =K$18*K13 -> 283953.27 | L23: =L$18*L13 -> 283953.27 | M23: =M$18*M13 -> 178323.04 | N23: =N$18*N13 -> 283953.27 | O23: =O$18*O13 -> 0 | P23: =P$18*P13 -> 423039.28 | ... AJ23: =AJ$18*AJ13 -> 0
E24: Total spending contributed by domestic governments (financial contributions) | F24: $ | G24: calc | H24: - | I24: =I$18*I14 -> 343767.91 | J24: =J$18*J14 -> 0 | K24: =K$18*K14 -> 68632.959 | L24: =L$18*L14 -> 68632.959 | M24: =M$18*M14 -> 0 | N24: =N$18*N14 -> 68632.959 | O24: =O$18*O14 -> 53454.405 | P24: =P$18*P14 -> 0 | ... AJ24: =AJ$18*AJ14 -> 0
E25: Total spending contributed by domestic governments (in-kind contributions) | F25: $ | G25: calc | H25: - | I25: =I$18*I15 -> 695952.66 | J25: =J$18*J15 -> 468500.89 | K25: =K$18*K15 -> 643790.09 | L25: =L$18*L15 -> 643790.09 | M25: =M$18*M15 -> 542724.64 | N25: =N$18*N15 -> 643790.09 | O25: =O$18*O15 -> 501412.4 | P25: =P$18*P15 -> 693695.03 | ... AJ25: =AJ$18*AJ15 -> 428571.43
C27: Upstream / downstream spending
E28: Total spending causally upstream of donations to grantee | F28: $ | G28: calc | H28: - | I28: =SUM(I21,I23:I24) -> 1474929.7 | J28: =SUM(J21,J23:J24) -> 1000000 | K28: =SUM(K21,K23:K24) -> 1352586.2 | L28: =SUM(L21,L23:L24) -> 1352586.2 | M28: =SUM(M21,M23:M24) -> 1178323 | N28: =SUM(N21,N23:N24) -> 1352586.2 | O28: =SUM(O21,O23:O24) -> 1053454.4 | P28: =SUM(P21,P23:P24) -> 1423039.3 | ... AJ28: =SUM(AJ21,AJ23:AJ24) -> 1000000
E29: Total spending causally downstream of donations to grantee | F29: $ | G29: calc | H29: - | I29: =SUM(I22,I25) -> 844912.52 | J29: =SUM(J22,J25) -> 561669.63 | K29: =SUM(K22,K25) -> 793380.72 | L29: =SUM(L22,L25) -> 793380.72 | M29: =SUM(M22,M25) -> 630759.1 | N29: =SUM(N22,N25) -> 793380.72 | O29: =SUM(O22,O25) -> 617920.24 | P29: =SUM(P22,P25) -> 889277.49 | ... AJ29: =SUM(AJ22,AJ25) -> 428571.43
C31: Cost per child covered
E32: Cost per vitamin A supplement delivered | F32: =Inputs!F18 -> $ | G32: =Inputs!G18 -> input | H32: =Inputs!H18 -> - | I32: =Inputs!I18 -> 1.05602 | J32: =Inputs!J18 -> 1.13658 | K32: =Inputs!K18 -> 1.01732 | L32: =Inputs!L18 -> 1.01732 | M32: =Inputs!M18 -> 1.39344 | ... AJ32: =Inputs!AJ18 -> 1.01732
E33: Supplementation rounds delivered per year | F33: =Inputs!F19 -> # | G33: =Inputs!G19 -> input | H33: =Inputs!H19 -> 2 | I33: =Inputs!I19 -> - | J33: =Inputs!J19 -> - | K33: =Inputs!K19 -> - | L33: =Inputs!L19 -> - | M33: =Inputs!M19 -> - | ... AJ33: =Inputs!AJ19 -> -
E34: Total cost per child receiving a year of vitamin A supplementation (VAS) | F34: $ | G34: calc | H34: - | I34: =I32*$H33 -> 2.11204 | J34: =J32*$H33 -> 2.27316 | K34: =K32*$H33 -> 2.03464 | L34: =L32*$H33 -> 2.03464 | M34: =M32*$H33 -> 2.78688 | N34: =N32*$H33 -> 2.03464 | O34: =O32*$H33 -> 2.03464 | P34: =P32*$H33 -> 1.60336 | ... AJ34: =AJ32*$H33 -> 2.03464
E35: Upstream costs per child receiving a year of VAS | F35: $ | G35: calc | H35: - | I35: =(I28/I18)*I34 -> 1.3428114 | J35: =(J28/J18)*J34 -> 1.455596 | K35: =(K28/K18)*K34 -> 1.2824177 | L35: =(L28/L18)*L34 -> 1.2824177 | M35: =(M28/M18)*M34 -> 1.8151995 | N35: =(N28/N18)*N34 -> 1.2824177 | O35: =(O28/O18)*O34 -> 1.2824177 | P35: =(P28/P18)*P34 -> 0.98673516 | ... AJ35: =(AJ28/AJ18)*AJ34 -> 1.424248
A37: Outputs
C39: Total children covered
E40: Total people under age 5 receiving a year of VAS | F40: # | G40: calc | H40: - | I40: =I21/I35 -> 744706.23 | J40: =J21/J35 -> 687003.83 | K40: =K21/K35 -> 779777.12 | L40: =L21/L35 -> 779777.12 | M40: =M21/M35 -> 550903.65 | N40: =N21/N35 -> 779777.12 | O40: =O21/O35 -> 779777.12 | P40: =P21/P35 -> 1013443.2 | ... AJ40: =AJ21/AJ35 -> 702124.91
E41: Baseline proportion of people under age 5 who receive VAS from non-campaign sources | F41: =Inputs!F139 -> % | G41: =Inputs!G139 -> input | H41: =Inputs!H139 -> - | I41: =Inputs!I139 -> 0.25 | J41: =Inputs!J139 -> 0.25 | K41: =Inputs!K139 -> 0.25 | L41: =Inputs!L139 -> 0.25 | M41: =Inputs!M139 -> 0.25 | ... AJ41: =Inputs!AJ139 -> 0.25
E42: Additional people under age 5 receiving a year of VAS as a result of the program | F42: # | G42: calc | H42: - | I42: =I40*(1-I41) -> 558529.67 | J42: =J40*(1-J41) -> 515252.87 | K42: =K40*(1-K41) -> 584832.84 | L42: =L40*(1-L41) -> 584832.84 | M42: =M40*(1-M41) -> 413177.74 | N42: =N40*(1-N41) -> 584832.84 | O42: =O40*(1-O41) -> 436675.19 | P42: =P40*(1-P41) -> 760082.37 | ... AJ42: =AJ40*(1-AJ41) -> 526593.68
A44: Outcomes
C46: Mortality reduction among people under age 5
E47: Reduction in all-cause mortality for children under age 5 participating in VAS programs found in the Imdad et al. 2017 meta-analysis | F47: =Inputs!F144 -> % | G47: =Inputs!G144 -> input | H47: =Inputs!H144 -> 0.24 | I47: =Inputs!I144 -> - | J47: =Inputs!J144 -> - | K47: =Inputs!K144 -> - | L47: =Inputs!L144 -> - | M47: =Inputs!M144 -> - | ... AJ47: =Inputs!AJ144 -> -
E48: Proportion of participating children that received VAS in the trials from the Imdad et al. 2017 meta-analysis | F48: =Inputs!F145 -> % | G48: =Inputs!G145 -> input | H48: =Inputs!H145 -> 0.8729567 | I48: =Inputs!I145 -> - | J48: =Inputs!J145 -> - | K48: =Inputs!K145 -> - | L48: =Inputs!L145 -> - | M48: =Inputs!M145 -> - | ... AJ48: =Inputs!AJ145 -> -
E49: Implied reduction in all-cause mortality for children under age 5 receiving vitamin A supplementation | F49: % | G49: calc | H49: =H47/H48 -> 0.27492773 | I49: - | J49: - | K49: - | L49: - | M49: - | N49: - | O49: - | P49: - | Q49: - | R49: - | S49: - | T49: - | U49: - | V49: - | W49: - | X49: - | Y49: - | Z49: - | AA49: - | AB49: - | AC49: - | AD49: - | AE49: - | AF49: - | AG49: - | AH49: - | AI49: - | AJ49: -
E50: Internal validity adjustment | F50: =Inputs!F146 -> % | G50: =Inputs!G146 -> input | H50: =Inputs!H146 -> -0.25 | I50: =Inputs!I146 -> - | J50: =Inputs!J146 -> - | K50: =Inputs!K146 -> - | L50: =Inputs!L146 -> - | M50: =Inputs!M146 -> - | ... AJ50: =Inputs!AJ146 -> -
E51: External validity adjustment | F51: ='External validity'!F182 -> % | G51: supp | H51: ='External validity'!H182 -> - | I51: ='External validity'!I182 -> -0.68871878 | J51: ='External validity'!J182 -> -0.4742831 | K51: ='External validity'!K182 -> -0.7452768 | L51: ='External validity'!L182 -> -0.52792594 | M51: ='External validity'!M182 -> -0.71225481 | N51: ='External validity'!N182 -> -0.69273135 | O51: ='External validity'!O182 -> -0.41093506 | ... AJ51: ='External validity'!AJ182 -> -0.72389772
E52: Expected reduction in all-cause mortality among 6-59-month-olds receiving vitamin A supplementation | F52: % | G52: calc | H52: - | I52: =$H49*(1+$H50)*(1+I51) -> 0.064184878 | J52: =$H49*(1+$H50)*(1+J51) -> 0.10840061 | K52: =$H49*(1+$H50)*(1+K51) -> 0.052522853 | L52: =$H49*(1+$H50)*(1+L51) -> 0.097339685 | M52: =$H49*(1+$H50)*(1+M51) -> 0.059331847 | N52: =$H49*(1+$H50)*(1+N51) -> 0.063357504 | O52: =$H49*(1+$H50)*(1+O51) -> 0.12146271 | P52: =$H49*(1+$H50)*(1+P51) -> 0.072696679 | ... AJ52: =$H49*(1+$H50)*(1+AJ51) -> 0.056931129
E53: ='Counterfactual mortality'!E26 -> Annual all-cause mortality rate among 6-59-month-olds in areas targeted for VAS | F53: ='Counterfactual mortality'!F26 -> % | G53: supp | H53: ='Counterfactual mortality'!H26 -> - | I53: ='Counterfactual mortality'!I26 -> 0.015038524 | J53: ='Counterfactual mortality'!J26 -> 0.007162023 | K53: ='Counterfactual mortality'!K26 -> 0.0076042273 | L53: ='Counterfactual mortality'!L26 -> 0.0061767469 | M53: ='Counterfactual mortality'!M26 -> 0.012447099 | N53: ='Counterfactual mortality'!N26 -> 0.0033328754 | O53: ='Counterfactual mortality'!O26 -> 0.0065381607 | ... AJ53: ='Counterfactual mortality'!AJ26 -> 0.0057949964
E54: Proportion of people under age 5 represented in GBD 2019 disease burden estimates who received VAS | F54: =Inputs!F147 -> % | G54: =Inputs!G147 -> input | H54: =Inputs!H147 -> - | I54: =Inputs!I147 -> 0.401 | J54: =Inputs!J147 -> 0.518 | K54: =Inputs!K147 -> 0.468 | L54: =Inputs!L147 -> 0.541 | M54: =Inputs!M147 -> 0.448 | ... AJ54: =Inputs!AJ147 -> 0.538
E55: All-cause mortality rate among 6-59-month-olds in the absence of VAS | F55: % | G55: calc | H55: - | I55: =I53/((1-I52)*I54+(1-I54)) -> 0.015435813 | J55: =J53/((1-J52)*J54+(1-J54)) -> 0.0075881067 | K55: =K53/((1-K52)*K54+(1-K54)) -> 0.0077958548 | L55: =L53/((1-L52)*L54+(1-L54)) -> 0.0065201004 | M55: =M53/((1-M52)*M54+(1-M54)) -> 0.012786985 | N55: =N53/((1-N52)*N54+(1-N54)) -> 0.0034664061 | O55: =O53/((1-O52)*O54+(1-O54)) -> 0.0068799443 | P55: =P53/((1-P52)*P54+(1-P54)) -> 0.01588123 | ... AJ55: =AJ53/((1-AJ52)*AJ54+(1-AJ54)) -> 0.0059780993
E56: Total deaths averted among people under age 5 | F56: # | G56: calc | H56: - | I56: =I42*I52*I55 -> 553.36091 | J56: =J42*J52*J55 -> 423.82404 | K56: =K42*K52*K55 -> 239.46597 | L56: =L42*L52*L55 -> 371.17265 | M56: =M42*M52*M55 -> 313.46781 | N56: =N42*N52*N55 -> 128.44265 | O56: =O42*O52*O55 -> 364.91055 | P56: =P42*P52*P55 -> 877.52473 | ... AJ56: =AJ42*AJ52*AJ55 -> 179.22086
C58: Long-term income increases for people under age 5
E59: Ratio of value generated from income increases to value generated from mortalities averted among people under age 15 by seasonal malaria chemoprevention (SMC) | F59: =Inputs!F150 -> # | G59: =Inputs!G150 -> input | H59: =Inputs!H150 -> 0.30647 | I59: =Inputs!I150 -> - | J59: =Inputs!J150 -> - | K59: =Inputs!K150 -> - | L59: =Inputs!L150 -> - | M59: =Inputs!M150 -> - | ... AJ59: =Inputs!AJ150 -> -
E60: Adjustment for income increases generated by VAS compared to SMC | F60: =Inputs!F151 -> % | G60: =Inputs!G151 -> input | H60: =Inputs!H151 -> -0.2 | I60: =Inputs!I151 -> - | J60: =Inputs!J151 -> - | K60: =Inputs!K151 -> - | L60: =Inputs!L151 -> - | M60: =Inputs!M151 -> - | ... AJ60: =Inputs!AJ151 -> -
E61: Ratio of value generated from income increases to value generated from mortalities averted among people under age 15 by VAS | F61: # | G61: calc | H61: =H59*(1+H60) -> 0.245176 | I61: - | J61: - | K61: - | L61: - | M61: - | N61: - | O61: - | P61: - | Q61: - | R61: - | S61: - | T61: - | U61: - | V61: - | W61: - | X61: - | Y61: - | Z61: - | AA61: - | AB61: - | AC61: - | AD61: - | AE61: - | AF61: - | AG61: - | AH61: - | AI61: - | AJ61: -
E62: Value assigned to averting a death of a person under age 5 with vitamin A supplementation | F62: =Inputs!F156 -> UoV | G62: =Inputs!G156 -> input | H62: =Inputs!H156 -> 118.73259 | I62: =Inputs!I156 -> - | J62: =Inputs!J156 -> - | K62: =Inputs!K156 -> - | L62: =Inputs!L156 -> - | M62: =Inputs!M156 -> - | ... AJ62: =Inputs!AJ156 -> -
E63: Units of value generated from deaths averted among people under age 15 | F63: UoV | G63: calc | H63: - | I63: =I56*$H62 -> 65701.974 | J63: =J56*$H62 -> 50321.726 | K63: =K56*$H62 -> 28432.415 | L63: =L56*$H62 -> 44070.29 | M63: =M56*$H62 -> 37218.845 | N63: =N56*$H62 -> 15250.328 | O63: =O56*$H62 -> 43326.775 | P63: =P56*$H62 -> 104190.78 | ... AJ63: =AJ56*$H62 -> 21279.357
E64: Units of value generated from long-term income increases | F64: UoV | G64: calc | H64: - | I64: =I63*$H61 -> 16108.547 | J64: =J63*$H61 -> 12337.68 | K64: =K63*$H61 -> 6970.9457 | L64: =L63*$H61 -> 10804.978 | M64: =M63*$H61 -> 9125.1676 | N64: =N63*$H61 -> 3739.0145 | O64: =O63*$H61 -> 10622.685 | P64: =P63*$H61 -> 25545.08 | ... AJ64: =AJ63*$H61 -> 5217.1877
M65: =M64/SUM(M63:M64) -> 0.19690068
A66: Value of outcomes
C68: Units of value from mortality reduction among people under age 5
E69: Value assigned to averting a death of a person under age 5 with vitamin A supplementation | F69: =Inputs!F156 -> UoV | G69: =Inputs!G156 -> input | H69: =Inputs!H156 -> 118.73259 | I69: =Inputs!I156 -> - | J69: =Inputs!J156 -> - | K69: =Inputs!K156 -> - | L69: =Inputs!L156 -> - | M69: =Inputs!M156 -> - | ... AJ69: =Inputs!AJ156 -> -
E70: Units of value from under-5 deaths averted (before accounting for leverage and funging) | F70: UoV | G70: calc | H70: - | I70: =I56*$H69 -> 65701.974 | J70: =J56*$H69 -> 50321.726 | K70: =K56*$H69 -> 28432.415 | L70: =L56*$H69 -> 44070.29 | M70: =M56*$H69 -> 37218.845 | N70: =N56*$H69 -> 15250.328 | O70: =O56*$H69 -> 43326.775 | P70: =P56*$H69 -> 104190.78 | ... AJ70: =AJ56*$H69 -> 21279.357
C72: Units of value from long-term income increases for children age 14 and under
E73: Units of value generated from long-term income increases per person receiving a year of VAS | F73: UoV | G73: calc | H73: =H42 -> - | I73: =I64/I42 -> 0.028840987 | J73: =J64/J42 -> 0.023944902 | K73: =K64/K42 -> 0.011919552 | L73: =L64/L42 -> 0.018475326 | M73: =M64/M42 -> 0.022085332 | N73: =N64/N42 -> 0.0063933046 | O73: =O64/O42 -> 0.024326285 | P73: =P64/P42 -> 0.033608305 | ... AJ73: =AJ64/AJ42 -> 0.0099074256
E74: Units of value from long-term income increases (before accounting for leverage and funging) | F74: UoV | G74: calc | H74: - | I74: =I42*I73 -> 16108.547 | J74: =J42*J73 -> 12337.68 | K74: =K42*K73 -> 6970.9457 | L74: =L42*L73 -> 10804.978 | M74: =M42*M73 -> 9125.1676 | N74: =N42*N73 -> 3739.0145 | O74: =O42*O73 -> 10622.685 | P74: =P42*P73 -> 25545.08 | ... AJ74: =AJ42*AJ73 -> 5217.1877
A76: Summary of outcomes and initial cost-effectiveness (before final adjustments)
C78: Summary of outcomes
E79: Total deaths averted among people under age 5 | F79: =F56 -> # | G79: feed | H79: =H56 -> - | I79: =I56 -> 553.36091 | J79: =J56 -> 423.82404 | K79: =K56 -> 239.46597 | L79: =L56 -> 371.17265 | M79: =M56 -> 313.46781 | N79: =N56 -> 128.44265 | O79: =O56 -> 364.91055 | ... AJ79: =AJ56 -> 179.22086
E80: Additional people under age 5 receiving a year of VAS as a result of the program | F80: =F42 -> # | G80: feed | H80: =H42 -> - | I80: =I42 -> 558529.67 | J80: =J42 -> 515252.87 | K80: =K42 -> 584832.84 | L80: =L42 -> 584832.84 | M80: =M42 -> 413177.74 | N80: =N42 -> 584832.84 | O80: =O42 -> 436675.19 | ... AJ80: =AJ42 -> 526593.68
C82: Value of individual outcomes
E83: Value assigned to averting a death of a person under age 5 with vitamin A supplementation | F83: =F69 -> UoV | G83: feed | H83: =H69 -> 118.73259 | I83: =I69 -> - | J83: =J69 -> - | K83: =K69 -> - | L83: =L69 -> - | M83: =M69 -> - | N83: =N69 -> - | O83: =O69 -> - | ... AJ83: =AJ69 -> -
E84: Units of value generated from long-term income increases per person receiving a year of VAS | F84: =F73 -> UoV | G84: feed | H84: =H73 -> - | I84: =I73 -> 0.028840987 | J84: =J73 -> 0.023944902 | K84: =K73 -> 0.011919552 | L84: =L73 -> 0.018475326 | M84: =M73 -> 0.022085332 | N84: =N73 -> 0.0063933046 | O84: =O73 -> 0.024326285 | ... AJ84: =AJ73 -> 0.0099074256
C86: Total value of outcomes
E87: Units of value from under-5 deaths averted (before final adjustments) | F87: UoV | G87: calc | H87: - | I87: =I79*$H83 -> 65701.974 | J87: =J79*$H83 -> 50321.726 | K87: =K79*$H83 -> 28432.415 | L87: =L79*$H83 -> 44070.29 | M87: =M79*$H83 -> 37218.845 | N87: =N79*$H83 -> 15250.328 | O87: =O79*$H83 -> 43326.775 | P87: =P79*$H83 -> 104190.78 | ... AJ87: =AJ79*$H83 -> 21279.357
E88: Units of value from long-term income increases (before final adjustments) | F88: UoV | G88: calc | H88: - | I88: =I80*I84 -> 16108.547 | J88: =J80*J84 -> 12337.68 | K88: =K80*K84 -> 6970.9457 | L88: =L80*L84 -> 10804.978 | M88: =M80*M84 -> 9125.1676 | N88: =N80*N84 -> 3739.0145 | O88: =O80*O84 -> 10622.685 | P88: =P80*P84 -> 25545.08 | ... AJ88: =AJ80*AJ84 -> 5217.1877
C90: Initial cost-effectiveness (before final adjustments)
E91: Total spending contributed by grantee | F91: =F21 -> $ | G91: feed | H91: =H21 -> - | I91: =I21 -> 1000000 | J91: =J21 -> 1000000 | K91: =K21 -> 1000000 | L91: =L21 -> 1000000 | M91: =M21 -> 1000000 | N91: =N21 -> 1000000 | O91: =O21 -> 1000000 | ... AJ91: =AJ21 -> 1000000
E92: Total units of value from all outcomes (before final adjustments) | F92: UoV | G92: calc | H92: - | I92: =SUM(I87:I88) -> 81810.521 | J92: =SUM(J87:J88) -> 62659.406 | K92: =SUM(K87:K88) -> 35403.361 | L92: =SUM(L87:L88) -> 54875.268 | M92: =SUM(M87:M88) -> 46344.013 | N92: =SUM(N87:N88) -> 18989.343 | O92: =SUM(O87:O88) -> 53949.46 | P92: =SUM(P87:P88) -> 129735.86 | ... AJ92: =SUM(AJ87:AJ88) -> 26496.545
E93: Units of value generated per dollar spent (before final adjustments) | F93: UoV | G93: calc | H93: - | I93: =I92/I91 -> 0.081810521 | J93: =J92/J91 -> 0.062659406 | K93: =K92/K91 -> 0.035403361 | L93: =L92/L91 -> 0.054875268 | M93: =M92/M91 -> 0.046344013 | N93: =N92/N91 -> 0.018989343 | O93: =O92/O91 -> 0.05394946 | P93: =P92/P91 -> 0.12973586 | ... AJ93: =AJ92/AJ91 -> 0.026496545
E94: Units of value per dollar spent, benchmark | F94: =Inputs!F163 -> UoV | G94: =Inputs!G163 -> input | H94: =Inputs!H163 -> 0.00333 | I94: =Inputs!I163 -> - | J94: =Inputs!J163 -> - | K94: =Inputs!K163 -> - | L94: =Inputs!L163 -> - | M94: =Inputs!M163 -> - | ... AJ94: =Inputs!AJ163 -> -
E95: Cost-effectiveness in terms of multiples of our benchmark (before final adjustments) | F95: xbenchmark | G95: calc | H95: - | I95: =I93/$H94 -> 24.567724 | J95: =J93/$H94 -> 18.816638 | K95: =K93/$H94 -> 10.63164 | L95: =L93/$H94 -> 16.479059 | M95: =M93/$H94 -> 13.917121 | N95: =N93/$H94 -> 5.7025054 | O95: =O93/$H94 -> 16.201039 | P95: =P93/$H94 -> 38.959719 | ... AJ95: =AJ93/$H94 -> 7.9569204
C97: Proportion of impact attributed to different outcomes
E98: Proportion of total units of value attributed to mortality reduction among people under age 5 | F98: % | G98: calc | H98: - | I98: =I87/I92 -> 0.80309932 | J98: =J87/J92 -> 0.80309932 | K98: =K87/K92 -> 0.80309932 | L98: =L87/L92 -> 0.80309932 | M98: =M87/M92 -> 0.80309932 | N98: =N87/N92 -> 0.80309932 | O98: =O87/O92 -> 0.80309932 | P98: =P87/P92 -> 0.80309932 | ... AJ98: =AJ87/AJ92 -> 0.80309932
E99: Proportion of total units of value attributed to long-term income increases | F99: % | G99: calc | H99: - | I99: =I88/I92 -> 0.19690068 | J99: =J88/J92 -> 0.19690068 | K99: =K88/K92 -> 0.19690068 | L99: =L88/L92 -> 0.19690068 | M99: =M88/M92 -> 0.19690068 | N99: =N88/N92 -> 0.19690068 | O99: =O88/O92 -> 0.19690068 | P99: =P88/P92 -> 0.19690068 | ... AJ99: =AJ88/AJ92 -> 0.19690068
C101: Cost per life saved (before final adjustments)
E102: Total spending contributed by grantee | F102: =F21 -> $ | G102: feed | H102: =H21 -> - | I102: =I21 -> 1000000 | J102: =J21 -> 1000000 | K102: =K21 -> 1000000 | L102: =L21 -> 1000000 | M102: =M21 -> 1000000 | N102: =N21 -> 1000000 | O102: =O21 -> 1000000 | ... AJ102: =AJ21 -> 1000000
E103: Total lives saved (before final adjustments) | F103: # | G103: calc | H103: - | I103: =I79 -> 553.36091 | J103: =J79 -> 423.82404 | K103: =K79 -> 239.46597 | L103: =L79 -> 371.17265 | M103: =M79 -> 313.46781 | N103: =N79 -> 128.44265 | O103: =O79 -> 364.91055 | P103: =P79 -> 877.52473 | ... AJ103: =AJ79 -> 179.22086
E104: Cost per life saved (before final adjustments) | F104: $ | G104: calc | H104: - | I104: =I102/I103 -> 1807.1389 | J104: =J102/J103 -> 2359.4697 | K104: =K102/K103 -> 4175.9587 | L104: =L102/L103 -> 2694.164 | M104: =M102/M103 -> 3190.1202 | N104: =N102/N103 -> 7785.5759 | O104: =O102/O103 -> 2740.3976 | P104: =P102/P103 -> 1139.569 | ... AJ104: =AJ102/AJ103 -> 5579.7075
A106: Adjustments
C108: Supplemental grantee-level adjustments
D109: Risk of wastage
E110: Double treatment | F110: =Inputs!F169 -> % | G110: =Inputs!G169 -> input | H110: =Inputs!H169 -> 0 | I110: =Inputs!I169 -> - | J110: =Inputs!J169 -> - | K110: =Inputs!K169 -> - | L110: =Inputs!L169 -> - | M110: =Inputs!M169 -> - | ... AJ110: =Inputs!AJ169 -> -
E111: Ineffective goods | F111: =Inputs!F170 -> % | G111: =Inputs!G170 -> input | H111: =Inputs!H170 -> 0 | I111: =Inputs!I170 -> - | J111: =Inputs!J170 -> - | K111: =Inputs!K170 -> - | L111: =Inputs!L170 -> - | M111: =Inputs!M170 -> - | ... AJ111: =Inputs!AJ170 -> -
E112: Goods purchased and left in storage until they expire / cash doesn't receive recipients or is taken back from them inappropriately | F112: =Inputs!F171 -> % | G112: =Inputs!G171 -> input | H112: =Inputs!H171 -> 0 | I112: =Inputs!I171 -> - | J112: =Inputs!J171 -> - | K112: =Inputs!K171 -> - | L112: =Inputs!L171 -> - | M112: =Inputs!M171 -> - | ... AJ112: =Inputs!AJ171 -> -
D113: Quality of monitoring and evaluation
E114: Misappropriation without monitoring results | F114: =Inputs!F173 -> % | G114: =Inputs!G173 -> input | H114: =Inputs!H173 -> - | I114: =Inputs!I173 -> -0.15 | J114: =Inputs!J173 -> -0.15 | K114: =Inputs!K173 -> -0.15 | L114: =Inputs!L173 -> -0.15 | M114: =Inputs!M173 -> -0.15 | ... AJ114: =Inputs!AJ173 -> -0.15
E115: False monitoring results | F115: =Inputs!F174 -> % | G115: =Inputs!G174 -> input | H115: =Inputs!H174 -> - | I115: =Inputs!I174 -> -0.02 | J115: =Inputs!J174 -> -0.02 | K115: =Inputs!K174 -> -0.02 | L115: =Inputs!L174 -> -0.02 | M115: =Inputs!M174 -> -0.02 | ... AJ115: =Inputs!AJ174 -> -0.02
D116: Confidence in funds being used for intended purpose
E117: Change of priorities | F117: =Inputs!F176 -> % | G117: =Inputs!G176 -> input | H117: =Inputs!H176 -> - | I117: =Inputs!I176 -> 0 | J117: =Inputs!J176 -> 0 | K117: =Inputs!K176 -> 0 | L117: =Inputs!L176 -> 0 | M117: =Inputs!M176 -> 0 | ... AJ117: =Inputs!AJ176 -> -0.05
E118: Non-funding bottlenecks | F118: =Inputs!F177 -> % | G118: =Inputs!G177 -> input | H118: =Inputs!H177 -> - | I118: =Inputs!I177 -> 0 | J118: =Inputs!J177 -> 0 | K118: =Inputs!K177 -> 0 | L118: =Inputs!L177 -> 0 | M118: =Inputs!M177 -> 0 | ... AJ118: =Inputs!AJ177 -> 0
E119: Within-org fungibility | F119: =Inputs!F178 -> % | G119: =Inputs!G178 -> input | H119: =Inputs!H178 -> - | I119: =Inputs!I178 -> -0.05 | J119: =Inputs!J178 -> -0.05 | K119: =Inputs!K178 -> -0.05 | L119: =Inputs!L178 -> -0.05 | M119: =Inputs!M178 -> -0.05 | ... AJ119: =Inputs!AJ178 -> -0.02
D121: Total supplemental grantee-level adjustment | F121: % | G121: calc | H121: - | I121: =SUM($H110:$H119,I110:I119) -> -0.22 | J121: =SUM($H110:$H119,J110:J119) -> -0.22 | K121: =SUM($H110:$H119,K110:K119) -> -0.22 | L121: =SUM($H110:$H119,L110:L119) -> -0.22 | M121: =SUM($H110:$H119,M110:M119) -> -0.22 | N121: =SUM($H110:$H119,N110:N119) -> -0.22 | O121: =SUM($H110:$H119,O110:O119) -> -0.22 | P121: =SUM($H110:$H119,P110:P119) -> -0.22 | ... AJ121: =SUM($H110:$H119,AJ110:AJ119) -> -0.24
C123: Supplemental intervention-level adjustments
D124: Adjustments not affecting cost per life saved
...

Sheet Counterfactual mortality
I1: Helen Keller International | Q1: Helen Keller International | Y1: Helen Keller International | AG1: Nutrition International
I2: Burkina Faso | J2: Cameroon | K2: Côte d'Ivoire | L2: DRC | M2: Guinea | N2: Kenya | O2: Madagascar | P2: Mali | Q2: Niger | R2: Nigeria | S2: Nigeria | T2: Nigeria | U2: Nigeria | V2: Nigeria | W2: Nigeria | X2: Nigeria | Y2: Nigeria | Z2: Nigeria | AA2: Nigeria | AB2: Nigeria | AC2: Nigeria | AD2: Nigeria | AE2: Nigeria | AF2: Nigeria | AG2: Angola | AH2: Chad | AI2: Togo | AJ2: Uganda
A3: Supplemental calculations for counterfactual mortality rates | H3: Overall | R3: Adamawa | S3: Akwa Ibom | T3: Anambra | U3: Benue | V3: Delta | W3: Ebonyi | X3: Edo | Y3: Ekiti | Z3: Imo | AA3: Kogi | AB3: Nasarawa | AC3: Ogun | AD3: Osun | AE3: Rivers | AF3: Taraba
E4: Final cost-effectiveness estimate (pulled from "Main calcs" sheet for visibility) | F4: ='Main CEA'!F149 -> xbenchmark | G4: main | H4: ='Main CEA'!H149 -> - | I4: ='Main CEA'!I149 -> 22.604158 | J4: ='Main CEA'!J149 -> 15.907951 | K4: ='Main CEA'!K149 -> 8.5391703 | L4: ='Main CEA'!L149 -> 16.914533 | M4: ='Main CEA'!M149 -> 10.932207 | N4: ='Main CEA'!N149 -> 4.7974496 | O4: ='Main CEA'!O149 -> 15.912911 | ... AJ4: ='Main CEA'!AJ149 -> 6.3105992
C7: Mortalities per year among people under age 5
E8: Total mortalities per year among people under age 5 | F8: =Inputs!F24 -> # | G8: =Inputs!G24 -> input | H8: =Inputs!H24 -> - | I8: =Inputs!I24 -> 98779.14 | J8: =Inputs!J24 -> 64035.007 | K8: =Inputs!K24 -> 64816.604 | L8: =Inputs!L24 -> 168468.45 | M8: =Inputs!M24 -> 45406.175 | ... AJ8: =Inputs!AJ24 -> 91702.416
E9: Total early neonatal mortalities per year (babies under 7 days old) | F9: =Inputs!F25 -> # | G9: =Inputs!G25 -> input | H9: =Inputs!H25 -> - | I9: =Inputs!I25 -> 19940.749 | J9: =Inputs!J25 -> 17016.724 | K9: =Inputs!K25 -> 25085.602 | L9: =Inputs!L25 -> 53762.704 | M9: =Inputs!M25 -> 11002.662 | ... AJ9: =Inputs!AJ25 -> 33674.565
E10: Total late neonatal mortalities per year (babies between 7 and 27 days old) | F10: =Inputs!F26 -> # | G10: =Inputs!G26 -> input | H10: =Inputs!H26 -> - | I10: =Inputs!I26 -> 6949.4673 | J10: =Inputs!J26 -> 4718.8947 | K10: =Inputs!K26 -> 5328.8585 | L10: =Inputs!L26 -> 10893.455 | M10: =Inputs!M26 -> 3633.8561 | ... AJ10: =Inputs!AJ26 -> 7103.6055
E11: Total post-neonatal mortalities per year (babies between 28 and 364 days old) | F11: =Inputs!F27 -> # | G11: =Inputs!G27 -> input | H11: =Inputs!H27 -> - | I11: =Inputs!I27 -> 30592.149 | J11: =Inputs!J27 -> 19245.01 | K11: =Inputs!K27 -> 12225.341 | L11: =Inputs!L27 -> 50492.306 | M11: =Inputs!M27 -> 11984.047 | ... AJ11: =Inputs!AJ27 -> 25133.879
C13: Estimated mortalities per year among the VAS-eligible population
E14: =Inputs!E30 -> Proportion of post-neonatal mortalities that are among 1-5-month-olds | F14: =Inputs!F30 -> % | G14: =Inputs!G30 -> input | H14: =Inputs!H30 -> 0.53 | I14: =Inputs!I30 | J14: =Inputs!J30 | K14: =Inputs!K30 | L14: =Inputs!L30 | ... AJ14: =Inputs!AJ30 -> -
E15: Estimated mortalities per year among 1-5-month-olds | F15: # | G15: calc | H15: - | I15: =I11*$H14 -> 16213.839 | J15: =J11*$H14 -> 10199.856 | K15: =K11*$H14 -> 6479.4309 | L15: =L11*$H14 -> 26760.922 | M15: =M11*$H14 -> 6351.545 | N15: =N11*$H14 -> 8124.8035 | O15: =O11*$H14 -> 8188.9652 | P15: =P11*$H14 -> 15058.856 | ... AJ15: =AJ11*$H14 -> 13320.956
E16: Total mortalities per year among 6-59-month-olds | F16: # | G16: calc | H16: - | I16: =I8-SUM(I9:I10,I15) -> 55675.086 | J16: =J8-SUM(J9:J10,J15) -> 32099.534 | K16: =K8-SUM(K9:K10,K15) -> 27922.712 | L16: =L8-SUM(L9:L10,L15) -> 77051.37 | M16: =M8-SUM(M9:M10,M15) -> 24418.112 | N16: =N8-SUM(N9:N10,N15) -> 19571.679 | O16: =O8-SUM(O9:O10,O15) -> 20147.329 | P16: =P8-SUM(P9:P10,P15) -> 56546.983 | ... AJ16: =AJ8-SUM(AJ9:AJ10,AJ15) -> 37603.289
E17: Proportion of mortalities among people under age 5 that occur among 6-59-month-olds | F17: % | G17: calc | H17: - | I17: =I16/I8 -> 0.56363201 | J17: =J16/J8 -> 0.50128102 | K17: =K16/K8 -> 0.43079567 | L17: =L16/L8 -> 0.45736379 | M17: =M16/M8 -> 0.53777073 | N17: =N16/N8 -> 0.36689072 | O17: =O16/O8 -> 0.41837539 | P17: =P16/P8 -> 0.51573906 | ... AJ17: =AJ16/AJ8 -> 0.41005778
C19: All-cause mortality rate among the VAS-eligible population
E20: All-cause mortality rate among people under age 5 | F20: =Inputs!F33 -> per 100k | G20: =Inputs!G33 -> input | H20: =Inputs!H33 -> - | I20: =Inputs!I33 -> 2442.0317 | J20: =Inputs!J33 -> 1522.0667 | K20: =Inputs!K33 -> 1615.569 | L20: =Inputs!L33 -> 1236.0606 | M20: =Inputs!M33 -> 2118.4232 | ... AJ20: =Inputs!AJ33 -> 1293.4507
E21: Implied population under age 5 | F21: # | G21: calc | H21: - | I21: =I8/I20*100000 -> 4044957.3 | J21: =J8/J20*100000 -> 4207109.2 | K21: =K8/K20*100000 -> 4011998.5 | L21: =L8/L20*100000 -> 13629465 | M21: =M8/M20*100000 -> 2143394.9 | N21: =N8/N20*100000 -> 6416042.8 | O21: =O8/O20*100000 -> 3939181.5 | P21: =P8/P20*100000 -> 4064332.1 | ... AJ21: =AJ8/AJ20*100000 -> 7089749.8
E22: Estimated proportion of people under age 5 who are 6-59-month-olds | F22: =Inputs!F34 -> % | G22: =Inputs!G34 -> input | H22: =Inputs!H34 -> - | I22: =Inputs!I34 -> 0.91525424 | J22: =Inputs!J34 -> 0.91525424 | K22: =Inputs!K34 -> 0.91525424 | L22: =Inputs!L34 -> 0.91525424 | M22: =Inputs!M34 -> 0.91525424 | ... AJ22: =Inputs!AJ34 -> 0.91525424
E23: Estimated population of 6-59-month-olds | F23: # | G23: calc | H23: - | I23: =I21*I22 -> 3702164.3 | J23: =J21*J22 -> 3850574.6 | K23: =K21*K22 -> 3671998.6 | L23: =L21*L22 -> 12474426 | M23: =M21*M22 -> 1961751.2 | N23: =N21*N22 -> 5872310.3 | O23: =O21*O22 -> 3605352.6 | P23: =P21*P22 -> 3719897.2 | ... AJ23: =AJ21*AJ22 -> 6488923.6
E24: Annual all-cause mortality rate among 6-59-month-olds | F24: % | G24: calc | H24: - | I24: =I16/I23 -> 0.015038524 | J24: =J16/J23 -> 0.0083362971 | K24: =K16/K23 -> 0.0076042273 | L24: =L16/L23 -> 0.0061767469 | M24: =M16/M23 -> 0.012447099 | N24: =N16/N23 -> 0.0033328754 | O24: =O16/O23 -> 0.0055881716 | P24: =P16/P23 -> 0.015201222 | ... AJ24: =AJ16/AJ23 -> 0.0057949964
E25: Adjustment for differences between the national mortality rate and mortality rates in the subnational areas targeted for VAS | F25: =Inputs!F37 -> % | G25: =Inputs!G37 -> input | H25: =Inputs!H37 -> - | I25: =Inputs!I37 -> - | J25: =Inputs!J37 -> -0.1408628 | K25: =Inputs!K37 -> - | L25: =Inputs!L37 -> - | M25: =Inputs!M37 -> - | ... AJ25: =Inputs!AJ37 -> -
E26: Annual all-cause mortality rate among 6-59-month-olds in areas targeted for VAS | F26: % | G26: calc | H26: - | I26: =IF(I25<>"-",I24*(1+I25),I24) -> 0.015038524 | J26: =IF(J25<>"-",J24*(1+J25),J24) -> 0.007162023 | K26: =IF(K25<>"-",K24*(1+K25),K24) -> 0.0076042273 | L26: =IF(L25<>"-",L24*(1+L25),L24) -> 0.0061767469 | M26: =IF(M25<>"-",M24*(1+M25),M24) -> 0.012447099 | N26: =IF(N25<>"-",N24*(1+N25),N24) -> 0.0033328754 | O26: =IF(O25<>"-",O24*(1+O25),O24) -> 0.0065381607 | P26: =IF(P25<>"-",P24*(1+P25),P24) -> 0.015201222 | ... AJ26: =IF(AJ25<>"-",AJ24*(1+AJ25),AJ24) -> 0.0057949964

Sheet External validity
I1: Helen Keller International | Q1: Helen Keller International | Y1: Helen Keller International | AG1: Nutrition International
I2: Burkina Faso | J2: Cameroon | K2: Côte d'Ivoire | L2: DRC | M2: Guinea | N2: Kenya | O2: Madagascar | P2: Mali | Q2: Niger | R2: Nigeria | S2: Nigeria | T2: Nigeria | U2: Nigeria | V2: Nigeria | W2: Nigeria | X2: Nigeria | Y2: Nigeria | Z2: Nigeria | AA2: Nigeria | AB2: Nigeria | AC2: Nigeria | AD2: Nigeria | AE2: Nigeria | AF2: Nigeria | AG2: Angola | AH2: Chad | AI2: Togo | AJ2: Uganda
H3: Overall | R3: Adamawa | S3: Akwa Ibom | T3: Anambra | U3: Benue | V3: Delta | W3: Ebonyi | X3: Edo | Y3: Ekiti | Z3: Imo | AA3: Kogi | AB3: Nasarawa | AC3: Ogun | AD3: Osun | AE3: Rivers | AF3: Taraba
E4: Final cost-effectiveness estimate (pulled from "Main calcs" sheet for visibility) | F4: ='Main CEA'!F149 -> xbenchmark | G4: main | H4: ='Main CEA'!H149 -> - | I4: ='Main CEA'!I149 -> 22.604158 | J4: ='Main CEA'!J149 -> 15.907951 | K4: ='Main CEA'!K149 -> 8.5391703 | L4: ='Main CEA'!L149 -> 16.914533 | M4: ='Main CEA'!M149 -> 10.932207 | N4: ='Main CEA'!N149 -> 4.7974496 | O4: ='Main CEA'!O149 -> 15.912911 | ... AJ4: ='Main CEA'!AJ149 -> 6.3105992
A5: Vitamin A deficiency prevalence for Nigerian states
C7: Vitamin A deficiency prevalence in Nigeria according to the latest national survey
E8: Vitamin A deficiency prevalence in Nigeria according to the latest national survey | F8: =Inputs!F42 -> % | G8: =Inputs!G42 -> input | H8: =Inputs!H42 -> - | I8: =Inputs!I42 -> - | J8: =Inputs!J42 -> - | K8: =Inputs!K42 -> - | L8: =Inputs!L42 -> - | M8: =Inputs!M42 -> - | ... AJ8: =Inputs!AJ42 -> -
E9: Year of latest national vitamin A deficiency survey in Nigeria | F9: =Inputs!F43 -> year | G9: =Inputs!G43 -> input | H9: =Inputs!H43 -> - | I9: =Inputs!I43 -> - | J9: =Inputs!J43 -> - | K9: =Inputs!K43 -> - | L9: =Inputs!L43 -> - | M9: =Inputs!M43 -> - | ... AJ9: =Inputs!AJ43 -> -
C11: National data on health proxies for vitamin A deficiency according to DHS surveys
E12: National proportion of people under age 5 who were experiencing stunting in 2003 | F12: =Inputs!F46 -> % | G12: =Inputs!G46 -> input | H12: =Inputs!H46 -> - | I12: =Inputs!I46 -> - | J12: =Inputs!J46 -> - | K12: =Inputs!K46 -> - | L12: =Inputs!L46 -> - | M12: =Inputs!M46 -> - | ... AJ12: =Inputs!AJ46 -> -
E13: National proportion of people under age 5 who were experiencing wasting in 2003 | F13: =Inputs!F47 -> % | G13: =Inputs!G47 -> input | H13: =Inputs!H47 -> - | I13: =Inputs!I47 -> - | J13: =Inputs!J47 -> - | K13: =Inputs!K47 -> - | L13: =Inputs!L47 -> - | M13: =Inputs!M47 -> - | ... AJ13: =Inputs!AJ47 -> -
E14: National proportion of people under age 5 who were experiencing stunting in 2018 | F14: =Inputs!F48 -> % | G14: =Inputs!G48 -> input | H14: =Inputs!H48 -> - | I14: =Inputs!I48 -> - | J14: =Inputs!J48 -> - | K14: =Inputs!K48 -> - | L14: =Inputs!L48 -> - | M14: =Inputs!M48 -> - | ... AJ14: =Inputs!AJ48 -> -
E15: National proportion of people under age 5 who were experiencing wasting in 2018 | F15: =Inputs!F49 -> % | G15: =Inputs!G49 -> input | H15: =Inputs!H49 -> - | I15: =Inputs!I49 -> - | J15: =Inputs!J49 -> - | K15: =Inputs!K49 -> - | L15: =Inputs!L49 -> - | M15: =Inputs!M49 -> - | ... AJ15: =Inputs!AJ49 -> -
E16: National proportion of 6-59-month-olds who were experiencing anemia in 2018 | F16: =Inputs!F50 -> % | G16: =Inputs!G50 -> input | H16: =Inputs!H50 -> - | I16: =Inputs!I50 -> - | J16: =Inputs!J50 -> - | K16: =Inputs!K50 -> - | L16: =Inputs!L50 -> - | M16: =Inputs!M50 -> - | ... AJ16: =Inputs!AJ50 -> -
C18: National data on economic proxies for vitamin A deficiency according to the World Bank
E19: National proportion of the population below the international poverty line in 2003 | F19: =Inputs!F53 -> % | G19: =Inputs!G53 -> input | H19: =Inputs!H53 -> - | I19: =Inputs!I53 -> - | J19: =Inputs!J53 -> - | K19: =Inputs!K53 -> - | L19: =Inputs!L53 -> - | M19: =Inputs!M53 -> - | ... AJ19: =Inputs!AJ53 -> -
E20: National proportion of the population below the international poverty line in 2018 | F20: =Inputs!F54 -> % | G20: =Inputs!G54 -> input | H20: =Inputs!H54 -> - | I20: =Inputs!I54 -> - | J20: =Inputs!J54 -> - | K20: =Inputs!K54 -> - | L20: =Inputs!L54 -> - | M20: =Inputs!M54 -> - | ... AJ20: =Inputs!AJ54 -> -
C22: National data on economic proxies for vitamin A deficiency according to a 2019 NBS survey
E23: National proportion of the population below Nigeria's poverty line in 2019 | F23: =Inputs!F57 -> % | G23: =Inputs!G57 -> input | H23: =Inputs!H57 -> - | I23: =Inputs!I57 -> - | J23: =Inputs!J57 -> - | K23: =Inputs!K57 -> - | L23: =Inputs!L57 -> - | M23: =Inputs!M57 -> - | ... AJ23: =Inputs!AJ57 -> -
C25: Change in proxies for vitamin A deficiency over time
E26: Change in rates of stunting among people under age 5 between 2003 and 2018 | F26: % | G26: calc | H26: - | I26: - | J26: - | K26: - | L26: - | M26: - | N26: - | O26: - | P26: - | Q26: - | R26: =(R14-R12)/R12 -> -0.039164491 | S26: =(S14-S12)/S12 -> -0.039164491 | T26: =(T14-T12)/T12 -> -0.039164491 | U26: =(U14-U12)/U12 -> -0.039164491 | V26: =(V14-V12)/V12 -> -0.039164491 | W26: =(W14-W12)/W12 -> -0.039164491 | X26: =(X14-X12)/X12 -> -0.039164491 | Y26: =(Y14-Y12)/Y12 -> -0.039164491 | ... AF26: =(AF14-AF12)/AF12 -> -0.039164491 | AG26: - | AH26: - | AI26: - | AJ26: -
E27: Change in rates of wasting among people under age 5 between 2003 and 2018 | F27: % | G27: calc | H27: - | I27: - | J27: - | K27: - | L27: - | M27: - | N27: - | O27: - | P27: - | Q27: - | R27: =(R15-R13)/R13 -> -0.26086957 | S27: =(S15-S13)/S13 -> -0.26086957 | T27: =(T15-T13)/T13 -> -0.26086957 | U27: =(U15-U13)/U13 -> -0.26086957 | V27: =(V15-V13)/V13 -> -0.26086957 | W27: =(W15-W13)/W13 -> -0.26086957 | X27: =(X15-X13)/X13 -> -0.26086957 | Y27: =(Y15-Y13)/Y13 -> -0.26086957 | ... AF27: =(AF15-AF13)/AF13 -> -0.26086957 | AG27: - | AH27: - | AI27: - | AJ27: -
E28: Change in poverty rates between 2003 and 2018 according to World Bank data | F28: % | G28: calc | H28: - | I28: - | J28: - | K28: - | L28: - | M28: - | N28: - | O28: - | P28: - | Q28: - | R28: =(R20-R19)/R19 -> -0.30053667 | S28: =(S20-S19)/S19 -> -0.30053667 | T28: =(T20-T19)/T19 -> -0.30053667 | U28: =(U20-U19)/U19 -> -0.30053667 | V28: =(V20-V19)/V19 -> -0.30053667 | W28: =(W20-W19)/W19 -> -0.30053667 | X28: =(X20-X19)/X19 -> -0.30053667 | Y28: =(Y20-Y19)/Y19 -> -0.30053667 | ... AF28: =(AF20-AF19)/AF19 -> -0.30053667 | AG28: - | AH28: - | AI28: - | AJ28: -
E29: Weight placed on change in rates of stunting as a proxy for changes in vitamin A deficiency | F29: =Inputs!F60 -> % | G29: =Inputs!G60 -> input | H29: =Inputs!H60 -> 0.33333333 | I29: =Inputs!I60 -> - | J29: =Inputs!J60 -> - | K29: =Inputs!K60 -> - | L29: =Inputs!L60 -> - | M29: =Inputs!M60 -> - | ... AK29: =Inputs!AK60
E30: Weight placed on change in rates of wasting as a proxy for changes in vitamin A deficiency | F30: =Inputs!F61 -> % | G30: =Inputs!G61 -> input | H30: =Inputs!H61 -> 0.33333333 | I30: =Inputs!I61 -> - | J30: =Inputs!J61 -> - | K30: =Inputs!K61 -> - | L30: =Inputs!L61 -> - | M30: =Inputs!M61 -> - | ... AK30: =Inputs!AK61
E31: Weight placed on change in poverty rates as a proxy for changes in vitamin A deficiency | F31: =Inputs!F62 -> % | G31: =Inputs!G62 -> input | H31: =Inputs!H62 -> 0.33333333 | I31: =Inputs!I62 -> - | J31: =Inputs!J62 -> - | K31: =Inputs!K62 -> - | L31: =Inputs!L62 -> - | M31: =Inputs!M62 -> - | ... AK31: =Inputs!AK62
C33: Approximated change in vitamin A deficiency prevalence over time
E34: Estimated change in vitamin A deficiency prevalence between 2003 and 2018 | F34: % | G34: calc | H34: - | I34: - | J34: - | K34: - | L34: - | M34: - | N34: - | O34: - | P34: - | Q34: - | R34: =SUMPRODUCT(R26:R28,$H29:$H31) -> -0.20019024 | S34: =SUMPRODUCT(S26:S28,$H29:$H31) -> -0.20019024 | T34: =SUMPRODUCT(T26:T28,$H29:$H31) -> -0.20019024 | U34: =SUMPRODUCT(U26:U28,$H29:$H31) -> -0.20019024 | V34: =SUMPRODUCT(V26:V28,$H29:$H31) -> -0.20019024 | W34: =SUMPRODUCT(W26:W28,$H29:$H31) -> -0.20019024 | X34: =SUMPRODUCT(X26:X28,$H29:$H31) -> -0.20019024 | Y34: =SUMPRODUCT(Y26:Y28,$H29:$H31) -> -0.20019024 | ... AF34: =SUMPRODUCT(AF26:AF28,$H29:$H31) -> -0.20019024 | AG34: - | AH34: - | AI34: - | AJ34: -
E35: Year of early data points for vitamin A deficiency proxies | F35: =Inputs!F65 -> year | G35: =Inputs!G65 -> input | H35: =Inputs!H65 -> - | I35: =Inputs!I65 -> - | J35: =Inputs!J65 -> - | K35: =Inputs!K65 -> - | L35: =Inputs!L65 -> - | M35: =Inputs!M65 -> - | ... AJ35: =Inputs!AJ65 -> -
E36: Year of late data points for vitamin A deficiency proxies | F36: =Inputs!F66 -> year | G36: =Inputs!G66 -> input | H36: =Inputs!H66 -> - | I36: =Inputs!I66 -> - | J36: =Inputs!J66 -> - | K36: =Inputs!K66 -> - | L36: =Inputs!L66 -> - | M36: =Inputs!M66 -> - | ... AJ36: =Inputs!AJ66 -> -
E37: Years between early and late data points for vitamin A deficiency proxies | F37: # | G37: calc | H37: - | I37: - | J37: - | K37: - | L37: - | M37: - | N37: - | O37: - | P37: - | Q37: - | R37: =R36-R35 -> 15 | S37: =S36-S35 -> 15 | T37: =T36-T35 -> 15 | U37: =U36-U35 -> 15 | V37: =V36-V35 -> 15 | W37: =W36-W35 -> 15 | X37: =X36-X35 -> 15 | Y37: =Y36-Y35 -> 15 | ... AF37: =AF36-AF35 -> 15 | AG37: - | AH37: - | AI37: - | AJ37: -
E38: Approximated average change in vitamin A deficiency per year | F38: ppt | G38: calc | H38: - | I38: - | J38: - | K38: - | L38: - | M38: - | N38: - | O38: - | P38: - | Q38: - | R38: =R34/R37 -> -0.013346016 | S38: =S34/S37 -> -0.013346016 | T38: =T34/T37 -> -0.013346016 | U38: =U34/U37 -> -0.013346016 | V38: =V34/V37 -> -0.013346016 | W38: =W34/W37 -> -0.013346016 | X38: =X34/X37 -> -0.013346016 | Y38: =Y34/Y37 -> -0.013346016 | ... AF38: =AF34/AF37 -> -0.013346016 | AG38: - | AH38: - | AI38: - | AJ38: -
E39: Expected year of the grantee's VAS campaign | F39: =Inputs!F67 -> year | G39: =Inputs!G67 -> input | H39: =Inputs!H67 -> - | I39: =Inputs!I67 -> 2022 | J39: =Inputs!J67 -> 2022 | K39: =Inputs!K67 -> 2022 | L39: =Inputs!L67 -> 2022 | M39: =Inputs!M67 -> - | ... AJ39: =Inputs!AJ67 -> 2022
E40: Years between the latest national vitamin A deficiency survey in Nigeria and the grantee's VAS campaign | F40: # | G40: calc | H40: - | I40: - | J40: - | K40: - | L40: - | M40: - | N40: - | O40: - | P40: - | Q40: - | R40: =R39-R9 -> 21 | S40: =S39-S9 -> 21 | T40: =T39-T9 -> 21 | U40: =U39-U9 -> 21 | V40: =V39-V9 -> 21 | W40: =W39-W9 -> 21 | X40: =X39-X9 -> 21 | Y40: =Y39-Y9 -> 21 | ... AF40: =AF39-AF9 -> 21 | AG40: - | AH40: - | AI40: - | AJ40: -
E41: Approximated change in vitamin A deficiency since the latest national survey in Nigeria | F41: % | G41: calc | H41: - | I41: - | J41: - | K41: - | L41: - | M41: - | N41: - | O41: - | P41: - | Q41: - | R41: =R38*R40 -> -0.28026634 | S41: =S38*S40 -> -0.28026634 | T41: =T38*T40 -> -0.28026634 | U41: =U38*U40 -> -0.28026634 | V41: =V38*V40 -> -0.28026634 | W41: =W38*W40 -> -0.28026634 | X41: =X38*X40 -> -0.28026634 | Y41: =Y38*Y40 -> -0.28026634 | ... AF41: =AF38*AF40 -> -0.28026634 | AG41: - | AH41: - | AI41: - | AJ41: -
C43: National vitamin A deficiency prevalence at the time of upcoming campaigns
E44: Estimated national vitamin A deficiency prevalence at the time of a grantee campaign | F44: % | G44: calc | H44: - | I44: - | J44: - | K44: - | L44: - | M44: - | N44: - | O44: - | P44: - | Q44: - | R44: =R8*(1+R41) -> 0.21232143 | S44: =S8*(1+S41) -> 0.21232143 | T44: =T8*(1+T41) -> 0.21232143 | U44: =U8*(1+U41) -> 0.21232143 | V44: =V8*(1+V41) -> 0.21232143 | W44: =W8*(1+W41) -> 0.21232143 | X44: =X8*(1+X41) -> 0.21232143 | Y44: =Y8*(1+Y41) -> 0.21232143 | ... AF44: =AF8*(1+AF41) -> 0.21232143 | AG44: - | AH44: - | AI44: - | AJ44: -
C46: State-level data on health proxies for vitamin A deficiency according to DHS surveys
E47: State-level proportion of people under age 5 who were experiencing stunting in 2018 | F47: =Inputs!F70 -> % | G47: =Inputs!G70 -> input | H47: =Inputs!H70 -> - | I47: =Inputs!I70 -> - | J47: =Inputs!J70 -> - | K47: =Inputs!K70 -> - | L47: =Inputs!L70 -> - | M47: =Inputs!M70 -> - | ... AJ47: =Inputs!AJ70 -> -
E48: State-level proportion of people under age 5 who were experiencing wasting in 2018 | F48: =Inputs!F71 -> % | G48: =Inputs!G71 -> input | H48: =Inputs!H71 -> - | I48: =Inputs!I71 -> - | J48: =Inputs!J71 -> - | K48: =Inputs!K71 -> - | L48: =Inputs!L71 -> - | M48: =Inputs!M71 -> - | ... AJ48: =Inputs!AJ71 -> -
E49: State-level proportion of 6-59-month-olds who were experiencing anemia in 2018 | F49: =Inputs!F72 -> % | G49: =Inputs!G72 -> input | H49: =Inputs!H72 -> - | I49: =Inputs!I72 -> - | J49: =Inputs!J72 -> - | K49: =Inputs!K72 -> - | L49: =Inputs!L72 -> - | M49: =Inputs!M72 -> - | ... AJ49: =Inputs!AJ72 -> -
C51: State-level data on economic proxies for vitamin A deficiency according to a 2019 NBS survey
E52: State-level proportion of the population below Nigeria's poverty line in 2019 | F52: =Inputs!F75 -> % | G52: =Inputs!G75 -> input | H52: =Inputs!H75 -> - | I52: =Inputs!I75 -> - | J52: =Inputs!J75 -> - | K52: =Inputs!K75 -> - | L52: =Inputs!L75 -> - | M52: =Inputs!M75 -> - | ... AJ52: =Inputs!AJ75 -> -
C54: Adjustment for variation in vitamin A deficiency prevalence across states
E55: Ratio of state-level rates of stunting to the national rate of stunting | F55: # | G55: calc | H55: - | I55: - | J55: - | K55: - | L55: - | M55: - | N55: - | O55: - | P55: - | Q55: - | R55: =R47/R14 -> 1.0788043 | S55: =S47/S14 -> 0.5326087 | T55: =T47/T14 -> 0.38043478 | U55: =U47/U14 -> 0.56521739 | V55: =V47/V14 -> 0.64402174 | W55: =W47/W14 -> 0.68478261 | X55: =X47/X14 -> 0.43478261 | Y55: =Y47/Y14 -> 0.60054348 | ... AF55: =AF47/AF14 -> 1.138587 | AG55: - | AH55: - | AI55: - | AJ55: -
E56: Ratio of state-level rates of wasting to the national rate of wasting | F56: # | G56: calc | H56: - | I56: - | J56: - | K56: - | L56: - | M56: - | N56: - | O56: - | P56: - | Q56: - | R56: =R48/R15 -> 0.61764706 | S56: =S48/S15 -> 0.61764706 | T56: =T48/T15 -> 0.33823529 | U56: =U48/U15 -> 1.1764706 | V56: =V48/V15 -> 0.29411765 | W56: =W48/W15 -> 0.66176471 | X56: =X48/X15 -> 0.48529412 | Y56: =Y48/Y15 -> 0.48529412 | ... AF56: =AF48/AF15 -> 0.77941176 | AG56: - | AH56: - | AI56: - | AJ56: -
E57: Ratio of state-level anemia rates to the national anemia rate | F57: # | G57: calc | H57: - | I57: - | J57: - | K57: - | L57: - | M57: - | N57: - | O57: - | P57: - | Q57: - | R57: =R49/R16 -> 0.82474227 | S57: =S49/S16 -> 1.1001473 | T57: =T49/T16 -> 1.107511 | U57: =U49/U16 -> 0.91310751 | V57: =V49/V16 -> 1.0279823 | W57: =W49/W16 -> 1.167894 | X57: =X49/X16 -> 0.97054492 | Y57: =Y49/Y16 -> 1.0589102 | ... AF57: =AF49/AF16 -> 1.0441826 | AG57: - | AH57: - | AI57: - | AJ57: -
E58: Ratio of state-level poverty rates to the national poverty rate | F58: # | G58: calc | H58: - | I58: - | J58: - | K58: - | L58: - | M58: - | N58: - | O58: - | P58: - | Q58: - | R58: =R52/R23 -> 1.8807683 | S58: =S52/S23 -> 0.66849588 | T58: =T52/T23 -> 0.36916937 | U58: =U52/U23 -> 0.82065353 | V58: =V52/V23 -> 0.14966326 | W58: =W52/W23 -> 1.9905213 | X58: =X52/X23 -> 0.29932652 | Y58: =Y52/Y23 -> 0.69842854 | ... AF58: =AF52/AF23 -> 2.187578 | AG58: - | AH58: - | AI58: - | AJ58: -
E59: Weight placed on change in rates of stunting as a proxy for changes in vitamin A deficiency | F59: =Inputs!F78 -> % | G59: =Inputs!G78 -> input | H59: =Inputs!H78 -> - | I59: =Inputs!I78 -> - | J59: =Inputs!J78 -> - | K59: =Inputs!K78 -> - | L59: =Inputs!L78 -> - | M59: =Inputs!M78 -> - | ... AJ59: =Inputs!AJ78 -> -
E60: Weight placed on change in rates of wasting as a proxy for changes in vitamin A deficiency | F60: =Inputs!F79 -> % | G60: =Inputs!G79 -> input | H60: =Inputs!H79 -> - | I60: =Inputs!I79 -> - | J60: =Inputs!J79 -> - | K60: =Inputs!K79 -> - | L60: =Inputs!L79 -> - | M60: =Inputs!M79 -> - | ... AJ60: =Inputs!AJ79 -> -
E61: Weight placed on change in rates of anemia as a proxy for changes in vitamin A deficiency | F61: =Inputs!F80 -> % | G61: =Inputs!G80 -> input | H61: =Inputs!H80 -> - | I61: =Inputs!I80 -> - | J61: =Inputs!J80 -> - | K61: =Inputs!K80 -> - | L61: =Inputs!L80 -> - | M61: =Inputs!M80 -> - | ... AJ61: =Inputs!AJ80 -> -
E62: Weight placed on change in poverty rates as a proxy for changes in vitamin A deficiency | F62: =Inputs!F81 -> % | G62: =Inputs!G81 -> input | H62: =Inputs!H81 -> - | I62: =Inputs!I81 -> - | J62: =Inputs!J81 -> - | K62: =Inputs!K81 -> - | L62: =Inputs!L81 -> - | M62: =Inputs!M81 -> - | ... AJ62: =Inputs!AJ81 -> -
E63: Overall adjustment for variation in vitaman A deficiency prevalence across states | F63: % | G63: calc | H63: - | I63: - | J63: - | K63: - | L63: - | M63: - | N63: - | O63: - | P63: - | Q63: - | R63: =SUMPRODUCT(R55:R58,R59:R62)-1 -> 0.10049049 | S63: =SUMPRODUCT(S55:S58,S59:S62)-1 -> -0.27027527 | T63: =SUMPRODUCT(T55:T58,T59:T62)-1 -> -0.45116238 | U63: =SUMPRODUCT(U55:U58,U59:U62)-1 -> -0.13113775 | V63: =SUMPRODUCT(V55:V58,V59:V62)-1 -> -0.47105376 | W63: =SUMPRODUCT(W55:W58,W59:W62)-1 -> 0.12624065 | X63: =SUMPRODUCT(X55:X58,X59:X62)-1 -> -0.45251296 | Y63: =SUMPRODUCT(Y55:Y58,Y59:Y62)-1 -> -0.28920593 | ... AF63: =SUMPRODUCT(AF55:AF58,AF59:AF62)-1 -> 0.28743982 | AG63: - | AH63: - | AI63: - | AJ63: -
C65: Estimated state-level vitamin A deficiency prevalence
E66: Final estimated vitamin A deficiency prevalence rate among people under age 5 | F66: % | G66: calc | H66: - | I66: - | J66: - | K66: - | L66: - | M66: - | N66: - | O66: - | P66: - | Q66: - | R66: =R44*(1+R63) -> 0.23365771 | S66: =S44*(1+S63) -> 0.1549362 | T66: =T44*(1+T63) -> 0.11652999 | U66: =U44*(1+U63) -> 0.18447808 | V66: =V44*(1+V63) -> 0.11230662 | W66: =W44*(1+W63) -> 0.23912503 | X66: =X44*(1+X63) -> 0.11624323 | Y66: =Y44*(1+Y63) -> 0.15091681 | ... AF66: =AF44*(1+AF63) -> 0.27335106 | AG66: - | AH66: - | AI66: - | AJ66: -
A68: Vitamin A deficiency prevalence for countries other than Nigeria
C70: Vitamin A deficiency prevalence based on the latest in-country surveys
E71: Vitamin A deficiency prevalence found in most recent survey of people under age 5 | F71: =Inputs!F84 -> % | G71: =Inputs!G84 -> input | H71: =Inputs!H84 -> - | I71: =Inputs!I84 -> 0.245 | J71: =Inputs!J84 -> 0.35 | K71: =Inputs!K84 -> 0.24 | L71: =Inputs!L84 -> 0.61 | M71: =Inputs!M84 -> - | ... AJ71: =Inputs!AJ84 -> -
E72: Year of most recent vitamin A deficiency survey of people under age 5 | F72: =Inputs!F85 -> year | G72: =Inputs!G85 -> input | H72: =Inputs!H85 -> - | I72: =Inputs!I85 -> 2010 | J72: =Inputs!J85 -> 2009 | K72: =Inputs!K85 -> 2007 | L72: =Inputs!L85 -> 1999 | M72: =Inputs!M85 -> - | ... AJ72: =Inputs!AJ85 -> -
E73: Expected year of the grantee's VAS campaign | F73: =Inputs!F67 -> year | G73: =Inputs!G67 -> input | H73: =Inputs!H67 -> - | I73: =Inputs!I67 -> 2022 | J73: =Inputs!J67 -> 2022 | K73: =Inputs!K67 -> 2022 | L73: =Inputs!L67 -> 2022 | M73: =Inputs!M67 -> - | ... AJ73: =Inputs!AJ67 -> 2022
E74: Years between the most recent vitamin A deficiency survey and the grantee's VAS campaign | F74: year | G74: calc | H74: - | I74: =IFERROR(I73-I72,"-") -> 12 | J74: =IFERROR(J73-J72,"-") -> 13 | K74: =IFERROR(K73-K72,"-") -> 15 | L74: =IFERROR(L73-L72,"-") -> 23 | M74: =IFERROR(M73-M72,"-") -> - | N74: =IFERROR(N73-N72,"-") -> 11 | O74: =IFERROR(O73-O72,"-") -> 22 | P74: =IFERROR(P73-P72,"-") -> 25 | ... AJ74: =IFERROR(AJ73-AJ72,"-") -> -
E75: Expected change in vitamin A deficiency per year | F75: ppt | G75: feed | H75: =R38 -> -0.013346016 | I75: - | J75: - | K75: - | L75: - | M75: - | N75: - | O75: - | P75: - | Q75: - | R75: - | S75: - | T75: - | U75: - | V75: - | W75: - | X75: - | Y75: - | Z75: - | AA75: - | AB75: - | AC75: - | AD75: - | AE75: - | AF75: - | AG75: - | AH75: - | AI75: - | AJ75: -
E76: Estimated change in baseline vitamin A deficiency since the most recent survey | F76: % | G76: calc | H76: - | I76: =IFERROR(I74*$H75,"-") -> -0.16015219 | J76: =IFERROR(J74*$H75,"-") -> -0.17349821 | K76: =IFERROR(K74*$H75,"-") -> -0.20019024 | L76: =IFERROR(L74*$H75,"-") -> -0.30695837 | M76: =IFERROR(M74*$H75,"-") -> - | N76: =IFERROR(N74*$H75,"-") -> -0.14680618 | O76: =IFERROR(O74*$H75,"-") -> -0.29361236 | P76: =IFERROR(P74*$H75,"-") -> -0.3336504 | ... AJ76: =IFERROR(AJ74*$H75,"-") -> -
E77: Estimated vitamin A deficiency prevalence at the time of the grantee's VAS campaign | F77: % | G77: calc | H77: - | I77: =IFERROR(I71*(1+I76),"-") -> 0.20576271 | J77: =IFERROR(J71*(1+J76),"-") -> 0.28927563 | K77: =IFERROR(K71*(1+K76),"-") -> 0.19195434 | L77: =IFERROR(L71*(1+L76),"-") -> 0.42275539 | M77: =IFERROR(M71*(1+M76),"-") -> - | N77: =IFERROR(N71*(1+N76),"-") -> 0.076787444 | O77: =IFERROR(O71*(1+O76),"-") -> 0.29668281 | P77: =IFERROR(P71*(1+P76),"-") -> 0.51375554 | ... AJ77: =IFERROR(AJ71*(1+AJ76),"-") -> -
C79: Vitamin A deficiency prevalence based on estimates from GBD 2017
E80: Vitamin A deficiency prevalence rate among 6-59-month-olds, derived from GBD 2017 | F80: =Inputs!F86 -> % | G80: =Inputs!G86 -> input | H80: =Inputs!H86 -> - | I80: =Inputs!I86 -> 0.3068667 | J80: =Inputs!J86 -> 0.3083889 | K80: =Inputs!K86 -> 0.3005 | L80: =Inputs!L86 -> 0.328 | M80: =Inputs!M86 -> 0.2774778 | ... AJ80: =Inputs!AJ86 -> 0.2343924
C82: Weighting for vitamin A deficiency prevalence rates from different sources
E83: Weight assigned to vitamin A deficiency rates found in the most recent surveys | F83: =Inputs!F89 -> % | G83: =Inputs!G89 -> input | H83: =Inputs!H89 -> - | I83: =Inputs!I89 -> 0.25 | J83: =Inputs!J89 -> 0.5 | K83: =Inputs!K89 -> 0.5 | L83: =Inputs!L89 -> 0.5 | M83: =Inputs!M89 -> 0 | ... AJ83: =Inputs!AJ89 -> 0
E84: Weight assigned to vitamin A deficiency rates from GBD 2017 | F84: =Inputs!F90 -> % | G84: =Inputs!G90 -> input | H84: =Inputs!H90 -> - | I84: =Inputs!I90 -> 0.75 | J84: =Inputs!J90 -> 0.5 | K84: =Inputs!K90 -> 0.5 | L84: =Inputs!L90 -> 0.5 | M84: =Inputs!M90 -> 1 | ... AJ84: =Inputs!AJ90 -> 1
C86: Estimated vitamin A deficiency prevalence
E87: Estimated vitamin A deficiency prevalence rate among people under age 5 | F87: % | G87: calc | H87: - | I87: =IFERROR(SUMPRODUCT({I77,I80},{I83,I84}),"-") -> 0.2815907 | J87: =IFERROR(SUMPRODUCT({J77,J80},{J83,J84}),"-") -> 0.29883226 | K87: =IFERROR(SUMPRODUCT({K77,K80},{K83,K84}),"-") -> 0.24622717 | L87: =IFERROR(SUMPRODUCT({L77,L80},{L83,L84}),"-") -> 0.3753777 | M87: =IFERROR(SUMPRODUCT({M77,M80},{M83,M84}),"-") -> 0.2774778 | N87: =IFERROR(SUMPRODUCT({N77,N80},{N83,N84}),"-") -> 0.22023262 | O87: =IFERROR(SUMPRODUCT({O77,O80},{O83,O84}),"-") -> 0.28104141 | P87: =IFERROR(SUMPRODUCT({P77,P80},{P83,P84}),"-") -> 0.35758053 | ... AJ87: =IFERROR(SUMPRODUCT({AJ77,AJ80},{AJ83,AJ84}),"-") -> 0.2343924
A89: External validity adjustment implied by vitamin A deficiency prevalence
C91: Final vitamin A deficiency prevalence estimate
E92: Vitamin A deficiency prevalence among people under age 5 | F92: % | G92: feed | H92: =IF(H87<>"-",H87,H66) -> - | I92: =IF(I66<>"-",I66,I87) -> 0.2815907 | J92: =IF(J66<>"-",J66,J87) -> 0.29883226 | K92: =IF(K66<>"-",K66,K87) -> 0.24622717 | L92: =IF(L66<>"-",L66,L87) -> 0.3753777 | M92: =IF(M66<>"-",M66,M87) -> 0.2774778 | N92: =IF(N66<>"-",N66,N87) -> 0.22023262 | O92: =IF(O66<>"-",O66,O87) -> 0.28104141 | P92: =IF(P66<>"-",P66,P87) -> 0.35758053 | ... AJ92: =IF(AJ66<>"-",AJ66,AJ87) -> 0.2343924
C94: Vitamin A deficiency prevalence in the populations studied by trials from Imdad et al. 2017
E95: Vitamin A deficiency prevalence in the populations studied by trials from Imdad et al. 2017 | F95: =Inputs!F93 -> % | G95: =Inputs!G93 -> input | H95: =Inputs!H93 -> 0.5891852 | I95: =Inputs!I93 -> - | J95: =Inputs!J93 -> - | K95: =Inputs!K93 -> - | L95: =Inputs!L93 -> - | M95: =Inputs!M93 -> - | ... AJ95: =Inputs!AJ93 -> -
E96: External validity adjustment based on vitamin A deficiency prevalence | F96: % | G96: calc | H96: - | I96: =(I92/$H95)-1 -> -0.52206759 | J96: =(J92/$H95)-1 -> -0.49280419 | K96: =(K92/$H95)-1 -> -0.58208867 | L96: =(L92/$H95)-1 -> -0.36288675 | M96: =(M92/$H95)-1 -> -0.52904825 | N96: =(N92/$H95)-1 -> -0.62620816 | O96: =(O92/$H95)-1 -> -0.52299989 | P96: =(P92/$H95)-1 -> -0.39309315 | ... AJ96: =(AJ92/$H95)-1 -> -0.60217534
A98: Proportion of mortalities that are susceptible to prevention through VAS
C100: Total mortalities among the VAS-eligible population
E101: Total mortalities per year among 6-59-month-olds | F101: ='Counterfactual mortality'!F16 -> # | G101: supp | H101: ='Counterfactual mortality'!H16 -> - | I101: ='Counterfactual mortality'!I16 -> 55675.086 | J101: ='Counterfactual mortality'!J16 -> 32099.534 | K101: ='Counterfactual mortality'!K16 -> 27922.712 | L101: ='Counterfactual mortality'!L16 -> 77051.37 | M101: ='Counterfactual mortality'!M16 -> 24418.112 | N101: ='Counterfactual mortality'!N16 -> 19571.679 | O101: ='Counterfactual mortality'!O16 -> 20147.329 | ... AJ101: ='Counterfactual mortality'!AJ16 -> 37603.289
C103: Proportion of post-neo-natal mortalities that are among 1-5-month-olds
E104: Proportion of post-neonatal mortalities that are among 1-5-month-olds | F104: ='Counterfactual mortality'!F14 -> % | G104: supp | H104: ='Counterfactual mortality'!H14 -> 0.53 | I104: ='Counterfactual mortality'!I14 | J104: ='Counterfactual mortality'!J14 | K104: ='Counterfactual mortality'!K14 | L104: ='Counterfactual mortality'!L14 | M104: ='Counterfactual mortality'!M14 -> - | N104: ='Counterfactual mortality'!N14 -> - | O104: ='Counterfactual mortality'!O14 -> - | ... AJ104: ='Counterfactual mortality'!AJ14 -> -
C106: Measles mortalities per year among people under five
E107: Measles mortalities per year among people under age 5 | F107: =Inputs!F96 -> # | G107: =Inputs!G96 -> input | H107: =Inputs!H96 -> - | I107: =Inputs!I96 -> 2083.4522 | J107: =Inputs!J96 -> 1942.618 | K107: =Inputs!K96 -> 188.81748 | L107: =Inputs!L96 -> 3123.4209 | M107: =Inputs!M96 -> 995.77131 | ... AJ107: =Inputs!AJ96 -> 3759.2508
E108: Early neonatal measles mortalities per year (babies under 7 days old) | F108: =Inputs!F97 -> # | G108: =Inputs!G97 -> input | H108: =Inputs!H97 -> - | I108: =Inputs!I97 -> 0 | J108: =Inputs!J97 -> 0 | K108: =Inputs!K97 -> 0 | L108: =Inputs!L97 -> 213.19054 | M108: =Inputs!M97 -> 0 | ... AJ108: =Inputs!AJ97 -> 0
E109: Late neonatal measles mortalities per year (babies between 7 and 27 days old) | F109: =Inputs!F98 -> # | G109: =Inputs!G98 -> input | H109: =Inputs!H98 -> - | I109: =Inputs!I98 -> 0 | J109: =Inputs!J98 -> 0 | K109: =Inputs!K98 -> 0 | L109: =Inputs!L98 -> 43.474521 | M109: =Inputs!M98 -> 0 | ... AJ109: =Inputs!AJ98 -> 0
E110: Post-neonatal measles mortalities per year (babies between 28 and 364 days old) | F110: =Inputs!F99 -> # | G110: =Inputs!G99 -> input | H110: =Inputs!H99 -> - | I110: =Inputs!I99 -> 615.97035 | J110: =Inputs!J99 -> 528.34301 | K110: =Inputs!K99 -> 51.675061 | L110: =Inputs!L99 -> 940.06798 | M110: =Inputs!M99 -> 252.31605 | ... AJ110: =Inputs!AJ99 -> 1053.3567
E111: Estimated measles mortalities per year among 1-5-month-olds | F111: # | G111: calc | H111: - | I111: =I110*$H$104 -> 326.46428 | J111: =J110*$H$104 -> 280.0218 | K111: =K110*$H$104 -> 27.387782 | L111: =L110*$H$104 -> 498.23603 | M111: =M110*$H$104 -> 133.7275 | N111: =N110*$H$104 -> 59.03747 | O111: =O110*$H$104 -> 321.37258 | P111: =P110*$H$104 -> 357.52491 | ... AJ111: =AJ110*$H$104 -> 558.27905
E112: Measles mortalities per year among 6-59-month-olds | F112: # | G112: calc | H112: - | I112: =I107-SUM(I108:I109,I111) -> 1756.9879 | J112: =J107-SUM(J108:J109,J111) -> 1662.5962 | K112: =K107-SUM(K108:K109,K111) -> 161.42969 | L112: =L107-SUM(L108:L109,L111) -> 2368.5198 | M112: =M107-SUM(M108:M109,M111) -> 862.0438 | N112: =N107-SUM(N108:N109,N111) -> 310.18162 | O112: =O107-SUM(O108:O109,O111) -> 1614.3404 | P112: =P107-SUM(P108:P109,P111) -> 2086.2938 | ... AJ112: =AJ107-SUM(AJ108:AJ109,AJ111) -> 3200.9718
C114: Diarrheal disease mortalities per year among people under five
E115: Diarrheal disease mortalities per year among people under age 5 | F115: =Inputs!F102 -> # | G115: =Inputs!G102 -> input | H115: =Inputs!H102 -> - | I115: =Inputs!I102 -> 9151.7311 | J115: =Inputs!J102 -> 13471.728 | K115: =Inputs!K102 -> 3977.8551 | L115: =Inputs!L102 -> 18979.547 | M115: =Inputs!M102 -> 2792.805 | ... AJ115: =Inputs!AJ102 -> 4492.678
E116: Early neonatal diarrheal disease mortalities per year (babies under 7 days old) | F116: =Inputs!F103 -> # | G116: =Inputs!G103 -> input | H116: =Inputs!H103 -> - | I116: =Inputs!I103 -> 138.92928 | J116: =Inputs!J103 -> 290.19735 | K116: =Inputs!K103 -> 108.52082 | L116: =Inputs!L103 -> 725.09589 | M116: =Inputs!M103 -> 61.524021 | ... AJ116: =Inputs!AJ103 -> 149.99415
E117: Late neonatal diarrheal disease mortalities per year (babies between 7 and 27 days old) | F117: =Inputs!F104 -> # | G117: =Inputs!G104 -> input | H117: =Inputs!H104 -> - | I117: =Inputs!I104 -> 420.13994 | J117: =Inputs!J104 -> 626.54214 | K117: =Inputs!K104 -> 245.07597 | L117: =Inputs!L104 -> 1156.6904 | M117: =Inputs!M104 -> 145.24443 | ... AJ117: =Inputs!AJ104 -> 257.41939
E118: Post-neonatal diarrheal disease mortalities per year (babies between 28 and 364 days old) | F118: =Inputs!F105 -> # | G118: =Inputs!G105 -> input | H118: =Inputs!H105 -> - | I118: =Inputs!I105 -> 4166.3922 | J118: =Inputs!J105 -> 6046.2044 | K118: =Inputs!K105 -> 1429.6183 | L118: =Inputs!L105 -> 10035.013 | M118: =Inputs!M105 -> 1141.9328 | ... AJ118: =Inputs!AJ105 -> 2144.9825
E119: Estimated diarrheal disease mortalities per year among 1-5-month-olds | F119: # | G119: calc | H119: - | I119: =I118*$H$104 -> 2208.1879 | J119: =J118*$H$104 -> 3204.4883 | K119: =K118*$H$104 -> 757.69771 | L119: =L118*$H$104 -> 5318.5572 | M119: =M118*$H$104 -> 605.2244 | N119: =N118*$H$104 -> 2075.3422 | O119: =O118*$H$104 -> 2749.5509 | P119: =P118*$H$104 -> 1502.1353 | ... AJ119: =AJ118*$H$104 -> 1136.8407
E120: Diarrheal disease mortalities per year among 6-59-month-olds | F120: # | G120: calc | H120: - | I120: =I115-SUM(I116:I117,I119) -> 6384.474 | J120: =J115-SUM(J116:J117,J119) -> 9350.5002 | K120: =K115-SUM(K116:K117,K119) -> 2866.5606 | L120: =L115-SUM(L116:L117,L119) -> 11779.203 | M120: =M115-SUM(M116:M117,M119) -> 1980.8122 | N120: =N115-SUM(N116:N117,N119) -> 4269.0306 | O120: =O115-SUM(O116:O117,O119) -> 7133.3348 | P120: =P115-SUM(P116:P117,P119) -> 4437.9276 | ... AJ120: =AJ115-SUM(AJ116:AJ117,AJ119) -> 2948.4238
C122: Communicable, maternal, maternal, neonatal, and nutritional disease mortalities per year among people under five
E123: Communicable, maternal, maternal, neonatal, and nutritional disease mortalities per year among people under age 5 | F123: =Inputs!F108 -> # | G123: =Inputs!G108 -> input | H123: =Inputs!H108 -> - | I123: =Inputs!I108 -> 78851.1 | J123: =Inputs!J108 -> 55800.17 | K123: =Inputs!K108 -> 57297.855 | L123: =Inputs!L108 -> 146985.76 | M123: =Inputs!M108 -> 38803.165 | ... AJ123: =Inputs!AJ108 -> 79959.293
E124: Early neonatal communicable, maternal, maternal, neonatal, and nutritional disease mortalities per year (babies under 7 days old) | F124: =Inputs!F109 -> # | G124: =Inputs!G109 -> input | H124: =Inputs!H109 -> - | I124: =Inputs!I109 -> 17929.345 | J124: =Inputs!J109 -> 15658.225 | K124: =Inputs!K109 -> 23250.278 | L124: =Inputs!L109 -> 47864.253 | M124: =Inputs!M109 -> 10088.261 | ... AJ124: =Inputs!AJ109 -> 31086.855
E125: Late neonatal communicable, maternal, maternal, neonatal, and nutritional disease mortalities per year (babies between 7 and 27 days old) | F125: =Inputs!F110 -> # | G125: =Inputs!G110 -> input | H125: =Inputs!H110 -> - | I125: =Inputs!I110 -> 5905.4799 | J125: =Inputs!J110 -> 4182.3207 | K125: =Inputs!K110 -> 4753.3884 | L125: =Inputs!L110 -> 9506.0479 | M125: =Inputs!M110 -> 3198.654 | ... AJ125: =Inputs!AJ110 -> 6358.7385
...

Sheet LeverageFunging
I1: Helen Keller International | Q1: Helen Keller International | Y1: Helen Keller International | AG1: Nutrition International
I2: Burkina Faso | J2: Cameroon | K2: Côte d'Ivoire | L2: DRC | M2: Guinea | N2: Kenya | O2: Madagascar | P2: Mali | Q2: Niger | R2: Nigeria | S2: Nigeria | T2: Nigeria | U2: Nigeria | V2: Nigeria | W2: Nigeria | X2: Nigeria | Y2: Nigeria | Z2: Nigeria | AA2: Nigeria | AB2: Nigeria | AC2: Nigeria | AD2: Nigeria | AE2: Nigeria | AF2: Nigeria | AG2: Angola | AH2: Chad | AI2: Togo | AJ2: Uganda
A3: Supplemental calculations for the leverage/funging adjustment | F3: unit | G3: type | H3: Overall | R3: Adamawa | S3: Akwa Ibom | T3: Anambra | U3: Benue | V3: Delta | W3: Ebonyi | X3: Edo | Y3: Ekiti | Z3: Imo | AA3: Kogi | AB3: Nasarawa | AC3: Ogun | AD3: Osun | AE3: Rivers | AF3: Taraba
E4: Final cost-effectiveness estimate (pulled from "Main calcs" sheet for visibility) | F4: ='Main CEA'!F149 -> xbenchmark | G4: main | H4: ='Main CEA'!H149 -> - | I4: ='Main CEA'!I149 -> 22.604158 | J4: ='Main CEA'!J149 -> 15.907951 | K4: ='Main CEA'!K149 -> 8.5391703 | L4: ='Main CEA'!L149 -> 16.914533 | M4: ='Main CEA'!M149 -> 10.932207 | N4: ='Main CEA'!N149 -> 4.7974496 | O4: ='Main CEA'!O149 -> 15.912911 | ... AJ4: ='Main CEA'!AJ149 -> 6.3105992
A5: Costs
C7: GiveWell costs
E8: Grant size | F8: =Inputs!F8 -> $ | G8: =Inputs!G8 -> input | H8: =Inputs!H8 -> 1000000 | I8: =Inputs!I8 -> - | J8: =Inputs!J8 -> - | K8: =Inputs!K8 -> - | L8: =Inputs!L8 -> - | M8: =Inputs!M8 -> - | ... AJ8: =Inputs!AJ8 -> -
C10: Cost breakdown
E11: Percentage of total costs covered by the grantee | F11: =Inputs!F11 -> % | G11: =Inputs!G11 -> input | H11: =Inputs!H11 -> - | I11: =Inputs!I11 -> 0.4310638 | J11: =Inputs!J11 -> 0.6403403 | K11: =Inputs!K11 -> 0.4659904 | L11: =Inputs!L11 -> 0.4659904 | M11: =Inputs!M11 -> 0.5527665 | ... AJ11: =Inputs!AJ11 -> 0.7
E12: Percentage of total costs covered by Nutrition International (vitamin A capsule procurement) | F12: =Inputs!F12 -> % | G12: =Inputs!G12 -> input | H12: =Inputs!H12 -> - | I12: =Inputs!I12 -> 0.0642112 | J12: =Inputs!J12 -> 0.0596597 | K12: =Inputs!K12 -> 0.0697078 | L12: =Inputs!L12 -> 0.0697078 | M12: =Inputs!M12 -> 0.0486625 | ... AJ12: =Inputs!AJ12 -> 0
E13: Percentage of total costs covered by other philanthropic actors | F13: =Inputs!F13 -> % | G13: =Inputs!G13 -> input | H13: =Inputs!H13 -> - | I13: =Inputs!I13 -> 0.0565391 | J13: =Inputs!J13 -> 0 | K13: =Inputs!K13 -> 0.1323195 | L13: =Inputs!L13 -> 0.1323195 | M13: =Inputs!M13 -> 0.098571 | ... AJ13: =Inputs!AJ13 -> 0
E14: Percentage of total costs covered by domestic governments (financial contributions) | F14: =Inputs!F14 -> % | G14: =Inputs!G14 -> input | H14: =Inputs!H14 -> - | I14: =Inputs!I14 -> 0.1481859 | J14: =Inputs!J14 -> 0 | K14: =Inputs!K14 -> 0.0319823 | L14: =Inputs!L14 -> 0.0319823 | M14: =Inputs!M14 -> 0 | ... AJ14: =Inputs!AJ14 -> 0
E15: Percentage of total costs covered by domestic governments (in-kind contributions) | F15: =Inputs!F15 -> % | G15: =Inputs!G15 -> input | H15: =Inputs!H15 -> - | I15: =Inputs!I15 -> 0.3 | J15: =Inputs!J15 -> 0.3 | K15: =Inputs!K15 -> 0.3 | L15: =Inputs!L15 -> 0.3 | M15: =Inputs!M15 -> 0.3 | ... AJ15: =Inputs!AJ15 -> 0.3
C17: Total costs
E18: Total spending by all contributors | F18: ='Main CEA'!F18 -> $ | G18: main | H18: ='Main CEA'!H18 -> - | I18: ='Main CEA'!I18 -> 2319842.2 | J18: ='Main CEA'!J18 -> 1561669.6 | K18: ='Main CEA'!K18 -> 2145967 | L18: ='Main CEA'!L18 -> 2145967 | M18: ='Main CEA'!M18 -> 1809082.1 | N18: ='Main CEA'!N18 -> 2145967 | O18: ='Main CEA'!O18 -> 1671374.6 | ... AJ18: ='Main CEA'!AJ18 -> 1428571.4
C20: Total spending attributable to different actors
E21: Total spending contributed by grantee | F21: ='Main CEA'!F21 -> $ | G21: main | H21: ='Main CEA'!H21 -> - | I21: ='Main CEA'!I21 -> 1000000 | J21: ='Main CEA'!J21 -> 1000000 | K21: ='Main CEA'!K21 -> 1000000 | L21: ='Main CEA'!L21 -> 1000000 | M21: ='Main CEA'!M21 -> 1000000 | N21: ='Main CEA'!N21 -> 1000000 | O21: ='Main CEA'!O21 -> 1000000 | ... AJ21: ='Main CEA'!AJ21 -> 1000000
E22: Total spending contributed by Nutrition International (vitamin A capsule procurement) | F22: ='Main CEA'!F22 -> $ | G22: main | H22: ='Main CEA'!H22 -> - | I22: ='Main CEA'!I22 -> 148959.85 | J22: ='Main CEA'!J22 -> 93168.742 | K22: ='Main CEA'!K22 -> 149590.64 | L22: ='Main CEA'!L22 -> 149590.64 | M22: ='Main CEA'!M22 -> 88034.459 | N22: ='Main CEA'!N22 -> 149590.64 | O22: ='Main CEA'!O22 -> 116507.85 | ... AJ22: ='Main CEA'!AJ22 -> 0
E23: Total spending contributed by other philanthropic actors | F23: ='Main CEA'!F23 -> $ | G23: main | H23: ='Main CEA'!H23 -> - | I23: ='Main CEA'!I23 -> 131161.79 | J23: ='Main CEA'!J23 -> 0 | K23: ='Main CEA'!K23 -> 283953.27 | L23: ='Main CEA'!L23 -> 283953.27 | M23: ='Main CEA'!M23 -> 178323.04 | N23: ='Main CEA'!N23 -> 283953.27 | O23: ='Main CEA'!O23 -> 0 | ... AJ23: ='Main CEA'!AJ23 -> 0
E24: Total spending contributed by domestic governments (financial contributions) | F24: ='Main CEA'!F24 -> $ | G24: main | H24: ='Main CEA'!H24 -> - | I24: ='Main CEA'!I24 -> 343767.91 | J24: ='Main CEA'!J24 -> 0 | K24: ='Main CEA'!K24 -> 68632.959 | L24: ='Main CEA'!L24 -> 68632.959 | M24: ='Main CEA'!M24 -> 0 | N24: ='Main CEA'!N24 -> 68632.959 | O24: ='Main CEA'!O24 -> 53454.405 | ... AJ24: ='Main CEA'!AJ24 -> 0
E25: Total spending contributed by domestic governments (in-kind contributions) | F25: ='Main CEA'!F25 -> $ | G25: main | H25: ='Main CEA'!H25 -> - | I25: ='Main CEA'!I25 -> 695952.66 | J25: ='Main CEA'!J25 -> 468500.89 | K25: ='Main CEA'!K25 -> 643790.09 | L25: ='Main CEA'!L25 -> 643790.09 | M25: ='Main CEA'!M25 -> 542724.64 | N25: ='Main CEA'!N25 -> 643790.09 | O25: ='Main CEA'!O25 -> 501412.4 | ... AJ25: ='Main CEA'!AJ25 -> 428571.43
C27: Upstream / downstream spending
E28: ='Main CEA'!E28 -> Total spending causally upstream of donations to grantee | F28: ='Main CEA'!F28 -> $ | G28: main | H28: ='Main CEA'!H28 -> - | I28: ='Main CEA'!I28 -> 1474929.7 | J28: ='Main CEA'!J28 -> 1000000 | K28: ='Main CEA'!K28 -> 1352586.2 | L28: ='Main CEA'!L28 -> 1352586.2 | M28: ='Main CEA'!M28 -> 1178323 | N28: ='Main CEA'!N28 -> 1352586.2 | O28: ='Main CEA'!O28 -> 1053454.4 | ... AJ28: ='Main CEA'!AJ28 -> 1000000
E29: ='Main CEA'!E29 -> Total spending causally downstream of donations to grantee | F29: ='Main CEA'!F29 -> $ | G29: main | H29: ='Main CEA'!H29 -> - | I29: ='Main CEA'!I29 -> 844912.52 | J29: ='Main CEA'!J29 -> 561669.63 | K29: ='Main CEA'!K29 -> 793380.72 | L29: ='Main CEA'!L29 -> 793380.72 | M29: ='Main CEA'!M29 -> 630759.1 | N29: ='Main CEA'!N29 -> 793380.72 | O29: ='Main CEA'!O29 -> 617920.24 | ... AJ29: ='Main CEA'!AJ29 -> 428571.43
A31: Counterfactual funding scenarios
C33: Probability of scenarios in the absence of philanthropic funding
E34: Scenario 1: Domestic governments would replace the grantee's costs | F34: =Inputs!F193 -> % | G34: =Inputs!G193 -> input | H34: =Inputs!H193 -> - | I34: =Inputs!I193 -> 0.1 | J34: =Inputs!J193 -> 0.05 | K34: =Inputs!K193 -> 0.1 | L34: =Inputs!L193 -> 0.1 | M34: =Inputs!M193 -> 0.1 | ... AJ34: =Inputs!AJ193 -> 0.1
E35: Scenario 2: Other philanthropic actors would replace the grantee's costs | F35: =Inputs!F194 -> % | G35: =Inputs!G194 -> input | H35: =Inputs!H194 -> - | I35: =Inputs!I194 -> 0.2 | J35: =Inputs!J194 -> 0.33 | K35: =Inputs!K194 -> 0.35 | L35: =Inputs!L194 -> 0.1 | M35: =Inputs!M194 -> 0.35 | ... AJ35: =Inputs!AJ194 -> 0.3
E36: Scenario 3: Other actors' upstream costs would stay the same (downstream costs would shrink in proportion to the total size of the program) | F36: =Inputs!F195 -> % | G36: =Inputs!G195 -> input | H36: =Inputs!H195 -> - | I36: =Inputs!I195 -> 0.7 | J36: =Inputs!J195 -> 0.62 | K36: =Inputs!K195 -> 0.55 | L36: =Inputs!L195 -> 0.8 | M36: =Inputs!M195 -> 0.55 | ... AJ36: =Inputs!AJ195 -> 0.6
E37: Scenario 4: Distributions would go unfunded | F37: % | G37: calc | H37: - | I37: =1-SUM(I34:I36) -> 0 | J37: =1-SUM(J34:J36) -> 0 | K37: =1-SUM(K34:K36) -> 0 | L37: =1-SUM(L34:L36) -> 0 | M37: =1-SUM(M34:M36) -> 0 | N37: =1-SUM(N34:N36) -> 0 | O37: =1-SUM(O34:O36) -> 0 | P37: =1-SUM(P34:P36) -> 0 | ... AJ37: =1-SUM(AJ34:AJ36) -> 0
C39: Proportion of the program that would still occur in each scenario
E40: Scenario 1: Domestic governments would replace the grantee's costs | F40: =Inputs!F198 -> % | G40: =Inputs!G198 -> input | H40: =Inputs!H198 -> 1 | I40: =Inputs!I198 -> - | J40: =Inputs!J198 -> - | K40: =Inputs!K198 -> - | L40: =Inputs!L198 -> - | M40: =Inputs!M198 -> - | ... AJ40: =Inputs!AJ198 -> -
E41: Scenario 2: Other philanthropic actors would replace the grantee's costs | F41: =Inputs!F199 -> % | G41: =Inputs!G199 -> input | H41: =Inputs!H199 -> 1 | I41: =Inputs!I199 -> - | J41: =Inputs!J199 -> - | K41: =Inputs!K199 -> - | L41: =Inputs!L199 -> - | M41: =Inputs!M199 -> - | ... AJ41: =Inputs!AJ199 -> -
E42: Scenario 3: Other actors' upstream costs would stay the same (downstream costs would shrink in proportion to the total size of the program) | F42: % | G42: calc | H42: - | I42: =SUM(I23:I24)/I28 -> 0.32200158 | J42: =SUM(J23:J24)/J28 -> 0 | K42: =SUM(K23:K24)/K28 -> 0.2606756 | L42: =SUM(L23:L24)/L28 -> 0.2606756 | M42: =SUM(M23:M24)/M28 -> 0.15133629 | N42: =SUM(N23:N24)/N28 -> 0.2606756 | O42: =SUM(O23:O24)/O28 -> 0.050742021 | P42: =SUM(P23:P24)/P28 -> 0.29727871 | ... AJ42: =SUM(AJ23:AJ24)/AJ28 -> 0
E43: Scenario 4: Distributions would go unfunded | F43: =Inputs!F200 -> % | G43: =Inputs!G200 -> input | H43: =Inputs!H200 -> 0 | I43: =Inputs!I200 -> - | J43: =Inputs!J200 -> - | K43: =Inputs!K200 -> - | L43: =Inputs!L200 -> - | M43: =Inputs!M200 -> - | ... AJ43: =Inputs!AJ200 -> -
A45: Value of spending
C47: Cost-effectiveness of the program (before leverage and funging)
E48: Units of value generated per dollar spent (before final adjustments) | F48: ='Main CEA'!F93 -> UoV | G48: main | H48: ='Main CEA'!H93 -> - | I48: ='Main CEA'!I93 -> 0.081810521 | J48: ='Main CEA'!J93 -> 0.062659406 | K48: ='Main CEA'!K93 -> 0.035403361 | L48: ='Main CEA'!L93 -> 0.054875268 | M48: ='Main CEA'!M93 -> 0.046344013 | N48: ='Main CEA'!N93 -> 0.018989343 | O48: ='Main CEA'!O93 -> 0.05394946 | ... AJ48: ='Main CEA'!AJ93 -> 0.026496545
E49: Total supplemental grantee-level adjustment | F49: ='Main CEA'!F121 -> % | G49: main | H49: ='Main CEA'!H121 -> - | I49: ='Main CEA'!I121 -> -0.22 | J49: ='Main CEA'!J121 -> -0.22 | K49: ='Main CEA'!K121 -> -0.22 | L49: ='Main CEA'!L121 -> -0.22 | M49: ='Main CEA'!M121 -> -0.22 | N49: ='Main CEA'!N121 -> -0.22 | O49: ='Main CEA'!O121 -> -0.22 | ... AJ49: ='Main CEA'!AJ121 -> -0.24
E50: Total supplemental intervention-level adjustment | F50: ='Main CEA'!F135 -> % | G50: main | H50: ='Main CEA'!H135 -> - | I50: ='Main CEA'!I135 -> 0.665 | J50: ='Main CEA'!J135 -> 0.665 | K50: ='Main CEA'!K135 -> 0.665 | L50: ='Main CEA'!L135 -> 0.665 | M50: ='Main CEA'!M135 -> 0.665 | N50: ='Main CEA'!N135 -> 0.665 | O50: ='Main CEA'!O135 -> 0.665 | ... AJ50: ='Main CEA'!AJ135 -> 0.665
E51: Units of value generated per dollar donated to grantee (after supplemental adjustments) | F51: UoV | G51: calc | H51: - | I51: =I48*(1+I49)*(1+I50) -> 0.10624732 | J51: =J48*(1+J49)*(1+J50) -> 0.08137577 | K51: =K48*(1+K49)*(1+K50) -> 0.045978344 | L51: =L48*(1+L49)*(1+L50) -> 0.07126651 | M51: =M48*(1+M49)*(1+M50) -> 0.060186969 | N51: =N48*(1+N49)*(1+N50) -> 0.02466146 | O51: =O48*(1+O49)*(1+O50) -> 0.070064164 | P51: =P48*(1+P49)*(1+P50) -> 0.16848797 | ... AJ51: =AJ48*(1+AJ49)*(1+AJ50) -> 0.033528728
C53: Lives saved by the program (before leverage and funging)
E54: Total lives saved (before final adjustments) | F54: ='Main CEA'!F103 -> # | G54: main | H54: ='Main CEA'!H103 -> - | I54: ='Main CEA'!I103 -> 553.36091 | J54: ='Main CEA'!J103 -> 423.82404 | K54: ='Main CEA'!K103 -> 239.46597 | L54: ='Main CEA'!L103 -> 371.17265 | M54: ='Main CEA'!M103 -> 313.46781 | N54: ='Main CEA'!N103 -> 128.44265 | O54: ='Main CEA'!O103 -> 364.91055 | ... AJ54: ='Main CEA'!AJ103 -> 179.22086
E55: ='Main CEA'!D121 -> Total supplemental grantee-level adjustment | F55: ='Main CEA'!F121 -> % | G55: ='Main CEA'!G121 -> calc | H55: ='Main CEA'!H121 -> - | I55: ='Main CEA'!I121 -> -0.22 | J55: ='Main CEA'!J121 -> -0.22 | K55: ='Main CEA'!K121 -> -0.22 | L55: ='Main CEA'!L121 -> -0.22 | M55: ='Main CEA'!M121 -> -0.22 | ... AJ55: ='Main CEA'!AJ121 -> -0.24
E56: Total supplemental intervention-level adjustment affecting lives saved | F56: ='Main CEA'!F160 -> % | G56: main | H56: ='Main CEA'!H160 -> - | I56: ='Main CEA'!I160 -> 0.015 | J56: ='Main CEA'!J160 -> 0.015 | K56: ='Main CEA'!K160 -> 0.015 | L56: ='Main CEA'!L160 -> 0.015 | M56: ='Main CEA'!M160 -> 0.015 | N56: ='Main CEA'!N160 -> 0.015 | O56: ='Main CEA'!O160 -> 0.015 | ... AJ56: ='Main CEA'!AJ160 -> 0.015
E57: Total lives saved (after supplemental adjustments) | F57: # | G57: calc | H57: - | I57: =I54*(1+I55)*(1+I56) -> 438.09583 | J57: =J54*(1+J55)*(1+J56) -> 335.54149 | K57: =K54*(1+K55)*(1+K56) -> 189.58521 | L57: =L54*(1+L55)*(1+L56) -> 293.85739 | M57: =M54*(1+M55)*(1+M56) -> 248.17247 | N57: =N54*(1+N55)*(1+N56) -> 101.68805 | O57: =O54*(1+O55)*(1+O56) -> 288.89968 | P57: =P54*(1+P55)*(1+P56) -> 694.73633 | ... AJ57: =AJ54*(1+AJ55)*(1+AJ56) -> 138.25097
C59: Counterfactual value of spending from non-philanthropic actors
E60: Counterfactual value per dollar spent by domestic governments on VAS programs | F60: =Inputs!F203 -> UoV | G60: =Inputs!G203 -> input | H60: =Inputs!H203 -> 0.005057 | I60: =Inputs!I203 -> - | J60: =Inputs!J203 -> - | K60: =Inputs!K203 -> - | L60: =Inputs!L203 -> - | M60: =Inputs!M203 -> - | ... AJ60: =Inputs!AJ203 -> -
E61: Counterfactual value per dollar spent by Nutrition International | F61: =Inputs!F204 -> UoV | G61: =Inputs!G204 -> input | H61: =Inputs!H204 -> 0.0056391 | I61: =Inputs!I204 -> - | J61: =Inputs!J204 -> - | K61: =Inputs!K204 -> - | L61: =Inputs!L204 -> - | M61: =Inputs!M204 -> - | ... AJ61: =Inputs!AJ204 -> -
E62: Counterfactual value per dollar spent by other philanthropic actors supporting VAS campaigns | F62: =Inputs!F205 -> UoV | G62: =Inputs!G205 -> input | H62: =Inputs!H205 -> - | I62: =Inputs!I205 -> 0.01231 | J62: =Inputs!J205 -> 0.01231 | K62: =Inputs!K205 -> 0.01231 | L62: =Inputs!L205 -> 0.01231 | M62: =Inputs!M205 -> 0.01231 | ... AJ62: =Inputs!AJ205 -> 0.0056391
A64: Value generated across different counterfactual scenarios
C66: Scenario 1: Domestic governments would replace the grantee's spending
D67: Hypothetical impact of shifting government spending
E68: Amount of spending domestic governments would shift to the grantee program | F68: $ | G68: calc | H68: - | I68: =I21 -> 1000000 | J68: =J21 -> 1000000 | K68: =K21 -> 1000000 | L68: =L21 -> 1000000 | M68: =M21 -> 1000000 | N68: =N21 -> 1000000 | O68: =O21 -> 1000000 | P68: =P21 -> 1000000 | ... AJ68: =AJ21 -> 1000000
E69: Value generated by shifting government spending to the grantee program | F69: UoV | G69: calc | H69: - | I69: =I68*I51 -> 106247.32 | J69: =J68*J51 -> 81375.77 | K69: =K68*K51 -> 45978.344 | L69: =L68*L51 -> 71266.51 | M69: =M68*M51 -> 60186.969 | N69: =N68*N51 -> 24661.46 | O69: =O68*O51 -> 70064.164 | P69: =P68*P51 -> 168487.97 | ... AJ69: =AJ68*AJ51 -> 33528.728
E70: Value lost by shifting spending away from programs domestic governments would otherwise have funded | F70: UoV | G70: calc | H70: - | I70: =I68*$H60 -> 5057 | J70: =J68*$H60 -> 5057 | K70: =K68*$H60 -> 5057 | L70: =L68*$H60 -> 5057 | M70: =M68*$H60 -> 5057 | N70: =N68*$H60 -> 5057 | O70: =O68*$H60 -> 5057 | P70: =P68*$H60 -> 5057 | ... AJ70: =AJ68*$H60 -> 5057
E71: Net value generated by shifting government spending to the grantee program | F71: UoV | G71: calc | H71: - | I71: =I69-I70 -> 101190.32 | J71: =J69-J70 -> 76318.77 | K71: =K69-K70 -> 40921.344 | L71: =L69-L70 -> 66209.51 | M71: =M69-M70 -> 55129.969 | N71: =N69-N70 -> 19604.46 | O71: =O69-O70 -> 65007.164 | P71: =P69-P70 -> 163430.97 | ... AJ71: =AJ69-AJ70 -> 28471.728
E72: Change in value generated by the grantee program if this scenario represented the true counterfactual | F72: UoV | G72: calc | H72: - | I72: =-I71 -> -101190.32 | J72: =-J71 -> -76318.77 | K72: =-K71 -> -40921.344 | L72: =-L71 -> -66209.51 | M72: =-M71 -> -55129.969 | N72: =-N71 -> -19604.46 | O72: =-O71 -> -65007.164 | P72: =-P71 -> -163430.97 | ... AJ72: =-AJ71 -> -28471.728
E73: Probability of this scenario representing the true counterfactual | F73: =F34 -> % | G73: feed | H73: =H34 -> - | I73: =I34 -> 0.1 | J73: =J34 -> 0.05 | K73: =K34 -> 0.1 | L73: =L34 -> 0.1 | M73: =M34 -> 0.1 | N73: =N34 -> 0.1 | O73: =O34 -> 0.05 | ... AJ73: =AJ34 -> 0.1
E74: Expected change in value generated by the grantee program | F74: UoV | G74: calc | H74: - | I74: =I72*I73 -> -10119.032 | J74: =J72*J73 -> -3815.9385 | K74: =K72*K73 -> -4092.1344 | L74: =L72*L73 -> -6620.951 | M74: =M72*M73 -> -5512.9969 | N74: =N72*N73 -> -1960.446 | O74: =O72*O73 -> -3250.3582 | P74: =P72*P73 -> -16343.097 | ... AJ74: =AJ72*AJ73 -> -2847.1728
C76: Scenario 2: Other philanthropic actors would replace the grantee's spending
D77: Hypothetical impact of shifting other philanthropic actors' spending
E78: Amount of spending other philanthropic actors would shift to the grantee program | F78: $ | G78: calc | H78: - | I78: =I21 -> 1000000 | J78: =J21 -> 1000000 | K78: =K21 -> 1000000 | L78: =L21 -> 1000000 | M78: =M21 -> 1000000 | N78: =N21 -> 1000000 | O78: =O21 -> 1000000 | P78: =P21 -> 1000000 | ... AJ78: =AJ21 -> 1000000
E79: Value generated by shifting other philanthropic actors' spending to the grantee program | F79: UoV | G79: calc | H79: - | I79: =I78*I51 -> 106247.32 | J79: =J78*J51 -> 81375.77 | K79: =K78*K51 -> 45978.344 | L79: =L78*L51 -> 71266.51 | M79: =M78*M51 -> 60186.969 | N79: =N78*N51 -> 24661.46 | O79: =O78*O51 -> 70064.164 | P79: =P78*P51 -> 168487.97 | ... AJ79: =AJ78*AJ51 -> 33528.728
E80: Value lost by shifting spending away from programs the other philanthropic actors would otherwise have funded | F80: UoV | G80: calc | H80: - | I80: =I78*I62 -> 12310 | J80: =J78*J62 -> 12310 | K80: =K78*K62 -> 12310 | L80: =L78*L62 -> 12310 | M80: =M78*M62 -> 12310 | N80: =N78*N62 -> 5639.1 | O80: =O78*O62 -> 12310 | P80: =P78*P62 -> 5639.1 | ... AJ80: =AJ78*AJ62 -> 5639.1
E81: Net value generated by shifting other philanthropic actors' spending to the grantee program | F81: UoV | G81: calc | H81: - | I81: =I79-I80 -> 93937.323 | J81: =J79-J80 -> 69065.77 | K81: =K79-K80 -> 33668.344 | L81: =L79-L80 -> 58956.51 | M81: =M79-M80 -> 47876.969 | N81: =N79-N80 -> 19022.36 | O81: =O79-O80 -> 57754.164 | P81: =P79-P80 -> 162848.87 | ... AJ81: =AJ79-AJ80 -> 27889.628
E82: Change in value generated by the grantee program if this scenario represented the true counterfactual | F82: UoV | G82: calc | H82: - | I82: =-I81 -> -93937.323 | J82: =-J81 -> -69065.77 | K82: =-K81 -> -33668.344 | L82: =-L81 -> -58956.51 | M82: =-M81 -> -47876.969 | N82: =-N81 -> -19022.36 | O82: =-O81 -> -57754.164 | P82: =-P81 -> -162848.87 | ... AJ82: =-AJ81 -> -27889.628
E83: Probability of this scenario representing the true counterfactual | F83: =F35 -> % | G83: feed | H83: =H35 -> - | I83: =I35 -> 0.2 | J83: =J35 -> 0.33 | K83: =K35 -> 0.35 | L83: =L35 -> 0.1 | M83: =M35 -> 0.35 | N83: =N35 -> 0.25 | O83: =O35 -> 0.2 | ... AJ83: =AJ35 -> 0.3
E84: Expected change in value generated by the grantee program | F84: UoV | G84: calc | H84: - | I84: =I82*I83 -> -18787.465 | J84: =J82*J83 -> -22791.704 | K84: =K82*K83 -> -11783.921 | L84: =L82*L83 -> -5895.651 | M84: =M82*M83 -> -16756.939 | N84: =N82*N83 -> -4755.5899 | O84: =O82*O83 -> -11550.833 | P84: =P82*P83 -> -40712.217 | ... AJ84: =AJ82*AJ83 -> -8366.8884
C86: Scenario 3: Other actors would spend the same amount and the program would be smaller
D87: Hypothetical impact of shifting government spending
E88: Amount of spending domestic governments would shift away from the grantee program | F88: $ | G88: calc | H88: - | I88: =I25*(1-I42) -> 471854.8 | J88: =J25*(1-J42) -> 468500.89 | K88: =K25*(1-K42) -> 475969.72 | L88: =L25*(1-L42) -> 475969.72 | M88: =M25*(1-M42) -> 460590.71 | N88: =N25*(1-N42) -> 475969.72 | O88: =O25*(1-O42) -> 475969.72 | P88: =P25*(1-P42) -> 487474.27 | ... AJ88: =AJ25*(1-AJ42) -> 428571.43
E89: Value generated by shifting spending toward programs domestic governments would otherwise have supported | F89: UoV | G89: calc | H89: - | I89: =I88*$H60 -> 2386.1697 | J89: =J88*$H60 -> 2369.209 | K89: =K88*$H60 -> 2406.9789 | L89: =L88*$H60 -> 2406.9789 | M89: =M88*$H60 -> 2329.2072 | N89: =N88*$H60 -> 2406.9789 | O89: =O88*$H60 -> 2406.9789 | P89: =P88*$H60 -> 2465.1574 | ... AJ89: =AJ88*$H60 -> 2167.2857
E90: Value lost by shifting government spending away from the grantee program | F90: UoV | G90: calc | H90: - | I90: 0 | J90: 0 | K90: 0 | L90: 0 | M90: 0 | N90: 0 | O90: 0 | P90: 0 | Q90: 0 | R90: 0 | S90: 0 | T90: 0 | U90: 0 | V90: 0 | W90: 0 | X90: 0 | Y90: 0 | Z90: 0 | AA90: 0 | AB90: 0 | AC90: 0 | AD90: 0 | AE90: 0 | AF90: 0 | AG90: 0 | AH90: 0 | AI90: 0 | AJ90: 0
E91: Net value generated by shifting government spending away from the grantee program | F91: UoV | G91: calc | H91: - | I91: =I89-I90 -> 2386.1697 | J91: =J89-J90 -> 2369.209 | K91: =K89-K90 -> 2406.9789 | L91: =L89-L90 -> 2406.9789 | M91: =M89-M90 -> 2329.2072 | N91: =N89-N90 -> 2406.9789 | O91: =O89-O90 -> 2406.9789 | P91: =P89-P90 -> 2465.1574 | ... AJ91: =AJ89-AJ90 -> 2167.2857
D92: Hypothetical impact of shifting Nutrition International's spending
E93: Amount of spending Nutrition International would shift away from the grantee program | F93: $ | G93: calc | H93: - | I93: =I22*(1-I42) -> 100994.54 | J93: =J22*(1-J42) -> 93168.742 | K93: =K22*(1-K42) -> 110596.01 | L93: =L22*(1-L42) -> 110596.01 | M93: =M22*(1-M42) -> 74711.651 | N93: =N22*(1-N42) -> 110596.01 | O93: =O22*(1-O42) -> 110596.01 | P93: =P22*(1-P42) -> 137439.96 | ... AJ93: =AJ22*(1-AJ42) -> 0
E94: Value generated by shifting spending toward programs Nutrition International would otherwise have supported | F94: UoV | G94: calc | H94: - | I94: =I93*$H61 -> 569.51833 | J94: =J93*$H61 -> 525.38785 | K94: =K93*$H61 -> 623.66194 | L94: =L93*$H61 -> 623.66194 | M94: =M93*$H61 -> 421.30647 | N94: =N93*$H61 -> 623.66194 | O94: =O93*$H61 -> 623.66194 | P94: =P93*$H61 -> 775.03766 | ... AJ94: =AJ93*$H61 -> 0
E95: Value lost by shifting Nutrition International's spending away from the grantee program | F95: UoV | G95: calc | H95: - | I95: 0 | J95: 0 | K95: 0 | L95: 0 | M95: 0 | N95: 0 | O95: 0 | P95: 0 | Q95: 0 | R95: 0 | S95: 0 | T95: 0 | U95: 0 | V95: 0 | W95: 0 | X95: 0 | Y95: 0 | Z95: 0 | AA95: 0 | AB95: 0 | AC95: 0 | AD95: 0 | AE95: 0 | AF95: 0 | AG95: 0 | AH95: 0 | AI95: 0 | AJ95: 0
E96: Net value generated by shifting Nutrition International's spending away from the grantee program | F96: UoV | G96: calc | H96: - | I96: =I94-I95 -> 569.51833 | J96: =J94-J95 -> 525.38785 | K96: =K94-K95 -> 623.66194 | L96: =L94-L95 -> 623.66194 | M96: =M94-M95 -> 421.30647 | N96: =N94-N95 -> 623.66194 | O96: =O94-O95 -> 623.66194 | P96: =P94-P95 -> 775.03766 | ... AJ96: =AJ94-AJ95 -> 0
D97: Overall impact of shifting spending
E98: Change in value generated by the grantee program if this scenario represented the true counterfactual | F98: UoV | G98: calc | H98: - | I98: =-SUM(I91,I96) -> -2955.6881 | J98: =-SUM(J91,J96) -> -2894.5968 | K98: =-SUM(K91,K96) -> -3030.6408 | L98: =-SUM(L91,L96) -> -3030.6408 | M98: =-SUM(M91,M96) -> -2750.5137 | N98: =-SUM(N91,N96) -> -3030.6408 | O98: =-SUM(O91,O96) -> -3030.6408 | P98: =-SUM(P91,P96) -> -3240.195 | ... AJ98: =-SUM(AJ91,AJ96) -> -2167.2857
E99: Probability of this scenario representing the true counterfactual | F99: =F36 -> % | G99: feed | H99: =H36 -> - | I99: =I36 -> 0.7 | J99: =J36 -> 0.62 | K99: =K36 -> 0.55 | L99: =L36 -> 0.8 | M99: =M36 -> 0.55 | N99: =N36 -> 0.65 | O99: =O36 -> 0.75 | ... AJ99: =AJ36 -> 0.6
E100: Expected change in value generated by the program | F100: UoV | G100: calc | H100: - | I100: =I98*I99 -> -2068.9817 | J100: =J98*J99 -> -1794.65 | K100: =K98*K99 -> -1666.8524 | L100: =L98*L99 -> -2424.5126 | M100: =M98*M99 -> -1512.7825 | N100: =N98*N99 -> -1969.9165 | O100: =O98*O99 -> -2272.9806 | P100: =P98*P99 -> -2106.1268 | ... AJ100: =AJ98*AJ99 -> -1300.3714
C102: Scenario 4: The grantee program would go unfunded
D103: Hypothetical impact of shifting government spending
E104: Amount of spending domestic governments would shift away from the grantee program | F104: $ | G104: calc | H104: - | I104: =I25 -> 695952.66 | J104: =J25 -> 468500.89 | K104: =K25 -> 643790.09 | L104: =L25 -> 643790.09 | M104: =M25 -> 542724.64 | N104: =N25 -> 643790.09 | O104: =O25 -> 501412.4 | P104: =P25 -> 693695.03 | ... AJ104: =AJ25 -> 428571.43
E105: Value generated by shifting spending to programs domestic governments would otherwise have funded | F105: UoV | G105: calc | H105: - | I105: =I104*$H60 -> 3519.4326 | J105: =J104*$H60 -> 2369.209 | K105: =K104*$H60 -> 3255.6465 | L105: =L104*$H60 -> 3255.6465 | M105: =M104*$H60 -> 2744.5585 | N105: =N104*$H60 -> 3255.6465 | O105: =O104*$H60 -> 2535.6425 | P105: =P104*$H60 -> 3508.0158 | ... AJ105: =AJ104*$H60 -> 2167.2857
E106: Value lost by shifting government spending away from the grantee program | F106: UoV | G106: calc | H106: - | I106: 0 | J106: 0 | K106: 0 | L106: 0 | M106: 0 | N106: 0 | O106: 0 | P106: 0 | Q106: 0 | R106: 0 | S106: 0 | T106: 0 | U106: 0 | V106: 0 | W106: 0 | X106: 0 | Y106: 0 | Z106: 0 | AA106: 0 | AB106: 0 | AC106: 0 | AD106: 0 | AE106: 0 | AF106: 0 | AG106: 0 | AH106: 0 | AI106: 0 | AJ106: 0
E107: Net value generated by shifting government spending away from the grantee program | F107: UoV | G107: calc | H107: - | I107: =I105-I106 -> 3519.4326 | J107: =J105-J106 -> 2369.209 | K107: =K105-K106 -> 3255.6465 | L107: =L105-L106 -> 3255.6465 | M107: =M105-M106 -> 2744.5585 | N107: =N105-N106 -> 3255.6465 | O107: =O105-O106 -> 2535.6425 | P107: =P105-P106 -> 3508.0158 | ... AJ107: =AJ105-AJ106 -> 2167.2857
D108: Hypothetical impact of shifting Nutrition International's spending
E109: Amount of spending Nutrition International would shift away from the grantee program | F109: $ | G109: calc | H109: - | I109: =I22 -> 148959.85 | J109: =J22 -> 93168.742 | K109: =K22 -> 149590.64 | L109: =L22 -> 149590.64 | M109: =M22 -> 88034.459 | N109: =N22 -> 149590.64 | O109: =O22 -> 116507.85 | P109: =P22 -> 195582.46 | ... AJ109: =AJ22 -> 0
E110: Value generated by shifting spending toward programs Nutrition International would otherwise have supported | F110: UoV | G110: calc | H110: - | I110: =I109*$H61 -> 839.9995 | J110: =J109*$H61 -> 525.38785 | K110: =K109*$H61 -> 843.55655 | L110: =L109*$H61 -> 843.55655 | M110: =M109*$H61 -> 496.43512 | N110: =N109*$H61 -> 843.55655 | O110: =O109*$H61 -> 656.99942 | P110: =P109*$H61 -> 1102.909 | ... AJ110: =AJ109*$H61 -> 0
E111: Value lost by shifting Nutrition International's spending away from the grantee program | F111: UoV | G111: calc | H111: - | I111: 0 | J111: 0 | K111: 0 | L111: 0 | M111: 0 | N111: 0 | O111: 0 | P111: 0 | Q111: 0 | R111: 0 | S111: 0 | T111: 0 | U111: 0 | V111: 0 | W111: 0 | X111: 0 | Y111: 0 | Z111: 0 | AA111: 0 | AB111: 0 | AC111: 0 | AD111: 0 | AE111: 0 | AF111: 0 | AG111: 0 | AH111: 0 | AI111: 0 | AJ111: 0
E112: Net value generated by shifting Nutrition International's spending away from the grantee program | F112: UoV | G112: calc | H112: - | I112: =I110-I111 -> 839.9995 | J112: =J110-J111 -> 525.38785 | K112: =K110-K111 -> 843.55655 | L112: =L110-L111 -> 843.55655 | M112: =M110-M111 -> 496.43512 | N112: =N110-N111 -> 843.55655 | O112: =O110-O111 -> 656.99942 | P112: =P110-P111 -> 1102.909 | ... AJ112: =AJ110-AJ111 -> 0
D113: Hypothetical impact of shifting other philanthropic actors' spending
E114: Amount of spending other philanthropic actors would saway from the grantee program | F114: $ | G114: calc | H114: - | I114: =I23 -> 131161.79 | J114: =J23 -> 0 | K114: =K23 -> 283953.27 | L114: =L23 -> 283953.27 | M114: =M23 -> 178323.04 | N114: =N23 -> 283953.27 | O114: =O23 -> 0 | P114: =P23 -> 423039.28 | ... AJ114: =AJ23 -> 0
E115: Value generated by shifting spending toward programs the other philanthropic actors would otherwise have funded | F115: UoV | G115: calc | H115: - | I115: =I114*I51 -> 13935.589 | J115: =J114*J51 -> 0 | K115: =K114*K51 -> 13055.701 | L115: =L114*L51 -> 20236.359 | M115: =M114*M51 -> 10732.723 | N115: =N114*N51 -> 7002.7022 | O115: =O114*O51 -> 0 | P115: =P114*P51 -> 71277.028 | ... AJ115: =AJ114*AJ51 -> 0
E116: Value lost by shifting other philanthropic actors' spending away from the grantee program | F116: UoV | G116: calc | H116: - | I116: 0 | J116: 0 | K116: 0 | L116: 0 | M116: 0 | N116: 0 | O116: 0 | P116: 0 | Q116: 0 | R116: 0 | S116: 0 | T116: 0 | U116: 0 | V116: 0 | W116: 0 | X116: 0 | Y116: 0 | Z116: 0 | AA116: 0 | AB116: 0 | AC116: 0 | AD116: 0 | AE116: 0 | AF116: 0 | AG116: 0 | AH116: 0 | AI116: 0 | AJ116: 0
E117: Net value generated by shifting other philanthropic actors' spending away from the grantee program | F117: UoV | G117: calc | H117: - | I117: =I115-I116 -> 13935.589 | J117: =J115-J116 -> 0 | K117: =K115-K116 -> 13055.701 | L117: =L115-L116 -> 20236.359 | M117: =M115-M116 -> 10732.723 | N117: =N115-N116 -> 7002.7022 | O117: =O115-O116 -> 0 | P117: =P115-P116 -> 71277.028 | ... AJ117: =AJ115-AJ116 -> 0
...

Sheet Inputs
I1: Helen Keller International | Q1: Helen Keller International | Y1: Helen Keller International | AG1: Nutrition International
I2: Burkina Faso | J2: Cameroon | K2: Côte d'Ivoire | L2: DRC | M2: Guinea | N2: Kenya | O2: Madagascar | P2: Mali | Q2: Niger | R2: Nigeria | S2: Nigeria | T2: Nigeria | U2: Nigeria | V2: Nigeria | W2: Nigeria | X2: Nigeria | Y2: Nigeria | Z2: Nigeria | AA2: Nigeria | AB2: Nigeria | AC2: Nigeria | AD2: Nigeria | AE2: Nigeria | AF2: Nigeria | AG2: Angola | AH2: Chad | AI2: Togo | AJ2: Uganda
A3: Inputs | F3: unit | G3: type | H3: Overall | R3: Adamawa | S3: Akwa Ibom | T3: Anambra | U3: Benue | V3: Delta | W3: Ebonyi | X3: Edo | Y3: Ekiti | Z3: Imo | AA3: Kogi | AB3: Nasarawa | AC3: Ogun | AD3: Osun | AE3: Rivers | AF3: Taraba | AL3: Source | AM3: GW analysis and discussion
E4: Final cost-effectiveness estimate (pulled from "Main calcs" sheet for visibility) | F4: ='Main CEA'!F149 -> xbenchmark | G4: main | H4: ='Main CEA'!H149 -> - | I4: ='Main CEA'!I149 -> 22.604158 | J4: ='Main CEA'!J149 -> 15.907951 | K4: ='Main CEA'!K149 -> 8.5391703 | L4: ='Main CEA'!L149 -> 16.914533 | M4: ='Main CEA'!M149 -> 10.932207 | N4: ='Main CEA'!N149 -> 4.7974496 | O4: ='Main CEA'!O149 -> 15.912911 | ... AJ4: ='Main CEA'!AJ149 -> 6.3105992
A5: Costs
C7: GiveWell costs
E8: Grant size | F8: $ | G8: input | H8: 1000000 | I8: - | J8: - | K8: - | L8: - | M8: - | N8: - | O8: - | P8: - | Q8: - | R8: - | S8: - | T8: - | U8: - | V8: - | W8: - | X8: - | Y8: - | Z8: - | AA8: - | AB8: - | AC8: - | AD8: - | AE8: - | AF8: - | AG8: - | AH8: - | AI8: - | AJ8: - | AL8: Arbitrary value
C10: Cost breakdown
E11: Percentage of total costs covered by the grantee | F11: % | G11: input | H11: - | I11: 0.4310638 | J11: 0.6403403 | K11: 0.4659904 | L11: 0.4659904 | M11: 0.5527665 | N11: 0.4659904 | O11: 0.5983099 | P11: 0.4324667 | Q11: 0.3616872 | R11: 0.4659904 | S11: 0.4659904 | T11: 0.4659904 | U11: 0.4659904 | V11: 0.4659904 | W11: 0.4659904 | X11: 0.4659904 | Y11: 0.4659904 | Z11: 0.4659904 | AA11: 0.4659904 | AB11: 0.4659904 | AC11: 0.4659904 | AD11: 0.4659904 | AE11: 0.4659904 | AF11: 0.4659904 | AG11: 0.7 | AH11: 0.7 | AI11: 0.7 | AJ11: 0.7 | AL11: GW analysis | AM11: GiveWell's analysis of Helen Keller International's cost per supplement
E12: Percentage of total costs covered by Nutrition International (vitamin A capsule procurement) | F12: % | G12: input | H12: - | I12: 0.0642112 | J12: 0.0596597 | K12: 0.0697078 | L12: 0.0697078 | M12: 0.0486625 | N12: 0.0697078 | O12: 0.0697078 | P12: 0.0845829 | Q12: 0.078881 | R12: 0.0697078 | S12: 0.0697078 | T12: 0.0697078 | U12: 0.0697078 | V12: 0.0697078 | W12: 0.0697078 | X12: 0.0697078 | Y12: 0.0697078 | Z12: 0.0697078 | AA12: 0.0697078 | AB12: 0.0697078 | AC12: 0.0697078 | AD12: 0.0697078 | AE12: 0.0697078 | AF12: 0.0697078 | AG12: 0 | AH12: 0 | AI12: 0 | AJ12: 0 | AL12: GW analysis | AM12: GiveWell's analysis of Helen Keller International's cost per supplement
E13: Percentage of total costs covered by other philanthropic actors | F13: % | G13: input | H13: - | I13: 0.0565391 | J13: 0 | K13: 0.1323195 | L13: 0.1323195 | M13: 0.098571 | N13: 0.1323195 | O13: 0 | P13: 0.1829504 | Q13: 0.2594317 | R13: 0.1323195 | S13: 0.1323195 | T13: 0.1323195 | U13: 0.1323195 | V13: 0.1323195 | W13: 0.1323195 | X13: 0.1323195 | Y13: 0.1323195 | Z13: 0.1323195 | AA13: 0.1323195 | AB13: 0.1323195 | AC13: 0.1323195 | AD13: 0.1323195 | AE13: 0.1323195 | AF13: 0.1323195 | AG13: 0 | AH13: 0 | AI13: 0 | AJ13: 0 | AL13: GW analysis | AM13: GiveWell's analysis of Helen Keller International's cost per supplement
E14: Percentage of total costs covered by domestic governments (financial contributions) | F14: % | G14: input | H14: - | I14: 0.1481859 | J14: 0 | K14: 0.0319823 | L14: 0.0319823 | M14: 0 | N14: 0.0319823 | O14: 0.0319823 | P14: 0 | Q14: 0 | R14: 0.0319823 | S14: 0.0319823 | T14: 0.0319823 | U14: 0.0319823 | V14: 0.0319823 | W14: 0.0319823 | X14: 0.0319823 | Y14: 0.0319823 | Z14: 0.0319823 | AA14: 0.0319823 | AB14: 0.0319823 | AC14: 0.0319823 | AD14: 0.0319823 | AE14: 0.0319823 | AF14: 0.0319823 | AG14: 0 | AH14: 0 | AI14: 0 | AJ14: 0 | AL14: GW analysis | AM14: GiveWell's analysis of Helen Keller International's cost per supplement
E15: Percentage of total costs covered by domestic governments (in-kind contributions) | F15: % | G15: input | H15: - | I15: 0.3 | J15: 0.3 | K15: 0.3 | L15: 0.3 | M15: 0.3 | N15: 0.3 | O15: 0.3 | P15: 0.3 | Q15: 0.3 | R15: 0.3 | S15: 0.3 | T15: 0.3 | U15: 0.3 | V15: 0.3 | W15: 0.3 | X15: 0.3 | Y15: 0.3 | Z15: 0.3 | AA15: 0.3 | AB15: 0.3 | AC15: 0.3 | AD15: 0.3 | AE15: 0.3 | AF15: 0.3 | AG15: 0.3 | AH15: 0.3 | AI15: 0.3 | AJ15: 0.3 | AL15: GW analysis | AM15: GiveWell's analysis of Helen Keller International's cost per supplement
C17: Cost per child covered
E18: Cost per vitamin A supplement delivered | F18: $ | G18: input | H18: - | I18: 1.05602 | J18: 1.13658 | K18: 1.01732 | L18: 1.01732 | M18: 1.39344 | N18: 1.01732 | O18: 1.01732 | P18: 0.80168 | Q18: 0.85963 | R18: 1.01732 | S18: 1.01732 | T18: 1.01732 | U18: 1.01732 | V18: 1.01732 | W18: 1.01732 | X18: 1.01732 | Y18: 1.01732 | Z18: 1.01732 | AA18: 1.01732 | AB18: 1.01732 | AC18: 1.01732 | AD18: 1.01732 | AE18: 1.01732 | AF18: 1.01732 | AG18: =AJ18*1.5 -> 1.52598 | AH18: =AJ18*1.5 -> 1.52598 | AI18: 1.0895 | AJ18: 1.01732 | AL18: GW analysis | AM18: GiveWell's analysis of Helen Keller International's cost per supplement
E19: Supplementation rounds delivered per year | F19: # | G19: input | H19: 2 | I19: - | J19: - | K19: - | L19: - | M19: - | N19: - | O19: - | P19: - | Q19: - | R19: - | S19: - | T19: - | U19: - | V19: - | W19: - | X19: - | Y19: - | Z19: - | AA19: - | AB19: - | AC19: - | AD19: - | AE19: - | AF19: - | AG19: - | AH19: - | AI19: - | AJ19: - | AL19: Helen Keller International
A21: Counterfactual mortality
C23: Mortalities per year among people under five
E24: Total mortalities per year among people under age 5 | F24: # | G24: input | H24: - | I24: =IFERROR(__xludf.DUMMYFUNCTION("FILTER('GBD estimates'!$I$4:$I$1203,'GBD estimates'!$C$4:$C$1203=I$2,'GBD estimates'!$F$4:$F$1203=""All causes"",'GBD estimates'!$E$4:$E$1203=""<5 years"")"),98779.14033) -> 98779.14 | J24: =IFERROR(__xludf.DUMMYFUNCTION("FILTER('GBD estimates'!$I$4:$I$1203,'GBD estimates'!$C$4:$C$1203=J$2,'GBD estimates'!$F$4:$F$1203=""All causes"",'GBD estimates'!$E$4:$E$1203=""<5 years"")"),64035.00739) -> 64035.007 | K24: =IFERROR(__xludf.DUMMYFUNCTION("FILTER('GBD estimates'!$I$4:$I$1203,'GBD estimates'!$C$4:$C$1203=K$2,'GBD estimates'!$F$4:$F$1203=""All causes"",'GBD estimates'!$E$4:$E$1203=""<5 years"")"),64816.60409) -> 64816.604 | L24: =IFERROR(__xludf.DUMMYFUNCTION("FILTER('GBD estimates'!$I$4:$I$1203,'GBD estimates'!$C$4:$C$1203=L$2,'GBD estimates'!$F$4:$F$1203=""All causes"",'GBD estimates'!$E$4:$E$1203=""<5 years"")"),168468.4512) -> 168468.45 | M24: =IFERROR(__xludf.DUMMYFUNCTION("FILTER('GBD estimates'!$I$4:$I$1203,'GBD estimates'!$C$4:$C$1203=M$2,'GBD estimates'!$F$4:$F$1203=""All causes"",'GBD estimates'!$E$4:$E$1203=""<5 years"")"),45406.17471) -> 45406.175 | N24: =IFERROR(__xludf.DUMMYFUNCTION("FILTER('GBD estimates'!$I$4:$I$1203,'GBD estimates'!$C$4:$C$1203=N$2,'GBD estimates'!$F$4:$F$1203=""All causes"",'GBD estimates'!$E$4:$E$1203=""<5 years"")"),53344.7099) -> 53344.71 | O24: =IFERROR(__xludf.DUMMYFUNCTION("FILTER('GBD estimates'!$I$4:$I$1203,'GBD estimates'!$C$4:$C$1203=O$2,'GBD estimates'!$F$4:$F$1203=""All causes"",'GBD estimates'!$E$4:$E$1203=""<5 years"")"),48156.10418) -> 48156.104 | P24: =IFERROR(__xludf.DUMMYFUNCTION("FILTER('GBD estimates'!$I$4:$I$1203,'GBD estimates'!$C$4:$C$1203=P$2,'GBD estimates'!$F$4:$F$1203=""All causes"",'GBD estimates'!$E$4:$E$1203=""<5 years"")"),109642.6225) -> 109642.62 | Q24: =IFERROR(__xludf.DUMMYFUNCTION("FILTER('GBD estimates'!$I$4:$I$1203,'GBD estimates'!$C$4:$C$1203=Q$2,'GBD estimates'!$F$4:$F$1203=""All causes"",'GBD estimates'!$E$4:$E$1203=""<5 years"")"),120216.7235) -> 120216.72 | R24: =IFERROR(__xludf.DUMMYFUNCTION("FILTER('GBD estimates'!$AF$4:$AF$1203,'GBD estimates'!$AA$4:$AA$1203=R$3,'GBD estimates'!$X$4:$X$1203=""All causes"",'GBD estimates'!$Z$4:$Z$1203=""Under 5"")"),13907.73873) -> 13907.739 | S24: =IFERROR(__xludf.DUMMYFUNCTION("FILTER('GBD estimates'!$AF$4:$AF$1203,'GBD estimates'!$AA$4:$AA$1203=S$3,'GBD estimates'!$X$4:$X$1203=""All causes"",'GBD estimates'!$Z$4:$Z$1203=""Under 5"")"),3462.225164) -> 3462.2252 | T24: =IFERROR(__xludf.DUMMYFUNCTION("FILTER('GBD estimates'!$AF$4:$AF$1203,'GBD estimates'!$AA$4:$AA$1203=T$3,'GBD estimates'!$X$4:$X$1203=""All causes"",'GBD estimates'!$Z$4:$Z$1203=""Under 5"")"),7871.751135) -> 7871.7511 | U24: =IFERROR(__xludf.DUMMYFUNCTION("FILTER('GBD estimates'!$AF$4:$AF$1203,'GBD estimates'!$AA$4:$AA$1203=U$3,'GBD estimates'!$X$4:$X$1203=""All causes"",'GBD estimates'!$Z$4:$Z$1203=""Under 5"")"),26884.78566) -> 26884.786 | V24: =IFERROR(__xludf.DUMMYFUNCTION("FILTER('GBD estimates'!$AF$4:$AF$1203,'GBD estimates'!$AA$4:$AA$1203=V$3,'GBD estimates'!$X$4:$X$1203=""All causes"",'GBD estimates'!$Z$4:$Z$1203=""Under 5"")"),7861.21423) -> 7861.2142 | W24: =IFERROR(__xludf.DUMMYFUNCTION("FILTER('GBD estimates'!$AF$4:$AF$1203,'GBD estimates'!$AA$4:$AA$1203=W$3,'GBD estimates'!$X$4:$X$1203=""All causes"",'GBD estimates'!$Z$4:$Z$1203=""Under 5"")"),7938.591477) -> 7938.5915 | X24: =IFERROR(__xludf.DUMMYFUNCTION("FILTER('GBD estimates'!$AF$4:$AF$1203,'GBD estimates'!$AA$4:$AA$1203=X$3,'GBD estimates'!$X$4:$X$1203=""All causes"",'GBD estimates'!$Z$4:$Z$1203=""Under 5"")"),5408.39386) -> 5408.3939 | Y24: =IFERROR(__xludf.DUMMYFUNCTION("FILTER('GBD estimates'!$AF$4:$AF$1203,'GBD estimates'!$AA$4:$AA$1203=Y$3,'GBD estimates'!$X$4:$X$1203=""All causes"",'GBD estimates'!$Z$4:$Z$1203=""Under 5"")"),2631.649859) -> 2631.6499 | Z24: =IFERROR(__xludf.DUMMYFUNCTION("FILTER('GBD estimates'!$AF$4:$AF$1203,'GBD estimates'!$AA$4:$AA$1203=Z$3,'GBD estimates'!$X$4:$X$1203=""All causes"",'GBD estimates'!$Z$4:$Z$1203=""Under 5"")"),11380.79524) -> 11380.795 | AA24: =IFERROR(__xludf.DUMMYFUNCTION("FILTER('GBD estimates'!$AF$4:$AF$1203,'GBD estimates'!$AA$4:$AA$1203=AA$3,'GBD estimates'!$X$4:$X$1203=""All causes"",'GBD estimates'!$Z$4:$Z$1203=""Under 5"")"),3662.544731) -> 3662.5447 | AB24: =IFERROR(__xludf.DUMMYFUNCTION("FILTER('GBD estimates'!$AF$4:$AF$1203,'GBD estimates'!$AA$4:$AA$1203=AB$3,'GBD estimates'!$X$4:$X$1203=""All causes"",'GBD estimates'!$Z$4:$Z$1203=""Under 5"")"),13333.45365) -> 13333.454 | AC24: =IFERROR(__xludf.DUMMYFUNCTION("FILTER('GBD estimates'!$AF$4:$AF$1203,'GBD estimates'!$AA$4:$AA$1203=AC$3,'GBD estimates'!$X$4:$X$1203=""All causes"",'GBD estimates'!$Z$4:$Z$1203=""Under 5"")"),20448.01213) -> 20448.012 | AD24: =IFERROR(__xludf.DUMMYFUNCTION("FILTER('GBD estimates'!$AF$4:$AF$1203,'GBD estimates'!$AA$4:$AA$1203=AD$3,'GBD estimates'!$X$4:$X$1203=""All causes"",'GBD estimates'!$Z$4:$Z$1203=""Under 5"")"),4522.234854) -> 4522.2349 | AE24: =IFERROR(__xludf.DUMMYFUNCTION("FILTER('GBD estimates'!$AF$4:$AF$1203,'GBD estimates'!$AA$4:$AA$1203=AE$3,'GBD estimates'!$X$4:$X$1203=""All causes"",'GBD estimates'!$Z$4:$Z$1203=""Under 5"")"),6707.239581) -> 6707.2396 | AF24: =IFERROR(__xludf.DUMMYFUNCTION("FILTER('GBD estimates'!$AF$4:$AF$1203,'GBD estimates'!$AA$4:$AA$1203=AF$3,'GBD estimates'!$X$4:$X$1203=""All causes"",'GBD estimates'!$Z$4:$Z$1203=""Under 5"")"),34193.94716) -> 34193.947 | AG24: =IFERROR(__xludf.DUMMYFUNCTION("FILTER('GBD estimates'!$I$4:$I$1203,'GBD estimates'!$C$4:$C$1203=AG$2,'GBD estimates'!$F$4:$F$1203=""All causes"",'GBD estimates'!$E$4:$E$1203=""<5 years"")"),58764.73414) -> 58764.734 | AH24: =IFERROR(__xludf.DUMMYFUNCTION("FILTER('GBD estimates'!$I$4:$I$1203,'GBD estimates'!$C$4:$C$1203=AH$2,'GBD estimates'!$F$4:$F$1203=""All causes"",'GBD estimates'!$E$4:$E$1203=""<5 years"")"),85575.12265) -> 85575.123 | AI24: =IFERROR(__xludf.DUMMYFUNCTION("FILTER('GBD estimates'!$I$4:$I$1203,'GBD estimates'!$C$4:$C$1203=AI$2,'GBD estimates'!$F$4:$F$1203=""All causes"",'GBD estimates'!$E$4:$E$1203=""<5 years"")"),15010.42875) -> 15010.429 | AJ24: =IFERROR(__xludf.DUMMYFUNCTION("FILTER('GBD estimates'!$I$4:$I$1203,'GBD estimates'!$C$4:$C$1203=AJ$2,'GBD estimates'!$F$4:$F$1203=""All causes"",'GBD estimates'!$E$4:$E$1203=""<5 years"")"),91702.41553) -> 91702.416 | AL24: GBD 2019
E25: Total early neonatal mortalities per year (babies under 7 days old) | F25: # | G25: input | H25: - | I25: =IFERROR(__xludf.DUMMYFUNCTION("FILTER('GBD estimates'!$I$4:$I$1203,'GBD estimates'!$C$4:$C$1203=I$2,'GBD estimates'!$F$4:$F$1203=""All causes"",'GBD estimates'!$E$4:$E$1203=""0-6 days"")"),19940.74855) -> 19940.749 | J25: =IFERROR(__xludf.DUMMYFUNCTION("FILTER('GBD estimates'!$I$4:$I$1203,'GBD estimates'!$C$4:$C$1203=J$2,'GBD estimates'!$F$4:$F$1203=""All causes"",'GBD estimates'!$E$4:$E$1203=""0-6 days"")"),17016.72353) -> 17016.724 | K25: =IFERROR(__xludf.DUMMYFUNCTION("FILTER('GBD estimates'!$I$4:$I$1203,'GBD estimates'!$C$4:$C$1203=K$2,'GBD estimates'!$F$4:$F$1203=""All causes"",'GBD estimates'!$E$4:$E$1203=""0-6 days"")"),25085.60233) -> 25085.602 | L25: =IFERROR(__xludf.DUMMYFUNCTION("FILTER('GBD estimates'!$I$4:$I$1203,'GBD estimates'!$C$4:$C$1203=L$2,'GBD estimates'!$F$4:$F$1203=""All causes"",'GBD estimates'!$E$4:$E$1203=""0-6 days"")"),53762.70372) -> 53762.704 | M25: =IFERROR(__xludf.DUMMYFUNCTION("FILTER('GBD estimates'!$I$4:$I$1203,'GBD estimates'!$C$4:$C$1203=M$2,'GBD estimates'!$F$4:$F$1203=""All causes"",'GBD estimates'!$E$4:$E$1203=""0-6 days"")"),11002.66188) -> 11002.662 | N25: =IFERROR(__xludf.DUMMYFUNCTION("FILTER('GBD estimates'!$I$4:$I$1203,'GBD estimates'!$C$4:$C$1203=N$2,'GBD estimates'!$F$4:$F$1203=""All causes"",'GBD estimates'!$E$4:$E$1203=""0-6 days"")"),20427.11313) -> 20427.113 | O25: =IFERROR(__xludf.DUMMYFUNCTION("FILTER('GBD estimates'!$I$4:$I$1203,'GBD estimates'!$C$4:$C$1203=O$2,'GBD estimates'!$F$4:$F$1203=""All causes"",'GBD estimates'!$E$4:$E$1203=""0-6 days"")"),15934.39256) -> 15934.393 | P25: =IFERROR(__xludf.DUMMYFUNCTION("FILTER('GBD estimates'!$I$4:$I$1203,'GBD estimates'!$C$4:$C$1203=P$2,'GBD estimates'!$F$4:$F$1203=""All causes"",'GBD estimates'!$E$4:$E$1203=""0-6 days"")"),31228.72021) -> 31228.72 | Q25: =IFERROR(__xludf.DUMMYFUNCTION("FILTER('GBD estimates'!$I$4:$I$1203,'GBD estimates'!$C$4:$C$1203=Q$2,'GBD estimates'!$F$4:$F$1203=""All causes"",'GBD estimates'!$E$4:$E$1203=""0-6 days"")"),22912.70936) -> 22912.709 | R25: =IFERROR(__xludf.DUMMYFUNCTION("FILTER('GBD estimates'!$AF$4:$AF$1203,'GBD estimates'!$AA$4:$AA$1203=R$3,'GBD estimates'!$X$4:$X$1203=""All causes"",'GBD estimates'!$Z$4:$Z$1203=""0 to 6 days (early neonatal)"")"),3823.608947) -> 3823.6089 | S25: =IFERROR(__xludf.DUMMYFUNCTION("FILTER('GBD estimates'!$AF$4:$AF$1203,'GBD estimates'!$AA$4:$AA$1203=S$3,'GBD estimates'!$X$4:$X$1203=""All causes"",'GBD estimates'!$Z$4:$Z$1203=""0 to 6 days (early neonatal)"")"),1329.358602) -> 1329.3586 | T25: =IFERROR(__xludf.DUMMYFUNCTION("FILTER('GBD estimates'!$AF$4:$AF$1203,'GBD estimates'!$AA$4:$AA$1203=T$3,'GBD estimates'!$X$4:$X$1203=""All causes"",'GBD estimates'!$Z$4:$Z$1203=""0 to 6 days (early neonatal)"")"),3453.101975) -> 3453.102 | U25: =IFERROR(__xludf.DUMMYFUNCTION("FILTER('GBD estimates'!$AF$4:$AF$1203,'GBD estimates'!$AA$4:$AA$1203=U$3,'GBD estimates'!$X$4:$X$1203=""All causes"",'GBD estimates'!$Z$4:$Z$1203=""0 to 6 days (early neonatal)"")"),9008.117154) -> 9008.1172 | V25: =IFERROR(__xludf.DUMMYFUNCTION("FILTER('GBD estimates'!$AF$4:$AF$1203,'GBD estimates'!$AA$4:$AA$1203=V$3,'GBD estimates'!$X$4:$X$1203=""All causes"",'GBD estimates'!$Z$4:$Z$1203=""0 to 6 days (early neonatal)"")"),2787.57299) -> 2787.573 | W25: =IFERROR(__xludf.DUMMYFUNCTION("FILTER('GBD estimates'!$AF$4:$AF$1203,'GBD estimates'!$AA$4:$AA$1203=W$3,'GBD estimates'!$X$4:$X$1203=""All causes"",'GBD estimates'!$Z$4:$Z$1203=""0 to 6 days (early neonatal)"")"),2640.671913) -> 2640.6719 | X25: =IFERROR(__xludf.DUMMYFUNCTION("FILTER('GBD estimates'!$AF$4:$AF$1203,'GBD estimates'!$AA$4:$AA$1203=X$3,'GBD estimates'!$X$4:$X$1203=""All causes"",'GBD estimates'!$Z$4:$Z$1203=""0 to 6 days (early neonatal)"")"),2146.970943) -> 2146.9709 | Y25: =IFERROR(__xludf.DUMMYFUNCTION("FILTER('GBD estimates'!$AF$4:$AF$1203,'GBD estimates'!$AA$4:$AA$1203=Y$3,'GBD estimates'!$X$4:$X$1203=""All causes"",'GBD estimates'!$Z$4:$Z$1203=""0 to 6 days (early neonatal)"")"),973.8088071) -> 973.80881 | Z25: =IFERROR(__xludf.DUMMYFUNCTION("FILTER('GBD estimates'!$AF$4:$AF$1203,'GBD estimates'!$AA$4:$AA$1203=Z$3,'GBD estimates'!$X$4:$X$1203=""All causes"",'GBD estimates'!$Z$4:$Z$1203=""0 to 6 days (early neonatal)"")"),5034.873061) -> 5034.8731 | AA25: =IFERROR(__xludf.DUMMYFUNCTION("FILTER('GBD estimates'!$AF$4:$AF$1203,'GBD estimates'!$AA$4:$AA$1203=AA$3,'GBD estimates'!$X$4:$X$1203=""All causes"",'GBD estimates'!$Z$4:$Z$1203=""0 to 6 days (early neonatal)"")"),1489.287) -> 1489.287 | AB25: =IFERROR(__xludf.DUMMYFUNCTION("FILTER('GBD estimates'!$AF$4:$AF$1203,'GBD estimates'!$AA$4:$AA$1203=AB$3,'GBD estimates'!$X$4:$X$1203=""All causes"",'GBD estimates'!$Z$4:$Z$1203=""0 to 6 days (early neonatal)"")"),4455.531084) -> 4455.5311 | AC25: =IFERROR(__xludf.DUMMYFUNCTION("FILTER('GBD estimates'!$AF$4:$AF$1203,'GBD estimates'!$AA$4:$AA$1203=AC$3,'GBD estimates'!$X$4:$X$1203=""All causes"",'GBD estimates'!$Z$4:$Z$1203=""0 to 6 days (early neonatal)"")"),8159.989527) -> 8159.9895 | AD25: =IFERROR(__xludf.DUMMYFUNCTION("FILTER('GBD estimates'!$AF$4:$AF$1203,'GBD estimates'!$AA$4:$AA$1203=AD$3,'GBD estimates'!$X$4:$X$1203=""All causes"",'GBD estimates'!$Z$4:$Z$1203=""0 to 6 days (early neonatal)"")"),2060.925307) -> 2060.9253 | AE25: =IFERROR(__xludf.DUMMYFUNCTION("FILTER('GBD estimates'!$AF$4:$AF$1203,'GBD estimates'!$AA$4:$AA$1203=AE$3,'GBD estimates'!$X$4:$X$1203=""All causes"",'GBD estimates'!$Z$4:$Z$1203=""0 to 6 days (early neonatal)"")"),2301.501831) -> 2301.5018 | AF25: =IFERROR(__xludf.DUMMYFUNCTION("FILTER('GBD estimates'!$AF$4:$AF$1203,'GBD estimates'!$AA$4:$AA$1203=AF$3,'GBD estimates'!$X$4:$X$1203=""All causes"",'GBD estimates'!$Z$4:$Z$1203=""0 to 6 days (early neonatal)"")"),9372.784678) -> 9372.7847 | AG25: =IFERROR(__xludf.DUMMYFUNCTION("FILTER('GBD estimates'!$I$4:$I$1203,'GBD estimates'!$C$4:$C$1203=AG$2,'GBD estimates'!$F$4:$F$1203=""All causes"",'GBD estimates'!$E$4:$E$1203=""0-6 days"")"),20694.58644) -> 20694.586 | AH25: =IFERROR(__xludf.DUMMYFUNCTION("FILTER('GBD estimates'!$I$4:$I$1203,'GBD estimates'!$C$4:$C$1203=AH$2,'GBD estimates'!$F$4:$F$1203=""All causes"",'GBD estimates'!$E$4:$E$1203=""0-6 days"")"),19471.00076) -> 19471.001 | AI25: =IFERROR(__xludf.DUMMYFUNCTION("FILTER('GBD estimates'!$I$4:$I$1203,'GBD estimates'!$C$4:$C$1203=AI$2,'GBD estimates'!$F$4:$F$1203=""All causes"",'GBD estimates'!$E$4:$E$1203=""0-6 days"")"),5107.64038) -> 5107.6404 | AJ25: =IFERROR(__xludf.DUMMYFUNCTION("FILTER('GBD estimates'!$I$4:$I$1203,'GBD estimates'!$C$4:$C$1203=AJ$2,'GBD estimates'!$F$4:$F$1203=""All causes"",'GBD estimates'!$E$4:$E$1203=""0-6 days"")"),33674.56533) -> 33674.565 | AL25: GBD 2019
E26: Total late neonatal mortalities per year (babies between 7 and 27 days old) | F26: # | G26: input | H26: - | I26: =IFERROR(__xludf.DUMMYFUNCTION("FILTER('GBD estimates'!$I$4:$I$1203,'GBD estimates'!$C$4:$C$1203=I$2,'GBD estimates'!$F$4:$F$1203=""All causes"",'GBD estimates'!$E$4:$E$1203=""7-27 days"")"),6949.467251) -> 6949.4673 | J26: =IFERROR(__xludf.DUMMYFUNCTION("FILTER('GBD estimates'!$I$4:$I$1203,'GBD estimates'!$C$4:$C$1203=J$2,'GBD estimates'!$F$4:$F$1203=""All causes"",'GBD estimates'!$E$4:$E$1203=""7-27 days"")"),4718.894707) -> 4718.8947 | K26: =IFERROR(__xludf.DUMMYFUNCTION("FILTER('GBD estimates'!$I$4:$I$1203,'GBD estimates'!$C$4:$C$1203=K$2,'GBD estimates'!$F$4:$F$1203=""All causes"",'GBD estimates'!$E$4:$E$1203=""7-27 days"")"),5328.858472) -> 5328.8585 | L26: =IFERROR(__xludf.DUMMYFUNCTION("FILTER('GBD estimates'!$I$4:$I$1203,'GBD estimates'!$C$4:$C$1203=L$2,'GBD estimates'!$F$4:$F$1203=""All causes"",'GBD estimates'!$E$4:$E$1203=""7-27 days"")"),10893.45506) -> 10893.455 | M26: =IFERROR(__xludf.DUMMYFUNCTION("FILTER('GBD estimates'!$I$4:$I$1203,'GBD estimates'!$C$4:$C$1203=M$2,'GBD estimates'!$F$4:$F$1203=""All causes"",'GBD estimates'!$E$4:$E$1203=""7-27 days"")"),3633.856099) -> 3633.8561 | N26: =IFERROR(__xludf.DUMMYFUNCTION("FILTER('GBD estimates'!$I$4:$I$1203,'GBD estimates'!$C$4:$C$1203=N$2,'GBD estimates'!$F$4:$F$1203=""All causes"",'GBD estimates'!$E$4:$E$1203=""7-27 days"")"),5221.114399) -> 5221.1144 | O26: =IFERROR(__xludf.DUMMYFUNCTION("FILTER('GBD estimates'!$I$4:$I$1203,'GBD estimates'!$C$4:$C$1203=O$2,'GBD estimates'!$F$4:$F$1203=""All causes"",'GBD estimates'!$E$4:$E$1203=""7-27 days"")"),3885.4177) -> 3885.4177 | P26: =IFERROR(__xludf.DUMMYFUNCTION("FILTER('GBD estimates'!$I$4:$I$1203,'GBD estimates'!$C$4:$C$1203=P$2,'GBD estimates'!$F$4:$F$1203=""All causes"",'GBD estimates'!$E$4:$E$1203=""7-27 days"")"),6808.063876) -> 6808.0639 | Q26: =IFERROR(__xludf.DUMMYFUNCTION("FILTER('GBD estimates'!$I$4:$I$1203,'GBD estimates'!$C$4:$C$1203=Q$2,'GBD estimates'!$F$4:$F$1203=""All causes"",'GBD estimates'!$E$4:$E$1203=""7-27 days"")"),7653.323267) -> 7653.3233 | R26: =IFERROR(__xludf.DUMMYFUNCTION("FILTER('GBD estimates'!$AF$4:$AF$1203,'GBD estimates'!$AA$4:$AA$1203=R$3,'GBD estimates'!$X$4:$X$1203=""All causes"",'GBD estimates'!$Z$4:$Z$1203=""7 to 27 days (late neonatal)"")"),961.7471079) -> 961.74711 | S26: =IFERROR(__xludf.DUMMYFUNCTION("FILTER('GBD estimates'!$AF$4:$AF$1203,'GBD estimates'!$AA$4:$AA$1203=S$3,'GBD estimates'!$X$4:$X$1203=""All causes"",'GBD estimates'!$Z$4:$Z$1203=""7 to 27 days (late neonatal)"")"),229.1202135) -> 229.12021 | T26: =IFERROR(__xludf.DUMMYFUNCTION("FILTER('GBD estimates'!$AF$4:$AF$1203,'GBD estimates'!$AA$4:$AA$1203=T$3,'GBD estimates'!$X$4:$X$1203=""All causes"",'GBD estimates'!$Z$4:$Z$1203=""7 to 27 days (late neonatal)"")"),566.9277211) -> 566.92772 | U26: =IFERROR(__xludf.DUMMYFUNCTION("FILTER('GBD estimates'!$AF$4:$AF$1203,'GBD estimates'!$AA$4:$AA$1203=U$3,'GBD estimates'!$X$4:$X$1203=""All causes"",'GBD estimates'!$Z$4:$Z$1203=""7 to 27 days (late neonatal)"")"),1900.406123) -> 1900.4061 | V26: =IFERROR(__xludf.DUMMYFUNCTION("FILTER('GBD estimates'!$AF$4:$AF$1203,'GBD estimates'!$AA$4:$AA$1203=V$3,'GBD estimates'!$X$4:$X$1203=""All causes"",'GBD estimates'!$Z$4:$Z$1203=""7 to 27 days (late neonatal)"")"),557.1714584) -> 557.17146 | W26: =IFERROR(__xludf.DUMMYFUNCTION("FILTER('GBD estimates'!$AF$4:$AF$1203,'GBD estimates'!$AA$4:$AA$1203=W$3,'GBD estimates'!$X$4:$X$1203=""All causes"",'GBD estimates'!$Z$4:$Z$1203=""7 to 27 days (late neonatal)"")"),574.2221148) -> 574.22211 | X26: =IFERROR(__xludf.DUMMYFUNCTION("FILTER('GBD estimates'!$AF$4:$AF$1203,'GBD estimates'!$AA$4:$AA$1203=X$3,'GBD estimates'!$X$4:$X$1203=""All causes"",'GBD estimates'!$Z$4:$Z$1203=""7 to 27 days (late neonatal)"")"),383.4652698) -> 383.46527 | Y26: =IFERROR(__xludf.DUMMYFUNCTION("FILTER('GBD estimates'!$AF$4:$AF$1203,'GBD estimates'!$AA$4:$AA$1203=Y$3,'GBD estimates'!$X$4:$X$1203=""All causes"",'GBD estimates'!$Z$4:$Z$1203=""7 to 27 days (late neonatal)"")"),185.3151303) -> 185.31513 | Z26: =IFERROR(__xludf.DUMMYFUNCTION("FILTER('GBD estimates'!$AF$4:$AF$1203,'GBD estimates'!$AA$4:$AA$1203=Z$3,'GBD estimates'!$X$4:$X$1203=""All causes"",'GBD estimates'!$Z$4:$Z$1203=""7 to 27 days (late neonatal)"")"),845.1846992) -> 845.1847 | AA26: =IFERROR(__xludf.DUMMYFUNCTION("FILTER('GBD estimates'!$AF$4:$AF$1203,'GBD estimates'!$AA$4:$AA$1203=AA$3,'GBD estimates'!$X$4:$X$1203=""All causes"",'GBD estimates'!$Z$4:$Z$1203=""7 to 27 days (late neonatal)"")"),256.7525313) -> 256.75253 | AB26: =IFERROR(__xludf.DUMMYFUNCTION("FILTER('GBD estimates'!$AF$4:$AF$1203,'GBD estimates'!$AA$4:$AA$1203=AB$3,'GBD estimates'!$X$4:$X$1203=""All causes"",'GBD estimates'!$Z$4:$Z$1203=""7 to 27 days (late neonatal)"")"),962.4266505) -> 962.42665 | AC26: =IFERROR(__xludf.DUMMYFUNCTION("FILTER('GBD estimates'!$AF$4:$AF$1203,'GBD estimates'!$AA$4:$AA$1203=AC$3,'GBD estimates'!$X$4:$X$1203=""All causes"",'GBD estimates'!$Z$4:$Z$1203=""7 to 27 days (late neonatal)"")"),1522.781504) -> 1522.7815 | AD26: =IFERROR(__xludf.DUMMYFUNCTION("FILTER('GBD estimates'!$AF$4:$AF$1203,'GBD estimates'!$AA$4:$AA$1203=AD$3,'GBD estimates'!$X$4:$X$1203=""All causes"",'GBD estimates'!$Z$4:$Z$1203=""7 to 27 days (late neonatal)"")"),328.0110029) -> 328.011 | AE26: =IFERROR(__xludf.DUMMYFUNCTION("FILTER('GBD estimates'!$AF$4:$AF$1203,'GBD estimates'!$AA$4:$AA$1203=AE$3,'GBD estimates'!$X$4:$X$1203=""All causes"",'GBD estimates'!$Z$4:$Z$1203=""7 to 27 days (late neonatal)"")"),460.3396178) -> 460.33962 | AF26: =IFERROR(__xludf.DUMMYFUNCTION("FILTER('GBD estimates'!$AF$4:$AF$1203,'GBD estimates'!$AA$4:$AA$1203=AF$3,'GBD estimates'!$X$4:$X$1203=""All causes"",'GBD estimates'!$Z$4:$Z$1203=""7 to 27 days (late neonatal)"")"),2484.410708) -> 2484.4107 | AG26: =IFERROR(__xludf.DUMMYFUNCTION("FILTER('GBD estimates'!$I$4:$I$1203,'GBD estimates'!$C$4:$C$1203=AG$2,'GBD estimates'!$F$4:$F$1203=""All causes"",'GBD estimates'!$E$4:$E$1203=""7-27 days"")"),3275.622234) -> 3275.6222 | AH26: =IFERROR(__xludf.DUMMYFUNCTION("FILTER('GBD estimates'!$I$4:$I$1203,'GBD estimates'!$C$4:$C$1203=AH$2,'GBD estimates'!$F$4:$F$1203=""All causes"",'GBD estimates'!$E$4:$E$1203=""7-27 days"")"),5935.057826) -> 5935.0578 | AI26: =IFERROR(__xludf.DUMMYFUNCTION("FILTER('GBD estimates'!$I$4:$I$1203,'GBD estimates'!$C$4:$C$1203=AI$2,'GBD estimates'!$F$4:$F$1203=""All causes"",'GBD estimates'!$E$4:$E$1203=""7-27 days"")"),819.2103542) -> 819.21035 | AJ26: =IFERROR(__xludf.DUMMYFUNCTION("FILTER('GBD estimates'!$I$4:$I$1203,'GBD estimates'!$C$4:$C$1203=AJ$2,'GBD estimates'!$F$4:$F$1203=""All causes"",'GBD estimates'!$E$4:$E$1203=""7-27 days"")"),7103.605519) -> 7103.6055 | AL26: GBD 2019
E27: Total post-neonatal mortalities per year (babies between 28 and 364 days old) | F27: # | G27: input | H27: - | I27: =IFERROR(__xludf.DUMMYFUNCTION("FILTER('GBD estimates'!$I$4:$I$1203,'GBD estimates'!$C$4:$C$1203=I$2,'GBD estimates'!$F$4:$F$1203=""All causes"",'GBD estimates'!$E$4:$E$1203=""28-364 days"")"),30592.14891) -> 30592.149 | J27: =IFERROR(__xludf.DUMMYFUNCTION("FILTER('GBD estimates'!$I$4:$I$1203,'GBD estimates'!$C$4:$C$1203=J$2,'GBD estimates'!$F$4:$F$1203=""All causes"",'GBD estimates'!$E$4:$E$1203=""28-364 days"")"),19245.01042) -> 19245.01 | K27: =IFERROR(__xludf.DUMMYFUNCTION("FILTER('GBD estimates'!$I$4:$I$1203,'GBD estimates'!$C$4:$C$1203=K$2,'GBD estimates'!$F$4:$F$1203=""All causes"",'GBD estimates'!$E$4:$E$1203=""28-364 days"")"),12225.34139) -> 12225.341 | L27: =IFERROR(__xludf.DUMMYFUNCTION("FILTER('GBD estimates'!$I$4:$I$1203,'GBD estimates'!$C$4:$C$1203=L$2,'GBD estimates'!$F$4:$F$1203=""All causes"",'GBD estimates'!$E$4:$E$1203=""28-364 days"")"),50492.30638) -> 50492.306 | M27: =IFERROR(__xludf.DUMMYFUNCTION("FILTER('GBD estimates'!$I$4:$I$1203,'GBD estimates'!$C$4:$C$1203=M$2,'GBD estimates'!$F$4:$F$1203=""All causes"",'GBD estimates'!$E$4:$E$1203=""28-364 days"")"),11984.04726) -> 11984.047 | N27: =IFERROR(__xludf.DUMMYFUNCTION("FILTER('GBD estimates'!$I$4:$I$1203,'GBD estimates'!$C$4:$C$1203=N$2,'GBD estimates'!$F$4:$F$1203=""All causes"",'GBD estimates'!$E$4:$E$1203=""28-364 days"")"),15329.81801) -> 15329.818 | O27: =IFERROR(__xludf.DUMMYFUNCTION("FILTER('GBD estimates'!$I$4:$I$1203,'GBD estimates'!$C$4:$C$1203=O$2,'GBD estimates'!$F$4:$F$1203=""All causes"",'GBD estimates'!$E$4:$E$1203=""28-364 days"")"),15450.8777) -> 15450.878 | P27: =IFERROR(__xludf.DUMMYFUNCTION("FILTER('GBD estimates'!$I$4:$I$1203,'GBD estimates'!$C$4:$C$1203=P$2,'GBD estimates'!$F$4:$F$1203=""All causes"",'GBD estimates'!$E$4:$E$1203=""28-364 days"")"),28412.93493) -> 28412.935 | Q27: =IFERROR(__xludf.DUMMYFUNCTION("FILTER('GBD estimates'!$I$4:$I$1203,'GBD estimates'!$C$4:$C$1203=Q$2,'GBD estimates'!$F$4:$F$1203=""All causes"",'GBD estimates'!$E$4:$E$1203=""28-364 days"")"),30362.1489) -> 30362.149 | R27: =IFERROR(__xludf.DUMMYFUNCTION("FILTER('GBD estimates'!$AF$4:$AF$1203,'GBD estimates'!$AA$4:$AA$1203=R$3,'GBD estimates'!$X$4:$X$1203=""All causes"",'GBD estimates'!$Z$4:$Z$1203=""28 to 364 days (post neonatal)"")"),3814.759117) -> 3814.7591 | S27: =IFERROR(__xludf.DUMMYFUNCTION("FILTER('GBD estimates'!$AF$4:$AF$1203,'GBD estimates'!$AA$4:$AA$1203=S$3,'GBD estimates'!$X$4:$X$1203=""All causes"",'GBD estimates'!$Z$4:$Z$1203=""28 to 364 days (post neonatal)"")"),899.2507422) -> 899.25074 | T27: =IFERROR(__xludf.DUMMYFUNCTION("FILTER('GBD estimates'!$AF$4:$AF$1203,'GBD estimates'!$AA$4:$AA$1203=T$3,'GBD estimates'!$X$4:$X$1203=""All causes"",'GBD estimates'!$Z$4:$Z$1203=""28 to 364 days (post neonatal)"")"),1977.83322) -> 1977.8332 | U27: =IFERROR(__xludf.DUMMYFUNCTION("FILTER('GBD estimates'!$AF$4:$AF$1203,'GBD estimates'!$AA$4:$AA$1203=U$3,'GBD estimates'!$X$4:$X$1203=""All causes"",'GBD estimates'!$Z$4:$Z$1203=""28 to 364 days (post neonatal)"")"),7596.611931) -> 7596.6119 | V27: =IFERROR(__xludf.DUMMYFUNCTION("FILTER('GBD estimates'!$AF$4:$AF$1203,'GBD estimates'!$AA$4:$AA$1203=V$3,'GBD estimates'!$X$4:$X$1203=""All causes"",'GBD estimates'!$Z$4:$Z$1203=""28 to 364 days (post neonatal)"")"),2133.298156) -> 2133.2982 | W27: =IFERROR(__xludf.DUMMYFUNCTION("FILTER('GBD estimates'!$AF$4:$AF$1203,'GBD estimates'!$AA$4:$AA$1203=W$3,'GBD estimates'!$X$4:$X$1203=""All causes"",'GBD estimates'!$Z$4:$Z$1203=""28 to 364 days (post neonatal)"")"),2185.101705) -> 2185.1017 | X27: =IFERROR(__xludf.DUMMYFUNCTION("FILTER('GBD estimates'!$AF$4:$AF$1203,'GBD estimates'!$AA$4:$AA$1203=X$3,'GBD estimates'!$X$4:$X$1203=""All causes"",'GBD estimates'!$Z$4:$Z$1203=""28 to 364 days (post neonatal)"")"),1406.128139) -> 1406.1281 | Y27: =IFERROR(__xludf.DUMMYFUNCTION("FILTER('GBD estimates'!$AF$4:$AF$1203,'GBD estimates'!$AA$4:$AA$1203=Y$3,'GBD estimates'!$X$4:$X$1203=""All causes"",'GBD estimates'!$Z$4:$Z$1203=""28 to 364 days (post neonatal)"")"),688.1729607) -> 688.17296 | Z27: =IFERROR(__xludf.DUMMYFUNCTION("FILTER('GBD estimates'!$AF$4:$AF$1203,'GBD estimates'!$AA$4:$AA$1203=Z$3,'GBD estimates'!$X$4:$X$1203=""All causes"",'GBD estimates'!$Z$4:$Z$1203=""28 to 364 days (post neonatal)"")"),2904.058815) -> 2904.0588 | AA27: =IFERROR(__xludf.DUMMYFUNCTION("FILTER('GBD estimates'!$AF$4:$AF$1203,'GBD estimates'!$AA$4:$AA$1203=AA$3,'GBD estimates'!$X$4:$X$1203=""All causes"",'GBD estimates'!$Z$4:$Z$1203=""28 to 364 days (post neonatal)"")"),901.7446937) -> 901.74469 | AB27: =IFERROR(__xludf.DUMMYFUNCTION("FILTER('GBD estimates'!$AF$4:$AF$1203,'GBD estimates'!$AA$4:$AA$1203=AB$3,'GBD estimates'!$X$4:$X$1203=""All causes"",'GBD estimates'!$Z$4:$Z$1203=""28 to 364 days (post neonatal)"")"),3747.540591) -> 3747.5406 | AC27: =IFERROR(__xludf.DUMMYFUNCTION("FILTER('GBD estimates'!$AF$4:$AF$1203,'GBD estimates'!$AA$4:$AA$1203=AC$3,'GBD estimates'!$X$4:$X$1203=""All causes"",'GBD estimates'!$Z$4:$Z$1203=""28 to 364 days (post neonatal)"")"),5457.207151) -> 5457.2072 | AD27: =IFERROR(__xludf.DUMMYFUNCTION("FILTER('GBD estimates'!$AF$4:$AF$1203,'GBD estimates'!$AA$4:$AA$1203=AD$3,'GBD estimates'!$X$4:$X$1203=""All causes"",'GBD estimates'!$Z$4:$Z$1203=""28 to 364 days (post neonatal)"")"),1063.922078) -> 1063.9221 | AE27: =IFERROR(__xludf.DUMMYFUNCTION("FILTER('GBD estimates'!$AF$4:$AF$1203,'GBD estimates'!$AA$4:$AA$1203=AE$3,'GBD estimates'!$X$4:$X$1203=""All causes"",'GBD estimates'!$Z$4:$Z$1203=""28 to 364 days (post neonatal)"")"),1846.545736) -> 1846.5457 | AF27: =IFERROR(__xludf.DUMMYFUNCTION("FILTER('GBD estimates'!$AF$4:$AF$1203,'GBD estimates'!$AA$4:$AA$1203=AF$3,'GBD estimates'!$X$4:$X$1203=""All causes"",'GBD estimates'!$Z$4:$Z$1203=""28 to 364 days (post neonatal)"")"),9773.849826) -> 9773.8498 | AG27: =IFERROR(__xludf.DUMMYFUNCTION("FILTER('GBD estimates'!$I$4:$I$1203,'GBD estimates'!$C$4:$C$1203=AG$2,'GBD estimates'!$F$4:$F$1203=""All causes"",'GBD estimates'!$E$4:$E$1203=""28-364 days"")"),17133.41458) -> 17133.415 | AH27: =IFERROR(__xludf.DUMMYFUNCTION("FILTER('GBD estimates'!$I$4:$I$1203,'GBD estimates'!$C$4:$C$1203=AH$2,'GBD estimates'!$F$4:$F$1203=""All causes"",'GBD estimates'!$E$4:$E$1203=""28-364 days"")"),27388.4432) -> 27388.443 | AI27: =IFERROR(__xludf.DUMMYFUNCTION("FILTER('GBD estimates'!$I$4:$I$1203,'GBD estimates'!$C$4:$C$1203=AI$2,'GBD estimates'!$F$4:$F$1203=""All causes"",'GBD estimates'!$E$4:$E$1203=""28-364 days"")"),3686.52231) -> 3686.5223 | AJ27: =IFERROR(__xludf.DUMMYFUNCTION("FILTER('GBD estimates'!$I$4:$I$1203,'GBD estimates'!$C$4:$C$1203=AJ$2,'GBD estimates'!$F$4:$F$1203=""All causes"",'GBD estimates'!$E$4:$E$1203=""28-364 days"")"),25133.87915) -> 25133.879 | AL27: GBD 2019
C29: Estimated mortalities per year among the VAS-eligible population
E30: Proportion of post-neonatal mortalities that are among 1-5-month-olds | F30: % | G30: input | H30: 0.53 | M30: - | N30: - | O30: - | P30: - | Q30: - | R30: - | S30: - | T30: - | U30: - | V30: - | W30: - | X30: - | Y30: - | Z30: - | AA30: - | AB30: - | AC30: - | AD30: - | AE30: - | AF30: - | AG30: - | AH30: - | AI30: - | AJ30: - | AL30: GW's analysis of the age breakdown of mortalities under age 1
C32: All-cause mortality rate among the VAS-eligible population
E33: All-cause mortality rate among people under age 5 | F33: per 100k | G33: input | H33: - | I33: =IFERROR(__xludf.DUMMYFUNCTION("FILTER('GBD estimates'!$T$4:$T$1203,'GBD estimates'!$N$4:$N$1203=I$2,'GBD estimates'!$Q$4:$Q$1203=""All causes"",'GBD estimates'!$P$4:$P$1203=""<5 years"")"),2442.031714) -> 2442.0317 | J33: =IFERROR(__xludf.DUMMYFUNCTION("FILTER('GBD estimates'!$T$4:$T$1203,'GBD estimates'!$N$4:$N$1203=J$2,'GBD estimates'!$Q$4:$Q$1203=""All causes"",'GBD estimates'!$P$4:$P$1203=""<5 years"")"),1522.066664) -> 1522.0667 | K33: =IFERROR(__xludf.DUMMYFUNCTION("FILTER('GBD estimates'!$T$4:$T$1203,'GBD estimates'!$N$4:$N$1203=K$2,'GBD estimates'!$Q$4:$Q$1203=""All causes"",'GBD estimates'!$P$4:$P$1203=""<5 years"")"),1615.568992) -> 1615.569 | L33: =IFERROR(__xludf.DUMMYFUNCTION("FILTER('GBD estimates'!$T$4:$T$1203,'GBD estimates'!$N$4:$N$1203=L$2,'GBD estimates'!$Q$4:$Q$1203=""All causes"",'GBD estimates'!$P$4:$P$1203=""<5 years"")"),1236.060618) -> 1236.0606 | M33: =IFERROR(__xludf.DUMMYFUNCTION("FILTER('GBD estimates'!$T$4:$T$1203,'GBD estimates'!$N$4:$N$1203=M$2,'GBD estimates'!$Q$4:$Q$1203=""All causes"",'GBD estimates'!$P$4:$P$1203=""<5 years"")"),2118.423217) -> 2118.4232 | N33: =IFERROR(__xludf.DUMMYFUNCTION("FILTER('GBD estimates'!$T$4:$T$1203,'GBD estimates'!$N$4:$N$1203=N$2,'GBD estimates'!$Q$4:$Q$1203=""All causes"",'GBD estimates'!$P$4:$P$1203=""<5 years"")"),831.4269669) -> 831.42697 | O33: =IFERROR(__xludf.DUMMYFUNCTION("FILTER('GBD estimates'!$T$4:$T$1203,'GBD estimates'!$N$4:$N$1203=O$2,'GBD estimates'!$Q$4:$Q$1203=""All causes"",'GBD estimates'!$P$4:$P$1203=""<5 years"")"),1222.490103) -> 1222.4901 | P33: =IFERROR(__xludf.DUMMYFUNCTION("FILTER('GBD estimates'!$T$4:$T$1203,'GBD estimates'!$N$4:$N$1203=P$2,'GBD estimates'!$Q$4:$Q$1203=""All causes"",'GBD estimates'!$P$4:$P$1203=""<5 years"")"),2697.678735) -> 2697.6787 | Q33: =IFERROR(__xludf.DUMMYFUNCTION("FILTER('GBD estimates'!$T$4:$T$1203,'GBD estimates'!$N$4:$N$1203=Q$2,'GBD estimates'!$Q$4:$Q$1203=""All causes"",'GBD estimates'!$P$4:$P$1203=""<5 years"")"),2477.232682) -> 2477.2327 | R33: =IFERROR(__xludf.DUMMYFUNCTION("FILTER('GBD estimates'!$AS$4:$AS$1203,'GBD estimates'!$AN$4:$AN$1203=R$3,'GBD estimates'!$AK$4:$AK$1203=""All causes"",'GBD estimates'!$AM$4:$AM$1203=""Under 5"")"),2457.694788) -> 2457.6948 | S33: =IFERROR(__xludf.DUMMYFUNCTION("FILTER('GBD estimates'!$AS$4:$AS$1203,'GBD estimates'!$AN$4:$AN$1203=S$3,'GBD estimates'!$AK$4:$AK$1203=""All causes"",'GBD estimates'!$AM$4:$AM$1203=""Under 5"")"),1223.997163) -> 1223.9972 | T33: =IFERROR(__xludf.DUMMYFUNCTION("FILTER('GBD estimates'!$AS$4:$AS$1203,'GBD estimates'!$AN$4:$AN$1203=T$3,'GBD estimates'!$AK$4:$AK$1203=""All causes"",'GBD estimates'!$AM$4:$AM$1203=""Under 5"")"),1006.968781) -> 1006.9688 | U33: =IFERROR(__xludf.DUMMYFUNCTION("FILTER('GBD estimates'!$AS$4:$AS$1203,'GBD estimates'!$AN$4:$AN$1203=U$3,'GBD estimates'!$AK$4:$AK$1203=""All causes"",'GBD estimates'!$AM$4:$AM$1203=""Under 5"")"),1771.778908) -> 1771.7789 | V33: =IFERROR(__xludf.DUMMYFUNCTION("FILTER('GBD estimates'!$AS$4:$AS$1203,'GBD estimates'!$AN$4:$AN$1203=V$3,'GBD estimates'!$AK$4:$AK$1203=""All causes"",'GBD estimates'!$AM$4:$AM$1203=""Under 5"")"),1546.205875) -> 1546.2059 | W33: =IFERROR(__xludf.DUMMYFUNCTION("FILTER('GBD estimates'!$AS$4:$AS$1203,'GBD estimates'!$AN$4:$AN$1203=W$3,'GBD estimates'!$AK$4:$AK$1203=""All causes"",'GBD estimates'!$AM$4:$AM$1203=""Under 5"")"),1814.277484) -> 1814.2775 | X33: =IFERROR(__xludf.DUMMYFUNCTION("FILTER('GBD estimates'!$AS$4:$AS$1203,'GBD estimates'!$AN$4:$AN$1203=X$3,'GBD estimates'!$AK$4:$AK$1203=""All causes"",'GBD estimates'!$AM$4:$AM$1203=""Under 5"")"),1286.059774) -> 1286.0598 | Y33: =IFERROR(__xludf.DUMMYFUNCTION("FILTER('GBD estimates'!$AS$4:$AS$1203,'GBD estimates'!$AN$4:$AN$1203=Y$3,'GBD estimates'!$AK$4:$AK$1203=""All causes"",'GBD estimates'!$AM$4:$AM$1203=""Under 5"")"),1405.186606) -> 1405.1866 | Z33: =IFERROR(__xludf.DUMMYFUNCTION("FILTER('GBD estimates'!$AS$4:$AS$1203,'GBD estimates'!$AN$4:$AN$1203=Z$3,'GBD estimates'!$AK$4:$AK$1203=""All causes"",'GBD estimates'!$AM$4:$AM$1203=""Under 5"")"),1006.944899) -> 1006.9449 | AA33: =IFERROR(__xludf.DUMMYFUNCTION("FILTER('GBD estimates'!$AS$4:$AS$1203,'GBD estimates'!$AN$4:$AN$1203=AA$3,'GBD estimates'!$AK$4:$AK$1203=""All causes"",'GBD estimates'!$AM$4:$AM$1203=""Under 5"")"),1097.602879) -> 1097.6029 | AB33: =IFERROR(__xludf.DUMMYFUNCTION("FILTER('GBD estimates'!$AS$4:$AS$1203,'GBD estimates'!$AN$4:$AN$1203=AB$3,'GBD estimates'!$AK$4:$AK$1203=""All causes"",'GBD estimates'!$AM$4:$AM$1203=""Under 5"")"),1763.388791) -> 1763.3888 | AC33: =IFERROR(__xludf.DUMMYFUNCTION("FILTER('GBD estimates'!$AS$4:$AS$1203,'GBD estimates'!$AN$4:$AN$1203=AC$3,'GBD estimates'!$AK$4:$AK$1203=""All causes"",'GBD estimates'!$AM$4:$AM$1203=""Under 5"")"),1354.029628) -> 1354.0296 | AD33: =IFERROR(__xludf.DUMMYFUNCTION("FILTER('GBD estimates'!$AS$4:$AS$1203,'GBD estimates'!$AN$4:$AN$1203=AD$3,'GBD estimates'!$AK$4:$AK$1203=""All causes"",'GBD estimates'!$AM$4:$AM$1203=""Under 5"")"),929.9922997) -> 929.9923 | AE33: =IFERROR(__xludf.DUMMYFUNCTION("FILTER('GBD estimates'!$AS$4:$AS$1203,'GBD estimates'!$AN$4:$AN$1203=AE$3,'GBD estimates'!$AK$4:$AK$1203=""All causes"",'GBD estimates'!$AM$4:$AM$1203=""Under 5"")"),1560.88469) -> 1560.8847 | AF33: =IFERROR(__xludf.DUMMYFUNCTION("FILTER('GBD estimates'!$AS$4:$AS$1203,'GBD estimates'!$AN$4:$AN$1203=AF$3,'GBD estimates'!$AK$4:$AK$1203=""All causes"",'GBD estimates'!$AM$4:$AM$1203=""Under 5"")"),2711.975471) -> 2711.9755 | AG33: =IFERROR(__xludf.DUMMYFUNCTION("FILTER('GBD estimates'!$T$4:$T$1203,'GBD estimates'!$N$4:$N$1203=AG$2,'GBD estimates'!$Q$4:$Q$1203=""All causes"",'GBD estimates'!$P$4:$P$1203=""<5 years"")"),1141.694553) -> 1141.6946 | AH33: =IFERROR(__xludf.DUMMYFUNCTION("FILTER('GBD estimates'!$T$4:$T$1203,'GBD estimates'!$N$4:$N$1203=AH$2,'GBD estimates'!$Q$4:$Q$1203=""All causes"",'GBD estimates'!$P$4:$P$1203=""<5 years"")"),2567.767314) -> 2567.7673 | AI33: =IFERROR(__xludf.DUMMYFUNCTION("FILTER('GBD estimates'!$T$4:$T$1203,'GBD estimates'!$N$4:$N$1203=AI$2,'GBD estimates'!$Q$4:$Q$1203=""All causes"",'GBD estimates'!$P$4:$P$1203=""<5 years"")"),1346.401636) -> 1346.4016 | AJ33: =IFERROR(__xludf.DUMMYFUNCTION("FILTER('GBD estimates'!$T$4:$T$1203,'GBD estimates'!$N$4:$N$1203=AJ$2,'GBD estimates'!$Q$4:$Q$1203=""All causes"",'GBD estimates'!$P$4:$P$1203=""<5 years"")"),1293.450656) -> 1293.4507 | AL33: GBD 2019
E34: Estimated proportion of people under age 5 who are 6-59-month-olds | F34: % | G34: input | H34: - | I34: =54/59 -> 0.91525424 | J34: =54/59 -> 0.91525424 | K34: =54/59 -> 0.91525424 | L34: =54/59 -> 0.91525424 | M34: =54/59 -> 0.91525424 | N34: =54/59 -> 0.91525424 | O34: =54/59 -> 0.91525424 | P34: =54/59 -> 0.91525424 | ... AJ34: =54/59 -> 0.91525424 | AL34: GW guesstimate
C36: All-cause mortality rate among the VAS-eligible population in the absence of VAS
E37: Adjustment for differences between the national mortality rate and mortality rates in the subnational areas targeted for VAS | F37: % | G37: input | H37: - | I37: - | J37: -0.1408628 | K37: - | L37: - | M37: - | N37: - | O37: 0.17 | P37: - | Q37: - | R37: - | S37: - | T37: - | U37: - | V37: - | W37: - | X37: - | Y37: - | Z37: - | AA37: - | AB37: - | AC37: - | AD37: - | AE37: - | AF37: - | AG37: - | AH37: - | AI37: - | AJ37: - | AL37: GW analysis | AM37: GW's analysis of subnational mortality rates for VAS
A39: External validity
C41: Vitamin A deficiency prevalence in Nigeria according to the latest national survey
E42: Vitamin A deficiency prevalence in Nigeria according to the latest national survey | F42: % | G42: input | H42: - | I42: - | J42: - | K42: - | L42: - | M42: - | N42: - | O42: - | P42: - | Q42: - | R42: 0.295 | S42: 0.295 | T42: 0.295 | U42: 0.295 | V42: 0.295 | W42: 0.295 | X42: 0.295 | Y42: 0.295 | Z42: 0.295 | AA42: 0.295 | AB42: 0.295 | AC42: 0.295 | AD42: 0.295 | AE42: 0.295 | AF42: 0.295 | AG42: - | AH42: - | AI42: - | AJ42: - | AL42: Maziya-Dixon et al. 2006
E43: Year of latest national vitamin A deficiency survey in Nigeria | F43: year | G43: input | H43: - | I43: - | J43: - | K43: - | L43: - | M43: - | N43: - | O43: - | P43: - | Q43: - | R43: 2001 | S43: 2001 | T43: 2001 | U43: 2001 | V43: 2001 | W43: 2001 | X43: 2001 | Y43: 2001 | Z43: 2001 | AA43: 2001 | AB43: 2001 | AC43: 2001 | AD43: 2001 | AE43: 2001 | AF43: 2001 | AG43: - | AH43: - | AI43: - | AJ43: - | AL43: Maziya-Dixon et al. 2006
C45: National data on health proxies for vitamin A deficiency according to DHS surveys
E46: National proportion of people under age 5 who were experiencing stunting in 2003 | F46: % | G46: input | H46: - | I46: - | J46: - | K46: - | L46: - | M46: - | N46: - | O46: - | P46: - | Q46: - | R46: 0.383 | S46: 0.383 | T46: 0.383 | U46: 0.383 | V46: 0.383 | W46: 0.383 | X46: 0.383 | Y46: 0.383 | Z46: 0.383 | AA46: 0.383 | AB46: 0.383 | AC46: 0.383 | AD46: 0.383 | AE46: 0.383 | AF46: 0.383 | AG46: - | AH46: - | AI46: - | AJ46: - | AL46: Nigeria DHS 2003 Final Report
E47: National proportion of people under age 5 who were experiencing wasting in 2003 | F47: % | G47: input | H47: - | I47: - | J47: - | K47: - | L47: - | M47: - | N47: - | O47: - | P47: - | Q47: - | R47: 0.092 | S47: 0.092 | T47: 0.092 | U47: 0.092 | V47: 0.092 | W47: 0.092 | X47: 0.092 | Y47: 0.092 | Z47: 0.092 | AA47: 0.092 | AB47: 0.092 | AC47: 0.092 | AD47: 0.092 | AE47: 0.092 | AF47: 0.092 | AG47: - | AH47: - | AI47: - | AJ47: - | AL47: Nigeria DHS 2003 Final Report
E48: National proportion of people under age 5 who were experiencing stunting in 2018 | F48: % | G48: input | H48: - | I48: - | J48: - | K48: - | L48: - | M48: - | N48: - | O48: - | P48: - | Q48: - | R48: 0.368 | S48: 0.368 | T48: 0.368 | U48: 0.368 | V48: 0.368 | W48: 0.368 | X48: 0.368 | Y48: 0.368 | Z48: 0.368 | AA48: 0.368 | AB48: 0.368 | AC48: 0.368 | AD48: 0.368 | AE48: 0.368 | AF48: 0.368 | AG48: - | AH48: - | AI48: - | AJ48: - | AL48: Nigeria DHS 2018 Final Report
E49: National proportion of people under age 5 who were experiencing wasting in 2018 | F49: % | G49: input | H49: - | I49: - | J49: - | K49: - | L49: - | M49: - | N49: - | O49: - | P49: - | Q49: - | R49: 0.068 | S49: 0.068 | T49: 0.068 | U49: 0.068 | V49: 0.068 | W49: 0.068 | X49: 0.068 | Y49: 0.068 | Z49: 0.068 | AA49: 0.068 | AB49: 0.068 | AC49: 0.068 | AD49: 0.068 | AE49: 0.068 | AF49: 0.068 | AG49: - | AH49: - | AI49: - | AJ49: - | AL49: Nigeria DHS 2018 Final Report
E50: National proportion of 6-59-month-olds who were experiencing anemia in 2018 | F50: % | G50: input | H50: - | I50: - | J50: - | K50: - | L50: - | M50: - | N50: - | O50: - | P50: - | Q50: - | R50: 0.679 | S50: 0.679 | T50: 0.679 | U50: 0.679 | V50: 0.679 | W50: 0.679 | X50: 0.679 | Y50: 0.679 | Z50: 0.679 | AA50: 0.679 | AB50: 0.679 | AC50: 0.679 | AD50: 0.679 | AE50: 0.679 | AF50: 0.679 | AG50: - | AH50: - | AI50: - | AJ50: - | AL50: Nigeria DHS 2018 Final Report
C52: National data on economic proxies for vitamin A deficiency according to the World Bank
E53: National proportion of the population below the international poverty line in 2003 | F53: % | G53: input | H53: - | I53: - | J53: - | K53: - | L53: - | M53: - | N53: - | O53: - | P53: - | Q53: - | R53: 0.559 | S53: 0.559 | T53: 0.559 | U53: 0.559 | V53: 0.559 | W53: 0.559 | X53: 0.559 | Y53: 0.559 | Z53: 0.559 | AA53: 0.559 | AB53: 0.559 | AC53: 0.559 | AD53: 0.559 | AE53: 0.559 | AF53: 0.559 | AG53: - | AH53: - | AI53: - | AJ53: - | AL53: World Bank Open Data
E54: National proportion of the population below the international poverty line in 2018 | F54: % | G54: input | H54: - | I54: - | J54: - | K54: - | L54: - | M54: - | N54: - | O54: - | P54: - | Q54: - | R54: 0.391 | S54: 0.391 | T54: 0.391 | U54: 0.391 | V54: 0.391 | W54: 0.391 | X54: 0.391 | Y54: 0.391 | Z54: 0.391 | AA54: 0.391 | AB54: 0.391 | AC54: 0.391 | AD54: 0.391 | AE54: 0.391 | AF54: 0.391 | AG54: - | AH54: - | AI54: - | AJ54: - | AL54: World Bank Open Data
C56: National data on economic proxies for vitamin A deficiency according to a 2019 NBS survey
E57: National proportion of the population below Nigeria's poverty line in 2019 | F57: % | G57: input | H57: - | I57: - | J57: - | K57: - | L57: - | M57: - | N57: - | O57: - | P57: - | Q57: - | R57: 0.4009 | S57: 0.4009 | T57: 0.4009 | U57: 0.4009 | V57: 0.4009 | W57: 0.4009 | X57: 0.4009 | Y57: 0.4009 | Z57: 0.4009 | AA57: 0.4009 | AB57: 0.4009 | AC57: 0.4009 | AD57: 0.4009 | AE57: 0.4009 | AF57: 0.4009 | AG57: - | AH57: - | AI57: - | AJ57: - | AL57: Nigeria NBS 2019 Poverty and Equality Report
C59: Change in proxies for vitamin A deficiency over time
E60: Weight placed on change in rates of stunting as a proxy for changes in vitamin A deficiency | F60: % | G60: input | H60: =1/3 -> 0.33333333 | I60: - | J60: - | K60: - | L60: - | M60: - | N60: - | O60: - | P60: - | Q60: - | R60: - | S60: - | T60: - | U60: - | V60: - | W60: - | X60: - | Y60: - | Z60: - | AA60: - | AB60: - | AC60: - | AD60: - | AE60: - | AF60: - | AG60: - | AH60: - | AI60: - | AJ60: - | AL60: GW guesstimate
E61: Weight placed on change in rates of wasting as a proxy for changes in vitamin A deficiency | F61: % | G61: input | H61: =1/3 -> 0.33333333 | I61: - | J61: - | K61: - | L61: - | M61: - | N61: - | O61: - | P61: - | Q61: - | R61: - | S61: - | T61: - | U61: - | V61: - | W61: - | X61: - | Y61: - | Z61: - | AA61: - | AB61: - | AC61: - | AD61: - | AE61: - | AF61: - | AG61: - | AH61: - | AI61: - | AJ61: - | AL61: GW guesstimate
E62: Weight placed on change in poverty rates as a proxy for changes in vitamin A deficiency | F62: % | G62: input | H62: =1/3 -> 0.33333333 | I62: - | J62: - | K62: - | L62: - | M62: - | N62: - | O62: - | P62: - | Q62: - | R62: - | S62: - | T62: - | U62: - | V62: - | W62: - | X62: - | Y62: - | Z62: - | AA62: - | AB62: - | AC62: - | AD62: - | AE62: - | AF62: - | AG62: - | AH62: - | AI62: - | AJ62: - | AL62: GW guesstimate
C64: Approximated change in vitamin A deficiency prevalence over time
E65: Year of early data points for vitamin A defiency proxies | F65: year | G65: input | H65: - | I65: - | J65: - | K65: - | L65: - | M65: - | N65: - | O65: - | P65: - | Q65: - | R65: 2003 | S65: 2003 | T65: 2003 | U65: 2003 | V65: 2003 | W65: 2003 | X65: 2003 | Y65: 2003 | Z65: 2003 | AA65: 2003 | AB65: 2003 | AC65: 2003 | AD65: 2003 | AE65: 2003 | AF65: 2003 | AG65: - | AH65: - | AI65: - | AJ65: - | AL65: Nigeria DHS 2003 Final Report
E66: Year of late data points for vitamin A defiency proxies | F66: year | G66: input | H66: - | I66: - | J66: - | K66: - | L66: - | M66: - | N66: - | O66: - | P66: - | Q66: - | R66: 2018 | S66: 2018 | T66: 2018 | U66: 2018 | V66: 2018 | W66: 2018 | X66: 2018 | Y66: 2018 | Z66: 2018 | AA66: 2018 | AB66: 2018 | AC66: 2018 | AD66: 2018 | AE66: 2018 | AF66: 2018 | AG66: - | AH66: - | AI66: - | AJ66: - | AL66: Nigeria DHS 2018 Final Report
E67: Expected year of the grantee's VAS campaign | F67: year | G67: input | H67: - | I67: 2022 | J67: 2022 | K67: 2022 | L67: 2022 | M67: - | N67: 2022 | O67: 2022 | P67: 2022 | Q67: - | R67: 2022 | S67: 2022 | T67: 2022 | U67: 2022 | V67: 2022 | W67: 2022 | X67: 2022 | Y67: 2022 | Z67: 2022 | AA67: 2022 | AB67: 2022 | AC67: 2022 | AD67: 2022 | AE67: 2022 | AF67: 2022 | AG67: 2022 | AH67: 2022 | AI67: 2022 | AJ67: 2022 | AL67: Helen Keller International
C69: State-level data on health proxies for vitamin A deficiency according to DHS surveys
E70: State-level proportion of people under age 5 who were experiencing stunting in 2018 | F70: % | G70: input | H70: - | I70: - | J70: - | K70: - | L70: - | M70: - | N70: - | O70: - | P70: - | Q70: - | R70: 0.397 | S70: 0.196 | T70: 0.14 | U70: 0.208 | V70: 0.237 | W70: 0.252 | X70: 0.16 | Y70: 0.221 | Z70: 0.176 | AA70: 0.2 | AB70: 0.314 | AC70: 0.266 | AD70: 0.237 | AE70: 0.168 | AF70: 0.419 | AG70: - | AH70: - | AI70: - | AJ70: - | AL70: Nigeria DHS 2018 Final Report
E71: State-level proportion of people under age 5 who were experiencing wasting in 2018 | F71: % | G71: input | H71: - | I71: - | J71: - | K71: - | L71: - | M71: - | N71: - | O71: - | P71: - | Q71: - | R71: 0.042 | S71: 0.042 | T71: 0.023 | U71: 0.08 | V71: 0.02 | W71: 0.045 | X71: 0.033 | Y71: 0.033 | Z71: 0.069 | AA71: 0.039 | AB71: 0.056 | AC71: 0.057 | AD71: 0.045 | AE71: 0.064 | AF71: 0.053 | AG71: - | AH71: - | AI71: - | AJ71: - | AL71: Nigeria DHS 2018 Final Report
E72: State-level proportion of 6-59-month-olds who were experiencing anemia in 2018 | F72: % | G72: input | H72: - | I72: - | J72: - | K72: - | L72: - | M72: - | N72: - | O72: - | P72: - | Q72: - | R72: 0.56 | S72: 0.747 | T72: 0.752 | U72: 0.62 | V72: 0.698 | W72: 0.793 | X72: 0.659 | Y72: 0.719 | Z72: 0.592 | AA72: 0.636 | AB72: 0.679 | AC72: 0.595 | AD72: 0.576 | AE72: 0.789 | AF72: 0.709 | AG72: - | AH72: - | AI72: - | AJ72: - | AL72: Nigeria DHS 2018 Final Report
C74: State-level data on economic proxies for vitamin A deficiency according to a 2019 NBS survey
E75: State-level proportion of the population below Nigeria's poverty line in 2019 | F75: % | G75: input | H75: - | I75: - | J75: - | K75: - | L75: - | M75: - | N75: - | O75: - | P75: - | Q75: - | R75: 0.754 | S75: 0.268 | T75: 0.148 | U75: 0.329 | V75: 0.06 | W75: 0.798 | X75: 0.12 | Y75: 0.28 | Z75: 0.289 | AA75: 0.285 | AB75: 0.573 | AC75: 0.093 | AD75: 0.085 | AE75: 0.239 | AF75: 0.877 | AG75: - | AH75: - | AI75: - | AJ75: - | AL75: Nigeria NBS 2019 Poverty and Equality Report
C77: Adjustment for variation in vitamin A deficiency prevalence across states
E78: Weight placed on change in rates of stunting as a proxy for changes in vitamin A deficiency | F78: % | G78: input | H78: - | I78: - | J78: - | K78: - | L78: - | M78: - | N78: - | O78: - | P78: - | Q78: - | R78: =1/4 -> 0.25 | S78: =1/4 -> 0.25 | T78: =1/4 -> 0.25 | U78: =1/4 -> 0.25 | V78: =1/4 -> 0.25 | W78: =1/4 -> 0.25 | X78: =1/4 -> 0.25 | Y78: =1/4 -> 0.25 | ... AF78: =1/4 -> 0.25 | AG78: - | AH78: - | AI78: - | AJ78: - | AL78: GW guesstimate
E79: Weight placed on change in rates of wasting as a proxy for changes in vitamin A deficiency | F79: % | G79: input | H79: - | I79: - | J79: - | K79: - | L79: - | M79: - | N79: - | O79: - | P79: - | Q79: - | R79: =1/4 -> 0.25 | S79: =1/4 -> 0.25 | T79: =1/4 -> 0.25 | U79: =1/4 -> 0.25 | V79: =1/4 -> 0.25 | W79: =1/4 -> 0.25 | X79: =1/4 -> 0.25 | Y79: =1/4 -> 0.25 | ... AF79: =1/4 -> 0.25 | AG79: - | AH79: - | AI79: - | AJ79: - | AL79: GW guesstimate
E80: Weight placed on change in rates of anemia as a proxy for changes in vitamin A deficiency | F80: % | G80: input | H80: - | I80: - | J80: - | K80: - | L80: - | M80: - | N80: - | O80: - | P80: - | Q80: - | R80: =1/4 -> 0.25 | S80: =1/4 -> 0.25 | T80: =1/4 -> 0.25 | U80: =1/4 -> 0.25 | V80: =1/4 -> 0.25 | W80: =1/4 -> 0.25 | X80: =1/4 -> 0.25 | Y80: =1/4 -> 0.25 | ... AF80: =1/4 -> 0.25 | AG80: - | AH80: - | AI80: - | AJ80: - | AL80: GW guesstimate
E81: Weight placed on change in poverty rates as a proxy for changes in vitamin A deficiency | F81: % | G81: input | H81: - | I81: - | J81: - | K81: - | L81: - | M81: - | N81: - | O81: - | P81: - | Q81: - | R81: =1/4 -> 0.25 | S81: =1/4 -> 0.25 | T81: =1/4 -> 0.25 | U81: =1/4 -> 0.25 | V81: =1/4 -> 0.25 | W81: =1/4 -> 0.25 | X81: =1/4 -> 0.25 | Y81: =1/4 -> 0.25 | ... AF81: =1/4 -> 0.25 | AG81: - | AH81: - | AI81: - | AJ81: - | AL81: GW guesstimate
C83: Vitamin A deficiency prevalence for countries other than Nigeria
E84: Vitamin A deficiency prevalence found in most recent survey of people under age 5 | F84: % | G84: input | H84: - | I84: 0.245 | J84: 0.35 | K84: 0.24 | L84: 0.61 | M84: - | N84: 0.09 | O84: 0.42 | P84: 0.771 | Q84: - | R84: - | S84: - | T84: - | U84: - | V84: - | W84: - | X84: - | Y84: - | Z84: - | AA84: - | AB84: - | AC84: - | AD84: - | AE84: - | AF84: - | AG84: - | AH84: 0.28 | AI84: - | AJ84: - | AL84: GW analysis | AM84: GW's analysis of recent vitamin A deficiency surveys
E85: Year of most recent vitamin A deficiency survey of people under age 5 | F85: year | G85: input | H85: - | I85: 2010 | J85: 2009 | K85: 2007 | L85: 1999 | M85: - | N85: 2011 | O85: 2000 | P85: 1997 | Q85: - | R85: - | S85: - | T85: - | U85: - | V85: - | W85: - | X85: - | Y85: - | Z85: - | AA85: - | AB85: - | AC85: - | AD85: - | AE85: - | AF85: - | AG85: - | AH85: 2008 | AI85: - | AJ85: - | AL85: GW analysis | AM85: GW's analysis of recent vitamin A deficiency surveys
E86: Vitamin A deficiency prevalence rate among 6-59-month-olds, derived from GBD 2017 | F86: % | G86: input | H86: - | I86: 0.3068667 | J86: 0.3083889 | K86: 0.3005 | L86: 0.328 | M86: 0.2774778 | N86: 0.3636778 | O86: 0.2654 | P86: 0.3055222 | Q86: 0.3227778 | R86: - | S86: - | T86: - | U86: - | V86: - | W86: - | X86: - | Y86: - | Z86: - | AA86: - | AB86: - | AC86: - | AD86: - | AE86: - | AF86: - | AG86: 0.2644151 | AH86: 0.2928463 | AI86: 0.2635964 | AJ86: 0.2343924 | AL86: GBD 2017
C88: Weighting for vitamin A deficiency prevalence rates from different sources
E89: Weight assigned to vitamin A deficiency rates found in the most recent surveys | F89: % | G89: input | H89: - | I89: 0.25 | J89: 0.5 | K89: 0.5 | L89: 0.5 | M89: 0 | N89: 0.5 | O89: 0.5 | P89: 0.25 | Q89: 0 | R89: - | S89: - | T89: - | U89: - | V89: - | W89: - | X89: - | Y89: - | Z89: - | AA89: - | AB89: - | AC89: - | AD89: - | AE89: - | AF89: - | AG89: 0 | AH89: 0.25 | AI89: 0 | AJ89: 0 | AL89: GW analysis | AM89: GW's analysis of recent vitamin A deficiency surveys
E90: Weight assigned to vitamin A deficiency rates from GBD 2017 | F90: % | G90: input | H90: - | I90: =1-I89 -> 0.75 | J90: =1-J89 -> 0.5 | K90: =1-K89 -> 0.5 | L90: =1-L89 -> 0.5 | M90: =1-M89 -> 1 | N90: =1-N89 -> 0.5 | O90: =1-O89 -> 0.5 | P90: =1-P89 -> 0.75 | Q90: =1-Q89 -> 1 | R90: - | S90: - | T90: - | U90: - | V90: - | W90: - | X90: - | Y90: - | Z90: - | AA90: - | AB90: - | AC90: - | AD90: - | AE90: - | AF90: - | AG90: 1 | AH90: 0.75 | AI90: 1 | AJ90: 1 | AL90: GW analysis
C92: Vitamin A deficiency prevalence in the populations studied by trials from Imdad et al. 2017
E93: Vitamin A deficiency prevalence in the populations studied by trials from Imdad et al. 2017 | F93: % | G93: input | H93: 0.5891852 | I93: - | J93: - | K93: - | L93: - | M93: - | N93: - | O93: - | P93: - | Q93: - | R93: - | S93: - | T93: - | U93: - | V93: - | W93: - | X93: - | Y93: - | Z93: - | AA93: - | AB93: - | AC93: - | AD93: - | AE93: - | AF93: - | AG93: - | AH93: - | AI93: - | AJ93: - | AL93: GW analysis | AM93: GW's VAS supplementary analysis (2024), Imdad 2017 VAD prevalence estimates
C95: Measles mortalities per year among people under five
E96: Measles mortalities per year among people under age 5 | F96: # | G96: input | H96: - | I96: =IFERROR(__xludf.DUMMYFUNCTION("FILTER('GBD estimates'!$I$4:$I$1203,'GBD estimates'!$C$4:$C$1203=I$2,'GBD estimates'!$F$4:$F$1203=""Measles"",'GBD estimates'!$E$4:$E$1203=""<5 years"")"),2083.452176) -> 2083.4522 | J96: =IFERROR(__xludf.DUMMYFUNCTION("FILTER('GBD estimates'!$I$4:$I$1203,'GBD estimates'!$C$4:$C$1203=J$2,'GBD estimates'!$F$4:$F$1203=""Measles"",'GBD estimates'!$E$4:$E$1203=""<5 years"")"),1942.618027) -> 1942.618 | K96: =IFERROR(__xludf.DUMMYFUNCTION("FILTER('GBD estimates'!$I$4:$I$1203,'GBD estimates'!$C$4:$C$1203=K$2,'GBD estimates'!$F$4:$F$1203=""Measles"",'GBD estimates'!$E$4:$E$1203=""<5 years"")"),188.8174766) -> 188.81748 | L96: =IFERROR(__xludf.DUMMYFUNCTION("FILTER('GBD estimates'!$I$4:$I$1203,'GBD estimates'!$C$4:$C$1203=L$2,'GBD estimates'!$F$4:$F$1203=""Measles"",'GBD estimates'!$E$4:$E$1203=""<5 years"")"),3123.420902) -> 3123.4209 | M96: =IFERROR(__xludf.DUMMYFUNCTION("FILTER('GBD estimates'!$I$4:$I$1203,'GBD estimates'!$C$4:$C$1203=M$2,'GBD estimates'!$F$4:$F$1203=""Measles"",'GBD estimates'!$E$4:$E$1203=""<5 years"")"),995.7713051) -> 995.77131 | N96: =IFERROR(__xludf.DUMMYFUNCTION("FILTER('GBD estimates'!$I$4:$I$1203,'GBD estimates'!$C$4:$C$1203=N$2,'GBD estimates'!$F$4:$F$1203=""Measles"",'GBD estimates'!$E$4:$E$1203=""<5 years"")"),369.2190891) -> 369.21909 | O96: =IFERROR(__xludf.DUMMYFUNCTION("FILTER('GBD estimates'!$I$4:$I$1203,'GBD estimates'!$C$4:$C$1203=O$2,'GBD estimates'!$F$4:$F$1203=""Measles"",'GBD estimates'!$E$4:$E$1203=""<5 years"")"),1935.712929) -> 1935.7129 | P96: =IFERROR(__xludf.DUMMYFUNCTION("FILTER('GBD estimates'!$I$4:$I$1203,'GBD estimates'!$C$4:$C$1203=P$2,'GBD estimates'!$F$4:$F$1203=""Measles"",'GBD estimates'!$E$4:$E$1203=""<5 years"")"),2443.818724) -> 2443.8187 | Q96: =IFERROR(__xludf.DUMMYFUNCTION("FILTER('GBD estimates'!$I$4:$I$1203,'GBD estimates'!$C$4:$C$1203=Q$2,'GBD estimates'!$F$4:$F$1203=""Measles"",'GBD estimates'!$E$4:$E$1203=""<5 years"")"),9653.753707) -> 9653.7537 | R96: =IFERROR(__xludf.DUMMYFUNCTION("FILTER('GBD estimates'!$AF$4:$AF$1203,'GBD estimates'!$AA$4:$AA$1203=R$3,'GBD estimates'!$X$4:$X$1203=""Measles"",'GBD estimates'!$Z$4:$Z$1203=""Under 5"")"),73.24455414) -> 73.244554 | S96: =IFERROR(__xludf.DUMMYFUNCTION("FILTER('GBD estimates'!$AF$4:$AF$1203,'GBD estimates'!$AA$4:$AA$1203=S$3,'GBD estimates'!$X$4:$X$1203=""Measles"",'GBD estimates'!$Z$4:$Z$1203=""Under 5"")"),5.309874607) -> 5.3098746 | T96: =IFERROR(__xludf.DUMMYFUNCTION("FILTER('GBD estimates'!$AF$4:$AF$1203,'GBD estimates'!$AA$4:$AA$1203=T$3,'GBD estimates'!$X$4:$X$1203=""Measles"",'GBD estimates'!$Z$4:$Z$1203=""Under 5"")"),17.85969748) -> 17.859697 | U96: =IFERROR(__xludf.DUMMYFUNCTION("FILTER('GBD estimates'!$AF$4:$AF$1203,'GBD estimates'!$AA$4:$AA$1203=U$3,'GBD estimates'!$X$4:$X$1203=""Measles"",'GBD estimates'!$Z$4:$Z$1203=""Under 5"")"),125.4070902) -> 125.40709 | V96: =IFERROR(__xludf.DUMMYFUNCTION("FILTER('GBD estimates'!$AF$4:$AF$1203,'GBD estimates'!$AA$4:$AA$1203=V$3,'GBD estimates'!$X$4:$X$1203=""Measles"",'GBD estimates'!$Z$4:$Z$1203=""Under 5"")"),18.72352073) -> 18.723521 | W96: =IFERROR(__xludf.DUMMYFUNCTION("FILTER('GBD estimates'!$AF$4:$AF$1203,'GBD estimates'!$AA$4:$AA$1203=W$3,'GBD estimates'!$X$4:$X$1203=""Measles"",'GBD estimates'!$Z$4:$Z$1203=""Under 5"")"),25.16038522) -> 25.160385 | X96: =IFERROR(__xludf.DUMMYFUNCTION("FILTER('GBD estimates'!$AF$4:$AF$1203,'GBD estimates'!$AA$4:$AA$1203=X$3,'GBD estimates'!$X$4:$X$1203=""Measles"",'GBD estimates'!$Z$4:$Z$1203=""Under 5"")"),11.55855753) -> 11.558558 | Y96: =IFERROR(__xludf.DUMMYFUNCTION("FILTER('GBD estimates'!$AF$4:$AF$1203,'GBD estimates'!$AA$4:$AA$1203=Y$3,'GBD estimates'!$X$4:$X$1203=""Measles"",'GBD estimates'!$Z$4:$Z$1203=""Under 5"")"),4.157590193) -> 4.1575902 | Z96: =IFERROR(__xludf.DUMMYFUNCTION("FILTER('GBD estimates'!$AF$4:$AF$1203,'GBD estimates'!$AA$4:$AA$1203=Z$3,'GBD estimates'!$X$4:$X$1203=""Measles"",'GBD estimates'!$Z$4:$Z$1203=""Under 5"")"),15.49645298) -> 15.496453 | AA96: =IFERROR(__xludf.DUMMYFUNCTION("FILTER('GBD estimates'!$AF$4:$AF$1203,'GBD estimates'!$AA$4:$AA$1203=AA$3,'GBD estimates'!$X$4:$X$1203=""Measles"",'GBD estimates'!$Z$4:$Z$1203=""Under 5"")"),12.10947664) -> 12.109477 | AB96: =IFERROR(__xludf.DUMMYFUNCTION("FILTER('GBD estimates'!$AF$4:$AF$1203,'GBD estimates'!$AA$4:$AA$1203=AB$3,'GBD estimates'!$X$4:$X$1203=""Measles"",'GBD estimates'!$Z$4:$Z$1203=""Under 5"")"),50.87708862) -> 50.877089 | AC96: =IFERROR(__xludf.DUMMYFUNCTION("FILTER('GBD estimates'!$AF$4:$AF$1203,'GBD estimates'!$AA$4:$AA$1203=AC$3,'GBD estimates'!$X$4:$X$1203=""Measles"",'GBD estimates'!$Z$4:$Z$1203=""Under 5"")"),55.7358234) -> 55.735823 | AD96: =IFERROR(__xludf.DUMMYFUNCTION("FILTER('GBD estimates'!$AF$4:$AF$1203,'GBD estimates'!$AA$4:$AA$1203=AD$3,'GBD estimates'!$X$4:$X$1203=""Measles"",'GBD estimates'!$Z$4:$Z$1203=""Under 5"")"),6.787061154) -> 6.7870612 | AE96: =IFERROR(__xludf.DUMMYFUNCTION("FILTER('GBD estimates'!$AF$4:$AF$1203,'GBD estimates'!$AA$4:$AA$1203=AE$3,'GBD estimates'!$X$4:$X$1203=""Measles"",'GBD estimates'!$Z$4:$Z$1203=""Under 5"")"),9.668580475) -> 9.6685805 | AF96: =IFERROR(__xludf.DUMMYFUNCTION("FILTER('GBD estimates'!$AF$4:$AF$1203,'GBD estimates'!$AA$4:$AA$1203=AF$3,'GBD estimates'!$X$4:$X$1203=""Measles"",'GBD estimates'!$Z$4:$Z$1203=""Under 5"")"),168.8162065) -> 168.81621 | AG96: =IFERROR(__xludf.DUMMYFUNCTION("FILTER('GBD estimates'!$I$4:$I$1203,'GBD estimates'!$C$4:$C$1203=AG$2,'GBD estimates'!$F$4:$F$1203=""Measles"",'GBD estimates'!$E$4:$E$1203=""<5 years"")"),931.9152524) -> 931.91525 | AH96: =IFERROR(__xludf.DUMMYFUNCTION("FILTER('GBD estimates'!$I$4:$I$1203,'GBD estimates'!$C$4:$C$1203=AH$2,'GBD estimates'!$F$4:$F$1203=""Measles"",'GBD estimates'!$E$4:$E$1203=""<5 years"")"),2382.051646) -> 2382.0516 | AI96: =IFERROR(__xludf.DUMMYFUNCTION("FILTER('GBD estimates'!$I$4:$I$1203,'GBD estimates'!$C$4:$C$1203=AI$2,'GBD estimates'!$F$4:$F$1203=""Measles"",'GBD estimates'!$E$4:$E$1203=""<5 years"")"),48.89229568) -> 48.892296 | AJ96: =IFERROR(__xludf.DUMMYFUNCTION("FILTER('GBD estimates'!$I$4:$I$1203,'GBD estimates'!$C$4:$C$1203=AJ$2,'GBD estimates'!$F$4:$F$1203=""Measles"",'GBD estimates'!$E$4:$E$1203=""<5 years"")"),3759.250822) -> 3759.2508 | AL96: GBD 2019
E97: Early neonatal measles mortalities per year (babies under 7 days old) | F97: # | G97: input | H97: - | I97: =IFERROR(__xludf.DUMMYFUNCTION("FILTER('GBD estimates'!$I$4:$I$1203,'GBD estimates'!$C$4:$C$1203=I$2,'GBD estimates'!$F$4:$F$1203=""Measles"",'GBD estimates'!$E$4:$E$1203=""0-6 days"")"),0.0) -> 0 | J97: =IFERROR(__xludf.DUMMYFUNCTION("FILTER('GBD estimates'!$I$4:$I$1203,'GBD estimates'!$C$4:$C$1203=J$2,'GBD estimates'!$F$4:$F$1203=""Measles"",'GBD estimates'!$E$4:$E$1203=""0-6 days"")"),0.0) -> 0 | K97: =IFERROR(__xludf.DUMMYFUNCTION("FILTER('GBD estimates'!$I$4:$I$1203,'GBD estimates'!$C$4:$C$1203=K$2,'GBD estimates'!$F$4:$F$1203=""Measles"",'GBD estimates'!$E$4:$E$1203=""0-6 days"")"),0.0) -> 0 | L97: =IFERROR(__xludf.DUMMYFUNCTION("FILTER('GBD estimates'!$I$4:$I$1203,'GBD estimates'!$C$4:$C$1203=L$2,'GBD estimates'!$F$4:$F$1203=""Measles"",'GBD estimates'!$E$4:$E$1203=""0-6 days"")"),213.1905408) -> 213.19054 | M97: =IFERROR(__xludf.DUMMYFUNCTION("FILTER('GBD estimates'!$I$4:$I$1203,'GBD estimates'!$C$4:$C$1203=M$2,'GBD estimates'!$F$4:$F$1203=""Measles"",'GBD estimates'!$E$4:$E$1203=""0-6 days"")"),0.0) -> 0 | N97: =IFERROR(__xludf.DUMMYFUNCTION("FILTER('GBD estimates'!$I$4:$I$1203,'GBD estimates'!$C$4:$C$1203=N$2,'GBD estimates'!$F$4:$F$1203=""Measles"",'GBD estimates'!$E$4:$E$1203=""0-6 days"")"),0.0) -> 0 | O97: =IFERROR(__xludf.DUMMYFUNCTION("FILTER('GBD estimates'!$I$4:$I$1203,'GBD estimates'!$C$4:$C$1203=O$2,'GBD estimates'!$F$4:$F$1203=""Measles"",'GBD estimates'!$E$4:$E$1203=""0-6 days"")"),0.0) -> 0 | P97: =IFERROR(__xludf.DUMMYFUNCTION("FILTER('GBD estimates'!$I$4:$I$1203,'GBD estimates'!$C$4:$C$1203=P$2,'GBD estimates'!$F$4:$F$1203=""Measles"",'GBD estimates'!$E$4:$E$1203=""0-6 days"")"),0.0) -> 0 | Q97: =IFERROR(__xludf.DUMMYFUNCTION("FILTER('GBD estimates'!$I$4:$I$1203,'GBD estimates'!$C$4:$C$1203=Q$2,'GBD estimates'!$F$4:$F$1203=""Measles"",'GBD estimates'!$E$4:$E$1203=""0-6 days"")"),0.0) -> 0 | R97: =IFERROR(__xludf.DUMMYFUNCTION("FILTER('GBD estimates'!$AF$4:$AF$1203,'GBD estimates'!$AA$4:$AA$1203=R$3,'GBD estimates'!$X$4:$X$1203=""Measles"",'GBD estimates'!$Z$4:$Z$1203=""0 to 6 days (early neonatal)"")"),0.0) -> 0 | S97: =IFERROR(__xludf.DUMMYFUNCTION("FILTER('GBD estimates'!$AF$4:$AF$1203,'GBD estimates'!$AA$4:$AA$1203=S$3,'GBD estimates'!$X$4:$X$1203=""Measles"",'GBD estimates'!$Z$4:$Z$1203=""0 to 6 days (early neonatal)"")"),0.0) -> 0 | T97: =IFERROR(__xludf.DUMMYFUNCTION("FILTER('GBD estimates'!$AF$4:$AF$1203,'GBD estimates'!$AA$4:$AA$1203=T$3,'GBD estimates'!$X$4:$X$1203=""Measles"",'GBD estimates'!$Z$4:$Z$1203=""0 to 6 days (early neonatal)"")"),0.0) -> 0 | U97: =IFERROR(__xludf.DUMMYFUNCTION("FILTER('GBD estimates'!$AF$4:$AF$1203,'GBD estimates'!$AA$4:$AA$1203=U$3,'GBD estimates'!$X$4:$X$1203=""Measles"",'GBD estimates'!$Z$4:$Z$1203=""0 to 6 days (early neonatal)"")"),0.0) -> 0 | V97: =IFERROR(__xludf.DUMMYFUNCTION("FILTER('GBD estimates'!$AF$4:$AF$1203,'GBD estimates'!$AA$4:$AA$1203=V$3,'GBD estimates'!$X$4:$X$1203=""Measles"",'GBD estimates'!$Z$4:$Z$1203=""0 to 6 days (early neonatal)"")"),0.0) -> 0 | W97: =IFERROR(__xludf.DUMMYFUNCTION("FILTER('GBD estimates'!$AF$4:$AF$1203,'GBD estimates'!$AA$4:$AA$1203=W$3,'GBD estimates'!$X$4:$X$1203=""Measles"",'GBD estimates'!$Z$4:$Z$1203=""0 to 6 days (early neonatal)"")"),0.0) -> 0 | X97: =IFERROR(__xludf.DUMMYFUNCTION("FILTER('GBD estimates'!$AF$4:$AF$1203,'GBD estimates'!$AA$4:$AA$1203=X$3,'GBD estimates'!$X$4:$X$1203=""Measles"",'GBD estimates'!$Z$4:$Z$1203=""0 to 6 days (early neonatal)"")"),0.0) -> 0 | Y97: =IFERROR(__xludf.DUMMYFUNCTION("FILTER('GBD estimates'!$AF$4:$AF$1203,'GBD estimates'!$AA$4:$AA$1203=Y$3,'GBD estimates'!$X$4:$X$1203=""Measles"",'GBD estimates'!$Z$4:$Z$1203=""0 to 6 days (early neonatal)"")"),0.0) -> 0 | Z97: =IFERROR(__xludf.DUMMYFUNCTION("FILTER('GBD estimates'!$AF$4:$AF$1203,'GBD estimates'!$AA$4:$AA$1203=Z$3,'GBD estimates'!$X$4:$X$1203=""Measles"",'GBD estimates'!$Z$4:$Z$1203=""0 to 6 days (early neonatal)"")"),0.0) -> 0 | AA97: =IFERROR(__xludf.DUMMYFUNCTION("FILTER('GBD estimates'!$AF$4:$AF$1203,'GBD estimates'!$AA$4:$AA$1203=AA$3,'GBD estimates'!$X$4:$X$1203=""Measles"",'GBD estimates'!$Z$4:$Z$1203=""0 to 6 days (early neonatal)"")"),0.0) -> 0 | AB97: =IFERROR(__xludf.DUMMYFUNCTION("FILTER('GBD estimates'!$AF$4:$AF$1203,'GBD estimates'!$AA$4:$AA$1203=AB$3,'GBD estimates'!$X$4:$X$1203=""Measles"",'GBD estimates'!$Z$4:$Z$1203=""0 to 6 days (early neonatal)"")"),0.0) -> 0 | AC97: =IFERROR(__xludf.DUMMYFUNCTION("FILTER('GBD estimates'!$AF$4:$AF$1203,'GBD estimates'!$AA$4:$AA$1203=AC$3,'GBD estimates'!$X$4:$X$1203=""Measles"",'GBD estimates'!$Z$4:$Z$1203=""0 to 6 days (early neonatal)"")"),0.0) -> 0 | AD97: =IFERROR(__xludf.DUMMYFUNCTION("FILTER('GBD estimates'!$AF$4:$AF$1203,'GBD estimates'!$AA$4:$AA$1203=AD$3,'GBD estimates'!$X$4:$X$1203=""Measles"",'GBD estimates'!$Z$4:$Z$1203=""0 to 6 days (early neonatal)"")"),0.0) -> 0 | AE97: =IFERROR(__xludf.DUMMYFUNCTION("FILTER('GBD estimates'!$AF$4:$AF$1203,'GBD estimates'!$AA$4:$AA$1203=AE$3,'GBD estimates'!$X$4:$X$1203=""Measles"",'GBD estimates'!$Z$4:$Z$1203=""0 to 6 days (early neonatal)"")"),0.0) -> 0 | AF97: =IFERROR(__xludf.DUMMYFUNCTION("FILTER('GBD estimates'!$AF$4:$AF$1203,'GBD estimates'!$AA$4:$AA$1203=AF$3,'GBD estimates'!$X$4:$X$1203=""Measles"",'GBD estimates'!$Z$4:$Z$1203=""0 to 6 days (early neonatal)"")"),0.0) -> 0 | AG97: =IFERROR(__xludf.DUMMYFUNCTION("FILTER('GBD estimates'!$I$4:$I$1203,'GBD estimates'!$C$4:$C$1203=AG$2,'GBD estimates'!$F$4:$F$1203=""Measles"",'GBD estimates'!$E$4:$E$1203=""0-6 days"")"),0.0) -> 0 | AH97: =IFERROR(__xludf.DUMMYFUNCTION("FILTER('GBD estimates'!$I$4:$I$1203,'GBD estimates'!$C$4:$C$1203=AH$2,'GBD estimates'!$F$4:$F$1203=""Measles"",'GBD estimates'!$E$4:$E$1203=""0-6 days"")"),0.0) -> 0 | AI97: =IFERROR(__xludf.DUMMYFUNCTION("FILTER('GBD estimates'!$I$4:$I$1203,'GBD estimates'!$C$4:$C$1203=AI$2,'GBD estimates'!$F$4:$F$1203=""Measles"",'GBD estimates'!$E$4:$E$1203=""0-6 days"")"),0.0) -> 0 | AJ97: =IFERROR(__xludf.DUMMYFUNCTION("FILTER('GBD estimates'!$I$4:$I$1203,'GBD estimates'!$C$4:$C$1203=AJ$2,'GBD estimates'!$F$4:$F$1203=""Measles"",'GBD estimates'!$E$4:$E$1203=""0-6 days"")"),0.0) -> 0 | AL97: GBD 2019
E98: Late neonatal measles mortalities per year (babies between 7 and 27 days old) | F98: # | G98: input | H98: - | I98: =IFERROR(__xludf.DUMMYFUNCTION("FILTER('GBD estimates'!$I$4:$I$1203,'GBD estimates'!$C$4:$C$1203=I$2,'GBD estimates'!$F$4:$F$1203=""Measles"",'GBD estimates'!$E$4:$E$1203=""7-27 days"")"),0.0) -> 0 | J98: =IFERROR(__xludf.DUMMYFUNCTION("FILTER('GBD estimates'!$I$4:$I$1203,'GBD estimates'!$C$4:$C$1203=J$2,'GBD estimates'!$F$4:$F$1203=""Measles"",'GBD estimates'!$E$4:$E$1203=""7-27 days"")"),0.0) -> 0 | K98: =IFERROR(__xludf.DUMMYFUNCTION("FILTER('GBD estimates'!$I$4:$I$1203,'GBD estimates'!$C$4:$C$1203=K$2,'GBD estimates'!$F$4:$F$1203=""Measles"",'GBD estimates'!$E$4:$E$1203=""7-27 days"")"),0.0) -> 0 | L98: =IFERROR(__xludf.DUMMYFUNCTION("FILTER('GBD estimates'!$I$4:$I$1203,'GBD estimates'!$C$4:$C$1203=L$2,'GBD estimates'!$F$4:$F$1203=""Measles"",'GBD estimates'!$E$4:$E$1203=""7-27 days"")"),43.47452123) -> 43.474521 | M98: =IFERROR(__xludf.DUMMYFUNCTION("FILTER('GBD estimates'!$I$4:$I$1203,'GBD estimates'!$C$4:$C$1203=M$2,'GBD estimates'!$F$4:$F$1203=""Measles"",'GBD estimates'!$E$4:$E$1203=""7-27 days"")"),0.0) -> 0 | N98: =IFERROR(__xludf.DUMMYFUNCTION("FILTER('GBD estimates'!$I$4:$I$1203,'GBD estimates'!$C$4:$C$1203=N$2,'GBD estimates'!$F$4:$F$1203=""Measles"",'GBD estimates'!$E$4:$E$1203=""7-27 days"")"),0.0) -> 0 | O98: =IFERROR(__xludf.DUMMYFUNCTION("FILTER('GBD estimates'!$I$4:$I$1203,'GBD estimates'!$C$4:$C$1203=O$2,'GBD estimates'!$F$4:$F$1203=""Measles"",'GBD estimates'!$E$4:$E$1203=""7-27 days"")"),0.0) -> 0 | P98: =IFERROR(__xludf.DUMMYFUNCTION("FILTER('GBD estimates'!$I$4:$I$1203,'GBD estimates'!$C$4:$C$1203=P$2,'GBD estimates'!$F$4:$F$1203=""Measles"",'GBD estimates'!$E$4:$E$1203=""7-27 days"")"),0.0) -> 0 | Q98: =IFERROR(__xludf.DUMMYFUNCTION("FILTER('GBD estimates'!$I$4:$I$1203,'GBD estimates'!$C$4:$C$1203=Q$2,'GBD estimates'!$F$4:$F$1203=""Measles"",'GBD estimates'!$E$4:$E$1203=""7-27 days"")"),0.0) -> 0 | R98: =IFERROR(__xludf.DUMMYFUNCTION("FILTER('GBD estimates'!$AF$4:$AF$1203,'GBD estimates'!$AA$4:$AA$1203=R$3,'GBD estimates'!$X$4:$X$1203=""Measles"",'GBD estimates'!$Z$4:$Z$1203=""7 to 27 days (late neonatal)"")"),0.0) -> 0 | S98: =IFERROR(__xludf.DUMMYFUNCTION("FILTER('GBD estimates'!$AF$4:$AF$1203,'GBD estimates'!$AA$4:$AA$1203=S$3,'GBD estimates'!$X$4:$X$1203=""Measles"",'GBD estimates'!$Z$4:$Z$1203=""7 to 27 days (late neonatal)"")"),0.0) -> 0 | T98: =IFERROR(__xludf.DUMMYFUNCTION("FILTER('GBD estimates'!$AF$4:$AF$1203,'GBD estimates'!$AA$4:$AA$1203=T$3,'GBD estimates'!$X$4:$X$1203=""Measles"",'GBD estimates'!$Z$4:$Z$1203=""7 to 27 days (late neonatal)"")"),0.0) -> 0 | U98: =IFERROR(__xludf.DUMMYFUNCTION("FILTER('GBD estimates'!$AF$4:$AF$1203,'GBD estimates'!$AA$4:$AA$1203=U$3,'GBD estimates'!$X$4:$X$1203=""Measles"",'GBD estimates'!$Z$4:$Z$1203=""7 to 27 days (late neonatal)"")"),0.0) -> 0 | V98: =IFERROR(__xludf.DUMMYFUNCTION("FILTER('GBD estimates'!$AF$4:$AF$1203,'GBD estimates'!$AA$4:$AA$1203=V$3,'GBD estimates'!$X$4:$X$1203=""Measles"",'GBD estimates'!$Z$4:$Z$1203=""7 to 27 days (late neonatal)"")"),0.0) -> 0 | W98: =IFERROR(__xludf.DUMMYFUNCTION("FILTER('GBD estimates'!$AF$4:$AF$1203,'GBD estimates'!$AA$4:$AA$1203=W$3,'GBD estimates'!$X$4:$X$1203=""Measles"",'GBD estimates'!$Z$4:$Z$1203=""7 to 27 days (late neonatal)"")"),0.0) -> 0 | X98: =IFERROR(__xludf.DUMMYFUNCTION("FILTER('GBD estimates'!$AF$4:$AF$1203,'GBD estimates'!$AA$4:$AA$1203=X$3,'GBD estimates'!$X$4:$X$1203=""Measles"",'GBD estimates'!$Z$4:$Z$1203=""7 to 27 days (late neonatal)"")"),0.0) -> 0 | Y98: =IFERROR(__xludf.DUMMYFUNCTION("FILTER('GBD estimates'!$AF$4:$AF$1203,'GBD estimates'!$AA$4:$AA$1203=Y$3,'GBD estimates'!$X$4:$X$1203=""Measles"",'GBD estimates'!$Z$4:$Z$1203=""7 to 27 days (late neonatal)"")"),0.0) -> 0 | Z98: =IFERROR(__xludf.DUMMYFUNCTION("FILTER('GBD estimates'!$AF$4:$AF$1203,'GBD estimates'!$AA$4:$AA$1203=Z$3,'GBD estimates'!$X$4:$X$1203=""Measles"",'GBD estimates'!$Z$4:$Z$1203=""7 to 27 days (late neonatal)"")"),0.0) -> 0 | AA98: =IFERROR(__xludf.DUMMYFUNCTION("FILTER('GBD estimates'!$AF$4:$AF$1203,'GBD estimates'!$AA$4:$AA$1203=AA$3,'GBD estimates'!$X$4:$X$1203=""Measles"",'GBD estimates'!$Z$4:$Z$1203=""7 to 27 days (late neonatal)"")"),0.0) -> 0 | AB98: =IFERROR(__xludf.DUMMYFUNCTION("FILTER('GBD estimates'!$AF$4:$AF$1203,'GBD estimates'!$AA$4:$AA$1203=AB$3,'GBD estimates'!$X$4:$X$1203=""Measles"",'GBD estimates'!$Z$4:$Z$1203=""7 to 27 days (late neonatal)"")"),0.0) -> 0 | AC98: =IFERROR(__xludf.DUMMYFUNCTION("FILTER('GBD estimates'!$AF$4:$AF$1203,'GBD estimates'!$AA$4:$AA$1203=AC$3,'GBD estimates'!$X$4:$X$1203=""Measles"",'GBD estimates'!$Z$4:$Z$1203=""7 to 27 days (late neonatal)"")"),0.0) -> 0 | AD98: =IFERROR(__xludf.DUMMYFUNCTION("FILTER('GBD estimates'!$AF$4:$AF$1203,'GBD estimates'!$AA$4:$AA$1203=AD$3,'GBD estimates'!$X$4:$X$1203=""Measles"",'GBD estimates'!$Z$4:$Z$1203=""7 to 27 days (late neonatal)"")"),0.0) -> 0 | AE98: =IFERROR(__xludf.DUMMYFUNCTION("FILTER('GBD estimates'!$AF$4:$AF$1203,'GBD estimates'!$AA$4:$AA$1203=AE$3,'GBD estimates'!$X$4:$X$1203=""Measles"",'GBD estimates'!$Z$4:$Z$1203=""7 to 27 days (late neonatal)"")"),0.0) -> 0 | AF98: =IFERROR(__xludf.DUMMYFUNCTION("FILTER('GBD estimates'!$AF$4:$AF$1203,'GBD estimates'!$AA$4:$AA$1203=AF$3,'GBD estimates'!$X$4:$X$1203=""Measles"",'GBD estimates'!$Z$4:$Z$1203=""7 to 27 days (late neonatal)"")"),0.0) -> 0 | AG98: =IFERROR(__xludf.DUMMYFUNCTION("FILTER('GBD estimates'!$I$4:$I$1203,'GBD estimates'!$C$4:$C$1203=AG$2,'GBD estimates'!$F$4:$F$1203=""Measles"",'GBD estimates'!$E$4:$E$1203=""7-27 days"")"),0.0) -> 0 | AH98: =IFERROR(__xludf.DUMMYFUNCTION("FILTER('GBD estimates'!$I$4:$I$1203,'GBD estimates'!$C$4:$C$1203=AH$2,'GBD estimates'!$F$4:$F$1203=""Measles"",'GBD estimates'!$E$4:$E$1203=""7-27 days"")"),0.0) -> 0 | AI98: =IFERROR(__xludf.DUMMYFUNCTION("FILTER('GBD estimates'!$I$4:$I$1203,'GBD estimates'!$C$4:$C$1203=AI$2,'GBD estimates'!$F$4:$F$1203=""Measles"",'GBD estimates'!$E$4:$E$1203=""7-27 days"")"),0.0) -> 0 | AJ98: =IFERROR(__xludf.DUMMYFUNCTION("FILTER('GBD estimates'!$I$4:$I$1203,'GBD estimates'!$C$4:$C$1203=AJ$2,'GBD estimates'!$F$4:$F$1203=""Measles"",'GBD estimates'!$E$4:$E$1203=""7-27 days"")"),0.0) -> 0 | AL98: GBD 2019
E99: Post-neonatal measles mortalities per year (babies between 28 and 364 days old) | F99: # | G99: input | H99: - | I99: =IFERROR(__xludf.DUMMYFUNCTION("FILTER('GBD estimates'!$I$4:$I$1203,'GBD estimates'!$C$4:$C$1203=I$2,'GBD estimates'!$F$4:$F$1203=""Measles"",'GBD estimates'!$E$4:$E$1203=""28-364 days"")"),615.9703476) -> 615.97035 | J99: =IFERROR(__xludf.DUMMYFUNCTION("FILTER('GBD estimates'!$I$4:$I$1203,'GBD estimates'!$C$4:$C$1203=J$2,'GBD estimates'!$F$4:$F$1203=""Measles"",'GBD estimates'!$E$4:$E$1203=""28-364 days"")"),528.3430129) -> 528.34301 | K99: =IFERROR(__xludf.DUMMYFUNCTION("FILTER('GBD estimates'!$I$4:$I$1203,'GBD estimates'!$C$4:$C$1203=K$2,'GBD estimates'!$F$4:$F$1203=""Measles"",'GBD estimates'!$E$4:$E$1203=""28-364 days"")"),51.67506087) -> 51.675061 | L99: =IFERROR(__xludf.DUMMYFUNCTION("FILTER('GBD estimates'!$I$4:$I$1203,'GBD estimates'!$C$4:$C$1203=L$2,'GBD estimates'!$F$4:$F$1203=""Measles"",'GBD estimates'!$E$4:$E$1203=""28-364 days"")"),940.0679784) -> 940.06798 | M99: =IFERROR(__xludf.DUMMYFUNCTION("FILTER('GBD estimates'!$I$4:$I$1203,'GBD estimates'!$C$4:$C$1203=M$2,'GBD estimates'!$F$4:$F$1203=""Measles"",'GBD estimates'!$E$4:$E$1203=""28-364 days"")"),252.3160467) -> 252.31605 | N99: =IFERROR(__xludf.DUMMYFUNCTION("FILTER('GBD estimates'!$I$4:$I$1203,'GBD estimates'!$C$4:$C$1203=N$2,'GBD estimates'!$F$4:$F$1203=""Measles"",'GBD estimates'!$E$4:$E$1203=""28-364 days"")"),111.3914527) -> 111.39145 | O99: =IFERROR(__xludf.DUMMYFUNCTION("FILTER('GBD estimates'!$I$4:$I$1203,'GBD estimates'!$C$4:$C$1203=O$2,'GBD estimates'!$F$4:$F$1203=""Measles"",'GBD estimates'!$E$4:$E$1203=""28-364 days"")"),606.3633556) -> 606.36336 | P99: =IFERROR(__xludf.DUMMYFUNCTION("FILTER('GBD estimates'!$I$4:$I$1203,'GBD estimates'!$C$4:$C$1203=P$2,'GBD estimates'!$F$4:$F$1203=""Measles"",'GBD estimates'!$E$4:$E$1203=""28-364 days"")"),674.5752946) -> 674.57529 | Q99: =IFERROR(__xludf.DUMMYFUNCTION("FILTER('GBD estimates'!$I$4:$I$1203,'GBD estimates'!$C$4:$C$1203=Q$2,'GBD estimates'!$F$4:$F$1203=""Measles"",'GBD estimates'!$E$4:$E$1203=""28-364 days"")"),2535.959019) -> 2535.959 | R99: =IFERROR(__xludf.DUMMYFUNCTION("FILTER('GBD estimates'!$AF$4:$AF$1203,'GBD estimates'!$AA$4:$AA$1203=R$3,'GBD estimates'!$X$4:$X$1203=""Measles"",'GBD estimates'!$Z$4:$Z$1203=""28 to 364 days (post neonatal)"")"),13.73704183) -> 13.737042 | S99: =IFERROR(__xludf.DUMMYFUNCTION("FILTER('GBD estimates'!$AF$4:$AF$1203,'GBD estimates'!$AA$4:$AA$1203=S$3,'GBD estimates'!$X$4:$X$1203=""Measles"",'GBD estimates'!$Z$4:$Z$1203=""28 to 364 days (post neonatal)"")"),1.406138079) -> 1.4061381 | T99: =IFERROR(__xludf.DUMMYFUNCTION("FILTER('GBD estimates'!$AF$4:$AF$1203,'GBD estimates'!$AA$4:$AA$1203=T$3,'GBD estimates'!$X$4:$X$1203=""Measles"",'GBD estimates'!$Z$4:$Z$1203=""28 to 364 days (post neonatal)"")"),4.423358327) -> 4.4233583 | U99: =IFERROR(__xludf.DUMMYFUNCTION("FILTER('GBD estimates'!$AF$4:$AF$1203,'GBD estimates'!$AA$4:$AA$1203=U$3,'GBD estimates'!$X$4:$X$1203=""Measles"",'GBD estimates'!$Z$4:$Z$1203=""28 to 364 days (post neonatal)"")"),27.96352296) -> 27.963523 | V99: =IFERROR(__xludf.DUMMYFUNCTION("FILTER('GBD estimates'!$AF$4:$AF$1203,'GBD estimates'!$AA$4:$AA$1203=V$3,'GBD estimates'!$X$4:$X$1203=""Measles"",'GBD estimates'!$Z$4:$Z$1203=""28 to 364 days (post neonatal)"")"),3.76375812) -> 3.7637581 | W99: =IFERROR(__xludf.DUMMYFUNCTION("FILTER('GBD estimates'!$AF$4:$AF$1203,'GBD estimates'!$AA$4:$AA$1203=W$3,'GBD estimates'!$X$4:$X$1203=""Measles"",'GBD estimates'!$Z$4:$Z$1203=""28 to 364 days (post neonatal)"")"),5.388017886) -> 5.3880179 | X99: =IFERROR(__xludf.DUMMYFUNCTION("FILTER('GBD estimates'!$AF$4:$AF$1203,'GBD estimates'!$AA$4:$AA$1203=X$3,'GBD estimates'!$X$4:$X$1203=""Measles"",'GBD estimates'!$Z$4:$Z$1203=""28 to 364 days (post neonatal)"")"),2.585096967) -> 2.585097 | Y99: =IFERROR(__xludf.DUMMYFUNCTION("FILTER('GBD estimates'!$AF$4:$AF$1203,'GBD estimates'!$AA$4:$AA$1203=Y$3,'GBD estimates'!$X$4:$X$1203=""Measles"",'GBD estimates'!$Z$4:$Z$1203=""28 to 364 days (post neonatal)"")"),0.8928297742) -> 0.89282977 | Z99: =IFERROR(__xludf.DUMMYFUNCTION("FILTER('GBD estimates'!$AF$4:$AF$1203,'GBD estimates'!$AA$4:$AA$1203=Z$3,'GBD estimates'!$X$4:$X$1203=""Measles"",'GBD estimates'!$Z$4:$Z$1203=""28 to 364 days (post neonatal)"")"),4.272886535) -> 4.2728865 | AA99: =IFERROR(__xludf.DUMMYFUNCTION("FILTER('GBD estimates'!$AF$4:$AF$1203,'GBD estimates'!$AA$4:$AA$1203=AA$3,'GBD estimates'!$X$4:$X$1203=""Measles"",'GBD estimates'!$Z$4:$Z$1203=""28 to 364 days (post neonatal)"")"),2.477968916) -> 2.4779689 | AB99: =IFERROR(__xludf.DUMMYFUNCTION("FILTER('GBD estimates'!$AF$4:$AF$1203,'GBD estimates'!$AA$4:$AA$1203=AB$3,'GBD estimates'!$X$4:$X$1203=""Measles"",'GBD estimates'!$Z$4:$Z$1203=""28 to 364 days (post neonatal)"")"),10.62345897) -> 10.623459 | AC99: =IFERROR(__xludf.DUMMYFUNCTION("FILTER('GBD estimates'!$AF$4:$AF$1203,'GBD estimates'!$AA$4:$AA$1203=AC$3,'GBD estimates'!$X$4:$X$1203=""Measles"",'GBD estimates'!$Z$4:$Z$1203=""28 to 364 days (post neonatal)"")"),13.68694176) -> 13.686942 | AD99: =IFERROR(__xludf.DUMMYFUNCTION("FILTER('GBD estimates'!$AF$4:$AF$1203,'GBD estimates'!$AA$4:$AA$1203=AD$3,'GBD estimates'!$X$4:$X$1203=""Measles"",'GBD estimates'!$Z$4:$Z$1203=""28 to 364 days (post neonatal)"")"),1.659767365) -> 1.6597674 | AE99: =IFERROR(__xludf.DUMMYFUNCTION("FILTER('GBD estimates'!$AF$4:$AF$1203,'GBD estimates'!$AA$4:$AA$1203=AE$3,'GBD estimates'!$X$4:$X$1203=""Measles"",'GBD estimates'!$Z$4:$Z$1203=""28 to 364 days (post neonatal)"")"),2.107528809) -> 2.1075288 | AF99: =IFERROR(__xludf.DUMMYFUNCTION("FILTER('GBD estimates'!$AF$4:$AF$1203,'GBD estimates'!$AA$4:$AA$1203=AF$3,'GBD estimates'!$X$4:$X$1203=""Measles"",'GBD estimates'!$Z$4:$Z$1203=""28 to 364 days (post neonatal)"")"),32.08340466) -> 32.083405 | AG99: =IFERROR(__xludf.DUMMYFUNCTION("FILTER('GBD estimates'!$I$4:$I$1203,'GBD estimates'!$C$4:$C$1203=AG$2,'GBD estimates'!$F$4:$F$1203=""Measles"",'GBD estimates'!$E$4:$E$1203=""28-364 days"")"),258.3427183) -> 258.34272 | AH99: =IFERROR(__xludf.DUMMYFUNCTION("FILTER('GBD estimates'!$I$4:$I$1203,'GBD estimates'!$C$4:$C$1203=AH$2,'GBD estimates'!$F$4:$F$1203=""Measles"",'GBD estimates'!$E$4:$E$1203=""28-364 days"")"),624.7785238) -> 624.77852 | AI99: =IFERROR(__xludf.DUMMYFUNCTION("FILTER('GBD estimates'!$I$4:$I$1203,'GBD estimates'!$C$4:$C$1203=AI$2,'GBD estimates'!$F$4:$F$1203=""Measles"",'GBD estimates'!$E$4:$E$1203=""28-364 days"")"),12.52153691) -> 12.521537 | AJ99: =IFERROR(__xludf.DUMMYFUNCTION("FILTER('GBD estimates'!$I$4:$I$1203,'GBD estimates'!$C$4:$C$1203=AJ$2,'GBD estimates'!$F$4:$F$1203=""Measles"",'GBD estimates'!$E$4:$E$1203=""28-364 days"")"),1053.356701) -> 1053.3567 | AL99: GBD 2019
C101: Diarrheal disease mortalities per year among people under five
E102: Diarrheal disease mortalities per year among people under age 5 | F102: # | G102: input | H102: - | I102: =IFERROR(__xludf.DUMMYFUNCTION("FILTER('GBD estimates'!$I$4:$I$1203,'GBD estimates'!$C$4:$C$1203=I$2,'GBD estimates'!$F$4:$F$1203=""Diarrheal diseases"",'GBD estimates'!$E$4:$E$1203=""<5 years"")"),9151.731106) -> 9151.7311 | J102: =IFERROR(__xludf.DUMMYFUNCTION("FILTER('GBD estimates'!$I$4:$I$1203,'GBD estimates'!$C$4:$C$1203=J$2,'GBD estimates'!$F$4:$F$1203=""Diarrheal diseases"",'GBD estimates'!$E$4:$E$1203=""<5 years"")"),13471.72799) -> 13471.728 | K102: =IFERROR(__xludf.DUMMYFUNCTION("FILTER('GBD estimates'!$I$4:$I$1203,'GBD estimates'!$C$4:$C$1203=K$2,'GBD estimates'!$F$4:$F$1203=""Diarrheal diseases"",'GBD estimates'!$E$4:$E$1203=""<5 years"")"),3977.855075) -> 3977.8551 | L102: =IFERROR(__xludf.DUMMYFUNCTION("FILTER('GBD estimates'!$I$4:$I$1203,'GBD estimates'!$C$4:$C$1203=L$2,'GBD estimates'!$F$4:$F$1203=""Diarrheal diseases"",'GBD estimates'!$E$4:$E$1203=""<5 years"")"),18979.54673) -> 18979.547 | M102: =IFERROR(__xludf.DUMMYFUNCTION("FILTER('GBD estimates'!$I$4:$I$1203,'GBD estimates'!$C$4:$C$1203=M$2,'GBD estimates'!$F$4:$F$1203=""Diarrheal diseases"",'GBD estimates'!$E$4:$E$1203=""<5 years"")"),2792.805045) -> 2792.805 | N102: =IFERROR(__xludf.DUMMYFUNCTION("FILTER('GBD estimates'!$I$4:$I$1203,'GBD estimates'!$C$4:$C$1203=N$2,'GBD estimates'!$F$4:$F$1203=""Diarrheal diseases"",'GBD estimates'!$E$4:$E$1203=""<5 years"")"),7847.490696) -> 7847.4907 | O102: =IFERROR(__xludf.DUMMYFUNCTION("FILTER('GBD estimates'!$I$4:$I$1203,'GBD estimates'!$C$4:$C$1203=O$2,'GBD estimates'!$F$4:$F$1203=""Diarrheal diseases"",'GBD estimates'!$E$4:$E$1203=""<5 years"")"),10970.43312) -> 10970.433 | P102: =IFERROR(__xludf.DUMMYFUNCTION("FILTER('GBD estimates'!$I$4:$I$1203,'GBD estimates'!$C$4:$C$1203=P$2,'GBD estimates'!$F$4:$F$1203=""Diarrheal diseases"",'GBD estimates'!$E$4:$E$1203=""<5 years"")"),6474.097551) -> 6474.0976 | Q102: =IFERROR(__xludf.DUMMYFUNCTION("FILTER('GBD estimates'!$I$4:$I$1203,'GBD estimates'!$C$4:$C$1203=Q$2,'GBD estimates'!$F$4:$F$1203=""Diarrheal diseases"",'GBD estimates'!$E$4:$E$1203=""<5 years"")"),22975.32483) -> 22975.325 | R102: =IFERROR(__xludf.DUMMYFUNCTION("FILTER('GBD estimates'!$AF$4:$AF$1203,'GBD estimates'!$AA$4:$AA$1203=R$3,'GBD estimates'!$X$4:$X$1203=""Diarrheal diseases"",'GBD estimates'!$Z$4:$Z$1203=""Under 5"")"),1792.518985) -> 1792.519 | S102: =IFERROR(__xludf.DUMMYFUNCTION("FILTER('GBD estimates'!$AF$4:$AF$1203,'GBD estimates'!$AA$4:$AA$1203=S$3,'GBD estimates'!$X$4:$X$1203=""Diarrheal diseases"",'GBD estimates'!$Z$4:$Z$1203=""Under 5"")"),235.8614688) -> 235.86147 | T102: =IFERROR(__xludf.DUMMYFUNCTION("FILTER('GBD estimates'!$AF$4:$AF$1203,'GBD estimates'!$AA$4:$AA$1203=T$3,'GBD estimates'!$X$4:$X$1203=""Diarrheal diseases"",'GBD estimates'!$Z$4:$Z$1203=""Under 5"")"),527.3843021) -> 527.3843 | U102: =IFERROR(__xludf.DUMMYFUNCTION("FILTER('GBD estimates'!$AF$4:$AF$1203,'GBD estimates'!$AA$4:$AA$1203=U$3,'GBD estimates'!$X$4:$X$1203=""Diarrheal diseases"",'GBD estimates'!$Z$4:$Z$1203=""Under 5"")"),2598.681099) -> 2598.6811 | V102: =IFERROR(__xludf.DUMMYFUNCTION("FILTER('GBD estimates'!$AF$4:$AF$1203,'GBD estimates'!$AA$4:$AA$1203=V$3,'GBD estimates'!$X$4:$X$1203=""Diarrheal diseases"",'GBD estimates'!$Z$4:$Z$1203=""Under 5"")"),932.7184668) -> 932.71847 | W102: =IFERROR(__xludf.DUMMYFUNCTION("FILTER('GBD estimates'!$AF$4:$AF$1203,'GBD estimates'!$AA$4:$AA$1203=W$3,'GBD estimates'!$X$4:$X$1203=""Diarrheal diseases"",'GBD estimates'!$Z$4:$Z$1203=""Under 5"")"),863.7292974) -> 863.7293 | X102: =IFERROR(__xludf.DUMMYFUNCTION("FILTER('GBD estimates'!$AF$4:$AF$1203,'GBD estimates'!$AA$4:$AA$1203=X$3,'GBD estimates'!$X$4:$X$1203=""Diarrheal diseases"",'GBD estimates'!$Z$4:$Z$1203=""Under 5"")"),531.9093041) -> 531.9093 | Y102: =IFERROR(__xludf.DUMMYFUNCTION("FILTER('GBD estimates'!$AF$4:$AF$1203,'GBD estimates'!$AA$4:$AA$1203=Y$3,'GBD estimates'!$X$4:$X$1203=""Diarrheal diseases"",'GBD estimates'!$Z$4:$Z$1203=""Under 5"")"),261.3046733) -> 261.30467 | Z102: =IFERROR(__xludf.DUMMYFUNCTION("FILTER('GBD estimates'!$AF$4:$AF$1203,'GBD estimates'!$AA$4:$AA$1203=Z$3,'GBD estimates'!$X$4:$X$1203=""Diarrheal diseases"",'GBD estimates'!$Z$4:$Z$1203=""Under 5"")"),684.6036095) -> 684.60361 | AA102: =IFERROR(__xludf.DUMMYFUNCTION("FILTER('GBD estimates'!$AF$4:$AF$1203,'GBD estimates'!$AA$4:$AA$1203=AA$3,'GBD estimates'!$X$4:$X$1203=""Diarrheal diseases"",'GBD estimates'!$Z$4:$Z$1203=""Under 5"")"),358.9317813) -> 358.93178 | AB102: =IFERROR(__xludf.DUMMYFUNCTION("FILTER('GBD estimates'!$AF$4:$AF$1203,'GBD estimates'!$AA$4:$AA$1203=AB$3,'GBD estimates'!$X$4:$X$1203=""Diarrheal diseases"",'GBD estimates'!$Z$4:$Z$1203=""Under 5"")"),1488.494934) -> 1488.4949 | AC102: =IFERROR(__xludf.DUMMYFUNCTION("FILTER('GBD estimates'!$AF$4:$AF$1203,'GBD estimates'!$AA$4:$AA$1203=AC$3,'GBD estimates'!$X$4:$X$1203=""Diarrheal diseases"",'GBD estimates'!$Z$4:$Z$1203=""Under 5"")"),1961.576696) -> 1961.5767 | AD102: =IFERROR(__xludf.DUMMYFUNCTION("FILTER('GBD estimates'!$AF$4:$AF$1203,'GBD estimates'!$AA$4:$AA$1203=AD$3,'GBD estimates'!$X$4:$X$1203=""Diarrheal diseases"",'GBD estimates'!$Z$4:$Z$1203=""Under 5"")"),331.6713724) -> 331.67137 | AE102: =IFERROR(__xludf.DUMMYFUNCTION("FILTER('GBD estimates'!$AF$4:$AF$1203,'GBD estimates'!$AA$4:$AA$1203=AE$3,'GBD estimates'!$X$4:$X$1203=""Diarrheal diseases"",'GBD estimates'!$Z$4:$Z$1203=""Under 5"")"),698.5771604) -> 698.57716 | AF102: =IFERROR(__xludf.DUMMYFUNCTION("FILTER('GBD estimates'!$AF$4:$AF$1203,'GBD estimates'!$AA$4:$AA$1203=AF$3,'GBD estimates'!$X$4:$X$1203=""Diarrheal diseases"",'GBD estimates'!$Z$4:$Z$1203=""Under 5"")"),4971.836451) -> 4971.8365 | AG102: =IFERROR(__xludf.DUMMYFUNCTION("FILTER('GBD estimates'!$I$4:$I$1203,'GBD estimates'!$C$4:$C$1203=AG$2,'GBD estimates'!$F$4:$F$1203=""Diarrheal diseases"",'GBD estimates'!$E$4:$E$1203=""<5 years"")"),7087.81383) -> 7087.8138 | AH102: =IFERROR(__xludf.DUMMYFUNCTION("FILTER('GBD estimates'!$I$4:$I$1203,'GBD estimates'!$C$4:$C$1203=AH$2,'GBD estimates'!$F$4:$F$1203=""Diarrheal diseases"",'GBD estimates'!$E$4:$E$1203=""<5 years"")"),25058.80896) -> 25058.809 | AI102: =IFERROR(__xludf.DUMMYFUNCTION("FILTER('GBD estimates'!$I$4:$I$1203,'GBD estimates'!$C$4:$C$1203=AI$2,'GBD estimates'!$F$4:$F$1203=""Diarrheal diseases"",'GBD estimates'!$E$4:$E$1203=""<5 years"")"),4191.828969) -> 4191.829 | AJ102: =IFERROR(__xludf.DUMMYFUNCTION("FILTER('GBD estimates'!$I$4:$I$1203,'GBD estimates'!$C$4:$C$1203=AJ$2,'GBD estimates'!$F$4:$F$1203=""Diarrheal diseases"",'GBD estimates'!$E$4:$E$1203=""<5 years"")"),4492.678036) -> 4492.678 | AL102: GBD 2019
E103: Early neonatal diarrheal disease mortalities per year (babies under 7 days old) | F103: # | G103: input | H103: - | I103: =IFERROR(__xludf.DUMMYFUNCTION("FILTER('GBD estimates'!$I$4:$I$1203,'GBD estimates'!$C$4:$C$1203=I$2,'GBD estimates'!$F$4:$F$1203=""Diarrheal diseases"",'GBD estimates'!$E$4:$E$1203=""0-6 days"")"),138.9292767) -> 138.92928 | J103: =IFERROR(__xludf.DUMMYFUNCTION("FILTER('GBD estimates'!$I$4:$I$1203,'GBD estimates'!$C$4:$C$1203=J$2,'GBD estimates'!$F$4:$F$1203=""Diarrheal diseases"",'GBD estimates'!$E$4:$E$1203=""0-6 days"")"),290.1973452) -> 290.19735 | K103: =IFERROR(__xludf.DUMMYFUNCTION("FILTER('GBD estimates'!$I$4:$I$1203,'GBD estimates'!$C$4:$C$1203=K$2,'GBD estimates'!$F$4:$F$1203=""Diarrheal diseases"",'GBD estimates'!$E$4:$E$1203=""0-6 days"")"),108.5208194) -> 108.52082 | L103: =IFERROR(__xludf.DUMMYFUNCTION("FILTER('GBD estimates'!$I$4:$I$1203,'GBD estimates'!$C$4:$C$1203=L$2,'GBD estimates'!$F$4:$F$1203=""Diarrheal diseases"",'GBD estimates'!$E$4:$E$1203=""0-6 days"")"),725.0958856) -> 725.09589 | M103: =IFERROR(__xludf.DUMMYFUNCTION("FILTER('GBD estimates'!$I$4:$I$1203,'GBD estimates'!$C$4:$C$1203=M$2,'GBD estimates'!$F$4:$F$1203=""Diarrheal diseases"",'GBD estimates'!$E$4:$E$1203=""0-6 days"")"),61.52402053) -> 61.524021 | N103: =IFERROR(__xludf.DUMMYFUNCTION("FILTER('GBD estimates'!$I$4:$I$1203,'GBD estimates'!$C$4:$C$1203=N$2,'GBD estimates'!$F$4:$F$1203=""Diarrheal diseases"",'GBD estimates'!$E$4:$E$1203=""0-6 days"")"),637.9846233) -> 637.98462 | O103: =IFERROR(__xludf.DUMMYFUNCTION("FILTER('GBD estimates'!$I$4:$I$1203,'GBD estimates'!$C$4:$C$1203=O$2,'GBD estimates'!$F$4:$F$1203=""Diarrheal diseases"",'GBD estimates'!$E$4:$E$1203=""0-6 days"")"),315.1634272) -> 315.16343 | P103: =IFERROR(__xludf.DUMMYFUNCTION("FILTER('GBD estimates'!$I$4:$I$1203,'GBD estimates'!$C$4:$C$1203=P$2,'GBD estimates'!$F$4:$F$1203=""Diarrheal diseases"",'GBD estimates'!$E$4:$E$1203=""0-6 days"")"),196.5409199) -> 196.54092 | Q103: =IFERROR(__xludf.DUMMYFUNCTION("FILTER('GBD estimates'!$I$4:$I$1203,'GBD estimates'!$C$4:$C$1203=Q$2,'GBD estimates'!$F$4:$F$1203=""Diarrheal diseases"",'GBD estimates'!$E$4:$E$1203=""0-6 days"")"),284.0441729) -> 284.04417 | R103: =IFERROR(__xludf.DUMMYFUNCTION("FILTER('GBD estimates'!$AF$4:$AF$1203,'GBD estimates'!$AA$4:$AA$1203=R$3,'GBD estimates'!$X$4:$X$1203=""Diarrheal diseases"",'GBD estimates'!$Z$4:$Z$1203=""0 to 6 days (early neonatal)"")"),27.40055133) -> 27.400551 | S103: =IFERROR(__xludf.DUMMYFUNCTION("FILTER('GBD estimates'!$AF$4:$AF$1203,'GBD estimates'!$AA$4:$AA$1203=S$3,'GBD estimates'!$X$4:$X$1203=""Diarrheal diseases"",'GBD estimates'!$Z$4:$Z$1203=""0 to 6 days (early neonatal)"")"),11.54580852) -> 11.545809 | T103: =IFERROR(__xludf.DUMMYFUNCTION("FILTER('GBD estimates'!$AF$4:$AF$1203,'GBD estimates'!$AA$4:$AA$1203=T$3,'GBD estimates'!$X$4:$X$1203=""Diarrheal diseases"",'GBD estimates'!$Z$4:$Z$1203=""0 to 6 days (early neonatal)"")"),24.09495771) -> 24.094958 | U103: =IFERROR(__xludf.DUMMYFUNCTION("FILTER('GBD estimates'!$AF$4:$AF$1203,'GBD estimates'!$AA$4:$AA$1203=U$3,'GBD estimates'!$X$4:$X$1203=""Diarrheal diseases"",'GBD estimates'!$Z$4:$Z$1203=""0 to 6 days (early neonatal)"")"),56.43793913) -> 56.437939 | V103: =IFERROR(__xludf.DUMMYFUNCTION("FILTER('GBD estimates'!$AF$4:$AF$1203,'GBD estimates'!$AA$4:$AA$1203=V$3,'GBD estimates'!$X$4:$X$1203=""Diarrheal diseases"",'GBD estimates'!$Z$4:$Z$1203=""0 to 6 days (early neonatal)"")"),22.96305318) -> 22.963053 | W103: =IFERROR(__xludf.DUMMYFUNCTION("FILTER('GBD estimates'!$AF$4:$AF$1203,'GBD estimates'!$AA$4:$AA$1203=W$3,'GBD estimates'!$X$4:$X$1203=""Diarrheal diseases"",'GBD estimates'!$Z$4:$Z$1203=""0 to 6 days (early neonatal)"")"),19.58391461) -> 19.583915 | X103: =IFERROR(__xludf.DUMMYFUNCTION("FILTER('GBD estimates'!$AF$4:$AF$1203,'GBD estimates'!$AA$4:$AA$1203=X$3,'GBD estimates'!$X$4:$X$1203=""Diarrheal diseases"",'GBD estimates'!$Z$4:$Z$1203=""0 to 6 days (early neonatal)"")"),17.45744143) -> 17.457441 | Y103: =IFERROR(__xludf.DUMMYFUNCTION("FILTER('GBD estimates'!$AF$4:$AF$1203,'GBD estimates'!$AA$4:$AA$1203=Y$3,'GBD estimates'!$X$4:$X$1203=""Diarrheal diseases"",'GBD estimates'!$Z$4:$Z$1203=""0 to 6 days (early neonatal)"")"),8.35399898) -> 8.353999 | Z103: =IFERROR(__xludf.DUMMYFUNCTION("FILTER('GBD estimates'!$AF$4:$AF$1203,'GBD estimates'!$AA$4:$AA$1203=Z$3,'GBD estimates'!$X$4:$X$1203=""Diarrheal diseases"",'GBD estimates'!$Z$4:$Z$1203=""0 to 6 days (early neonatal)"")"),38.53956214) -> 38.539562 | AA103: =IFERROR(__xludf.DUMMYFUNCTION("FILTER('GBD estimates'!$AF$4:$AF$1203,'GBD estimates'!$AA$4:$AA$1203=AA$3,'GBD estimates'!$X$4:$X$1203=""Diarrheal diseases"",'GBD estimates'!$Z$4:$Z$1203=""0 to 6 days (early neonatal)"")"),11.53787961) -> 11.53788 | AB103: =IFERROR(__xludf.DUMMYFUNCTION("FILTER('GBD estimates'!$AF$4:$AF$1203,'GBD estimates'!$AA$4:$AA$1203=AB$3,'GBD estimates'!$X$4:$X$1203=""Diarrheal diseases"",'GBD estimates'!$Z$4:$Z$1203=""0 to 6 days (early neonatal)"")"),32.05425906) -> 32.054259 | AC103: =IFERROR(__xludf.DUMMYFUNCTION("FILTER('GBD estimates'!$AF$4:$AF$1203,'GBD estimates'!$AA$4:$AA$1203=AC$3,'GBD estimates'!$X$4:$X$1203=""Diarrheal diseases"",'GBD estimates'!$Z$4:$Z$1203=""0 to 6 days (early neonatal)"")"),58.34086374) -> 58.340864 | AD103: =IFERROR(__xludf.DUMMYFUNCTION("FILTER('GBD estimates'!$AF$4:$AF$1203,'GBD estimates'!$AA$4:$AA$1203=AD$3,'GBD estimates'!$X$4:$X$1203=""Diarrheal diseases"",'GBD estimates'!$Z$4:$Z$1203=""0 to 6 days (early neonatal)"")"),17.17300355) -> 17.173004 | AE103: =IFERROR(__xludf.DUMMYFUNCTION("FILTER('GBD estimates'!$AF$4:$AF$1203,'GBD estimates'!$AA$4:$AA$1203=AE$3,'GBD estimates'!$X$4:$X$1203=""Diarrheal diseases"",'GBD estimates'!$Z$4:$Z$1203=""0 to 6 days (early neonatal)"")"),20.83510073) -> 20.835101 | AF103: =IFERROR(__xludf.DUMMYFUNCTION("FILTER('GBD estimates'!$AF$4:$AF$1203,'GBD estimates'!$AA$4:$AA$1203=AF$3,'GBD estimates'!$X$4:$X$1203=""Diarrheal diseases"",'GBD estimates'!$Z$4:$Z$1203=""0 to 6 days (early neonatal)"")"),70.61424279) -> 70.614243 | AG103: =IFERROR(__xludf.DUMMYFUNCTION("FILTER('GBD estimates'!$I$4:$I$1203,'GBD estimates'!$C$4:$C$1203=AG$2,'GBD estimates'!$F$4:$F$1203=""Diarrheal diseases"",'GBD estimates'!$E$4:$E$1203=""0-6 days"")"),127.5268529) -> 127.52685 | AH103: =IFERROR(__xludf.DUMMYFUNCTION("FILTER('GBD estimates'!$I$4:$I$1203,'GBD estimates'!$C$4:$C$1203=AH$2,'GBD estimates'!$F$4:$F$1203=""Diarrheal diseases"",'GBD estimates'!$E$4:$E$1203=""0-6 days"")"),584.7971654) -> 584.79717 | AI103: =IFERROR(__xludf.DUMMYFUNCTION("FILTER('GBD estimates'!$I$4:$I$1203,'GBD estimates'!$C$4:$C$1203=AI$2,'GBD estimates'!$F$4:$F$1203=""Diarrheal diseases"",'GBD estimates'!$E$4:$E$1203=""0-6 days"")"),141.5992773) -> 141.59928 | AJ103: =IFERROR(__xludf.DUMMYFUNCTION("FILTER('GBD estimates'!$I$4:$I$1203,'GBD estimates'!$C$4:$C$1203=AJ$2,'GBD estimates'!$F$4:$F$1203=""Diarrheal diseases"",'GBD estimates'!$E$4:$E$1203=""0-6 days"")"),149.9941463) -> 149.99415 | AL103: GBD 2019
