Workbook

Sheet Key
A1: Guide to interpreting this cost-effectiveness analysis
A2: Sheet descriptions
E4: Main CEA | F4: This sheet contains the primary calculations that result in final cost-effectiveness estimates. This sheet draws on inputs from the "Inputs" sheet and inputs calculated in the other supplemental sheets listed below.
E5: Counterfactual malaria | F5: This sheet contains our calculations of how high malaria mortality and prevalence rates would be in the absence of SMC campaigns.
E6: Leverage/Funging | F6: This sheet contains our calculations of the impact that crowding in and crowding out funding by other contributors has on the benefits of the program.
E7: Inputs | F7: This sheet contains all of the manually entered input values informing the CEA, along with the sources and reasoning supporting them. This sheet also contains inputs sourced from the "GBD estimates" sheet.
E8: GBD estimates | F8: This sheet contains disease burden and population datasets downloaded from the Institute of Health Metrics (IHME)'s Global Burden of Disease (GBD) project.
E9: Simple CEA | F9: This sheet contains a simplified version of the CEA that is designed to be comparable to our CEAs of other programs.
E10: Sensitivity analysis | F10: This sheet contains the outputs of a sensitivity analysis macro that tests the cost-effectiveness ranges that would result from updating certain inputs to their 25th or 75th percentile values.
A12: Terminology key
C14: Terms specific to this CEA
E15: SMC season | F15: The part of the year when SMC is delivered because malaria transmission is highest. In locations where GiveWell currently supports SMC, this is either four or five months each year.
E16: SMC cycle | F16: Refers to a monthly SMC treatment cycle, which consists of a three-day treatment regimen of SMC medication that provides protection from malaria for one month.
E17: SMC round | F17: Refers to a year's worth of SMC cycles, which are typically delievered over a period of four to five consecutive months during the rainy season.
E18: Sahel | F18: A subregion of Africa where malaria transmission tends to be highly seasonal. Historically, SMC was only delivered at large scale within the Sahel. Since 2020-21, SMC is now being piloted in locations outside the Sahel.
E19: Malaria-attributable mortality | F19: Deaths that could be averted by SMC, either directly (because they are malaria deaths) or indirectly (because malaria indirectly increases the risk of death from other causes).
E20: Indirect malaria deaths | F20: Deaths in which malaria plays a causal role, but are attributed to another cause. For example, malaria may increase the likelihood of death from malnutrition or other infectious diseases. Malaria control interventions often have a larger effect on all-cause mortality than would be expected exclusively from declines in malaria-specific mortality, which we interpret as evidence that averting malaria may also avert deaths attributed to other causes.
C22: Terms used across GiveWell's CEAs
E23: Internal validity | F23: Describes an adjustment we make to the treatment effect of an intervention to account for the possibility that the treatment effects found in studies may not represent the true effect the intervention had on the populations studied.
E24: External validity | F24: Describes an adjustment we make to the treatment effect of an intervention to account for differences in the program implementation or populations treated in studies from the program implementation or populations treated by grantee programs.
E25: Leverage | F25: Describes a situation where a grantee's spending on a program causes other organizations or governments to contribute more to the program than they otherwise would have. In most cases, accounting for leverage increases cost-effectiveness
E26: Funging | F26: Describes a situation where a grantee's spending on a program causes other organizations or governments to contribute less to the program than they otherwise would have. In most cases, accounting for funging decreases cost-effectiveness.
E27: Counterfactual | F27: In most cases, describes the state of the world that would exist if we did not provide funding to a grantee for a program. When discussing the "counterfactual value of other actors' spending," we are referring to how much benefit another organization's or government's spending would generate if it were spent on something other than the grantee program.
E28: Moral weights | F28: To compare cost-effectiveness across different programs, we use ‘moral weights’ to quantify the benefits of different program impacts (e.g. increased income vs reduced deaths). We benchmark the value of each benefit to a value of 1, which we define as the value of doubling someone’s consumption for one year.
E29: Philanthropic actors | F29: Non-governmental organizations (NGOs) providing funding to philanthropic programs.
A31: Unit and source key
C33: Unit labels used in the CEA
E34: # | F34: Number
E35: per 1k | F35: Rate per 1,000
E36: per 100k | F36: Rate per 100,000
E37: $ | F37: U.S. dollars
E38: ln($) | F38: The natural logarithm of a monetary value
E39: % | F39: Percentage
E40: ppt | F40: Percentage points
E41: UoV | F41: Units of value: an arbitrary unit GiveWell uses to compare the moral value of different types of outcomes, such as saving lives or increasing income
E42: xbenchmark | F42: Cost-effectiveness in terms of multiples of GiveWell's benchmark
C44: Source labels used in the CEA
E46: input | F46: A value pulled from the "Inputs" sheet
E47: calc | F47: A value calculated using other values in the same sheet
E48: supp | F48: A value pulled from one of the sheets hosting supplemental calculations
E49: main | F49: A value pulled fom the "Main CEA" sheet
E50: feed | F50: A value pulled from an earlier section within the same sheet
A52: GiveWell analyses informing this model
C54: Analyses specific to this CEA
E55: GW's analysis of Malaria Consortium's cost per SMC cycle administered
E56: GW's analysis of the number of SMC cycles delivered per year
E57: GW's analysis of the indirect effects of Malaria Consortium's SMC programs relative to Cisse et al. 2016
E58: GW's analysis of SMC coverage in trials
E59: GW's analysis of malaria income effect size
E60: GW's analysis of subnational mortality rates for SMC
E61: GW's analysis of leverage and funging risk for SMC
C63: Analyses referenced across GiveWell's CEAs
E64: GW's moral weights and discount rate
E65: GW's analysis on estimating multiplier for benefits experienced by other household members
E66: GW's supplemental intervention-level adjustments
E67: GWs benchmark for evaluating cost effectiveness
E68: GW's analysis of the counterfactual value of other actors' spending
E69: GW's analysis of the counterfactual value of Global Fund spending

Sheet Main CEA
I1: Malaria Consortium | R1: Malaria Consortium
I2: Burkina Faso | J2: Chad | K2: DRC | L2: DRC | M2: DRC | N2: DRC | O2: Mozambique | P2: Nigeria | Q2: Nigeria | R2: Nigeria | S2: Nigeria | T2: Nigeria | U2: Nigeria | V2: Nigeria | W2: Nigeria | X2: Nigeria | Y2: Togo | Z2: Uganda
A3: Main calculations | F3: unit | G3: type | H3: Overall | K3: Haut-Katanga | L3: Haut-Lomami | M3: Lualaba | N3: Tanganyika | O3: Nampula | P3: Bauchi | Q3: Borno | R3: FCT (Abuja) | S3: Kebbi | T3: Kogi | U3: Nasarawa | V3: Oyo | W3: Plateau | X3: Sokoto | Z3: Karamoja
E4: Final cost-effectiveness estimate (pulled from below for visibility) | F4: =F191 -> xbenchmark | G4: feed | H4: =H191 -> - | I4: =I191 -> 18.017467 | J4: =J191 -> 8.0191284 | K4: =K191 -> 7.8521256 | L4: =L191 -> 9.2460297 | M4: =M191 -> 9.1012718 | N4: =N191 -> 12.57331 | O4: =O191 -> 11.495836 | ... Z4: =Z191 -> 10.360783
A5: Costs
C7: GiveWell costs
E8: Grant size | F8: =Inputs!F8 -> $ | G8: =Inputs!G8 -> input | H8: =Inputs!H8 -> 1000000 | I8: =Inputs!I8 -> - | J8: =Inputs!J8 -> - | K8: =Inputs!K8 -> - | L8: =Inputs!L8 -> - | M8: =Inputs!M8 -> - | ... Z8: =Inputs!Z8 -> -
C10: Cost breakdown
E11: Percentage of total costs covered by the grantee | F11: =Inputs!F11 -> % | G11: =Inputs!G11 -> input | H11: =Inputs!H11 -> - | I11: =Inputs!I11 -> 0.8872139 | J11: =Inputs!J11 -> 0.8943595 | K11: =Inputs!K11 -> 0.8943595 | L11: =Inputs!L11 -> 0.8943595 | M11: =Inputs!M11 -> 0.8943595 | ... Z11: =Inputs!Z11 -> 0.8943595
E12: Percentage of total costs covered by other philanthropic actors | F12: =Inputs!F12 -> % | G12: =Inputs!G12 -> input | H12: =Inputs!H12 -> - | I12: =Inputs!I12 -> 0.0081278 | J12: =Inputs!J12 -> 0 | K12: =Inputs!K12 -> 0 | L12: =Inputs!L12 -> 0 | M12: =Inputs!M12 -> 0 | ... Z12: =Inputs!Z12 -> 0
E13: Percentage of total costs covered by domestic governments | F13: =Inputs!F13 -> % | G13: =Inputs!G13 -> input | H13: =Inputs!H13 -> - | I13: =Inputs!I13 -> 0.1046583 | J13: =Inputs!J13 -> 0.1056405 | K13: =Inputs!K13 -> 0.1056405 | L13: =Inputs!L13 -> 0.1056405 | M13: =Inputs!M13 -> 0.1056405 | ... Z13: =Inputs!Z13 -> 0.1056405
C15: Total costs
E16: Total spending by all contributors | F16: $ | G16: calc | H16: - | I16: =IF(I8="-",$H8/I11,I8/I11) -> 1127123.9 | J16: =IF(J8="-",$H8/J11,J8/J11) -> 1118118.6 | K16: =IF(K8="-",$H8/K11,K8/K11) -> 1118118.6 | L16: =IF(L8="-",$H8/L11,L8/L11) -> 1118118.6 | M16: =IF(M8="-",$H8/M11,M8/M11) -> 1118118.6 | N16: =IF(N8="-",$H8/N11,N8/N11) -> 1118118.6 | O16: =IF(O8="-",$H8/O11,O8/O11) -> 1118118.6 | P16: =IF(P8="-",$H8/P11,P8/P11) -> 1162184.7 | ... Z16: =IF(Z8="-",$H8/Z11,Z8/Z11) -> 1118118.6
C18: Total spending attributable to different actors
E19: Total spending contributed by grantee | F19: $ | G19: calc | H19: - | I19: =I$16*I11 -> 1000000 | J19: =J$16*J11 -> 1000000 | K19: =K$16*K11 -> 1000000 | L19: =L$16*L11 -> 1000000 | M19: =M$16*M11 -> 1000000 | N19: =N$16*N11 -> 1000000 | O19: =O$16*O11 -> 1000000 | P19: =P$16*P11 -> 1000000 | ... Z19: =Z$16*Z11 -> 1000000
E20: Total spending contributed by other philanthropic actors | F20: $ | G20: calc | H20: - | I20: =I$16*I12 -> 9161.0377 | J20: =J$16*J12 -> 0 | K20: =K$16*K12 -> 0 | L20: =L$16*L12 -> 0 | M20: =M$16*M12 -> 0 | N20: =N$16*N12 -> 0 | O20: =O$16*O12 -> 0 | P20: =P$16*P12 -> 44631.497 | ... Z20: =Z$16*Z12 -> 0
E21: Total spending contributed by domestic governments | F21: $ | G21: calc | H21: - | I21: =I$16*I13 -> 117962.87 | J21: =J$16*J13 -> 118118.61 | K21: =K$16*K13 -> 118118.61 | L21: =L$16*L13 -> 118118.61 | M21: =M$16*M13 -> 118118.61 | N21: =N$16*N13 -> 118118.61 | O21: =O$16*O13 -> 118118.61 | P21: =P$16*P13 -> 117553.24 | ... Z21: =Z$16*Z13 -> 118118.61
C23: Upstream / downstream spending
E24: Total spending causally upstream of donations to grantee | F24: $ | G24: calc | H24: - | I24: =SUM(I19:I20) -> 1009161 | J24: =SUM(J19:J20) -> 1000000 | K24: =SUM(K19:K20) -> 1000000 | L24: =SUM(L19:L20) -> 1000000 | M24: =SUM(M19:M20) -> 1000000 | N24: =SUM(N19:N20) -> 1000000 | O24: =SUM(O19:O20) -> 1000000 | P24: =SUM(P19:P20) -> 1044631.5 | ... Z24: =SUM(Z19:Z20) -> 1000000
E25: Total spending causally downstream of donations to grantee | F25: $ | G25: calc | H25: - | I25: =I21 -> 117962.87 | J25: =J21 -> 118118.61 | K25: =K21 -> 118118.61 | L25: =L21 -> 118118.61 | M25: =M21 -> 118118.61 | N25: =N21 -> 118118.61 | O25: =O21 -> 118118.61 | P25: =P21 -> 117553.24 | ... Z25: =Z21 -> 118118.61
C27: Cost per child covered
E28: Cost per seasonal malaria chemoprevention (SMC) cycle administered | F28: =Inputs!F16 -> $ | G28: =Inputs!G16 -> input | H28: =Inputs!H16 -> - | I28: =Inputs!I16 -> 1.47763 | J28: =Inputs!J16 -> 1.81008 | K28: =Inputs!K16 -> 1.81008 | L28: =Inputs!L16 -> 1.81008 | M28: =Inputs!M16 -> 1.81008 | ... Z28: =Inputs!Z16 -> 1.81008
E29: Number of SMC cycles per year | F29: =Inputs!F17 -> # | G29: =Inputs!G17 -> input | H29: =Inputs!H17 -> - | I29: =Inputs!I17 -> 4.3 | J29: =Inputs!J17 -> 4 | K29: =Inputs!K17 -> 4 | L29: =Inputs!L17 -> 4 | M29: =Inputs!M17 -> 4 | ... Z29: =Inputs!Z17 -> 5
E30: Total cost per child treated with all cycles of SMC in a year | F30: $ | G30: calc | H30: - | I30: =I28*I29 -> 6.353809 | J30: =J28*J29 -> 7.24032 | K30: =K28*K29 -> 7.24032 | L30: =L28*L29 -> 7.24032 | M30: =M28*M29 -> 7.24032 | N30: =N28*N29 -> 7.24032 | O30: =O28*O29 -> 7.24032 | P30: =P28*P29 -> 5.6102 | ... Z30: =Z28*Z29 -> 9.0504
E31: Upstream costs per child treated with all cycles of SMC in a year | F31: $ | G31: calc | H31: - | I31: =(I24/I16)*I30 -> 5.6888302 | J31: =(J24/J16)*J30 -> 6.475449 | K31: =(K24/K16)*K30 -> 6.475449 | L31: =(L24/L16)*L30 -> 6.475449 | M31: =(M24/M16)*M30 -> 6.475449 | N31: =(N24/N16)*N30 -> 6.475449 | O31: =(O24/O16)*O30 -> 6.475449 | P31: =(P24/P16)*P30 -> 5.0427367 | ... Z31: =(Z24/Z16)*Z30 -> 8.0943112
A33: Outputs
C35: Total children covered
E36: Total people under age 5 receiving a year of SMC | F36: # | G36: calc | H36: - | I36: =I19/I31 -> 175783.06 | J36: =J19/J31 -> 154429.45 | K36: =K19/K31 -> 154429.45 | L36: =L19/L31 -> 154429.45 | M36: =M19/M31 -> 154429.45 | N36: =N19/N31 -> 154429.45 | O36: =O19/O31 -> 154429.45 | P36: =P19/P31 -> 198305.02 | ... Z36: =Z19/Z31 -> 123543.56
A38: Outcomes
C40: Mortality reduction among people under age 5 (treated population)
E41: Reduction in malaria incidence for children under age 5 targeted for SMC found in GiveWell's adjusted version of the Meremikwu et al. 2012 meta-analysis | F41: =Inputs!F45 -> % | G41: =Inputs!G45 -> input | H41: =Inputs!H45 -> 0.75 | I41: =Inputs!I45 -> - | J41: =Inputs!J45 -> - | K41: =Inputs!K45 -> - | L41: =Inputs!L45 -> - | M41: =Inputs!M45 -> - | ... Z41: =Inputs!Z45 -> -
E42: Estimated proportion of children targeted for SMC in trials that received SMC | F42: =Inputs!F46 -> % | G42: =Inputs!G46 -> input | H42: =Inputs!H46 -> 0.8977 | I42: - | J42: - | K42: - | L42: - | M42: - | N42: - | O42: - | P42: - | Q42: - | R42: - | S42: - | T42: - | U42: - | V42: - | W42: - | X42: - | Y42: - | Z42: -
E43: Implied reduction in malaria incidence among children under age 5 receiving SMC | F43: % | G43: calc | H43: =H41/H42 -> 0.83546842 | I43: - | J43: - | K43: - | L43: - | M43: - | N43: - | O43: - | P43: - | Q43: - | R43: - | S43: - | T43: - | U43: - | V43: - | W43: - | X43: - | Y43: - | Z43: -
E44: Internal validity adjustment | F44: =Inputs!F47 -> % | G44: =Inputs!G47 -> input | H44: =Inputs!H47 -> -0.05 | I44: =Inputs!I47 -> - | J44: =Inputs!J47 -> - | K44: =Inputs!K47 -> - | L44: =Inputs!L47 -> - | M44: =Inputs!M47 -> - | ... Z44: =Inputs!Z47 -> -
E45: External validity adjustment | F45: =Inputs!F48 -> % | G45: =Inputs!G48 -> input | H45: =Inputs!H48 -> 0 | I45: =Inputs!I48 -> - | J45: =Inputs!J48 -> - | K45: =Inputs!K48 -> - | L45: =Inputs!L48 -> - | M45: =Inputs!M48 -> - | ... Z45: =Inputs!Z48 -> -
E46: Adjustment for lower effectiveness outside the Sahel region of Africa | F46: =Inputs!F49 -> % | G46: =Inputs!G49 -> input | H46: =Inputs!H49 -> - | I46: =Inputs!I49 -> 0 | J46: =Inputs!J49 -> 0 | K46: =Inputs!K49 -> -0.1955888 | L46: =Inputs!L49 -> -0.1955888 | M46: =Inputs!M49 -> -0.1955888 | ... Z46: =Inputs!Z49 -> -0.1955888
E47: Expected reduction in malaria incidence among children under age 5 receiving SMC | F47: % | G47: calc | H47: - | I47: =$H43*(1+$H44)*(1+$H45)*(1+I46) -> 0.793695 | J47: =$H43*(1+$H44)*(1+$H45)*(1+J46) -> 0.793695 | K47: =$H43*(1+$H44)*(1+$H45)*(1+K46) -> 0.63845715 | L47: =$H43*(1+$H44)*(1+$H45)*(1+L46) -> 0.63845715 | M47: =$H43*(1+$H44)*(1+$H45)*(1+M46) -> 0.63845715 | N47: =$H43*(1+$H44)*(1+$H45)*(1+N46) -> 0.63845715 | O47: =$H43*(1+$H44)*(1+$H45)*(1+O46) -> 0.63845715 | P47: =$H43*(1+$H44)*(1+$H45)*(1+P46) -> 0.793695 | ... Z47: =$H43*(1+$H44)*(1+$H45)*(1+Z46) -> 0.63845715
E48: Ratio of the reduction in malaria mortality to the reduction in malaria incidence | F48: =Inputs!F50 -> % | G48: =Inputs!G50 -> input | H48: =Inputs!H50 -> 1 | I48: =Inputs!I50 -> - | J48: =Inputs!J50 -> - | K48: =Inputs!K50 -> - | L48: =Inputs!L50 -> - | M48: =Inputs!M50 -> - | ... Z48: =Inputs!Z50 -> -
E49: Expected reduction in malaria mortality among children under age 5 receiving SMC | F49: % | G49: calc | H49: - | I49: =I47*$H48 -> 0.793695 | J49: =J47*$H48 -> 0.793695 | K49: =K47*$H48 -> 0.63845715 | L49: =L47*$H48 -> 0.63845715 | M49: =M47*$H48 -> 0.63845715 | N49: =N47*$H48 -> 0.63845715 | O49: =O47*$H48 -> 0.63845715 | P49: =P47*$H48 -> 0.793695 | ... Z49: =Z47*$H48 -> 0.63845715
E50: Annual malaria mortality rate among 3-59-month-olds | F50: ='Counterfactual malaria'!F30 -> % | G50: supp | H50: ='Counterfactual malaria'!H30 -> - | I50: ='Counterfactual malaria'!I30 -> 0.0038458826 | J50: ='Counterfactual malaria'!J30 -> 0.0012832309 | K50: ='Counterfactual malaria'!K30 -> 0.001839785 | L50: ='Counterfactual malaria'!L30 -> 0.0021782154 | M50: ='Counterfactual malaria'!M30 -> 0.0021631673 | N50: ='Counterfactual malaria'!N30 -> 0.0032525987 | O50: ='Counterfactual malaria'!O30 -> 0.0027758991 | ... Z50: ='Counterfactual malaria'!Z30 -> 0.0030891296
E51: Indirect malaria deaths per direct malaria death | F51: =Inputs!F51 -> # | G51: =Inputs!G51 -> input | H51: =Inputs!H51 -> 0.75 | I51: =Inputs!I51 -> - | J51: =Inputs!J51 -> - | K51: =Inputs!K51 -> - | L51: =Inputs!L51 -> - | M51: =Inputs!M51 -> - | ... Z51: =Inputs!Z51 -> -
E52: Total malaria-attributable mortality rate (including direct and indirect malaria deaths) | F52: % | G52: calc | H52: - | I52: =I50*(1+$H51) -> 0.0067302945 | J52: =J50*(1+$H51) -> 0.0022456541 | K52: =K50*(1+$H51) -> 0.0032196238 | L52: =L50*(1+$H51) -> 0.0038118769 | M52: =M50*(1+$H51) -> 0.0037855428 | N52: =N50*(1+$H51) -> 0.0056920478 | O52: =O50*(1+$H51) -> 0.0048578234 | P52: =P50*(1+$H51) -> 0.0042610274 | ... Z52: =Z50*(1+$H51) -> 0.0054059768
E53: Expected number of annual malaria-attributable mortalities among the target population in the absence of SMC | F53: # | G53: calc | H53: - | I53: =I36*I52 -> 1183.0718 | J53: =J36*J52 -> 346.79512 | K53: =K36*K52 -> 497.20472 | L53: =L36*L52 -> 588.66604 | M53: =M36*M52 -> 584.59927 | N53: =N36*N52 -> 879.01979 | O53: =O36*O52 -> 750.19097 | P53: =P36*P52 -> 844.98313 | ... Z53: =Z36*Z52 -> 667.8736
E54: Proportion of annual malaria mortality that occurs during the SMC season | F54: =Inputs!F52 -> % | G54: =Inputs!G52 -> input | H54: =Inputs!H52 -> - | I54: =Inputs!I52 -> 0.7 | J54: =Inputs!J52 -> 0.7 | K54: =Inputs!K52 -> 0.515 | L54: =Inputs!L52 -> 0.515 | M54: =Inputs!M52 -> 0.515 | ... Z54: =Inputs!Z52 -> 0.62
E55: Expected number of malaria-attributable mortalities among the target population during the SMC season in the absence of SMC | F55: # | G55: calc | H55: - | I55: =I53*I54 -> 828.15026 | J55: =J53*J54 -> 242.75658 | K55: =K53*K54 -> 256.06043 | L55: =L53*L54 -> 303.16301 | M55: =M53*M54 -> 301.06862 | N55: =N53*N54 -> 452.69519 | O55: =O53*O54 -> 386.34835 | P55: =P53*P54 -> 591.48819 | ... Z55: =Z53*Z54 -> 414.08163
E56: Total deaths averted among people under age 5 | F56: # | G56: calc | H56: - | I56: =I49*I55 -> 657.29872 | J56: =J49*J55 -> 192.67468 | K56: =K49*K55 -> 163.48361 | L56: =L49*L55 -> 193.55659 | M56: =M49*M55 -> 192.21941 | N56: =N49*N55 -> 289.02648 | O56: =O49*O55 -> 246.66687 | P56: =P49*P55 -> 469.46122 | ... Z56: =Z49*Z55 -> 264.37338
C58: Mortality reduction among people over age 5 (untreated population)
E59: Reduction in malaria incidence among the SMC-eligible population found in Cisse et al. 2016 | F59: =Inputs!F55 -> % | G59: =Inputs!G55 -> input | H59: =Inputs!H55 -> 0.6 | I59: =Inputs!I55 -> - | J59: =Inputs!J55 -> - | K59: =Inputs!K55 -> - | L59: =Inputs!L55 -> - | M59: =Inputs!M55 -> - | ... Z59: =Inputs!Z55 -> -
E60: Reduction in malaria incidence among the population too old to be eligible for SMC found in Cisse et al. 2016 | F60: =Inputs!F56 -> % | G60: =Inputs!G56 -> input | H60: =Inputs!H56 -> 0.26 | I60: =Inputs!I56 -> - | J60: =Inputs!J56 -> - | K60: =Inputs!K56 -> - | L60: =Inputs!L56 -> - | M60: =Inputs!M56 -> - | ... Z60: =Inputs!Z56 -> -
E61: Implied proportion of the protective effect of SMC received by the population too old to be eligible for SMC | F61: % | G61: calc | H61: =H60/H59 -> 0.43333333 | I61: - | J61: - | K61: - | L61: - | M61: - | N61: - | O61: - | P61: - | Q61: - | R61: - | S61: - | T61: - | U61: - | V61: - | W61: - | X61: - | Y61: - | Z61: -
E62: Adjustment for differences in program coverage and transmission intensity in the populations studied by the Cisse et al. 2016 trial and the populations targeted by grantee programs | F62: =Inputs!F57 -> % | G62: =Inputs!G57 -> input | H62: =Inputs!H57 -> -0.6912579 | I62: =Inputs!I57 -> - | J62: =Inputs!J57 -> - | K62: =Inputs!K57 -> - | L62: =Inputs!L57 -> - | M62: =Inputs!M57 -> - | ... Z62: =Inputs!Z57 -> -
E63: Expected proportion of the protective effect of SMC received by the population too old to be eligible for SMC | F63: % | G63: calc | H63: =H61*(1+H62) -> 0.13378824 | I63: - | J63: - | K63: - | L63: - | M63: - | N63: - | O63: - | P63: - | Q63: - | R63: - | S63: - | T63: - | U63: - | V63: - | W63: - | X63: - | Y63: - | Z63: -
E64: Expected reduction in malaria incidence among people over age 5 | F64: % | G64: calc | H64: - | I64: =I49*$H63 -> 0.10618706 | J64: =J49*$H63 -> 0.10618706 | K64: =K49*$H63 -> 0.08541806 | L64: =L49*$H63 -> 0.08541806 | M64: =M49*$H63 -> 0.08541806 | N64: =N49*$H63 -> 0.08541806 | O64: =O49*$H63 -> 0.08541806 | P64: =P49*$H63 -> 0.10618706 | ... Z64: =Z49*$H63 -> 0.08541806
E65: Ratio of the reduction in malaria mortality to the reduction in malaria incidence | F65: =F48 -> % | G65: feed | H65: =H48 -> 1 | I65: =I48 -> - | J65: =J48 -> - | K65: =K48 -> - | L65: =L48 -> - | M65: =M48 -> - | N65: =N48 -> - | O65: =O48 -> - | ... Z65: =Z48 -> -
E66: Expected reduction in malaria mortality among people over age 5 | F66: % | G66: calc | H66: - | I66: =I64*$H65 -> 0.10618706 | J66: =J64*$H65 -> 0.10618706 | K66: =K64*$H65 -> 0.08541806 | L66: =L64*$H65 -> 0.08541806 | M66: =M64*$H65 -> 0.08541806 | N66: =N64*$H65 -> 0.08541806 | O66: =O64*$H65 -> 0.08541806 | P66: =P64*$H65 -> 0.10618706 | ... Z66: =Z64*$H65 -> 0.08541806
E67: Malaria mortalities among people over age 5 per malaria mortality among 3-59-month-olds | F67: ='Counterfactual malaria'!F35 -> # | G67: supp | H67: ='Counterfactual malaria'!H35 -> - | I67: ='Counterfactual malaria'!I35 -> 0.67052164 | J67: ='Counterfactual malaria'!J35 -> 0.65681272 | K67: ='Counterfactual malaria'!K35 -> 0.34608247 | L67: ='Counterfactual malaria'!L35 -> 0.34608247 | M67: ='Counterfactual malaria'!M35 -> 0.34608247 | N67: ='Counterfactual malaria'!N35 -> 0.34608247 | O67: ='Counterfactual malaria'!O35 -> 1.4923914 | ... Z67: ='Counterfactual malaria'!Z35 -> 0.34600144
E68: Expected number of malaria-attributable mortalities among the target population during the SMC season in the absence of SMC | F68: # | G68: calc | H68: - | I68: =I55*I67 -> 555.29267 | J68: =J55*J67 -> 159.44561 | K68: =K55*K67 -> 88.618027 | L68: =L55*L67 -> 104.9194 | M68: =M55*M67 -> 104.19457 | N68: =N55*N67 -> 156.66987 | O68: =O55*O67 -> 576.58298 | P68: =P55*P67 -> 164.44509 | ... Z68: =Z55*Z67 -> 143.27284
E69: Total deaths averted among people age 5 and older | F69: # | G69: calc | H69: - | I69: =I66*I68 -> 58.964895 | J69: =J66*J68 -> 16.931061 | K69: =K66*K68 -> 7.5695799 | L69: =L66*L68 -> 8.9620119 | M69: =M66*M68 -> 8.9000983 | N69: =N66*N68 -> 13.382436 | O69: =O66*O68 -> 49.250599 | P69: =P66*P68 -> 17.46194 | ... Z69: =Z66*Z68 -> 12.238088
C71: Malaria incidence reduction among people under age 15
E72: Adjusted malaria incidence among people age 1 to 4 | F72: ='Counterfactual malaria'!F43 -> % | G72: supp | H72: ='Counterfactual malaria'!H43 -> - | I72: ='Counterfactual malaria'!I43 -> 0.60060984 | J72: ='Counterfactual malaria'!J43 -> 0.37423266 | K72: ='Counterfactual malaria'!K43 -> 0.3073136 | L72: ='Counterfactual malaria'!L43 -> 0.374479 | M72: ='Counterfactual malaria'!M43 -> 0.3536466 | N72: ='Counterfactual malaria'!N43 -> 0.3510289 | O72: ='Counterfactual malaria'!O43 -> 0.3632733 | ... Z72: ='Counterfactual malaria'!Z43 -> 0.3452223
E73: Adjusted malaria incidence among people age 5 to 14 | F73: ='Counterfactual malaria'!F44 -> % | G73: supp | H73: ='Counterfactual malaria'!H44 -> - | I73: ='Counterfactual malaria'!I44 -> 0.24693609 | J73: ='Counterfactual malaria'!J44 -> 0.16222621 | K73: ='Counterfactual malaria'!K44 -> 0.3073136 | L73: ='Counterfactual malaria'!L44 -> 0.374479 | M73: ='Counterfactual malaria'!M44 -> 0.3536466 | N73: ='Counterfactual malaria'!N44 -> 0.3510289 | O73: ='Counterfactual malaria'!O44 -> 0.3632733 | ... Z73: ='Counterfactual malaria'!Z44 -> 0.3452223
E74: Expected reduction in malaria incidence among people age 1 to 4 | F74: ppt | G74: calc | H74: - | I74: =I47*I54*I72 -> 0.33369072 | J74: =J47*J54*J72 -> 0.20791861 | K74: =K47*K54*K72 -> 0.10104638 | L74: =L47*L54*L72 -> 0.12313073 | M74: =M47*M54*M72 -> 0.11628092 | N74: =N47*N54*N72 -> 0.11542021 | O74: =O47*O54*O72 -> 0.11944623 | P74: =P47*P54*P72 -> 0.25156296 | ... Z74: =Z47*Z54*Z72 -> 0.13665398
E75: Expected reduction in malaria incidence among people age 5 to 14 | F75: ppt | G75: calc | H75: - | I75: =I64*I54*I73 -> 0.018354992 | J75: =J64*J54*J73 -> 0.012058427 | K75: =K64*K54*K73 -> 0.013518818 | L75: =L64*L54*L73 -> 0.016473444 | M75: =M64*M54*M73 -> 0.01555702 | N75: =N64*N54*N73 -> 0.015441867 | O75: =O64*O54*O73 -> 0.015980502 | P75: =P64*P54*P73 -> 0.013835583 | ... Z75: =Z64*Z54*Z73 -> 0.018282696
E76: National population age 1 to 4 | F76: =Inputs!F60 -> # | G76: =Inputs!G60 -> input | H76: =Inputs!H60 -> - | I76: =Inputs!I60 -> 3159819.7 | J76: =Inputs!J60 -> 2593740.2 | K76: =Inputs!K60 -> 10821149 | L76: =Inputs!L60 -> 10821149 | M76: =Inputs!M60 -> 10821149 | ... Z76: =Inputs!Z60 -> 5581405.2
E77: National population age 5 to 14 | F77: =Inputs!F61 -> # | G77: =Inputs!G61 -> input | H77: =Inputs!H61 -> - | I77: =Inputs!I61 -> 6348445.6 | J77: =Inputs!J61 -> 4977421 | K77: =Inputs!K61 -> 24065680 | L77: =Inputs!L61 -> 24065680 | M77: =Inputs!M61 -> 24065680 | ... Z77: =Inputs!Z61 -> 11987722
E78: Number of 5-14-year-olds exposed to spillover effects per person targeted to receive SMC | F78: # | G78: calc | H78: - | I78: =I77/I76 -> 2.0091164 | J78: =J77/J76 -> 1.919013 | K78: =K77/K76 -> 2.2239488 | L78: =L77/L76 -> 2.2239488 | M78: =M77/M76 -> 2.2239488 | N78: =N77/N76 -> 2.2239488 | O78: =O77/O76 -> 2.1445636 | P78: =P77/P76 -> 2.2812118 | ... Z78: =Z77/Z76 -> 2.1477964
E79: Total 5-14-year-olds exposed to spillover effects from SMC | F79: # | G79: calc | H79: - | I79: =I36*I78 -> 353168.64 | J79: =J36*J78 -> 296352.11 | K79: =K36*K78 -> 343443.18 | L79: =L36*L78 -> 343443.18 | M79: =M36*M78 -> 343443.18 | N79: =N36*N78 -> 343443.18 | O79: =O36*O78 -> 331183.77 | P79: =P36*P78 -> 452375.76 | ... Z79: =Z36*Z78 -> 265346.41
E80: Malaria cases averted among people under age 5 | F80: # | G80: calc | H80: - | I80: =I36*I74 -> 58657.177 | J80: =J36*J74 -> 32108.756 | K80: =K36*K74 -> 15604.537 | L80: =L36*L74 -> 19015.01 | M80: =M36*M74 -> 17957.198 | N80: =N36*N74 -> 17824.279 | O80: =O36*O74 -> 18446.016 | P80: =P36*P74 -> 49886.198 | ... Z80: =Z36*Z74 -> 16882.719
E81: Malaria cases averted among people age 5 to 14 | F81: # | G81: calc | H81: - | I81: =I75*I79 -> 6482.4075 | J81: =J75*J79 -> 3573.5403 | K81: =K75*K79 -> 4642.9457 | L81: =L75*L79 -> 5657.6919 | M81: =M75*M79 -> 5342.9525 | N81: =N75*N79 -> 5303.4038 | O81: =O75*O79 -> 5292.4829 | P81: =P75*P79 -> 6258.8823 | ... Z81: =Z75*Z79 -> 4851.2477
C83: Long-term income increases for people under age 15
E84: Increase in annual income per malaria case averted among people under age 15 | F84: =Inputs!F64 -> % | G84: =Inputs!G64 -> input | H84: =Inputs!H64 -> 0.0064543 | I84: =Inputs!I64 -> - | J84: =Inputs!J64 -> - | K84: =Inputs!K64 -> - | L84: =Inputs!L64 -> - | M84: =Inputs!M64 -> - | ... Z84: =Inputs!Z64 -> -
E85: Adjusted increase in ln(income) per malaria case averted among people under age 15 | F85: ln($) | G85: calc | H85: =(ln(1+H84)-ln(1)) -> 0.0064335602 | I85: - | J85: - | K85: - | L85: - | M85: - | N85: - | O85: - | P85: - | Q85: - | R85: - | S85: - | T85: - | U85: - | V85: - | W85: - | X85: - | Y85: - | Z85: -
E86: Average number of years between receiving SMC and the beginning of long-term benefits | F86: =Inputs!F65 -> # | G86: =Inputs!G65 -> input | H86: =Inputs!H65 -> 12.5 | I86: =Inputs!I65 -> - | J86: =Inputs!J65 -> - | K86: =Inputs!K65 -> - | L86: =Inputs!L65 -> - | M86: =Inputs!M65 -> - | ... Z86: =Inputs!Z65 -> -
E87: Discount rate for future benefits | F87: =Inputs!F66 -> % | G87: =Inputs!G66 -> input | H87: =Inputs!H66 -> 0.04 | I87: =Inputs!I66 -> - | J87: =Inputs!J66 -> - | K87: =Inputs!K66 -> - | L87: =Inputs!L66 -> - | M87: =Inputs!M66 -> - | ... Z87: =Inputs!Z66 -> -
E88: Discounted increase in ln(income) per malaria case averted among people under age 15 | F88: ln($) | G88: calc | H88: =H85/(1+H87)^H86 -> 0.0039403484 | I88: - | J88: - | K88: - | L88: - | M88: - | N88: - | O88: - | P88: - | Q88: - | R88: - | S88: - | T88: - | U88: - | V88: - | W88: - | X88: - | Y88: - | Z88: -
E89: Expected number of years the long-term benefits of receiving SMC will last | F89: =Inputs!F67 -> # | G89: =Inputs!G67 -> input | H89: =Inputs!H67 -> 40 | I89: =Inputs!I67 -> - | J89: =Inputs!J67 -> - | K89: =Inputs!K67 -> - | L89: =Inputs!L67 -> - | M89: =Inputs!M67 -> - | ... Z89: =Inputs!Z67 -> -
E90: Present value of individual lifetime benefits per malaria case averted among people under age 15 | F90: ln($) | G90: calc | H90: =pv(H87,H89,-H88,,1) -> 0.081110043 | I90: - | J90: - | K90: - | L90: - | M90: - | N90: - | O90: - | P90: - | Q90: - | R90: - | S90: - | T90: - | U90: - | V90: - | W90: - | X90: - | Y90: - | Z90: -
E91: Multiplier for resource sharing within households | F91: =Inputs!F68 -> # | G91: =Inputs!G68 -> input | H91: =Inputs!H68 -> 2 | I91: =Inputs!I68 -> - | J91: =Inputs!J68 -> - | K91: =Inputs!K68 -> - | L91: =Inputs!L68 -> - | M91: =Inputs!M68 -> - | ... Z91: =Inputs!Z68 -> -
E92: Present value of total lifetime benefits per malaria case averted among people under age 15 | F92: ln($) | G92: calc | H92: =H90*H91 -> 0.16222009 | I92: - | J92: - | K92: - | L92: - | M92: - | N92: - | O92: - | P92: - | Q92: - | R92: - | S92: - | T92: - | U92: - | V92: - | W92: - | X92: - | Y92: - | Z92: -
E93: Present value of increase in units of annual ln(income) among people under age 5 | F93: ln($) | G93: calc | H93: - | I93: =I80*$H92 -> 9515.3723 | J93: =J80*$H92 -> 5208.6851 | K93: =K80*$H92 -> 2531.3693 | L93: =L80*$H92 -> 3084.6166 | M93: =M80*$H92 -> 2913.0183 | N93: =N80*$H92 -> 2891.456 | O93: =O80*$H92 -> 2992.3142 | P93: =P80*$H92 -> 8092.5433 | ... Z93: =Z80*$H92 -> 2738.7161
E94: Present value of increase in units of annual ln(income) among people age 5 to 14 | F94: ln($) | G94: calc | H94: - | I94: =I81*$H92 -> 1051.5767 | J94: =J81*$H92 -> 579.70002 | K94: =K81*$H92 -> 753.17905 | L94: =L81*$H92 -> 917.79127 | M94: =M81*$H92 -> 866.73421 | N94: =N81*$H92 -> 860.31863 | O94: =O81*$H92 -> 858.54703 | P94: =P81*$H92 -> 1015.3164 | ... Z94: =Z81*$H92 -> 786.96981
E95: Total present value of units of increase in units of annual ln(income) among people under age 15 | F95: ln($) | G95: calc | H95: - | I95: =SUM(I93:I94) -> 10566.949 | J95: =SUM(J93:J94) -> 5788.3852 | K95: =SUM(K93:K94) -> 3284.5483 | L95: =SUM(L93:L94) -> 4002.4079 | M95: =SUM(M93:M94) -> 3779.7525 | N95: =SUM(N93:N94) -> 3751.7747 | O95: =SUM(O93:O94) -> 3850.8613 | P95: =SUM(P93:P94) -> 9107.8597 | ... Z95: =SUM(Z93:Z94) -> 3525.6859
A97: Value of outcomes
C99: Units of value from mortality reduction among people under age 5
E100: Value assigned to averting a malaria-attributable death of a person under age 5 | F100: =Inputs!F73 -> UoV | G100: =Inputs!G73 -> input | H100: =Inputs!H73 -> 116.25262 | I100: =Inputs!I73 -> - | J100: =Inputs!J73 -> - | K100: =Inputs!K73 -> - | L100: =Inputs!L73 -> - | M100: =Inputs!M73 -> - | ... Z100: =Inputs!Z73 -> -
E101: Units of value from under-5 deaths averted (before accounting for leverage and funging) | F101: UoV | G101: calc | H101: - | I101: =I56*$H100 -> 76412.698 | J101: =J56*$H100 -> 22398.937 | K101: =K56*$H100 -> 19005.398 | L101: =L56*$H100 -> 22501.461 | M101: =M56*$H100 -> 22346.011 | N101: =N56*$H100 -> 33600.085 | O101: =O56*$H100 -> 28675.669 | P101: =P56*$H100 -> 54576.097 | ... Z101: =Z56*$H100 -> 30734.098
C103: Units of value from mortality reduction among people age 5 and older
E104: Value assigned to averting a malaria-attributable death of a person age 5 or older | F104: =Inputs!F74 -> UoV | G104: =Inputs!G74 -> input | H104: =Inputs!H74 -> 73.1914 | I104: =Inputs!I74 -> - | J104: =Inputs!J74 -> - | K104: =Inputs!K74 -> - | L104: =Inputs!L74 -> - | M104: =Inputs!M74 -> - | ... Z104: =Inputs!Z74 -> -
E105: Units of value from 5-and-over deaths averted (before accounting for leverage and funging) | F105: UoV | G105: calc | H105: - | I105: =I69*$H104 -> 4315.7233 | J105: =J69*$H104 -> 1239.208 | K105: =K69*$H104 -> 554.02815 | L105: =L69*$H104 -> 655.9422 | M105: =M69*$H104 -> 651.41066 | N105: =N69*$H104 -> 979.47926 | O105: =O69*$H104 -> 3604.7203 | P105: =P69*$H104 -> 1278.0639 | ... Z105: =Z69*$H104 -> 895.72279
C107: Units of value from long-term income increases for people under age 15
E108: Value assigned to increasing ln(consumption) by one unit for one person for one year | F108: =Inputs!F76 -> UoV | G108: =Inputs!G76 -> input | H108: =Inputs!H76 -> 1.442695 | I108: =Inputs!I76 -> - | J108: =Inputs!J76 -> - | K108: =Inputs!K76 -> - | L108: =Inputs!L76 -> - | M108: =Inputs!M76 -> - | ... Z108: =Inputs!Z76 -> -
E109: Units of value from long-term income increases (before accounting for leverage and funging) | F109: UoV | G109: calc | H109: - | I109: =I95*$H108 -> 15244.885 | J109: =J95*$H108 -> 8350.8746 | K109: =K95*$H108 -> 4738.6016 | L109: =L95*$H108 -> 5774.254 | M109: =M95*$H108 -> 5453.0302 | N109: =N95*$H108 -> 5412.6667 | O109: =O95*$H108 -> 5555.6185 | P109: =P95*$H108 -> 13139.864 | ... Z109: =Z95*$H108 -> 5086.4895
E110: Units of value generated from long-term income increases per year of SMC treatment | F110: UoV | G110: calc | H110: - | I110: =I109/I36 -> 0.086725561 | J110: =J109/J36 -> 0.054075662 | K110: =K109/K36 -> 0.030684573 | L110: =L109/L36 -> 0.037390887 | M110: =M109/M36 -> 0.035310819 | N110: =N109/N36 -> 0.035049447 | O110: =O109/O36 -> 0.035975124 | P110: =P109/P36 -> 0.066260874 | ... Z110: =Z109/Z36 -> 0.041171629
A112: Summary of outcomes and initial cost-effectiveness (before final adjustments)
C114: Summary of outcomes
E115: Total deaths averted among people under age 5 | F115: =F56 -> # | G115: feed | H115: =H56 -> - | I115: =I56 -> 657.29872 | J115: =J56 -> 192.67468 | K115: =K56 -> 163.48361 | L115: =L56 -> 193.55659 | M115: =M56 -> 192.21941 | N115: =N56 -> 289.02648 | O115: =O56 -> 246.66687 | ... Z115: =Z56 -> 264.37338
E116: Total deaths averted among people age 5 and older | F116: =F69 -> # | G116: feed | H116: =H69 -> - | I116: =I69 -> 58.964895 | J116: =J69 -> 16.931061 | K116: =K69 -> 7.5695799 | L116: =L69 -> 8.9620119 | M116: =M69 -> 8.9000983 | N116: =N69 -> 13.382436 | O116: =O69 -> 49.250599 | ... Z116: =Z69 -> 12.238088
E117: Total malaria cases averted among people under age 15 | F117: # | G117: calc | H117: - | I117: =SUM(I80:I81) -> 65139.584 | J117: =SUM(J80:J81) -> 35682.296 | K117: =SUM(K80:K81) -> 20247.482 | L117: =SUM(L80:L81) -> 24672.702 | M117: =SUM(M80:M81) -> 23300.151 | N117: =SUM(N80:N81) -> 23127.683 | O117: =SUM(O80:O81) -> 23738.499 | P117: =SUM(P80:P81) -> 56145.08 | ... Z117: =SUM(Z80:Z81) -> 21733.966
C119: Value of individual outcomes
E120: Value assigned to averting a malaria-attributable death of a person under age 5 | F120: =Inputs!F73 -> UoV | G120: =Inputs!G73 -> input | H120: =Inputs!H73 -> 116.25262 | I120: =Inputs!I73 -> - | J120: =Inputs!J73 -> - | K120: =Inputs!K73 -> - | L120: =Inputs!L73 -> - | M120: =Inputs!M73 -> - | ... Z120: =Inputs!Z73 -> -
...

Sheet Counterfactual malaria
I1: Malaria Consortium | R1: Malaria Consortium
I2: Burkina Faso | J2: Chad | K2: DRC | L2: DRC | M2: DRC | N2: DRC | O2: Mozambique | P2: Nigeria | Q2: Nigeria | R2: Nigeria | S2: Nigeria | T2: Nigeria | U2: Nigeria | V2: Nigeria | W2: Nigeria | X2: Nigeria | Y2: Togo | Z2: Uganda
A3: Supplemental calculations for counterfactual malaria mortality and prevalence rates | H3: Overall | K3: Haut-Katanga | L3: Haut-Lomami | M3: Lualaba | N3: Tanganyika | O3: Nampula | P3: Bauchi | Q3: Borno | R3: FCT (Abuja) | S3: Kebbi | T3: Kogi | U3: Nasarawa | V3: Oyo | W3: Plateau | X3: Sokoto | Z3: Karamoja
E4: Final cost-effectiveness estimate (pulled from "Main calcs" sheet for visibility) | F4: ='Main CEA'!F191 -> xbenchmark | G4: main | H4: ='Main CEA'!H191 -> - | I4: ='Main CEA'!I191 -> 18.017467 | J4: ='Main CEA'!J191 -> 8.0191284 | K4: ='Main CEA'!K191 -> 7.8521256 | L4: ='Main CEA'!L191 -> 9.2460297 | M4: ='Main CEA'!M191 -> 9.1012718 | N4: ='Main CEA'!N191 -> 12.57331 | O4: ='Main CEA'!O191 -> 11.495836 | ... Z4: ='Main CEA'!Z191 -> 10.360783
A5: Malaria mortality among the SMC-eligible population
C7: Malaria mortalities per year among people under age 5
E8: Malaria mortalities per year among people under age 5 | F8: =Inputs!F22 -> # | G8: =Inputs!G22 -> input | H8: =Inputs!H22 -> - | I8: =Inputs!I22 -> 16395.369 | J8: =Inputs!J22 -> 4525.7324 | K8: =Inputs!K22 -> 4108.1367 | L8: =Inputs!L22 -> 3604.3863 | M8: =Inputs!M22 -> 1046.9126 | ... Z8: =Inputs!Z22 -> 3723.9932
E9: Early neonatal malaria mortalities per year (babies under 7 days old) | F9: =Inputs!F23 -> # | G9: =Inputs!G23 -> input | H9: =Inputs!H23 -> - | I9: =Inputs!I23 -> 0 | J9: =Inputs!J23 -> 0 | K9: =Inputs!K23 -> 0 | L9: =Inputs!L23 -> 0 | M9: =Inputs!M23 -> 0 | ... Z9: =Inputs!Z23 -> 0
E10: Late neonatal malaria mortalities per year (babies between 7 and 27 days old) | F10: =Inputs!F24 -> # | G10: =Inputs!G24 -> input | H10: =Inputs!H24 -> - | I10: =Inputs!I24 -> 683.0121 | J10: =Inputs!J24 -> 207.98591 | K10: =Inputs!K24 -> 288.24933 | L10: =Inputs!L24 -> 252.90345 | M10: =Inputs!M24 -> 73.45711 | ... Z10: =Inputs!Z24 -> 214.2493
E11: Post-neonatal malaria mortalities per year (babies between 28 and 364 days old) | F11: =Inputs!F25 -> # | G11: =Inputs!G25 -> input | H11: =Inputs!H25 -> - | I11: =Inputs!I25 -> 5135.6144 | J11: =Inputs!J25 -> 1402.4717 | K11: =Inputs!K25 -> 1632.3436 | L11: =Inputs!L25 -> 1432.1813 | M11: =Inputs!M25 -> 415.98445 | ... Z11: =Inputs!Z25 -> 1595.4637
C13: Estimated malaria mortalities per year among the SMC-eligible population
E14: Number of post-neonatal months of life in which children are under 1 year old | F14: =Inputs!F26 -> # | G14: =Inputs!G26 -> input | H14: =Inputs!H26 -> 11 | I14: =Inputs!I26 -> - | J14: =Inputs!J26 -> - | K14: =Inputs!K26 -> - | L14: =Inputs!L26 -> - | M14: =Inputs!M26 -> - | ... Z14: =Inputs!Z26 -> -
E15: Number of post-neonatal months of life in which children are under 3 months old | F15: =Inputs!F27 -> # | G15: =Inputs!G27 -> input | H15: =Inputs!H27 -> 2 | I15: =Inputs!I27 -> - | J15: =Inputs!J27 -> - | K15: =Inputs!K27 -> - | L15: =Inputs!L27 -> - | M15: =Inputs!M27 -> - | ... Z15: =Inputs!Z27 -> -
E16: Proportion of post-neonatal malaria mortalities that are among 1-2-month-olds | F16: % | G16: calc | H16: =H15/H14 -> 0.18181818 | I16: - | J16: - | K16: - | L16: - | M16: - | N16: - | O16: - | P16: - | Q16: - | R16: - | S16: - | T16: - | U16: - | V16: - | W16: - | X16: - | Y16: - | Z16: -
E17: Estimated malaria mortalities per year among 1-2-month-olds | F17: # | G17: calc | H17: - | I17: =I11*$H16 -> 933.74807 | J17: =J11*$H16 -> 254.99485 | K17: =K11*$H16 -> 296.78974 | L17: =L11*$H16 -> 260.39661 | M17: =M11*$H16 -> 75.633536 | N17: =N11*$H16 -> 271.0651 | O17: =O11*$H16 -> 285.45557 | P17: =P11*$H16 -> 93.475062 | ... Z17: =Z11*$H16 -> 290.08431
E18: Total malaria mortalities per year among 3-59-month-olds | F18: # | G18: calc | H18: - | I18: =I8-SUM(I9:I10,I17) -> 14778.609 | J18: =J8-SUM(J9:J10,J17) -> 4062.7517 | K18: =K8-SUM(K9:K10,K17) -> 3523.0976 | L18: =L8-SUM(L9:L10,L17) -> 3091.0862 | M18: =M8-SUM(M9:M10,M17) -> 897.82192 | N18: =N8-SUM(N9:N10,N17) -> 3217.7285 | O18: =O8-SUM(O9:O10,O17) -> 2601.9125 | P18: =P8-SUM(P9:P10,P17) -> 3422.5386 | ... Z18: =Z8-SUM(Z9:Z10,Z17) -> 3219.6596
E19: Proportion of malaria mortalities among people under age 5 that occur among 3-59-month-olds | F19: % | G19: calc | H19: - | I19: =I18/I8 -> 0.90138922 | J19: =J18/J8 -> 0.89770037 | K19: =K18/K8 -> 0.85759016 | L19: =L18/L8 -> 0.85759016 | M19: =M18/M8 -> 0.85759016 | N19: =N18/N8 -> 0.85759016 | O19: =O18/O8 -> 0.86530585 | P19: =P18/P8 -> 0.95240497 | ... Z19: =Z18/Z8 -> 0.86457182
C21: Annual malaria mortality rate among the SMC-eligible population
E22: Annual malaria mortality rate among people under age 5 | F22: =Inputs!F30 -> per 100k | G22: =Inputs!G30 -> input | H22: =Inputs!H30 -> - | I22: =Inputs!I30 -> 405.32862 | J22: =Inputs!J30 -> 135.79914 | K22: =Inputs!K30 -> 203.80315 | L22: =Inputs!L30 -> 241.29295 | M22: =Inputs!M30 -> 239.62599 | ... Z22: =Inputs!Z30 -> 339.43659
E23: Implied population of people under age 5 | F23: # | G23: calc | H23: - | I23: =I8/I22*100000 -> 4044957.3 | J23: =J8/J22*100000 -> 3332666.6 | K23: =K8/K22*100000 -> 2015737.6 | L23: =L8/L22*100000 -> 1493780.2 | M23: =M8/M22*100000 -> 436894.42 | N23: =N8/N22*100000 -> 1041346.6 | O23: =O8/O22*100000 -> 986655.19 | P23: =P8/P22*100000 -> 1405633.4 | ... Z23: =Z8/Z22*100000 -> 1097110.1
E24: Total number of months of life in which children are under 5 years old | F24: =Inputs!F31 -> # | G24: =Inputs!G31 -> input | H24: =Inputs!H31 -> 60 | I24: =Inputs!I31 -> - | J24: =Inputs!J31 -> - | K24: =Inputs!K31 -> - | L24: =Inputs!L31 -> - | M24: =Inputs!M31 -> - | ... Z24: =Inputs!Z31 -> -
E25: =HYPERLINK(buildUrl(CELL("address", Inputs!E32)), Inputs!E32) -> #ERROR! | F25: =Inputs!F32 -> # | G25: =Inputs!G32 -> input | H25: =Inputs!H32 -> 3 | I25: =Inputs!I32 -> - | J25: =Inputs!J32 -> - | K25: =Inputs!K32 -> - | L25: =Inputs!L32 -> - | M25: =Inputs!M32 -> - | ... Z25: =Inputs!Z32 -> -
E26: Proportion of people under age 5 who are 3-59-month-olds | F26: % | G26: calc | H26: =(H24-H25)/H24 -> 0.95 | I26: - | J26: - | K26: - | L26: - | M26: - | N26: - | O26: - | P26: - | Q26: - | R26: - | S26: - | T26: - | U26: - | V26: - | W26: - | X26: - | Y26: - | Z26: -
E27: Estimated population of 3-59-month olds | F27: # | G27: calc | H27: - | I27: =I23*$H26 -> 3842709.4 | J27: =J23*$H26 -> 3166033.2 | K27: =K23*$H26 -> 1914950.7 | L27: =L23*$H26 -> 1419091.2 | M27: =M23*$H26 -> 415049.7 | N27: =N23*$H26 -> 989279.27 | O27: =O23*$H26 -> 937322.43 | P27: =P23*$H26 -> 1335351.8 | ... Z27: =Z23*$H26 -> 1042254.6
E28: Unadjusted annual malaria mortality rate among 3-59-month-olds | F28: % | G28: calc | H28: - | I28: =I18/I27 -> 0.0038458826 | J28: =J18/J27 -> 0.0012832309 | K28: =K18/K27 -> 0.001839785 | L28: =L18/L27 -> 0.0021782154 | M28: =M18/M27 -> 0.0021631673 | N28: =N18/N27 -> 0.0032525987 | O28: =O18/O27 -> 0.0027758991 | P28: =P18/P27 -> 0.002563024 | ... Z28: =Z18/Z27 -> 0.0030891296
E29: Adjustment for malaria averted by ITN distributions not accounted for in GBD 2019 | F29: =Inputs!F33 -> % | G29: =Inputs!G33 -> input | H29: =Inputs!H33 -> - | I29: =Inputs!I33 -> 0 | J29: =Inputs!J33 -> 0 | K29: =Inputs!K33 -> 0 | L29: =Inputs!L33 -> 0 | M29: =Inputs!M33 -> 0 | ... Z29: =Inputs!Z33 -> 0
E30: Annual malaria mortality rate among 3-59-month-olds | F30: % | G30: calc | H30: - | I30: =I28*(1+I29) -> 0.0038458826 | J30: =J28*(1+J29) -> 0.0012832309 | K30: =K28*(1+K29) -> 0.001839785 | L30: =L28*(1+L29) -> 0.0021782154 | M30: =M28*(1+M29) -> 0.0021631673 | N30: =N28*(1+N29) -> 0.0032525987 | O30: =O28*(1+O29) -> 0.0027758991 | P30: =P28*(1+P29) -> 0.0024348728 | ... Z30: =Z28*(1+Z29) -> 0.0030891296
C32: Proportion of malaria mortalities that are among the SMC-eligible population
E33: Total malaria mortalities per year | F33: =Inputs!F36 -> # | G33: =Inputs!G36 -> input | H33: =Inputs!H36 -> - | I33: =Inputs!I36 -> 26304.747 | J33: =Inputs!J36 -> 7194.1994 | K33: =Inputs!K36 -> 5327.419 | L33: =Inputs!L36 -> 4674.157 | M33: =Inputs!M36 -> 1357.633 | ... Z33: =Inputs!Z36 -> 4838
E34: Malaria mortalities per year among people over age 5 | F34: # | G34: calc | H34: - | I34: =I33-I8 -> 9909.3773 | J34: =J33-J8 -> 2668.467 | K34: =K33-K8 -> 1219.2823 | L34: =L33-L8 -> 1069.7707 | M34: =M33-M8 -> 310.72043 | N34: =N33-N8 -> 1113.5994 | O34: =O33-O8 -> 3883.0719 | P34: =P33-P8 -> 951.53154 | ... Z34: =Z33-Z8 -> 1114.0068
E35: Malaria mortalities among people over age 5 per malaria mortality among 3-59-month-olds | F35: # | G35: calc | H35: - | I35: =I34/I18 -> 0.67052164 | J35: =J34/J18 -> 0.65681272 | K35: =K34/K18 -> 0.34608247 | L35: =L34/L18 -> 0.34608247 | M35: =M34/M18 -> 0.34608247 | N35: =N34/N18 -> 0.34608247 | O35: =O34/O18 -> 1.4923914 | P35: =P34/P18 -> 0.27801922 | ... Z35: =Z34/Z18 -> 0.34600144
A37: Malaria incidence among the SMC-eligible population
C39: Malaria incidence among people under age 15
E40: Malaria incidence among people age 1 to 4 | F40: =Inputs!F39 -> per 100k | G40: =Inputs!G39 -> input | H40: =Inputs!H39 -> - | I40: =Inputs!I39 -> 60060.984 | J40: =Inputs!J39 -> 37423.266 | K40: =Inputs!K39 -> 30731.36 | L40: =Inputs!L39 -> 37447.9 | M40: =Inputs!M39 -> 35364.66 | ... Z40: =Inputs!Z39 -> 34522.23
E41: Malaria incidence among people age 5 to 14 | F41: =Inputs!F40 -> per 100k | G41: =Inputs!G40 -> input | H41: =Inputs!H40 -> - | I41: =Inputs!I40 -> 24693.609 | J41: =Inputs!J40 -> 16222.621 | K41: =Inputs!K40 -> 30731.36 | L41: =Inputs!L40 -> 37447.9 | M41: =Inputs!M40 -> 35364.66 | ... Z41: =Inputs!Z40 -> 34522.23
E42: Adjustment for malaria averted by ITN distributions not accounted for in GBD 2019 | F42: =Inputs!F33 -> % | G42: =Inputs!G33 -> input | H42: =Inputs!H33 -> - | I42: =Inputs!I33 -> 0 | J42: =Inputs!J33 -> 0 | K42: =Inputs!K33 -> 0 | L42: =Inputs!L33 -> 0 | M42: =Inputs!M33 -> 0 | ... Z42: =Inputs!Z33 -> 0
E43: Adjusted malaria incidence among people age 1 to 4 | F43: % | G43: calc | H43: - | I43: =(I40/100000)*(1+I42) -> 0.60060984 | J43: =(J40/100000)*(1+J42) -> 0.37423266 | K43: =(K40/100000)*(1+K42) -> 0.3073136 | L43: =(L40/100000)*(1+L42) -> 0.374479 | M43: =(M40/100000)*(1+M42) -> 0.3536466 | N43: =(N40/100000)*(1+N42) -> 0.3510289 | O43: =(O40/100000)*(1+O42) -> 0.3632733 | P43: =(P40/100000)*(1+P42) -> 0.45278811 | ... Z43: =(Z40/100000)*(1+Z42) -> 0.3452223
E44: Adjusted malaria incidence among people age 5 to 14 | F44: % | G44: calc | H44: - | I44: =(I41/100000)*(1+I42) -> 0.24693609 | J44: =(J41/100000)*(1+J42) -> 0.16222621 | K44: =(K41/100000)*(1+K42) -> 0.3073136 | L44: =(L41/100000)*(1+L42) -> 0.374479 | M44: =(M41/100000)*(1+M42) -> 0.3536466 | N44: =(N41/100000)*(1+N42) -> 0.3510289 | O44: =(O41/100000)*(1+O42) -> 0.3632733 | P44: =(P41/100000)*(1+P42) -> 0.18613491 | ... Z44: =(Z41/100000)*(1+Z42) -> 0.3452223

Sheet LeverageFunging
I1: Malaria Consortium | R1: Malaria Consortium
I2: Burkina Faso | J2: Chad | K2: DRC | L2: DRC | M2: DRC | N2: DRC | O2: Mozambique | P2: Nigeria | Q2: Nigeria | R2: Nigeria | S2: Nigeria | T2: Nigeria | U2: Nigeria | V2: Nigeria | W2: Nigeria | X2: Nigeria | Y2: Togo | Z2: Uganda
A3: Supplemental calculations for the leverage/funging adjustment | F3: unit | G3: type | H3: Overall | K3: Haut-Katanga | L3: Haut-Lomami | M3: Lualaba | N3: Tanganyika | O3: Nampula | P3: Bauchi | Q3: Borno | R3: FCT (Abuja) | S3: Kebbi | T3: Kogi | U3: Nasarawa | V3: Oyo | W3: Plateau | X3: Sokoto | Z3: Karamoja
E4: Final cost-effectiveness estimate (pulled from "Main calcs" sheet for visibility) | F4: ='Main CEA'!F191 -> xbenchmark | G4: main | H4: ='Main CEA'!H191 -> - | I4: ='Main CEA'!I191 -> 18.017467 | J4: ='Main CEA'!J191 -> 8.0191284 | K4: ='Main CEA'!K191 -> 7.8521256 | L4: ='Main CEA'!L191 -> 9.2460297 | M4: ='Main CEA'!M191 -> 9.1012718 | N4: ='Main CEA'!N191 -> 12.57331 | O4: ='Main CEA'!O191 -> 11.495836 | ... Z4: ='Main CEA'!Z191 -> 10.360783
A5: Costs
C7: GiveWell costs
E8: Grant size | F8: =Inputs!F8 -> $ | G8: =Inputs!G8 -> input | H8: =Inputs!H8 -> 1000000 | I8: =Inputs!I8 -> - | J8: =Inputs!J8 -> - | K8: =Inputs!K8 -> - | L8: =Inputs!L8 -> - | M8: =Inputs!M8 -> - | ... Z8: =Inputs!Z8 -> -
C10: Cost breakdown
E11: Percentage of total costs covered by the grantee | F11: =Inputs!F11 -> % | G11: =Inputs!G11 -> input | H11: =Inputs!H11 -> - | I11: =Inputs!I11 -> 0.8872139 | J11: =Inputs!J11 -> 0.8943595 | K11: =Inputs!K11 -> 0.8943595 | L11: =Inputs!L11 -> 0.8943595 | M11: =Inputs!M11 -> 0.8943595 | ... Z11: =Inputs!Z11 -> 0.8943595
E12: Percentage of total costs covered by other philanthropic actors | F12: =Inputs!F12 -> % | G12: =Inputs!G12 -> input | H12: =Inputs!H12 -> - | I12: =Inputs!I12 -> 0.0081278 | J12: =Inputs!J12 -> 0 | K12: =Inputs!K12 -> 0 | L12: =Inputs!L12 -> 0 | M12: =Inputs!M12 -> 0 | ... Z12: =Inputs!Z12 -> 0
E13: Percentage of total costs covered by domestic governments | F13: =Inputs!F13 -> % | G13: =Inputs!G13 -> input | H13: =Inputs!H13 -> - | I13: =Inputs!I13 -> 0.1046583 | J13: =Inputs!J13 -> 0.1056405 | K13: =Inputs!K13 -> 0.1056405 | L13: =Inputs!L13 -> 0.1056405 | M13: =Inputs!M13 -> 0.1056405 | ... Z13: =Inputs!Z13 -> 0.1056405
C15: Total costs
E16: Total spending by all contributors | F16: ='Main CEA'!F16 -> $ | G16: main | H16: ='Main CEA'!H16 -> - | I16: ='Main CEA'!I16 -> 1127123.9 | J16: ='Main CEA'!J16 -> 1118118.6 | K16: ='Main CEA'!K16 -> 1118118.6 | L16: ='Main CEA'!L16 -> 1118118.6 | M16: ='Main CEA'!M16 -> 1118118.6 | N16: ='Main CEA'!N16 -> 1118118.6 | O16: ='Main CEA'!O16 -> 1118118.6 | ... Z16: ='Main CEA'!Z16 -> 1118118.6
C18: Total spending attributable to different actors
E19: Total spending contributed by grantee | F19: ='Main CEA'!F19 -> $ | G19: main | H19: ='Main CEA'!H19 -> - | I19: ='Main CEA'!I19 -> 1000000 | J19: ='Main CEA'!J19 -> 1000000 | K19: ='Main CEA'!K19 -> 1000000 | L19: ='Main CEA'!L19 -> 1000000 | M19: ='Main CEA'!M19 -> 1000000 | N19: ='Main CEA'!N19 -> 1000000 | O19: ='Main CEA'!O19 -> 1000000 | ... Z19: ='Main CEA'!Z19 -> 1000000
E20: Total spending contributed by other philanthropic actors | F20: ='Main CEA'!F20 -> $ | G20: main | H20: ='Main CEA'!H20 -> - | I20: ='Main CEA'!I20 -> 9161.0377 | J20: ='Main CEA'!J20 -> 0 | K20: ='Main CEA'!K20 -> 0 | L20: ='Main CEA'!L20 -> 0 | M20: ='Main CEA'!M20 -> 0 | N20: ='Main CEA'!N20 -> 0 | O20: ='Main CEA'!O20 -> 0 | ... Z20: ='Main CEA'!Z20 -> 0
E21: Total spending contributed by domestic governments | F21: ='Main CEA'!F21 -> $ | G21: main | H21: ='Main CEA'!H21 -> - | I21: ='Main CEA'!I21 -> 117962.87 | J21: ='Main CEA'!J21 -> 118118.61 | K21: ='Main CEA'!K21 -> 118118.61 | L21: ='Main CEA'!L21 -> 118118.61 | M21: ='Main CEA'!M21 -> 118118.61 | N21: ='Main CEA'!N21 -> 118118.61 | O21: ='Main CEA'!O21 -> 118118.61 | ... Z21: ='Main CEA'!Z21 -> 118118.61
C23: Upstream / downstream spending
E24: Total spending causally upstream of donations to grantee | F24: ='Main CEA'!F24 -> $ | G24: main | H24: ='Main CEA'!H24 -> - | I24: ='Main CEA'!I24 -> 1009161 | J24: ='Main CEA'!J24 -> 1000000 | K24: ='Main CEA'!K24 -> 1000000 | L24: ='Main CEA'!L24 -> 1000000 | M24: ='Main CEA'!M24 -> 1000000 | N24: ='Main CEA'!N24 -> 1000000 | O24: ='Main CEA'!O24 -> 1000000 | ... Z24: ='Main CEA'!Z24 -> 1000000
E25: Total spending causally downstream of donations to grantee | F25: ='Main CEA'!F25 -> $ | G25: main | H25: ='Main CEA'!H25 -> - | I25: ='Main CEA'!I25 -> 117962.87 | J25: ='Main CEA'!J25 -> 118118.61 | K25: ='Main CEA'!K25 -> 118118.61 | L25: ='Main CEA'!L25 -> 118118.61 | M25: ='Main CEA'!M25 -> 118118.61 | N25: ='Main CEA'!N25 -> 118118.61 | O25: ='Main CEA'!O25 -> 118118.61 | ... Z25: ='Main CEA'!Z25 -> 118118.61
A27: Counterfactual funding scenarios
C29: Probability of scenarios in the absence of philanthropic funding
E30: Scenario 1: Domestic governments would replace the grantee's costs | F30: =Inputs!F113 -> % | G30: =Inputs!G113 -> input | H30: =Inputs!H113 -> - | I30: =Inputs!I113 -> 0 | J30: =Inputs!J113 -> 0 | K30: =Inputs!K113 -> 0 | L30: =Inputs!L113 -> 0 | M30: =Inputs!M113 -> 0 | ... Z30: =Inputs!Z113 -> 0
E31: Scenario 2: Global Fund and/or PMI would replace the grantee's costs | F31: =Inputs!F114 -> % | G31: =Inputs!G114 -> input | H31: =Inputs!H114 -> - | I31: =Inputs!I114 -> 0.5 | J31: =Inputs!J114 -> 0.45 | K31: =Inputs!K114 -> 0.15 | L31: =Inputs!L114 -> 0.15 | M31: =Inputs!M114 -> 0.15 | ... Z31: =Inputs!Z114 -> 0.3
E32: Scenario 3: Other actors' upstream costs would stay the same (downstream costs would shrink in proportion to the total size of the program) | F32: =Inputs!F115 -> % | G32: =Inputs!G115 -> input | H32: =Inputs!H115 -> - | I32: =Inputs!I115 -> 0 | J32: =Inputs!J115 -> 0 | K32: =Inputs!K115 -> 0 | L32: =Inputs!L115 -> 0 | M32: =Inputs!M115 -> 0 | ... Z32: =Inputs!Z115 -> 0
E33: Scenario 4: Distributions would go unfunded | F33: % | G33: calc | H33: - | I33: =1-SUM(I30:I32) -> 0.5 | J33: =1-SUM(J30:J32) -> 0.55 | K33: =1-SUM(K30:K32) -> 0.85 | L33: =1-SUM(L30:L32) -> 0.85 | M33: =1-SUM(M30:M32) -> 0.85 | N33: =1-SUM(N30:N32) -> 0.85 | O33: =1-SUM(O30:O32) -> 0.8 | P33: =1-SUM(P30:P32) -> 0.8 | ... Z33: =1-SUM(Z30:Z32) -> 0.7
C35: Proportion of the program that would still occur in each scenario
E36: Scenario 1: Domestic governments would replace the grantee's costs | F36: =Inputs!F118 -> % | G36: =Inputs!G118 -> input | H36: =Inputs!H118 -> 1 | I36: =Inputs!I118 -> - | J36: =Inputs!J118 -> - | K36: =Inputs!K118 -> - | L36: =Inputs!L118 -> - | M36: =Inputs!M118 -> - | ... Z36: =Inputs!Z118 -> -
E37: Scenario 2: Global Fund and/or PMI would replace the grantee's costs | F37: =Inputs!F119 -> % | G37: =Inputs!G119 -> input | H37: =Inputs!H119 -> 1 | I37: =Inputs!I119 -> - | J37: =Inputs!J119 -> - | K37: =Inputs!K119 -> - | L37: =Inputs!L119 -> - | M37: =Inputs!M119 -> - | ... Z37: =Inputs!Z119 -> -
E38: Scenario 3: Other actors' upstream costs would stay the same (downstream costs would shrink in proportion to the total size of the program) | F38: % | G38: calc | H38: - | I38: =I20/I24 -> 0.009077875 | J38: =J20/J24 -> 0 | K38: =K20/K24 -> 0 | L38: =L20/L24 -> 0 | M38: =M20/M24 -> 0 | N38: =N20/N24 -> 0 | O38: =O20/O24 -> 0 | P38: =P20/P24 -> 0.042724632 | ... Z38: =Z20/Z24 -> 0
E39: Scenario 4: Distributions would go unfunded | F39: =Inputs!F120 -> % | G39: =Inputs!G120 -> input | H39: =Inputs!H120 -> 0 | I39: =Inputs!I120 -> - | J39: =Inputs!J120 -> - | K39: =Inputs!K120 -> - | L39: =Inputs!L120 -> - | M39: =Inputs!M120 -> - | ... Z39: =Inputs!Z120 -> -
A41: Value of spending
C43: Cost-effectiveness of the program (before leverage and funging)
E44: Units of value generated per dollar (before final adjustments) | F44: ='Main CEA'!F132 -> UoV | G44: main | H44: ='Main CEA'!H132 -> - | I44: ='Main CEA'!I132 -> 0.095973306 | J44: ='Main CEA'!J132 -> 0.031989019 | K44: ='Main CEA'!K132 -> 0.024298028 | L44: ='Main CEA'!L132 -> 0.028931657 | M44: ='Main CEA'!M132 -> 0.028450451 | N44: ='Main CEA'!N132 -> 0.039992231 | O44: ='Main CEA'!O132 -> 0.037836008 | ... Z44: ='Main CEA'!Z132 -> 0.03671631
E45: Total supplemental grantee-level adjustment | F45: ='Main CEA'!F161 -> % | G45: main | H45: ='Main CEA'!H161 -> -0.08 | I45: ='Main CEA'!I161 -> - | J45: ='Main CEA'!J161 -> - | K45: ='Main CEA'!K161 -> - | L45: ='Main CEA'!L161 -> - | M45: ='Main CEA'!M161 -> - | N45: ='Main CEA'!N161 -> - | O45: ='Main CEA'!O161 -> - | ... Z45: ='Main CEA'!Z161 -> -
E46: Total supplemental intervention-level adjustment | F46: ='Main CEA'!F177 -> % | G46: main | H46: ='Main CEA'!H177 -> - | I46: ='Main CEA'!I177 -> 0.191 | J46: ='Main CEA'!J177 -> 0.241 | K46: ='Main CEA'!K177 -> 0.281 | L46: ='Main CEA'!L177 -> 0.281 | M46: ='Main CEA'!M177 -> 0.281 | N46: ='Main CEA'!N177 -> 0.281 | O46: ='Main CEA'!O177 -> 0.281 | ... Z46: ='Main CEA'!Z177 -> 0.281
E47: Units of value generated per dollar donated to grantee (after supplemental adjustments) | F47: UoV | G47: calc | H47: - | I47: =I44*(1+$H45)*(1+I46) -> 0.10515987 | J47: =J44*(1+$H45)*(1+J46) -> 0.036522503 | K47: =K44*(1+$H45)*(1+K46) -> 0.028635712 | L47: =L44*(1+$H45)*(1+L46) -> 0.034096536 | M47: =M44*(1+$H45)*(1+M46) -> 0.033529426 | N47: =N44*(1+$H45)*(1+N46) -> 0.047131645 | O47: =O44*(1+$H45)*(1+O46) -> 0.044590492 | P47: =P44*(1+$H45)*(1+P46) -> 0.085119308 | ... Z47: =Z44*(1+$H45)*(1+Z46) -> 0.043270906
C49: Lives saved by the program (before leverage and funging)
E50: Total lives saved (before final adjustments) | F50: ='Main CEA'!F143 -> # | G50: main | H50: ='Main CEA'!H143 -> - | I50: ='Main CEA'!I143 -> 716.26361 | J50: ='Main CEA'!J143 -> 209.60575 | K50: ='Main CEA'!K143 -> 171.05319 | L50: ='Main CEA'!L143 -> 202.5186 | M50: ='Main CEA'!M143 -> 201.11951 | N50: ='Main CEA'!N143 -> 302.40892 | O50: ='Main CEA'!O143 -> 295.91747 | ... Z50: ='Main CEA'!Z143 -> 276.61147
E51: Total supplemental grantee-level adjustment | F51: ='Main CEA'!F161 -> % | G51: main | H51: ='Main CEA'!H161 -> -0.08 | I51: ='Main CEA'!I161 -> - | J51: ='Main CEA'!J161 -> - | K51: ='Main CEA'!K161 -> - | L51: ='Main CEA'!L161 -> - | M51: ='Main CEA'!M161 -> - | N51: ='Main CEA'!N161 -> - | O51: ='Main CEA'!O161 -> - | ... Z51: ='Main CEA'!Z161 -> -
E52: Total supplemental intervention-level adjustment affecting lives saved | F52: ='Main CEA'!F202 -> % | G52: main | H52: ='Main CEA'!H202 -> - | I52: ='Main CEA'!I202 -> -0.198 | J52: ='Main CEA'!J202 -> -0.148 | K52: ='Main CEA'!K202 -> -0.108 | L52: ='Main CEA'!L202 -> -0.108 | M52: ='Main CEA'!M202 -> -0.108 | N52: ='Main CEA'!N202 -> -0.108 | O52: ='Main CEA'!O202 -> -0.108 | ... Z52: ='Main CEA'!Z202 -> -0.108
E53: Total lives saved (after supplemental adjustments) | F53: # | G53: calc | H53: - | I53: =I50*(1+$H51)*(1+I52) -> 528.48794 | J53: =J50*(1+$H51)*(1+J52) -> 164.29737 | K53: =K50*(1+$H51)*(1+K52) -> 140.37309 | L53: =L50*(1+$H51)*(1+L52) -> 166.19487 | M53: =M50*(1+$H51)*(1+M52) -> 165.04672 | N53: =N50*(1+$H51)*(1+N52) -> 248.16885 | O53: =O50*(1+$H51)*(1+O52) -> 242.84171 | P53: =P50*(1+$H51)*(1+P52) -> 426.46678 | ... Z53: =Z50*(1+$H51)*(1+Z52) -> 226.99843
C55: Counterfactual value of spending from non-philanthropic actors
E56: Counterfactual value per dollar spent by domestic governments | F56: =Inputs!F123 -> UoV | G56: =Inputs!G123 -> input | H56: =Inputs!H123 -> 0.005057 | I56: =Inputs!I123 -> - | J56: =Inputs!J123 -> - | K56: =Inputs!K123 -> - | L56: =Inputs!L123 -> - | M56: =Inputs!M123 -> - | ... Z56: =Inputs!Z123 -> -
E57: Counterfactual value per dollar spent by the Global Fund or PMI | F57: =Inputs!F124 -> UoV | G57: =Inputs!G124 -> input | H57: =Inputs!H124 -> 0.015433 | I57: =Inputs!I124 -> - | J57: =Inputs!J124 -> - | K57: =Inputs!K124 -> - | L57: =Inputs!L124 -> - | M57: =Inputs!M124 -> - | ... Z57: =Inputs!Z124 -> -
A59: Value generated across different counterfactual scenarios
C61: Scenario 1: Domestic governments would replace philanthropic spending
D62: Hypothetical impact of shifting government spending
E63: Amount of spending domestic governments would shift to the grantee program | F63: $ | G63: calc | H63: - | I63: =I19 -> 1000000 | J63: =J19 -> 1000000 | K63: =K19 -> 1000000 | L63: =L19 -> 1000000 | M63: =M19 -> 1000000 | N63: =N19 -> 1000000 | O63: =O19 -> 1000000 | P63: =P19 -> 1000000 | ... Z63: =Z19 -> 1000000
E64: Value generated by shifting government spending to the grantee program | F64: UoV | G64: calc | H64: - | I64: =I63*I47 -> 105159.87 | J64: =J63*J47 -> 36522.503 | K64: =K63*K47 -> 28635.712 | L64: =L63*L47 -> 34096.536 | M64: =M63*M47 -> 33529.426 | N64: =N63*N47 -> 47131.645 | O64: =O63*O47 -> 44590.492 | P64: =P63*P47 -> 85119.308 | ... Z64: =Z63*Z47 -> 43270.906
E65: Value lost by shifting spending away from programs domestic governments would otherwise have funded | F65: UoV | G65: calc | H65: - | I65: =I63*$H56 -> 5057 | J65: =J63*$H56 -> 5057 | K65: =K63*$H56 -> 5057 | L65: =L63*$H56 -> 5057 | M65: =M63*$H56 -> 5057 | N65: =N63*$H56 -> 5057 | O65: =O63*$H56 -> 5057 | P65: =P63*$H56 -> 5057 | ... Z65: =Z63*$H56 -> 5057
E66: Net value generated by shifting government spending to the grantee program | F66: UoV | G66: calc | H66: - | I66: =I64-I65 -> 100102.87 | J66: =J64-J65 -> 31465.503 | K66: =K64-K65 -> 23578.712 | L66: =L64-L65 -> 29039.536 | M66: =M64-M65 -> 28472.426 | N66: =N64-N65 -> 42074.645 | O66: =O64-O65 -> 39533.492 | P66: =P64-P65 -> 80062.308 | ... Z66: =Z64-Z65 -> 38213.906
E67: Change in value generated by the grantee program if this scenario represented the true counterfactual | F67: UoV | G67: calc | H67: - | I67: =-I66 -> -100102.87 | J67: =-J66 -> -31465.503 | K67: =-K66 -> -23578.712 | L67: =-L66 -> -29039.536 | M67: =-M66 -> -28472.426 | N67: =-N66 -> -42074.645 | O67: =-O66 -> -39533.492 | P67: =-P66 -> -80062.308 | ... Z67: =-Z66 -> -38213.906
E68: Probability of this scenario representing the true counterfactual | F68: =F30 -> % | G68: feed | H68: =H30 -> - | I68: =I30 -> 0 | J68: =J30 -> 0 | K68: =K30 -> 0 | L68: =L30 -> 0 | M68: =M30 -> 0 | N68: =N30 -> 0 | O68: =O30 -> 0 | ... Z68: =Z30 -> 0
E69: Expected change in value generated by the grantee program | F69: UoV | G69: calc | H69: - | I69: =I67*I68 -> 0 | J69: =J67*J68 -> 0 | K69: =K67*K68 -> 0 | L69: =L67*L68 -> 0 | M69: =M67*M68 -> 0 | N69: =N67*N68 -> 0 | O69: =O67*O68 -> 0 | P69: =P67*P68 -> 0 | ... Z69: =Z67*Z68 -> 0
C71: Scenario 2: The Global Fund and/or PMI would replace philanthropic spending
D72: Hypothetical impact of shifting Global Fund and/or PMI spending
E73: Amount of spending Global Fund and/or PMI would shift to the grantee program | F73: $ | G73: calc | H73: - | I73: =I19 -> 1000000 | J73: =J19 -> 1000000 | K73: =K19 -> 1000000 | L73: =L19 -> 1000000 | M73: =M19 -> 1000000 | N73: =N19 -> 1000000 | O73: =O19 -> 1000000 | P73: =P19 -> 1000000 | ... Z73: =Z19 -> 1000000
E74: Value generated by shifting Global Fund and/or PMI spending to the grantee program | F74: UoV | G74: calc | H74: - | I74: =I73*I47 -> 105159.87 | J74: =J73*J47 -> 36522.503 | K74: =K73*K47 -> 28635.712 | L74: =L73*L47 -> 34096.536 | M74: =M73*M47 -> 33529.426 | N74: =N73*N47 -> 47131.645 | O74: =O73*O47 -> 44590.492 | P74: =P73*P47 -> 85119.308 | ... Z74: =Z73*Z47 -> 43270.906
E75: Value lost by shifting spending away from programs the Global Fund and/or PMI would otherwise have funded | F75: UoV | G75: calc | H75: - | I75: =I73*$H57 -> 15433 | J75: =J73*$H57 -> 15433 | K75: =K73*$H57 -> 15433 | L75: =L73*$H57 -> 15433 | M75: =M73*$H57 -> 15433 | N75: =N73*$H57 -> 15433 | O75: =O73*$H57 -> 15433 | P75: =P73*$H57 -> 15433 | ... Z75: =Z73*$H57 -> 15433
E76: Net value generated by shifting Global Fund and/or PMI spending to the grantee program | F76: UoV | G76: calc | H76: - | I76: =I74-I75 -> 89726.871 | J76: =J74-J75 -> 21089.503 | K76: =K74-K75 -> 13202.712 | L76: =L74-L75 -> 18663.536 | M76: =M74-M75 -> 18096.426 | N76: =N74-N75 -> 31698.645 | O76: =O74-O75 -> 29157.492 | P76: =P74-P75 -> 69686.308 | ... Z76: =Z74-Z75 -> 27837.906
E77: Change in value generated by the grantee program if this scenario represented the true counterfactual | F77: UoV | G77: calc | H77: - | I77: =-I76 -> -89726.871 | J77: =-J76 -> -21089.503 | K77: =-K76 -> -13202.712 | L77: =-L76 -> -18663.536 | M77: =-M76 -> -18096.426 | N77: =-N76 -> -31698.645 | O77: =-O76 -> -29157.492 | P77: =-P76 -> -69686.308 | ... Z77: =-Z76 -> -27837.906
E78: Probability of this scenario representing the true counterfactual | F78: =F31 -> % | G78: feed | H78: =H31 -> - | I78: =I31 -> 0.5 | J78: =J31 -> 0.45 | K78: =K31 -> 0.15 | L78: =L31 -> 0.15 | M78: =M31 -> 0.15 | N78: =N31 -> 0.15 | O78: =O31 -> 0.2 | ... Z78: =Z31 -> 0.3
E79: Expected change in value generated by the grantee program | F79: UoV | G79: calc | H79: - | I79: =I77*I78 -> -44863.436 | J79: =J77*J78 -> -9490.2765 | K79: =K77*K78 -> -1980.4068 | L79: =L77*L78 -> -2799.5304 | M79: =M77*M78 -> -2714.4639 | N79: =N77*N78 -> -4754.7967 | O79: =O77*O78 -> -5831.4985 | P79: =P77*P78 -> -13937.262 | ... Z79: =Z77*Z78 -> -8351.3717
C81: Scenario 3: The government would spend the same amount and the program would be smaller
D82: Hypothetical impact of shifting government spending
E83: Amount of spending domestic governments would shift away from the grantee program | F83: $ | G83: calc | H83: - | I83: =I21*(1-I38) -> 116892.02 | J83: =J21*(1-J38) -> 118118.61 | K83: =K21*(1-K38) -> 118118.61 | L83: =L21*(1-L38) -> 118118.61 | M83: =M21*(1-M38) -> 118118.61 | N83: =N21*(1-N38) -> 118118.61 | O83: =O21*(1-O38) -> 118118.61 | P83: =P21*(1-P38) -> 112530.82 | ... Z83: =Z21*(1-Z38) -> 118118.61
E84: Value generated by shifting spending toward programs domestic governments would otherwise have supported | F84: UoV | G84: calc | H84: - | I84: =I83*$H56 -> 591.12295 | J84: =J83*$H56 -> 597.32581 | K84: =K83*$H56 -> 597.32581 | L84: =L83*$H56 -> 597.32581 | M84: =M83*$H56 -> 597.32581 | N84: =N83*$H56 -> 597.32581 | O84: =O83*$H56 -> 597.32581 | P84: =P83*$H56 -> 569.06838 | ... Z84: =Z83*$H56 -> 597.32581
E85: Value lost by shifting government spending away from the grantee program | F85: UoV | G85: calc | H85: - | I85: 0 | J85: 0 | K85: 0 | L85: 0 | M85: 0 | N85: 0 | O85: 0 | P85: 0 | Q85: 0 | R85: 0 | S85: 0 | T85: 0 | U85: 0 | V85: 0 | W85: 0 | X85: 0 | Y85: 0 | Z85: 0
E86: Net value generated by shifting government spending away from the grantee program | F86: UoV | G86: calc | H86: - | I86: =I84-I85 -> 591.12295 | J86: =J84-J85 -> 597.32581 | K86: =K84-K85 -> 597.32581 | L86: =L84-L85 -> 597.32581 | M86: =M84-M85 -> 597.32581 | N86: =N84-N85 -> 597.32581 | O86: =O84-O85 -> 597.32581 | P86: =P84-P85 -> 569.06838 | ... Z86: =Z84-Z85 -> 597.32581
E87: Change in value generated by the grantee program if this scenario represented the true counterfactual | F87: UoV | G87: calc | H87: - | I87: =-I86 -> -591.12295 | J87: =-J86 -> -597.32581 | K87: =-K86 -> -597.32581 | L87: =-L86 -> -597.32581 | M87: =-M86 -> -597.32581 | N87: =-N86 -> -597.32581 | O87: =-O86 -> -597.32581 | P87: =-P86 -> -569.06838 | ... Z87: =-Z86 -> -597.32581
E88: Probability of this scenario representing the true counterfactual | F88: =F32 -> % | G88: feed | H88: =H32 -> - | I88: =I32 -> 0 | J88: =J32 -> 0 | K88: =K32 -> 0 | L88: =L32 -> 0 | M88: =M32 -> 0 | N88: =N32 -> 0 | O88: =O32 -> 0 | ... Z88: =Z32 -> 0
E89: Expected change in value generated by the program | F89: UoV | G89: calc | H89: - | I89: =I87*I88 -> 0 | J89: =J87*J88 -> 0 | K89: =K87*K88 -> 0 | L89: =L87*L88 -> 0 | M89: =M87*M88 -> 0 | N89: =N87*N88 -> 0 | O89: =O87*O88 -> 0 | P89: =P87*P88 -> 0 | ... Z89: =Z87*Z88 -> 0
C91: Scenario 4: The grantee program would go unfunded
D92: Hypothetical impact of shifting government spending
E93: Amount of spending domestic governments would shift away from the grantee program | F93: $ | G93: calc | H93: - | I93: =I21 -> 117962.87 | J93: =J21 -> 118118.61 | K93: =K21 -> 118118.61 | L93: =L21 -> 118118.61 | M93: =M21 -> 118118.61 | N93: =N21 -> 118118.61 | O93: =O21 -> 118118.61 | P93: =P21 -> 117553.24 | ... Z93: =Z21 -> 118118.61
E94: Value generated by shifting spending to programs domestic governments would otherwise have funded | F94: UoV | G94: calc | H94: - | I94: =I93*$H56 -> 596.53825 | J94: =J93*$H56 -> 597.32581 | K94: =K93*$H56 -> 597.32581 | L94: =L93*$H56 -> 597.32581 | M94: =M93*$H56 -> 597.32581 | N94: =N93*$H56 -> 597.32581 | O94: =O93*$H56 -> 597.32581 | P94: =P93*$H56 -> 594.46675 | ... Z94: =Z93*$H56 -> 597.32581
E95: Value lost by shifting government spending away from the grantee program | F95: UoV | G95: calc | H95: - | I95: 0 | J95: 0 | K95: 0 | L95: 0 | M95: 0 | N95: 0 | O95: 0 | P95: 0 | Q95: 0 | R95: 0 | S95: 0 | T95: 0 | U95: 0 | V95: 0 | W95: 0 | X95: 0 | Y95: 0 | Z95: 0
E96: Net value generated by shifting government spending away from the grantee program | F96: UoV | G96: calc | H96: - | I96: =I94-I95 -> 596.53825 | J96: =J94-J95 -> 597.32581 | K96: =K94-K95 -> 597.32581 | L96: =L94-L95 -> 597.32581 | M96: =M94-M95 -> 597.32581 | N96: =N94-N95 -> 597.32581 | O96: =O94-O95 -> 597.32581 | P96: =P94-P95 -> 594.46675 | ... Z96: =Z94-Z95 -> 597.32581
E97: Change in value generated by the grantee program if this scenario represented the true counterfactual | F97: UoV | G97: calc | H97: - | I97: =-I96 -> -596.53825 | J97: =-J96 -> -597.32581 | K97: =-K96 -> -597.32581 | L97: =-L96 -> -597.32581 | M97: =-M96 -> -597.32581 | N97: =-N96 -> -597.32581 | O97: =-O96 -> -597.32581 | P97: =-P96 -> -594.46675 | ... Z97: =-Z96 -> -597.32581
E98: Probability of this scenario representing the true counterfactual | F98: =F33 -> % | G98: feed | H98: =H33 -> - | I98: =I33 -> 0.5 | J98: =J33 -> 0.55 | K98: =K33 -> 0.85 | L98: =L33 -> 0.85 | M98: =M33 -> 0.85 | N98: =N33 -> 0.85 | O98: =O33 -> 0.8 | ... Z98: =Z33 -> 0.7
E99: Expected change in value generated by the program | F99: UoV | G99: calc | H99: - | I99: =I97*I98 -> -298.26912 | J99: =J97*J98 -> -328.52919 | K99: =K97*K98 -> -507.72693 | L99: =L97*L98 -> -507.72693 | M99: =M97*M98 -> -507.72693 | N99: =N97*N98 -> -507.72693 | O99: =O97*O98 -> -477.86064 | P99: =P97*P98 -> -475.5734 | ... Z99: =Z97*Z98 -> -418.12806
A101: Final leverage and funging adjustment
C103: Change in value generated as a result of leverage and funging
E104: Total value generated by grantee spending before adjusting for leverage and funging | F104: UoV | G104: calc | H104: - | I104: =I19*I47 -> 105159.87 | J104: =J19*J47 -> 36522.503 | K104: =K19*K47 -> 28635.712 | L104: =L19*L47 -> 34096.536 | M104: =M19*M47 -> 33529.426 | N104: =N19*N47 -> 47131.645 | O104: =O19*O47 -> 44590.492 | P104: =P19*P47 -> 85119.308 | ... Z104: =Z19*Z47 -> 43270.906
E105: Change in value generated as a result of crowding funding into the program (leverage) | F105: UoV | G105: calc | H105: - | I105: =SUM(I89,I99) -> -298.26912 | J105: =SUM(J89,J99) -> -328.52919 | K105: =SUM(K89,K99) -> -507.72693 | L105: =SUM(L89,L99) -> -507.72693 | M105: =SUM(M89,M99) -> -507.72693 | N105: =SUM(N89,N99) -> -507.72693 | O105: =SUM(O89,O99) -> -477.86064 | P105: =SUM(P89,P99) -> -475.5734 | ... Z105: =SUM(Z89,Z99) -> -418.12806
E106: Change in value generated as a result of crowding funding out of the program (funging) | F106: UoV | G106: calc | H106: - | I106: =SUM(I69,I79) -> -44863.436 | J106: =SUM(J69,J79) -> -9490.2765 | K106: =SUM(K69,K79) -> -1980.4068 | L106: =SUM(L69,L79) -> -2799.5304 | M106: =SUM(M69,M79) -> -2714.4639 | N106: =SUM(N69,N79) -> -4754.7967 | O106: =SUM(O69,O79) -> -5831.4985 | P106: =SUM(P69,P79) -> -13937.262 | ... Z106: =SUM(Z69,Z79) -> -8351.3717
E107: Total expected change in value generated as a result of leverage and funging | F107: UoV | G107: calc | H107: - | I107: =SUM(I69,I79,I89,I99) -> -45161.705 | J107: =SUM(J69,J79,J89,J99) -> -9818.8057 | K107: =SUM(K69,K79,K89,K99) -> -2488.1337 | L107: =SUM(L69,L79,L89,L99) -> -3307.2574 | M107: =SUM(M69,M79,M89,M99) -> -3222.1908 | N107: =SUM(N69,N79,N89,N99) -> -5262.5236 | O107: =SUM(O69,O79,O89,O99) -> -6309.3591 | P107: =SUM(P69,P79,P89,P99) -> -14412.835 | ... Z107: =SUM(Z69,Z79,Z89,Z99) -> -8769.4998
E108: Total value generated by grantee spending after adjusting for leverage and funging | F108: UOV | G108: calc | H108: - | I108: =SUM(I104,I107) -> 59998.166 | J108: =SUM(J104,J107) -> 26703.698 | K108: =SUM(K104,K107) -> 26147.578 | L108: =SUM(L104,L107) -> 30789.279 | M108: =SUM(M104,M107) -> 30307.235 | N108: =SUM(N104,N107) -> 41869.121 | O108: =SUM(O104,O107) -> 38281.133 | P108: =SUM(P104,P107) -> 70706.473 | ... Z108: =SUM(Z104,Z107) -> 34501.406
C110: Final leverage and funging adjustment
E111: Adjustment for the possibility of crowding funding into the program (leverage) | F111: % | G111: calc | H111: - | I111: =I105/I104 -> -0.0028363398 | J111: =J105/J104 -> -0.008995254 | K111: =K105/K104 -> -0.017730551 | L111: =L105/L104 -> -0.014890865 | M111: =M105/M104 -> -0.015142727 | N111: =N105/N104 -> -0.010772527 | O111: =O105/O104 -> -0.010716649 | P111: =P105/P104 -> -0.0055871389 | ... Z111: =Z105/Z104 -> -0.0096630301
E112: Adjustment for the possibility of crowding funding out of the program (funging) | F112: % | G112: calc | H112: - | I112: =I106/I104 -> -0.42662125 | J112: =J106/J104 -> -0.25984737 | K112: =K106/K104 -> -0.069158636 | L112: =L106/L104 -> -0.082106007 | M112: =M106/M104 -> -0.080957661 | N112: =N106/N104 -> -0.10088332 | O112: =O106/O104 -> -0.13077897 | P112: =P106/P104 -> -0.16373796 | ... Z112: =Z106/Z104 -> -0.19300201
E113: Adjustment for leverage and funging | F113: % | G113: calc | H113: - | I113: =I107/I104 -> -0.42945759 | J113: =J107/J104 -> -0.26884263 | K113: =K107/K104 -> -0.086889187 | L113: =L107/L104 -> -0.096996872 | M113: =M107/M104 -> -0.096100388 | N113: =N107/N104 -> -0.11165585 | O113: =O107/O104 -> -0.14149561 | P113: =P107/P104 -> -0.1693251 | ... Z113: =Z107/Z104 -> -0.20266504
A115: Leverage and funging adjustment for counterfactual impact estimates
C117: Leverage and funging adjustment for counterfactual output estimates
E118: Leverage and funging adjustment for counterfactual output estimates | F118: % | G118: calc | H118: - | I118: =((MIN(I67,0)*I68)+(MIN(I77,0)*I78)+I105)/I104 -> -0.42945759 | J118: =((MIN(J67,0)*J68)+(MIN(J77,0)*J78)+J105)/J104 -> -0.26884263 | K118: =((MIN(K67,0)*K68)+(MIN(K77,0)*K78)+K105)/K104 -> -0.086889187 | L118: =((MIN(L67,0)*L68)+(MIN(L77,0)*L78)+L105)/L104 -> -0.096996872 | M118: =((MIN(M67,0)*M68)+(MIN(M77,0)*M78)+M105)/M104 -> -0.096100388 | N118: =((MIN(N67,0)*N68)+(MIN(N77,0)*N78)+N105)/N104 -> -0.11165585 | O118: =((MIN(O67,0)*O68)+(MIN(O77,0)*O78)+O105)/O104 -> -0.14149561 | P118: =((MIN(P67,0)*P68)+(MIN(P77,0)*P78)+P105)/P104 -> -0.1693251 | ... Z118: =((MIN(Z67,0)*Z68)+(MIN(Z77,0)*Z78)+Z105)/Z104 -> -0.20266504
C120: Leverage and funging adjustment for counterfactual outcome estimates (lives saved)
E121: =Inputs!E73 -> Value assigned to averting a malaria-attributable death of a person under age 5 | F121: =Inputs!F73 -> UoV | G121: =Inputs!G73 -> input | H121: =Inputs!H73 -> 116.25262 | I121: =Inputs!I73 -> - | J121: =Inputs!J73 -> - | K121: =Inputs!K73 -> - | L121: =Inputs!L73 -> - | ... Z121: =Inputs!Z73 -> -
E122: Mortalities averted among people under age 5 by the counterfactual usage of leveraged funds, assuming they would have been spent on exclusively life-saving programs | F122: # | G122: calc | H122: - | I122: =-(I105/$H121) -> 2.5656981 | J122: =-(J105/$H121) -> 2.8259939 | K122: =-(K105/$H121) -> 4.3674451 | L122: =-(L105/$H121) -> 4.3674451 | M122: =-(M105/$H121) -> 4.3674451 | N122: =-(N105/$H121) -> 4.3674451 | O122: =-(O105/$H121) -> 4.1105366 | P122: =-(P105/$H121) -> 4.0908618 | ... Z122: =-(Z105/$H121) -> 3.5967195
E123: =E53 -> Total lives saved (after supplemental adjustments) | F123: =F53 -> # | G123: feed | H123: =H53 -> - | I123: =I53 -> 528.48794 | J123: =J53 -> 164.29737 | K123: =K53 -> 140.37309 | L123: =L53 -> 166.19487 | M123: =M53 -> 165.04672 | N123: =N53 -> 248.16885 | O123: =O53 -> 242.84171 | ... Z123: =Z53 -> 226.99843
...

Sheet Inputs
I1: Malaria Consortium | R1: Malaria Consortium
I2: Burkina Faso | J2: Chad | K2: DRC | L2: DRC | M2: DRC | N2: DRC | O2: Mozambique | P2: Nigeria | Q2: Nigeria | R2: Nigeria | S2: Nigeria | T2: Nigeria | U2: Nigeria | V2: Nigeria | W2: Nigeria | X2: Nigeria | Y2: Togo | Z2: Uganda
A3: Inputs | F3: unit | G3: type | H3: Overall | K3: Haut-Katanga | L3: Haut-Lomami | M3: Lualaba | N3: Tanganyika | O3: Nampula | P3: Bauchi | Q3: Borno | R3: FCT (Abuja) | S3: Kebbi | T3: Kogi | U3: Nasarawa | V3: Oyo | W3: Plateau | X3: Sokoto | Z3: Karamoja | AB3: Source | AC3: GW analysis and discussion
E4: Final cost-effectiveness estimate (pulled from "Main calcs" sheet for visibility) | F4: ='Main CEA'!F191 -> xbenchmark | G4: main | H4: ='Main CEA'!H191 -> - | I4: ='Main CEA'!I191 -> 18.017467 | J4: ='Main CEA'!J191 -> 8.0191284 | K4: ='Main CEA'!K191 -> 7.8521256 | L4: ='Main CEA'!L191 -> 9.2460297 | M4: ='Main CEA'!M191 -> 9.1012718 | N4: ='Main CEA'!N191 -> 12.57331 | O4: ='Main CEA'!O191 -> 11.495836 | ... Z4: ='Main CEA'!Z191 -> 10.360783
A5: Costs
C7: GiveWell costs
E8: Grant size | F8: $ | G8: input | H8: 1000000 | I8: - | J8: - | K8: - | L8: - | M8: - | N8: - | O8: - | P8: - | Q8: - | R8: - | S8: - | T8: - | U8: - | V8: - | W8: - | X8: - | Y8: - | Z8: - | AB8: Arbitrary value
C10: Cost breakdown
E11: Percentage of total costs covered by the grantee | F11: % | G11: input | H11: - | I11: 0.8872139 | J11: 0.8943595 | K11: 0.8943595 | L11: 0.8943595 | M11: 0.8943595 | N11: 0.8943595 | O11: 0.8943595 | P11: 0.8604484 | Q11: 0.8604484 | R11: 0.8604484 | S11: 0.8604484 | T11: 0.8604484 | U11: 0.8604484 | V11: 0.8604484 | W11: 0.8604484 | X11: 0.8604484 | Y11: 0.874083 | Z11: 0.8943595 | AB11: GW analysis | AC11: GW's analysis of Malaria Consortium's cost per SMC cycle administration
E12: Percentage of total costs covered by other philanthropic actors | F12: % | G12: input | H12: - | I12: 0.0081278 | J12: 0 | K12: 0 | L12: 0 | M12: 0 | N12: 0 | O12: 0 | P12: 0.0384031 | Q12: 0.0384031 | R12: 0.0384031 | S12: 0.0384031 | T12: 0.0384031 | U12: 0.0384031 | V12: 0.0384031 | W12: 0.0384031 | X12: 0.0384031 | Y12: 0.0244652 | Z12: 0 | AB12: GW analysis | AC12: GW's analysis of Malaria Consortium's cost per SMC cycle administration
E13: Percentage of total costs covered by domestic governments | F13: % | G13: input | H13: - | I13: 0.1046583 | J13: 0.1056405 | K13: 0.1056405 | L13: 0.1056405 | M13: 0.1056405 | N13: 0.1056405 | O13: 0.1056405 | P13: 0.1011485 | Q13: 0.1011485 | R13: 0.1011485 | S13: 0.1011485 | T13: 0.1011485 | U13: 0.1011485 | V13: 0.1011485 | W13: 0.1011485 | X13: 0.1011485 | Y13: 0.1014518 | Z13: 0.1056405 | AB13: GW analysis | AC13: GW's analysis of Malaria Consortium's cost per SMC cycle administration
C15: Cost per child covered
E16: Cost per seasonal malaria chemoprevention (SMC) cycle administered | F16: $ | G16: input | H16: - | I16: 1.47763 | J16: 1.81008 | K16: 1.81008 | L16: 1.81008 | M16: 1.81008 | N16: 1.81008 | O16: 1.81008 | P16: 1.40255 | Q16: 1.40255 | R16: 1.40255 | S16: 1.40255 | T16: 1.40255 | U16: 1.40255 | V16: 1.40255 | W16: 1.40255 | X16: 1.40255 | Y16: 1.49507 | Z16: 1.81008 | AB16: GW analysis | AC16: GW's analysis of Malaria Consortium's cost per SMC cycle administration
E17: Number of SMC cycles per year | F17: # | G17: input | H17: - | I17: 4.3 | J17: 4 | K17: 4 | L17: 4 | M17: 4 | N17: 4 | O17: 4 | P17: 4 | Q17: 4 | R17: 5 | S17: 4 | T17: 5 | U17: 5 | V17: 5 | W17: 5 | X17: 4 | Y17: 4 | Z17: 5 | AB17: GW analysis | AC17: GW's analysis of the number of SMC cycles delivered per year
A19: Counterfactual malaria
C21: Malaria mortalities among the SMC-eligible population
E22: Malaria mortalities per year among people under age 5 | F22: # | G22: input | H22: - | I22: =IFERROR(__xludf.DUMMYFUNCTION("FILTER('GBD estimates'!$S$4:$S$309,'GBD estimates'!$M$4:$M$309=I$2,'GBD estimates'!$O$4:$O$309=""<5 years"")"),16395.3694901677) -> 16395.369 | J22: =IFERROR(__xludf.DUMMYFUNCTION("FILTER('GBD estimates'!$S$4:$S$309,'GBD estimates'!$M$4:$M$309=J$2,'GBD estimates'!$O$4:$O$309=""<5 years"")"),4525.73244604996) -> 4525.7324 | K22: 4108.1367 | L22: 3604.3863 | M22: 1046.9126 | N22: 3752.0586 | O22: 3006.9281 | P22: =IFERROR(__xludf.DUMMYFUNCTION("FILTER('GBD estimates'!$BA$4:$BA$258,'GBD estimates'!$AV$4:$AV$258=P$3,'GBD estimates'!$AU$4:$AU$258=""Under 5"")"),3593.574945) -> 3593.5749 | Q22: =IFERROR(__xludf.DUMMYFUNCTION("FILTER('GBD estimates'!$BA$4:$BA$258,'GBD estimates'!$AV$4:$AV$258=Q$3,'GBD estimates'!$AU$4:$AU$258=""Under 5"")"),1707.805365) -> 1707.8054 | R22: =IFERROR(__xludf.DUMMYFUNCTION("FILTER('GBD estimates'!$BA$4:$BA$258,'GBD estimates'!$AV$4:$AV$258=R$3,'GBD estimates'!$AU$4:$AU$258=""Under 5"")"),1882.032542) -> 1882.0325 | S22: =IFERROR(__xludf.DUMMYFUNCTION("FILTER('GBD estimates'!$BA$4:$BA$258,'GBD estimates'!$AV$4:$AV$258=S$3,'GBD estimates'!$AU$4:$AU$258=""Under 5"")"),3140.509316) -> 3140.5093 | T22: =IFERROR(__xludf.DUMMYFUNCTION("FILTER('GBD estimates'!$BA$4:$BA$258,'GBD estimates'!$AV$4:$AV$258=T$3,'GBD estimates'!$AU$4:$AU$258=""Under 5"")"),800.9679515) -> 800.96795 | U22: =IFERROR(__xludf.DUMMYFUNCTION("FILTER('GBD estimates'!$BA$4:$BA$258,'GBD estimates'!$AV$4:$AV$258=U$3,'GBD estimates'!$AU$4:$AU$258=""Under 5"")"),2258.288279) -> 2258.2883 | V22: =IFERROR(__xludf.DUMMYFUNCTION("FILTER('GBD estimates'!$BA$4:$BA$258,'GBD estimates'!$AV$4:$AV$258=V$3,'GBD estimates'!$AU$4:$AU$258=""Under 5"")"),1857.078678) -> 1857.0787 | W22: =IFERROR(__xludf.DUMMYFUNCTION("FILTER('GBD estimates'!$BA$4:$BA$258,'GBD estimates'!$AV$4:$AV$258=W$3,'GBD estimates'!$AU$4:$AU$258=""Under 5"")"),3181.704964) -> 3181.705 | X22: =IFERROR(__xludf.DUMMYFUNCTION("FILTER('GBD estimates'!$BA$4:$BA$258,'GBD estimates'!$AV$4:$AV$258=X$3,'GBD estimates'!$AU$4:$AU$258=""Under 5"")"),4918.708785) -> 4918.7088 | Y22: =IFERROR(__xludf.DUMMYFUNCTION("FILTER('GBD estimates'!$S$4:$S$309,'GBD estimates'!$M$4:$M$309=Y$2,'GBD estimates'!$O$4:$O$309=""<5 years"")"),1880.40794320354) -> 1880.4079 | Z22: 3723.9932 | AB22: GBD 2019
E23: Early neonatal malaria mortalities per year (babies under 7 days old) | F23: # | G23: input | H23: - | I23: =IFERROR(__xludf.DUMMYFUNCTION("FILTER('GBD estimates'!$S$4:$S$309,'GBD estimates'!$M$4:$M$309=I$2,'GBD estimates'!$O$4:$O$309=""0-6 days"")"),0.0) -> 0 | J23: =IFERROR(__xludf.DUMMYFUNCTION("FILTER('GBD estimates'!$S$4:$S$309,'GBD estimates'!$M$4:$M$309=J$2,'GBD estimates'!$O$4:$O$309=""0-6 days"")"),0.0) -> 0 | K23: 0 | L23: 0 | M23: 0 | N23: 0 | O23: 0 | P23: 0 | Q23: 0 | R23: 0 | S23: 0 | T23: 0 | U23: 0 | V23: 0 | W23: 0 | X23: 0 | Y23: =IFERROR(__xludf.DUMMYFUNCTION("FILTER('GBD estimates'!$S$4:$S$309,'GBD estimates'!$M$4:$M$309=Y$2,'GBD estimates'!$O$4:$O$309=""0-6 days"")"),0.0) -> 0 | Z23: 0 | AB23: GBD 2019
E24: Late neonatal malaria mortalities per year (babies between 7 and 27 days old) | F24: # | G24: input | H24: - | I24: =IFERROR(__xludf.DUMMYFUNCTION("FILTER('GBD estimates'!$S$4:$S$309,'GBD estimates'!$M$4:$M$309=I$2,'GBD estimates'!$O$4:$O$309=""7-27 days"")"),683.012100501328) -> 683.0121 | J24: =IFERROR(__xludf.DUMMYFUNCTION("FILTER('GBD estimates'!$S$4:$S$309,'GBD estimates'!$M$4:$M$309=J$2,'GBD estimates'!$O$4:$O$309=""7-27 days"")"),207.98591325582) -> 207.98591 | K24: 288.24933 | L24: 252.90345 | M24: 73.45711 | N24: 263.26495 | O24: 119.56005 | P24: =IFERROR(__xludf.DUMMYFUNCTION("FILTER('GBD estimates'!$BA$4:$BA$258,'GBD estimates'!$AV$4:$AV$258=P$3,'GBD estimates'!$AU$4:$AU$258=""7 to 27 days (late neonatal)"")"),77.56124047) -> 77.56124 | Q24: =IFERROR(__xludf.DUMMYFUNCTION("FILTER('GBD estimates'!$BA$4:$BA$258,'GBD estimates'!$AV$4:$AV$258=Q$3,'GBD estimates'!$AU$4:$AU$258=""7 to 27 days (late neonatal)"")"),67.45050889) -> 67.450509 | R24: =IFERROR(__xludf.DUMMYFUNCTION("FILTER('GBD estimates'!$BA$4:$BA$258,'GBD estimates'!$AV$4:$AV$258=R$3,'GBD estimates'!$AU$4:$AU$258=""7 to 27 days (late neonatal)"")"),112.9551112) -> 112.95511 | S24: =IFERROR(__xludf.DUMMYFUNCTION("FILTER('GBD estimates'!$BA$4:$BA$258,'GBD estimates'!$AV$4:$AV$258=S$3,'GBD estimates'!$AU$4:$AU$258=""7 to 27 days (late neonatal)"")"),84.23526307) -> 84.235263 | T24: =IFERROR(__xludf.DUMMYFUNCTION("FILTER('GBD estimates'!$BA$4:$BA$258,'GBD estimates'!$AV$4:$AV$258=T$3,'GBD estimates'!$AU$4:$AU$258=""7 to 27 days (late neonatal)"")"),49.43917069) -> 49.439171 | U24: =IFERROR(__xludf.DUMMYFUNCTION("FILTER('GBD estimates'!$BA$4:$BA$258,'GBD estimates'!$AV$4:$AV$258=U$3,'GBD estimates'!$AU$4:$AU$258=""7 to 27 days (late neonatal)"")"),97.97276234) -> 97.972762 | V24: =IFERROR(__xludf.DUMMYFUNCTION("FILTER('GBD estimates'!$BA$4:$BA$258,'GBD estimates'!$AV$4:$AV$258=V$3,'GBD estimates'!$AU$4:$AU$258=""7 to 27 days (late neonatal)"")"),155.6540484) -> 155.65405 | W24: =IFERROR(__xludf.DUMMYFUNCTION("FILTER('GBD estimates'!$BA$4:$BA$258,'GBD estimates'!$AV$4:$AV$258=W$3,'GBD estimates'!$AU$4:$AU$258=""7 to 27 days (late neonatal)"")"),160.3877065) -> 160.38771 | X24: =IFERROR(__xludf.DUMMYFUNCTION("FILTER('GBD estimates'!$BA$4:$BA$258,'GBD estimates'!$AV$4:$AV$258=X$3,'GBD estimates'!$AU$4:$AU$258=""7 to 27 days (late neonatal)"")"),107.7832724) -> 107.78327 | Y24: =IFERROR(__xludf.DUMMYFUNCTION("FILTER('GBD estimates'!$S$4:$S$309,'GBD estimates'!$M$4:$M$309=Y$2,'GBD estimates'!$O$4:$O$309=""7-27 days"")"),82.1438456374381) -> 82.143846 | Z24: 214.2493 | AB24: GBD 2019
E25: Post-neonatal malaria mortalities per year (babies between 28 and 364 days old) | F25: # | G25: input | H25: - | I25: =IFERROR(__xludf.DUMMYFUNCTION("FILTER('GBD estimates'!$S$4:$S$309,'GBD estimates'!$M$4:$M$309=I$2,'GBD estimates'!$O$4:$O$309=""28-364 days"")"),5135.61437005002) -> 5135.6144 | J25: =IFERROR(__xludf.DUMMYFUNCTION("FILTER('GBD estimates'!$S$4:$S$309,'GBD estimates'!$M$4:$M$309=J$2,'GBD estimates'!$O$4:$O$309=""28-364 days"")"),1402.47165898354) -> 1402.4717 | K25: 1632.3436 | L25: 1432.1813 | M25: 415.98445 | N25: 1490.858 | O25: 1570.0056 | P25: =IFERROR(__xludf.DUMMYFUNCTION("FILTER('GBD estimates'!$BA$4:$BA$258,'GBD estimates'!$AV$4:$AV$258=P$3,'GBD estimates'!$AU$4:$AU$258=""28 to 364 days (post neonatal)"")"),514.1128436) -> 514.11284 | Q25: =IFERROR(__xludf.DUMMYFUNCTION("FILTER('GBD estimates'!$BA$4:$BA$258,'GBD estimates'!$AV$4:$AV$258=Q$3,'GBD estimates'!$AU$4:$AU$258=""28 to 364 days (post neonatal)"")"),362.4923754) -> 362.49238 | R25: =IFERROR(__xludf.DUMMYFUNCTION("FILTER('GBD estimates'!$BA$4:$BA$258,'GBD estimates'!$AV$4:$AV$258=R$3,'GBD estimates'!$AU$4:$AU$258=""28 to 364 days (post neonatal)"")"),590.6183608) -> 590.61836 | S25: =IFERROR(__xludf.DUMMYFUNCTION("FILTER('GBD estimates'!$BA$4:$BA$258,'GBD estimates'!$AV$4:$AV$258=S$3,'GBD estimates'!$AU$4:$AU$258=""28 to 364 days (post neonatal)"")"),501.3440327) -> 501.34403 | T25: =IFERROR(__xludf.DUMMYFUNCTION("FILTER('GBD estimates'!$BA$4:$BA$258,'GBD estimates'!$AV$4:$AV$258=T$3,'GBD estimates'!$AU$4:$AU$258=""28 to 364 days (post neonatal)"")"),249.8757855) -> 249.87579 | U25: =IFERROR(__xludf.DUMMYFUNCTION("FILTER('GBD estimates'!$BA$4:$BA$258,'GBD estimates'!$AV$4:$AV$258=U$3,'GBD estimates'!$AU$4:$AU$258=""28 to 364 days (post neonatal)"")"),584.2162297) -> 584.21623 | V25: =IFERROR(__xludf.DUMMYFUNCTION("FILTER('GBD estimates'!$BA$4:$BA$258,'GBD estimates'!$AV$4:$AV$258=V$3,'GBD estimates'!$AU$4:$AU$258=""28 to 364 days (post neonatal)"")"),658.0187831) -> 658.01878 | W25: =IFERROR(__xludf.DUMMYFUNCTION("FILTER('GBD estimates'!$BA$4:$BA$258,'GBD estimates'!$AV$4:$AV$258=W$3,'GBD estimates'!$AU$4:$AU$258=""28 to 364 days (post neonatal)"")"),921.5288306) -> 921.52883 | X25: =IFERROR(__xludf.DUMMYFUNCTION("FILTER('GBD estimates'!$BA$4:$BA$258,'GBD estimates'!$AV$4:$AV$258=X$3,'GBD estimates'!$AU$4:$AU$258=""28 to 364 days (post neonatal)"")"),726.8852489) -> 726.88525 | Y25: =IFERROR(__xludf.DUMMYFUNCTION("FILTER('GBD estimates'!$S$4:$S$309,'GBD estimates'!$M$4:$M$309=Y$2,'GBD estimates'!$O$4:$O$309=""28-364 days"")"),575.084442435558) -> 575.08444 | Z25: 1595.4637 | AB25: GBD 2019
E26: Number of post-neonatal months of life in which children are under 1 year old | F26: # | G26: input | H26: 11 | I26: - | J26: - | K26: - | L26: - | M26: - | N26: - | O26: - | P26: - | Q26: - | R26: - | S26: - | T26: - | U26: - | V26: - | W26: - | X26: - | Y26: - | Z26: -
E27: Number of post-neonatal months of life in which children are under 3 months old | F27: # | G27: input | H27: 2 | I27: - | J27: - | K27: - | L27: - | M27: - | N27: - | O27: - | P27: - | Q27: - | R27: - | S27: - | T27: - | U27: - | V27: - | W27: - | X27: - | Y27: - | Z27: -
C29: Malaria mortality rate among the SMC-eligible population
E30: Annual malaria mortality rate among people under age 5 | F30: per 100k | G30: input | H30: - | I30: =IFERROR(__xludf.DUMMYFUNCTION("FILTER('GBD estimates'!$AD$4:$AD$54,'GBD estimates'!$X$4:$X$54=I$2)"),405.3286161) -> 405.32862 | J30: =IFERROR(__xludf.DUMMYFUNCTION("FILTER('GBD estimates'!$AD$4:$AD$54,'GBD estimates'!$X$4:$X$54=J$2)"),135.7991375) -> 135.79914 | K30: 203.80315 | L30: 241.29295 | M30: 239.62599 | N30: 360.30833 | O30: 304.75977 | P30: =IFERROR(__xludf.DUMMYFUNCTION("FILTER('GBD estimates'!$BN$4:$BN$54,'GBD estimates'!$BI$4:$BI$54=P$3)"),255.6551987) -> 255.6552 | Q30: =IFERROR(__xludf.DUMMYFUNCTION("FILTER('GBD estimates'!$BN$4:$BN$54,'GBD estimates'!$BI$4:$BI$54=Q$3)"),178.1742523) -> 178.17425 | R30: =IFERROR(__xludf.DUMMYFUNCTION("FILTER('GBD estimates'!$BN$4:$BN$54,'GBD estimates'!$BI$4:$BI$54=R$3)"),288.3183134) -> 288.31831 | S30: =IFERROR(__xludf.DUMMYFUNCTION("FILTER('GBD estimates'!$BN$4:$BN$54,'GBD estimates'!$BI$4:$BI$54=S$3)"),331.5302296) -> 331.53023 | T30: =IFERROR(__xludf.DUMMYFUNCTION("FILTER('GBD estimates'!$BN$4:$BN$54,'GBD estimates'!$BI$4:$BI$54=T$3)"),240.036585) -> 240.03659 | U30: =IFERROR(__xludf.DUMMYFUNCTION("FILTER('GBD estimates'!$BN$4:$BN$54,'GBD estimates'!$BI$4:$BI$54=U$3)"),298.6653229) -> 298.66532 | V30: =IFERROR(__xludf.DUMMYFUNCTION("FILTER('GBD estimates'!$BN$4:$BN$54,'GBD estimates'!$BI$4:$BI$54=V$3)"),261.8332491) -> 261.83325 | W30: =IFERROR(__xludf.DUMMYFUNCTION("FILTER('GBD estimates'!$BN$4:$BN$54,'GBD estimates'!$BI$4:$BI$54=W$3)"),210.2157784) -> 210.21578 | X30: =IFERROR(__xludf.DUMMYFUNCTION("FILTER('GBD estimates'!$BN$4:$BN$54,'GBD estimates'!$BI$4:$BI$54=X$3)"),361.0521294) -> 361.05213 | Y30: =IFERROR(__xludf.DUMMYFUNCTION("FILTER('GBD estimates'!$AD$4:$AD$54,'GBD estimates'!$X$4:$X$54=Y$2)"),168.6683554) -> 168.66836 | Z30: 339.43659 | AB30: GBD 2019
E31: Total number of months of life in which children are under 5 years old | F31: # | G31: input | H31: 60 | I31: - | J31: - | K31: - | L31: - | M31: - | N31: - | O31: - | P31: - | Q31: - | R31: - | S31: - | T31: - | U31: - | V31: - | W31: - | X31: - | Y31: - | Z31: -
E32: Number of months of life in which children are under 3 months old | F32: # | G32: input | H32: 3 | I32: - | J32: - | K32: - | L32: - | M32: - | N32: - | O32: - | P32: - | Q32: - | R32: - | S32: - | T32: - | U32: - | V32: - | W32: - | X32: - | Y32: - | Z32: -
E33: Adjustment for malaria averted by ITN distributions not accounted for in GBD 2019 | F33: % | G33: input | H33: - | I33: 0 | J33: 0 | K33: 0 | L33: 0 | M33: 0 | N33: 0 | O33: 0 | P33: -0.05 | Q33: -0.05 | R33: -0.3512063 | S33: -0.05 | T33: -0.05 | U33: -0.05 | V33: -0.05 | W33: -0.05 | X33: -0.05 | Y33: 0 | Z33: 0 | AB33: GW guesstimate
C35: Proportion of malaria mortalities that are among the SMC-eligible population
E36: Total malaria mortalities per year | F36: # | G36: input | H36: - | I36: =IFERROR(__xludf.DUMMYFUNCTION("FILTER('GBD estimates'!$S$4:$S$309,'GBD estimates'!$M$4:$M$309=I$2,'GBD estimates'!$O$4:$O$309=""All ages"")"),26304.7468000016) -> 26304.747 | J36: =IFERROR(__xludf.DUMMYFUNCTION("FILTER('GBD estimates'!$S$4:$S$309,'GBD estimates'!$M$4:$M$309=J$2,'GBD estimates'!$O$4:$O$309=""All ages"")"),7194.19944040964) -> 7194.1994 | K36: 5327.419 | L36: 4674.157 | M36: 1357.633 | N36: 4865.658 | O36: 6890 | P36: =IFERROR(__xludf.DUMMYFUNCTION("FILTER('GBD estimates'!$BA$4:$BA$258,'GBD estimates'!$AV$4:$AV$258=P$3,'GBD estimates'!$AU$4:$AU$258=""All ages"")"),4545.106485) -> 4545.1065 | Q36: =IFERROR(__xludf.DUMMYFUNCTION("FILTER('GBD estimates'!$BA$4:$BA$258,'GBD estimates'!$AV$4:$AV$258=Q$3,'GBD estimates'!$AU$4:$AU$258=""All ages"")"),3093.504749) -> 3093.5047 | R36: =IFERROR(__xludf.DUMMYFUNCTION("FILTER('GBD estimates'!$BA$4:$BA$258,'GBD estimates'!$AV$4:$AV$258=R$3,'GBD estimates'!$AU$4:$AU$258=""All ages"")"),4417.546406) -> 4417.5464 | S36: =IFERROR(__xludf.DUMMYFUNCTION("FILTER('GBD estimates'!$BA$4:$BA$258,'GBD estimates'!$AV$4:$AV$258=S$3,'GBD estimates'!$AU$4:$AU$258=""All ages"")"),4606.794083) -> 4606.7941 | T36: =IFERROR(__xludf.DUMMYFUNCTION("FILTER('GBD estimates'!$BA$4:$BA$258,'GBD estimates'!$AV$4:$AV$258=T$3,'GBD estimates'!$AU$4:$AU$258=""All ages"")"),2471.067612) -> 2471.0676 | U36: =IFERROR(__xludf.DUMMYFUNCTION("FILTER('GBD estimates'!$BA$4:$BA$258,'GBD estimates'!$AV$4:$AV$258=U$3,'GBD estimates'!$AU$4:$AU$258=""All ages"")"),4449.598839) -> 4449.5988 | V36: =IFERROR(__xludf.DUMMYFUNCTION("FILTER('GBD estimates'!$BA$4:$BA$258,'GBD estimates'!$AV$4:$AV$258=V$3,'GBD estimates'!$AU$4:$AU$258=""All ages"")"),7026.505839) -> 7026.5058 | W36: =IFERROR(__xludf.DUMMYFUNCTION("FILTER('GBD estimates'!$BA$4:$BA$258,'GBD estimates'!$AV$4:$AV$258=W$3,'GBD estimates'!$AU$4:$AU$258=""All ages"")"),6892.924992) -> 6892.925 | X36: =IFERROR(__xludf.DUMMYFUNCTION("FILTER('GBD estimates'!$BA$4:$BA$258,'GBD estimates'!$AV$4:$AV$258=X$3,'GBD estimates'!$AU$4:$AU$258=""All ages"")"),6247.24128) -> 6247.2413 | Y36: =IFERROR(__xludf.DUMMYFUNCTION("FILTER('GBD estimates'!$S$4:$S$309,'GBD estimates'!$M$4:$M$309=Y$2,'GBD estimates'!$O$4:$O$309=""All ages"")"),5436.18786097608) -> 5436.1879 | Z36: 4838 | AB36: GBD 2019
C38: Malaria incidence among people under age 15
E39: Malaria incidence among people age 1 to 4 | F39: per 100k | G39: input | H39: - | I39: =IFERROR(__xludf.DUMMYFUNCTION("FILTER('GBD estimates'!$AO$4:$AO$105,'GBD estimates'!$AI$4:$AI$105=I$2,'GBD estimates'!$AK$4:$AK$105=""1-4 years"")"),60060.98378) -> 60060.984 | J39: =IFERROR(__xludf.DUMMYFUNCTION("FILTER('GBD estimates'!$AO$4:$AO$105,'GBD estimates'!$AI$4:$AI$105=J$2,'GBD estimates'!$AK$4:$AK$105=""1-4 years"")"),37423.26557) -> 37423.266 | K39: 30731.36 | L39: 37447.9 | M39: 35364.66 | N39: 35102.89 | O39: 36327.33 | P39: =IFERROR(__xludf.DUMMYFUNCTION("FILTER('GBD estimates'!$CA$4:$CA$105,'GBD estimates'!$BV$4:$BV$105=P$3,'GBD estimates'!$BU$4:$BU$105=""1 to 4"")"),47661.90624) -> 47661.906 | Q39: =IFERROR(__xludf.DUMMYFUNCTION("FILTER('GBD estimates'!$CA$4:$CA$105,'GBD estimates'!$BV$4:$BV$105=Q$3,'GBD estimates'!$BU$4:$BU$105=""1 to 4"")"),49206.23234) -> 49206.232 | R39: =IFERROR(__xludf.DUMMYFUNCTION("FILTER('GBD estimates'!$CA$4:$CA$105,'GBD estimates'!$BV$4:$BV$105=R$3,'GBD estimates'!$BU$4:$BU$105=""1 to 4"")"),81529.9384) -> 81529.938 | S39: =IFERROR(__xludf.DUMMYFUNCTION("FILTER('GBD estimates'!$CA$4:$CA$105,'GBD estimates'!$BV$4:$BV$105=S$3,'GBD estimates'!$BU$4:$BU$105=""1 to 4"")"),85869.02616) -> 85869.026 | T39: =IFERROR(__xludf.DUMMYFUNCTION("FILTER('GBD estimates'!$CA$4:$CA$105,'GBD estimates'!$BV$4:$BV$105=T$3,'GBD estimates'!$BU$4:$BU$105=""1 to 4"")"),76182.96693) -> 76182.967 | U39: =IFERROR(__xludf.DUMMYFUNCTION("FILTER('GBD estimates'!$CA$4:$CA$105,'GBD estimates'!$BV$4:$BV$105=U$3,'GBD estimates'!$BU$4:$BU$105=""1 to 4"")"),89798.63281) -> 89798.633 | V39: =IFERROR(__xludf.DUMMYFUNCTION("FILTER('GBD estimates'!$CA$4:$CA$105,'GBD estimates'!$BV$4:$BV$105=V$3,'GBD estimates'!$BU$4:$BU$105=""1 to 4"")"),130288.462) -> 130288.46 | W39: =IFERROR(__xludf.DUMMYFUNCTION("FILTER('GBD estimates'!$CA$4:$CA$105,'GBD estimates'!$BV$4:$BV$105=W$3,'GBD estimates'!$BU$4:$BU$105=""1 to 4"")"),63655.29509) -> 63655.295 | X39: =IFERROR(__xludf.DUMMYFUNCTION("FILTER('GBD estimates'!$CA$4:$CA$105,'GBD estimates'!$BV$4:$BV$105=X$3,'GBD estimates'!$BU$4:$BU$105=""1 to 4"")"),69580.73086) -> 69580.731 | Y39: =IFERROR(__xludf.DUMMYFUNCTION("FILTER('GBD estimates'!$AO$4:$AO$105,'GBD estimates'!$AI$4:$AI$105=Y$2,'GBD estimates'!$AK$4:$AK$105=""1-4 years"")"),79106.01535) -> 79106.015 | Z39: 34522.23 | AB39: GBD 2019
E40: Malaria incidence among people age 5 to 14 | F40: per 100k | G40: input | H40: - | I40: =IFERROR(__xludf.DUMMYFUNCTION("FILTER('GBD estimates'!$AO$4:$AO$105,'GBD estimates'!$AI$4:$AI$105=I$2,'GBD estimates'!$AK$4:$AK$105=""5-14 years"")"),24693.60871) -> 24693.609 | J40: =IFERROR(__xludf.DUMMYFUNCTION("FILTER('GBD estimates'!$AO$4:$AO$105,'GBD estimates'!$AI$4:$AI$105=J$2,'GBD estimates'!$AK$4:$AK$105=""5-14 years"")"),16222.6214) -> 16222.621 | K40: 30731.36 | L40: 37447.9 | M40: 35364.66 | N40: 35102.89 | O40: 36327.33 | P40: =IFERROR(__xludf.DUMMYFUNCTION("FILTER('GBD estimates'!$CA$4:$CA$105,'GBD estimates'!$BV$4:$BV$105=P$3,'GBD estimates'!$BU$4:$BU$105=""5 to 14"")"),19593.14817) -> 19593.148 | Q40: =IFERROR(__xludf.DUMMYFUNCTION("FILTER('GBD estimates'!$CA$4:$CA$105,'GBD estimates'!$BV$4:$BV$105=Q$3,'GBD estimates'!$BU$4:$BU$105=""5 to 14"")"),20783.80124) -> 20783.801 | R40: =IFERROR(__xludf.DUMMYFUNCTION("FILTER('GBD estimates'!$CA$4:$CA$105,'GBD estimates'!$BV$4:$BV$105=R$3,'GBD estimates'!$BU$4:$BU$105=""5 to 14"")"),31209.9027) -> 31209.903 | S40: =IFERROR(__xludf.DUMMYFUNCTION("FILTER('GBD estimates'!$CA$4:$CA$105,'GBD estimates'!$BV$4:$BV$105=S$3,'GBD estimates'!$BU$4:$BU$105=""5 to 14"")"),33795.62909) -> 33795.629 | T40: =IFERROR(__xludf.DUMMYFUNCTION("FILTER('GBD estimates'!$CA$4:$CA$105,'GBD estimates'!$BV$4:$BV$105=T$3,'GBD estimates'!$BU$4:$BU$105=""5 to 14"")"),29812.0385) -> 29812.038 | U40: =IFERROR(__xludf.DUMMYFUNCTION("FILTER('GBD estimates'!$CA$4:$CA$105,'GBD estimates'!$BV$4:$BV$105=U$3,'GBD estimates'!$BU$4:$BU$105=""5 to 14"")"),33528.33274) -> 33528.333 | V40: =IFERROR(__xludf.DUMMYFUNCTION("FILTER('GBD estimates'!$CA$4:$CA$105,'GBD estimates'!$BV$4:$BV$105=V$3,'GBD estimates'!$BU$4:$BU$105=""5 to 14"")"),48687.08739) -> 48687.087 | W40: =IFERROR(__xludf.DUMMYFUNCTION("FILTER('GBD estimates'!$CA$4:$CA$105,'GBD estimates'!$BV$4:$BV$105=W$3,'GBD estimates'!$BU$4:$BU$105=""5 to 14"")"),25166.99536) -> 25166.995 | X40: =IFERROR(__xludf.DUMMYFUNCTION("FILTER('GBD estimates'!$CA$4:$CA$105,'GBD estimates'!$BV$4:$BV$105=X$3,'GBD estimates'!$BU$4:$BU$105=""5 to 14"")"),28680.35419) -> 28680.354 | Y40: =IFERROR(__xludf.DUMMYFUNCTION("FILTER('GBD estimates'!$AO$4:$AO$105,'GBD estimates'!$AI$4:$AI$105=Y$2,'GBD estimates'!$AK$4:$AK$105=""5-14 years"")"),30845.0741) -> 30845.074 | Z40: 34522.23 | AB40: GBD 2019
A42: Outcomes
C44: Mortality reduction among people under age 5
E45: Reduction in malaria incidence for children under age 5 targeted for SMC found in GiveWell's adjusted version of the Meremikwu et al. 2012 meta-analysis | F45: % | G45: input | H45: 0.75 | I45: - | J45: - | K45: - | L45: - | M45: - | N45: - | O45: - | P45: - | Q45: - | R45: - | S45: - | T45: - | U45: - | V45: - | W45: - | X45: - | Y45: - | Z45: - | AB45: GW analysis | AC45: GW's report on seasonal malaria chemoprevention (SMC)
E46: Estimated proportion of children targeted for SMC in trials that received SMC | F46: % | G46: input | H46: 0.8977 | I46: - | J46: - | K46: - | L46: - | M46: - | N46: - | O46: - | P46: - | Q46: - | R46: - | S46: - | T46: - | U46: - | V46: - | W46: - | X46: - | Y46: - | Z46: - | AB46: GW analysis | AC46: GW's analysis of SMC coverage in trials
E47: Internal validity adjustment | F47: % | G47: input | H47: -0.05 | I47: - | J47: - | K47: - | L47: - | M47: - | N47: - | O47: - | P47: - | Q47: - | R47: - | S47: - | T47: - | U47: - | V47: - | W47: - | X47: - | Y47: - | Z47: - | AB47: GW guesstimate
E48: External validity adjustment | F48: % | G48: input | H48: 0 | I48: - | J48: - | K48: - | L48: - | M48: - | N48: - | O48: - | P48: - | Q48: - | R48: - | S48: - | T48: - | U48: - | V48: - | W48: - | X48: - | Y48: - | Z48: - | AB48: GW guesstimate
E49: Adjustment for lower effectiveness outside the Sahel region of Africa | F49: % | G49: input | H49: - | I49: 0 | J49: 0 | K49: -0.1955888 | L49: -0.1955888 | M49: -0.1955888 | N49: -0.1955888 | O49: -0.1955888 | P49: 0 | Q49: 0 | R49: 0 | S49: 0 | T49: 0 | U49: 0 | V49: 0 | W49: 0 | X49: 0 | Y49: 0 | Z49: -0.1955888 | AB49: GW analysis
E50: Ratio of the reduction in malaria mortality to the reduction in malaria incidence | F50: % | G50: input | H50: 1 | I50: - | J50: - | K50: - | L50: - | M50: - | N50: - | O50: - | P50: - | Q50: - | R50: - | S50: - | T50: - | U50: - | V50: - | W50: - | X50: - | Y50: - | Z50: - | AB50: GW guesstimate
E51: Indirect malaria deaths per direct malaria death | F51: # | G51: input | H51: 0.75 | I51: - | J51: - | K51: - | L51: - | M51: - | N51: - | O51: - | P51: - | Q51: - | R51: - | S51: - | T51: - | U51: - | V51: - | W51: - | X51: - | Y51: - | Z51: - | AB51: GW guesstimate
E52: Proportion of annual malaria mortality that occurs during the SMC season | F52: % | G52: input | H52: - | I52: 0.7 | J52: 0.7 | K52: =AVERAGE(33%, 70%) -> 0.515 | L52: =AVERAGE(33%, 70%) -> 0.515 | M52: =AVERAGE(33%, 70%) -> 0.515 | N52: =AVERAGE(33%, 70%) -> 0.515 | O52: =AVERAGE(33%, 70%) -> 0.515 | P52: 0.7 | Q52: 0.7 | R52: 0.7 | S52: 0.7 | T52: 0.7 | U52: 0.7 | V52: 0.7 | W52: 0.7 | X52: 0.7 | Y52: 0.7 | Z52: 0.62 | AB52: GW guesstimate
C54: Mortality reduction among people over age 5
E55: Reduction in malaria incidence among the SMC-eligible population found in Cisse et al. 2016 | F55: % | G55: input | H55: 0.6 | I55: - | J55: - | K55: - | L55: - | M55: - | N55: - | O55: - | P55: - | Q55: - | R55: - | S55: - | T55: - | U55: - | V55: - | W55: - | X55: - | Y55: - | Z55: - | AB55: Cisse et al. 2016
E56: Reduction in malaria incidence among the population too old to be eligible for SMC found in Cisse et al. 2016 | F56: % | G56: input | H56: 0.26 | I56: - | J56: - | K56: - | L56: - | M56: - | N56: - | O56: - | P56: - | Q56: - | R56: - | S56: - | T56: - | U56: - | V56: - | W56: - | X56: - | Y56: - | Z56: - | AB56: Cisse et al. 2016
E57: Adjustment for differences in program coverage and transmission intensity in the populations studied by the Cisse et al. 2016 trial and the populations targeted by grantee programs | F57: % | G57: input | H57: -0.6912579 | I57: - | J57: - | K57: - | L57: - | M57: - | N57: - | O57: - | P57: - | Q57: - | R57: - | S57: - | T57: - | U57: - | V57: - | W57: - | X57: - | Y57: - | Z57: - | AB57: GW analysis | AC57: GW's analysis of the indirect effects of Malaria Consortium's SMC programs relative to Cisse et al. 2016
C59: Malaria prevalence reduction among people under age 15
E60: National population age 1 to 4 | F60: # | G60: input | H60: - | I60: =IFERROR(__xludf.DUMMYFUNCTION("FILTER('GBD estimates'!$H$4:$H$2400,'GBD estimates'!$B$4:$B$2400=I$2,'GBD estimates'!$D$4:$D$2400=""1 to 4"")"),3159819.734) -> 3159819.7 | J60: =IFERROR(__xludf.DUMMYFUNCTION("FILTER('GBD estimates'!$H$4:$H$2400,'GBD estimates'!$B$4:$B$2400=J$2,'GBD estimates'!$D$4:$D$2400=""1 to 4"")"),2593740.178) -> 2593740.2 | K60: =IFERROR(__xludf.DUMMYFUNCTION("FILTER('GBD estimates'!$H$4:$H$2400,'GBD estimates'!$B$4:$B$2400=K$2,'GBD estimates'!$D$4:$D$2400=""1 to 4"")"),1.082114861E7) -> 10821149 | L60: =IFERROR(__xludf.DUMMYFUNCTION("FILTER('GBD estimates'!$H$4:$H$2400,'GBD estimates'!$B$4:$B$2400=L$2,'GBD estimates'!$D$4:$D$2400=""1 to 4"")"),1.082114861E7) -> 10821149 | M60: =IFERROR(__xludf.DUMMYFUNCTION("FILTER('GBD estimates'!$H$4:$H$2400,'GBD estimates'!$B$4:$B$2400=M$2,'GBD estimates'!$D$4:$D$2400=""1 to 4"")"),1.082114861E7) -> 10821149 | N60: =IFERROR(__xludf.DUMMYFUNCTION("FILTER('GBD estimates'!$H$4:$H$2400,'GBD estimates'!$B$4:$B$2400=N$2,'GBD estimates'!$D$4:$D$2400=""1 to 4"")"),1.082114861E7) -> 10821149 | O60: =IFERROR(__xludf.DUMMYFUNCTION("FILTER('GBD estimates'!$H$4:$H$2400,'GBD estimates'!$B$4:$B$2400=O$2,'GBD estimates'!$D$4:$D$2400=""1 to 4"")"),4037237.425) -> 4037237.4 | P60: =IFERROR(__xludf.DUMMYFUNCTION("FILTER('GBD estimates'!$H$4:$H$2400,'GBD estimates'!$B$4:$B$2400=P$2,'GBD estimates'!$D$4:$D$2400=""1 to 4"")"),2.64010714E7) -> 26401071 | Q60: =IFERROR(__xludf.DUMMYFUNCTION("FILTER('GBD estimates'!$H$4:$H$2400,'GBD estimates'!$B$4:$B$2400=Q$2,'GBD estimates'!$D$4:$D$2400=""1 to 4"")"),2.64010714E7) -> 26401071 | R60: =IFERROR(__xludf.DUMMYFUNCTION("FILTER('GBD estimates'!$H$4:$H$2400,'GBD estimates'!$B$4:$B$2400=R$2,'GBD estimates'!$D$4:$D$2400=""1 to 4"")"),2.64010714E7) -> 26401071 | S60: =IFERROR(__xludf.DUMMYFUNCTION("FILTER('GBD estimates'!$H$4:$H$2400,'GBD estimates'!$B$4:$B$2400=S$2,'GBD estimates'!$D$4:$D$2400=""1 to 4"")"),2.64010714E7) -> 26401071 | T60: =IFERROR(__xludf.DUMMYFUNCTION("FILTER('GBD estimates'!$H$4:$H$2400,'GBD estimates'!$B$4:$B$2400=T$2,'GBD estimates'!$D$4:$D$2400=""1 to 4"")"),2.64010714E7) -> 26401071 | U60: =IFERROR(__xludf.DUMMYFUNCTION("FILTER('GBD estimates'!$H$4:$H$2400,'GBD estimates'!$B$4:$B$2400=U$2,'GBD estimates'!$D$4:$D$2400=""1 to 4"")"),2.64010714E7) -> 26401071 | V60: =IFERROR(__xludf.DUMMYFUNCTION("FILTER('GBD estimates'!$H$4:$H$2400,'GBD estimates'!$B$4:$B$2400=V$2,'GBD estimates'!$D$4:$D$2400=""1 to 4"")"),2.64010714E7) -> 26401071 | W60: =IFERROR(__xludf.DUMMYFUNCTION("FILTER('GBD estimates'!$H$4:$H$2400,'GBD estimates'!$B$4:$B$2400=W$2,'GBD estimates'!$D$4:$D$2400=""1 to 4"")"),2.64010714E7) -> 26401071 | X60: =IFERROR(__xludf.DUMMYFUNCTION("FILTER('GBD estimates'!$H$4:$H$2400,'GBD estimates'!$B$4:$B$2400=X$2,'GBD estimates'!$D$4:$D$2400=""1 to 4"")"),2.64010714E7) -> 26401071 | Y60: =IFERROR(__xludf.DUMMYFUNCTION("FILTER('GBD estimates'!$H$4:$H$2400,'GBD estimates'!$B$4:$B$2400=Y$2,'GBD estimates'!$D$4:$D$2400=""1 to 4"")"),887125.4327) -> 887125.43 | Z60: =IFERROR(__xludf.DUMMYFUNCTION("FILTER('GBD estimates'!$H$4:$H$2400,'GBD estimates'!$B$4:$B$2400=Z$2,'GBD estimates'!$D$4:$D$2400=""1 to 4"")"),5581405.246) -> 5581405.2 | AB60: GBD 2019
E61: National population age 5 to 14 | F61: # | G61: input | H61: - | I61: =IFERROR(__xludf.DUMMYFUNCTION("FILTER('GBD estimates'!$H$4:$H$2400,'GBD estimates'!$B$4:$B$2400=I$2,'GBD estimates'!$D$4:$D$2400=""5-14 years"")"),6348445.622) -> 6348445.6 | J61: =IFERROR(__xludf.DUMMYFUNCTION("FILTER('GBD estimates'!$H$4:$H$2400,'GBD estimates'!$B$4:$B$2400=J$2,'GBD estimates'!$D$4:$D$2400=""5-14 years"")"),4977421.002) -> 4977421 | K61: =IFERROR(__xludf.DUMMYFUNCTION("FILTER('GBD estimates'!$H$4:$H$2400,'GBD estimates'!$B$4:$B$2400=K$2,'GBD estimates'!$D$4:$D$2400=""5-14 years"")"),2.406568016E7) -> 24065680 | L61: =IFERROR(__xludf.DUMMYFUNCTION("FILTER('GBD estimates'!$H$4:$H$2400,'GBD estimates'!$B$4:$B$2400=L$2,'GBD estimates'!$D$4:$D$2400=""5-14 years"")"),2.406568016E7) -> 24065680 | M61: =IFERROR(__xludf.DUMMYFUNCTION("FILTER('GBD estimates'!$H$4:$H$2400,'GBD estimates'!$B$4:$B$2400=M$2,'GBD estimates'!$D$4:$D$2400=""5-14 years"")"),2.406568016E7) -> 24065680 | N61: =IFERROR(__xludf.DUMMYFUNCTION("FILTER('GBD estimates'!$H$4:$H$2400,'GBD estimates'!$B$4:$B$2400=N$2,'GBD estimates'!$D$4:$D$2400=""5-14 years"")"),2.406568016E7) -> 24065680 | O61: =IFERROR(__xludf.DUMMYFUNCTION("FILTER('GBD estimates'!$H$4:$H$2400,'GBD estimates'!$B$4:$B$2400=O$2,'GBD estimates'!$D$4:$D$2400=""5-14 years"")"),8658112.544) -> 8658112.5 | P61: =IFERROR(__xludf.DUMMYFUNCTION("FILTER('GBD estimates'!$H$4:$H$2400,'GBD estimates'!$B$4:$B$2400=P$2,'GBD estimates'!$D$4:$D$2400=""5-14 years"")"),6.022643653E7) -> 60226437 | Q61: =IFERROR(__xludf.DUMMYFUNCTION("FILTER('GBD estimates'!$H$4:$H$2400,'GBD estimates'!$B$4:$B$2400=Q$2,'GBD estimates'!$D$4:$D$2400=""5-14 years"")"),6.022643653E7) -> 60226437 | R61: =IFERROR(__xludf.DUMMYFUNCTION("FILTER('GBD estimates'!$H$4:$H$2400,'GBD estimates'!$B$4:$B$2400=R$2,'GBD estimates'!$D$4:$D$2400=""5-14 years"")"),6.022643653E7) -> 60226437 | S61: =IFERROR(__xludf.DUMMYFUNCTION("FILTER('GBD estimates'!$H$4:$H$2400,'GBD estimates'!$B$4:$B$2400=S$2,'GBD estimates'!$D$4:$D$2400=""5-14 years"")"),6.022643653E7) -> 60226437 | T61: =IFERROR(__xludf.DUMMYFUNCTION("FILTER('GBD estimates'!$H$4:$H$2400,'GBD estimates'!$B$4:$B$2400=T$2,'GBD estimates'!$D$4:$D$2400=""5-14 years"")"),6.022643653E7) -> 60226437 | U61: =IFERROR(__xludf.DUMMYFUNCTION("FILTER('GBD estimates'!$H$4:$H$2400,'GBD estimates'!$B$4:$B$2400=U$2,'GBD estimates'!$D$4:$D$2400=""5-14 years"")"),6.022643653E7) -> 60226437 | V61: =IFERROR(__xludf.DUMMYFUNCTION("FILTER('GBD estimates'!$H$4:$H$2400,'GBD estimates'!$B$4:$B$2400=V$2,'GBD estimates'!$D$4:$D$2400=""5-14 years"")"),6.022643653E7) -> 60226437 | W61: =IFERROR(__xludf.DUMMYFUNCTION("FILTER('GBD estimates'!$H$4:$H$2400,'GBD estimates'!$B$4:$B$2400=W$2,'GBD estimates'!$D$4:$D$2400=""5-14 years"")"),6.022643653E7) -> 60226437 | X61: =IFERROR(__xludf.DUMMYFUNCTION("FILTER('GBD estimates'!$H$4:$H$2400,'GBD estimates'!$B$4:$B$2400=X$2,'GBD estimates'!$D$4:$D$2400=""5-14 years"")"),6.022643653E7) -> 60226437 | Y61: =IFERROR(__xludf.DUMMYFUNCTION("FILTER('GBD estimates'!$H$4:$H$2400,'GBD estimates'!$B$4:$B$2400=Y$2,'GBD estimates'!$D$4:$D$2400=""5-14 years"")"),2032780.787) -> 2032780.8 | Z61: =IFERROR(__xludf.DUMMYFUNCTION("FILTER('GBD estimates'!$H$4:$H$2400,'GBD estimates'!$B$4:$B$2400=Z$2,'GBD estimates'!$D$4:$D$2400=""5-14 years"")"),1.198772212E7) -> 11987722 | AB61: GBD 2019
C63: Long-term income increases for people under age 15
E64: Increase in annual income per malaria case averted among people under age 15 | F64: % | G64: input | H64: 0.0064543 | I64: - | J64: - | K64: - | L64: - | M64: - | N64: - | O64: - | P64: - | Q64: - | R64: - | S64: - | T64: - | U64: - | V64: - | W64: - | X64: - | Y64: - | Z64: - | AB64: GW guesstimate | AC64: GW's analysis of malaria income effect size
E65: Average number of years between receiving SMC and the beginning of long-term benefits | F65: # | G65: input | H65: 12.5 | I65: - | J65: - | K65: - | L65: - | M65: - | N65: - | O65: - | P65: - | Q65: - | R65: - | S65: - | T65: - | U65: - | V65: - | W65: - | X65: - | Y65: - | Z65: - | AB65: GW guesstimate
E66: Discount rate for future benefits | F66: % | G66: input | H66: 0.04 | I66: - | J66: - | K66: - | L66: - | M66: - | N66: - | O66: - | P66: - | Q66: - | R66: - | S66: - | T66: - | U66: - | V66: - | W66: - | X66: - | Y66: - | Z66: - | AB66: GW analysis | AC66: GW's moral weights and discount rate
E67: Expected number of years the long-term benefits of receiving SMC will last | F67: # | G67: input | H67: 40 | I67: - | J67: - | K67: - | L67: - | M67: - | N67: - | O67: - | P67: - | Q67: - | R67: - | S67: - | T67: - | U67: - | V67: - | W67: - | X67: - | Y67: - | Z67: - | AB67: GW guesstimate
E68: Multiplier for resource sharing within households | F68: # | G68: input | H68: 2 | I68: - | J68: - | K68: - | L68: - | M68: - | N68: - | O68: - | P68: - | Q68: - | R68: - | S68: - | T68: - | U68: - | V68: - | W68: - | X68: - | Y68: - | Z68: - | AB68: GW analysis | AC68: GW's analysis on estimating multiplier for benefits experienced by other household members
A70: Value of outcomes
C72: Value of outcomes
E73: Value assigned to averting a malaria-attributable death of a person under age 5 | F73: UoV | G73: input | H73: 116.25262 | I73: - | J73: - | K73: - | L73: - | M73: - | N73: - | O73: - | P73: - | Q73: - | R73: - | S73: - | T73: - | U73: - | V73: - | W73: - | X73: - | Y73: - | Z73: - | AB73: GW value judgment | AC73: GW's moral weights and discount rate
E74: Value assigned to averting a malaria-attributable death of a person age 5 or older | F74: UoV | G74: input | H74: 73.1914 | I74: - | J74: - | K74: - | L74: - | M74: - | N74: - | O74: - | P74: - | Q74: - | R74: - | S74: - | T74: - | U74: - | V74: - | W74: - | X74: - | Y74: - | Z74: - | AB74: GW value judgment | AC74: GW's moral weights and discount rate
E75: Value assigned to doubling consumption for one person for one year | F75: UoV | G75: input | H75: 1 | I75: - | J75: - | K75: - | L75: - | M75: - | N75: - | O75: - | P75: - | Q75: - | R75: - | S75: - | T75: - | U75: - | V75: - | W75: - | X75: - | Y75: - | Z75: - | AB75: GW value judgment | AC75: GW's moral weights and discount rate
E76: Value assigned to increasing ln(consumption) by one unit for one person for one year | F76: UoV | G76: input | H76: =H75/ln(2) -> 1.442695 | I76: - | J76: - | K76: - | L76: - | M76: - | N76: - | O76: - | P76: - | Q76: - | R76: - | S76: - | T76: - | U76: - | V76: - | W76: - | X76: - | Y76: - | Z76: - | AB76: GW value judgment | AC76: GW's moral weights and discount rate
A78: Summary of outcomes and initial cost-effectiveness (before final adjustments)
C80: Cost-effectiveness benchmark
E81: Units of value per dollar spent, benchmark | F81: UoV | G81: input | H81: 0.00333 | I81: - | J81: - | K81: - | L81: - | M81: - | N81: - | O81: - | P81: - | Q81: - | R81: - | S81: - | T81: - | U81: - | V81: - | W81: - | X81: - | Y81: - | Z81: - | AB81: GW analysis | AC81: GWs benchmark for evaluating cost effectiveness
A83: Adjustments
C85: Supplemental grantee-level adjustments
D86: Risk of wastage
E87: Double treatment | F87: % | G87: input | H87: 0 | I87: - | J87: - | K87: - | L87: - | M87: - | N87: - | O87: - | P87: - | Q87: - | R87: - | S87: - | T87: - | U87: - | V87: - | W87: - | X87: - | Y87: - | Z87: - | AB87: GW guesstimate
E88: Ineffective goods | F88: % | G88: input | H88: 0 | I88: - | J88: - | K88: - | L88: - | M88: - | N88: - | O88: - | P88: - | Q88: - | R88: - | S88: - | T88: - | U88: - | V88: - | W88: - | X88: - | Y88: - | Z88: - | AB88: GW guesstimate
E89: Goods purchased and left in storage until they expire / cash doesn't receive recipients or is taken back from them inappropriately | F89: % | G89: input | H89: 0 | I89: - | J89: - | K89: - | L89: - | M89: - | N89: - | O89: - | P89: - | Q89: - | R89: - | S89: - | T89: - | U89: - | V89: - | W89: - | X89: - | Y89: - | Z89: - | AB89: GW guesstimate
D90: Quality of monitoring and evaluation
E91: Misappropriation without monitoring results | F91: % | G91: input | H91: 0 | I91: - | J91: - | K91: - | L91: - | M91: - | N91: - | O91: - | P91: - | Q91: - | R91: - | S91: - | T91: - | U91: - | V91: - | W91: - | X91: - | Y91: - | Z91: - | AB91: GW guesstimate
E92: False monitoring results | F92: % | G92: input | H92: -0.02 | I92: - | J92: - | K92: - | L92: - | M92: - | N92: - | O92: - | P92: - | Q92: - | R92: - | S92: - | T92: - | U92: - | V92: - | W92: - | X92: - | Y92: - | Z92: - | AB92: GW guesstimate
D93: Confidence in funds being used for intended purpose
E94: Change of priorities | F94: % | G94: input | H94: -0.01 | I94: - | J94: - | K94: - | L94: - | M94: - | N94: - | O94: - | P94: - | Q94: - | R94: - | S94: - | T94: - | U94: - | V94: - | W94: - | X94: - | Y94: - | Z94: - | AB94: GW guesstimate
E95: Non-funding bottlenecks | F95: % | G95: input | H95: 0 | I95: - | J95: - | K95: - | L95: - | M95: - | N95: - | O95: - | P95: - | Q95: - | R95: - | S95: - | T95: - | U95: - | V95: - | W95: - | X95: - | Y95: - | Z95: - | AB95: GW guesstimate
E96: Within-org fungibility | F96: % | G96: input | H96: -0.05 | I96: - | J96: - | K96: - | L96: - | M96: - | N96: - | O96: - | P96: - | Q96: - | R96: - | S96: - | T96: - | U96: - | V96: - | W96: - | X96: - | Y96: - | Z96: - | AB96: GW guesstimate
C98: Supplemental intervention-level adjustments
E99: Malaria morbidity | F99: % | G99: input | H99: 0.09 | I99: - | J99: - | K99: - | L99: - | M99: - | N99: - | O99: - | P99: - | Q99: - | R99: - | S99: - | T99: - | U99: - | V99: - | W99: - | X99: - | Y99: - | Z99: - | AB99: GW guesstimate | AC99: GW's supplemental intervention-level adjustments
E100: Short-term anemia effects | F100: % | G100: input | H100: 0.09 | I100: - | J100: - | K100: - | L100: - | M100: - | N100: - | O100: - | P100: - | Q100: - | R100: - | S100: - | T100: - | U100: - | V100: - | W100: - | X100: - | Y100: - | Z100: - | AB100: GW guesstimate | AC100: GW's supplemental intervention-level adjustments
E101: Investment of income increases | F101: % | G101: input | H101: 0.05 | I101: - | J101: - | K101: - | L101: - | M101: - | N101: - | O101: - | P101: - | Q101: - | R101: - | S101: - | T101: - | U101: - | V101: - | W101: - | X101: - | Y101: - | Z101: - | AB101: GW guesstimate | AC101: GW's supplemental intervention-level adjustments
E102: Treatment costs averted from prevention | F102: % | G102: input | H102: 0.2 | I102: - | J102: - | K102: - | L102: - | M102: - | N102: - | O102: - | P102: - | Q102: - | R102: - | S102: - | T102: - | U102: - | V102: - | W102: - | X102: - | Y102: - | Z102: - | AB102: GW guesstimate | AC102: GW's supplemental intervention-level adjustments
E103: Serious adverse events due to side effects of treatment | F103: % | G103: input | H103: -0.006 | I103: - | J103: - | K103: - | L103: - | M103: - | N103: - | O103: - | P103: - | Q103: - | R103: - | S103: - | T103: - | U103: - | V103: - | W103: - | X103: - | Y103: - | Z103: - | AB103: GW guesstimate | AC103: GW's supplemental intervention-level adjustments
E104: Failure to ingest first day of treatment of SMC | F104: % | G104: input | H104: -0.035 | I104: - | J104: - | K104: - | L104: - | M104: - | N104: - | O104: - | P104: - | Q104: - | R104: - | S104: - | T104: - | U104: - | V104: - | W104: - | X104: - | Y104: - | Z104: - | AB104: GW guesstimate | AC104: GW's supplemental intervention-level adjustments
E105: Rebound effects / decreased immunity development | F105: % | G105: input | H105: -0.04 | I105: - | J105: - | K105: - | L105: - | M105: - | N105: - | O105: - | P105: - | Q105: - | R105: - | S105: - | T105: - | U105: - | V105: - | W105: - | X105: - | Y105: - | Z105: - | AB105: GW guesstimate | AC105: GW's supplemental intervention-level adjustments
E106: Drug resistance | F106: % | G106: input | H106: - | I106: -0.04 | J106: -0.04 | K106: -0.1 | L106: -0.1 | M106: -0.1 | N106: -0.1 | O106: -0.1 | P106: -0.04 | Q106: -0.04 | R106: -0.04 | S106: -0.04 | T106: -0.04 | U106: -0.04 | V106: -0.04 | W106: -0.04 | X106: -0.04 | Y106: -0.04 | Z106: -0.1 | AB106: GW guesstimate | AC106: GW's supplemental intervention-level adjustments
E107: Subnational adjustments | F107: % | G107: input | H107: 0.032 | I107: - | J107: - | K107: - | L107: - | M107: - | N107: - | O107: - | P107: - | Q107: - | R107: - | S107: - | T107: - | U107: - | V107: - | W107: - | X107: - | Y107: - | Z107: - | AB107: GW guesstimate | AC107: GW's supplemental intervention-level adjustments
E108: Marginal funding goes to lower priority areas | F108: % | G108: input | H108: - | I108: -0.15 | J108: -0.1 | K108: 0 | L108: 0 | M108: 0 | N108: 0 | O108: 0 | P108: 0 | Q108: 0 | R108: 0 | S108: 0 | T108: 0 | U108: 0 | V108: 0 | W108: 0 | X108: 0 | Y108: -0.05 | Z108: 0 | AB108: GW guesstimate | AC108: GW's supplemental intervention-level adjustments
A110: Leverage and funging adjustment
C112: Probability of scenarios in the absence of philanthropic funding
E113: Scenario 1: Domestic governments would replace the grantee's costs | F113: % | G113: input | H113: - | I113: 0 | J113: 0 | K113: 0 | L113: 0 | M113: 0 | N113: 0 | O113: 0 | P113: 0 | Q113: 0 | R113: 0 | S113: 0 | T113: 0 | U113: 0 | V113: 0 | W113: 0 | X113: 0 | Y113: 0 | Z113: 0 | AB113: GW analysis | AC113: GW's analysis of leverage and funging risk for SMC
E114: Scenario 2: Global Fund and/or PMI would replace the grantee's costs | F114: % | G114: input | H114: - | I114: 0.5 | J114: 0.45 | K114: 0.15 | L114: 0.15 | M114: 0.15 | N114: 0.15 | O114: 0.2 | P114: 0.2 | Q114: 0.1 | R114: 0.1 | S114: 0.2 | T114: 0.1 | U114: 0.2 | V114: 0.2 | W114: 0.2 | X114: 0.2 | Y114: 0.65 | Z114: 0.3 | AB114: GW analysis | AC114: GW's analysis of leverage and funging risk for SMC
E115: Scenario 3: Other actors' upstream costs would stay the same (downstream costs would shrink in proportion to the total size of the program) | F115: % | G115: input | H115: - | I115: 0 | J115: 0 | K115: 0 | L115: 0 | M115: 0 | N115: 0 | O115: 0 | P115: 0 | Q115: 0 | R115: 0 | S115: 0 | T115: 0 | U115: 0 | V115: 0 | W115: 0 | X115: 0 | Y115: 0 | Z115: 0 | AB115: GW analysis | AC115: GW's analysis of leverage and funging risk for SMC
C117: Proportion of the program that would still occur in each scenario
E118: Scenario 1: Domestic governments would replace the grantee's costs | F118: % | G118: input | H118: 1 | I118: - | J118: - | K118: - | L118: - | M118: - | N118: - | O118: - | P118: - | Q118: - | R118: - | S118: - | T118: - | U118: - | V118: - | W118: - | X118: - | Y118: - | Z118: - | AB118: GW analysis
E119: Scenario 2: Global Fund and/or PMI would replace the grantee's costs | F119: % | G119: input | H119: 1 | I119: - | J119: - | K119: - | L119: - | M119: - | N119: - | O119: - | P119: - | Q119: - | R119: - | S119: - | T119: - | U119: - | V119: - | W119: - | X119: - | Y119: - | Z119: - | AB119: GW analysis
E120: Scenario 4: Distributions would go unfunded | F120: % | G120: input | H120: 0 | I120: - | J120: - | K120: - | L120: - | M120: - | N120: - | O120: - | P120: - | Q120: - | R120: - | S120: - | T120: - | U120: - | V120: - | W120: - | X120: - | Y120: - | Z120: - | AB120: GW analysis
C122: Counterfactual value of spending from non-philanthropic actors
E123: Counterfactual value per dollar spent by domestic governments | F123: UoV | G123: input | H123: 0.005057 | I123: - | J123: - | K123: - | L123: - | M123: - | N123: - | O123: - | P123: - | Q123: - | R123: - | S123: - | T123: - | U123: - | V123: - | W123: - | X123: - | Y123: - | Z123: - | AB123: GW analysis | AC123: GW's analysis of the counterfactual value of other actors' spending
E124: Counterfactual value per dollar spent by the Global Fund or PMI | F124: UoV | G124: input | H124: 0.015433 | I124: - | J124: - | K124: - | L124: - | M124: - | N124: - | O124: - | P124: - | Q124: - | R124: - | S124: - | T124: - | U124: - | V124: - | W124: - | X124: - | Y124: - | Z124: - | AB124: GW analysis | AC124: GW's analysis of the counterfactual value of Global Fund spending

Sheet GBD estimates
B2: Global Burden of Disease Study 2019 (GBD 2019) Population Estimates 1950-2019 | L2: GBD 2019 Results Tool: Malaria mortalities among people under age 5 | W2: GBD 2019 Results Tool: Malaria mortality rate among people under age 5 | AH2: GBD 2019 Results Tool: Malaria incidence (2019) | AS2: GBD 2019: Malaria mortalities among people under age 5 (Nigerian states) | BF2: GBD 2019: Malaria mortality rate among people under age 5 (Nigerian states) | BS2: GBD 2019: Malaria incidence rate among people under age 5 (Nigerian states)
B3: Location | C3: Sex | D3: Age group | E3: Year | F3: Measure | G3: Metric | H3: val | I3: upper | J3: lower | L3: measure | M3: location | N3: sex | O3: age | P3: cause | Q3: metric | R3: year | S3: val | T3: upper | U3: lower | W3: measure | X3: location | Y3: sex | Z3: age | AA3: cause | AB3: metric | AC3: year | AD3: val | AE3: upper | AF3: lower | AH3: measure | AI3: location | AJ3: sex | AK3: age | AL3: cause | AM3: metric | AN3: year | AO3: val | AP3: upper | AQ3: lower | AS3: Condition | AT3: Sex | AU3: Age | AV3: Location | AW3: Measure | AX3: Unit | AY3: Forecast Scenario | AZ3: Year | BA3: Value | BB3: Lower | BC3: Upper | BD3: Data Suite | BF3: Condition | BG3: Sex | BH3: Age | BI3: Location | BJ3: Measure | BK3: Unit | BL3: Forecast Scenario | BM3: Year | BN3: Value | BO3: Lower | BP3: Upper | BQ3: Data Suite | BS3: Condition | BT3: Sex | BU3: Age | BV3: Location | BW3: Measure | BX3: Unit | BY3: Forecast Scenario | BZ3: Year | CA3: Value | CB3: Lower | CC3: Upper | CD3: Data Suite
B4: Angola | C4: both | D4: <1 year | E4: 2019 | F4: Population | G4: Number | H4: 1060897.5 | I4: 1165729.5 | J4: 952349.72 | L4: Deaths | M4: Gambia | N4: Both | O4: <5 years | P4: Malaria | Q4: Number | R4: 2019 | S4: 138.28564 | T4: 449.29743 | U4: 35.259251 | W4: Deaths | X4: Angola | Y4: Both | Z4: <5 years | AA4: Malaria | AB4: Rate | AC4: 2019 | AD4: 117.45141 | AE4: 219.30664 | AF4: 50.300943 | AH4: Incidence | AI4: India | AJ4: Both | AK4: 5-14 years | AL4: Malaria | AM4: Rate | AN4: 2019 | AO4: 490.38606 | AP4: 1009.685 | AQ4: 226.732 | AS4: Malaria | AT4: Both | AU4: Under 5 | AV4: Abia | AW4: Deaths | AX4: Number | AY4: Past estimate | AZ4: 2019 | BA4: 2025.4445 | BB4: 1200.206 | BC4: 3034.5004 | BD4: GBD 2019 | BF4: Malaria | BG4: Both | BH4: Under 5 | BI4: Abia | BJ4: Deaths | BK4: Rate (per 100,000) | BL4: Past estimate | BM4: 2019 | BN4: 402.31599 | BO4: 238.39807 | BP4: 602.74575 | BQ4: GBD 2019 | BS4: Malaria | BT4: Both | BU4: 1 to 4 | BV4: Abia | BW4: Incidence | BX4: Rate (per 100,000) | BY4: Past estimate | BZ4: 2019 | CA4: 126179.71 | CB4: 34732.681 | CC4: 184925.81 | CD4: GBD 2019
B5: Angola | C5: both | D5: <20 years | E5: 2019 | F5: Population | G5: Number | H5: 17055870 | I5: 18741235 | J5: 15310765 | L5: Deaths | M5: Gambia | N5: Both | O5: 0-6 days | P5: Malaria | Q5: Number | R5: 2019 | S5: 0 | T5: 0 | U5: 0 | W5: Deaths | X5: Bangladesh | Y5: Both | Z5: <5 years | AA5: Malaria | AB5: Rate | AC5: 2019 | AD5: 0.00021243274 | AE5: 0.0012753086 | AF5: 4.52e-06 | AH5: Incidence | AI5: Somalia | AJ5: Both | AK5: 5-14 years | AL5: Malaria | AM5: Rate | AN5: 2019 | AO5: 11422.297 | AP5: 19989.444 | AQ5: 5341.921 | AS5: Malaria | AT5: Both | AU5: 7 to 27 days (late neonatal) | AV5: Abia | AW5: Deaths | AX5: Number | AY5: Past estimate | AZ5: 2019 | BA5: 146.91116 | BB5: 69.04558 | BC5: 258.87055 | BD5: GBD 2019 | BF5: Malaria | BG5: Both | BH5: Under 5 | BI5: Adamawa | BJ5: Deaths | BK5: Rate (per 100,000) | BL5: Past estimate | BM5: 2019 | BN5: 461.88107 | BO5: 138.51771 | BP5: 898.35824 | BQ5: GBD 2019 | BS5: Malaria | BT5: Both | BU5: 5 to 14 | BV5: Abia | BW5: Incidence | BX5: Rate (per 100,000) | BY5: Past estimate | BZ5: 2019 | CA5: 48591.687 | CB5: 18313.455 | CC5: 96630.527 | CD5: GBD 2019
B6: Angola | C6: both | D6: 0 to 14 | E6: 2019 | F6: Population | G6: Number | H6: 13987336 | I6: 15369486 | J6: 12556194 | L6: Deaths | M6: Gambia | N6: Both | O6: 7-27 days | P6: Malaria | Q6: Number | R6: 2019 | S6: 6.4296188 | T6: 25.08996 | U6: 1.3585762 | W6: Deaths | X6: Benin | Y6: Both | Z6: <5 years | AA6: Malaria | AB6: Rate | AC6: 2019 | AD6: 343.82215 | AE6: 584.3359 | AF6: 156.67061 | AH6: Incidence | AI6: Somalia | AJ6: Both | AK6: 1-4 years | AL6: Malaria | AM6: Rate | AN6: 2019 | AO6: 25864.918 | AP6: 59794.725 | AQ6: 7199.7711 | AS6: Malaria | AT6: Both | AU6: 28 to 364 days (post neonatal) | AV6: Abia | AW6: Deaths | AX6: Number | AY6: Past estimate | AZ6: 2019 | BA6: 736.35318 | BB6: 376.41044 | BC6: 1223.0604 | BD6: GBD 2019 | BF6: Malaria | BG6: Both | BH6: Under 5 | BI6: Akwa Ibom | BJ6: Deaths | BK6: Rate (per 100,000) | BL6: Past estimate | BM6: 2019 | BN6: 368.64871 | BO6: 207.20865 | BP6: 555.25442 | BQ6: GBD 2019 | BS6: Malaria | BT6: Both | BU6: 1 to 4 | BV6: Adamawa | BW6: Incidence | BX6: Rate (per 100,000) | BY6: Past estimate | BZ6: 2019 | CA6: 91183.877 | CB6: 22383.688 | CC6: 171798 | CD6: GBD 2019
B7: Angola | C7: both | D7: 1 to 4 | E7: 2019 | F7: Population | G7: Number | H7: 4086252.7 | I7: 4490033.3 | J7: 3668159.8 | L7: Deaths | M7: Gambia | N7: Both | O7: 28-364 days | P7: Malaria | Q7: Number | R7: 2019 | S7: 46.653134 | T7: 159.22005 | U7: 11.32949 | W7: Deaths | X7: Bhutan | Y7: Both | Z7: <5 years | AA7: Malaria | AB7: Rate | AC7: 2019 | AD7: 0 | AE7: 0 | AF7: 0 | AH7: Incidence | AI7: Zambia | AJ7: Both | AK7: 1-4 years | AL7: Malaria | AM7: Rate | AN7: 2019 | AO7: 38967.737 | AP7: 70692.621 | AQ7: 20503.828 | AS7: Malaria | AT7: Both | AU7: All Ages | AV7: Abia | AW7: Deaths | AX7: Number | AY7: Past estimate | AZ7: 2019 | BA7: 5644.0722 | BB7: 2969.679 | BC7: 9507.4757 | BD7: GBD 2019 | BF7: Malaria | BG7: Both | BH7: Under 5 | BI7: Anambra | BJ7: Deaths | BK7: Rate (per 100,000) | BL7: Past estimate | BM7: 2019 | BN7: 253.28008 | BO7: 115.25702 | BP7: 432.54526 | BQ7: GBD 2019 | BS7: Malaria | BT7: Both | BU7: 5 to 14 | BV7: Adamawa | BW7: Incidence | BX7: Rate (per 100,000) | BY7: Past estimate | BZ7: 2019 | CA7: 34976.673 | CB7: 11125.463 | CC7: 65890.529 | CD7: GBD 2019
B8: Angola | C8: both | D8: 10 to 14 | E8: 2019 | F8: Population | G8: Number | H8: 3998471.9 | I8: 4393578.5 | J8: 3589360.5 | L8: Deaths | M8: Gambia | N8: Both | O8: All ages | P8: Malaria | Q8: Number | R8: 2019 | S8: 637.4707 | T8: 2219.5441 | U8: 166.53101 | W8: Deaths | X8: Botswana | Y8: Both | Z8: <5 years | AA8: Malaria | AB8: Rate | AC8: 2019 | AD8: 2.3985318 | AE8: 6.8756803 | AF8: 0.42729726 | AH8: Incidence | AI8: Burkina Faso | AJ8: Both | AK8: 1-4 years | AL8: Malaria | AM8: Rate | AN8: 2019 | AO8: 60060.984 | AP8: 93833.721 | AQ8: 34224.577 | AS8: Malaria | AT8: Both | AU8: Under 5 | AV8: Adamawa | AW8: Deaths | AX8: Number | AY8: Past estimate | AZ8: 2019 | BA8: 2613.718 | BB8: 783.85167 | BC8: 5083.6791 | BD8: GBD 2019 | BF8: Malaria | BG8: Both | BH8: Under 5 | BI8: Bauchi | BJ8: Deaths | BK8: Rate (per 100,000) | BL8: Past estimate | BM8: 2019 | BN8: 255.6552 | BO8: 66.24142 | BP8: 626.88523 | BQ8: GBD 2019 | BS8: Malaria | BT8: Both | BU8: 1 to 4 | BV8: Akwa Ibom | BW8: Incidence | BX8: Rate (per 100,000) | BY8: Past estimate | BZ8: 2019 | CA8: 132397.76 | CB8: 43126.143 | CC8: 196081.89 | CD8: GBD 2019
B9: Angola | C9: both | D9: 10 to 19 | E9: 2019 | F9: Population | G9: Number | H9: 7067006.1 | I9: 7765327.9 | J9: 6343931.5 | L9: Deaths | M9: Gambia | N9: Both | O9: 5-14 years | P9: Malaria | Q9: Number | R9: 2019 | S9: 24.507282 | T9: 86.149491 | U9: 6.0451132 | W9: Deaths | X9: Burkina Faso | Y9: Both | Z9: <5 years | AA9: Malaria | AB9: Rate | AC9: 2019 | AD9: 405.32862 | AE9: 740.4159 | AF9: 169.8445 | AH9: Incidence | AI9: Kenya | AJ9: Both | AK9: 1-4 years | AL9: Malaria | AM9: Rate | AN9: 2019 | AO9: 29398.847 | AP9: 57076.176 | AQ9: 10022.622 | AS9: Malaria | AT9: Both | AU9: 7 to 27 days (late neonatal) | AV9: Adamawa | AW9: Deaths | AX9: Number | AY9: Past estimate | AZ9: 2019 | BA9: 95.103257 | BB9: 20.236414 | BC9: 225.46779 | BD9: GBD 2019 | BF9: Malaria | BG9: Both | BH9: Under 5 | BI9: Bayelsa | BJ9: Deaths | BK9: Rate (per 100,000) | BL9: Past estimate | BM9: 2019 | BN9: 220.89319 | BO9: 88.903426 | BP9: 399.01457 | BQ9: GBD 2019 | BS9: Malaria | BT9: Both | BU9: 5 to 14 | BV9: Akwa Ibom | BW9: Incidence | BX9: Rate (per 100,000) | BY9: Past estimate | BZ9: 2019 | CA9: 50147.684 | CB9: 18262.421 | CC9: 106089.34 | CD9: GBD 2019
B10: Angola | C10: both | D10: 10 to 24 | E10: 2019 | F10: Population | G10: Number | H10: 9628365.6 | I10: 10579787 | J10: 8643220.5 | L10: Deaths | M10: Comoros | N10: Both | O10: <5 years | P10: Malaria | Q10: Number | R10: 2019 | S10: 14.704695 | T10: 72.682168 | U10: 0.29707613 | W10: Deaths | X10: Burundi | Y10: Both | Z10: <5 years | AA10: Malaria | AB10: Rate | AC10: 2019 | AD10: 277.82055 | AE10: 550.37143 | AF10: 104.11669 | AH10: Incidence | AI10: Burkina Faso | AJ10: Both | AK10: 5-14 years | AL10: Malaria | AM10: Rate | AN10: 2019 | AO10: 24693.609 | AP10: 38635.958 | AQ10: 16809.516 | AS10: Malaria | AT10: Both | AU10: 28 to 364 days (post neonatal) | AV10: Adamawa | AW10: Deaths | AX10: Number | AY10: Past estimate | AZ10: 2019 | BA10: 564.31219 | BB10: 133.6525 | BC10: 1270.2649 | BD10: GBD 2019 | BF10: Malaria | BG10: Both | BH10: Under 5 | BI10: Benue | BJ10: Deaths | BK10: Rate (per 100,000) | BL10: Past estimate | BM10: 2019 | BN10: 306.51959 | BO10: 116.75827 | BP10: 569.1595 | BQ10: GBD 2019 | BS10: Malaria | BT10: Both | BU10: 1 to 4 | BV10: Anambra | BW10: Incidence | BX10: Rate (per 100,000) | BY10: Past estimate | BZ10: 2019 | CA10: 71493.621 | CB10: 10334.131 | CC10: 167559.67 | CD10: GBD 2019
B11: Angola | C11: both | D11: 15 to 19 | E11: 2019 | F11: Population | G11: Number | H11: 3068534.1 | I11: 3371749.5 | J11: 2754571.1 | L11: Deaths | M11: Comoros | N11: Both | O11: 0-6 days | P11: Malaria | Q11: Number | R11: 2019 | S11: 0 | T11: 0 | U11: 0 | W11: Deaths | X11: Cabo Verde | Y11: Both | Z11: <5 years | AA11: Malaria | AB11: Rate | AC11: 2019 | AD11: 9.9295586 | AE11: 69.146341 | AF11: 0.026603318 | AH11: Incidence | AI11: Zambia | AJ11: Both | AK11: 5-14 years | AL11: Malaria | AM11: Rate | AN11: 2019 | AO11: 16566.732 | AP11: 25701.206 | AQ11: 8401.6182 | AS11: Malaria | AT11: Both | AU11: All Ages | AV11: Adamawa | AW11: Deaths | AX11: Number | AY11: Past estimate | AZ11: 2019 | BA11: 4208.3027 | BB11: 1125.5973 | BC11: 8279.0443 | BD11: GBD 2019 | BF11: Malaria | BG11: Both | BH11: Under 5 | BI11: Borno | BJ11: Deaths | BK11: Rate (per 100,000) | BL11: Past estimate | BM11: 2019 | BN11: 178.17425 | BO11: 32.451519 | BP11: 404.35848 | BQ11: GBD 2019 | BS11: Malaria | BT11: Both | BU11: 5 to 14 | BV11: Anambra | BW11: Incidence | BX11: Rate (per 100,000) | BY11: Past estimate | BZ11: 2019 | CA11: 28807.451 | CB11: 6762.8227 | CC11: 77456.074 | CD11: GBD 2019
B12: Angola | C12: both | D12: 15 to 39 | E12: 2019 | F12: Population | G12: Number | H12: 11203690 | I12: 12311528 | J12: 10057585 | L12: Deaths | M12: Comoros | N12: Both | O12: 7-27 days | P12: Malaria | Q12: Number | R12: 2019 | S12: 0.34643545 | T12: 1.8996011 | U12: 0.00632715 | W12: Deaths | X12: Cameroon | Y12: Both | Z12: <5 years | AA12: Malaria | AB12: Rate | AC12: 2019 | AD12: 232.21919 | AE12: 435.08627 | AF12: 87.66352 | AH12: Incidence | AI12: Chad | AJ12: Both | AK12: 5-14 years | AL12: Malaria | AM12: Rate | AN12: 2019 | AO12: 16222.621 | AP12: 38103.808 | AQ12: 7414.9986 | AS12: Malaria | AT12: Both | AU12: Under 5 | AV12: Akwa Ibom | AW12: Deaths | AX12: Number | AY12: Past estimate | AZ12: 2019 | BA12: 1042.7678 | BB12: 586.11492 | BC12: 1570.6048 | BD12: GBD 2019 | BF12: Malaria | BG12: Both | BH12: Under 5 | BI12: Cross River | BJ12: Deaths | BK12: Rate (per 100,000) | BL12: Past estimate | BM12: 2019 | BN12: 264.89032 | BO12: 126.69431 | BP12: 446.65604 | BQ12: GBD 2019 | BS12: Malaria | BT12: Both | BU12: 1 to 4 | BV12: Bauchi | BW12: Incidence | BX12: Rate (per 100,000) | BY12: Past estimate | BZ12: 2019 | CA12: 47661.906 | CB12: 10878.529 | CC12: 114935.17 | CD12: GBD 2019
B13: Angola | C13: both | D13: 15-49 years | E13: 2019 | F13: Population | G13: Number | H13: 13529214 | I13: 14866095 | J13: 12144946 | L13: Deaths | M13: Comoros | N13: Both | O13: 28-364 days | P13: Malaria | Q13: Number | R13: 2019 | S13: 6.0877026 | T13: 31.925668 | U13: 0.12172982 | W13: Deaths | X13: CĆ´te d'Ivoire | Y13: Both | Z13: <5 years | AA13: Malaria | AB13: Rate | AC13: 2019 | AD13: 348.79557 | AE13: 575.4261 | AF13: 174.52541 | AH13: Incidence | AI13: India | AJ13: Both | AK13: 1-4 years | AL13: Malaria | AM13: Rate | AN13: 2019 | AO13: 422.91924 | AP13: 1065.7795 | AQ13: 155.27788 | AS13: Malaria | AT13: Both | AU13: 7 to 27 days (late neonatal) | AV13: Akwa Ibom | AW13: Deaths | AX13: Number | AY13: Past estimate | AZ13: 2019 | BA13: 80.972094 | BB13: 35.991154 | BC13: 144.84402 | BD13: GBD 2019 | BF13: Malaria | BG13: Both | BH13: Under 5 | BI13: Delta | BJ13: Deaths | BK13: Rate (per 100,000) | BL13: Past estimate | BM13: 2019 | BN13: 312.67607 | BO13: 111.18698 | BP13: 582.14831 | BQ13: GBD 2019 | BS13: Malaria | BT13: Both | BU13: 5 to 14 | BV13: Bauchi | BW13: Incidence | BX13: Rate (per 100,000) | BY13: Past estimate | BZ13: 2019 | CA13: 19593.148 | CB13: 6046.2066 | CC13: 40406.236 | CD13: GBD 2019
B14: Angola | C14: both | D14: 20 plus | E14: 2019 | F14: Population | G14: Number | H14: 13082292 | I14: 14375889 | J14: 11744011 | L14: Deaths | M14: Comoros | N14: Both | O14: All ages | P14: Malaria | Q14: Number | R14: 2019 | S14: 174.49318 | T14: 792.56375 | U14: 4.3136148 | W14: Deaths | X14: Central African Republic | Y14: Both | Z14: <5 years | AA14: Malaria | AB14: Rate | AC14: 2019 | AD14: 274.77822 | AE14: 561.69059 | AF14: 107.39738 | AH14: Incidence | AI14: Chad | AJ14: Both | AK14: 1-4 years | AL14: Malaria | AM14: Rate | AN14: 2019 | AO14: 37423.266 | AP14: 81929.595 | AQ14: 14315.445 | AS14: Malaria | AT14: Both | AU14: 28 to 364 days (post neonatal) | AV14: Akwa Ibom | AW14: Deaths | AX14: Number | AY14: Past estimate | AZ14: 2019 | BA14: 385.15703 | BB14: 188.17243 | BC14: 626.62484 | BD14: GBD 2019 | BF14: Malaria | BG14: Both | BH14: Under 5 | BI14: Ebonyi | BJ14: Deaths | BK14: Rate (per 100,000) | BL14: Past estimate | BM14: 2019 | BN14: 431.77174 | BO14: 180.66682 | BP14: 761.94853 | BQ14: GBD 2019 | BS14: Malaria | BT14: Both | BU14: 1 to 4 | BV14: Bayelsa | BW14: Incidence | BX14: Rate (per 100,000) | BY14: Past estimate | BZ14: 2019 | CA14: 91871.029 | CB14: 21595.338 | CC14: 174570.9 | CD14: GBD 2019
B15: Angola | C15: both | D15: 20 to 24 | E15: 2019 | F15: Population | G15: Number | H15: 2561359.5 | I15: 2814458.7 | J15: 2299289 | L15: Deaths | M15: Comoros | N15: Both | O15: 5-14 years | P15: Malaria | Q15: Number | R15: 2019 | S15: 8.3960988 | T15: 38.642985 | U15: 0.20156633 | W15: Deaths | X15: Chad | Y15: Both | Z15: <5 years | AA15: Malaria | AB15: Rate | AC15: 2019 | AD15: 135.79914 | AE15: 328.48689 | AF15: 40.006937 | AH15: Incidence | AI15: Kenya | AJ15: Both | AK15: 5-14 years | AL15: Malaria | AM15: Rate | AN15: 2019 | AO15: 12152.384 | AP15: 23117.956 | AQ15: 5931.3612 | AS15: Malaria | AT15: Both | AU15: All Ages | AV15: Akwa Ibom | AW15: Deaths | AX15: Number | AY15: Past estimate | AZ15: 2019 | BA15: 3262.4958 | BB15: 1600.0075 | BC15: 5521.0984 | BD15: GBD 2019 | BF15: Malaria | BG15: Both | BH15: Under 5 | BI15: Edo | BJ15: Deaths | BK15: Rate (per 100,000) | BL15: Past estimate | BM15: 2019 | BN15: 295.86279 | BO15: 128.70519 | BP15: 515.86852 | BQ15: GBD 2019 | BS15: Malaria | BT15: Both | BU15: 5 to 14 | BV15: Bayelsa | BW15: Incidence | BX15: Rate (per 100,000) | BY15: Past estimate | BZ15: 2019 | CA15: 36160.028 | CB15: 12420.655 | CC15: 81346.722 | CD15: GBD 2019
... B40: Angola | C40: both | D40: 85 plus | E40: 2019 | F40: Population | G40: Number | H40: 28097.263 | I40: 30875.563 | J40: 25222.993 | L40: Deaths | M40: Ethiopia | N40: Both | O40: All ages | P40: Malaria | Q40: Number | R40: 2019 | S40: 13103.663 | T40: 34632.111 | U40: 2584.9356 | W40: Deaths | X40: Niger | Y40: Both | Z40: <5 years | AA40: Malaria | AB40: Rate | AC40: 2019 | AD40: 341.33616 | AE40: 686.30117 | AF40: 117.26006 | AH40: Incidence | AI40: Rwanda | AJ40: Both | AK40: 5-14 years | AL40: Malaria | AM40: Rate | AN40: 2019 | AO40: 5641.1675 | AP40: 14412.19 | AQ40: 2025.1666 | AS40: Malaria | AT40: Both | AU40: Under 5 | AV40: Delta | AW40: Deaths | AX40: Number | AY40: Past estimate | AZ40: 2019 | BA40: 1589.7065 | BB40: 565.29642 | BC40: 2959.7563 | BD40: GBD 2019 | BF40: Malaria | BG40: Both | BH40: Under 5 | BI40: Zamfara | BJ40: Deaths | BK40: Rate (per 100,000) | BL40: Past estimate | BM40: 2019 | BN40: 312.96214 | BO40: 61.596522 | BP40: 708.67897 | BQ40: GBD 2019 | BS40: Malaria | BT40: Both | BU40: 1 to 4 | BV40: Kaduna | BW40: Incidence | BX40: Rate (per 100,000) | BY40: Past estimate | BZ40: 2019 | CA40: 69112.496 | CB40: 22314.054 | CC40: 140498.95 | CD40: GBD 2019
B41: Angola | C41: both | D41: 85 to 89 | E41: 2019 | F41: Population | G41: Number | H41: 20550.491 | I41: 22581.175 | J41: 18447.827 | L41: Deaths | M41: Ethiopia | N41: Both | O41: 5-14 years | P41: Malaria | Q41: Number | R41: 2019 | S41: 627.62348 | T41: 1732.497 | U41: 117.9122 | W41: Deaths | X41: Nigeria | Y41: Both | Z41: <5 years | AA41: Malaria | AB41: Rate | AC41: 2019 | AD41: 285.2967 | AE41: 517.11085 | AF41: 133.93314 | AH41: Incidence | AI41: Bangladesh | AJ41: Both | AK41: 1-4 years | AL41: Malaria | AM41: Rate | AN41: 2019 | AO41: 1.9664837 | AP41: 8.5253851 | AQ41: 0.2040962 | AS41: Malaria | AT41: Both | AU41: 7 to 27 days (late neonatal) | AV41: Delta | AW41: Deaths | AX41: Number | AY41: Past estimate | AZ41: 2019 | BA41: 79.404373 | BB41: 18.640166 | BC41: 189.39753 | BD41: GBD 2019 | BS41: Malaria | BT41: Both | BU41: 5 to 14 | BV41: Kaduna | BW41: Incidence | BX41: Rate (per 100,000) | BY41: Past estimate | BZ41: 2019 | CA41: 27045.225 | CB41: 8581.4701 | CC41: 53106.171 | CD41: GBD 2019
B42: Angola | C42: both | D42: 90 to 94 | E42: 2019 | F42: Population | G42: Number | H42: 6232.5855 | I42: 6848.4546 | J42: 5594.8863 | L42: Deaths | M42: Niger | N42: Both | O42: <5 years | P42: Malaria | Q42: Number | R42: 2019 | S42: 16564.578 | T42: 33305.26 | U42: 5690.4707 | W42: Deaths | X42: Pakistan | Y42: Both | Z42: <5 years | AA42: Malaria | AB42: Rate | AC42: 2019 | AD42: 1.733758 | AE42: 4.6966185 | AF42: 0.43422529 | AH42: Incidence | AI42: South Africa | AJ42: Both | AK42: 1-4 years | AL42: Malaria | AM42: Rate | AN42: 2019 | AO42: 256.15355 | AP42: 1970.8798 | AQ42: 2.9292151 | AS42: Malaria | AT42: Both | AU42: 28 to 364 days (post neonatal) | AV42: Delta | AW42: Deaths | AX42: Number | AY42: Past estimate | AZ42: 2019 | BA42: 458.36718 | BB42: 128.38832 | BC42: 1011.2091 | BD42: GBD 2019 | BS42: Malaria | BT42: Both | BU42: 1 to 4 | BV42: Kano | BW42: Incidence | BX42: Rate (per 100,000) | BY42: Past estimate | BZ42: 2019 | CA42: 28602.585 | CB42: 3895.9823 | CC42: 96556.552 | CD42: GBD 2019
B43: Angola | C43: both | D43: 95 plus | E43: 2019 | F43: Population | G43: Number | H43: 1314.9574 | I43: 1444.8941 | J43: 1180.415 | L43: Deaths | M43: Niger | N43: Both | O43: 0-6 days | P43: Malaria | Q43: Number | R43: 2019 | S43: 0 | T43: 0 | U43: 0 | W43: Deaths | X43: Rwanda | Y43: Both | Z43: <5 years | AA43: Malaria | AB43: Rate | AC43: 2019 | AD43: 127.07054 | AE43: 271.45848 | AF43: 46.351566 | AH43: Incidence | AI43: South Africa | AJ43: Both | AK43: 5-14 years | AL43: Malaria | AM43: Rate | AN43: 2019 | AO43: 229.03535 | AP43: 1578.6145 | AQ43: 5.3413046 | AS43: Malaria | AT43: Both | AU43: All Ages | AV43: Delta | AW43: Deaths | AX43: Number | AY43: Past estimate | AZ43: 2019 | BA43: 3269.0618 | BB43: 1076.1187 | BC43: 7078.5528 | BD43: GBD 2019 | BS43: Malaria | BT43: Both | BU43: 5 to 14 | BV43: Kano | BW43: Incidence | BX43: Rate (per 100,000) | BY43: Past estimate | BZ43: 2019 | CA43: 12477.716 | CB43: 2394.0993 | CC43: 31885.18 | CD43: GBD 2019
B44: Angola | C44: both | D44: All Ages | E44: 2019 | F44: Population | G44: Number | H44: 30138521 | I44: 33116641 | J44: 27054840 | L44: Deaths | M44: Niger | N44: Both | O44: 7-27 days | P44: Malaria | Q44: Number | R44: 2019 | S44: 623.02961 | T44: 1467.0566 | U44: 165.99143 | W44: Deaths | X44: Sao Tome and Principe | Y44: Both | Z44: <5 years | AA44: Malaria | AB44: Rate | AC44: 2019 | AD44: 33.218382 | AE44: 77.511241 | AF44: 9.4207413 | AH44: Incidence | AI44: Gabon | AJ44: Both | AK44: 5-14 years | AL44: Malaria | AM44: Rate | AN44: 2019 | AO44: 31543.414 | AP44: 58783.344 | AQ44: 13627.227 | AS44: Malaria | AT44: Both | AU44: Under 5 | AV44: Ebonyi | AW44: Deaths | AX44: Number | AY44: Past estimate | AZ44: 2019 | BA44: 1889.2697 | BB44: 790.52963 | BC44: 3333.9983 | BD44: GBD 2019 | BS44: Malaria | BT44: Both | BU44: 1 to 4 | BV44: Katsina | BW44: Incidence | BX44: Rate (per 100,000) | BY44: Past estimate | BZ44: 2019 | CA44: 37883.543 | CB44: 7564.7785 | CC44: 101176.35 | CD44: GBD 2019
B45: Angola | C45: both | D45: Birth | E45: 2019 | F45: Population | G45: Number | H45: 1104438.8 | I45: 1214100.5 | J45: 999012.36 | L45: Deaths | M45: Niger | N45: Both | O45: 28-364 days | P45: Malaria | Q45: Number | R45: 2019 | S45: 3829.9242 | T45: 8037.5573 | U45: 1203.8981 | W45: Deaths | X45: Senegal | Y45: Both | Z45: <5 years | AA45: Malaria | AB45: Rate | AC45: 2019 | AD45: 92.945191 | AE45: 259.28207 | AF45: 13.869034 | AH45: Incidence | AI45: Ghana | AJ45: Both | AK45: 5-14 years | AL45: Malaria | AM45: Rate | AN45: 2019 | AO45: 26425.992 | AP45: 50293.977 | AQ45: 14953.471 | AS45: Malaria | AT45: Both | AU45: 7 to 27 days (late neonatal) | AV45: Ebonyi | AW45: Deaths | AX45: Number | AY45: Past estimate | AZ45: 2019 | BA45: 94.082263 | BB45: 29.208727 | BC45: 215.55375 | BD45: GBD 2019 | BS45: Malaria | BT45: Both | BU45: 5 to 14 | BV45: Katsina | BW45: Incidence | BX45: Rate (per 100,000) | BY45: Past estimate | BZ45: 2019 | CA45: 16054.048 | CB45: 3275.2002 | CC45: 32120.87 | CD45: GBD 2019
B46: Angola | C46: both | D46: Early Neonatal | E46: 2019 | F46: Population | G46: Number | H46: 21032.612 | I46: 23110.936 | J46: 18880.619 | L46: Deaths | M46: Niger | N46: Both | O46: All ages | P46: Malaria | Q46: Number | R46: 2019 | S46: 23821.79 | T46: 48710.808 | U46: 8061.7011 | W46: Deaths | X46: Sierra Leone | Y46: Both | Z46: <5 years | AA46: Malaria | AB46: Rate | AC46: 2019 | AD46: 524.05262 | AE46: 886.73781 | AF46: 224.83278 | AH46: Incidence | AI46: Gabon | AJ46: Both | AK46: 1-4 years | AL46: Malaria | AM46: Rate | AN46: 2019 | AO46: 83693.129 | AP46: 152854.99 | AQ46: 29994.335 | AS46: Malaria | AT46: Both | AU46: 28 to 364 days (post neonatal) | AV46: Ebonyi | AW46: Deaths | AX46: Number | AY46: Past estimate | AZ46: 2019 | BA46: 527.88322 | BB46: 171.48281 | BC46: 1123.1357 | BD46: GBD 2019 | BS46: Malaria | BT46: Both | BU46: 1 to 4 | BV46: Kebbi | BW46: Incidence | BX46: Rate (per 100,000) | BY46: Past estimate | BZ46: 2019 | CA46: 85869.026 | CB46: 28590.995 | CC46: 145703.33 | CD46: GBD 2019
B47: Angola | C47: both | D47: Late Neonatal | E47: 2019 | F47: Population | G47: Number | H47: 62342.203 | I47: 68502.51 | J47: 55963.539 | L47: Deaths | M47: Niger | N47: Both | O47: 5-14 years | P47: Malaria | Q47: Number | R47: 2019 | S47: 800.82273 | T47: 1777.8222 | U47: 246.53464 | W47: Deaths | X47: Somalia | Y47: Both | Z47: <5 years | AA47: Malaria | AB47: Rate | AC47: 2019 | AD47: 64.611706 | AE47: 162.94863 | AF47: 19.5078 | AH47: Incidence | AI47: Liberia | AJ47: Both | AK47: 1-4 years | AL47: Malaria | AM47: Rate | AN47: 2019 | AO47: 112843.84 | AP47: 166478.33 | AQ47: 44825.622 | AS47: Malaria | AT47: Both | AU47: All Ages | AV47: Ebonyi | AW47: Deaths | AX47: Number | AY47: Past estimate | AZ47: 2019 | BA47: 3798.3945 | BB47: 1448.5191 | BC47: 7736.806 | BD47: GBD 2019 | BS47: Malaria | BT47: Both | BU47: 5 to 14 | BV47: Kebbi | BW47: Incidence | BX47: Rate (per 100,000) | BY47: Past estimate | BZ47: 2019 | CA47: 33795.629 | CB47: 14920.306 | CC47: 72288.739 | CD47: GBD 2019
B48: Angola | C48: both | D48: Neonatal | E48: 2019 | F48: Population | G48: Number | H48: 83374.815 | I48: 91613.446 | J48: 74844.158 | L48: Deaths | M48: Benin | N48: Both | O48: <5 years | P48: Malaria | Q48: Number | R48: 2019 | S48: 7660.5447 | T48: 13019.322 | U48: 3490.7064 | W48: Deaths | X48: South Africa | Y48: Both | Z48: <5 years | AA48: Malaria | AB48: Rate | AC48: 2019 | AD48: 0.76124881 | AE48: 6.2997636 | AF48: 0.015528067 | AH48: Incidence | AI48: Zimbabwe | AJ48: Both | AK48: 1-4 years | AL48: Malaria | AM48: Rate | AN48: 2019 | AO48: 4244.9478 | AP48: 20441.562 | AQ48: 354.77327 | AS48: Malaria | AT48: Both | AU48: Under 5 | AV48: Edo | AW48: Deaths | AX48: Number | AY48: Past estimate | AZ48: 2019 | BA48: 1244.2209 | BB48: 541.2566 | BC48: 2169.4327 | BD48: GBD 2019 | BS48: Malaria | BT48: Both | BU48: 1 to 4 | BV48: Kogi | BW48: Incidence | BX48: Rate (per 100,000) | BY48: Past estimate | BZ48: 2019 | CA48: 76182.967 | CB48: 10378.785 | CC48: 162076.07 | CD48: GBD 2019
B49: Angola | C49: both | D49: Post Neonatal | E49: 2019 | F49: Population | G49: Number | H49: 977522.71 | I49: 1074116 | J49: 877505.56 | L49: Deaths | M49: Benin | N49: Both | O49: 0-6 days | P49: Malaria | Q49: Number | R49: 2019 | S49: 0 | T49: 0 | U49: 0 | W49: Deaths | X49: South Sudan | Y49: Both | Z49: <5 years | AA49: Malaria | AB49: Rate | AC49: 2019 | AD49: 264.46645 | AE49: 496.79642 | AF49: 85.754887 | AH49: Incidence | AI49: Zimbabwe | AJ49: Both | AK49: 5-14 years | AL49: Malaria | AM49: Rate | AN49: 2019 | AO49: 3382.5798 | AP49: 13012.384 | AQ49: 509.97148 | AS49: Malaria | AT49: Both | AU49: 7 to 27 days (late neonatal) | AV49: Edo | AW49: Deaths | AX49: Number | AY49: Past estimate | AZ49: 2019 | BA49: 78.523686 | BB49: 24.33519 | BC49: 173.49284 | BD49: GBD 2019 | BS49: Malaria | BT49: Both | BU49: 5 to 14 | BV49: Kogi | BW49: Incidence | BX49: Rate (per 100,000) | BY49: Past estimate | BZ49: 2019 | CA49: 29812.038 | CB49: 10578.477 | CC49: 73480.88 | CD49: GBD 2019
B50: Angola | C50: both | D50: Under 5 | E50: 2019 | F50: Population | G50: Number | H50: 5147150.3 | I50: 5655762.7 | J50: 4620509.5 | L50: Deaths | M50: Benin | N50: Both | O50: 7-27 days | P50: Malaria | Q50: Number | R50: 2019 | S50: 308.97854 | T50: 607.74843 | U50: 118.86269 | W50: Deaths | X50: Togo | Y50: Both | Z50: <5 years | AA50: Malaria | AB50: Rate | AC50: 2019 | AD50: 168.66836 | AE50: 347.00812 | AF50: 62.755711 | AH50: Incidence | AI50: Djibouti | AJ50: Both | AK50: 5-14 years | AL50: Malaria | AM50: Rate | AN50: 2019 | AO50: 4505.2053 | AP50: 29764.736 | AQ50: 41.426396 | AS50: Malaria | AT50: Both | AU50: 28 to 364 days (post neonatal) | AV50: Edo | AW50: Deaths | AX50: Number | AY50: Past estimate | AZ50: 2019 | BA50: 409.21702 | BB50: 142.68719 | BC50: 817.13527 | BD50: GBD 2019 | BS50: Malaria | BT50: Both | BU50: 1 to 4 | BV50: Kwara | BW50: Incidence | BX50: Rate (per 100,000) | BY50: Past estimate | BZ50: 2019 | CA50: 120864.05 | CB50: 52268.128 | CC50: 185875.29 | CD50: GBD 2019
B51: Bangladesh | C51: both | D51: <1 year | E51: 2019 | F51: Population | G51: Number | H51: 2634237.6 | I51: 2941774.6 | J51: 2335516 | L51: Deaths | M51: Benin | N51: Both | O51: 28-364 days | P51: Malaria | Q51: Number | R51: 2019 | S51: 2633.1984 | T51: 4718.3124 | U51: 1169.1651 | W51: Deaths | X51: Uganda | Y51: Both | Z51: <5 years | AA51: Malaria | AB51: Rate | AC51: 2019 | AD51: 245.22396 | AE51: 437.90896 | AF51: 92.542789 | AH51: Incidence | AI51: Guinea | AJ51: Both | AK51: 5-14 years | AL51: Malaria | AM51: Rate | AN51: 2019 | AO51: 29839.074 | AP51: 55533.264 | AQ51: 15847.425 | AS51: Malaria | AT51: Both | AU51: All Ages | AV51: Edo | AW51: Deaths | AX51: Number | AY51: Past estimate | AZ51: 2019 | BA51: 3244.5027 | BB51: 1217.4061 | BC51: 6194.5293 | BD51: GBD 2019 | BS51: Malaria | BT51: Both | BU51: 5 to 14 | BV51: Kwara | BW51: Incidence | BX51: Rate (per 100,000) | BY51: Past estimate | BZ51: 2019 | CA51: 45307.766 | CB51: 19893.471 | CC51: 91539.151 | CD51: GBD 2019
B52: Bangladesh | C52: both | D52: <20 years | E52: 2019 | F52: Population | G52: Number | H52: 59367610 | I52: 66298548 | J52: 52635345 | L52: Deaths | M52: Benin | N52: Both | O52: All ages | P52: Malaria | Q52: Number | R52: 2019 | S52: 13263.969 | T52: 24203.424 | U52: 5733.2203 | W52: Deaths | X52: Tanzania | Y52: Both | Z52: <5 years | AA52: Malaria | AB52: Rate | AC52: 2019 | AD52: 143.59021 | AE52: 280.79355 | AF52: 57.121817 | AH52: Incidence | AI52: Cameroon | AJ52: Both | AK52: 1-4 years | AL52: Malaria | AM52: Rate | AN52: 2019 | AO52: 71817.496 | AP52: 131526.6 | AQ52: 28837.605 | AS52: Malaria | AT52: Both | AU52: Under 5 | AV52: Ekiti | AW52: Deaths | AX52: Number | AY52: Past estimate | AZ52: 2019 | BA52: 775.59979 | BB52: 425.8913 | BC52: 1237.4093 | BD52: GBD 2019 | BS52: Malaria | BT52: Both | BU52: 1 to 4 | BV52: Lagos | BW52: Incidence | BX52: Rate (per 100,000) | BY52: Past estimate | BZ52: 2019 | CA52: 67976.314 | CB52: 23276.049 | CC52: 150324.98 | CD52: GBD 2019
... B54: Bangladesh | C54: both | D54: 1 to 4 | E54: 2019 | F54: Population | G54: Number | H54: 11111674 | I54: 12408919 | J54: 9851614.3 | L54: Deaths | M54: Congo | N54: Both | O54: <5 years | P54: Malaria | Q54: Number | R54: 2019 | S54: 734.00894 | T54: 1400.8385 | U54: 261.61254 | W54: Deaths | X54: Zimbabwe | Y54: Both | Z54: <5 years | AA54: Malaria | AB54: Rate | AC54: 2019 | AD54: 57.204338 | AE54: 156.39909 | AF54: 6.4159521 | AH54: Incidence | AI54: Madagascar | AJ54: Both | AK54: 5-14 years | AL54: Malaria | AM54: Rate | AN54: 2019 | AO54: 10463.392 | AP54: 16650.013 | AQ54: 5582.6396 | AS54: Malaria | AT54: Both | AU54: 28 to 364 days (post neonatal) | AV54: Ekiti | AW54: Deaths | AX54: Number | AY54: Past estimate | AZ54: 2019 | BA54: 255.84743 | BB54: 115.59707 | BC54: 452.79718 | BD54: GBD 2019 | BS54: Malaria | BT54: Both | BU54: 1 to 4 | BV54: Nasarawa | BW54: Incidence | BX54: Rate (per 100,000) | BY54: Past estimate | BZ54: 2019 | CA54: 89798.633 | CB54: 15862.247 | CC54: 181615.08 | CD54: GBD 2019
B55: Bangladesh | C55: both | D55: 10 to 14 | E55: 2019 | F55: Population | G55: Number | H55: 15384844 | I55: 17180965 | J55: 13640208 | L55: Deaths | M55: Congo | N55: Both | O55: 0-6 days | P55: Malaria | Q55: Number | R55: 2019 | S55: 0 | T55: 0 | U55: 0 | AH55: Incidence | AI55: Congo | AJ55: Both | AK55: 5-14 years | AL55: Malaria | AM55: Rate | AN55: 2019 | AO55: 28330.388 | AP55: 55372.859 | AQ55: 14662.158 | AS55: Malaria | AT55: Both | AU55: All Ages | AV55: Ekiti | AW55: Deaths | AX55: Number | AY55: Past estimate | AZ55: 2019 | BA55: 2130.8266 | BB55: 1018.9632 | BC55: 3763.7798 | BD55: GBD 2019 | BS55: Malaria | BT55: Both | BU55: 5 to 14 | BV55: Nasarawa | BW55: Incidence | BX55: Rate (per 100,000) | BY55: Past estimate | BZ55: 2019 | CA55: 33528.333 | CB55: 11744.678 | CC55: 69036.728 | CD55: GBD 2019
B56: Bangladesh | C56: both | D56: 10 to 19 | E56: 2019 | F56: Population | G56: Number | H56: 30703530 | I56: 34288048 | J56: 27221761 | L56: Deaths | M56: Congo | N56: Both | O56: 7-27 days | P56: Malaria | Q56: Number | R56: 2019 | S56: 56.481594 | T56: 116.91599 | U56: 19.789412 | AH56: Incidence | AI56: Uganda | AJ56: Both | AK56: 5-14 years | AL56: Malaria | AM56: Rate | AN56: 2019 | AO56: 27394.999 | AP56: 55512.54 | AQ56: 13774.021 | AS56: Malaria | AT56: Both | AU56: Under 5 | AV56: Enugu | AW56: Deaths | AX56: Number | AY56: Past estimate | AZ56: 2019 | BA56: 1067.6421 | BB56: 518.55618 | BC56: 1907.5792 | BD56: GBD 2019 | BS56: Malaria | BT56: Both | BU56: 1 to 4 | BV56: Niger | BW56: Incidence | BX56: Rate (per 100,000) | BY56: Past estimate | BZ56: 2019 | CA56: 90724.599 | CB56: 31442.108 | CC56: 153622.42 | CD56: GBD 2019
B57: Bangladesh | C57: both | D57: 10 to 24 | E57: 2019 | F57: Population | G57: Number | H57: 45315333 | I57: 50605722 | J57: 40176591 | L57: Deaths | M57: Congo | N57: Both | O57: 28-364 days | P57: Malaria | Q57: Number | R57: 2019 | S57: 218.83664 | T57: 449.94562 | U57: 77.554895 | AH57: Incidence | AI57: Cameroon | AJ57: Both | AK57: 5-14 years | AL57: Malaria | AM57: Rate | AN57: 2019 | AO57: 27944.266 | AP57: 48179.81 | AQ57: 15016.769 | AS57: Malaria | AT57: Both | AU57: 7 to 27 days (late neonatal) | AV57: Enugu | AW57: Deaths | AX57: Number | AY57: Past estimate | AZ57: 2019 | BA57: 79.292631 | BB57: 29.009476 | BC57: 189.3582 | BD57: GBD 2019 | BS57: Malaria | BT57: Both | BU57: 5 to 14 | BV57: Niger | BW57: Incidence | BX57: Rate (per 100,000) | BY57: Past estimate | BZ57: 2019 | CA57: 35092.102 | CB57: 14722.658 | CC57: 75465.448 | CD57: GBD 2019
B58: Bangladesh | C58: both | D58: 15 to 19 | E58: 2019 | F58: Population | G58: Number | H58: 15318686 | I58: 17107083 | J58: 13581553 | L58: Deaths | M58: Congo | N58: Both | O58: All ages | P58: Malaria | Q58: Number | R58: 2019 | S58: 2102.129 | T58: 4389.4653 | U58: 726.96889 | AH58: Incidence | AI58: Djibouti | AJ58: Both | AK58: 1-4 years | AL58: Malaria | AM58: Rate | AN58: 2019 | AO58: 7180.6257 | AP58: 54294.484 | AQ58: 23.174389 | AS58: Malaria | AT58: Both | AU58: 28 to 364 days (post neonatal) | AV58: Enugu | AW58: Deaths | AX58: Number | AY58: Past estimate | AZ58: 2019 | BA58: 386.71522 | BB58: 154.82824 | BC58: 770.21877 | BD58: GBD 2019 | BS58: Malaria | BT58: Both | BU58: 1 to 4 | BV58: Ogun | BW58: Incidence | BX58: Rate (per 100,000) | BY58: Past estimate | BZ58: 2019 | CA58: 114787.05 | CB58: 57893.429 | CC58: 179212.28 | CD58: GBD 2019
B59: Bangladesh | C59: both | D59: 15 to 39 | E59: 2019 | F59: Population | G59: Number | H59: 67803097 | I59: 75724239 | J59: 60115635 | L59: Deaths | M59: Congo | N59: Both | O59: 5-14 years | P59: Malaria | Q59: Number | R59: 2019 | S59: 139.0769 | T59: 279.68163 | U59: 52.017164 | AH59: Incidence | AI59: Sao Tome and Principe | AJ59: Both | AK59: 1-4 years | AL59: Malaria | AM59: Rate | AN59: 2019 | AO59: 2644.0691 | AP59: 4248.5243 | AQ59: 875.00298 | AS59: Malaria | AT59: Both | AU59: All Ages | AV59: Enugu | AW59: Deaths | AX59: Number | AY59: Past estimate | AZ59: 2019 | BA59: 3556.3712 | BB59: 1482.2725 | BC59: 7748.6966 | BD59: GBD 2019 | BS59: Malaria | BT59: Both | BU59: 5 to 14 | BV59: Ogun | BW59: Incidence | BX59: Rate (per 100,000) | BY59: Past estimate | BZ59: 2019 | CA59: 43169.967 | CB59: 22793.766 | CC59: 80634.296 | CD59: GBD 2019
B60: Bangladesh | C60: both | D60: 15-49 years | E60: 2019 | F60: Population | G60: Number | H60: 86164879 | I60: 96224293 | J60: 76393813 | L60: Deaths | M60: Cabo Verde | N60: Both | O60: <5 years | P60: Malaria | Q60: Number | R60: 2019 | S60: 5.277809 | T60: 36.753011 | U60: 0.014140329 | AH60: Incidence | AI60: Lesotho | AJ60: Both | AK60: 1-4 years | AL60: Malaria | AM60: Rate | AN60: 2019 | AO60: 0 | AP60: 0 | AQ60: 0 | AS60: Malaria | AT60: Both | AU60: Under 5 | AV60: FCT (Abuja) | AW60: Deaths | AX60: Number | AY60: Past estimate | AZ60: 2019 | BA60: 1882.0325 | BB60: 794.72126 | BC60: 3313.6163 | BD60: GBD 2019 | BS60: Malaria | BT60: Both | BU60: 1 to 4 | BV60: Ondo | BW60: Incidence | BX60: Rate (per 100,000) | BY60: Past estimate | BZ60: 2019 | CA60: 113608.23 | CB60: 32822.611 | CC60: 196186 | CD60: GBD 2019
B61: Bangladesh | C61: both | D61: 20 plus | E61: 2019 | F61: Population | G61: Number | H61: 99889476 | I61: 1.1155913e+08 | J61: 88564086 | L61: Deaths | M61: Cabo Verde | N61: Both | O61: 0-6 days | P61: Malaria | Q61: Number | R61: 2019 | S61: 0 | T61: 0 | U61: 0 | AH61: Incidence | AI61: Benin | AJ61: Both | AK61: 5-14 years | AL61: Malaria | AM61: Rate | AN61: 2019 | AO61: 42747.546 | AP61: 78705.929 | AQ61: 26041.858 | AS61: Malaria | AT61: Both | AU61: 7 to 27 days (late neonatal) | AV61: FCT (Abuja) | AW61: Deaths | AX61: Number | AY61: Past estimate | AZ61: 2019 | BA61: 112.95511 | BB61: 35.449493 | BC61: 247.887 | BD61: GBD 2019 | BS61: Malaria | BT61: Both | BU61: 5 to 14 | BV61: Ondo | BW61: Incidence | BX61: Rate (per 100,000) | BY61: Past estimate | BZ61: 2019 | CA61: 42822.54 | CB61: 16970.646 | CC61: 86099.497 | CD61: GBD 2019
B62: Bangladesh | C62: both | D62: 20 to 24 | E62: 2019 | F62: Population | G62: Number | H62: 14611803 | I62: 16317674 | J62: 12954830 | L62: Deaths | M62: Cabo Verde | N62: Both | O62: 7-27 days | P62: Malaria | Q62: Number | R62: 2019 | S62: 0.28736209 | T62: 1.7151457 | U62: 0.000440924 | AH62: Incidence | AI62: Benin | AJ62: Both | AK62: 1-4 years | AL62: Malaria | AM62: Rate | AN62: 2019 | AO62: 113806.95 | AP62: 151668.64 | AQ62: 77613.773 | AS62: Malaria | AT62: Both | AU62: 28 to 364 days (post neonatal) | AV62: FCT (Abuja) | AW62: Deaths | AX62: Number | AY62: Past estimate | AZ62: 2019 | BA62: 590.61836 | BB62: 199.53972 | BC62: 1211.3072 | BD62: GBD 2019 | BS62: Malaria | BT62: Both | BU62: 1 to 4 | BV62: Osun | BW62: Incidence | BX62: Rate (per 100,000) | BY62: Past estimate | BZ62: 2019 | CA62: 118840.96 | CB62: 43143.591 | CC62: 191769.17 | CD62: GBD 2019
B63: Bangladesh | C63: both | D63: 25 plus | E63: 2019 | F63: Population | G63: Number | H63: 85280436 | I63: 95236596 | J63: 75609666 | L63: Deaths | M63: Cabo Verde | N63: Both | O63: 28-364 days | P63: Malaria | Q63: Number | R63: 2019 | S63: 3.2042993 | T63: 22.824195 | U63: 0.008560918 | AH63: Incidence | AI63: Mali | AJ63: Both | AK63: 1-4 years | AL63: Malaria | AM63: Rate | AN63: 2019 | AO63: 42479.559 | AP63: 69048.142 | AQ63: 19018.495 | AS63: Malaria | AT63: Both | AU63: All Ages | AV63: FCT (Abuja) | AW63: Deaths | AX63: Number | AY63: Past estimate | AZ63: 2019 | BA63: 4417.5464 | BB63: 1780.1837 | BC63: 8246.2941 | BD63: GBD 2019 | BS63: Malaria | BT63: Both | BU63: 5 to 14 | BV63: Osun | BW63: Incidence | BX63: Rate (per 100,000) | BY63: Past estimate | BZ63: 2019 | CA63: 45392.551 | CB63: 14921.575 | CC63: 92520.516 | CD63: GBD 2019
B64: Bangladesh | C64: both | D64: 25 to 29 | E64: 2019 | F64: Population | G64: Number | H64: 13893664 | I64: 15515696 | J64: 12318128 | L64: Deaths | M64: Cabo Verde | N64: Both | O64: All ages | P64: Malaria | Q64: Number | R64: 2019 | S64: 8.5316251 | T64: 54.300756 | U64: 0.018439852 | AH64: Incidence | AI64: Guinea-Bissau | AJ64: Both | AK64: 1-4 years | AL64: Malaria | AM64: Rate | AN64: 2019 | AO64: 28676.335 | AP64: 80677.292 | AQ64: 5590.3422 | AS64: Malaria | AT64: Both | AU64: Under 5 | AV64: Gombe | AW64: Deaths | AX64: Number | AY64: Past estimate | AZ64: 2019 | BA64: 2410.0205 | BB64: 721.7842 | BC64: 5278.9862 | BD64: GBD 2019 | BS64: Malaria | BT64: Both | BU64: 1 to 4 | BV64: Oyo | BW64: Incidence | BX64: Rate (per 100,000) | BY64: Past estimate | BZ64: 2019 | CA64: 130288.46 | CB64: 62633.288 | CC64: 190413.63 | CD64: GBD 2019
B65: Bangladesh | C65: both | D65: 25 to 49 | E65: 2019 | F65: Population | G65: Number | H65: 56232834 | I65: 62802273 | J65: 49857199 | L65: Deaths | M65: Cabo Verde | N65: Both | O65: 5-14 years | P65: Malaria | Q65: Number | R65: 2019 | S65: 0.017473196 | T65: 0.094457019 | U65: 1.9961647e-05 | AH65: Incidence | AI65: Guinea-Bissau | AJ65: Both | AK65: 5-14 years | AL65: Malaria | AM65: Rate | AN65: 2019 | AO65: 12906.885 | AP65: 30335.178 | AQ65: 2909.024 | AS65: Malaria | AT65: Both | AU65: 7 to 27 days (late neonatal) | AV65: Gombe | AW65: Deaths | AX65: Number | AY65: Past estimate | AZ65: 2019 | BA65: 73.710282 | BB65: 18.416752 | BC65: 209.15569 | BD65: GBD 2019 | BS65: Malaria | BT65: Both | BU65: 5 to 14 | BV65: Oyo | BW65: Incidence | BX65: Rate (per 100,000) | BY65: Past estimate | BZ65: 2019 | CA65: 48687.087 | CB65: 21857.389 | CC65: 92267.614 | CD65: GBD 2019
B66: Bangladesh | C66: both | D66: 30 to 34 | E66: 2019 | F66: Population | G66: Number | H66: 12819236 | I66: 14315832 | J66: 11365539 | L66: Deaths | M66: Gabon | N66: Both | O66: <5 years | P66: Malaria | Q66: Number | R66: 2019 | S66: 228.36803 | T66: 457.12743 | U66: 90.005026 | AH66: Incidence | AI66: Nigeria | AJ66: Both | AK66: 5-14 years | AL66: Malaria | AM66: Rate | AN66: 2019 | AO66: 30218.504 | AP66: 49149.49 | AQ66: 18693.551 | AS66: Malaria | AT66: Both | AU66: 28 to 364 days (post neonatal) | AV66: Gombe | AW66: Deaths | AX66: Number | AY66: Past estimate | AZ66: 2019 | BA66: 416.07107 | BB66: 102.71471 | BC66: 1098.8126 | BD66: GBD 2019 | BS66: Malaria | BT66: Both | BU66: 1 to 4 | BV66: Plateau | BW66: Incidence | BX66: Rate (per 100,000) | BY66: Past estimate | BZ66: 2019 | CA66: 63655.295 | CB66: 11866.666 | CC66: 156110.88 | CD66: GBD 2019
... B77: Bangladesh | C77: both | D77: 60 to 64 | E77: 2019 | F77: Population | G77: Number | H77: 4971113.7 | I77: 5551471.9 | J77: 4407391.2 | L77: Deaths | M77: Senegal | N77: Both | O77: 5-14 years | P77: Malaria | Q77: Number | R77: 2019 | S77: 280.56292 | T77: 816.38413 | U77: 36.924163 | AH77: Incidence | AI77: Mozambique | AJ77: Both | AK77: 1-4 years | AL77: Malaria | AM77: Rate | AN77: 2019 | AO77: 83471.636 | AP77: 110652.24 | AQ77: 57911.878 | AS77: Malaria | AT77: Both | AU77: 7 to 27 days (late neonatal) | AV77: Kaduna | AW77: Deaths | AX77: Number | AY77: Past estimate | AZ77: 2019 | BA77: 184.67609 | BB77: 49.850615 | BC77: 470.2465 | BD77: GBD 2019 | BS77: Malaria | BT77: Both | BU77: 5 to 14 | BV77: Zamfara | BW77: Incidence | BX77: Rate (per 100,000) | BY77: Past estimate | BZ77: 2019 | CA77: 26962.508 | CB77: 6685.1798 | CC77: 57261.471 | CD77: GBD 2019
B78: Bangladesh | C78: both | D78: 65 to 69 | E78: 2019 | F78: Population | G78: Number | H78: 3881865.2 | I78: 4335057.8 | J78: 3441663.1 | L78: Deaths | M78: Uganda | N78: Both | O78: <5 years | P78: Malaria | Q78: Number | R78: 2019 | S78: 17385.765 | T78: 31046.65 | U78: 6561.0522 | AH78: Incidence | AI78: Mozambique | AJ78: Both | AK78: 5-14 years | AL78: Malaria | AM78: Rate | AN78: 2019 | AO78: 32584.045 | AP78: 50940.581 | AQ78: 20759.735 | AS78: Malaria | AT78: Both | AU78: 28 to 364 days (post neonatal) | AV78: Kaduna | AW78: Deaths | AX78: Number | AY78: Past estimate | AZ78: 2019 | BA78: 1090.7619 | BB78: 302.81754 | BC78: 2635.118 | BD78: GBD 2019
B79: Bangladesh | C79: both | D79: 65 to 74 | E79: 2019 | F79: Population | G79: Number | H79: 6867936.5 | I79: 7670287.9 | J79: 6089255.3 | L79: Deaths | M79: Uganda | N79: Both | O79: 0-6 days | P79: Malaria | Q79: Number | R79: 2019 | S79: 0 | T79: 0 | U79: 0 | AH79: Incidence | AI79: Ghana | AJ79: Both | AK79: 1-4 years | AL79: Malaria | AM79: Rate | AN79: 2019 | AO79: 67042.509 | AP79: 109229.1 | AQ79: 30489.654 | AS79: Malaria | AT79: Both | AU79: All Ages | AV79: Kaduna | AW79: Deaths | AX79: Number | AY79: Past estimate | AZ79: 2019 | BA79: 8362.1862 | BB79: 2740.1542 | BC79: 17195.675 | BD79: GBD 2019
B80: Bangladesh | C80: both | D80: 70 to 74 | E80: 2019 | F80: Population | G80: Number | H80: 2986261.3 | I80: 3334895.7 | J80: 2647620.4 | L80: Deaths | M80: Uganda | N80: Both | O80: 7-27 days | P80: Malaria | Q80: Number | R80: 2019 | S80: 1000.2433 | T80: 2136.2965 | U80: 309.58074 | AH80: Incidence | AI80: Namibia | AJ80: Both | AK80: 5-14 years | AL80: Malaria | AM80: Rate | AN80: 2019 | AO80: 8444.9008 | AP80: 59544.242 | AQ80: 185.92927 | AS80: Malaria | AT80: Both | AU80: Under 5 | AV80: Kano | AW80: Deaths | AX80: Number | AY80: Past estimate | AZ80: 2019 | BA80: 7803.7954 | BB80: 1535.6603 | BC80: 22187.889 | BD80: GBD 2019
B81: Bangladesh | C81: both | D81: 70+ years | E81: 2019 | F81: Population | G81: Number | H81: 6964174.1 | I81: 7777214.3 | J81: 6174439.3 | L81: Deaths | M81: Uganda | N81: Both | O81: 28-364 days | P81: Malaria | Q81: Number | R81: 2019 | S81: 7448.5499 | T81: 13272.726 | U81: 2882.1354 | AH81: Incidence | AI81: Nepal | AJ81: Both | AK81: 1-4 years | AL81: Malaria | AM81: Rate | AN81: 2019 | AO81: 2.1508734 | AP81: 8.6741 | AQ81: 0.31843706 | AS81: Malaria | AT81: Both | AU81: 7 to 27 days (late neonatal) | AV81: Kano | AW81: Deaths | AX81: Number | AY81: Past estimate | AZ81: 2019 | BA81: 193.68513 | BB81: 34.109975 | BC81: 633.88095 | BD81: GBD 2019
B82: Bangladesh | C82: both | D82: 75 plus | E82: 2019 | F82: Population | G82: Number | H82: 3977802.7 | I82: 4442512.2 | J82: 3526802.6 | L82: Deaths | M82: Uganda | N82: Both | O82: All ages | P82: Malaria | Q82: Number | R82: 2019 | S82: 22586.593 | T82: 43010.429 | U82: 7949.3569 | AH82: Incidence | AI82: Liberia | AJ82: Both | AK82: 5-14 years | AL82: Malaria | AM82: Rate | AN82: 2019 | AO82: 42035.054 | AP82: 69863.091 | AQ82: 22032.812 | AS82: Malaria | AT82: Both | AU82: 28 to 364 days (post neonatal) | AV82: Kano | AW82: Deaths | AX82: Number | AY82: Past estimate | AZ82: 2019 | BA82: 1132.7102 | BB82: 193.49374 | BC82: 3625.652 | BD82: GBD 2019
B83: Bangladesh | C83: both | D83: 75 to 79 | E83: 2019 | F83: Population | G83: Number | H83: 2053049.7 | I83: 2292735.3 | J83: 1820234.6 | L83: Deaths | M83: Uganda | N83: Both | O83: 5-14 years | P83: Malaria | Q83: Number | R83: 2019 | S83: 1231.1284 | T83: 2607.4541 | U83: 377.75806 | AH83: Incidence | AI83: Namibia | AJ83: Both | AK83: 1-4 years | AL83: Malaria | AM83: Rate | AN83: 2019 | AO83: 14045.576 | AP83: 115947.13 | AQ83: 114.30997 | AS83: Malaria | AT83: Both | AU83: All Ages | AV83: Kano | AW83: Deaths | AX83: Number | AY83: Past estimate | AZ83: 2019 | BA83: 10157.759 | BB83: 2021.7706 | BC83: 29669.435 | BD83: GBD 2019
B84: Bangladesh | C84: both | D84: 75 to 84 | E84: 2019 | F84: Population | G84: Number | H84: 3248638.5 | I84: 3628162.9 | J84: 2880310.4 | L84: Deaths | M84: Guinea | N84: Both | O84: <5 years | P84: Malaria | Q84: Number | R84: 2019 | S84: 8181.1025 | T84: 15280.052 | U84: 3222.5077 | AH84: Incidence | AI84: Sierra Leone | AJ84: Both | AK84: 1-4 years | AL84: Malaria | AM84: Rate | AN84: 2019 | AO84: 97584.257 | AP84: 162237.48 | AQ84: 31987.043 | AS84: Malaria | AT84: Both | AU84: Under 5 | AV84: Katsina | AW84: Deaths | AX84: Number | AY84: Past estimate | AZ84: 2019 | BA84: 4177.6012 | BB84: 810.41445 | BC84: 10506.424 | BD84: GBD 2019
B85: Bangladesh | C85: both | D85: 80 plus | E85: 2019 | F85: Population | G85: Number | H85: 1924863 | I85: 2149583.3 | J85: 1706584.3 | L85: Deaths | M85: Guinea | N85: Both | O85: 0-6 days | P85: Malaria | Q85: Number | R85: 2019 | S85: 0 | T85: 0 | U85: 0 | AH85: Incidence | AI85: Sierra Leone | AJ85: Both | AK85: 5-14 years | AL85: Malaria | AM85: Rate | AN85: 2019 | AO85: 35829.518 | AP85: 67861.97 | AQ85: 19084.835 | AS85: Malaria | AT85: Both | AU85: 7 to 27 days (late neonatal) | AV85: Katsina | AW85: Deaths | AX85: Number | AY85: Past estimate | AZ85: 2019 | BA85: 90.674687 | BB85: 15.914337 | BC85: 254.81256 | BD85: GBD 2019
B86: Bangladesh | C86: both | D86: 80 to 84 | E86: 2019 | F86: Population | G86: Number | H86: 1195678.7 | I86: 1335269.5 | J86: 1060089.1 | L86: Deaths | M86: Guinea | N86: Both | O86: 7-27 days | P86: Malaria | Q86: Number | R86: 2019 | S86: 438.58032 | T86: 957.98809 | U86: 155.4646 | AH86: Incidence | AI86: Eritrea | AJ86: Both | AK86: 5-14 years | AL86: Malaria | AM86: Rate | AN86: 2019 | AO86: 2036.4347 | AP86: 6185.8834 | AQ86: 514.51092 | AS86: Malaria | AT86: Both | AU86: 28 to 364 days (post neonatal) | AV86: Katsina | AW86: Deaths | AX86: Number | AY86: Past estimate | AZ86: 2019 | BA86: 578.23956 | BB86: 101.67519 | BC86: 1555.1799 | BD86: GBD 2019
B87: Bangladesh | C87: both | D87: 85 plus | E87: 2019 | F87: Population | G87: Number | H87: 729164.21 | I87: 814349.31 | J87: 646492.14 | L87: Deaths | M87: Guinea | N87: Both | O87: 28-364 days | P87: Malaria | Q87: Number | R87: 2019 | S87: 2497.8419 | T87: 4886.6302 | U87: 932.54029 | AH87: Incidence | AI87: Côte d'Ivoire | AJ87: Both | AK87: 1-4 years | AL87: Malaria | AM87: Rate | AN87: 2019 | AO87: 99877.184 | AP87: 155438.32 | AQ87: 57468.958 | AS87: Malaria | AT87: Both | AU87: All Ages | AV87: Katsina | AW87: Deaths | AX87: Number | AY87: Past estimate | AZ87: 2019 | BA87: 5451.2463 | BB87: 1086.0182 | BC87: 13978.416 | BD87: GBD 2019
B88: Bangladesh | C88: both | D88: 85 to 89 | E88: 2019 | F88: Population | G88: Number | H88: 550941.69 | I88: 615261.99 | J88: 488465.1 | L88: Deaths | M88: Guinea | N88: Both | O88: All ages | P88: Malaria | Q88: Number | R88: 2019 | S88: 11336.501 | T88: 22065.809 | U88: 4354.0934 | AH88: Incidence | AI88: Côte d'Ivoire | AJ88: Both | AK88: 5-14 years | AL88: Malaria | AM88: Rate | AN88: 2019 | AO88: 37591.985 | AP88: 67350.402 | AQ88: 21275.896 | AS88: Malaria | AT88: Both | AU88: Under 5 | AV88: Kebbi | AW88: Deaths | AX88: Number | AY88: Past estimate | AZ88: 2019 | BA88: 3140.5093 | BB88: 938.8709 | BC88: 6431.5945 | BD88: GBD 2019
B89: Bangladesh | C89: both | D89: 90 to 94 | E89: 2019 | F89: Population | G89: Number | H89: 152687.71 | I89: 170513.41 | J89: 135372.98 | L89: Deaths | M89: Guinea | N89: Both | O89: 5-14 years | P89: Malaria | Q89: Number | R89: 2019 | S89: 267.92671 | T89: 590.63212 | U89: 89.768577 | AH89: Incidence | AI89: Niger | AJ89: Both | AK89: 1-4 years | AL89: Malaria | AM89: Rate | AN89: 2019 | AO89: 52970.249 | AP89: 99668.928 | AQ89: 16478.096 | AS89: Malaria | AT89: Both | AU89: 7 to 27 days (late neonatal) | AV89: Kebbi | AW89: Deaths | AX89: Number | AY89: Past estimate | AZ89: 2019 | BA89: 84.235263 | BB89: 21.664792 | BC89: 206.64645 | BD89: GBD 2019
... B105: Benin | C105: both | D105: 15 to 19 | E105: 2019 | F105: Population | G105: Number | H105: 1340791.1 | I105: 1480254.3 | J105: 1198000.9 | L105: Deaths | M105: Zambia | N105: Both | O105: 5-14 years | P105: Malaria | Q105: Number | R105: 2019 | S105: 505.59364 | T105: 1064.3378 | U105: 160.1096 | AH105: Incidence | AI105: South Sudan | AJ105: Both | AK105: 5-14 years | AL105: Malaria | AM105: Rate | AN105: 2019 | AO105: 24977.745 | AP105: 44732.505 | AQ105: 12396.692 | AS105: Malaria | AT105: Both | AU105: 7 to 27 days (late neonatal) | AV105: Nasarawa | AW105: Deaths | AX105: Number | AY105: Past estimate | AZ105: 2019 | BA105: 97.972762 | BB105: 27.537119 | BC105: 205.29733 | BD105: GBD 2019
B106: Benin | C106: both | D106: 15 to 39 | E106: 2019 | F106: Population | G106: Number | H106: 4887393.8 | I106: 5395880.9 | J106: 4366734.8 | L106: Deaths | M106: Burundi | N106: Both | O106: <5 years | P106: Malaria | Q106: Number | R106: 2019 | S106: 5775.8088 | T106: 11442.063 | U106: 2164.5558 | AS106: Malaria | AT106: Both | AU106: 28 to 364 days (post neonatal) | AV106: Nasarawa | AW106: Deaths | AX106: Number | AY106: Past estimate | AZ106: 2019 | BA106: 584.21623 | BB106: 170.22369 | BC106: 1201.5416 | BD106: GBD 2019
B107: Benin | C107: both | D107: 15-49 years | E107: 2019 | F107: Population | G107: Number | H107: 5823842.2 | I107: 6429612.3 | J107: 5203620.5 | L107: Deaths | M107: Burundi | N107: Both | O107: 0-6 days | P107: Malaria | Q107: Number | R107: 2019 | S107: 0 | T107: 0 | U107: 0 | AS107: Malaria | AT107: Both | AU107: All Ages | AV107: Nasarawa | AW107: Deaths | AX107: Number | AY107: Past estimate | AZ107: 2019 | BA107: 4449.5988 | BB107: 1484.2792 | BC107: 8065.6361 | BD107: GBD 2019
B108: Benin | C108: both | D108: 20 plus | E108: 2019 | F108: Population | G108: Number | H108: 5563282.3 | I108: 6142089.2 | J108: 4970620.3 | L108: Deaths | M108: Burundi | N108: Both | O108: 7-27 days | P108: Malaria | Q108: Number | R108: 2019 | S108: 372.94918 | T108: 809.60153 | U108: 137.22831 | AS108: Malaria | AT108: Both | AU108: Under 5 | AV108: Niger | AW108: Deaths | AX108: Number | AY108: Past estimate | AZ108: 2019 | BA108: 5603.3545 | BB108: 2017.1356 | BC108: 11593.227 | BD108: GBD 2019
B109: Benin | C109: both | D109: 20 to 24 | E109: 2019 | F109: Population | G109: Number | H109: 1157654.3 | I109: 1278068.3 | J109: 1034367.6 | L109: Deaths | M109: Burundi | N109: Both | O109: 28-364 days | P109: Malaria | Q109: Number | R109: 2019 | S109: 2515.4432 | T109: 4896.5198 | U109: 957.48606 | AS109: Malaria | AT109: Both | AU109: 7 to 27 days (late neonatal) | AV109: Niger | AW109: Deaths | AX109: Number | AY109: Past estimate | AZ109: 2019 | BA109: 186.39485 | BB109: 57.222936 | BC109: 470.18248 | BD109: GBD 2019
B110: Benin | C110: both | D110: 25 plus | E110: 2019 | F110: Population | G110: Number | H110: 4405622.1 | I110: 4863875.3 | J110: 3936436.5 | L110: Deaths | M110: Burundi | N110: Both | O110: All ages | P110: Malaria | Q110: Number | R110: 2019 | S110: 7279.8828 | T110: 14854.845 | U110: 2823.0274 | AS110: Malaria | AT110: Both | AU110: 28 to 364 days (post neonatal) | AV110: Niger | AW110: Deaths | AX110: Number | AY110: Past estimate | AZ110: 2019 | BA110: 1104.5886 | BB110: 347.88696 | BC110: 2734.2166 | BD110: GBD 2019
B111: Benin | C111: both | D111: 25 to 29 | E111: 2019 | F111: Population | G111: Number | H111: 972108.33 | I111: 1073222.7 | J111: 868581.7 | L111: Deaths | M111: Burundi | N111: Both | O111: 5-14 years | P111: Malaria | Q111: Number | R111: 2019 | S111: 324.59688 | T111: 693.76552 | U111: 122.23818 | AS111: Malaria | AT111: Both | AU111: All Ages | AV111: Niger | AW111: Deaths | AX111: Number | AY111: Past estimate | AZ111: 2019 | BA111: 9093.9392 | BB111: 3283.7966 | BC111: 19558.098 | BD111: GBD 2019
B112: Benin | C112: both | D112: 25 to 49 | E112: 2019 | F112: Population | G112: Number | H112: 3325400.3 | I112: 3671376.8 | J112: 2971142.1 | L112: Deaths | M112: Bangladesh | N112: Both | O112: <5 years | P112: Malaria | Q112: Number | R112: 2019 | S112: 0.029200817 | T112: 0.17530279 | U112: 0.000621395 | AS112: Malaria | AT112: Both | AU112: Under 5 | AV112: Ogun | AW112: Deaths | AX112: Number | AY112: Past estimate | AZ112: 2019 | BA112: 4655.8321 | BB112: 2410.7184 | BC112: 7466.7383 | BD112: GBD 2019
B113: Benin | C113: both | D113: 30 to 34 | E113: 2019 | F113: Population | G113: Number | H113: 779117.56 | I113: 860157.9 | J113: 696143.87 | L113: Deaths | M113: Bangladesh | N113: Both | O113: 0-6 days | P113: Malaria | Q113: Number | R113: 2019 | S113: 0 | T113: 0 | U113: 0 | AS113: Malaria | AT113: Both | AU113: 7 to 27 days (late neonatal) | AV113: Ogun | AW113: Deaths | AX113: Number | AY113: Past estimate | AZ113: 2019 | BA113: 288.99289 | BB113: 119.04828 | BC113: 560.92617 | BD113: GBD 2019
B114: Benin | C114: both | D114: 35 to 39 | E114: 2019 | F114: Population | G114: Number | H114: 637717.21 | I114: 704049.71 | J114: 569802.24 | L114: Deaths | M114: Bangladesh | N114: Both | O114: 7-27 days | P114: Malaria | Q114: Number | R114: 2019 | S114: 0.000801616 | T114: 0.004922226 | U114: 1.6176334e-05 | AS114: Malaria | AT114: Both | AU114: 28 to 364 days (post neonatal) | AV114: Ogun | AW114: Deaths | AX114: Number | AY114: Past estimate | AZ114: 2019 | BA114: 1511.0054 | BB114: 654.2913 | BC114: 2735.1444 | BD114: GBD 2019
B115: Benin | C115: both | D115: 40 to 44 | E115: 2019 | F115: Population | G115: Number | H115: 524920.51 | I115: 579520.4 | J115: 469018.05 | L115: Deaths | M115: Bangladesh | N115: Both | O115: 28-364 days | P115: Malaria | Q115: Number | R115: 2019 | S115: 0.016774879 | T115: 0.10167557 | U115: 0.000353148 | AS115: Malaria | AT115: Both | AU115: All Ages | AV115: Ogun | AW115: Deaths | AX115: Number | AY115: Past estimate | AZ115: 2019 | BA115: 12558.687 | BB115: 6134.3064 | BC115: 21478.188 | BD115: GBD 2019
B116: Benin | C116: both | D116: 45 to 49 | E116: 2019 | F116: Population | G116: Number | H116: 411533.16 | I116: 454339 | J116: 367706.11 | L116: Deaths | M116: Bangladesh | N116: Both | O116: All ages | P116: Malaria | Q116: Number | R116: 2019 | S116: 110.05186 | T116: 658.22848 | U116: 2.2528956 | AS116: Malaria | AT116: Both | AU116: Under 5 | AV116: Ondo | AW116: Deaths | AX116: Number | AY116: Past estimate | AZ116: 2019 | BA116: 1398.5762 | BB116: 716.76959 | BC116: 2303.7112 | BD116: GBD 2019
B117: Benin | C117: both | D117: 5 to 19 | E117: 2019 | F117: Population | G117: Number | H117: 4874425.4 | I117: 5381563.2 | J117: 4355147.9 | L117: Deaths | M117: Bangladesh | N117: Both | O117: 5-14 years | P117: Malaria | Q117: Number | R117: 2019 | S117: 27.816421 | T117: 169.03438 | U117: 0.57042101 | AS117: Malaria | AT117: Both | AU117: 7 to 27 days (late neonatal) | AV117: Ondo | AW117: Deaths | AX117: Number | AY117: Past estimate | AZ117: 2019 | BA117: 91.727952 | BB117: 36.195455 | BC117: 182.10404 | BD117: GBD 2019
... B151: Bhutan | C151: both | D151: 10 to 24 | E151: 2019 | F151: Population | G151: Number | H151: 214022.78 | I151: 231383.97 | J151: 197766.44 | L151: Deaths | M151: Liberia | N151: Both | O151: 5-14 years | P151: Malaria | Q151: Number | R151: 2019 | S151: 218.48311 | T151: 403.39586 | U151: 82.486852 | AS151: Malaria | AT151: Both | AU151: All Ages | AV151: Zamfara | AW151: Deaths | AX151: Number | AY151: Past estimate | AZ151: 2019 | BA151: 3363.4713 | BB151: 646.53054 | BC151: 7576.6033 | BD151: GBD 2019
B152: Bhutan | C152: both | D152: 15 to 19 | E152: 2019 | F152: Population | G152: Number | H152: 70283.034 | I152: 75984.284 | J152: 64944.607 | L152: Deaths | M152: Bhutan | N152: Both | O152: All ages | P152: Malaria | Q152: Number | R152: 2019 | S152: 0 | T152: 0 | U152: 0
B153: Bhutan | C153: both | D153: 15 to 39 | E153: 2019 | F153: Population | G153: Number | H153: 351165.67 | I153: 379669.67 | J153: 324486.23 | L153: Deaths | M153: Bhutan | N153: Both | O153: 5-14 years | P153: Malaria | Q153: Number | R153: 2019 | S153: 0 | T153: 0 | U153: 0
B154: Bhutan | C154: both | D154: 15-49 years | E154: 2019 | F154: Population | G154: Number | H154: 435629.93 | I154: 470967.55 | J154: 402541.17 | L154: Deaths | M154: South Africa | N154: Both | O154: <5 years | P154: Malaria | Q154: Number | R154: 2019 | S154: 38.782028 | T154: 320.94317 | U154: 0.79108161
B155: Bhutan | C155: both | D155: 20 plus | E155: 2019 | F155: Population | G155: Number | H155: 489321.19 | I155: 529039.22 | J155: 452145.52 | L155: Deaths | M155: South Africa | N155: Both | O155: 0-6 days | P155: Malaria | Q155: Number | R155: 2019 | S155: 0 | T155: 0 | U155: 0
B156: Bhutan | C156: both | D156: 20 to 24 | E156: 2019 | F156: Population | G156: Number | H156: 76964.82 | I156: 83208.085 | J156: 71118.87 | L156: Deaths | M156: South Africa | N156: Both | O156: 7-27 days | P156: Malaria | Q156: Number | R156: 2019 | S156: 0.14307603 | T156: 1.2994716 | U156: 0.002603206
B157: Bhutan | C157: both | D157: 25 plus | E157: 2019 | F157: Population | G157: Number | H157: 412377.71 | I157: 445829.15 | J157: 381055.1 | L157: Deaths | M157: South Africa | N157: Both | O157: 28-364 days | P157: Malaria | Q157: Number | R157: 2019 | S157: 7.592742 | T157: 67.388568 | U157: 0.1444942
B158: Bhutan | C158: both | D158: 25 to 29 | E158: 2019 | F158: Population | G158: Number | H158: 75403.306 | I158: 81519.904 | J158: 69675.963 | L158: Deaths | M158: South Africa | N158: Both | O158: All ages | P158: Malaria | Q158: Number | R158: 2019 | S158: 463.62149 | T158: 3994.0206 | U158: 9.9205819
B159: Bhutan | C159: both | D159: 25 to 49 | E159: 2019 | F159: Population | G159: Number | H159: 288369.5 | I159: 311776.35 | J159: 266460.93 | L159: Deaths | M159: South Africa | N159: Both | O159: 5-14 years | P159: Malaria | Q159: Number | R159: 2019 | S159: 26.905195 | T159: 207.36669 | U159: 0.58090372
B160: Bhutan | C160: both | D160: 30 to 34 | E160: 2019 | F160: Population | G160: Number | H160: 68987.073 | I160: 74583.196 | J160: 63747.082 | L160: Deaths | M160: Mauritania | N160: Both | O160: <5 years | P160: Malaria | Q160: Number | R160: 2019 | S160: 479.41429 | T160: 1274.9722 | U160: 44.263796
B161: Bhutan | C161: both | D161: 35 to 39 | E161: 2019 | F161: Population | G161: Number | H161: 59542.759 | I161: 64372.774 | J161: 55020.122 | L161: Deaths | M161: Mauritania | N161: Both | O161: 0-6 days | P161: Malaria | Q161: Number | R161: 2019 | S161: 0 | T161: 0 | U161: 0
B162: Bhutan | C162: both | D162: 40 to 44 | E162: 2019 | F162: Population | G162: Number | H162: 46682.536 | I162: 50469.35 | J162: 43136.712 | L162: Deaths | M162: Mauritania | N162: Both | O162: 7-27 days | P162: Malaria | Q162: Number | R162: 2019 | S162: 63.646122 | T162: 179.41755 | U162: 5.1688572
B163: Bhutan | C163: both | D163: 45 to 49 | E163: 2019 | F163: Population | G163: Number | H163: 37766.405 | I163: 40829.956 | J163: 34897.815 | L163: Deaths | M163: Mauritania | N163: Both | O163: 28-364 days | P163: Malaria | Q163: Number | R163: 2019 | S163: 201.81198 | T163: 584.92878 | U163: 19.310895
... B309: Burundi | C309: both | D309: 5-14 years | E309: 2019 | F309: Population | G309: Number | H309: 3322415.4 | I309: 3767200.3 | J309: 2868708.5 | L309: Deaths | M309: Somalia | N309: Both | O309: 5-14 years | P309: Malaria | Q309: Number | R309: 2019 | S309: 293.02486 | T309: 745.95231 | U309: 93.977619
B310: Burundi | C310: both | D310: 55 plus | E310: 2019 | F310: Population | G310: Number | H310: 746567.06 | I310: 846614.44 | J310: 644650.91
B311: Burundi | C311: both | D311: 55 to 59 | E311: 2019 | F311: Population | G311: Number | H311: 253069.44 | I311: 286948.85 | J311: 218510.44
B312: Burundi | C312: both | D312: 60 to 64 | E312: 2019 | F312: Population | G312: Number | H312: 195824.2 | I312: 222039.96 | J312: 169082.57
B313: Burundi | C313: both | D313: 65 to 69 | E313: 2019 | F313: Population | G313: Number | H313: 134163.77 | I313: 152124.81 | J313: 115842.45
B314: Burundi | C314: both | D314: 65 to 74 | E314: 2019 | F314: Population | G314: Number | H314: 210245.05 | I314: 238419.97 | J314: 181543.85
B315: Burundi | C315: both | D315: 70 to 74 | E315: 2019 | F315: Population | G315: Number | H315: 76106.297 | I315: 86294.948 | J315: 65713.27
B316: Burundi | C316: both | D316: 70+ years | E316: 2019 | F316: Population | G316: Number | H316: 163598.5 | I316: 185500.07 | J316: 141257.59
B317: Burundi | C317: both | D317: 75 plus | E317: 2019 | F317: Population | G317: Number | H317: 87481.788 | I317: 99205.215 | J317: 75539.382
B318: Burundi | C318: both | D318: 75 to 79 | E318: 2019 | F318: Population | G318: Number | H318: 46369.552 | I318: 52577.227 | J318: 40037.356
B319: Burundi | C319: both | D319: 75 to 84 | E319: 2019 | F319: Population | G319: Number | H319: 72611.472 | I319: 82342.13 | J319: 62699.059
B320: Burundi | C320: both | D320: 80 plus | E320: 2019 | F320: Population | G320: Number | H320: 41122.647 | I320: 46627.898 | J320: 35506.965
B321: Burundi | C321: both | D321: 80 to 84 | E321: 2019 | F321: Population | G321: Number | H321: 26250.562 | I321: 29764.828 | J321: 22665.802
... B2400: Zimbabwe | C2400: both | D2400: Under 5 | E2400: 2019 | F2400: Population | G2400: Number | H2400: 2109552.7 | I2400: 2340010.2 | J2400: 1871535.6

Sheet Simple CEA
I1: Malaria Consortium | R1: Malaria Consortium
I2: Burkina Faso | J2: Chad | K2: DRC | L2: DRC | M2: DRC | N2: DRC | O2: Mozambique | P2: Nigeria | Q2: Nigeria | R2: Nigeria | S2: Nigeria | T2: Nigeria | U2: Nigeria | V2: Nigeria | W2: Nigeria | X2: Nigeria | Y2: Togo | Z2: Uganda
F3: unit | G3: type | H3: Overall | K3: Haut-Katanga | L3: Haut-Lomami | M3: Lualaba | N3: Tanganyika | O3: Nampula | P3: Bauchi | Q3: Borno | R3: FCT (Abuja) | S3: Kebbi | T3: Kogi | U3: Nasarawa | V3: Oyo | W3: Plateau | X3: Sokoto | Z3: Karamoja
A4: Simple CEA
C6: Grant
E7: Grant size | F7: $ | G7: input | H7: - | I7: 1000000 | J7: 1000000 | K7: 1000000 | L7: 1000000 | M7: 1000000 | N7: 1000000 | O7: 1000000 | P7: 1000000 | Q7: 1000000 | R7: 1000000 | S7: 1000000 | T7: 1000000 | U7: 1000000 | V7: 1000000 | W7: 1000000 | X7: 1000000 | Y7: 1000000 | Z7: 1000000
C9: Under-five mortality benefits
E10: Cost per person under age five reached | F10: $ | G10: input | H10: - | I10: ='Main CEA'!I31 -> 5.6888302 | J10: ='Main CEA'!J31 -> 6.475449 | K10: ='Main CEA'!K31 -> 6.475449 | L10: ='Main CEA'!L31 -> 6.475449 | M10: ='Main CEA'!M31 -> 6.475449 | N10: ='Main CEA'!N31 -> 6.475449 | O10: ='Main CEA'!O31 -> 6.475449 | P10: ='Main CEA'!P31 -> 5.0427367 | ... Z10: ='Main CEA'!Z31 -> 8.0943112
E11: Number of people under age five reached | F11: # | G11: calc | H11: - | I11: =I7/I10 -> 175783.06 | J11: =J7/J10 -> 154429.45 | K11: =K7/K10 -> 154429.45 | L11: =L7/L10 -> 154429.45 | M11: =M7/M10 -> 154429.45 | N11: =N7/N10 -> 154429.45 | O11: =O7/O10 -> 154429.45 | P11: =P7/P10 -> 198305.02 | ... Z11: =Z7/Z10 -> 123543.56
E12: Proportion of reached children who would have received SMC in the absence of the program | F12: % | G12: input | H12: - | I12: 0 | J12: 0 | K12: 0 | L12: 0 | M12: 0 | N12: 0 | O12: 0 | P12: 0 | Q12: 0 | R12: 0 | S12: 0 | T12: 0 | U12: 0 | V12: 0 | W12: 0 | X12: 0 | Y12: 0 | Z12: 0
E13: Number of additional children receiving SMC as a result of the program | F13: # | G13: calc | H13: - | I13: =I11*(1-I12) -> 175783.06 | J13: =J11*(1-J12) -> 154429.45 | K13: =K11*(1-K12) -> 154429.45 | L13: =L11*(1-L12) -> 154429.45 | M13: =M11*(1-M12) -> 154429.45 | N13: =N11*(1-N12) -> 154429.45 | O13: =O11*(1-O12) -> 154429.45 | P13: =P11*(1-P12) -> 198305.02 | ... Z13: =Z11*(1-Z12) -> 123543.56
E14: Malaria-attributable mortality rate among people under age five | F14: % | G14: input | H14: - | I14: ='Main CEA'!I52 -> 0.0067302945 | J14: ='Main CEA'!J52 -> 0.0022456541 | K14: ='Main CEA'!K52 -> 0.0032196238 | L14: ='Main CEA'!L52 -> 0.0038118769 | M14: ='Main CEA'!M52 -> 0.0037855428 | N14: ='Main CEA'!N52 -> 0.0056920478 | O14: ='Main CEA'!O52 -> 0.0048578234 | P14: ='Main CEA'!P52 -> 0.0042610274 | ... Z14: ='Main CEA'!Z52 -> 0.0054059768
E15: Proportion of malaria mortality occurring during the SMC season | F15: % | G15: input | H15: - | I15: ='Main CEA'!I54 -> 0.7 | J15: ='Main CEA'!J54 -> 0.7 | K15: ='Main CEA'!K54 -> 0.515 | L15: ='Main CEA'!L54 -> 0.515 | M15: ='Main CEA'!M54 -> 0.515 | N15: ='Main CEA'!N54 -> 0.515 | O15: ='Main CEA'!O54 -> 0.515 | P15: ='Main CEA'!P54 -> 0.7 | ... Z15: ='Main CEA'!Z54 -> 0.62
E16: Effect of SMC on under-five deaths related to malaria | F16: % | G16: input | H16: - | I16: ='Main CEA'!I49 -> 0.793695 | J16: ='Main CEA'!J49 -> 0.793695 | K16: ='Main CEA'!K49 -> 0.63845715 | L16: ='Main CEA'!L49 -> 0.63845715 | M16: ='Main CEA'!M49 -> 0.63845715 | N16: ='Main CEA'!N49 -> 0.63845715 | O16: ='Main CEA'!O49 -> 0.63845715 | P16: ='Main CEA'!P49 -> 0.793695 | ... Z16: ='Main CEA'!Z49 -> 0.63845715
E17: Number of deaths averted among people under age five | F17: # | G17: calc | H17: - | I17: =I11*I14*I15*I16 -> 657.29872 | J17: =J11*J14*J15*J16 -> 192.67468 | K17: =K11*K14*K15*K16 -> 163.48361 | L17: =L11*L14*L15*L16 -> 193.55659 | M17: =M11*M14*M15*M16 -> 192.21941 | N17: =N11*N14*N15*N16 -> 289.02648 | O17: =O11*O14*O15*O16 -> 246.66687 | P17: =P11*P14*P15*P16 -> 469.46122 | ... Z17: =Z11*Z14*Z15*Z16 -> 264.37338
C19: Initial cost-effectiveness estimate
E20: Cost per under-five death averted | F20: $ | G20: calc | H20: - | I20: =I7/I17 -> 1521.3783 | J20: =J7/J17 -> 5190.0954 | K20: =K7/K17 -> 6116.8211 | L20: =L7/L17 -> 5166.4477 | M20: =M7/M17 -> 5202.3881 | N20: =N7/N17 -> 3459.8906 | O20: =O7/O17 -> 4054.0508 | P20: =P7/P17 -> 2130.1014 | ... Z20: =Z7/Z17 -> 3782.5291
E21: Moral value of averting the death of a person under age five | F21: UoV | G21: input | H21: ='Main CEA'!H$100 -> 116.25262 | I21: ='Main CEA'!I$100 -> - | J21: ='Main CEA'!J$100 -> - | K21: ='Main CEA'!K$100 -> - | L21: ='Main CEA'!L$100 -> - | M21: ='Main CEA'!M$100 -> - | N21: ='Main CEA'!N$100 -> - | O21: ='Main CEA'!O$100 -> - | ... Z21: ='Main CEA'!Z$100 -> -
E22: Initial cost-effectiveness in terms of multiples of our benchmark | F22: xbenchmark | G22: calc | H22: - | I22: =((I17*$H21)/I7)/'Main CEA'!$H$133 -> 22.946756 | J22: =((J17*$H21)/J7)/'Main CEA'!$H$133 -> 6.7264075 | K22: =((K17*$H21)/K7)/'Main CEA'!$H$133 -> 5.7073268 | L22: =((L17*$H21)/L7)/'Main CEA'!$H$133 -> 6.7571954 | M22: =((M17*$H21)/M7)/'Main CEA'!$H$133 -> 6.7105137 | N22: =((N17*$H21)/N7)/'Main CEA'!$H$133 -> 10.090116 | O22: =((O17*$H21)/O7)/'Main CEA'!$H$133 -> 8.6113122 | P22: =((P17*$H21)/P7)/'Main CEA'!$H$133 -> 16.389218 | ... Z22: =((Z17*$H21)/Z7)/'Main CEA'!$H$133 -> 9.2294588
C24: Adjustments for other benefits
E25: Adjustment to account for mortalities averted among people age 5 and older | F25: % | G25: input | H25: - | I25: ='Main CEA'!I126/'Main CEA'!I125 -> 0.056479137 | J25: ='Main CEA'!J126/'Main CEA'!J125 -> 0.055324413 | K25: ='Main CEA'!K126/'Main CEA'!K125 -> 0.029151094 | L25: ='Main CEA'!L126/'Main CEA'!L125 -> 0.029151094 | M25: ='Main CEA'!M126/'Main CEA'!M125 -> 0.029151094 | N25: ='Main CEA'!N126/'Main CEA'!N125 -> 0.029151094 | O25: ='Main CEA'!O126/'Main CEA'!O125 -> 0.12570658 | P25: ='Main CEA'!P126/'Main CEA'!P125 -> 0.023418015 | ... Z25: ='Main CEA'!Z126/'Main CEA'!Z125 -> 0.029144268
E26: Adjustment to account for developmental benefits (long-term income increases) | F26: % | G26: input | H26: - | I26: ='Main CEA'!I127/SUM('Main CEA'!I125:I126) -> 0.18884161 | J26: ='Main CEA'!J127/SUM('Main CEA'!J125:J126) -> 0.35327961 | K26: ='Main CEA'!K127/SUM('Main CEA'!K125:K126) -> 0.2422669 | L26: ='Main CEA'!L127/SUM('Main CEA'!L125:L126) -> 0.24934808 | M26: ='Main CEA'!M127/SUM('Main CEA'!M125:M126) -> 0.23711485 | N26: ='Main CEA'!N127/SUM('Main CEA'!N125:N126) -> 0.1565279 | O26: ='Main CEA'!O127/SUM('Main CEA'!O125:O126) -> 0.17210506 | P26: ='Main CEA'!P127/SUM('Main CEA'!P125:P126) -> 0.23525309 | ... Z26: ='Main CEA'!Z127/SUM('Main CEA'!Z125:Z126) -> 0.1608131
C28: Percentage of program impact coming from different benefits
E29: Mortalities averted for people under age five | F29: % | G29: calc | H29: - | I29: =1-SUM(I30:I31) -> 0.79618699 | J29: =1-SUM(J30:J31) -> 0.70020705 | K29: =1-SUM(K30:K31) -> 0.78217863 | L29: =1-SUM(L30:L31) -> 0.77774532 | M29: =1-SUM(M30:M31) -> 0.78543606 | N29: =1-SUM(N30:N31) -> 0.84016531 | O29: =1-SUM(O30:O31) -> 0.75789363 | P29: =1-SUM(P30:P31) -> 0.79102643 | ... Z29: =1-SUM(Z30:Z31) -> 0.83706935
E30: Mortalities averted for people over age five | F30: % | G30: calc | H30: - | I30: =I25/(1*(1+I25)*(1+I26)) -> 0.044967954 | J30: =J25/(1*(1+J25)*(1+J26)) -> 0.038738544 | K30: =K25/(1*(1+K25)*(1+K26)) -> 0.022801363 | L30: =L25/(1*(1+L25)*(1+L26)) -> 0.022672127 | M30: =M25/(1*(1+M25)*(1+M26)) -> 0.022896321 | N30: =N25/(1*(1+N25)*(1+N26)) -> 0.024491738 | O30: =O25/(1*(1+O25)*(1+O26)) -> 0.095272215 | P30: =P25/(1*(1+P25)*(1+P26)) -> 0.018524269 | ... Z30: =Z25/(1*(1+Z25)*(1+Z26)) -> 0.024395774
E31: Developmental benefits (long-term income increases) | F31: % | G31: calc | H31: - | I31: =I26/(1*(1+I26)) -> 0.15884505 | J31: =J26/(1*(1+J26)) -> 0.26105441 | K31: =K26/(1*(1+K26)) -> 0.19502001 | L31: =L26/(1*(1+L26)) -> 0.19958255 | M31: =M26/(1*(1+M26)) -> 0.19166761 | N31: =N26/(1*(1+N26)) -> 0.13534295 | O31: =O26/(1*(1+O26)) -> 0.14683416 | P31: =P26/(1*(1+P26)) -> 0.1904493 | ... Z31: =Z26/(1*(1+Z26)) -> 0.13853488
C33: Supplemental adjustments
E34: Adjustment for additional program benefits and downsides | F34: % | G34: input | H34: - | I34: ='Main CEA'!I177 -> 0.191 | J34: ='Main CEA'!J177 -> 0.241 | K34: ='Main CEA'!K177 -> 0.281 | L34: ='Main CEA'!L177 -> 0.281 | M34: ='Main CEA'!M177 -> 0.281 | N34: ='Main CEA'!N177 -> 0.281 | O34: ='Main CEA'!O177 -> 0.281 | P34: ='Main CEA'!P177 -> 0.341 | ... Z34: ='Main CEA'!Z177 -> 0.281
E35: Adjustment for grantee-level factors | F35: % | G35: input | H35: ='Main CEA'!H161 -> -0.08 | I35: ='Main CEA'!I161 -> - | J35: ='Main CEA'!J161 -> - | K35: ='Main CEA'!K161 -> - | L35: ='Main CEA'!L161 -> - | M35: ='Main CEA'!M161 -> - | N35: ='Main CEA'!N161 -> - | O35: ='Main CEA'!O161 -> - | ... Z35: ='Main CEA'!Z161 -> -
E36: Adjustment for leverage | F36: % | G36: input | H36: - | I36: ='Main CEA'!I180 -> -0.0028363398 | J36: ='Main CEA'!J180 -> -0.008995254 | K36: ='Main CEA'!K180 -> -0.017730551 | L36: ='Main CEA'!L180 -> -0.014890865 | M36: ='Main CEA'!M180 -> -0.015142727 | N36: ='Main CEA'!N180 -> -0.010772527 | O36: ='Main CEA'!O180 -> -0.010716649 | P36: ='Main CEA'!P180 -> -0.0055871389 | ... Z36: ='Main CEA'!Z180 -> -0.0096630301
E37: Adjustment for funging | F37: % | G37: input | H37: ='Main CEA'!H$183 -> - | I37: ='Main CEA'!I181 -> -0.42662125 | J37: ='Main CEA'!J181 -> -0.25984737 | K37: ='Main CEA'!K181 -> -0.069158636 | L37: ='Main CEA'!L181 -> -0.082106007 | M37: ='Main CEA'!M181 -> -0.080957661 | N37: ='Main CEA'!N181 -> -0.10088332 | O37: ='Main CEA'!O181 -> -0.13077897 | P37: ='Main CEA'!P181 -> -0.16373796 | ... Z37: ='Main CEA'!Z181 -> -0.19300201
C39: Final cost-effectiveness estimate
E40: Final cost-effectiveness in terms of multiples of our benchmark | F40: xbenchmark | G40: calc | H40: - | I40: =I22/I29*(1+I34)*(1+$H35)*(1+SUM(I36:I37)) -> 18.017467 | J40: =J22/J29*(1+J34)*(1+$H35)*(1+SUM(J36:J37)) -> 8.0191284 | K40: =K22/K29*(1+K34)*(1+$H35)*(1+SUM(K36:K37)) -> 7.8521256 | L40: =L22/L29*(1+L34)*(1+$H35)*(1+SUM(L36:L37)) -> 9.2460297 | M40: =M22/M29*(1+M34)*(1+$H35)*(1+SUM(M36:M37)) -> 9.1012718 | N40: =N22/N29*(1+N34)*(1+$H35)*(1+SUM(N36:N37)) -> 12.57331 | O40: =O22/O29*(1+O34)*(1+$H35)*(1+SUM(O36:O37)) -> 11.495836 | P40: =P22/P29*(1+P34)*(1+$H35)*(1+SUM(P36:P37)) -> 21.233175 | ... Z40: =Z22/Z29*(1+Z34)*(1+$H35)*(1+SUM(Z36:Z37)) -> 10.360783
E41: Final cost per life saved | F41: $ | G41: calc | H41: - | I41: =I20*('Main CEA'!I56/SUM('Main CEA'!I56,'Main CEA'!I69))/(1+'Main CEA'!I204) -> 3328.2515 | J41: =J20*('Main CEA'!J56/SUM('Main CEA'!J56,'Main CEA'!J69))/(1+'Main CEA'!J204) -> 8418.9871 | K41: =K20*('Main CEA'!K56/SUM('Main CEA'!K56,'Main CEA'!K69))/(1+'Main CEA'!K204) -> 7917.8047 | L41: =L20*('Main CEA'!L56/SUM('Main CEA'!L56,'Main CEA'!L69))/(1+'Main CEA'!L204) -> 6748.466 | M41: =M20*('Main CEA'!M56/SUM('Main CEA'!M56,'Main CEA'!M69))/(1+'Main CEA'!M204) -> 6788.0609 | N41: =N20*('Main CEA'!N56/SUM('Main CEA'!N56,'Main CEA'!N69))/(1+'Main CEA'!N204) -> 4571.1086 | O41: =O20*('Main CEA'!O56/SUM('Main CEA'!O56,'Main CEA'!O69))/(1+'Main CEA'!O204) -> 4831.5578 | P41: =P20*('Main CEA'!P56/SUM('Main CEA'!P56,'Main CEA'!P69))/(1+'Main CEA'!P204) -> 2836.5003 | ... Z41: =Z20*('Main CEA'!Z56/SUM('Main CEA'!Z56,'Main CEA'!Z69))/(1+'Main CEA'!Z204) -> 5568.2214

Sheet Confidence intervals
F1: Malaria Consortium
F2: Burkina Faso | I2: Chad | L2: DRC | O2: DRC | R2: DRC | U2: DRC | X2: Mozambique | AA2: Nigeria | AD2: Nigeria | AG2: Nigeria | AJ2: Nigeria | AM2: Nigeria | AP2: Nigeria | AS2: Nigeria | AV2: Nigeria | AY2: Nigeria | BB2: Togo | BE2: Uganda
A3: Simple CEA | L3: Haut-Katanga | O3: Haut-Lomami | R3: Lualaba | U3: Tanganyika | X3: Nampula | AA3: Bauchi | AD3: Borno | AG3: FCT (Abuja) | AJ3: Kebbi | AM3: Kogi | AP3: Nasarawa | AS3: Oyo | AV3: Plateau | AY3: Sokoto | BE3: Karamoja
F4: 25th | G4: Best guess | H4: 75th | I4: 25th | J4: Best guess | K4: 75th | L4: 25th | M4: Best guess | N4: 75th | O4: 25th | P4: Best guess | Q4: 75th | R4: 25th | S4: Best guess | T4: 75th | U4: 25th | V4: Best guess | W4: 75th | X4: 25th | Y4: Best guess | Z4: 75th | AA4: 25th | AB4: Best guess | AC4: 75th | AD4: 25th | AE4: Best guess | AF4: 75th | AG4: 25th | AH4: Best guess | AI4: 75th | AJ4: 25th | AK4: Best guess | AL4: 75th | AM4: 25th | AN4: Best guess | AO4: 75th | AP4: 25th | AQ4: Best guess | AR4: 75th | AS4: 25th | AT4: Best guess | AU4: 75th | AV4: 25th | AW4: Best guess | AX4: 75th | AY4: 25th | AZ4: Best guess | BA4: 75th | BB4: 25th | BC4: Best guess | BD4: 75th | BE4: 25th | BF4: Best guess | BG4: 75th
A5: Final cost-effectiveness estimate (pulled from "Main calcs" sheet) | F5: ='Main CEA'!I191 -> 18.017467 | I5: ='Main CEA'!J191 -> 8.0191284 | L5: ='Main CEA'!K191 -> 7.8521256 | O5: ='Main CEA'!L191 -> 9.2460297 | R5: ='Main CEA'!M191 -> 9.1012718 | U5: ='Main CEA'!N191 -> 12.57331 | X5: ='Main CEA'!O191 -> 11.495836 | AA5: ='Main CEA'!P191 -> 21.233175 | AD5: ='Main CEA'!Q191 -> 18.026571 | AG5: ='Main CEA'!R191 -> 16.096733 | AJ5: ='Main CEA'!S191 -> 29.428169 | AM5: ='Main CEA'!T191 -> 21.047859 | AP5: ='Main CEA'!U191 -> 22.329384 | AS5: ='Main CEA'!V191 -> 24.33013 | AV5: ='Main CEA'!W191 -> 16.045914 | AY5: ='Main CEA'!X191 -> 29.832969 | BB5: ='Main CEA'!Y191 -> 10.567669 | BE5: ='Main CEA'!Z191 -> 10.360783
A6: GiveWell's 25th and 75th percentile values for key inputs
C8: Under-five mortality benefits
