Workbook

Sheet Key
A1: [April
A2: Sheet descriptions
E4: Main CEA | F4: This sheet contains the primary calculations that result in final cost-effectiveness estimates. This sheet draws on inputs from the "Inputs" sheet and inputs calculated in the other supplemental sheets listed below.
E5: Aggregation across vaccines | F5: This sheet contains our calculations for pulling CEA parameters from other supplementary sheets and aggregating them across vaccines before entering them in the "Main CEA" sheet.
E6: Treatment effect | F6: This sheet contains our calculations of the effect of New Incentives' program on vaccine uptake.
E7: Disease burden | F7: This sheet contains our calculations of vaccine-preventable disease burden among New Incentives' target population.
E8: Vaccine coverage | F8: This sheet contains our calculations of baseline vaccination coverage among New Incentives' target population, as well as vaccination coverage among populations represented by GBD disease burden estimates.
E9: Vaccine efficacy | F9: This sheet contains our calculations of the effect of vaccination on disease incidence for each vaccine incentivized by New Incentives' program.
E10: Leverage/Funging | F10: This sheet contains our calculations of the impact that crowding in and crowding out funding by other contributors has on the benefits of the program.
E11: Inputs | F11: This sheet contains all of the manually entered input values informing the CEA, along with the sources and reasoning supporting them. This sheet also contains inputs sourced from the "GBD estimates" sheet.
E12: GBD estimates | F12: This sheet contains disease burden and population datasets downloaded from the Institute of Health Metrics (IHME)'s Global Burden of Disease (GBD) project.
E13: Simple CEA | F13: This sheet contains a simplified version of the CEA that is designed to be comparable to our CEAs of other programs.
E14: Sensitivity analysis | F14: This sheet contains the outputs of a sensitivity analysis macro that tests the cost-effectiveness ranges that would result from updating certain inputs to their 25th or 75th percentile values.
A16: Terminology key
C18: Terms specific to this CEA
E19: BCG vaccine | F19: The Bacillus Calmette-Guerin (BCG) vaccine is designed to prevent tuberculosis and other mycobacterial infections. BCG is one of the vaccines directly incentivized by New Incentives' program.
E20: Penta vaccine | F20: The pentavalent vaccine (referred to as Penta in this CEA) is a 5-in-1 vaccine that is designed to prevent diphtheria, pertussis, tetanus, hepatitis B, and H. influenza type B infections. Penta is one of the vaccines directly incentivized by New Incentives' program.
E21: DTP vaccine | F21: The DTP vaccine is designed to prevent diphtheria, pertussis, and tetanus. In Nigeria, the DTP vaccine is typically delivered as part of the Penta vaccine, which is one of the vaccines directly incentivized by New Incentives' program.
E22: Hib vaccine | F22: The HiB vaccine is designed to prevent H. influenzae type B (Hib) infections. In Nigeria, the Hib vaccine is typically delivered as part of the Penta vaccine, which is one of the vaccines directly incentivized by New Incentives' program.
E23: PCV vaccine | F23: The pneumococcal conjugate vaccine (PCV) is designed to prevent pneumococcal infections. PCV is one of the vaccines directly incentivized by New Incentives' program.
E24: Vaccine efficacy | F24: The efficacy rate of a vaccine refers to the reduction in vaccine-targeted disease incidence among people who receive the vaccine compared to those who do not receive the vaccine.
E25: Vaccine-preventable causes | F25: In this CEA, we use "vaccine-preventable causes" to refer to causes of disease incidence and mortality that are addressable by the specific set of vaccines directly incentivized by New Incentives' program.
E26: Vaccine-preventable mortalities | F26: In this CEA, we use "vaccine-preventable mortalities" to refer to mortalities that we expect would be averted if all children were fully vaccinated with the set of vaccines directly incentivized by New Incentives' program. Because vaccines are not 100% effective, the number of "vaccine-preventable mortalities" will always represent a subset of "mortalities from vaccine-preventable causes."
E27: MICS survey | F27: Multiple Indicator Cluster Surveys (MICS) are standardized household surveys implemented in many countries to collect data on a variety of indicators, including child vaccination rates.
C29: Terms used across GiveWell's CEAs
E30: Internal validity | F30: Describes an adjustment we make to the treatment effect of an intervention to account for the possibility that the treatment effects found in studies may not represent the true effect the intervention had on the populations studied.
E31: External validity | F31: Describes an adjustment we make to the treatment effect of an intervention to account for differences in the program implementation or populations treated in studies from the program implementation or populations treated by grantee programs.
E32: Leverage | F32: Describes a situation where a grantee's spending on a program causes other organizations or governments to contribute more to the program than they otherwise would have. In most cases, accounting for leverage increases cost-effectiveness
E33: Funging | F33: Describes a situation where a grantee's spending on a program causes other organizations or governments to contribute less to the program than they otherwise would have. In most cases, accounting for funging decreases cost-effectiveness.
E34: Counterfactual | F34: In most cases, describes the state of the world that would exist if we did not provide funding to a grantee for a program. When discussing the "counterfactual value of other actors' spending," we are referring to how much benefit another organization's or government's spending would generate if it were spent on something other than the grantee program.
E35: Moral weights | F35: To compare cost-effectiveness across different programs, we use ‘moral weights’ to quantify the benefits of different program impacts (e.g. increased income vs reduced deaths). We benchmark the value of each benefit to a value of 1, which we define as the value of doubling someone’s consumption for one year.
E36: Philanthropic actors | F36: Non-governmental organizations (NGOs) providing funding to philanthropic programs.
A38: Unit and source key
C40: Unit labels used in the CEA
E41: # | F41: Number
E42: per 1k | F42: Rate per 1,000
E43: per 100k | F43: Rate per 100,000
E44: $ | F44: U.S. dollars
E45: ln($) | F45: The natural logarithm of a monetary value
E46: % | F46: Percentage
E47: ppt | F47: Percentage points
E48: UoV | F48: Units of value: an arbitrary unit GiveWell uses to compare the moral value of different types of outcomes, such as saving lives or increasing income
E49: xcash | F49: Cost-effectiveness in terms of multiples of GiveDirectly's unconditional cash transfer program
C51: Source labels used in the CEA
E53: Input | F53: A value pulled from the "Inputs" sheet
E54: Calc | F54: A value calculated using other values in the same sheet
E55: Supp | F55: A value pulled from one of the sheets hosting supplemental calculations
E56: Main | F56: A value pulled from the "Main CEA" sheet
E57: Feed | F57: A value pulled from an earlier section within the same sheet
A59: GiveWell analyses informing this model
C61: Analyses specific to this CEA
E62: GW's analysis of New Incentives cost per infant immunized
E63: GW's analysis of the biomarkers pilot results for Nigeria
E64: GW's analysis of self-report bias in vaccine coverage sources for New Incentives
E65: GW's analysis of disease etiology for lower respiratory infections and meningitis
E66: GW's analysis of average household size in Northwest Nigeria
C68: Analyses referenced across GiveWell's CEAs
E69: GW's moral weights and discount rate
E70: GW's supplemental intervention-level adjustments
E71: GiveWell's CEA for GiveDirectly's unconditional cash transfers
E72: GW's analysis of the counterfactual value of other actors' spending
E73: GW's analysis of the counterfactual value of Global Fund spending

Sheet Main CEA
I1: New Incentives – current states of operation | R1: New Incentives – prospective states | AF1: New Incentives – prospective states
I2: Nigeria | J2: Nigeria | K2: Nigeria | L2: Nigeria | M2: Nigeria | N2: Nigeria | O2: Nigeria | P2: Nigeria | Q2: Nigeria | R2: Nigeria | S2: Nigeria | T2: Nigeria | U2: Nigeria | V2: Nigeria | W2: Nigeria | X2: Nigeria | Y2: Nigeria | Z2: Nigeria | AA2: Nigeria | AB2: Nigeria | AC2: Nigeria | AD2: Nigeria | AE2: Nigeria | AF2: Nigeria | AG2: Nigeria | AH2: Nigeria | AI2: Nigeria | AJ2: Nigeria | AK2: Nigeria | AL2: Nigeria | AM2: Nigeria | AN2: Nigeria | AO2: Nigeria | AP2: Nigeria | AQ2: Nigeria | AR2: Nigeria | AS2: Nigeria
A3: Main calculations | F3: unit | G3: type | H3: Overall | I3: Bauchi | J3: Gombe | K3: Jigawa | L3: Kaduna | M3: Kano | N3: Katsina | O3: Kebbi | P3: Sokoto | Q3: Zamfara | R3: Abia | S3: Adamawa | T3: Akwa Ibom | U3: Anambra | V3: Bayelsa | W3: Benue | X3: Borno | Y3: Cross River | Z3: Delta | AA3: Ebonyi | AB3: Edo | AC3: Ekiti | AD3: Enugu | AE3: FCT | AF3: Imo | AG3: Kogi | AH3: Kwara | AI3: Lagos | AJ3: Nasarawa | AK3: Niger | AL3: Ogun | AM3: Ondo | AN3: Osun | AO3: Oyo | AP3: Plateau | AQ3: Rivers | AR3: Taraba | AS3: Yobe
E4: Final cost-effectiveness estimate (pulled from below for visibility) | F4: =F241 -> xcash | G4: feed | H4: =H241 -> - | I4: =I241 -> 23.798889 | J4: =J241 -> 10.800641 | K4: =K241 -> 19.899944 | L4: =L241 -> 5.6568275 | M4: =M241 -> 13.129176 | N4: =N241 -> 20.329812 | O4: =O241 -> 31.532139 | ... AS4: =AS241 -> 6.7228331
A5: Grantee costs
C7: GiveWell costs
E8: Grant size | F8: =Inputs!F8 -> $ | G8: =Inputs!G8 -> input | H8: =Inputs!H8 -> 1000000 | I8: =Inputs!I8 -> - | J8: =Inputs!J8 -> - | K8: =Inputs!K8 -> - | L8: =Inputs!L8 -> - | M8: =Inputs!M8 -> - | ... AS8: =Inputs!AS8 -> -
C10: Spending attributable to grantee
E11: Total spending contributed by grantee | F11: $ | G11: calc | H11: - | I11: =IF(I8="-",$H8,I8) -> 1000000 | J11: =IF(J8="-",$H8,J8) -> 1000000 | K11: =IF(K8="-",$H8,K8) -> 1000000 | L11: =IF(L8="-",$H8,L8) -> 1000000 | M11: =IF(M8="-",$H8,M8) -> 1000000 | N11: =IF(N8="-",$H8,N8) -> 1000000 | O11: =IF(O8="-",$H8,O8) -> 1000000 | P11: =IF(P8="-",$H8,P8) -> 1000000 | ... AS11: =IF(AS8="-",$H8,AS8) -> 1000000
C13: Cost per child enrolled
E14: Cost per infant enrolled in the program | F14: =Inputs!F11 -> $ | G14: =Inputs!G11 -> input | H14: =Inputs!H11 -> 21.27455 | I14: =Inputs!I11 -> - | J14: =Inputs!J11 -> - | K14: =Inputs!K11 -> - | L14: =Inputs!L11 -> - | M14: =Inputs!M11 -> - | ... AS14: =Inputs!AS11 -> -
A16: Outputs
C18: Total children enrolled
E19: Total children enrolled in the program | F19: # | G19: calc | H19: - | I19: =I11/$H14 -> 47004.519 | J19: =J11/$H14 -> 47004.519 | K19: =K11/$H14 -> 47004.519 | L19: =L11/$H14 -> 47004.519 | M19: =M11/$H14 -> 47004.519 | N19: =N11/$H14 -> 47004.519 | O19: =O11/$H14 -> 47004.519 | P19: =P11/$H14 -> 47004.519 | ... AS19: =AS11/$H14 -> 47004.519
C21: Total children vaccinated
E22: Proportion of vaccinated children who are enrolled in New Incentives' program | F22: =Inputs!F220 -> % | G22: =Inputs!G220 -> input | H22: =Inputs!H220 -> 0.95 | I22: =Inputs!I220 -> - | J22: =Inputs!J220 -> - | K22: =Inputs!K220 -> - | L22: =Inputs!L220 -> - | M22: =Inputs!M220 -> - | ... AS22: =Inputs!AS220 -> -
E23: Total children vaccinated in program areas | F23: % | G23: calc | H23: - | I23: =I19/$H22 -> 49478.442 | J23: =J19/$H22 -> 49478.442 | K23: =K19/$H22 -> 49478.442 | L23: =L19/$H22 -> 49478.442 | M23: =M19/$H22 -> 49478.442 | N23: =N19/$H22 -> 49478.442 | O23: =O19/$H22 -> 49478.442 | P23: =P19/$H22 -> 49478.442 | ... AS23: =AS19/$H22 -> 49478.442
C25: Counterfactual vaccination coverage
E26: Proportion of children in the target population who would be vaccinated in the absence of the program, aggregated across vaccines | F26: ='Aggregation across vaccines'!F32 -> % | G26: supp | H26: ='Aggregation across vaccines'!H32 -> - | I26: ='Aggregation across vaccines'!I32 -> 0.47613003 | J26: ='Aggregation across vaccines'!J32 -> 0.62518435 | K26: ='Aggregation across vaccines'!K32 -> 0.55281297 | L26: ='Aggregation across vaccines'!L32 -> 0.69332916 | M26: ='Aggregation across vaccines'!M32 -> 0.53428802 | N26: ='Aggregation across vaccines'!N32 -> 0.43954496 | O26: ='Aggregation across vaccines'!O32 -> 0.32205884 | ... AS26: ='Aggregation across vaccines'!AS32 -> 0.71672388
E27: Corresponding proportion of children who would not be vaccinated in the absence of the program, aggregated across incentivized vaccines | F27: % | G27: calc | H27: - | I27: =1-I26 -> 0.52386997 | J27: =1-J26 -> 0.37481565 | K27: =1-K26 -> 0.44718703 | L27: =1-L26 -> 0.30667084 | M27: =1-M26 -> 0.46571198 | N27: =1-N26 -> 0.56045504 | O27: =1-O26 -> 0.67794116 | P27: =1-P26 -> 0.7531465 | ... AS27: =1-AS26 -> 0.28327612
C29: Effect of the program on vaccination coverage
E30: Reduction in the proportion of children who are unvaccinated as a result of New Incentives' program, based on GW's analysis of the New Incentives RCT, aggregated across vaccines | F30: ='Treatment effect'!F70 -> % | G30: supp | H30: ='Treatment effect'!H70 -> 0.33388688 | I30: ='Treatment effect'!I70 -> - | J30: ='Treatment effect'!J70 -> - | K30: ='Treatment effect'!K70 -> - | L30: ='Treatment effect'!L70 -> - | M30: ='Treatment effect'!M70 -> - | N30: ='Treatment effect'!N70 -> - | O30: ='Treatment effect'!O70 -> - | ... AS30: ='Treatment effect'!AS70 -> -
E31: Internal validity adjustment | F31: =Inputs!F223 -> % | G31: =Inputs!G223 -> input | H31: =Inputs!H223 -> -0.12 | I31: =Inputs!I223 -> - | J31: =Inputs!J223 -> - | K31: =Inputs!K223 -> - | L31: =Inputs!L223 -> - | M31: =Inputs!M223 -> - | ... AS31: =Inputs!AS223 -> -
E32: Reduction in the proportion of children who are unvaccinated as a result of New Incentives' program | F32: % | G32: calc | H32: =H30*(1+H31) -> 0.29382046 | I32: - | J32: - | K32: - | L32: - | M32: - | N32: - | O32: - | P32: - | R32: - | S32: - | T32: - | U32: - | V32: - | W32: - | X32: - | Y32: - | Z32: - | AA32: - | AB32: - | AC32: - | AD32: - | AE32: - | AF32: - | AG32: - | AH32: - | AI32: - | AJ32: - | AK32: - | AL32: - | AM32: - | AN32: - | AO32: - | AP32: - | AQ32: - | AR32: - | AS32: -
E33: Corresponding increase in the proportion of children who are vaccinated as a result of New Incentives' program | F33: ppt | G33: calc | H33: - | I33: =I27*$H32 -> 0.15392371 | J33: =J27*$H32 -> 0.1101285 | K33: =K27*$H32 -> 0.1313927 | L33: =L27*$H32 -> 0.090106167 | M33: =M27*$H32 -> 0.1368357 | N33: =N27*$H32 -> 0.16467315 | O33: =O27*$H32 -> 0.19919298 | P33: =P27*$H32 -> 0.22128985 | ... AS33: =AS27*$H32 -> 0.08323232
E34: Total proportion of children in the target population who are vaccinated | F34: % | G34: calc | H34: - | I34: =I26+I33 -> 0.63005374 | J34: =J26+J33 -> 0.73531286 | K34: =K26+K33 -> 0.68420567 | L34: =L26+L33 -> 0.78343532 | M34: =M26+M33 -> 0.67112373 | N34: =N26+N33 -> 0.60421812 | O34: =O26+O33 -> 0.52125182 | P34: =P26+P33 -> 0.46814335 | ... AS34: =AS26+AS33 -> 0.7999562
C36: Number of children vaccinated as a result of New Incentives' program
E37: Children in the target population | F37: # | G37: calc | H37: - | I37: =I23/I34 -> 78530.51 | J37: =J23/J34 -> 67288.966 | K37: =K23/K34 -> 72315.159 | L37: =L23/L34 -> 63155.745 | M37: =M23/M34 -> 73724.769 | N37: =N23/N34 -> 81888.378 | O37: =O23/O34 -> 94922.338 | P37: =P23/P34 -> 105690.79 | ... AS37: =AS23/AS34 -> 61851.439
E38: Children counterfactually vaccinated | F38: # | G38: calc | H38: - | I38: =I37*I33 -> 12087.708 | J38: =J37*J33 -> 7410.4331 | K38: =K37*K33 -> 9501.6837 | L38: =L37*L33 -> 5690.7221 | M38: =M37*M33 -> 10088.181 | N38: =N37*N33 -> 13484.817 | O38: =O37*O33 -> 18907.863 | P38: =P37*P33 -> 23388.3 | ... AS38: =AS37*AS33 -> 5148.0387
A40: Outcomes
C42: Mortality reduction among people under age 5
E43: Probability that a person will die of a vaccine-preventable cause before reaching age 5, adjusted for deaths occurring before the age of vaccination | F43: ='Disease burden'!F184 -> % | G43: supp | H43: ='Disease burden'!H184 -> - | I43: ='Disease burden'!I184 -> 0.029558884 | J43: ='Disease burden'!J184 -> 0.021078685 | K43: ='Disease burden'!K184 -> 0.029201114 | L43: ='Disease burden'!L184 -> 0.012703905 | M43: ='Disease burden'!M184 -> 0.020249832 | N43: ='Disease burden'!N184 -> 0.021535107 | O43: ='Disease burden'!O184 -> 0.023390457 | ... AS43: ='Disease burden'!AS184 -> 0.015604259
E44: Proportion of people under age 5 represented in GBD 2021 disease burden estimates who were vaccinated, aggregated across vaccines | F44: ='Aggregation across vaccines'!F64 -> % | G44: supp | H44: ='Aggregation across vaccines'!H64 -> - | I44: ='Aggregation across vaccines'!I64 -> 0.27548418 | J44: ='Aggregation across vaccines'!J64 -> 0.34752396 | K44: ='Aggregation across vaccines'!K64 -> 0.30600516 | L44: ='Aggregation across vaccines'!L64 -> 0.4480187 | M44: ='Aggregation across vaccines'!M64 -> 0.29422974 | N44: ='Aggregation across vaccines'!N64 -> 0.2806275 | O44: ='Aggregation across vaccines'!O64 -> 0.31099173 | ... AS44: ='Aggregation across vaccines'!AS64 -> 0.33924752
E45: Proportion of vaccine-preventable disease incidence averted by full vaccination among people under age 5, aggregated across vaccines | F45: ='Aggregation across vaccines'!F53 -> % | G45: supp | H45: ='Aggregation across vaccines'!H53 -> - | I45: ='Aggregation across vaccines'!I53 -> 0.52870848 | J45: ='Aggregation across vaccines'!J53 -> 0.52476274 | K45: ='Aggregation across vaccines'!K53 -> 0.54543544 | L45: ='Aggregation across vaccines'!L53 -> 0.53079041 | M45: ='Aggregation across vaccines'!M53 -> 0.51766922 | N45: ='Aggregation across vaccines'!N53 -> 0.53814058 | O45: ='Aggregation across vaccines'!O53 -> 0.53885814 | ... AS45: ='Aggregation across vaccines'!AS53 -> 0.54241469
E46: Probability that an unvaccinated person will die of a vaccine-preventable cause before reaching age 5, adjusted for deaths occurring before the age of vaccination | F46: ='Disease burden'!F209 -> % | G46: calc | H46: ='Disease burden'!H209 -> - | I46: =I43/((1-I44)+(I44*(1-I45))) -> 0.03459813 | J46: =J43/((1-J44)+(J44*(1-J45))) -> 0.02578015 | K46: =K43/((1-K44)+(K44*(1-K45))) -> 0.035051406 | L46: =L43/((1-L44)+(L44*(1-L45))) -> 0.016667505 | M46: =M43/((1-M44)+(M44*(1-M45))) -> 0.023888356 | N46: =N43/((1-N44)+(N44*(1-N45))) -> 0.025365771 | O46: =O43/((1-O44)+(O44*(1-O45))) -> 0.02809936 | P46: =P43/((1-P44)+(P44*(1-P45))) -> 0.037980473 | ... AS46: =AS43/((1-AS44)+(AS44*(1-AS45))) -> 0.019123167
E47: Mortalities indirectly attributable to vaccine-preventable disease per mortality directly caused by vaccine-preventable disease | F47: =Inputs!F228 -> % | G47: =Inputs!G228 -> input | H47: =Inputs!H228 -> 0.75 | I47: =Inputs!I228 -> - | J47: =Inputs!J228 -> - | K47: =Inputs!K228 -> - | L47: =Inputs!L228 -> - | M47: =Inputs!M228 -> - | ... AS47: =Inputs!AS228 -> -
E48: Probability that an unvaccinated person will die of a vaccine-preventable cause before reaching age 5, including mortalities indirectly attributable to vaccine-preventable disease | F48: % | G48: calc | H48: - | I48: =I46*(1+$H47) -> 0.060546727 | J48: =J46*(1+$H47) -> 0.045115262 | K48: =K46*(1+$H47) -> 0.061339961 | L48: =L46*(1+$H47) -> 0.029168133 | M48: =M46*(1+$H47) -> 0.041804622 | N48: =N46*(1+$H47) -> 0.044390098 | O48: =O46*(1+$H47) -> 0.04917388 | P48: =P46*(1+$H47) -> 0.066465827 | ... AS48: =AS46*(1+$H47) -> 0.033465543
E49: Ratio of the reduction in vaccine-preventable disease mortality to the reduction in vaccine-preventable disease incidence | F49: =Inputs!F229 -> % | G49: =Inputs!G229 -> input | H49: =Inputs!H229 -> 1 | I49: =Inputs!I229 -> - | J49: =Inputs!J229 -> - | K49: =Inputs!K229 -> - | L49: =Inputs!L229 -> - | M49: =Inputs!M229 -> - | ... AS49: =Inputs!AS229 -> -
E50: Total deaths averted among people under age 5 | F50: # | G50: calc | H50: - | I50: =I38*I45*I48*$H49 -> 386.94648 | J50: =J38*J45*J48*$H49 -> 175.44058 | K50: =K38*K45*K48*$H49 -> 317.89772 | L50: =L38*L45*L48*$H49 -> 88.1047 | M50: =M38*M45*M48*$H49 -> 218.31798 | N50: =N38*N45*N48*$H49 -> 322.12685 | O50: =O38*O45*O48*$H49 -> 501.01575 | P50: =P38*P45*P48*$H49 -> 825.62163 | ... AS50: =AS38*AS45*AS48*$H49 -> 93.448237
C52: Mortality reduction among people age 5 through age 14
E53: Probability that a 5-year-old will die of a vaccine-preventable cause before reaching age 15 | F53: ='Disease burden'!F229 -> % | G53: supp | H53: ='Disease burden'!H229 -> - | I53: ='Disease burden'!I229 -> 0.0023902112 | J53: ='Disease burden'!J229 -> 0.001688536 | K53: ='Disease burden'!K229 -> 0.0023980106 | L53: ='Disease burden'!L229 -> 0.0010928606 | M53: ='Disease burden'!M229 -> 0.0016600387 | N53: ='Disease burden'!N229 -> 0.001936983 | O53: ='Disease burden'!O229 -> 0.0021528314 | ... AS53: ='Disease burden'!AS229 -> 0.0017136421
E54: Proportion of 5-14-year-olds represented in GBD 2021 disease burden estimates who were vaccinated, aggregated across vaccines | F54: ='Aggregation across vaccines'!F97 -> % | G54: supp | H54: ='Aggregation across vaccines'!H97 -> - | I54: ='Aggregation across vaccines'!I97 -> 0.15653547 | J54: ='Aggregation across vaccines'!J97 -> 0.19816078 | K54: ='Aggregation across vaccines'!K97 -> 0.17370305 | L54: ='Aggregation across vaccines'!L97 -> 0.2547922 | M54: ='Aggregation across vaccines'!M97 -> 0.17551178 | N54: ='Aggregation across vaccines'!N97 -> 0.16136707 | O54: ='Aggregation across vaccines'!O97 -> 0.17900497 | ... AS54: ='Aggregation across vaccines'!AS97 -> 0.18833308
E55: Proportion of vaccine-preventable disease incidence averted by full vaccination among 5-14-year-olds, aggregated across vaccines | F55: ='Aggregation across vaccines'!F85 -> % | G55: supp | H55: ='Aggregation across vaccines'!H85 -> - | I55: ='Aggregation across vaccines'!I85 -> 0.51480362 | J55: ='Aggregation across vaccines'!J85 -> 0.50911907 | K55: ='Aggregation across vaccines'!K85 -> 0.53344153 | L55: ='Aggregation across vaccines'!L85 -> 0.51807461 | M55: ='Aggregation across vaccines'!M85 -> 0.5076137 | N55: ='Aggregation across vaccines'!N85 -> 0.52476473 | O55: ='Aggregation across vaccines'!O85 -> 0.52713556 | ... AS55: ='Aggregation across vaccines'!AS85 -> 0.51871968
E56: Probability that an unvaccinated 5-year-old will die of a vaccine-preventable cause before reaching age 15 | F56: ='Disease burden'!F255 -> % | G56: calc | H56: ='Disease burden'!H255 -> - | I56: =I53/((1-I54)+(I54*(1-I55))) -> 0.0025997088 | J56: =J53/((1-J54)+(J54*(1-J55))) -> 0.0018780029 | K56: =K53/((1-K54)+(K54*(1-K55))) -> 0.0026429031 | L56: =L53/((1-L54)+(L54*(1-L55))) -> 0.0012590579 | M56: =M53/((1-M54)+(M54*(1-M55))) -> 0.0018224003 | N56: =N53/((1-N54)+(N54*(1-N55))) -> 0.0021161806 | O56: =O53/((1-O54)+(O54*(1-O55))) -> 0.0023771379 | P56: =P53/((1-P54)+(P54*(1-P55))) -> 0.0030368658 | ... AS56: =AS53/((1-AS54)+(AS54*(1-AS55))) -> 0.0018991766
E57: Mortalities indirectly attributable to vaccine-preventable disease per mortality directly caused by vaccine-preventable disease | F57: =Inputs!F228 -> % | G57: =Inputs!G228 -> input | H57: =Inputs!H228 -> 0.75 | I57: =Inputs!I228 -> - | J57: =Inputs!J228 -> - | K57: =Inputs!K228 -> - | L57: =Inputs!L228 -> - | M57: =Inputs!M228 -> - | ... AS57: =Inputs!AS228 -> -
E58: Probability that an unvaccinated 5-year-old will die of a vaccine-preventable cause before reaching age 15, including mortalities indirectly attributable to vaccine-preventable disease | F58: % | G58: calc | H58: - | I58: =I56*(1+$H57) -> 0.0045494905 | J58: =J56*(1+$H57) -> 0.0032865051 | K58: =K56*(1+$H57) -> 0.0046250804 | L58: =L56*(1+$H57) -> 0.0022033514 | M58: =M56*(1+$H57) -> 0.0031892006 | N58: =N56*(1+$H57) -> 0.0037033161 | O58: =O56*(1+$H57) -> 0.0041599913 | P58: =P56*(1+$H57) -> 0.0053145151 | ... AS58: =AS56*(1+$H57) -> 0.0033235591
E59: Ratio of the reduction in vaccine-preventable disease mortality to the reduction in vaccine-preventable disease incidence | F59: =Inputs!F229 -> % | G59: =Inputs!G229 -> input | H59: =Inputs!H229 -> 1 | I59: =Inputs!I229 -> - | J59: =Inputs!J229 -> - | K59: =Inputs!K229 -> - | L59: =Inputs!L229 -> - | M59: =Inputs!M229 -> - | ... AS59: =Inputs!AS229 -> -
E60: Deaths averted among people age 5 through 14 | F60: # | G60: calc | H60: - | I60: =I$38*I55*I58*$H59 -> 28.31055 | J60: =J$38*J55*J58*$H59 -> 12.399303 | K60: =K$38*K55*K58*$H59 -> 23.442648 | L60: =L$38*L55*L58*$H59 -> 6.4959616 | M60: =M$38*M55*M58*$H59 -> 16.331573 | N60: =N$38*N55*N58*$H59 -> 26.205985 | O60: =O$38*O55*O58*$H59 -> 41.462663 | P60: =P$38*P55*P58*$H59 -> 65.649305 | ... AS60: =AS$38*AS55*AS58*$H59 -> 8.8751956
E61: Discount rate for deaths averted in the future | F61: =Inputs!F$232 -> % | G61: =Inputs!G$232 -> input | H61: =Inputs!H$232 -> 0.005 | I61: =Inputs!I$232 -> - | J61: =Inputs!J$232 -> - | K61: =Inputs!K$232 -> - | L61: =Inputs!L$232 -> - | M61: =Inputs!M$232 -> - | ... AS61: =Inputs!AS$232 -> -
E62: Average years between vaccination and a mortality occuring among 5-15-year-olds | F62: =Inputs!F233 -> # | G62: =Inputs!G233 -> input | H62: =Inputs!H233 -> 10 | I62: =Inputs!I233 -> - | J62: =Inputs!J233 -> - | K62: =Inputs!K233 -> - | L62: =Inputs!L233 -> - | M62: =Inputs!M233 -> - | ... AT62: =Inputs!AT233
E63: Discounted deaths averted among people age 5 through age 14 | F63: # | G63: calc | H63: - | I63: =I60*((1/(1+$H61))^$H62) -> 26.933183 | J63: =J60*((1/(1+$H61))^$H62) -> 11.796051 | K63: =K60*((1/(1+$H61))^$H62) -> 22.302115 | L63: =L60*((1/(1+$H61))^$H62) -> 6.1799197 | M63: =M60*((1/(1+$H61))^$H62) -> 15.537009 | N63: =N60*((1/(1+$H61))^$H62) -> 24.93101 | O63: =O60*((1/(1+$H61))^$H62) -> 39.445419 | P63: =P60*((1/(1+$H61))^$H62) -> 62.455331 | ... AS63: =AS60*((1/(1+$H61))^$H62) -> 8.4433991
C65: Mortality reduction among people age 15 through age 49
E66: Probability that a 15-year-old will die of a vaccine-preventable cause before reaching age 50 | F66: ='Disease burden'!F273 -> % | G66: supp | H66: ='Disease burden'!H273 -> - | I66: ='Disease burden'!I273 -> 0.0078743682 | J66: ='Disease burden'!J273 -> 0.0047114699 | K66: ='Disease burden'!K273 -> 0.0089669442 | L66: ='Disease burden'!L273 -> 0.0034785849 | M66: ='Disease burden'!M273 -> 0.0044360557 | N66: ='Disease burden'!N273 -> 0.0073672295 | O66: ='Disease burden'!O273 -> 0.0078794161 | ... AS66: ='Disease burden'!AS273 -> 0.0074035197
E67: Proportion of 15-49-year-olds represented in GBD 2021 disease burden estimates who were vaccinated, aggregated across vaccines | F67: ='Aggregation across vaccines'!F128 -> % | G67: supp | H67: ='Aggregation across vaccines'!H128 -> - | I67: ='Aggregation across vaccines'!I128 -> 0.07715206 | J67: ='Aggregation across vaccines'!J128 -> 0.096666232 | K67: ='Aggregation across vaccines'!K128 -> 0.079905606 | L67: ='Aggregation across vaccines'!L128 -> 0.11475448 | M67: ='Aggregation across vaccines'!M128 -> 0.081906502 | N67: ='Aggregation across vaccines'!N128 -> 0.074903536 | O67: ='Aggregation across vaccines'!O128 -> 0.07687099 | ... AS67: ='Aggregation across vaccines'!AS128 -> 0.081231334
E68: Proportion of vaccine-preventable disease incidence averted by full vaccination among 15-49-year-olds, aggregated across vaccines | F68: ='Aggregation across vaccines'!F116 -> % | G68: supp | H68: ='Aggregation across vaccines'!H116 -> - | I68: ='Aggregation across vaccines'!I116 -> 0.37754097 | J68: ='Aggregation across vaccines'!J116 -> 0.37417812 | K68: ='Aggregation across vaccines'!K116 -> 0.38709176 | L68: ='Aggregation across vaccines'!L116 -> 0.37439658 | M68: ='Aggregation across vaccines'!M116 -> 0.37591977 | N68: ='Aggregation across vaccines'!N116 -> 0.38148823 | O68: ='Aggregation across vaccines'!O116 -> 0.38190571 | ... AS68: ='Aggregation across vaccines'!AS116 -> 0.37836382
E69: Probability that an unvaccinated 15-year-old will die of a vaccine-preventable cause before reaching age 50 | F69: ='Disease burden'!F299 -> % | G69: calc | H69: ='Disease burden'!H299 -> - | I69: =I66/((1-I67)+(I67*(1-I68))) -> 0.0081106147 | J69: =J66/((1-J67)+(J67*(1-J68))) -> 0.0048882809 | K69: =K66/((1-K67)+(K67*(1-K68))) -> 0.0092531516 | L69: =L66/((1-L67)+(L67*(1-L68))) -> 0.003634747 | M69: =M66/((1-M67)+(M67*(1-M68))) -> 0.0045769822 | N69: =N66/((1-N67)+(N67*(1-N68))) -> 0.0075839392 | O69: =O66/((1-O67)+(O67*(1-O68))) -> 0.0081177322 | P69: =P66/((1-P67)+(P67*(1-P68))) -> 0.010882021 | ... AS69: =AS66/((1-AS67)+(AS67*(1-AS68))) -> 0.0076382823
E70: Mortalities indirectly attributable to vaccine-preventable disease per mortality directly caused by vaccine-preventable disease | F70: =Inputs!F228 -> % | G70: =Inputs!G228 -> input | H70: =Inputs!H228 -> 0.75 | I70: =Inputs!I228 -> - | J70: =Inputs!J228 -> - | K70: =Inputs!K228 -> - | L70: =Inputs!L228 -> - | M70: =Inputs!M228 -> - | ... AS70: =Inputs!AS228 -> -
E71: Probability that an unvaccinated 15-year-old will die of a vaccine-preventable cause before reaching age 50, including mortalities indirectly attributable to vaccine-preventable disease | F71: % | G71: calc | H71: - | I71: =I69*(1+$H70) -> 0.014193576 | J71: =J69*(1+$H70) -> 0.0085544916 | K71: =K69*(1+$H70) -> 0.016193015 | L71: =L69*(1+$H70) -> 0.0063608072 | M71: =M69*(1+$H70) -> 0.0080097189 | N71: =N69*(1+$H70) -> 0.013271894 | O71: =O69*(1+$H70) -> 0.014206031 | P71: =P69*(1+$H70) -> 0.019043537 | ... AS71: =AS69*(1+$H70) -> 0.013366994
E72: Ratio of the reduction in vaccine-preventable disease mortality to the reduction in vaccine-preventable disease incidence | F72: =Inputs!F229 -> % | G72: =Inputs!G229 -> input | H72: =Inputs!H229 -> 1 | I72: =Inputs!I229 -> - | J72: =Inputs!J229 -> - | K72: =Inputs!K229 -> - | L72: =Inputs!L229 -> - | M72: =Inputs!M229 -> - | ... AS72: =Inputs!AS229 -> -
E73: Deaths averted among people age 15 through 49 | F73: # | G73: calc | H73: - | I73: =I$38*I68*I71*$H72 -> 64.773871 | J73: =J$38*J68*J71*$H72 -> 23.720082 | K73: =K$38*K68*K71*$H72 -> 59.55829 | L73: =L$38*L68*L71*$H72 -> 13.552253 | M73: =M$38*M68*M71*$H72 -> 30.37563 | N73: =N$38*N68*N71*$H72 -> 68.274591 | O73: =O$38*O68*O71*$H72 -> 102.58205 | P73: =P$38*P68*P71*$H72 -> 170.776 | ... AS73: =AS$38*AS68*AS71*$H72 -> 26.036653
E74: Discount rate for deaths averted in the future | F74: =Inputs!F$232 -> % | G74: =Inputs!G$232 -> input | H74: =Inputs!H$232 -> 0.005 | I74: =Inputs!I$232 -> - | J74: =Inputs!J$232 -> - | K74: =Inputs!K$232 -> - | L74: =Inputs!L$232 -> - | M74: =Inputs!M$232 -> - | ... AS74: =Inputs!AS$232 -> -
E75: Average years between vaccination and a mortality occuring among 15-49-year-olds | F75: =Inputs!F234 -> # | G75: =Inputs!G234 -> input | H75: =Inputs!H234 -> 32.5 | I75: =Inputs!I234 -> - | J75: =Inputs!J234 -> - | K75: =Inputs!K234 -> - | L75: =Inputs!L234 -> - | M75: =Inputs!M234 -> - | ... AS75: =Inputs!AS234 -> -
E76: Discounted deaths averted among people age 15 through age 49 | F76: # | G76: calc | H76: - | I76: =I73*((1/(1+$H74))^$H75) -> 55.081131 | J76: =J73*((1/(1+$H74))^$H75) -> 20.170617 | K76: =K73*((1/(1+$H74))^$H75) -> 50.646007 | L76: =L73*((1/(1+$H74))^$H75) -> 11.524298 | M76: =M73*((1/(1+$H74))^$H75) -> 25.830231 | N76: =N73*((1/(1+$H74))^$H75) -> 58.058004 | O76: =O73*((1/(1+$H74))^$H75) -> 87.231706 | P76: =P73*((1/(1+$H74))^$H75) -> 145.22113 | ... AS76: =AS73*((1/(1+$H74))^$H75) -> 22.140537
C78: Mortality reduction among people age 50 through age 74
E79: Probability that a 50-year-old will die of a vaccine-preventable cause before reaching age 75 | F79: ='Disease burden'!F317 -> % | G79: supp | H79: ='Disease burden'!H317 -> - | I79: ='Disease burden'!I317 -> 0.031493246 | J79: ='Disease burden'!J317 -> 0.022096409 | K79: ='Disease burden'!K317 -> 0.031039617 | L79: ='Disease burden'!L317 -> 0.012590742 | M79: ='Disease burden'!M317 -> 0.016735516 | N79: ='Disease burden'!N317 -> 0.026807429 | O79: ='Disease burden'!O317 -> 0.033178372 | ... AS79: ='Disease burden'!AS317 -> 0.02792182
E80: Proportion of 50-74-year-olds represented in GBD 2021 disease burden estimates who were vaccinated, aggregated across vaccines | F80: ='Aggregation across vaccines'!F159 -> % | G80: supp | H80: ='Aggregation across vaccines'!H159 -> - | I80: ='Aggregation across vaccines'!I159 -> 0.038121136 | J80: ='Aggregation across vaccines'!J159 -> 0.046588507 | K80: ='Aggregation across vaccines'!K159 -> 0.03956062 | L80: ='Aggregation across vaccines'!L159 -> 0.056736112 | M80: ='Aggregation across vaccines'!M159 -> 0.040408754 | N80: ='Aggregation across vaccines'!N159 -> 0.036956956 | O80: ='Aggregation across vaccines'!O159 -> 0.037695408 | ... AS80: ='Aggregation across vaccines'!AS159 -> 0.040025988
E81: Proportion of vaccine-preventable disease incidence averted by full vaccination among 50-74-year-olds, aggregated across vaccines | F81: ='Aggregation across vaccines'!F147 -> % | G81: supp | H81: ='Aggregation across vaccines'!H147 -> - | I81: ='Aggregation across vaccines'!I147 -> 0.18643861 | J81: ='Aggregation across vaccines'!J147 -> 0.18127692 | K81: ='Aggregation across vaccines'!K147 -> 0.19140833 | L81: ='Aggregation across vaccines'!L147 -> 0.18415342 | M81: ='Aggregation across vaccines'!M147 -> 0.18527006 | N81: ='Aggregation across vaccines'!N147 -> 0.1882717 | O81: ='Aggregation across vaccines'!O147 -> 0.1877035 | ... AS81: ='Aggregation across vaccines'!AS147 -> 0.18681578
E82: Probability that an unvaccinated 50-year-old will die of a vaccine-preventable cause before reaching age 75 | F82: ='Disease burden'!F343 -> % | G82: calc | H82: ='Disease burden'!H343 -> - | I82: =I79/((1-I80)+(I80*(1-I81))) -> 0.031718679 | J82: =J79/((1-J80)+(J80*(1-J81))) -> 0.022284612 | K82: =K79/((1-K80)+(K80*(1-K81))) -> 0.031276449 | L82: =L79/((1-L80)+(L80*(1-L81))) -> 0.012723681 | M82: =M79/((1-M80)+(M80*(1-M81))) -> 0.016861752 | N82: =N79/((1-N80)+(N80*(1-N81))) -> 0.02699526 | O82: =O79/((1-O80)+(O80*(1-O81))) -> 0.0334148 | P82: =P79/((1-P80)+(P80*(1-P81))) -> 0.034148534 | ... AS82: =AS79/((1-AS80)+(AS80*(1-AS81))) -> 0.028132178
E83: Mortalities indirectly attributable to vaccine-preventable disease per mortality directly caused by vaccine-preventable disease | F83: =Inputs!F228 -> % | G83: =Inputs!G228 -> input | H83: =Inputs!H228 -> 0.75 | I83: =Inputs!I228 -> - | J83: =Inputs!J228 -> - | K83: =Inputs!K228 -> - | L83: =Inputs!L228 -> - | M83: =Inputs!M228 -> - | ... AS83: =Inputs!AS228 -> -
E84: Probability that an unvaccinated 50-year-old will die of a vaccine-preventable cause before reaching age 75, including mortalities indirectly attributable to vaccine-preventable disease | F84: % | G84: calc | H84: - | I84: =I82*(1+$H83) -> 0.055507687 | J84: =J82*(1+$H83) -> 0.03899807 | K84: =K82*(1+$H83) -> 0.054733786 | L84: =L82*(1+$H83) -> 0.022266442 | M84: =M82*(1+$H83) -> 0.029508066 | N84: =N82*(1+$H83) -> 0.047241706 | O84: =O82*(1+$H83) -> 0.0584759 | P84: =P82*(1+$H83) -> 0.059759934 | ... AS84: =AS82*(1+$H83) -> 0.049231312
E85: Ratio of the reduction in vaccine-preventable disease mortality to the reduction in vaccine-preventable disease incidence | F85: =Inputs!F229 -> % | G85: =Inputs!G229 -> input | H85: =Inputs!H229 -> 1 | I85: =Inputs!I229 -> - | J85: =Inputs!J229 -> - | K85: =Inputs!K229 -> - | L85: =Inputs!L229 -> - | M85: =Inputs!M229 -> - | ... AS85: =Inputs!AS229 -> -
E86: Deaths averted among people age 50 through 74 | F86: # | G86: calc | H86: - | I86: =I$38*I81*I84*$H85 -> 125.09298 | J86: =J$38*J81*J84*$H85 -> 52.387688 | K86: =K$38*K81*K84*$H85 -> 99.544416 | L86: =L$38*L81*L84*$H85 -> 23.334474 | M86: =M$38*M81*M84*$H85 -> 55.151692 | N86: =N$38*N81*N84*$H85 -> 119.93769 | O86: =O$38*O81*O84*$H85 -> 207.53519 | P86: =P$38*P81*P84*$H85 -> 264.79715 | ... AS86: =AS$38*AS81*AS84*$H85 -> 47.347469
E87: Discount rate for deaths averted in the future | F87: =Inputs!F$232 -> % | G87: =Inputs!G$232 -> input | H87: =Inputs!H$232 -> 0.005 | I87: =Inputs!I$232 -> - | J87: =Inputs!J$232 -> - | K87: =Inputs!K$232 -> - | L87: =Inputs!L$232 -> - | M87: =Inputs!M$232 -> - | ... AS87: =Inputs!AS$232 -> -
E88: Average years between vaccination and a mortality occuring among 50-74-year-olds | F88: =Inputs!F235 -> # | G88: =Inputs!G235 -> input | H88: =Inputs!H235 -> 62.5 | I88: =Inputs!I235 -> - | J88: =Inputs!J235 -> - | K88: =Inputs!K235 -> - | L88: =Inputs!L235 -> - | M88: =Inputs!M235 -> - | ... AS88: =Inputs!AS235 -> -
E89: Discounted deaths averted among people age 50 through age 74 | F89: # | G89: calc | H89: - | I89: =I86*((1/(1+$H87))^$H88) -> 91.591271 | J89: =J86*((1/(1+$H87))^$H88) -> 38.357507 | K89: =K86*((1/(1+$H87))^$H88) -> 72.884981 | L89: =L86*((1/(1+$H87))^$H88) -> 17.085164 | M89: =M86*((1/(1+$H87))^$H88) -> 40.381271 | N89: =N86*((1/(1+$H87))^$H88) -> 87.816641 | O89: =O86*((1/(1+$H87))^$H88) -> 151.95426 | P89: =P86*((1/(1+$H87))^$H88) -> 193.88064 | ... AS89: =AS86*((1/(1+$H87))^$H88) -> 34.667131
C91: Long-term income increases
E92: Ratio of value generated from income increases to value generated from mortalities averted among people under age 15 by seasonal malaria chemoprevention (SMC) | F92: =Inputs!F238 -> # | G92: =Inputs!G238 -> input | H92: =Inputs!H238 -> 0.30647 | I92: =Inputs!I238 -> - | J92: =Inputs!J238 -> - | K92: =Inputs!K238 -> - | L92: =Inputs!L238 -> - | M92: =Inputs!M238 -> - | ... AS92: =Inputs!AS238 -> -
E93: Adjustment for income increases generated by New Incentives' program compared to SMC | F93: =Inputs!F239 -> % | G93: =Inputs!G239 -> input | H93: =Inputs!H239 -> 0 | I93: =Inputs!I239 -> - | J93: =Inputs!J239 -> - | K93: =Inputs!K239 -> - | L93: =Inputs!L239 -> - | M93: =Inputs!M239 -> - | ... AS93: =Inputs!AS239 -> -
E94: Ratio of value generated from income increases to value generated from mortalities averted among people under age 15 by New Incentives' program | F94: # | G94: calc | H94: =H92*(1+H93) -> 0.30647 | I94: - | J94: - | K94: - | L94: - | M94: - | N94: - | O94: - | P94: - | Q94: - | R94: - | S94: - | T94: - | U94: - | V94: - | W94: - | X94: - | Y94: - | Z94: - | AA94: - | AB94: - | AC94: - | AD94: - | AE94: - | AF94: - | AG94: - | AH94: - | AI94: - | AJ94: - | AK94: - | AL94: - | AM94: - | AN94: - | AO94: - | AP94: - | AQ94: - | AR94: - | AS94: -
E95: Value assigned to averting a death from vaccine-preventable disease of a person under age 5 | F95: =Inputs!F256 -> UoV | G95: =Inputs!G256 -> input | H95: =Inputs!H256 -> 116.25262 | I95: =Inputs!I256 -> - | J95: =Inputs!J256 -> - | K95: =Inputs!K256 -> - | L95: =Inputs!L256 -> - | M95: =Inputs!M256 -> - | ... AS95: =Inputs!AS256 -> -
E96: Value assigned to averting a death from vaccine-preventable disease of a person age 5-14 | F96: =Inputs!F257 -> UoV | G96: =Inputs!G257 -> input | H96: =Inputs!H257 -> 133.7 | I96: =Inputs!I257 -> - | J96: =Inputs!J257 -> - | K96: =Inputs!K257 -> - | L96: =Inputs!L257 -> - | M96: =Inputs!M257 -> - | ... AS96: =Inputs!AS257 -> -
E97: Units of value generated from deaths averted among people under age 15 | F97: UoV | G97: calc | H97: - | I97: =(I50*$H95)+(I63*$H96) -> 48584.509 | J97: =(J50*$H95)+(J63*$H96) -> 21972.56 | K97: =(K50*$H95)+(K63*$H96) -> 39938.236 | L97: =(L50*$H95)+(L63*$H96) -> 11068.658 | M97: =(M50*$H95)+(M63*$H96) -> 27457.335 | N97: =(N50*$H95)+(N63*$H96) -> 40781.366 | O97: =(O50*$H95)+(O63*$H96) -> 63518.246 | P97: =(P50*$H95)+(P63*$H96) -> 104330.96 | ... AS97: =(AS50*$H95)+(AS63*$H96) -> 11992.485
E98: Units of value generated from long-term income increases | F98: UoV | G98: calc | H98: - | I98: =I97*$H94 -> 14889.694 | J98: =J97*$H94 -> 6733.9304 | K98: =K97*$H94 -> 12239.871 | L98: =L97*$H94 -> 3392.2115 | M98: =M97*$H94 -> 8414.8494 | N98: =N97*$H94 -> 12498.265 | O98: =O97*$H94 -> 19466.437 | P98: =P97*$H94 -> 31974.308 | ... AS98: =AS97*$H94 -> 3675.3368
C100: Consumption increases
E101: Travel cost of bringing a child to a health clinic for vaccination | F101: =Inputs!F242 -> ₦ | G101: =Inputs!G242 -> input | H101: =Inputs!H242 -> 200 | I101: =Inputs!I242 -> - | J101: =Inputs!J242 -> - | K101: =Inputs!K242 -> - | L101: =Inputs!L242 -> - | M101: =Inputs!M242 -> - | ... AS101: =Inputs!AS242 -> -
E102: Number of routine vaccination visits incentivized by New Incentives' program | F102: =Inputs!F243 -> # | G102: =Inputs!G243 -> input | H102: =Inputs!H243 -> 5 | I102: =Inputs!I243 -> - | J102: =Inputs!J243 -> - | K102: =Inputs!K243 -> - | L102: =Inputs!L243 -> - | M102: =Inputs!M243 -> - | ... AS102: =Inputs!AS243 -> -
E103: Total travel costs of bringing a child to all incentivized vaccination visits | F103: =Inputs!F244 -> ₦ | G103: calc | H103: =H101*H102 -> 1000 | I103: =Inputs!I244 -> - | J103: =Inputs!J244 -> - | K103: =Inputs!K244 -> - | L103: =Inputs!L244 -> - | M103: =Inputs!M244 -> - | N103: =Inputs!N244 -> - | O103: =Inputs!O244 -> - | P103: =Inputs!P244 -> - | ... AS103: =Inputs!AS244 -> -
E104: Size of cash transfer disbursed for the routine vaccination visit at birth | F104: =Inputs!F244 -> ₦ | G104: =Inputs!G244 -> input | H104: =Inputs!H244 -> 500 | I104: =Inputs!I244 -> - | J104: =Inputs!J244 -> - | K104: =Inputs!K244 -> - | L104: =Inputs!L244 -> - | M104: =Inputs!M244 -> - | ... AS104: =Inputs!AS244 -> -
E105: Size of cash transfer disbursed for the routine vaccination visit at 6 weeks | F105: =Inputs!F245 -> ₦ | G105: =Inputs!G245 -> input | H105: =Inputs!H245 -> 500 | I105: =Inputs!I245 -> - | J105: =Inputs!J245 -> - | K105: =Inputs!K245 -> - | L105: =Inputs!L245 -> - | M105: =Inputs!M245 -> - | ... AS105: =Inputs!AS245 -> -
E106: Size of cash transfer disbursed for the routine vaccination visit at 10 weeks | F106: =Inputs!F246 -> ₦ | G106: =Inputs!G246 -> input | H106: =Inputs!H246 -> 500 | I106: =Inputs!I246 -> - | J106: =Inputs!J246 -> - | K106: =Inputs!K246 -> - | L106: =Inputs!L246 -> - | M106: =Inputs!M246 -> - | ... AS106: =Inputs!AS246 -> -
E107: Size of cash transfer disbursed for the routine vaccination visit at 14 weeks | F107: =Inputs!F247 -> ₦ | G107: =Inputs!G247 -> input | H107: =Inputs!H247 -> 500 | I107: =Inputs!I247 -> - | J107: =Inputs!J247 -> - | K107: =Inputs!K247 -> - | L107: =Inputs!L247 -> - | M107: =Inputs!M247 -> - | ... AS107: =Inputs!AS247 -> -
E108: Size of cash transfer disbursed for the routine vaccination visit at 9 months | F108: =Inputs!F248 -> ₦ | G108: =Inputs!G248 -> input | H108: =Inputs!H248 -> 2000 | I108: =Inputs!I248 -> - | J108: =Inputs!J248 -> - | K108: =Inputs!K248 -> - | L108: =Inputs!L248 -> - | M108: =Inputs!M248 -> - | ... AS108: =Inputs!AS248 -> -
E109: Total cash transfer disbursed for all incentivized routine vaccination visits | F109: ₦ | G109: calc | H109: =SUM(H104:H108) -> 4000 | I109: - | J109: - | K109: - | L109: - | M109: - | N109: - | O109: - | P109: - | Q109: - | R109: - | S109: - | T109: - | U109: - | V109: - | W109: - | X109: - | Y109: - | Z109: - | AA109: - | AB109: - | AC109: - | AD109: - | AE109: - | AF109: - | AG109: - | AH109: - | AI109: - | AJ109: - | AK109: - | AL109: - | AM109: - | AN109: - | AO109: - | AP109: - | AQ109: - | AR109: - | AS109: -
E110: Nigerian naira per U.S. dollar | F110: =Inputs!F249 -> ₦ | G110: =Inputs!G249 -> input | H110: =Inputs!H249 -> 362.31884 | I110: =Inputs!I249 -> - | J110: =Inputs!J249 -> - | K110: =Inputs!K249 -> - | L110: =Inputs!L249 -> - | M110: =Inputs!M249 -> - | ... AS110: =Inputs!AS249 -> -
E111: Total travel costs of bringing a child to all incentivized vaccination visits (in U.S. dollars) | F111: $ | G111: calc | H111: =H103/H110 -> 2.76 | I111: - | J111: - | K111: - | L111: - | M111: - | N111: - | O111: - | P111: - | Q111: - | R111: - | S111: - | T111: - | U111: - | V111: - | W111: - | X111: - | Y111: - | Z111: - | AA111: - | AB111: - | AC111: - | AD111: - | AE111: - | AF111: - | AG111: - | AH111: - | AI111: - | AJ111: - | AK111: - | AL111: - | AM111: - | AN111: - | AO111: - | AP111: - | AQ111: - | AR111: - | AS111: -
E112: Total cash transfer disbursed for all incentivized routine vaccination visits (in U.S. dollars) | F112: $ | G112: calc | H112: =H109/H110 -> 11.04 | I112: - | J112: - | K112: - | L112: - | M112: - | N112: - | O112: - | P112: - | Q112: - | R112: - | S112: - | T112: - | U112: - | V112: - | W112: - | X112: - | Y112: - | Z112: - | AA112: - | AB112: - | AC112: - | AD112: - | AE112: - | AF112: - | AG112: - | AH112: - | AI112: - | AJ112: - | AK112: - | AL112: - | AM112: - | AN112: - | AO112: - | AP112: - | AQ112: - | AR112: - | AS112: -
E113: Net increase in household consumption from bringing a child to all incentivized vaccination visits | F113: $ | G113: calc | H113: =H112-H111 -> 8.28 | I113: - | J113: - | K113: - | L113: - | M113: - | N113: - | O113: - | P113: - | Q113: - | R113: - | S113: - | T113: - | U113: - | V113: - | W113: - | X113: - | Y113: - | Z113: - | AA113: - | AB113: - | AC113: - | AD113: - | AE113: - | AF113: - | AG113: - | AH113: - | AI113: - | AJ113: - | AK113: - | AL113: - | AM113: - | AN113: - | AO113: - | AP113: - | AQ113: - | AR113: - | AS113: -
E114: Average number of people per household | F114: =Inputs!F250 -> # | G114: =Inputs!G250 -> input | H114: =Inputs!H250 -> 6.8 | I114: =Inputs!I250 -> - | J114: =Inputs!J250 -> - | K114: =Inputs!K250 -> - | L114: =Inputs!L250 -> - | M114: =Inputs!M250 -> - | ... AS114: =Inputs!AS250 -> -
E115: Increase in consumption per person | F115: $ | G115: calc | H115: =H113/H114 -> 1.2176471 | I115: - | J115: - | K115: - | L115: - | M115: - | N115: - | O115: - | P115: - | Q115: - | R115: - | S115: - | T115: - | U115: - | V115: - | W115: - | X115: - | Y115: - | Z115: - | AA115: - | AB115: - | AC115: - | AD115: - | AE115: - | AF115: - | AG115: - | AH115: - | AI115: - | AJ115: - | AK115: - | AL115: - | AM115: - | AN115: - | AO115: - | AP115: - | AQ115: - | AR115: - | AS115: -
E116: Baseline annual consumption per capita | F116: =Inputs!F251 -> $ | G116: =Inputs!G251 -> input | H116: =Inputs!H251 -> 285.92 | I116: =Inputs!I251 -> - | J116: =Inputs!J251 -> - | K116: =Inputs!K251 -> - | L116: =Inputs!L251 -> - | M116: =Inputs!M251 -> - | ... AS116: =Inputs!AS251 -> -
...

Sheet Aggregation across vaccines
I1: New Incentives – current states of operation | R1: New Incentives – prospective states | AF1: New Incentives – prospective states
I2: Nigeria | J2: Nigeria | K2: Nigeria | L2: Nigeria | M2: Nigeria | N2: Nigeria | O2: Nigeria | P2: Nigeria | Q2: Nigeria | R2: Nigeria | S2: Nigeria | T2: Nigeria | U2: Nigeria | V2: Nigeria | W2: Nigeria | X2: Nigeria | Y2: Nigeria | Z2: Nigeria | AA2: Nigeria | AB2: Nigeria | AC2: Nigeria | AD2: Nigeria | AE2: Nigeria | AF2: Nigeria | AG2: Nigeria | AH2: Nigeria | AI2: Nigeria | AJ2: Nigeria | AK2: Nigeria | AL2: Nigeria | AM2: Nigeria | AN2: Nigeria | AO2: Nigeria | AP2: Nigeria | AQ2: Nigeria | AR2: Nigeria | AS2: Nigeria
A3: Main calculations | F3: unit | G3: type | H3: Overall | I3: Bauchi | J3: Gombe | K3: Jigawa | L3: Kaduna | M3: Kano | N3: Katsina | O3: Kebbi | P3: Sokoto | Q3: Zamfara | R3: Abia | S3: Adamawa | T3: Akwa Ibom | U3: Anambra | V3: Bayelsa | W3: Benue | X3: Borno | Y3: Cross River | Z3: Delta | AA3: Ebonyi | AB3: Edo | AC3: Ekiti | AD3: Enugu | AE3: FCT | AF3: Imo | AG3: Kogi | AH3: Kwara | AI3: Lagos | AJ3: Nasarawa | AK3: Niger | AL3: Ogun | AM3: Ondo | AN3: Osun | AO3: Oyo | AP3: Plateau | AQ3: Rivers | AR3: Taraba | AS3: Yobe
E4: Final cost-effectiveness estimate (pulled from "Main calcs" sheet for visibility) | F4: ='Main CEA'!F241 -> xcash | G4: ='Main CEA'!G241 -> calc | H4: ='Main CEA'!H241 -> - | I4: ='Main CEA'!I241 -> 23.798889 | J4: ='Main CEA'!J241 -> 10.800641 | K4: ='Main CEA'!K241 -> 19.899944 | L4: ='Main CEA'!L241 -> 5.6568275 | M4: ='Main CEA'!M241 -> 13.129176 | ... AS4: ='Main CEA'!AS241 -> 6.7228331
A5: Baseline coverage for the target population
C7: Baseline vaccination coverage for the target population
E8: Baseline proportion of children in the target population who receive the BCG vaccine | F8: ='Vaccine coverage'!F91 -> % | G8: supp | H8: ='Vaccine coverage'!H91 -> - | I8: ='Vaccine coverage'!I91 -> 0.55353772 | J8: ='Vaccine coverage'!J91 -> 0.72328382 | K8: ='Vaccine coverage'!K91 -> 0.61118826 | L8: ='Vaccine coverage'!L91 -> 0.77568938 | M8: ='Vaccine coverage'!M91 -> 0.62892504 | N8: ='Vaccine coverage'!N91 -> 0.49455416 | O8: ='Vaccine coverage'!O91 -> 0.39201909 | ... AS8: ='Vaccine coverage'!AS91 -> 0.7529799
E9: Baseline proportion of children in the target population who receive the 1st dose of the Penta vaccine | F9: ='Vaccine coverage'!F92 -> % | G9: supp | H9: ='Vaccine coverage'!H92 -> - | I9: ='Vaccine coverage'!I92 -> 0.49558276 | J9: ='Vaccine coverage'!J92 -> 0.67331278 | K9: ='Vaccine coverage'!K92 -> 0.57384453 | L9: ='Vaccine coverage'!L92 -> 0.74159805 | M9: ='Vaccine coverage'!M92 -> 0.57953749 | N9: ='Vaccine coverage'!N92 -> 0.45805759 | O9: ='Vaccine coverage'!O92 -> 0.32588565 | ... AS9: ='Vaccine coverage'!AS92 -> 0.73896166
E10: Baseline proportion of children in the target population who receive the 2nd dose of the Penta vaccine | F10: ='Vaccine coverage'!F93 -> % | G10: supp | H10: ='Vaccine coverage'!H93 -> - | I10: ='Vaccine coverage'!I93 -> 0.45193705 | J10: ='Vaccine coverage'!J93 -> 0.63149437 | K10: ='Vaccine coverage'!K93 -> 0.51747533 | L10: ='Vaccine coverage'!L93 -> 0.67035112 | M10: ='Vaccine coverage'!M93 -> 0.49860579 | N10: ='Vaccine coverage'!N93 -> 0.4193159 | O10: ='Vaccine coverage'!O93 -> 0.23438593 | ... AS10: ='Vaccine coverage'!AS93 -> 0.71292778
E11: Baseline proportion of children in the target population who receive the 3rd dose of the Penta vaccine | F11: ='Vaccine coverage'!F94 -> % | G11: supp | H11: ='Vaccine coverage'!H94 -> - | I11: ='Vaccine coverage'!I94 -> 0.36136808 | J11: ='Vaccine coverage'!J94 -> 0.50198796 | K11: ='Vaccine coverage'!K94 -> 0.39680563 | L11: ='Vaccine coverage'!L94 -> 0.57935842 | M11: ='Vaccine coverage'!M94 -> 0.38185245 | N11: ='Vaccine coverage'!N94 -> 0.35294269 | O11: ='Vaccine coverage'!O94 -> 0.14129572 | ... AS11: ='Vaccine coverage'!AS94 -> 0.64283656
E12: Baseline proportion of children in the target population who receive the 1st dose of the PCV vaccine | F12: ='Vaccine coverage'!F103 -> % | G12: supp | H12: ='Vaccine coverage'!H103 -> - | I12: ='Vaccine coverage'!I103 -> 0.49380009 | J12: ='Vaccine coverage'!J103 -> 0.63762814 | K12: ='Vaccine coverage'!K103 -> 0.56626675 | L12: ='Vaccine coverage'!L103 -> 0.7278372 | M12: ='Vaccine coverage'!M103 -> 0.56588241 | N12: ='Vaccine coverage'!N103 -> 0.44352586 | O12: ='Vaccine coverage'!O103 -> 0.32098795 | ... AS12: ='Vaccine coverage'!AS103 -> 0.7209382
E13: Baseline proportion of children in the target population who receive the 2nd dose of the PCV vaccine | F13: ='Vaccine coverage'!F104 -> % | G13: supp | H13: ='Vaccine coverage'!H104 -> - | I13: ='Vaccine coverage'!I104 -> 0.45031138 | J13: ='Vaccine coverage'!J104 -> 0.59802605 | K13: ='Vaccine coverage'!K104 -> 0.51064193 | L13: ='Vaccine coverage'!L104 -> 0.65791231 | M13: ='Vaccine coverage'!M104 -> 0.48685763 | N13: ='Vaccine coverage'!N104 -> 0.39808199 | O13: ='Vaccine coverage'!O104 -> 0.23086336 | ... AS13: ='Vaccine coverage'!AS104 -> 0.68188738
E14: Baseline proportion of children in the target population who receive the 3rd dose of the PCV vaccine | F14: ='Vaccine coverage'!F105 -> % | G14: supp | H14: ='Vaccine coverage'!H105 -> - | I14: ='Vaccine coverage'!I105 -> 0.36006819 | J14: ='Vaccine coverage'!J105 -> 0.4753833 | K14: ='Vaccine coverage'!K105 -> 0.3915657 | L14: ='Vaccine coverage'!L105 -> 0.56860804 | M14: ='Vaccine coverage'!M105 -> 0.37285523 | N14: ='Vaccine coverage'!N105 -> 0.33628008 | O14: ='Vaccine coverage'!O105 -> 0.1391722 | ... AS14: ='Vaccine coverage'!AS105 -> 0.63182223
E15: Baseline proportion of children in the target popullation who receive the 1st dose of the rotavirus vaccine | F15: ='Vaccine coverage'!F110 -> % | G15: supp | H15: ='Vaccine coverage'!H110 -> - | I15: ='Vaccine coverage'!I110 -> 0.49469143 | J15: ='Vaccine coverage'!J110 -> 0.65547046 | K15: ='Vaccine coverage'!K110 -> 0.57005564 | L15: ='Vaccine coverage'!L110 -> 0.73471763 | M15: ='Vaccine coverage'!M110 -> 0.57270995 | N15: ='Vaccine coverage'!N110 -> 0.45079172 | O15: ='Vaccine coverage'!O110 -> 0.3234368 | ... AS15: ='Vaccine coverage'!AS110 -> 0.72994993
E16: Estimated proportion of children in the target population who receive the 2nd dose of the rotavirus vaccine | F16: ='Vaccine coverage'!F111 -> % | G16: supp | H16: ='Vaccine coverage'!H111 -> - | I16: ='Vaccine coverage'!I111 -> 0.45112421 | J16: ='Vaccine coverage'!J111 -> 0.61476021 | K16: ='Vaccine coverage'!K111 -> 0.51405863 | L16: ='Vaccine coverage'!L111 -> 0.66413171 | M16: ='Vaccine coverage'!M111 -> 0.49273171 | N16: ='Vaccine coverage'!N111 -> 0.40869894 | O16: ='Vaccine coverage'!O111 -> 0.23262465 | ... AS16: ='Vaccine coverage'!AS111 -> 0.69740758
E17: Baseline proportion of children in the target population who receive the 1st dose of the measles vaccine | F17: ='Vaccine coverage'!F118 -> % | G17: supp | H17: ='Vaccine coverage'!H118 -> - | I17: ='Vaccine coverage'!I118 -> 0.30840134 | J17: ='Vaccine coverage'!J118 -> 0.36747822 | K17: ='Vaccine coverage'!K118 -> 0.55972841 | L17: ='Vaccine coverage'!L118 -> 0.56773883 | M17: ='Vaccine coverage'!M118 -> 0.40552774 | N17: ='Vaccine coverage'!N118 -> 0.43756944 | O17: ='Vaccine coverage'!O118 -> 0.63282353 | ... AS17: ='Vaccine coverage'!AS118 -> 0.71392908
C19: Proportion of vaccine-preventable mortalities that could be prevented by each vaccine dose
E20: Proportion of vaccine-preventable mortalities among people under age 5 that could be prevented by the BCG vaccine | F20: ='Disease burden'!F384 -> % | G20: ='Disease burden'!G384 -> feed | H20: ='Disease burden'!H384 -> - | I20: ='Disease burden'!I384 -> 0.2130494 | J20: ='Disease burden'!J384 -> 0.15347722 | K20: ='Disease burden'!K384 -> 0.24112748 | L20: ='Disease burden'!L384 -> 0.13471259 | M20: ='Disease burden'!M384 -> 0.15263081 | ... AS20: ='Disease burden'!AS384 -> 0.19515058
E21: Proportion of vaccine-preventable mortalities among people under age 5 that could be prevented by the 1st dose of the Penta vaccine | F21: ='Disease burden'!F385 -> % | G21: supp | H21: ='Disease burden'!H385 -> - | I21: ='Disease burden'!I385 -> 0.053131051 | J21: ='Disease burden'!J385 -> 0.06606296 | K21: ='Disease burden'!K385 -> 0.059308756 | L21: ='Disease burden'!L385 -> 0.070627408 | M21: ='Disease burden'!M385 -> 0.057825023 | N21: ='Disease burden'!N385 -> 0.062888388 | O21: ='Disease burden'!O385 -> 0.070475442 | ... AS21: ='Disease burden'!AS385 -> 0.071075284
E22: Proportion of vaccine-preventable mortalities among people under age 5 that could be prevented by the 2nd dose of the Penta vaccine | F22: ='Disease burden'!F386 -> % | G22: supp | H22: ='Disease burden'!H386 -> - | I22: ='Disease burden'!I386 -> 0.083491652 | J22: ='Disease burden'!J386 -> 0.10381322 | K22: ='Disease burden'!K386 -> 0.093199474 | L22: ='Disease burden'!L386 -> 0.11098593 | M22: ='Disease burden'!M386 -> 0.090867893 | N22: ='Disease burden'!N386 -> 0.098824609 | O22: ='Disease burden'!O386 -> 0.11074712 | ... AS22: ='Disease burden'!AS386 -> 0.11168973
E23: Proportion of vaccine-preventable mortalities among people under age 5 that could be prevented by the 3rd dose of the Penta vaccine | F23: ='Disease burden'!F387 -> % | G23: supp | H23: ='Disease burden'!H387 -> - | I23: ='Disease burden'!I387 -> 0.0151803 | J23: ='Disease burden'!J387 -> 0.018875132 | K23: ='Disease burden'!K387 -> 0.016945359 | L23: ='Disease burden'!L387 -> 0.020179259 | M23: ='Disease burden'!M387 -> 0.016521435 | N23: ='Disease burden'!N387 -> 0.017968111 | O23: ='Disease burden'!O387 -> 0.02013584 | ... AS23: ='Disease burden'!AS387 -> 0.020307224
E24: Proportion of vaccine-preventable mortalities among people under age 5 that could be prevented by the 1st dose of the PCV vaccine | F24: ='Disease burden'!F388 -> % | G24: supp | H24: ='Disease burden'!H388 -> - | I24: ='Disease burden'!I388 -> 0.11779326 | J24: ='Disease burden'!J388 -> 0.13550544 | K24: ='Disease burden'!K388 -> 0.11656148 | L24: ='Disease burden'!L388 -> 0.14964149 | M24: ='Disease burden'!M388 -> 0.14524548 | N24: ='Disease burden'!N388 -> 0.10887223 | O24: ='Disease burden'!O388 -> 0.1087302 | ... AS24: ='Disease burden'!AS388 -> 0.11016126
E25: Proportion of vaccine-preventable mortalities among people under age 5 that could be prevented by the 2nd dose of the PCV vaccine | F25: ='Disease burden'!F389 -> % | G25: supp | H25: ='Disease burden'!H389 -> - | I25: ='Disease burden'!I389 -> 0.18510369 | J25: ='Disease burden'!J389 -> 0.21293712 | K25: ='Disease burden'!K389 -> 0.18316803 | L25: ='Disease burden'!L389 -> 0.23515091 | M25: ='Disease burden'!M389 -> 0.2282429 | N25: ='Disease burden'!N389 -> 0.17108494 | O25: ='Disease burden'!O389 -> 0.17086174 | ... AS25: ='Disease burden'!AS389 -> 0.17311055
E26: Proportion of vaccine-preventable mortalities among people under age 5 that could be prevented by the 3rd dose of the PCV vaccine | F26: ='Disease burden'!F390 -> % | G26: supp | H26: ='Disease burden'!H390 -> - | I26: ='Disease burden'!I390 -> 0.033655217 | J26: ='Disease burden'!J390 -> 0.03871584 | K26: ='Disease burden'!K390 -> 0.033303279 | L26: ='Disease burden'!L390 -> 0.042754711 | M26: ='Disease burden'!M390 -> 0.041498709 | N26: ='Disease burden'!N390 -> 0.031106352 | O26: ='Disease burden'!O390 -> 0.031065772 | ... AS26: ='Disease burden'!AS390 -> 0.031474645
E27: Proportion of vaccine-preventable mortalities among people under age 5 that could be prevented by the 1st dose of the rotavirus vaccine | F27: ='Disease burden'!F391 -> % | G27: supp | H27: ='Disease burden'!H391 -> - | I27: ='Disease burden'!I391 -> 0.20297125 | J27: ='Disease burden'!J391 -> 0.19018131 | K27: ='Disease burden'!K391 -> 0.16184636 | L27: ='Disease burden'!L391 -> 0.15476798 | M27: ='Disease burden'!M391 -> 0.19738225 | N27: ='Disease burden'!N391 -> 0.18869946 | O27: ='Disease burden'!O391 -> 0.18724923 | ... AS27: ='Disease burden'!AS391 -> 0.17620694
E28: Proportion of vaccine-preventable mortalities among people under age 5 that could be prevented by the 2nd dose of the rotavirus vaccine | F28: ='Disease burden'!F392 -> % | G28: supp | H28: ='Disease burden'!H392 -> - | I28: ='Disease burden'!I392 -> 0.035818456 | J28: ='Disease burden'!J392 -> 0.033561407 | K28: ='Disease burden'!K392 -> 0.028561122 | L28: ='Disease burden'!L392 -> 0.027311996 | M28: ='Disease burden'!M392 -> 0.034832162 | N28: ='Disease burden'!N392 -> 0.033299904 | O28: ='Disease burden'!O392 -> 0.033043981 | ... AS28: ='Disease burden'!AS392 -> 0.031095342
E29: Proportion of vaccine-preventable mortalities among people under age 5 that could be prevented by the 1st dose of the measles vaccine | F29: ='Disease burden'!F393 -> % | G29: supp | H29: ='Disease burden'!H393 -> - | I29: ='Disease burden'!I393 -> 0.059805717 | J29: ='Disease burden'!J393 -> 0.046870343 | K29: ='Disease burden'!K393 -> 0.06597866 | L29: ='Disease burden'!L393 -> 0.053867734 | M29: ='Disease burden'!M393 -> 0.034953333 | N29: ='Disease burden'!N393 -> 0.081308726 | O29: ='Disease burden'!O393 -> 0.076530784 | ... AS29: ='Disease burden'!AS393 -> 0.079728455
C31: Baseline vaccination coverage for the target population, aggregated across vaccines
E32: Proportion of children in the target population who would be vaccinated in the absence of the program, aggregated across vaccines | F32: % | G32: calc | H32: - | I32: =SUMPRODUCT(I8:I17,I20:I29) -> 0.47613003 | J32: =SUMPRODUCT(J8:J17,J20:J29) -> 0.62518435 | K32: =SUMPRODUCT(K8:K17,K20:K29) -> 0.55281297 | L32: =SUMPRODUCT(L8:L17,L20:L29) -> 0.69332916 | M32: =SUMPRODUCT(M8:M17,M20:M29) -> 0.53428802 | N32: =SUMPRODUCT(N8:N17,N20:N29) -> 0.43954496 | O32: =SUMPRODUCT(O8:O17,O20:O29) -> 0.32205884 | P32: =SUMPRODUCT(P8:P17,P20:P29) -> 0.2468535 | ... AS32: =SUMPRODUCT(AS8:AS17,AS20:AS29) -> 0.71672388
A34: Vaccine efficacy and coverage for people under age 5, aggregated across vaccines
C36: Vaccine efficacy with universal coverage
E37: BCG vaccine efficacy rate with universal coverage | F37: ='Vaccine efficacy'!F49 -> % | G37: supp | H37: ='Vaccine efficacy'!H49 -> 0.7226738 | I37: ='Vaccine efficacy'!I49 -> - | J37: ='Vaccine efficacy'!J49 -> - | K37: ='Vaccine efficacy'!K49 -> - | L37: ='Vaccine efficacy'!L49 -> - | M37: ='Vaccine efficacy'!M49 -> - | N37: ='Vaccine efficacy'!N49 -> - | O37: ='Vaccine efficacy'!O49 -> - | ... AT37: ='Vaccine efficacy'!AT49
E38: DTP vaccine efficacy rate with universal coverage (part of the Penta vaccine) | F38: ='Vaccine efficacy'!F50 -> % | G38: supp | H38: ='Vaccine efficacy'!H50 -> 0.71417176 | I38: ='Vaccine efficacy'!I50 -> - | J38: ='Vaccine efficacy'!J50 -> - | K38: ='Vaccine efficacy'!K50 -> - | L38: ='Vaccine efficacy'!L50 -> - | M38: ='Vaccine efficacy'!M50 -> - | N38: ='Vaccine efficacy'!N50 -> - | O38: ='Vaccine efficacy'!O50 -> - | ... AT38: ='Vaccine efficacy'!AT50
E39: Hib vaccine efficacy rate with universal coverage (part of the Penta vaccine) | F39: ='Vaccine efficacy'!F51 -> % | G39: supp | H39: ='Vaccine efficacy'!H51 -> 0.69716767 | I39: ='Vaccine efficacy'!I51 -> - | J39: ='Vaccine efficacy'!J51 -> - | K39: ='Vaccine efficacy'!K51 -> - | L39: ='Vaccine efficacy'!L51 -> - | M39: ='Vaccine efficacy'!M51 -> - | N39: ='Vaccine efficacy'!N51 -> - | O39: ='Vaccine efficacy'!O51 -> - | ... AT39: ='Vaccine efficacy'!AT51
E40: PCV vaccine efficacy rate with universal coverage | F40: ='Vaccine efficacy'!F52 -> % | G40: supp | H40: ='Vaccine efficacy'!H52 -> 0.49311859 | I40: ='Vaccine efficacy'!I52 -> - | J40: ='Vaccine efficacy'!J52 -> - | K40: ='Vaccine efficacy'!K52 -> - | L40: ='Vaccine efficacy'!L52 -> - | M40: ='Vaccine efficacy'!M52 -> - | N40: ='Vaccine efficacy'!N52 -> - | O40: ='Vaccine efficacy'!O52 -> - | ... AT40: ='Vaccine efficacy'!AT52
E41: Rotavirus vaccine efficacy rate with universal coverage | F41: ='Vaccine efficacy'!F53 -> % | G41: supp | H41: ='Vaccine efficacy'!H53 -> 0.39109406 | I41: ='Vaccine efficacy'!I53 -> - | J41: ='Vaccine efficacy'!J53 -> - | K41: ='Vaccine efficacy'!K53 -> - | L41: ='Vaccine efficacy'!L53 -> - | M41: ='Vaccine efficacy'!M53 -> - | N41: ='Vaccine efficacy'!N53 -> - | O41: ='Vaccine efficacy'!O53 -> - | ... AT41: ='Vaccine efficacy'!AT53
E42: Measles vaccine efficacy rate with universal coverage | F42: ='Vaccine efficacy'!F54 -> % | G42: supp | H42: ='Vaccine efficacy'!H54 -> 0.66531945 | I42: ='Vaccine efficacy'!I54 -> - | J42: ='Vaccine efficacy'!J54 -> - | K42: ='Vaccine efficacy'!K54 -> - | L42: ='Vaccine efficacy'!L54 -> - | M42: ='Vaccine efficacy'!M54 -> - | N42: ='Vaccine efficacy'!N54 -> - | O42: ='Vaccine efficacy'!O54 -> - | ... AT42: ='Vaccine efficacy'!AT54
C44: Proportion of deaths from vaccine-preventable causes among unvaccinated people under age 5 that are addressable by each vaccine, adjusted for deaths occurring before the age of vaccination
E45: Proportion of deaths from vaccine-preventable causes among unvaccinated people under age 5 that are addressable by the BCG vaccine, adjusted for deaths occurring before the age of vaccination | F45: ='Disease burden'!F212 -> % | G45: supp | H45: ='Disease burden'!H212 -> - | I45: ='Disease burden'!I212 -> 0.15586704 | J45: ='Disease burden'!J212 -> 0.11144603 | K45: ='Disease burden'!K212 -> 0.1819901 | L45: ='Disease burden'!L212 -> 0.098943878 | M45: ='Disease burden'!M212 -> 0.10933325 | N45: ='Disease burden'!N212 -> 0.15335908 | O45: ='Disease burden'!O212 -> 0.14253742 | ... AS45: ='Disease burden'!AS212 -> 0.14647347
E46: Proportion of deaths from vaccine-preventable causes among unvaccinated people under age 5 that are addressable by the DTP vaccine, adjusted for deaths occurring before the age of vaccination | F46: ='Disease burden'!F213 -> % | G46: supp | H46: ='Disease burden'!H213 -> - | I46: ='Disease burden'!I213 -> 0.088968849 | J46: ='Disease burden'!J213 -> 0.11092845 | K46: ='Disease burden'!K213 -> 0.10532978 | L46: ='Disease burden'!L213 -> 0.11816781 | M46: ='Disease burden'!M213 -> 0.091164015 | N46: ='Disease burden'!N213 -> 0.11285135 | O46: ='Disease burden'!O213 -> 0.12932727 | ... AS46: ='Disease burden'!AS213 -> 0.13083474
E47: Proportion of deaths from vaccine-preventable causes among unvaccinated people under age 5 that are addressable by the Hib vaccine, adjusted for deaths occurring before the age of vaccination | F47: ='Disease burden'!F214 -> % | G47: supp | H47: ='Disease burden'!H214 -> - | I47: ='Disease burden'!I214 -> 0.023983465 | J47: ='Disease burden'!J214 -> 0.028440354 | K47: ='Disease burden'!K214 -> 0.024674757 | L47: ='Disease burden'!L214 -> 0.03258536 | M47: ='Disease burden'!M214 -> 0.029289396 | N47: ='Disease burden'!N214 -> 0.023091221 | O47: ='Disease burden'!O214 -> 0.023153299 | ... Q47: ='Disease burden'!Q214 -> 0.0190194 | R47: ='Disease burden'!I214 -> 0.023983465 | S47: ='Disease burden'!S214 -> 0.033383469 | T47: ='Disease burden'!T214 -> 0.042036984 | U47: ='Disease burden'!U214 -> 0.045389923 | V47: ='Disease burden'!V214 -> 0.030613479 | W47: ='Disease burden'!W214 -> 0.032954001 | X47: ='Disease burden'!X214 -> 0.023713557 | Y47: ='Disease burden'!Y214 -> 0.041298614 | Z47: ='Disease burden'!Z214 -> 0.040532201 | ... AS47: ='Disease burden'!AS214 -> 0.023969685
E48: Proportion of deaths from vaccine-preventable causes among unvaccinated people under age 5 that are addressable by the PCV vaccine, adjusted for deaths occurring before the age of vaccination | F48: ='Disease burden'!F215 -> % | G48: supp | H48: ='Disease burden'!H215 -> - | I48: ='Disease burden'!I215 -> 0.36084218 | J48: ='Disease burden'!J215 -> 0.41200293 | K48: ='Disease burden'!K215 -> 0.36836551 | L48: ='Disease burden'!L215 -> 0.46020959 | M48: ='Disease burden'!M215 -> 0.43564783 | N48: ='Disease burden'!N215 -> 0.33946379 | O48: ='Disease burden'!O215 -> 0.33947298 | ... AS48: ='Disease burden'!AS215 -> 0.34621103
E49: Proportion of deaths from vaccine-preventable causes among unvaccinated people under age 5 that are addressable by the rotavirus vaccine, adjusted for deaths occurring before the age of vaccination | F49: ='Disease burden'!F216 -> % | G49: supp | H49: ='Disease burden'!H216 -> - | I49: ='Disease burden'!I216 -> 0.32281274 | J49: ='Disease burden'!J216 -> 0.30021382 | K49: ='Disease burden'!K216 -> 0.2655499 | L49: ='Disease burden'!L216 -> 0.2471178 | M49: ='Disease burden'!M216 -> 0.30736916 | N49: ='Disease burden'!N216 -> 0.30546838 | O49: ='Disease burden'!O216 -> 0.30352491 | ... AS49: ='Disease burden'!AS216 -> 0.28751089
E50: Proportion of deaths from vaccine-preventable causes among unvaccinated people under age 5 that are addressable by the measles vaccine, adjusted for deaths occurring before the age of vaccination | F50: ='Disease burden'!F217 -> % | G50: supp | H50: ='Disease burden'!H217 -> - | I50: ='Disease burden'!I217 -> 0.047525726 | J50: ='Disease burden'!J217 -> 0.036968421 | K50: ='Disease burden'!K217 -> 0.054089955 | L50: ='Disease burden'!L217 -> 0.042975561 | M50: ='Disease burden'!M217 -> 0.027196356 | N50: ='Disease burden'!N217 -> 0.06576619 | O50: ='Disease burden'!O217 -> 0.061984113 | ... AS50: ='Disease burden'!AS217 -> 0.065000181
C52: Vaccine efficacy for people under age 5, aggregated across vaccines
E53: Proportion of vaccine-preventable disease incidence averted by full vaccination among people under age 5, aggregated across vaccines | F53: % | G53: calc | H53: - | I53: =SUMPRODUCT($H$37:$H$42,I45:I50) -> 0.52870848 | J53: =SUMPRODUCT($H$37:$H$42,J45:J50) -> 0.52476274 | K53: =SUMPRODUCT($H$37:$H$42,K45:K50) -> 0.54543544 | L53: =SUMPRODUCT($H$37:$H$42,L45:L50) -> 0.53079041 | M53: =SUMPRODUCT($H$37:$H$42,M45:M50) -> 0.51766922 | N53: =SUMPRODUCT($H$37:$H$42,N45:N50) -> 0.53814058 | O53: =SUMPRODUCT($H$37:$H$42,O45:O50) -> 0.53885814 | P53: =SUMPRODUCT($H$37:$H$42,P45:P50) -> 0.53110942 | ... AS53: =SUMPRODUCT($H$37:$H$42,AS45:AS50) -> 0.54241469
C55: Vaccine coverage for populations under age 5 represented by GBD 2021, aggregated across doses
E56: Proportion of people under age 5 represented in GBD 2021 disease burden estimates who received the BCG vaccine | F56: ='Vaccine coverage'!F146 -> % | G56: supp | H56: ='Vaccine coverage'!H146 -> - | I56: ='Vaccine coverage'!I146 -> 0.4523656 | J56: ='Vaccine coverage'!J146 -> 0.56810494 | K56: ='Vaccine coverage'!K146 -> 0.4462528 | L56: ='Vaccine coverage'!L146 -> 0.64868965 | M56: ='Vaccine coverage'!M146 -> 0.47083923 | N56: ='Vaccine coverage'!N146 -> 0.42774821 | O56: ='Vaccine coverage'!O146 -> 0.43171371 | ... AS56: ='Vaccine coverage'!AS146 -> 0.45820585
E57: Proportion of people under age 5 represented in GBD 2021 disease burden estimates who received the DTP vaccine, aggregated across doses | F57: ='Vaccine coverage'!F147 -> % | G57: supp | H57: ='Vaccine coverage'!H147 -> - | I57: ='Vaccine coverage'!I147 -> 0.33402331 | J57: ='Vaccine coverage'!J147 -> 0.42618415 | K57: ='Vaccine coverage'!K147 -> 0.34991428 | L57: ='Vaccine coverage'!L147 -> 0.52159655 | M57: ='Vaccine coverage'!M147 -> 0.36139889 | N57: ='Vaccine coverage'!N147 -> 0.34781976 | O57: ='Vaccine coverage'!O147 -> 0.37981112 | ... AS57: ='Vaccine coverage'!AS147 -> 0.42374023
E58: Proportion of people under age 5 represented in GBD 2021 disease burden estimates who received the Hib vaccine, aggregated across doses | F58: ='Vaccine coverage'!F148 -> % | G58: supp | H58: ='Vaccine coverage'!H148 -> - | I58: ='Vaccine coverage'!I148 -> 0.33402331 | J58: ='Vaccine coverage'!J148 -> 0.42618415 | K58: ='Vaccine coverage'!K148 -> 0.34991428 | L58: ='Vaccine coverage'!L148 -> 0.52159655 | M58: ='Vaccine coverage'!M148 -> 0.36139889 | N58: ='Vaccine coverage'!N148 -> 0.34781976 | O58: ='Vaccine coverage'!O148 -> 0.37981112 | ... AS58: ='Vaccine coverage'!AS148 -> 0.42374023
E59: Proportion of people under age 5 represented in GBD 2021 disease burden estimates who received the PCV vaccine, aggregated across doses | F59: ='Vaccine coverage'!F149 -> % | G59: supp | H59: ='Vaccine coverage'!H149 -> - | I59: ='Vaccine coverage'!I149 -> 0.33434375 | J59: ='Vaccine coverage'!J149 -> 0.42273382 | K59: ='Vaccine coverage'!K149 -> 0.35192353 | L59: ='Vaccine coverage'!L149 -> 0.53432023 | M59: ='Vaccine coverage'!M149 -> 0.3647019 | N59: ='Vaccine coverage'!N149 -> 0.33320325 | O59: ='Vaccine coverage'!O149 -> 0.37980211 | ... AS59: ='Vaccine coverage'!AS149 -> 0.41126029
E60: Proportion of people under age 5 represented in GBD 2021 disease burden estimates who received the rotavirus vaccine, aggregated across doses | F60: ='Vaccine coverage'!F150 -> % | G60: supp | H60: ='Vaccine coverage'!H150 -> - | I60: ='Vaccine coverage'!I150 -> 0 | J60: ='Vaccine coverage'!J150 -> 0 | K60: ='Vaccine coverage'!K150 -> 0 | L60: ='Vaccine coverage'!L150 -> 0 | M60: ='Vaccine coverage'!M150 -> 0 | N60: ='Vaccine coverage'!N150 -> 0 | O60: ='Vaccine coverage'!O150 -> 0 | ... AS60: ='Vaccine coverage'!AS150 -> 0
E61: Proportion of people under age 5 represented in GBD 2021 disease burden estimates who received the measles vaccine | F61: ='Vaccine coverage'!F151 -> % | G61: supp | H61: ='Vaccine coverage'!H151 -> - | I61: ='Vaccine coverage'!I151 -> 0.26549471 | J61: ='Vaccine coverage'!J151 -> 0.34616826 | K61: ='Vaccine coverage'!K151 -> 0.33200195 | L61: ='Vaccine coverage'!L151 -> 0.49994028 | M61: ='Vaccine coverage'!M151 -> 0.32358308 | N61: ='Vaccine coverage'!N151 -> 0.32456419 | O61: ='Vaccine coverage'!O151 -> 0.44424952 | ... AS61: ='Vaccine coverage'!AS151 -> 0.43065924
C63: Vaccine coverage for populations under age 5 represented by GBD 2021, aggregated across vaccines
E64: Proportion of people under age 5 represented in GBD 2021 disease burden estimates who were vaccinated, aggregated across vaccines | F64: % | G64: calc | H64: - | I64: =SUMPRODUCT($H37:$H42,I45:I50,I56:I61)/I53 -> 0.27548418 | J64: =SUMPRODUCT($H37:$H42,J45:J50,J56:J61)/J53 -> 0.34752396 | K64: =SUMPRODUCT($H37:$H42,K45:K50,K56:K61)/K53 -> 0.30600516 | L64: =SUMPRODUCT($H37:$H42,L45:L50,L56:L61)/L53 -> 0.4480187 | M64: =SUMPRODUCT($H37:$H42,M45:M50,M56:M61)/M53 -> 0.29422974 | N64: =SUMPRODUCT($H37:$H42,N45:N50,N56:N61)/N53 -> 0.2806275 | O64: =SUMPRODUCT($H37:$H42,O45:O50,O56:O61)/O53 -> 0.31099173 | P64: =SUMPRODUCT($H37:$H42,P45:P50,P56:P61)/P53 -> 0.12038231 | ... AS64: =SUMPRODUCT($H37:$H42,AS45:AS50,AS56:AS61)/AS53 -> 0.33924752
A66: Vaccine efficacy and coverage for older age groups, aggregated across vaccines
C68: Effect of vaccination on disease incidence among 5-14-year-olds
E69: Proportion of vaccine-preventable disease incidence averted by BCG vaccination among 5-14-year-olds | F69: ='Disease burden'!F241 -> % | G69: supp | H69: ='Disease burden'!H241 -> 0.65040642 | I69: ='Disease burden'!I241 -> - | J69: ='Disease burden'!J241 -> - | K69: ='Disease burden'!K241 -> - | L69: ='Disease burden'!L241 -> - | M69: ='Disease burden'!M241 -> - | N69: ='Disease burden'!N241 -> - | O69: ='Disease burden'!O241 -> - | ... AS69: ='Disease burden'!AS241 -> -
E70: Proportion of vaccine-preventable disease incidence averted by DTP vaccination among 5-14-year-olds | F70: ='Disease burden'!F242 -> % | G70: supp | H70: ='Disease burden'!H242 -> 0.64275458 | I70: ='Disease burden'!I242 -> - | J70: ='Disease burden'!J242 -> - | K70: ='Disease burden'!K242 -> - | L70: ='Disease burden'!L242 -> - | M70: ='Disease burden'!M242 -> - | N70: ='Disease burden'!N242 -> - | O70: ='Disease burden'!O242 -> - | ... AS70: ='Disease burden'!AS242 -> - | AT70: ='Vaccine efficacy'!AT90
E71: Proportion of vaccine-preventable disease incidence averted by Hib vaccination among 5-14-year-olds | F71: ='Disease burden'!F243 -> % | G71: supp | H71: ='Disease burden'!H243 -> 0.6274509 | I71: ='Disease burden'!I243 -> - | J71: ='Disease burden'!J243 -> - | K71: ='Disease burden'!K243 -> - | L71: ='Disease burden'!L243 -> - | M71: ='Disease burden'!M243 -> - | N71: ='Disease burden'!N243 -> - | O71: ='Disease burden'!O243 -> - | ... AS71: ='Disease burden'!AS243 -> - | AT71: ='Vaccine efficacy'!AT91
E72: Proportion of vaccine-preventable disease incidence averted by PCV vaccination among 5-14-year-olds | F72: ='Disease burden'!F244 -> % | G72: supp | H72: ='Disease burden'!H244 -> 0.44380673 | I72: ='Disease burden'!I244 -> - | J72: ='Disease burden'!J244 -> - | K72: ='Disease burden'!K244 -> - | L72: ='Disease burden'!L244 -> - | M72: ='Disease burden'!M244 -> - | N72: ='Disease burden'!N244 -> - | O72: ='Disease burden'!O244 -> - | ... AS72: ='Disease burden'!AS244 -> - | AT72: ='Vaccine efficacy'!AT92
E73: Proportion of vaccine-preventable disease incidence averted by rotavirus vaccination among 5-14-year-olds | F73: ='Disease burden'!F245 -> % | G73: supp | H73: ='Disease burden'!H245 -> 0.35198465 | I73: ='Disease burden'!I245 -> - | J73: ='Disease burden'!J245 -> - | K73: ='Disease burden'!K245 -> - | L73: ='Disease burden'!L245 -> - | M73: ='Disease burden'!M245 -> - | N73: ='Disease burden'!N245 -> - | O73: ='Disease burden'!O245 -> - | ... AS73: ='Disease burden'!AS245 -> - | AT73: ='Vaccine efficacy'!AT93
E74: Proportion of vaccine-preventable disease incidence averted by measles vaccination among 5-14-year-olds | F74: ='Disease burden'!F246 -> % | G74: supp | H74: ='Disease burden'!H246 -> 0.59878751 | I74: ='Disease burden'!I246 -> - | J74: ='Disease burden'!J246 -> - | K74: ='Disease burden'!K246 -> - | L74: ='Disease burden'!L246 -> - | M74: ='Disease burden'!M246 -> - | N74: ='Disease burden'!N246 -> - | O74: ='Disease burden'!O246 -> - | ... AS74: ='Disease burden'!AS246 -> - | AT74: ='Vaccine efficacy'!AT94
C76: Proportion of deaths from vaccine-preventable causes among unvaccinated 5-14-year-olds that are addressable by each vaccine
E77: Proportion of deaths from vaccine-preventable causes among unvaccinated 5-14-year-olds that are addressable by the BCG vaccine | F77: ='Disease burden'!F258 -> % | G77: supp | H77: ='Disease burden'!H258 -> - | I77: ='Disease burden'!I258 -> 0.21559519 | J77: ='Disease burden'!J258 -> 0.15333373 | K77: ='Disease burden'!K258 -> 0.23865108 | L77: ='Disease burden'!L258 -> 0.12640196 | M77: ='Disease burden'!M258 -> 0.16503159 | N77: ='Disease burden'!N258 -> 0.20326965 | O77: ='Disease burden'!O258 -> 0.196602 | ... AS77: ='Disease burden'!AS258 -> 0.2164136
E78: Proportion of deaths from vaccine-preventable causes among unvaccinated 5-14-year-olds that are addressable by the DTP vaccine | F78: ='Disease burden'!F259 -> % | G78: supp | H78: ='Disease burden'!H259 -> - | I78: ='Disease burden'!I259 -> 0.12807675 | J78: ='Disease burden'!J259 -> 0.16245783 | K78: ='Disease burden'!K259 -> 0.15297105 | L78: ='Disease burden'!L259 -> 0.18672972 | M78: ='Disease burden'!M259 -> 0.13558359 | N78: ='Disease burden'!N259 -> 0.15446457 | O78: ='Disease burden'!O259 -> 0.18740379 | ... AS78: ='Disease burden'!AS259 -> 0.14329981
E79: Proportion of deaths from vaccine-preventable causes among unvaccinated 5-14-year-olds that are addressable by the Hib vaccine | F79: ='Disease burden'!F260 -> % | G79: supp | H79: ='Disease burden'!H260 -> - | I79: ='Disease burden'!I260 -> 0.022918275 | J79: ='Disease burden'!J260 -> 0.028391782 | K79: ='Disease burden'!K260 -> 0.023847608 | L79: ='Disease burden'!L260 -> 0.031873165 | M79: ='Disease burden'!M260 -> 0.032514512 | N79: ='Disease burden'!N260 -> 0.022912414 | O79: ='Disease burden'!O260 -> 0.022110475 | ... AS79: ='Disease burden'!AS260 -> 0.02333132
E80: Proportion of deaths from vaccine-preventable causes among unvaccinated 5-14-year-olds that are addressable by the PCV vaccine | F80: ='Disease burden'!F261 -> % | G80: supp | H80: ='Disease burden'!H261 -> - | I80: ='Disease burden'!I261 -> 0.33681086 | J80: ='Disease burden'!J261 -> 0.41381898 | K80: ='Disease burden'!K261 -> 0.3494857 | L80: ='Disease burden'!L261 -> 0.46470174 | M80: ='Disease burden'!M261 -> 0.4817172 | N80: ='Disease burden'!N261 -> 0.33508609 | O80: ='Disease burden'!O261 -> 0.31969684 | ... AS80: ='Disease burden'!AS261 -> 0.33695124
E81: Proportion of deaths from vaccine-preventable causes among unvaccinated 5-14-year-olds that are addressable by the rotavirus vaccine | F81: ='Disease burden'!F262 -> % | G81: supp | H81: ='Disease burden'!H262 -> - | I81: ='Disease burden'!I262 -> 0.19935566 | J81: ='Disease burden'!J262 -> 0.16776941 | K81: ='Disease burden'!K262 -> 0.12524397 | L81: ='Disease burden'!L262 -> 0.098626696 | M81: ='Disease burden'!M262 -> 0.12936984 | N81: ='Disease burden'!N262 -> 0.16220046 | O81: ='Disease burden'!O262 -> 0.16663836 | ... AS81: ='Disease burden'!AS262 -> 0.18633142
E82: Proportion of deaths from vaccine-preventable causes among unvaccinated 5-14-year-olds that are addressable by the measles vaccine | F82: ='Disease burden'!F263 -> % | G82: supp | H82: ='Disease burden'!H263 -> - | I82: ='Disease burden'!I263 -> 0.097243259 | J82: ='Disease burden'!J263 -> 0.074228262 | K82: ='Disease burden'!K263 -> 0.10980059 | L82: ='Disease burden'!L263 -> 0.091666717 | M82: ='Disease burden'!M263 -> 0.055783264 | N82: ='Disease burden'!N263 -> 0.12206683 | O82: ='Disease burden'!O263 -> 0.10754853 | ... AS82: ='Disease burden'!AS263 -> 0.093672618
C84: Vaccine efficacy, aggregated across vaccines
E85: Proportion of vaccine-preventable disease incidence averted by full vaccination among 5-14-year-olds, aggregated across vaccines | F85: % | G85: calc | H85: - | I85: =SUMPRODUCT($H69:$H74,I77:I82) -> 0.51480362 | J85: =SUMPRODUCT($H69:$H74,J77:J82) -> 0.50911907 | K85: =SUMPRODUCT($H69:$H74,K77:K82) -> 0.53344153 | L85: =SUMPRODUCT($H69:$H74,L77:L82) -> 0.51807461 | M85: =SUMPRODUCT($H69:$H74,M77:M82) -> 0.5076137 | N85: =SUMPRODUCT($H69:$H74,N77:N82) -> 0.52476473 | O85: =SUMPRODUCT($H69:$H74,O77:O82) -> 0.52713556 | P85: =SUMPRODUCT($H69:$H74,P77:P82) -> 0.52816284 | ... AS85: =SUMPRODUCT($H69:$H74,AS77:AS82) -> 0.51871968
C87: Vaccine coverage for 5-14-year-old populations represented by GBD 2021, aggregated across doses
E88: Adjustment for lower vaccine coverage among 5-14-year-olds represented in GBD 2021 disease burden estimates | F88: =Inputs!F182 -> % | G88: =Inputs!G182 -> input | H88: =Inputs!H182 -> -0.5 | I88: =Inputs!I182 -> - | J88: =Inputs!J182 -> - | K88: =Inputs!K182 -> - | L88: =Inputs!L182 -> - | M88: =Inputs!M182 -> - | ... AS88: =Inputs!AS182 -> -
E89: Proportion of 5-14-year-olds represented in GBD 2021 disease burden estimates who received the BCG vaccine | F89: % | G89: calc | H89: - | I89: =I56*(1+$H$88) -> 0.2261828 | J89: =J56*(1+$H$88) -> 0.28405247 | K89: =K56*(1+$H$88) -> 0.2231264 | L89: =L56*(1+$H$88) -> 0.32434482 | M89: =M56*(1+$H$88) -> 0.23541962 | N89: =N56*(1+$H$88) -> 0.2138741 | O89: =O56*(1+$H$88) -> 0.21585686 | P89: =P56*(1+$H$88) -> 0.12521773 | ... AS89: =AS56*(1+$H$88) -> 0.22910292
E90: Proportion of 5-14-year-olds represented in GBD 2021 disease burden estimates who received the DTP vaccine, aggregated across doses | F90: % | G90: calc | H90: - | I90: =I57*(1+$H$88) -> 0.16701166 | J90: =J57*(1+$H$88) -> 0.21309207 | K90: =K57*(1+$H$88) -> 0.17495714 | L90: =L57*(1+$H$88) -> 0.26079828 | M90: =M57*(1+$H$88) -> 0.18069944 | N90: =N57*(1+$H$88) -> 0.17390988 | O90: =O57*(1+$H$88) -> 0.18990556 | P90: =P57*(1+$H$88) -> 0.0695872 | ... AS90: =AS57*(1+$H$88) -> 0.21187011
E91: Proportion of 5-14-year-olds represented in GBD 2021 disease burden estimates who received the Hib vaccine, aggregated across doses | F91: % | G91: calc | H91: - | I91: =I58*(1+$H$88) -> 0.16701166 | J91: =J58*(1+$H$88) -> 0.21309207 | K91: =K58*(1+$H$88) -> 0.17495714 | L91: =L58*(1+$H$88) -> 0.26079828 | M91: =M58*(1+$H$88) -> 0.18069944 | N91: =N58*(1+$H$88) -> 0.17390988 | O91: =O58*(1+$H$88) -> 0.18990556 | P91: =P58*(1+$H$88) -> 0.0695872 | ... AS91: =AS58*(1+$H$88) -> 0.21187011
E92: Proportion of 5-14-year-olds represented in GBD 2021 disease burden estimates who received the PCV vaccine, aggregated across doses | F92: % | G92: calc | H92: - | I92: =I59*(1+$H$88) -> 0.16717187 | J92: =J59*(1+$H$88) -> 0.21136691 | K92: =K59*(1+$H$88) -> 0.17596177 | L92: =L59*(1+$H$88) -> 0.26716011 | M92: =M59*(1+$H$88) -> 0.18235095 | N92: =N59*(1+$H$88) -> 0.16660162 | O92: =O59*(1+$H$88) -> 0.18990106 | P92: =P59*(1+$H$88) -> 0.056466279 | ... AS92: =AS59*(1+$H$88) -> 0.20563014
E93: Proportion of 5-14-year-olds represented in GBD 2021 disease burden estimates who received the rotavirus vaccine, aggregated across doses | F93: % | G93: calc | H93: - | I93: =I60*(1+$H$88) -> 0 | J93: =J60*(1+$H$88) -> 0 | K93: =K60*(1+$H$88) -> 0 | L93: =L60*(1+$H$88) -> 0 | M93: =M60*(1+$H$88) -> 0 | N93: =N60*(1+$H$88) -> 0 | O93: =O60*(1+$H$88) -> 0 | P93: =P60*(1+$H$88) -> 0 | ... AS93: =AS60*(1+$H$88) -> 0
E94: Proportion of 5-14-year-olds represented in GBD 2021 disease burden estimates who received the measles vaccine | F94: % | G94: calc | H94: - | I94: =I61*(1+$H$88) -> 0.13274736 | J94: =J61*(1+$H$88) -> 0.17308413 | K94: =K61*(1+$H$88) -> 0.16600098 | L94: =L61*(1+$H$88) -> 0.24997014 | M94: =M61*(1+$H$88) -> 0.16179154 | N94: =N61*(1+$H$88) -> 0.1622821 | O94: =O61*(1+$H$88) -> 0.22212476 | P94: =P61*(1+$H$88) -> 0.072377122 | ... AS94: =AS61*(1+$H$88) -> 0.21532962
C96: Vaccine coverage for 5-14-year-old populations represented by GBD 2021, aggregated across vaccines
E97: Proportion of 5-14-year-olds represented in GBD 2021 disease burden estimates who were vaccinated, aggregated across vaccines | F97: % | G97: calc | H97: - | I97: =SUMPRODUCT($H69:$H74,I77:I82,I89:I94)/I85 -> 0.15653547 | J97: =SUMPRODUCT($H69:$H74,J77:J82,J89:J94)/J85 -> 0.19816078 | K97: =SUMPRODUCT($H69:$H74,K77:K82,K89:K94)/K85 -> 0.17370305 | L97: =SUMPRODUCT($H69:$H74,L77:L82,L89:L94)/L85 -> 0.2547922 | M97: =SUMPRODUCT($H69:$H74,M77:M82,M89:M94)/M85 -> 0.17551178 | N97: =SUMPRODUCT($H69:$H74,N77:N82,N89:N94)/N85 -> 0.16136707 | O97: =SUMPRODUCT($H69:$H74,O77:O82,O89:O94)/O85 -> 0.17900497 | P97: =SUMPRODUCT($H69:$H74,P77:P82,P89:P94)/P85 -> 0.07352943 | ... AS97: =SUMPRODUCT($H69:$H74,AS77:AS82,AS89:AS94)/AS85 -> 0.18833308
C99: Effect of vaccination on disease incidence among 15-49-year-olds
E100: Proportion of vaccine-preventable disease incidence averted by BCG vaccination among 15-49-year-olds | F100: ='Disease burden'!F285 -> % | G100: supp | H100: ='Disease burden'!H285 -> 0.43360428 | I100: ='Disease burden'!I285 -> - | J100: ='Disease burden'!J285 -> - | K100: ='Disease burden'!K285 -> - | L100: ='Disease burden'!L285 -> - | M100: ='Disease burden'!M285 -> - | N100: ='Disease burden'!N285 -> - | O100: ='Disease burden'!O285 -> - | ... AS100: ='Disease burden'!AS285 -> -
E101: Proportion of vaccine-preventable disease incidence averted by DTP vaccination among 15-49-year-olds | F101: ='Disease burden'!F286 -> % | G101: supp | H101: ='Disease burden'!H286 -> 0.42850305 | I101: ='Disease burden'!I286 -> - | J101: ='Disease burden'!J286 -> - | K101: ='Disease burden'!K286 -> - | L101: ='Disease burden'!L286 -> - | M101: ='Disease burden'!M286 -> - | N101: ='Disease burden'!N286 -> - | O101: ='Disease burden'!O286 -> - | ... AS101: ='Disease burden'!AS286 -> -
E102: Proportion of vaccine-preventable disease incidence averted by Hib vaccination among 15-49-year-olds | F102: ='Disease burden'!F287 -> % | G102: supp | H102: ='Disease burden'!H287 -> 0.4183006 | I102: ='Disease burden'!I287 -> - | J102: ='Disease burden'!J287 -> - | K102: ='Disease burden'!K287 -> - | L102: ='Disease burden'!L287 -> - | M102: ='Disease burden'!M287 -> - | N102: ='Disease burden'!N287 -> - | O102: ='Disease burden'!O287 -> - | ... AS102: ='Disease burden'!AS287 -> -
E103: Proportion of vaccine-preventable disease incidence averted by PCV vaccination among 15-49-year-olds | F103: ='Disease burden'!F288 -> % | G103: supp | H103: ='Disease burden'!H288 -> 0.29587116 | I103: ='Disease burden'!I288 -> - | J103: ='Disease burden'!J288 -> - | K103: ='Disease burden'!K288 -> - | L103: ='Disease burden'!L288 -> - | M103: ='Disease burden'!M288 -> - | N103: ='Disease burden'!N288 -> - | O103: ='Disease burden'!O288 -> - | ... AS103: ='Disease burden'!AS288 -> -
E104: Proportion of vaccine-preventable disease incidence averted by rotavirus vaccination among 15-49-year-olds | F104: ='Disease burden'!F289 -> % | G104: supp | H104: ='Disease burden'!H289 -> 0.23465643 | I104: ='Disease burden'!I289 -> - | J104: ='Disease burden'!J289 -> - | K104: ='Disease burden'!K289 -> - | L104: ='Disease burden'!L289 -> - | M104: ='Disease burden'!M289 -> - | N104: ='Disease burden'!N289 -> - | O104: ='Disease burden'!O289 -> - | ... AS104: ='Disease burden'!AS289 -> -
E105: Proportion of vaccine-preventable disease incidence averted by measles vaccination among 15-49-year-olds | F105: ='Disease burden'!F290 -> % | G105: supp | H105: ='Disease burden'!H290 -> 0.39919167 | I105: ='Disease burden'!I290 -> - | J105: ='Disease burden'!J290 -> - | K105: ='Disease burden'!K290 -> - | L105: ='Disease burden'!L290 -> - | M105: ='Disease burden'!M290 -> - | N105: ='Disease burden'!N290 -> - | O105: ='Disease burden'!O290 -> - | ... AS105: ='Disease burden'!AS290 -> -
C107: Proportion of deaths from vaccine-preventable causes among unvaccinated 15-49-year-olds that are addressable by each vaccine
E108: Proportion of deaths from vaccine-preventable causes among unvaccinated 15-49-year-olds that are addressable by the BCG vaccine | F108: ='Disease burden'!F302 -> % | G108: supp | H108: ='Disease burden'!H302 -> - | I108: ='Disease burden'!I302 -> 0.642312 | J108: ='Disease burden'!J302 -> 0.60365051 | K108: ='Disease burden'!K302 -> 0.68354386 | L108: ='Disease burden'!L302 -> 0.58025396 | M108: ='Disease burden'!M302 -> 0.60830812 | N108: ='Disease burden'!N302 -> 0.65827248 | O108: ='Disease burden'!O302 -> 0.65803647 | ... AS108: ='Disease burden'!AS302 -> 0.64019477
E109: Proportion of deaths from vaccine-preventable causes among unvaccinated 15-49-year-olds that are addressable by the DTP vaccine | F109: ='Disease burden'!F303 -> % | G109: supp | H109: ='Disease burden'!H303 -> - | I109: ='Disease burden'!I303 -> 0.013745106 | J109: ='Disease burden'!J303 -> 0.019485151 | K109: ='Disease burden'!K303 -> 0.015691309 | L109: ='Disease burden'!L303 -> 0.020321002 | M109: ='Disease burden'!M303 -> 0.015151435 | N109: ='Disease burden'!N303 -> 0.014489239 | O109: ='Disease burden'!O303 -> 0.020271077 | ... AS109: ='Disease burden'!AS303 -> 0.015424745
E110: Proportion of deaths from vaccine-preventable causes among unvaccinated 15-49-year-olds that are addressable by the Hib vaccine | F110: ='Disease burden'!F304 -> % | G110: supp | H110: ='Disease burden'!H304 -> - | I110: ='Disease burden'!I304 -> 0.01056251 | J110: ='Disease burden'!J304 -> 0.013612421 | K110: ='Disease burden'!K304 -> 0.011308568 | L110: ='Disease burden'!L304 -> 0.017605915 | M110: ='Disease burden'!M304 -> 0.015124015 | N110: ='Disease burden'!N304 -> 0.010998798 | O110: ='Disease burden'!O304 -> 0.010629892 | ... AS110: ='Disease burden'!AS304 -> 0.011475025
E111: Proportion of deaths from vaccine-preventable causes among unvaccinated 15-49-year-olds that are addressable by the PCV vaccine | F111: ='Disease burden'!F305 -> % | G111: supp | H111: ='Disease burden'!H305 -> - | I111: ='Disease burden'!I305 -> 0.15884063 | J111: ='Disease burden'!J305 -> 0.20531333 | K111: ='Disease burden'!K305 -> 0.16889617 | L111: ='Disease burden'!L305 -> 0.26777039 | M111: ='Disease burden'!M305 -> 0.22929886 | N111: ='Disease burden'!N305 -> 0.16529325 | O111: ='Disease burden'!O305 -> 0.1585001 | ... AS111: ='Disease burden'!AS305 -> 0.17147311
E112: Proportion of deaths from vaccine-preventable causes among unvaccinated 15-49-year-olds that are addressable by the rotavirus vaccine | F112: ='Disease burden'!F306 -> % | G112: supp | H112: ='Disease burden'!H306 -> - | I112: ='Disease burden'!I306 -> 0.16985763 | J112: ='Disease burden'!J306 -> 0.1544041 | K112: ='Disease burden'!K306 -> 0.11455313 | L112: ='Disease burden'!L306 -> 0.10957553 | M112: ='Disease burden'!M306 -> 0.12913466 | N112: ='Disease burden'!N306 -> 0.1453367 | O112: ='Disease burden'!O306 -> 0.14800296 | ... AS112: ='Disease burden'!AS306 -> 0.15688631
E113: Proportion of deaths from vaccine-preventable causes among unvaccinated 15-49-year-olds that are addressable by the measles vaccine | F113: ='Disease burden'!F307 -> % | G113: supp | H113: ='Disease burden'!H307 -> - | I113: ='Disease burden'!I307 -> 0.0046821287 | J113: ='Disease burden'!J307 -> 0.0035344751 | K113: ='Disease burden'!K307 -> 0.0060069607 | L113: ='Disease burden'!L307 -> 0.0044732046 | M113: ='Disease burden'!M307 -> 0.0029829062 | N113: ='Disease burden'!N307 -> 0.0056095369 | O113: ='Disease burden'!O307 -> 0.0045594968 | ... AS113: ='Disease burden'!AS307 -> 0.0045460373
C115: Vaccine efficacy, aggregated across vaccines
E116: Proportion of vaccine-preventable disease incidence averted by full vaccination among 15-49-year-olds, aggregated across vaccines | F116: % | G116: calc | H116: - | I116: =SUMPRODUCT($H100:$H105,I108:I113) -> 0.37754097 | J116: =SUMPRODUCT($H100:$H105,J108:J113) -> 0.37417812 | K116: =SUMPRODUCT($H100:$H105,K108:K113) -> 0.38709176 | L116: =SUMPRODUCT($H100:$H105,L108:L113) -> 0.37439658 | M116: =SUMPRODUCT($H100:$H105,M108:M113) -> 0.37591977 | N116: =SUMPRODUCT($H100:$H105,N108:N113) -> 0.38148823 | O116: =SUMPRODUCT($H100:$H105,O108:O113) -> 0.38190571 | P116: =SUMPRODUCT($H100:$H105,P108:P113) -> 0.38342513 | ... AS116: =SUMPRODUCT($H100:$H105,AS108:AS113) -> 0.37836382
C118: Vaccine coverage for 15-49-year-old populations represented by GBD 2021, aggregated across doses
E119: Adjustment for lower vaccine coverage among 15-49-year-olds represented in GBD 2021 disease burden estimates | F119: =Inputs!F185 -> % | G119: =Inputs!G185 -> input | H119: =Inputs!H185 -> -0.8 | I119: =Inputs!I185 -> - | J119: =Inputs!J185 -> - | K119: =Inputs!K185 -> - | L119: =Inputs!L185 -> - | M119: =Inputs!M185 -> - | ... AS119: =Inputs!AS185 -> -
...

Sheet Treatment effect
I1: New Incentives – current states of operation | R1: New Incentives – prospective states | AF1: New Incentives – prospective states
I2: Nigeria | J2: Nigeria | K2: Nigeria | L2: Nigeria | M2: Nigeria | N2: Nigeria | O2: Nigeria | P2: Nigeria | Q2: Nigeria | R2: Nigeria | S2: Nigeria | T2: Nigeria | U2: Nigeria | V2: Nigeria | W2: Nigeria | X2: Nigeria | Y2: Nigeria | Z2: Nigeria | AA2: Nigeria | AB2: Nigeria | AC2: Nigeria | AD2: Nigeria | AE2: Nigeria | AF2: Nigeria | AG2: Nigeria | AH2: Nigeria | AI2: Nigeria | AJ2: Nigeria | AK2: Nigeria | AL2: Nigeria | AM2: Nigeria | AN2: Nigeria | AO2: Nigeria | AP2: Nigeria | AQ2: Nigeria | AR2: Nigeria | AS2: Nigeria
A3: Main calculations | F3: unit | G3: type | H3: Overall | I3: Bauchi | J3: Gombe | K3: Jigawa | L3: Kaduna | M3: Kano | N3: Katsina | O3: Kebbi | P3: Sokoto | Q3: Zamfara | R3: Abia | S3: Adamawa | T3: Akwa Ibom | U3: Anambra | V3: Bayelsa | W3: Benue | X3: Borno | Y3: Cross River | Z3: Delta | AA3: Ebonyi | AB3: Edo | AC3: Ekiti | AD3: Enugu | AE3: FCT | AF3: Imo | AG3: Kogi | AH3: Kwara | AI3: Lagos | AJ3: Nasarawa | AK3: Niger | AL3: Ogun | AM3: Ondo | AN3: Osun | AO3: Oyo | AP3: Plateau | AQ3: Rivers | AR3: Taraba | AS3: Yobe
E4: Final cost-effectiveness estimate (pulled from "Main calcs" sheet for visibility) | F4: ='Main CEA'!F241 -> xcash | G4: ='Main CEA'!G241 -> calc | H4: ='Main CEA'!H241 -> - | I4: ='Main CEA'!I241 -> 23.798889 | J4: ='Main CEA'!J241 -> 10.800641 | K4: ='Main CEA'!K241 -> 19.899944 | L4: ='Main CEA'!L241 -> 5.6568275 | M4: ='Main CEA'!M241 -> 13.129176 | ... AS4: ='Main CEA'!AS241 -> 6.7228331
A5: Vaccination coverage rates for the control group of the New Incentives RCT
C7: Vaccination coverage rates for the control group of the New Incentives RCT
E8: Proportion of children in the New Incentives RCT control group who reported receiving the BCG vaccine | F8: =Inputs!F195 -> % | G8: =Inputs!G195 -> input | H8: =Inputs!H195 -> 0.63 | I8: =Inputs!I195 -> - | J8: =Inputs!J195 -> - | K8: =Inputs!K195 -> - | L8: =Inputs!L195 -> - | M8: =Inputs!M195 -> - | ... AS8: =Inputs!AS195 -> -
E9: Proportion of children in the New Incentives RCT control group who reported receiving the 1st dose of the Penta vaccine | F9: =Inputs!F196 -> % | G9: =Inputs!G196 -> input | H9: =Inputs!H196 -> 0.5419 | I9: =Inputs!I196 -> - | J9: =Inputs!J196 -> - | K9: =Inputs!K196 -> - | L9: =Inputs!L196 -> - | M9: =Inputs!M196 -> - | ... AS9: =Inputs!AS196 -> -
E10: Proportion of children in the New Incentives RCT control group who reported receiving the 2nd dose of the Penta vaccine | F10: =Inputs!F197 -> % | G10: =Inputs!G197 -> input | H10: =Inputs!H197 -> 0.3961 | I10: =Inputs!I197 -> - | J10: =Inputs!J197 -> - | K10: =Inputs!K197 -> - | L10: =Inputs!L197 -> - | M10: =Inputs!M197 -> - | ... AS10: =Inputs!AS197 -> -
E11: Proportion of children in the New Incentives RCT control group who reported receiving the 3rd dose of the Penta vaccine | F11: =Inputs!F198 -> % | G11: =Inputs!G198 -> input | H11: =Inputs!H198 -> 0.2978 | I11: =Inputs!I198 -> - | J11: =Inputs!J198 -> - | K11: =Inputs!K198 -> - | L11: =Inputs!L198 -> - | M11: =Inputs!M198 -> - | ... AS11: =Inputs!AS198 -> -
E12: Proportion of children in the New Incentives RCT control group who reported receiving the 1st dose of the PCV vaccine | F12: =Inputs!F199 -> % | G12: =Inputs!G199 -> input | H12: =Inputs!H199 -> 0.4954 | I12: =Inputs!I199 -> - | J12: =Inputs!J199 -> - | K12: =Inputs!K199 -> - | L12: =Inputs!L199 -> - | M12: =Inputs!M199 -> - | ... AS12: =Inputs!AS199 -> -
E13: Proportion of children in the New Incentives RCT control group who reported receiving the 2nd dose of the PCV vaccine | F13: =Inputs!F200 -> % | G13: =Inputs!G200 -> input | H13: =Inputs!H200 -> 0.3554 | I13: =Inputs!I200 -> - | J13: =Inputs!J200 -> - | K13: =Inputs!K200 -> - | L13: =Inputs!L200 -> - | M13: =Inputs!M200 -> - | ... AS13: =Inputs!AS200 -> -
E14: Proportion of children in the New Incentives RCT control group who reported receiving the 3rd dose of the PCV vaccine | F14: =Inputs!F201 -> % | G14: =Inputs!G201 -> input | H14: =Inputs!H201 -> 0.266 | I14: =Inputs!I201 -> - | J14: =Inputs!J201 -> - | K14: =Inputs!K201 -> - | L14: =Inputs!L201 -> - | M14: =Inputs!M201 -> - | ... AS14: =Inputs!AS201 -> -
E15: Proportion of children in the New Incentives RCT control group who reported receiving the measles vaccine | F15: =Inputs!F202 -> % | G15: =Inputs!G202 -> input | H15: =Inputs!H202 -> 0.5894 | I15: =Inputs!I202 -> - | J15: =Inputs!J202 -> - | K15: =Inputs!K202 -> - | L15: =Inputs!L202 -> - | M15: =Inputs!M202 -> - | ... AS15: =Inputs!AS202 -> -
C17: Adjustment for self-report bias
E18: Adjustment for self-report bias in the New Incentives RCT | F18: =Inputs!F205 -> % | G18: =Inputs!G205 -> input | H18: =Inputs!H205 -> -0.2768959 | I18: =Inputs!I205 -> - | J18: =Inputs!J205 -> - | K18: =Inputs!K205 -> - | L18: =Inputs!L205 -> - | M18: =Inputs!M205 -> - | ... AS18: =Inputs!AS205 -> -
C20: Vaccination coverage rates for the control group of the New Incentives RCT, adjusted for self-report bias
E21: Proportion of children in the New Incentives RCT control group who received the BCG vaccine | F21: % | G21: calc | H21: =H8*(1+H$18) -> 0.45555558 | I21: - | J21: - | K21: - | L21: - | M21: - | N21: - | O21: - | P21: - | Q21: - | R21: - | S21: - | T21: - | U21: - | V21: - | W21: - | X21: - | Y21: - | Z21: - | AA21: - | AB21: - | AC21: - | AD21: - | AE21: - | AF21: - | AG21: - | AH21: - | AI21: - | AJ21: - | AK21: - | AL21: - | AM21: - | AN21: - | AO21: - | AP21: - | AQ21: - | AR21: - | AS21: -
E22: Proportion of children in the New Incentives RCT control group who received the 1st dose of the Penta vaccine | F22: % | G22: calc | H22: =H9*(1+H$18) -> 0.39185011 | I22: - | J22: - | K22: - | L22: - | M22: - | N22: - | O22: - | P22: - | Q22: - | R22: - | S22: - | T22: - | U22: - | V22: - | W22: - | X22: - | Y22: - | Z22: - | AA22: - | AB22: - | AC22: - | AD22: - | AE22: - | AF22: - | AG22: - | AH22: - | AI22: - | AJ22: - | AK22: - | AL22: - | AM22: - | AN22: - | AO22: - | AP22: - | AQ22: - | AR22: - | AS22: -
E23: Proportion of children in the New Incentives RCT control group who received the 2nd dose of the Penta vaccine | F23: % | G23: calc | H23: =H10*(1+H$18) -> 0.28642153 | I23: - | J23: - | K23: - | L23: - | M23: - | N23: - | O23: - | P23: - | Q23: - | R23: - | S23: - | T23: - | U23: - | V23: - | W23: - | X23: - | Y23: - | Z23: - | AA23: - | AB23: - | AC23: - | AD23: - | AE23: - | AF23: - | AG23: - | AH23: - | AI23: - | AJ23: - | AK23: - | AL23: - | AM23: - | AN23: - | AO23: - | AP23: - | AQ23: - | AR23: - | AS23: -
E24: Proportion of children in the New Incentives RCT control group who received the 3rd dose of the Penta vaccine | F24: % | G24: calc | H24: =H11*(1+H$18) -> 0.2153404 | I24: - | J24: - | K24: - | L24: - | M24: - | N24: - | O24: - | P24: - | Q24: - | R24: - | S24: - | T24: - | U24: - | V24: - | W24: - | X24: - | Y24: - | Z24: - | AA24: - | AB24: - | AC24: - | AD24: - | AE24: - | AF24: - | AG24: - | AH24: - | AI24: - | AJ24: - | AK24: - | AL24: - | AM24: - | AN24: - | AO24: - | AP24: - | AQ24: - | AR24: - | AS24: -
E25: Proportion of children in the New Incentives RCT control group who received the 1st dose of the PCV vaccine | F25: % | G25: calc | H25: =H12*(1+H$18) -> 0.35822577 | I25: - | J25: - | K25: - | L25: - | M25: - | N25: - | O25: - | P25: - | Q25: - | R25: - | S25: - | T25: - | U25: - | V25: - | W25: - | X25: - | Y25: - | Z25: - | AA25: - | AB25: - | AC25: - | AD25: - | AE25: - | AF25: - | AG25: - | AH25: - | AI25: - | AJ25: - | AK25: - | AL25: - | AM25: - | AN25: - | AO25: - | AP25: - | AQ25: - | AR25: - | AS25: -
E26: Proportion of children in the New Incentives RCT control group who received the 2nd dose of the PCV vaccine | F26: % | G26: calc | H26: =H13*(1+H$18) -> 0.2569912 | I26: - | J26: - | K26: - | L26: - | M26: - | N26: - | O26: - | P26: - | Q26: - | R26: - | S26: - | T26: - | U26: - | V26: - | W26: - | X26: - | Y26: - | Z26: - | AA26: - | AB26: - | AC26: - | AD26: - | AE26: - | AF26: - | AG26: - | AH26: - | AI26: - | AJ26: - | AK26: - | AL26: - | AM26: - | AN26: - | AO26: - | AP26: - | AQ26: - | AR26: - | AS26: -
E27: Proportion of children in the New Incentives RCT control group who received the 3rd dose of the PCV vaccine | F27: % | G27: calc | H27: =H14*(1+H$18) -> 0.19234569 | I27: - | J27: - | K27: - | L27: - | M27: - | N27: - | O27: - | P27: - | Q27: - | R27: - | S27: - | T27: - | U27: - | V27: - | W27: - | X27: - | Y27: - | Z27: - | AA27: - | AB27: - | AC27: - | AD27: - | AE27: - | AF27: - | AG27: - | AH27: - | AI27: - | AJ27: - | AK27: - | AL27: - | AM27: - | AN27: - | AO27: - | AP27: - | AQ27: - | AR27: - | AS27: -
E28: Proportion of children in the New Incentives RCT control group who received the measles vaccine | F28: % | G28: calc | H28: =H15*(1+H$18) -> 0.42619756 | I28: - | J28: - | K28: - | L28: - | M28: - | N28: - | O28: - | P28: - | Q28: - | R28: - | S28: - | T28: - | U28: - | V28: - | W28: - | X28: - | Y28: - | Z28: - | AA28: - | AB28: - | AC28: - | AD28: - | AE28: - | AF28: - | AG28: - | AH28: - | AI28: - | AJ28: - | AK28: - | AL28: - | AM28: - | AN28: - | AO28: - | AP28: - | AQ28: - | AR28: - | AS28: -
C30: Proportion of vaccine-preventable mortalities that could be prevented by each vaccine dose
E31: Proportion of vaccine-preventable mortalities among people under age 5 that could be prevented by the BCG vaccine | F31: ='Disease burden'!F384 -> % | G31: supp | H31: ='Disease burden'!H384 -> - | I31: ='Disease burden'!I384 -> 0.2130494 | J31: ='Disease burden'!J384 -> 0.15347722 | K31: ='Disease burden'!K384 -> 0.24112748 | L31: ='Disease burden'!L384 -> 0.13471259 | M31: ='Disease burden'!M384 -> 0.15263081 | N31: ='Disease burden'!N384 -> 0.20594728 | O31: ='Disease burden'!O384 -> 0.19115989 | ... AS31: ='Disease burden'!AS384 -> 0.19515058
E32: Proportion of vaccine-preventable mortalities among people under age 5 that could be prevented by the 1st dose of the Penta vaccine | F32: ='Disease burden'!F385 -> % | G32: supp | H32: ='Disease burden'!H385 -> - | I32: ='Disease burden'!I385 -> 0.053131051 | J32: ='Disease burden'!J385 -> 0.06606296 | K32: ='Disease burden'!K385 -> 0.059308756 | L32: ='Disease burden'!L385 -> 0.070627408 | M32: ='Disease burden'!M385 -> 0.057825023 | N32: ='Disease burden'!N385 -> 0.062888388 | O32: ='Disease burden'!O385 -> 0.070475442 | ... AS32: ='Disease burden'!AS385 -> 0.071075284
E33: Proportion of vaccine-preventable mortalities among people under age 5 that could be prevented by the 2nd dose of the Penta vaccine | F33: ='Disease burden'!F386 -> % | G33: supp | H33: ='Disease burden'!H386 -> - | I33: ='Disease burden'!I386 -> 0.083491652 | J33: ='Disease burden'!J386 -> 0.10381322 | K33: ='Disease burden'!K386 -> 0.093199474 | L33: ='Disease burden'!L386 -> 0.11098593 | M33: ='Disease burden'!M386 -> 0.090867893 | N33: ='Disease burden'!N386 -> 0.098824609 | O33: ='Disease burden'!O386 -> 0.11074712 | ... AS33: ='Disease burden'!AS386 -> 0.11168973
E34: Proportion of vaccine-preventable mortalities among people under age 5 that could be prevented by the 3rd dose of the Penta vaccine | F34: ='Disease burden'!F387 -> % | G34: supp | H34: ='Disease burden'!H387 -> - | I34: ='Disease burden'!I387 -> 0.0151803 | J34: ='Disease burden'!J387 -> 0.018875132 | K34: ='Disease burden'!K387 -> 0.016945359 | L34: ='Disease burden'!L387 -> 0.020179259 | M34: ='Disease burden'!M387 -> 0.016521435 | N34: ='Disease burden'!N387 -> 0.017968111 | O34: ='Disease burden'!O387 -> 0.02013584 | ... AS34: ='Disease burden'!AS387 -> 0.020307224
E35: Proportion of vaccine-preventable mortalities among people under age 5 that could be prevented by the 1st dose of the PCV vaccine | F35: ='Disease burden'!F388 -> % | G35: supp | H35: ='Disease burden'!H388 -> - | I35: ='Disease burden'!I388 -> 0.11779326 | J35: ='Disease burden'!J388 -> 0.13550544 | K35: ='Disease burden'!K388 -> 0.11656148 | L35: ='Disease burden'!L388 -> 0.14964149 | M35: ='Disease burden'!M388 -> 0.14524548 | N35: ='Disease burden'!N388 -> 0.10887223 | O35: ='Disease burden'!O388 -> 0.1087302 | ... AS35: ='Disease burden'!AS388 -> 0.11016126
E36: Proportion of vaccine-preventable mortalities among people under age 5 that could be prevented by the 2nd dose of the PCV vaccine | F36: ='Disease burden'!F389 -> % | G36: supp | H36: ='Disease burden'!H389 -> - | I36: ='Disease burden'!I389 -> 0.18510369 | J36: ='Disease burden'!J389 -> 0.21293712 | K36: ='Disease burden'!K389 -> 0.18316803 | L36: ='Disease burden'!L389 -> 0.23515091 | M36: ='Disease burden'!M389 -> 0.2282429 | N36: ='Disease burden'!N389 -> 0.17108494 | O36: ='Disease burden'!O389 -> 0.17086174 | ... AS36: ='Disease burden'!AS389 -> 0.17311055
E37: Proportion of vaccine-preventable mortalities among people under age 5 that could be prevented by the 3rd dose of the PCV vaccine | F37: ='Disease burden'!F390 -> % | G37: supp | H37: ='Disease burden'!H390 -> - | I37: ='Disease burden'!I390 -> 0.033655217 | J37: ='Disease burden'!J390 -> 0.03871584 | K37: ='Disease burden'!K390 -> 0.033303279 | L37: ='Disease burden'!L390 -> 0.042754711 | M37: ='Disease burden'!M390 -> 0.041498709 | N37: ='Disease burden'!N390 -> 0.031106352 | O37: ='Disease burden'!O390 -> 0.031065772 | ... AS37: ='Disease burden'!AS390 -> 0.031474645
E38: Proportion of vaccine-preventable mortalities among people under age 5 that could be prevented by the 1st dose of the measles vaccine | F38: ='Disease burden'!F393 -> % | G38: supp | H38: ='Disease burden'!H393 -> - | I38: ='Disease burden'!I393 -> 0.059805717 | J38: ='Disease burden'!J393 -> 0.046870343 | K38: ='Disease burden'!K393 -> 0.06597866 | L38: ='Disease burden'!L393 -> 0.053867734 | M38: ='Disease burden'!M393 -> 0.034953333 | N38: ='Disease burden'!N393 -> 0.081308726 | O38: ='Disease burden'!O393 -> 0.076530784 | ... AS38: ='Disease burden'!AS393 -> 0.079728455
C40: Average proportion of vaccine-preventable mortalities that could be prevented by each vaccine dose in RCT states (Jigawa, Katsina, Zamfara)
E41: Proportion of vaccine-preventable mortalities among people under age 5 that could be prevented by the BCG vaccine in RCT states | F41: % | G41: calc | H41: =AVERAGE(K31,N31,Q31) -> 0.22901989 | I41: - | J41: - | K41: - | L41: - | M41: - | N41: - | O41: - | P41: - | Q41: - | R41: - | S41: - | T41: - | U41: - | V41: - | W41: - | X41: - | Y41: - | Z41: - | AA41: - | AB41: - | AC41: - | AD41: - | AE41: - | AF41: - | AG41: - | AH41: - | AI41: - | AJ41: - | AK41: - | AL41: - | AM41: - | AN41: - | AO41: - | AP41: - | AQ41: - | AR41: - | AS41: -
E42: Proportion of vaccine-preventable mortalities among people under age 5 that could be prevented by the 1st dose of the Penta vaccine in RCT states | F42: % | G42: calc | H42: =AVERAGE(K32,N32,Q32) -> 0.061544223 | I42: - | J42: - | K42: - | L42: - | M42: - | N42: - | O42: - | P42: - | Q42: - | R42: - | S42: - | T42: - | U42: - | V42: - | W42: - | X42: - | Y42: - | Z42: - | AA42: - | AB42: - | AC42: - | AD42: - | AE42: - | AF42: - | AG42: - | AH42: - | AI42: - | AJ42: - | AK42: - | AL42: - | AM42: - | AN42: - | AO42: - | AP42: - | AQ42: - | AR42: - | AS42: -
E43: Proportion of vaccine-preventable mortalities among people under age 5 that could be prevented by the 2nd dose of the Penta vaccine in RCT states | F43: % | G43: calc | H43: =AVERAGE(K33,N33,Q33) -> 0.096712351 | I43: - | J43: - | K43: - | L43: - | M43: - | N43: - | O43: - | P43: - | Q43: - | R43: - | S43: - | T43: - | U43: - | V43: - | W43: - | X43: - | Y43: - | Z43: - | AA43: - | AB43: - | AC43: - | AD43: - | AE43: - | AF43: - | AG43: - | AH43: - | AI43: - | AJ43: - | AK43: - | AL43: - | AM43: - | AN43: - | AO43: - | AP43: - | AQ43: - | AR43: - | AS43: -
E44: Proportion of vaccine-preventable mortalities among people under age 5 that could be prevented by the 3rd dose of the Penta vaccine in RCT states | F44: % | G44: calc | H44: =AVERAGE(K34,N34,Q34) -> 0.017584064 | I44: - | J44: - | K44: - | L44: - | M44: - | N44: - | O44: - | P44: - | Q44: - | R44: - | S44: - | T44: - | U44: - | V44: - | W44: - | X44: - | Y44: - | Z44: - | AA44: - | AB44: - | AC44: - | AD44: - | AE44: - | AF44: - | AG44: - | AH44: - | AI44: - | AJ44: - | AK44: - | AL44: - | AM44: - | AN44: - | AO44: - | AP44: - | AQ44: - | AR44: - | AS44: -
E45: Proportion of vaccine-preventable mortalities among people under age 5 that could be prevented by the 1st dose of the PCV vaccine in RCT states | F45: % | G45: calc | H45: =AVERAGE(K35,N35,Q35) -> 0.10556603 | I45: - | J45: - | K45: - | L45: - | M45: - | N45: - | O45: - | P45: - | Q45: - | R45: - | S45: - | T45: - | U45: - | V45: - | W45: - | X45: - | Y45: - | Z45: - | AA45: - | AB45: - | AC45: - | AD45: - | AE45: - | AF45: - | AG45: - | AH45: - | AI45: - | AJ45: - | AK45: - | AL45: - | AM45: - | AN45: - | AO45: - | AP45: - | AQ45: - | AR45: - | AS45: -
E46: Proportion of vaccine-preventable mortalities among people under age 5 that could be prevented by the 2nd dose of the PCV vaccine in RCT states | F46: % | G46: calc | H46: =AVERAGE(K36,N36,Q36) -> 0.16588948 | I46: - | J46: - | K46: - | L46: - | M46: - | N46: - | O46: - | P46: - | Q46: - | R46: - | S46: - | T46: - | U46: - | V46: - | W46: - | X46: - | Y46: - | Z46: - | AA46: - | AB46: - | AC46: - | AD46: - | AE46: - | AF46: - | AG46: - | AH46: - | AI46: - | AJ46: - | AK46: - | AL46: - | AM46: - | AN46: - | AO46: - | AP46: - | AQ46: - | AR46: - | AS46: -
E47: Proportion of vaccine-preventable mortalities among people under age 5 that could be prevented by the 3rd dose of the PCV vaccine in RCT states | F47: % | G47: calc | H47: =AVERAGE(K37,N37,Q37) -> 0.030161724 | I47: - | J47: - | K47: - | L47: - | M47: - | N47: - | O47: - | P47: - | Q47: - | R47: - | S47: - | T47: - | U47: - | V47: - | W47: - | X47: - | Y47: - | Z47: - | AA47: - | AB47: - | AC47: - | AD47: - | AE47: - | AF47: - | AG47: - | AH47: - | AI47: - | AJ47: - | AK47: - | AL47: - | AM47: - | AN47: - | AO47: - | AP47: - | AQ47: - | AR47: - | AS47: -
E48: Proportion of vaccine-preventable mortalities among people under age 5 that could be prevented by the 1st dose of the measles vaccine in RCT states | F48: % | G48: calc | H48: =AVERAGE(K38,N38,Q38) -> 0.073076749 | I48: - | J48: - | K48: - | L48: - | M48: - | N48: - | O48: - | P48: - | Q48: - | R48: - | S48: - | T48: - | U48: - | V48: - | W48: - | X48: - | Y48: - | Z48: - | AA48: - | AB48: - | AC48: - | AD48: - | AE48: - | AF48: - | AG48: - | AH48: - | AI48: - | AJ48: - | AK48: - | AL48: - | AM48: - | AN48: - | AO48: - | AP48: - | AQ48: - | AR48: - | AS48: -
C50: Vaccination coverage rates for the control group of the New Incentives RCT, adjusted for self-report bias, aggregated across vaccines
E51: Proportion of children in the New Incentives RCT control group who were vaccinated, aggregated across vaccines | F51: % | G51: calc | H51: =SUMPRODUCT(H21:H28,H41:H48)/SUM(H41:H48) -> 0.35575405 | I51: - | J51: - | K51: - | L51: - | M51: - | N51: - | O51: - | P51: - | Q51: - | R51: - | S51: - | T51: - | U51: - | V51: - | W51: - | X51: - | Y51: - | Z51: - | AA51: - | AB51: - | AC51: - | AD51: - | AE51: - | AF51: - | AG51: - | AH51: - | AI51: - | AJ51: - | AK51: - | AL51: - | AM51: - | AN51: - | AO51: - | AP51: - | AQ51: - | AR51: - | AS51: -
E52: Corresponding proportion of children in the New Incentives RCT control group who were not vaccinated, aggregated across vaccines | F52: % | G52: calc | H52: =1-H51 -> 0.64424595 | I52: - | J52: - | K52: - | L52: - | M52: - | N52: - | O52: - | P52: - | Q52: - | R52: - | S52: - | T52: - | U52: - | V52: - | W52: - | X52: - | Y52: - | Z52: - | AA52: - | AB52: - | AC52: - | AD52: - | AE52: - | AF52: - | AG52: - | AH52: - | AI52: - | AJ52: - | AK52: - | AL52: - | AM52: - | AN52: - | AO52: - | AP52: - | AQ52: - | AR52: - | AS52: -
C56: Treatment effects found by the New Incentives' RCT
E57: Increase in the proportion of children receiving the BCG vaccine | F57: =Inputs!F208 -> % | G57: =Inputs!G208 -> input | H57: =Inputs!H208 -> 0.1642 | I57: =Inputs!I208 -> - | J57: =Inputs!J208 -> - | K57: =Inputs!K208 -> - | L57: =Inputs!L208 -> - | M57: =Inputs!M208 -> - | ... AS57: =Inputs!AS208 -> -
E58: Increase in the proportion of children receiving the 1st dose of the Penta vaccine | F58: =Inputs!F209 -> % | G58: =Inputs!G209 -> input | H58: =Inputs!H209 -> 0.2093 | I58: =Inputs!I209 -> - | J58: =Inputs!J209 -> - | K58: =Inputs!K209 -> - | L58: =Inputs!L209 -> - | M58: =Inputs!M209 -> - | ... AS58: =Inputs!AS209 -> -
E59: Increase in the proportion of children receiving the 2nd dose of the Penta vaccine | F59: =Inputs!F210 -> % | G59: =Inputs!G210 -> input | H59: =Inputs!H210 -> 0.2659 | I59: =Inputs!I210 -> - | J59: =Inputs!J210 -> - | K59: =Inputs!K210 -> - | L59: =Inputs!L210 -> - | M59: =Inputs!M210 -> - | ... AS59: =Inputs!AS210 -> -
E60: Increase in the proportion of children receiving the 3rd dose of the Penta vaccine | F60: =Inputs!F211 -> % | G60: =Inputs!G211 -> input | H60: =Inputs!H211 -> 0.275 | I60: =Inputs!I211 -> - | J60: =Inputs!J211 -> - | K60: =Inputs!K211 -> - | L60: =Inputs!L211 -> - | M60: =Inputs!M211 -> - | ... AS60: =Inputs!AS211 -> -
E61: Increase in the proportion of children receiving the 1st dose of the PCV vaccine | F61: =Inputs!F212 -> % | G61: =Inputs!G212 -> input | H61: =Inputs!H212 -> 0.2227 | I61: =Inputs!I212 -> - | J61: =Inputs!J212 -> - | K61: =Inputs!K212 -> - | L61: =Inputs!L212 -> - | M61: =Inputs!M212 -> - | ... AS61: =Inputs!AS212 -> -
E62: Increase in the proportion of children receiving the 2nd dose of the PCV vaccine | F62: =Inputs!F213 -> % | G62: =Inputs!G213 -> input | H62: =Inputs!H213 -> 0.2726 | I62: =Inputs!I213 -> - | J62: =Inputs!J213 -> - | K62: =Inputs!K213 -> - | L62: =Inputs!L213 -> - | M62: =Inputs!M213 -> - | ... AS62: =Inputs!AS213 -> -
E63: Increase in the proportion of children receiving the 3rd dose of the PCV vaccine | F63: =Inputs!F214 -> % | G63: =Inputs!G214 -> input | H63: =Inputs!H214 -> 0.2471 | I63: =Inputs!I214 -> - | J63: =Inputs!J214 -> - | K63: =Inputs!K214 -> - | L63: =Inputs!L214 -> - | M63: =Inputs!M214 -> - | ... AS63: =Inputs!AS214 -> -
E64: Increase in the proportion of children receiving the measles vaccine | F64: =Inputs!F215 -> % | G64: =Inputs!G215 -> input | H64: =Inputs!H215 -> 0.1432 | I64: =Inputs!I215 -> - | J64: =Inputs!J215 -> - | K64: =Inputs!K215 -> - | L64: =Inputs!L215 -> - | M64: =Inputs!M215 -> - | ... AS64: =Inputs!AS215 -> -
C66: Treatment effect found by the New Incentives RCT, aggregated across vaccines
E67: Increase in proportion of children who are vaccinated, aggregated across vaccines | F67: % | G67: calc | H67: =SUMPRODUCT(H41:H48,H57:H64)/SUM(H41:H48) -> 0.21510527 | I67: - | J67: - | K67: - | L67: - | M67: - | N67: - | O67: - | P67: - | Q67: - | R67: - | S67: - | T67: - | U67: - | V67: - | W67: - | X67: - | Y67: - | Z67: - | AA67: - | AB67: - | AC67: - | AD67: - | AE67: - | AF67: - | AG67: - | AH67: - | AI67: - | AJ67: - | AK67: - | AL67: - | AM67: - | AN67: - | AO67: - | AP67: - | AQ67: - | AR67: - | AS67: -
C69: Implied reduction in the proportion of children who are unvaccinated as a result of New Incentives program
E70: Reduction in the proportion of children who are unvaccinated as a result of New Incentives' program, based on GW's analysis of the New Incentives RCT, aggregated across vaccines | F70: % | G70: calc | H70: =H67/H52 -> 0.33388688 | I70: - | J70: - | K70: - | L70: - | M70: - | N70: - | O70: - | P70: - | Q70: - | R70: - | S70: - | T70: - | U70: - | V70: - | W70: - | X70: - | Y70: - | Z70: - | AA70: - | AB70: - | AC70: - | AD70: - | AE70: - | AF70: - | AG70: - | AH70: - | AI70: - | AJ70: - | AK70: - | AL70: - | AM70: - | AN70: - | AO70: - | AP70: - | AQ70: - | AR70: - | AS70: -

Sheet Disease burden
I1: New Incentives – current states of operation | R1: New Incentives – prospective states | AF1: New Incentives – prospective states
I2: Nigeria | J2: Nigeria | K2: Nigeria | L2: Nigeria | M2: Nigeria | N2: Nigeria | O2: Nigeria | P2: Nigeria | Q2: Nigeria | R2: Nigeria | S2: Nigeria | T2: Nigeria | U2: Nigeria | V2: Nigeria | W2: Nigeria | X2: Nigeria | Y2: Nigeria | Z2: Nigeria | AA2: Nigeria | AB2: Nigeria | AC2: Nigeria | AD2: Nigeria | AE2: Nigeria | AF2: Nigeria | AG2: Nigeria | AH2: Nigeria | AI2: Nigeria | AJ2: Nigeria | AK2: Nigeria | AL2: Nigeria | AM2: Nigeria | AN2: Nigeria | AO2: Nigeria | AP2: Nigeria | AQ2: Nigeria | AR2: Nigeria | AS2: Nigeria
A3: Main calculations | F3: unit | G3: type | H3: Overall | I3: Bauchi | J3: Gombe | K3: Jigawa | L3: Kaduna | M3: Kano | N3: Katsina | O3: Kebbi | P3: Sokoto | Q3: Zamfara | R3: Abia | S3: Adamawa | T3: Akwa Ibom | U3: Anambra | V3: Bayelsa | W3: Benue | X3: Borno | Y3: Cross River | Z3: Delta | AA3: Ebonyi | AB3: Edo | AC3: Ekiti | AD3: Enugu | AE3: FCT | AF3: Imo | AG3: Kogi | AH3: Kwara | AI3: Lagos | AJ3: Nasarawa | AK3: Niger | AL3: Ogun | AM3: Ondo | AN3: Osun | AO3: Oyo | AP3: Plateau | AQ3: Rivers | AR3: Taraba | AS3: Yobe
E4: Final cost-effectiveness estimate (pulled from "Main calcs" sheet for visibility) | F4: ='Main CEA'!F241 -> xcash | G4: ='Main CEA'!G241 -> calc | H4: ='Main CEA'!H241 -> - | I4: ='Main CEA'!I241 -> 23.798889 | J4: ='Main CEA'!J241 -> 10.800641 | K4: ='Main CEA'!K241 -> 19.899944 | L4: ='Main CEA'!L241 -> 5.6568275 | M4: ='Main CEA'!M241 -> 13.129176 | ... AS4: ='Main CEA'!AS241 -> 6.7228331
A5: Tuberculosis
C7: Probability of dying of tuberculosis
E8: Probability that a person will die of tuberculosis before reaching age 5 | F8: =Inputs!F100 -> % | G8: =Inputs!G100 -> input | H8: =Inputs!H100 -> - | I8: =Inputs!I100 -> 0.003629763 | J8: =Inputs!J100 -> 0.001693533 | K8: =Inputs!K100 -> 0.004321809 | L8: =Inputs!L100 -> 0.000876042 | M8: =Inputs!M100 -> 0.001723095 | ... AS8: =Inputs!AS100 -> 0.00187352
E9: Probability that a 5-year-old will die of tuberculosis before reaching age 15 | F9: =Inputs!F101 -> % | G9: =Inputs!G101 -> input | H9: =Inputs!H101 -> - | I9: =Inputs!I101 -> 0.000531146 | J9: =Inputs!J101 -> 0.000260845 | K9: =Inputs!K101 -> 0.000599109 | L9: =Inputs!L101 -> 0.000139527 | M9: =Inputs!M101 -> 0.000283003 | ... AS9: =Inputs!AS101 -> 0.000388626
E10: Probability that a 15-year-old will die of tuberculosis before reaching age 50 | F10: =Inputs!F102 -> % | G10: =Inputs!G102 -> input | H10: =Inputs!H102 -> - | I10: =Inputs!I102 -> 0.007150253 | J10: =Inputs!J102 -> 0.004007767 | K10: =Inputs!K102 -> 0.008685948 | L10: =Inputs!L102 -> 0.002843472 | M10: =Inputs!M102 -> 0.003815045 | ... AS10: =Inputs!AS102 -> 0.006708114
E11: Probability that a 50-year-old will die of tuberculosis before reaching age 75 | F11: =Inputs!F103 -> % | G11: =Inputs!G103 -> input | H11: =Inputs!H103 -> - | I11: =Inputs!I103 -> 0.049361812 | J11: =Inputs!J103 -> 0.030242318 | K11: =Inputs!K103 -> 0.052337352 | L11: =Inputs!L103 -> 0.017468647 | M11: =Inputs!M103 -> 0.024547523 | ... AS11: =Inputs!AS103 -> 0.043770944
C13: Tuberculosis mortalities occurring before the age of vaccination
E14: Proportion of tuberculosis mortalities among people under age 5 that occur prior to the age of BCG vaccination (birth) | F14: % | G14: input | H14: =Inputs!H104 -> 0 | I14: =Inputs!I104 -> - | J14: =Inputs!J104 -> - | K14: =Inputs!K104 -> - | L14: =Inputs!L104 -> - | M14: =Inputs!M104 -> - | N14: =Inputs!N104 -> - | O14: =Inputs!O104 -> - | ... AS14: =Inputs!AS104 -> -
E15: Probability that a person will die of tuberculosis before reaching age 5, adjusted for deaths occurring before the age of vaccination | F15: % | G15: calc | H15: - | I15: =I8*(1-$H14) -> 0.003629763 | J15: =J8*(1-$H14) -> 0.001693533 | K15: =K8*(1-$H14) -> 0.004321809 | L15: =L8*(1-$H14) -> 0.000876042 | M15: =M8*(1-$H14) -> 0.001723095 | N15: =N8*(1-$H14) -> 0.002687563 | O15: =O8*(1-$H14) -> 0.002755632 | P15: =P8*(1-$H14) -> 0.004692335 | ... AS15: =AS8*(1-$H14) -> 0.00187352
A17: Diphtheria
C19: Probability of dying of diphtheria
E20: Probability that a person will die of diphtheria before reaching age 5 | F20: % | G20: input | H20: =Inputs!H107 -> - | I20: =Inputs!I107 -> 0.000501357 | J20: =Inputs!J107 -> 0.000347103 | K20: =Inputs!K107 -> 0.000579052 | L20: =Inputs!L107 -> 0.000105863 | M20: =Inputs!M107 -> 0.000247733 | N20: =Inputs!N107 -> 0.000380731 | O20: =Inputs!O107 -> 0.000728763 | ... AS20: =Inputs!AS107 -> 0.000257334
E21: Probability that a 5-year-old will die of diphtheria before reaching age 15 | F21: % | G21: input | H21: =Inputs!H108 -> - | I21: =Inputs!I108 -> 5.88e-05 | J21: =Inputs!J108 -> 4.39e-05 | K21: =Inputs!K108 -> 6.71e-05 | L21: =Inputs!L108 -> 1.99e-05 | M21: =Inputs!M108 -> 3.53e-05 | N21: =Inputs!N108 -> 4.59e-05 | O21: =Inputs!O108 -> 0.000109744 | ... AS21: =Inputs!AS108 -> 4.46e-05
E22: Probability that a 15-year-old will die of diphtheria before reaching age 50 | F22: % | G22: input | H22: =Inputs!H109 -> - | I22: =Inputs!I109 -> 2.77e-05 | J22: =Inputs!J109 -> 2.01e-05 | K22: =Inputs!K109 -> 3.52e-05 | L22: =Inputs!L109 -> 1.12e-05 | M22: =Inputs!M109 -> 1.33e-05 | N22: =Inputs!N109 -> 2.68e-05 | O22: =Inputs!O109 -> 5.9e-05 | ... AS22: =Inputs!AS109 -> 3.04e-05
E23: Probability that a 50-year-old will die of diphtheria before reaching age 75 | F23: % | G23: input | H23: =Inputs!H110 -> - | I23: =Inputs!I110 -> 4.12e-05 | J23: =Inputs!J110 -> 3.15e-05 | K23: =Inputs!K110 -> 4.55e-05 | L23: =Inputs!L110 -> 1.6e-05 | M23: =Inputs!M110 -> 2.15e-05 | N23: =Inputs!N110 -> 3.93e-05 | O23: =Inputs!O110 -> 8.1e-05 | ... AS23: =Inputs!AS110 -> 4.25e-05
C25: Diphtheria mortalities occurring before the age of vaccination
E26: Diphtheria mortalities per year among people under age 5 | F26: # | G26: input | H26: =Inputs!H111 -> - | I26: =Inputs!I111 -> 140.59257 | J26: =Inputs!J111 -> 45.34226 | K26: =Inputs!K111 -> 133.20073 | L26: =Inputs!L111 -> 41.327866 | M26: =Inputs!M111 -> 169.10401 | N26: =Inputs!N111 -> 160.20219 | O26: =Inputs!O111 -> 145.30193 | ... AS26: =Inputs!AS111 -> 43.778357
E27: Diphtheria mortalities per year among people under age 1 | F27: # | G27: input | H27: =Inputs!H112 -> - | I27: =Inputs!I112 -> 17.735934 | J27: =Inputs!J112 -> 7.3454386 | K27: =Inputs!K112 -> 17.622697 | L27: =Inputs!L112 -> 10.456793 | M27: =Inputs!M112 -> 24.367067 | N27: =Inputs!N112 -> 29.171431 | O27: =Inputs!O112 -> 26.006764 | ... AS27: =Inputs!AS112 -> 7.8200449
E28: Proportion of diphtheria mortalities among people under age 5 that occur before age 1 | F28: % | G28: calc | H28: - | I28: =I27/I26 -> 0.12615129 | J28: =J27/J26 -> 0.16199983 | K28: =K27/K26 -> 0.1323018 | L28: =L27/L26 -> 0.25302039 | M28: =M27/M26 -> 0.14409515 | N28: =N27/N26 -> 0.18209133 | O28: =O27/O26 -> 0.1789843 | P28: =P27/P26 -> 0.14956457 | ... AS28: =AS27/AS26 -> 0.1786281
E29: Assumed proportion of diphtheria mortalities among people under age 1 occurring before the age of Penta vaccination (6 weeks) | F29: % | G29: input | H29: =Inputs!H113 -> 0.15 | I29: =Inputs!I113 -> - | J29: =Inputs!J113 -> - | K29: =Inputs!K113 -> - | L29: =Inputs!L113 -> - | M29: =Inputs!M113 -> - | N29: =Inputs!N113 -> - | O29: =Inputs!O113 -> - | ... AS29: =Inputs!AS113 -> -
E30: Proportion of diphtheria mortalities among people under age 5 that occur before the age of Penta vaccination (6 weeks) | F30: % | G30: calc | H30: - | I30: =I28*$H29 -> 0.018922694 | J30: =J28*$H29 -> 0.024299975 | K30: =K28*$H29 -> 0.019845271 | L30: =L28*$H29 -> 0.037953058 | M30: =M28*$H29 -> 0.021614272 | N30: =N28*$H29 -> 0.0273137 | O30: =O28*$H29 -> 0.026847644 | P30: =P28*$H29 -> 0.022434685 | ... AS30: =AS28*$H29 -> 0.026794216
E31: Probability that a person will die of diphtheria before reaching age 5, adjusted for deaths occurring before the age of vaccination | F31: % | G31: calc | H31: - | I31: =I20*(1-I30) -> 0.00049186998 | J31: =J20*(1-J30) -> 0.00033866841 | K31: =K20*(1-K30) -> 0.00056756056 | L31: =L20*(1-L30) -> 0.00010184518 | M31: =M20*(1-M30) -> 0.00024237843 | N31: =N20*(1-N30) -> 0.00037033183 | O31: =O20*(1-O30) -> 0.00070919743 | P31: =P20*(1-P30) -> 0.0013868309 | ... AS31: =AS20*(1-AS30) -> 0.00025043894
A33: Pertussis
C35: Probability of dying of pertussis
E36: Probability that a person will die of pertussis before reaching age 5 | F36: % | G36: input | H36: =Inputs!H116 -> - | I36: =Inputs!I116 -> 0.001926586 | J36: =Inputs!J116 -> 0.001715755 | K36: =Inputs!K116 -> 0.002305103 | L36: =Inputs!L116 -> 0.001196296 | M36: =Inputs!M116 -> 0.001434608 | N36: =Inputs!N116 -> 0.001871217 | O36: =Inputs!O116 -> 0.002022091 | ... AS36: =Inputs!AS116 -> 0.001569238
E37: Probability that a 5-year-old will die of pertussis before reaching age 15 | F37: % | G37: input | H37: =Inputs!H117 -> - | I37: =Inputs!I117 -> 0.000230744 | J37: =Inputs!J117 -> 0.000206465 | K37: =Inputs!K117 -> 0.000290793 | L37: =Inputs!L117 -> 0.000172137 | M37: =Inputs!M117 -> 0.000177755 | N37: =Inputs!N117 -> 0.000245196 | O37: =Inputs!O117 -> 0.00027482 | ... AS37: =Inputs!AS117 -> 0.000187811
E38: Probability that a 15-year-old will die of pertussis before reaching age 50 | F38: % | G38: input | H38: =Inputs!H118 -> - | I38: =Inputs!I118 -> 4.74e-05 | J38: =Inputs!J118 -> 3.78e-05 | K38: =Inputs!K118 -> 6.91e-05 | L38: =Inputs!L118 -> 3.12e-05 | M38: =Inputs!M118 -> 3.37e-05 | N38: =Inputs!N118 -> 5.12e-05 | O38: =Inputs!O118 -> 5.8e-05 | ... AS38: =Inputs!AS118 -> 5.25e-05
E39: Probability that a 50-year-old will die of pertussis before reaching age 75 | F39: % | G39: input | H39: =Inputs!H119 -> - | I39: =Inputs!I119 -> 4.66e-05 | J39: =Inputs!J119 -> 3.85e-05 | K39: =Inputs!K119 -> 5.41e-05 | L39: =Inputs!L119 -> 2.93e-05 | M39: =Inputs!M119 -> 3.67e-05 | N39: =Inputs!N119 -> 4.68e-05 | O39: =Inputs!O119 -> 5.17e-05 | ... AS39: =Inputs!AS119 -> 4.43e-05
C41: Pertussis mortalities occurring before the age of vaccination
E42: Pertussis mortalities per year among people under age 5 | F42: # | G42: input | H42: =Inputs!H120 -> - | I42: =Inputs!I120 -> 540.80112 | J42: =Inputs!J120 -> 224.34515 | K42: =Inputs!K120 -> 530.89059 | L42: =Inputs!L120 -> 467.37802 | M42: =Inputs!M120 -> 980.08608 | N42: =Inputs!N120 -> 788.18415 | O42: =Inputs!O120 -> 403.53311 | ... AS42: =Inputs!AS120 -> 267.20856
E43: Pertussis mortalities per year among people under age 1 | F43: # | G43: input | H43: =Inputs!H121 -> - | I43: =Inputs!I121 -> 189.83394 | J43: =Inputs!J121 -> 81.000224 | K43: =Inputs!K121 -> 199.56906 | L43: =Inputs!L121 -> 197.55097 | M43: =Inputs!M121 -> 363.12604 | N43: =Inputs!N121 -> 306.15867 | O43: =Inputs!O121 -> 151.45647 | ... AS43: =Inputs!AS121 -> 102.6045
E44: Proportion of pertussis mortalities among people under age 5 that occur before age 1 | F44: % | G44: calc | H44: - | I44: =I43/I42 -> 0.35102357 | J44: =J43/J42 -> 0.36105182 | K44: =K43/K42 -> 0.37591373 | L44: =L43/L42 -> 0.42267921 | M44: =M43/M42 -> 0.37050423 | N44: =N43/N42 -> 0.38843546 | O44: =O43/O42 -> 0.37532601 | P44: =P43/P42 -> 0.36234088 | ... AS44: =AS43/AS42 -> 0.38398658
E45: Assumed proportion of pertussis mortalities among people under age 1 occurring before the age of Penta vaccination (6 weeks) | F45: % | G45: input | H45: =Inputs!H122 -> 0.15 | I45: =Inputs!I122 -> - | J45: =Inputs!J122 -> - | K45: =Inputs!K122 -> - | L45: =Inputs!L122 -> - | M45: =Inputs!M122 -> - | N45: =Inputs!N122 -> - | O45: =Inputs!O122 -> - | ... AS45: =Inputs!AS122 -> -
E46: Proportion of pertussis mortalities among people under age 5 that occur before the age of Penta vaccination (6 weeks) | F46: % | G46: calc | H46: - | I46: =I44*$H45 -> 0.052653535 | J46: =J44*$H45 -> 0.054157773 | K46: =K44*$H45 -> 0.05638706 | L46: =L44*$H45 -> 0.063401881 | M46: =M44*$H45 -> 0.055575635 | N46: =N44*$H45 -> 0.058265318 | O46: =O44*$H45 -> 0.056298901 | P46: =P44*$H45 -> 0.054351132 | ... AS46: =AS44*$H45 -> 0.057597988
E47: Probability that a person will die of pertussis before reaching age 5, adjusted for deaths occurring before the age of vaccination | F47: % | G47: calc | H47: - | I47: =I36*(1-I46) -> 0.0018251444 | J47: =J36*(1-J46) -> 0.0016228335 | K47: =K36*(1-K46) -> 0.002175125 | L47: =L36*(1-L46) -> 0.0011204486 | M47: =M36*(1-M46) -> 0.0013548787 | N47: =N36*(1-N46) -> 0.0017621899 | O47: =O36*(1-O46) -> 0.0019082495 | P47: =P36*(1-P46) -> 0.0022006705 | ... AS47: =AS36*(1-AS46) -> 0.001478853
A49: Tetanus
C51: Probability of dying of tetanus
E52: Probability that a person will die of tetanus before reaching age 5 | F52: % | G52: input | H52: =Inputs!H125 -> - | I52: =Inputs!I125 -> 0.000194494 | J52: =Inputs!J125 -> 0.000165483 | K52: =Inputs!K125 -> 0.000136302 | L52: =Inputs!L125 -> 0.0001208 | M52: =Inputs!M125 -> 0.000125013 | N52: =Inputs!N125 -> 0.000144148 | O52: =Inputs!O125 -> 0.000289399 | ... AS52: =Inputs!AS125 -> 0.000133492
E53: Probability that a 5-year-old will die of tetanus before reaching age 15 | F53: % | G53: input | H53: =Inputs!H126 -> - | I53: =Inputs!I126 -> 4.07e-05 | J53: =Inputs!J126 -> 4.22e-05 | K53: =Inputs!K126 -> 4.08e-05 | L53: =Inputs!L126 -> 2.54e-05 | M53: =Inputs!M126 -> 2.96e-05 | N53: =Inputs!N126 -> 3.15e-05 | O53: =Inputs!O126 -> 5e-05 | ... AS53: =Inputs!AS126 -> 2.88e-05
E54: Probability that a 15-year-old will die of tetanus before reaching age 50 | F54: % | G54: input | H54: =Inputs!H127 -> - | I54: =Inputs!I127 -> 7.96e-05 | J54: =Inputs!J127 -> 7.32e-05 | K54: =Inputs!K127 -> 9.69e-05 | L54: =Inputs!L127 -> 5.84e-05 | M54: =Inputs!M127 -> 4.9e-05 | N54: =Inputs!N127 -> 7.43e-05 | O54: =Inputs!O127 -> 0.000110427 | ... AS54: =Inputs!AS127 -> 7.93e-05
E55: Probability that a 50-year-old will die of tetanus before reaching age 75 | F55: % | G55: input | H55: =Inputs!H128 -> - | I55: =Inputs!I128 -> 0.000285466 | J55: =Inputs!J128 -> 0.000340228 | K55: =Inputs!K128 -> 0.000269698 | L55: =Inputs!L128 -> 0.00019924 | M55: =Inputs!M128 -> 0.000175487 | N55: =Inputs!N128 -> 0.000234563 | O55: =Inputs!O128 -> 0.000414794 | ... AS55: =Inputs!AS128 -> 0.000243663
C57: Tetanus mortalities occurring before the age of vaccination
E58: Tetanus mortalities per year among people under age 5 | F58: # | G58: input | H58: =Inputs!H129 -> - | I58: =Inputs!I129 -> 54.529057 | J58: =Inputs!J129 -> 21.614357 | K58: =Inputs!K129 -> 31.344077 | L58: =Inputs!L129 -> 47.159682 | M58: =Inputs!M129 -> 85.327054 | N58: =Inputs!N129 -> 60.643753 | O58: =Inputs!O129 -> 57.683113 | ... AS58: =Inputs!AS129 -> 22.708009
E59: Early neonatal tetanus mortalities per year (babies under 7 days old) | F59: # | G59: input | H59: =Inputs!H130 -> - | I59: =Inputs!I130 -> 30.478887 | J59: =Inputs!J130 -> 10.964286 | K59: =Inputs!K130 -> 15.563906 | L59: =Inputs!L130 -> 23.683078 | M59: =Inputs!M130 -> 43.12276 | N59: =Inputs!N130 -> 28.61758 | O59: =Inputs!O130 -> 31.957012 | ... AS59: =Inputs!AS130 -> 13.357209
E60: Late neonatal tetanus mortalities per year (babies between 7 and 27 days old) | F60: # | G60: input | H60: =Inputs!H131 -> - | I60: =Inputs!I131 -> 13.788224 | J60: =Inputs!J131 -> 5.840665 | K60: =Inputs!K131 -> 7.8627662 | L60: =Inputs!L131 -> 14.891264 | M60: =Inputs!M131 -> 25.744596 | N60: =Inputs!N131 -> 21.068592 | O60: =Inputs!O131 -> 16.169646 | ... AS60: =Inputs!AS131 -> 5.701252
E61: Tetanus mortalities per year among people under age 1 | F61: # | G61: input | H61: =Inputs!H132 -> - | I61: =Inputs!I132 -> 47.002054 | J61: =Inputs!J132 -> 17.979237 | K61: =Inputs!K132 -> 25.214423 | L61: =Inputs!L132 -> 41.855 | M61: =Inputs!M132 -> 72.754659 | N61: =Inputs!N132 -> 52.662731 | O61: =Inputs!O132 -> 51.536258 | ... AS61: =Inputs!AS132 -> 20.066783
E62: Proportion of tetanus mortalities among people under age 5 that occur during the neonatal period (babies between 0 and 27 days old) | F62: % | G62: calc | H62: - | I62: =SUM(I59:I60)/I58 -> 0.81180775 | J62: =SUM(J59:J60)/J58 -> 0.77749021 | K62: =SUM(K59:K60)/K58 -> 0.74740349 | L62: =SUM(L59:L60)/L58 -> 0.81795169 | M62: =SUM(M59:M60)/M58 -> 0.80709872 | N62: =SUM(N59:N60)/N58 -> 0.81931229 | O62: =SUM(O59:O60)/O58 -> 0.83432839 | P62: =SUM(P59:P60)/P58 -> 0.79893461 | ... AS62: =SUM(AS59:AS60)/AS58 -> 0.83928366
E63: Assumed ratio of tetanus mortalities among people under age 5 occurring after the neonatal period but before the age of Penta vaccination (6 weeks) to tetanus mortalities occurring in the neonatal period | F63: % | G63: input | H63: =Inputs!H133 -> 0.1 | I63: =Inputs!I133 -> - | J63: =Inputs!J133 -> - | K63: =Inputs!K133 -> - | L63: =Inputs!L133 -> - | M63: =Inputs!M133 -> - | N63: =Inputs!N133 -> - | O63: =Inputs!O133 -> - | ... AS63: =Inputs!AS133 -> -
E64: Proportion of tetanus mortalities among people under age 5 that occur before age 1 | F64: % | G64: calc | H64: - | I64: =I61/I58 -> 0.86196344 | J64: =J61/J58 -> 0.83181919 | K64: =K61/K58 -> 0.80443981 | L64: =L61/L58 -> 0.88751659 | M64: =M61/M58 -> 0.8526564 | N64: =N61/N58 -> 0.86839498 | O64: =O61/O58 -> 0.89343754 | P64: =P61/P58 -> 0.85734153 | ... AS64: =AS61/AS58 -> 0.88368746
E65: Proportion of tetanus mortalities among people under age 5 that occur before the age of Penta vaccination (6 weeks) | F65: % | G65: calc | H65: - | I65: =MIN(I64,I62*(1+$H63)) -> 0.86196344 | J65: =MIN(J64,J62*(1+$H63)) -> 0.83181919 | K65: =MIN(K64,K62*(1+$H63)) -> 0.80443981 | L65: =MIN(L64,L62*(1+$H63)) -> 0.88751659 | M65: =MIN(M64,M62*(1+$H63)) -> 0.8526564 | N65: =MIN(N64,N62*(1+$H63)) -> 0.86839498 | O65: =MIN(O64,O62*(1+$H63)) -> 0.89343754 | P65: =MIN(P64,P62*(1+$H63)) -> 0.85734153 | ... AS65: =MIN(AS64,AS62*(1+$H63)) -> 0.88368746
E66: Probability that a person will die of tetanus before reaching age 5, adjusted for deaths occurring before the age of vaccination | F66: % | G66: calc | H66: - | I66: =I52*(1-I65) -> 2.6847282e-05 | J66: =J52*(1-J65) -> 2.7831065e-05 | K66: =K52*(1-K65) -> 2.6655245e-05 | L66: =L52*(1-L65) -> 1.3587996e-05 | M66: =M52*(1-M65) -> 1.8419865e-05 | N66: =N52*(1-N65) -> 1.8970601e-05 | O66: =O52*(1-O65) -> 3.0839069e-05 | P66: =P52*(1-P65) -> 5.4654314e-05 | ... AS66: =AS52*(1-AS65) -> 1.5526793e-05
A68: Lower respiratory infections
C70: Probability of dying of a lower respiratory infection
E71: Probability that a person will die of a lower respiratory infection before reaching age 5 | F71: % | G71: input | H71: =Inputs!H136 -> - | I71: =Inputs!I136 -> 0.023390685 | J71: =Inputs!J136 -> 0.018787823 | K71: =Inputs!K136 -> 0.023068706 | L71: =Inputs!L136 -> 0.01387223 | M71: =Inputs!M136 -> 0.021079399 | N71: =Inputs!N136 -> 0.01695616 | O71: =Inputs!O136 -> 0.018438313 | ... AS71: =Inputs!AS136 -> 0.013456401
E72: Probability that a 5-year-old will die of a lower respiratory infection before reaching age 15 | F72: % | G72: input | H72: =Inputs!H137 -> - | I72: =Inputs!I137 -> 0.001298445 | J72: =Inputs!J137 -> 0.001136902 | K72: =Inputs!K137 -> 0.001358999 | L72: =Inputs!L137 -> 0.000848418 | M72: =Inputs!M137 -> 0.001325756 | N72: =Inputs!N137 -> 0.001052452 | O72: =Inputs!O137 -> 0.001083798 | ... AS72: =Inputs!AS137 -> 0.000921898
E73: Probability that a 15-year-old will die of a lower respiratory infection before reaching age 50 | F73: % | G73: input | H73: =Inputs!H138 -> - | I73: =Inputs!I138 -> 0.002586005 | J73: =Inputs!J138 -> 0.00203186 | K73: =Inputs!K138 -> 0.003081885 | L73: =Inputs!L138 -> 0.002004393 | M73: =Inputs!M138 -> 0.002148469 | N73: =Inputs!N138 -> 0.002520287 | O73: =Inputs!O138 -> 0.002528167 | ... AS73: =Inputs!AS138 -> 0.002595537
E74: Probability that a 50-year-old will die of a lower respiratory infection before reaching age 75 | F74: % | G74: input | H74: =Inputs!H139 -> - | I74: =Inputs!I139 -> 0.023849512 | J74: =Inputs!J139 -> 0.02352892 | K74: =Inputs!K139 -> 0.024494371 | L74: =Inputs!L139 -> 0.016803436 | M74: =Inputs!M139 -> 0.018501934 | N74: =Inputs!N139 -> 0.02109105 | O74: =Inputs!O139 -> 0.025109776 | ... AS74: =Inputs!AS139 -> 0.022438887
C76: Lower respiratory infection mortalities occurring before the age of vaccination
E77: Lower respiratory infection mortalities per year among people under age 5 | F77: # | G77: input | H77: =Inputs!H140 -> - | I77: =Inputs!I140 -> 6666.1604 | J77: =Inputs!J140 -> 2486.3679 | K77: =Inputs!K140 -> 5391.4653 | L77: =Inputs!L140 -> 5468.2709 | M77: =Inputs!M140 -> 14601.878 | N77: =Inputs!N140 -> 7218.5082 | O77: =Inputs!O140 -> 3722.4286 | ... AS77: =Inputs!AS140 -> 2310.5925
E78: Early neonatal lower respiratory infection mortalities per year (babies under 7 days old) | F78: # | G78: input | H78: =Inputs!H141 -> - | I78: =Inputs!I141 -> 1061.4675 | J78: =Inputs!J141 -> 381.06813 | K78: =Inputs!K141 -> 750.41368 | L78: =Inputs!L141 -> 981.21336 | M78: =Inputs!M141 -> 2779.113 | N78: =Inputs!N141 -> 1075.5619 | O78: =Inputs!O141 -> 697.04728 | ... AS78: =Inputs!AS141 -> 517.09376
E79: Late neonatal lower respiratory infection mortalities per year (babies between 7 and 27 days old) | F79: # | G79: input | H79: =Inputs!H142 -> - | I79: =Inputs!I142 -> 404.60418 | J79: =Inputs!J142 -> 172.49652 | K79: =Inputs!K142 -> 322.76861 | L79: =Inputs!L142 -> 560.45741 | M79: =Inputs!M142 -> 1432.3301 | N79: =Inputs!N142 -> 842.4771 | O79: =Inputs!O142 -> 317.37145 | ... AS79: =Inputs!AS142 -> 188.41491
E80: Proportion of lower respiratory infection mortalities among people under age 5 that occur during the neonatal period (babies between 0 and 27 days old) | F80: % | G80: calc | H80: - | I80: =SUM(I78:I79)/I77 -> 0.21992745 | J80: =SUM(J78:J79)/J77 -> 0.22263988 | K80: =SUM(K78:K79)/K77 -> 0.19905206 | L80: =SUM(L78:L79)/L77 -> 0.28193021 | M80: =SUM(M78:M79)/M77 -> 0.2884179 | N80: =SUM(N78:N79)/N77 -> 0.26571127 | O80: =SUM(O78:O79)/O77 -> 0.27251529 | P80: =SUM(P78:P79)/P77 -> 0.22209998 | ... AS80: =SUM(AS78:AS79)/AS77 -> 0.30533669
E81: Assumed ratio of lower respiratory infection mortalities among people under age 5 occurring after the neonatal period but before the age of Penta and PCV vaccination (6 weeks) to lower respiratory infection mortalities occurring in the neonatal period | F81: % | G81: input | H81: =Inputs!H143 -> 0.1 | I81: =Inputs!I143 -> - | J81: =Inputs!J143 -> - | K81: =Inputs!K143 -> - | L81: =Inputs!L143 -> - | M81: =Inputs!M143 -> - | N81: =Inputs!N143 -> - | O81: =Inputs!O143 -> - | ... AS81: =Inputs!AS143 -> -
E82: Proportion of lower respiratory infection mortalities among people under age 5 that occur before the age of Penta and PCV vaccination (6 weeks) | F82: % | G82: calc | H82: - | I82: =I80*(1+$H81) -> 0.24192019 | J82: =J80*(1+$H81) -> 0.24490387 | K82: =K80*(1+$H81) -> 0.21895727 | L82: =L80*(1+$H81) -> 0.31012323 | M82: =M80*(1+$H81) -> 0.31725969 | N82: =N80*(1+$H81) -> 0.29228239 | O82: =O80*(1+$H81) -> 0.29976682 | P82: =P80*(1+$H81) -> 0.24430998 | ... AS82: =AS80*(1+$H81) -> 0.33587036
E83: Probability that a person will die of a lower respiratory infection before reaching age 5, adjusted for deaths occurring before the age of vaccination | F83: % | G83: calc | H83: - | I83: =I71*(1-I82) -> 0.017732006 | J83: =J71*(1-J82) -> 0.014186612 | K83: =K71*(1-K82) -> 0.018017645 | L83: =L71*(1-L82) -> 0.0095701292 | M83: =M71*(1-M82) -> 0.014391755 | N83: =N71*(1-N82) -> 0.012000173 | O83: =O71*(1-O82) -> 0.012911118 | P83: =P71*(1-P82) -> 0.020371852 | ... AS83: =AS71*(1-AS82) -> 0.0089367948
C85: Disease etiology for lower respiratory infections
D86: Pathogens addressed by the Penta vaccine (H. influenzae type B)
E87: Proportion of lower respiratory infection deaths caused by pathogens addressed by the Penta vaccine (H. influenzae type B) | F87: % | G87: input | H87: =Inputs!H144 -> 0.0281715 | I87: =Inputs!I144 -> - | J87: =Inputs!J144 -> - | K87: =Inputs!K144 -> - | L87: =Inputs!L144 -> - | M87: =Inputs!M144 -> - | N87: =Inputs!N144 -> - | O87: =Inputs!O144 -> - | ... AS87: =Inputs!AS144 -> -
E88: Probability that a person will die of a lower respiratory infection caused by H. influenzae type B before reaching age 5, adjusted for deaths occuring before the age of vaccination | F88: % | G88: calc | H88: - | I88: =I83*$H$87 -> 0.00049953721 | J88: =J83*$H$87 -> 0.00039965815 | K88: =K83*$H$87 -> 0.00050758409 | L88: =L83*$H$87 -> 0.0002696049 | M88: =M83*$H$87 -> 0.00040543734 | N88: =N83*$H$87 -> 0.00033806287 | O88: =O83*$H$87 -> 0.00036372557 | P88: =P83*$H$87 -> 0.00057390564 | ... AS88: =AS83*$H$87 -> 0.00025176291
E89: Probability that a 5-year-old will die of a lower respiratory infection caused by H. influenzae type B before reaching age 15 | F89: % | G89: calc | H89: - | I89: =I72*$H$87 -> 3.6579143e-05 | J89: =J72*$H$87 -> 3.2028235e-05 | K89: =K72*$H$87 -> 3.828504e-05 | L89: =L72*$H$87 -> 2.3901208e-05 | M89: =M72*$H$87 -> 3.7348535e-05 | N89: =N72*$H$87 -> 2.9649152e-05 | O89: =O72*$H$87 -> 3.0532215e-05 | P89: =P72*$H$87 -> 4.1895641e-05 | ... AS89: =AS72*$H$87 -> 2.597125e-05
E90: Probability that a 15-year-old will die of a lower respiratory infection caused by H. influenzae type B before reaching age 50 | F90: % | G90: calc | H90: - | I90: =I73*$H$87 -> 7.285164e-05 | J90: =J73*$H$87 -> 5.7240544e-05 | K90: =K73*$H$87 -> 8.6821323e-05 | L90: =L73*$H$87 -> 5.6466757e-05 | M90: =M73*$H$87 -> 6.0525594e-05 | N90: =N73*$H$87 -> 7.1000265e-05 | O90: =O73*$H$87 -> 7.1222257e-05 | P90: =P73*$H$87 -> 9.3151572e-05 | ... AS90: =AS73*$H$87 -> 7.3120171e-05
E91: Probability that a 50-year-old will die of a lower respiratory infection caused by H. influenzae type B before reaching age 75 | F91: % | G91: calc | H91: - | I91: =I74*$H$87 -> 0.00067187653 | J91: =J74*$H$87 -> 0.00066284497 | K91: =K74*$H$87 -> 0.00069004317 | L91: =L74*$H$87 -> 0.000473378 | M91: =M74*$H$87 -> 0.00052122723 | N91: =N74*$H$87 -> 0.00059416652 | O91: =O74*$H$87 -> 0.00070738005 | P91: =P74*$H$87 -> 0.00068035068 | ... AS91: =AS74*$H$87 -> 0.00063213711
D92: Pathogens addressed by the PCV vaccine (S. pneumoniae)
E93: Proportion of lower respiratory infection deaths caused by pathogens addressed by the PCV vaccine (S. pneumoniae) | F93: % | G93: input | H93: =Inputs!H145 -> 0.5041559 | I93: =Inputs!I145 -> - | J93: =Inputs!J145 -> - | K93: =Inputs!K145 -> - | L93: =Inputs!L145 -> - | M93: =Inputs!M145 -> - | N93: =Inputs!N145 -> - | O93: =Inputs!O145 -> - | ... AS93: =Inputs!AS145 -> -
E94: Probability that a person will die of a lower respiratory infection caused by S. pneumoniae before reaching age 5, adjusted for deaths occuring before the age of vaccination | F94: % | G94: calc | H94: - | I94: =I83*$H$93 -> 0.0089396955 | J94: =J83*$H$93 -> 0.0071522643 | K94: =K83*$H$93 -> 0.0090837021 | L94: =L83*$H$93 -> 0.0048248371 | M94: =M83*$H$93 -> 0.0072556884 | N94: =N83*$H$93 -> 0.006049958 | O94: =O83*$H$93 -> 0.0065092166 | P94: =P83*$H$93 -> 0.01027059 | ... AS94: =AS83*$H$93 -> 0.0045055378
E95: Probability that a 5-year-old will die of a lower respiratory infection caused by S. pneumoniae before reaching age 15 | F95: % | G95: calc | H95: - | I95: =I72*$H$93 -> 0.00065461871 | J95: =J72*$H$93 -> 0.00057317585 | K95: =K72*$H$93 -> 0.00068514736 | L95: =L72*$H$93 -> 0.00042773494 | M95: =M72*$H$93 -> 0.00066838771 | N95: =N72*$H$93 -> 0.00053059989 | O95: =O72*$H$93 -> 0.00054640316 | P95: =P72*$H$93 -> 0.0007497625 | ... AS95: =AS72*$H$93 -> 0.00046478032
E96: Probability that a 15-year-old will die of a lower respiratory infection caused by S. pneumoniae before reaching age 50 | F96: % | G96: calc | H96: - | I96: =I73*$H$93 -> 0.0013037497 | J96: =J73*$H$93 -> 0.0010243742 | K96: =K73*$H$93 -> 0.0015537505 | L96: =L73*$H$93 -> 0.0010105266 | M96: =M73*$H$93 -> 0.0010831633 | N96: =N73*$H$93 -> 0.0012706176 | O96: =O73*$H$93 -> 0.0012745903 | P96: =P73*$H$93 -> 0.0016670364 | ... AS96: =AS73*$H$93 -> 0.0013085553
E97: Probability that a 50-year-old will die of a lower respiratory infection caused by S. pneumoniae before reaching age 75 | F97: % | G97: calc | H97: - | I97: =I74*$H$93 -> 0.012023872 | J97: =J74*$H$93 -> 0.011862244 | K97: =K74*$H$93 -> 0.012348982 | L97: =L74*$H$93 -> 0.0084715514 | M97: =M74*$H$93 -> 0.0093278592 | N97: =N74*$H$93 -> 0.010633177 | O97: =O74*$H$93 -> 0.012659242 | P97: =P74*$H$93 -> 0.012175525 | ... AS97: =AS74*$H$93 -> 0.011312697
A99: Meningitis
C101: Probability of dying of meningitis
E102: Probability that a person will die of meningitis before reaching age 5 | F102: % | G102: input | H102: =Inputs!H148 -> - | I102: =Inputs!I148 -> 0.006177361 | J102: =Inputs!J148 -> 0.005211418 | K102: =Inputs!K148 -> 0.006472392 | L102: =Inputs!L148 -> 0.003542222 | M102: =Inputs!M148 -> 0.005411087 | N102: =Inputs!N148 -> 0.004841311 | O102: =Inputs!O148 -> 0.005304934 | ... AS102: =Inputs!AS148 -> 0.003392061
E103: Probability that a 5-year-old will die of meningitis before reaching age 15 | F103: % | G103: input | H103: =Inputs!H149 -> - | I103: =Inputs!I149 -> 0.000920251 | J103: =Inputs!J149 -> 0.00078274 | K103: =Inputs!K149 -> 0.000975938 | L103: =Inputs!L149 -> 0.000543254 | M103: =Inputs!M149 -> 0.00085293 | N103: =Inputs!N149 -> 0.000744263 | O103: =Inputs!O149 -> 0.000848212 | ... AS103: =Inputs!AS149 -> 0.000678181
E104: Probability that a 15-year-old will die of meningitis before reaching age 50 | F104: % | G104: input | H104: =Inputs!H150 -> - | I104: =Inputs!I150 -> 0.001870641 | J104: =Inputs!J150 -> 0.001396704 | K104: =Inputs!K150 -> 0.002364602 | L104: =Inputs!L150 -> 0.001256075 | M104: =Inputs!M150 -> 0.001435015 | N104: =Inputs!N150 -> 0.001813177 | O104: =Inputs!O150 -> 0.001952634 | ... AS104: =Inputs!AS150 -> 0.001933221
E105: Probability that a 50-year-old will die of meningitis before reaching age 75 | F105: % | G105: input | H105: =Inputs!H151 -> - | I105: =Inputs!I151 -> 0.004939422 | J105: =Inputs!J151 -> 0.00469284 | K105: =Inputs!K151 -> 0.005174821 | L105: =Inputs!L151 -> 0.003177413 | M105: =Inputs!M151 -> 0.003663199 | N105: =Inputs!N151 -> 0.004443934 | O105: =Inputs!O151 -> 0.005659515 | ... AS105: =Inputs!AS151 -> 0.004682851
C107: Meningitis mortalities occurring before the age of vaccination
E108: Meningitis mortalities per year among people under age 5 | F108: # | G108: input | H108: =Inputs!H152 -> - | I108: =Inputs!I152 -> 1739.1942 | J108: =Inputs!J152 -> 683.0973 | K108: =Inputs!K152 -> 1495.0313 | L108: =Inputs!L152 -> 1386.1806 | M108: =Inputs!M152 -> 3707.0388 | N108: =Inputs!N152 -> 2043.4856 | O108: =Inputs!O152 -> 1061.1067 | ... AS108: =Inputs!AS152 -> 578.33614
E109: Early neonatal meningitis mortalities per year (babies under 7 days old) | F109: # | G109: input | H109: =Inputs!H153 -> - | I109: =Inputs!I153 -> 106.41412 | J109: =Inputs!J153 -> 39.269078 | K109: =Inputs!K153 -> 72.158886 | L109: =Inputs!L153 -> 94.853912 | M109: =Inputs!M153 -> 232.53891 | N109: =Inputs!N153 -> 108.23066 | O109: =Inputs!O153 -> 74.780463 | ... AS109: =Inputs!AS153 -> 53.6266
E110: Late neonatal meningitis mortalities per year (babies between 7 and 27 days old) | F110: # | G110: input | H110: =Inputs!H154 -> - | I110: =Inputs!I154 -> 52.032348 | J110: =Inputs!J154 -> 22.478349 | K110: =Inputs!K154 -> 40.572531 | L110: =Inputs!L154 -> 68.290076 | M110: =Inputs!M154 -> 157.41032 | N110: =Inputs!N154 -> 105.15979 | O110: =Inputs!O154 -> 44.52236 | ... AS110: =Inputs!AS154 -> 24.434616
E111: Proportion of meningitis mortalities among people under age 5 that occur during the neonatal period (babies between 0 and 27 days old) | F111: % | G111: calc | H111: - | I111: =SUM(I109:I110)/I108 -> 0.09110338 | J111: =SUM(J109:J110)/J108 -> 0.090393311 | K111: =SUM(K109:K110)/K108 -> 0.075404054 | L111: =SUM(L109:L110)/L108 -> 0.11769317 | M111: =SUM(M109:M110)/M108 -> 0.10519157 | N111: =SUM(N109:N110)/N108 -> 0.10442474 | O111: =SUM(O109:O110)/O108 -> 0.11243245 | P111: =SUM(P109:P110)/P108 -> 0.091013481 | ... AS111: =SUM(AS109:AS110)/AS108 -> 0.13497551
E112: Assumed ratio of meningitis mortalities among people under age 5 occurring after the neonatal period but before the age of Penta and PCV vaccination (6 weeks) to meningitis mortalities occurring in the neonatal period | F112: % | G112: input | H112: =Inputs!H155 -> 0.1 | I112: =Inputs!I155 -> - | J112: =Inputs!J155 -> - | K112: =Inputs!K155 -> - | L112: =Inputs!L155 -> - | M112: =Inputs!M155 -> - | N112: =Inputs!N155 -> - | O112: =Inputs!O155 -> - | ... AS112: =Inputs!AS155 -> -
E113: Proportion of meningitis mortalities among people under age 5 that occur before the age of Penta and PCV vaccination (6 weeks) | F113: % | G113: calc | H113: - | I113: =I111*(1+$H112) -> 0.10021372 | J113: =J111*(1+$H112) -> 0.099432642 | K113: =K111*(1+$H112) -> 0.082944459 | L113: =L111*(1+$H112) -> 0.12946248 | M113: =M111*(1+$H112) -> 0.11571073 | N113: =N111*(1+$H112) -> 0.11486721 | O113: =O111*(1+$H112) -> 0.12367569 | P113: =P111*(1+$H112) -> 0.10011483 | ... AS113: =AS111*(1+$H112) -> 0.14847306
E114: Probability that a person will die of meningitis before reaching age 5, adjusted for deaths occurring before the age of vaccination | F114: % | G114: calc | H114: - | I114: =I102*(1-I113) -> 0.0055583047 | J114: =J102*(1-J113) -> 0.0046932329 | K114: =K102*(1-K113) -> 0.0059355429 | L114: =L102*(1-L113) -> 0.0030836371 | M114: =M102*(1-M113) -> 0.0047849662 | N114: =N102*(1-N113) -> 0.0042852031 | O114: =O102*(1-O113) -> 0.0046488426 | P114: =P102*(1-P113) -> 0.0072214453 | ... AS114: =AS102*(1-AS113) -> 0.0028884313
C116: Disease etiology for meningitis
D117: Pathogens addressed by the Penta vaccine (H. influenzae type B)
E118: Proportion of meningitis deaths caused by pathogens addressed by the Penta vaccine (H. influenzae type B) according to GBD 2019 | F118: % | G118: input | H118: =Inputs!H156 -> 0.2189 | I118: =Inputs!I156 -> - | J118: =Inputs!J156 -> - | K118: =Inputs!K156 -> - | L118: =Inputs!L156 -> - | M118: =Inputs!M156 -> - | N118: =Inputs!N156 -> - | O118: =Inputs!O156 -> - | ... AS118: =Inputs!AS156 -> -
E119: Adjustment for alignment with Hib meningitis burden estimates from View-Hub | F119: =Inputs!F157 -> % | G119: =Inputs!G157 -> input | H119: =Inputs!H157 -> 0.11261 | I119: =Inputs!I157 -> - | J119: =Inputs!J157 -> - | K119: =Inputs!K157 -> - | L119: =Inputs!L157 -> - | M119: =Inputs!M157 -> - | ... AS119: =Inputs!AS157 -> -
...

Sheet Vaccine coverage
I1: New Incentives – current states of operation | R1: New Incentives – prospective states | AF1: New Incentives – prospective states
I2: Nigeria | J2: Nigeria | K2: Nigeria | L2: Nigeria | M2: Nigeria | N2: Nigeria | O2: Nigeria | P2: Nigeria | Q2: Nigeria | R2: Nigeria | S2: Nigeria | T2: Nigeria | U2: Nigeria | V2: Nigeria | W2: Nigeria | X2: Nigeria | Y2: Nigeria | Z2: Nigeria | AA2: Nigeria | AB2: Nigeria | AC2: Nigeria | AD2: Nigeria | AE2: Nigeria | AF2: Nigeria | AG2: Nigeria | AH2: Nigeria | AI2: Nigeria | AJ2: Nigeria | AK2: Nigeria | AL2: Nigeria | AM2: Nigeria | AN2: Nigeria | AO2: Nigeria | AP2: Nigeria | AQ2: Nigeria | AR2: Nigeria | AS2: Nigeria
A3: Main calculations | F3: unit | G3: type | H3: Overall | I3: Bauchi | J3: Gombe | K3: Jigawa | L3: Kaduna | M3: Kano | N3: Katsina | O3: Kebbi | P3: Sokoto | Q3: Zamfara | R3: Abia | S3: Adamawa | T3: Akwa Ibom | U3: Anambra | V3: Bayelsa | W3: Benue | X3: Borno | Y3: Cross River | Z3: Delta | AA3: Ebonyi | AB3: Edo | AC3: Ekiti | AD3: Enugu | AE3: FCT | AF3: Imo | AG3: Kogi | AH3: Kwara | AI3: Lagos | AJ3: Nasarawa | AK3: Niger | AL3: Ogun | AM3: Ondo | AN3: Osun | AO3: Oyo | AP3: Plateau | AQ3: Rivers | AR3: Taraba | AS3: Yobe
E4: Final cost-effectiveness estimate (pulled from "Main calcs" sheet for visibility) | F4: ='Main CEA'!F241 -> xcash | G4: ='Main CEA'!G241 -> calc | H4: ='Main CEA'!H241 -> - | I4: ='Main CEA'!I241 -> 23.798889 | J4: ='Main CEA'!J241 -> 10.800641 | K4: ='Main CEA'!K241 -> 19.899944 | L4: ='Main CEA'!L241 -> 5.6568275 | M4: ='Main CEA'!M241 -> 13.129176 | ... AS4: ='Main CEA'!AS241 -> 6.7228331
A5: Baseline vaccination coverage among the target population according to New Incentives' coverage surveys
C7: Populations targeted by New Incentives' coverage surveys
E8: Number of local government areas (LGAs) within the state | F8: # | G8: input | H8: =Inputs!H39 -> - | I8: =Inputs!I39 -> 20 | J8: =Inputs!J39 -> 11 | K8: =Inputs!K39 -> 27 | L8: =Inputs!L39 -> 23 | M8: =Inputs!M39 -> 44 | N8: =Inputs!N39 -> 34 | O8: =Inputs!O39 -> 21 | ... AS8: =Inputs!AS39 -> 17
E9: Number of LGAs surveyed by New Incentives' coverage survey | F9: # | G9: input | H9: =Inputs!H40 -> - | I9: =Inputs!I40 -> 20 | J9: =Inputs!J40 -> 11 | K9: =Inputs!K40 -> 23 | L9: =Inputs!L40 -> 18 | M9: =Inputs!M40 -> 44 | N9: =Inputs!N40 -> 12 | O9: =Inputs!O40 -> 16 | ... AS9: =Inputs!AS40 -> 0
E10: Proportion of LGAs surveyed | F10: % | G10: calc | H10: - | I10: =I9/I8 -> 1 | J10: =J9/J8 -> 1 | K10: =K9/K8 -> 0.85185185 | L10: =L9/L8 -> 0.7826087 | M10: =M9/M8 -> 1 | N10: =N9/N8 -> 0.35294118 | O10: =O9/O8 -> 0.76190476 | P10: =P9/P8 -> 0.60869565 | ... AS10: =AS9/AS8 -> 0
E11: Adjustment for higher confidence in coverage survey results | F11: % | G11: input | H11: =Inputs!H41 -> 0.5 | I11: =Inputs!I41 -> - | J11: =Inputs!J41 -> - | K11: =Inputs!K41 -> - | L11: =Inputs!L41 -> - | M11: =Inputs!M41 -> - | N11: =Inputs!N41 -> - | O11: =Inputs!O41 -> - | ... AS11: =Inputs!AS41 -> -
E12: Weight placed on the results of New Incentives' coverage surveys for estimating BCG, Penta, and PCV coverage | F12: % | G12: calc | H12: - | I12: =IF(I10=0,0,MIN(1,(I10*(1+$H11)))) -> 1 | J12: =IF(J10=0,0,MIN(1,(J10*(1+$H11)))) -> 1 | K12: =IF(K10=0,0,MIN(1,(K10*(1+$H11)))) -> 1 | L12: =IF(L10=0,0,MIN(1,(L10*(1+$H11)))) -> 1 | M12: =IF(M10=0,0,MIN(1,(M10*(1+$H11)))) -> 1 | N12: =IF(N10=0,0,MIN(1,(N10*(1+$H11)))) -> 0.52941176 | O12: =IF(O10=0,0,MIN(1,(O10*(1+$H11)))) -> 1 | P12: =IF(P10=0,0,MIN(1,(P10*(1+$H11)))) -> 0.91304348 | ... AS12: =IF(AS10=0,0,MIN(1,(AS10*(1+$H11)))) -> 0
C14: Baseline vaccination coverage found in New Incentives' coverage surveys
E15: Proportion of children reported to have received the BCG vaccine in New Incentives' coverage surveys | F15: % | G15: input | H15: =Inputs!H44 -> - | I15: =Inputs!I44 -> 0.5502363 | J15: =Inputs!J44 -> 0.71897 | K15: =Inputs!K44 -> 0.607543 | L15: =Inputs!L44 -> 0.771063 | M15: =Inputs!M44 -> 0.625174 | N15: =Inputs!N44 -> 0.42517 | O15: =Inputs!O44 -> 0.389681 | ... AS15: =Inputs!AS44 -> -
E16: Proportion of children reported to have received the 1st dose of the Penta vaccine in New Incentives' coverage surveys | F16: % | G16: input | H16: =Inputs!H45 -> - | I16: =Inputs!I45 -> 0.492627 | J16: =Inputs!J45 -> 0.669297 | K16: =Inputs!K45 -> 0.570422 | L16: =Inputs!L45 -> 0.737175 | M16: =Inputs!M45 -> 0.576081 | N16: =Inputs!N45 -> 0.391148 | O16: =Inputs!O45 -> 0.323942 | ... AS16: =Inputs!AS45 -> -
E17: Proportion of children reported to have received the 2nd dose of the Penta vaccine in New Incentives' coverage surveys | F17: % | G17: input | H17: =Inputs!H46 -> - | I17: =Inputs!I46 -> 0.4492416 | J17: =Inputs!J46 -> 0.627728 | K17: =Inputs!K46 -> 0.514389 | L17: =Inputs!L46 -> 0.666353 | M17: =Inputs!M46 -> 0.495632 | N17: =Inputs!N46 -> 0.375029 | O17: =Inputs!O46 -> 0.232988 | ... AS17: =Inputs!AS46 -> -
E18: Proportion of children reported to have received the 3rd dose of the Penta vaccine in New Incentives' coverage surveys | F18: % | G18: input | H18: =Inputs!H47 -> - | I18: =Inputs!I47 -> 0.3592128 | J18: =Inputs!J47 -> 0.498994 | K18: =Inputs!K47 -> 0.394439 | L18: =Inputs!L47 -> 0.575903 | M18: =Inputs!M47 -> 0.379575 | N18: =Inputs!N47 -> 0.298181 | O18: =Inputs!O47 -> 0.140453 | ... AS18: =Inputs!AS47 -> -
E19: Proportion of children reported to have received the 1st dose of the measles vaccine in New Incentives' coverage surveys | F19: % | G19: input | H19: =Inputs!H48 -> - | I19: =Inputs!I48 -> 0.3507536 | J19: =Inputs!J48 -> 0.487185 | K19: =Inputs!K48 -> 0.376109 | L19: =Inputs!L48 -> 0.534296 | M19: =Inputs!M48 -> 0.341451 | N19: =Inputs!N48 -> 0.267725 | O19: =Inputs!O48 -> 0.216692 | ... AS19: =Inputs!AS48 -> -
C21: Baseline vaccination coverage found in coverage surveys, adjusted for self-report bias
E22: Adjustment for self-report bias in New Incentives' coverage surveys | F22: % | G22: input | H22: =Inputs!H51 -> 0.006
E23: Estimated proportion of children who receive the BCG vaccine according to New Incentives' coverage surveys | F23: % | G23: calc | H23: - | I23: =IFERROR(I15*(1+$H$22),"-") -> 0.55353772 | J23: =IFERROR(J15*(1+$H$22),"-") -> 0.72328382 | K23: =IFERROR(K15*(1+$H$22),"-") -> 0.61118826 | L23: =IFERROR(L15*(1+$H$22),"-") -> 0.77568938 | M23: =IFERROR(M15*(1+$H$22),"-") -> 0.62892504 | N23: =IFERROR(N15*(1+$H$22),"-") -> 0.42772102 | O23: =IFERROR(O15*(1+$H$22),"-") -> 0.39201909 | P23: =IFERROR(P15*(1+$H$22),"-") -> 0.34918059 | ... AS23: =IFERROR(AS15*(1+$H$22),"-") -> -
E24: Estimated proportion of children who receive the 1st dose of the Penta vaccine according to New Incentives' coverage surveys | F24: % | G24: calc | H24: - | I24: =IFERROR(I16*(1+$H$22),"-") -> 0.49558276 | J24: =IFERROR(J16*(1+$H$22),"-") -> 0.67331278 | K24: =IFERROR(K16*(1+$H$22),"-") -> 0.57384453 | L24: =IFERROR(L16*(1+$H$22),"-") -> 0.74159805 | M24: =IFERROR(M16*(1+$H$22),"-") -> 0.57953749 | N24: =IFERROR(N16*(1+$H$22),"-") -> 0.39349489 | O24: =IFERROR(O16*(1+$H$22),"-") -> 0.32588565 | P24: =IFERROR(P16*(1+$H$22),"-") -> 0.26896818 | ... AS24: =IFERROR(AS16*(1+$H$22),"-") -> -
E25: Estimated proportion of children who receive the 2nd dose of the Penta vaccine according to New Incentives' coverage surveys | F25: % | G25: calc | H25: - | I25: =IFERROR(I17*(1+$H$22),"-") -> 0.45193705 | J25: =IFERROR(J17*(1+$H$22),"-") -> 0.63149437 | K25: =IFERROR(K17*(1+$H$22),"-") -> 0.51747533 | L25: =IFERROR(L17*(1+$H$22),"-") -> 0.67035112 | M25: =IFERROR(M17*(1+$H$22),"-") -> 0.49860579 | N25: =IFERROR(N17*(1+$H$22),"-") -> 0.37727917 | O25: =IFERROR(O17*(1+$H$22),"-") -> 0.23438593 | P25: =IFERROR(P17*(1+$H$22),"-") -> 0.25801787 | ... AS25: =IFERROR(AS17*(1+$H$22),"-") -> -
E26: Estimated proportion of children who receive the 3rd dose of the Penta vaccine according to New Incentives' coverage surveys | F26: % | G26: calc | H26: - | I26: =IFERROR(I18*(1+$H$22),"-") -> 0.36136808 | J26: =IFERROR(J18*(1+$H$22),"-") -> 0.50198796 | K26: =IFERROR(K18*(1+$H$22),"-") -> 0.39680563 | L26: =IFERROR(L18*(1+$H$22),"-") -> 0.57935842 | M26: =IFERROR(M18*(1+$H$22),"-") -> 0.38185245 | N26: =IFERROR(N18*(1+$H$22),"-") -> 0.29997009 | O26: =IFERROR(O18*(1+$H$22),"-") -> 0.14129572 | P26: =IFERROR(P18*(1+$H$22),"-") -> 0.18584442 | ... AS26: =IFERROR(AS18*(1+$H$22),"-") -> -
E27: Estimated proportion of children who receive the 1st dose of the measles vaccine according to New Incentives' coverage surveys | F27: % | G27: calc | H27: - | I27: =IFERROR(I19*(1+$H$22),"-") -> 0.35285812 | J27: =IFERROR(J19*(1+$H$22),"-") -> 0.49010811 | K27: =IFERROR(K19*(1+$H$22),"-") -> 0.37836565 | L27: =IFERROR(L19*(1+$H$22),"-") -> 0.53750178 | M27: =IFERROR(M19*(1+$H$22),"-") -> 0.34349971 | N27: =IFERROR(N19*(1+$H$22),"-") -> 0.26933135 | O27: =IFERROR(O19*(1+$H$22),"-") -> 0.21799215 | P27: =IFERROR(P19*(1+$H$22),"-") -> 0.21425889 | ... AS27: =IFERROR(AS19*(1+$H$22),"-") -> -
A29: Baseline vaccination coverage among the target population according to the 2021 MICS survey results
C31: Baseline vaccination coverage found in the 2021 MICS coverage survey
E32: Proportion of children reported to have received the BCG vaccine in the 2021 MICS survey | F32: % | G32: input | H32: =Inputs!H54 -> - | I32: =Inputs!I54 -> 0.491 | J32: =Inputs!J54 -> 0.59 | K32: =Inputs!K54 -> 0.635 | L32: =Inputs!L54 -> 0.781 | M32: =Inputs!M54 -> 0.603 | N32: =Inputs!N54 -> 0.569 | O32: =Inputs!O54 -> 0.636 | ... AS32: =Inputs!AS54 -> 0.752
E33: Proportion of children reported to have received the 1st dose of the Penta vaccine in the 2021 MICS survey | F33: % | G33: input | H33: =Inputs!H55 -> - | I33: =Inputs!I55 -> 0.423 | J33: =Inputs!J55 -> 0.542 | K33: =Inputs!K55 -> 0.614 | L33: =Inputs!L55 -> 0.726 | M33: =Inputs!M55 -> 0.549 | N33: =Inputs!N55 -> 0.53 | O33: =Inputs!O55 -> 0.595 | ... AS33: =Inputs!AS55 -> 0.738
E34: Proportion of children reported to have received the 2nd dose of the Penta vaccine in the 2021 MICS survey | F34: % | G34: input | H34: =Inputs!H56 -> - | I34: =Inputs!I56 -> 0.376 | J34: =Inputs!J56 -> 0.512 | K34: =Inputs!K56 -> 0.564 | L34: =Inputs!L56 -> 0.665 | M34: =Inputs!M56 -> 0.47 | N34: =Inputs!N56 -> 0.466 | O34: =Inputs!O56 -> 0.584 | ... AS34: =Inputs!AS56 -> 0.712
E35: Proportion of children reported to have received the 3rd dose of the Penta vaccine in the 2021 MICS survey | F35: % | G35: input | H35: =Inputs!H57 -> - | I35: =Inputs!I57 -> 0.313 | J35: =Inputs!J57 -> 0.38 | K35: =Inputs!K57 -> 0.488 | L35: =Inputs!L57 -> 0.603 | M35: =Inputs!M57 -> 0.424 | N35: =Inputs!N57 -> 0.412 | O35: =Inputs!O57 -> 0.551 | ... AS35: =Inputs!AS57 -> 0.642
E36: Proportion of children reported to have received the 1st dose of the PCV vaccine in the 2021 MICS survey | F36: % | G36: input | H36: =Inputs!H58 -> - | I36: =Inputs!I58 -> 0.415 | J36: =Inputs!J58 -> 0.522 | K36: =Inputs!K58 -> 0.606 | L36: =Inputs!L58 -> 0.72 | M36: =Inputs!M58 -> 0.544 | N36: =Inputs!N58 -> 0.518 | O36: =Inputs!O58 -> 0.596 | ... AS36: =Inputs!AS58 -> 0.72
E37: Proportion of children reported to have received the 2nd dose of the PCV vaccine in the 2021 MICS survey | F37: % | G37: input | H37: =Inputs!H59 -> - | I37: =Inputs!I59 -> 0.38 | J37: =Inputs!J59 -> 0.467 | K37: =Inputs!K59 -> 0.555 | L37: =Inputs!L59 -> 0.647 | M37: =Inputs!M59 -> 0.466 | N37: =Inputs!N59 -> 0.439 | O37: =Inputs!O59 -> 0.569 | ... AS37: =Inputs!AS59 -> 0.681
E38: Proportion of children reported to have received the 3rd dose of the PCV vaccine in the 2021 MICS survey | F38: % | G38: input | H38: =Inputs!H60 -> - | I38: =Inputs!I60 -> 0.313 | J38: =Inputs!J60 -> 0.369 | K38: =Inputs!K60 -> 0.483 | L38: =Inputs!L60 -> 0.59 | M38: =Inputs!M60 -> 0.399 | N38: =Inputs!N60 -> 0.391 | O38: =Inputs!O60 -> 0.539 | ... AS38: =Inputs!AS60 -> 0.631
E39: Proportion of children reported to have received the 1st dose of the measles vaccine in the 2021 MICS survey | F39: % | G39: input | H39: =Inputs!H61 -> - | I39: =Inputs!I61 -> 0.308 | J39: =Inputs!J61 -> 0.367 | K39: =Inputs!K61 -> 0.559 | L39: =Inputs!L61 -> 0.567 | M39: =Inputs!M61 -> 0.405 | N39: =Inputs!N61 -> 0.437 | O39: =Inputs!O61 -> 0.632 | ... AS39: =Inputs!AS61 -> 0.713
C41: Baseline vaccination coverage based on the 2021 MICS survey, adjusted for self-report bias
E42: Proportion of positive responses that came from self-report in the 2021 MICS survey | F42: % | G42: input | H42: =Inputs!H71 -> 0.217176 | I42: =Inputs!I71 -> - | J42: =Inputs!J71 -> - | K42: =Inputs!K71 -> - | L42: =Inputs!L71 -> - | M42: =Inputs!M71 -> - | N42: =Inputs!N71 -> - | O42: =Inputs!O71 -> - | ... AS42: =Inputs!AS71 -> -
E43: Adjustment for self-report bias in the 2021 MICS coverage survey | F43: % | G43: calc | H43: =H22*H42 -> 0.001303056 | I43: - | J43: - | K43: - | L43: - | M43: - | N43: - | O43: - | P43: - | Q43: - | R43: - | S43: - | T43: - | U43: - | V43: - | W43: - | X43: - | Y43: - | Z43: - | AA43: - | AB43: - | AC43: - | AD43: - | AE43: - | AF43: - | AG43: - | AH43: - | AI43: - | AJ43: - | AK43: - | AL43: - | AM43: - | AN43: - | AO43: - | AP43: - | AQ43: - | AR43: - | AS43: -
E44: Estimated proportion of children who receive the BCG vaccine | F44: % | G44: calc | H44: - | I44: =I32*(1+$H$43) -> 0.4916398 | J44: =J32*(1+$H$43) -> 0.5907688 | K44: =K32*(1+$H$43) -> 0.63582744 | L44: =L32*(1+$H$43) -> 0.78201769 | M44: =M32*(1+$H$43) -> 0.60378574 | N44: =N32*(1+$H$43) -> 0.56974144 | O44: =O32*(1+$H$43) -> 0.63682874 | P44: =P32*(1+$H$43) -> 0.33743913 | ... AS44: =AS32*(1+$H$43) -> 0.7529799
E45: Estimated proportion of children who receive the 1st dose of the Penta vaccine according to the 2021 MICS survey | F45: % | G45: calc | H45: - | I45: =I33*(1+$H$43) -> 0.42355119 | J45: =J33*(1+$H$43) -> 0.54270626 | K45: =K33*(1+$H$43) -> 0.61480008 | L45: =L33*(1+$H$43) -> 0.72694602 | M45: =M33*(1+$H$43) -> 0.54971538 | N45: =N33*(1+$H$43) -> 0.53069062 | O45: =O33*(1+$H$43) -> 0.59577532 | P45: =P33*(1+$H$43) -> 0.28837528 | ... AS45: =AS33*(1+$H$43) -> 0.73896166
E46: Estimated proportion of children who receive the 2nd dose of the Penta vaccine according to the 2021 MICS survey | F46: % | G46: calc | H46: - | I46: =I34*(1+$H$43) -> 0.37648995 | J46: =J34*(1+$H$43) -> 0.51266716 | K46: =K34*(1+$H$43) -> 0.56473492 | L46: =L34*(1+$H$43) -> 0.66586653 | M46: =M34*(1+$H$43) -> 0.47061244 | N46: =N34*(1+$H$43) -> 0.46660722 | O46: =O34*(1+$H$43) -> 0.58476098 | P46: =P34*(1+$H$43) -> 0.18423976 | ... AS46: =AS34*(1+$H$43) -> 0.71292778
E47: Estimated proportion of children who receive the 3rd dose of the Penta vaccine according to the 2021 MICS survey | F47: % | G47: calc | H47: - | I47: =I35*(1+$H$43) -> 0.31340786 | J47: =J35*(1+$H$43) -> 0.38049516 | K47: =K35*(1+$H$43) -> 0.48863589 | L47: =L35*(1+$H$43) -> 0.60378574 | M47: =M35*(1+$H$43) -> 0.4245525 | N47: =N35*(1+$H$43) -> 0.41253686 | O47: =O35*(1+$H$43) -> 0.55171798 | P47: =P35*(1+$H$43) -> 0.11514985 | ... AS47: =AS35*(1+$H$43) -> 0.64283656
E48: Estimated proportion of children who receive the 1st dose of the PCV vaccine according to the 2021 MICS survey | F48: % | G48: calc | H48: - | I48: =I36*(1+$H$43) -> 0.41554077 | J48: =J36*(1+$H$43) -> 0.5226802 | K48: =K36*(1+$H$43) -> 0.60678965 | L48: =L36*(1+$H$43) -> 0.7209382 | M48: =M36*(1+$H$43) -> 0.54470886 | N48: =N36*(1+$H$43) -> 0.51867498 | O48: =O36*(1+$H$43) -> 0.59677662 | P48: =P36*(1+$H$43) -> 0.21828407 | ... AS48: =AS36*(1+$H$43) -> 0.7209382
E49: Estimated proportion of children who receive the 2nd dose of the PCV vaccine according to the 2021 MICS survey | F49: % | G49: calc | H49: - | I49: =I37*(1+$H$43) -> 0.38049516 | J49: =J37*(1+$H$43) -> 0.46760853 | K49: =K37*(1+$H$43) -> 0.5557232 | L49: =L37*(1+$H$43) -> 0.64784308 | M49: =M37*(1+$H$43) -> 0.46660722 | N49: =N37*(1+$H$43) -> 0.43957204 | O49: =O37*(1+$H$43) -> 0.56974144 | P49: =P37*(1+$H$43) -> 0.14218503 | ... AS49: =AS37*(1+$H$43) -> 0.68188738
E50: Estimated proportion of children who receive the 3rd dose of the PCV vaccine according to the 2021 MICS survey | F50: % | G50: calc | H50: - | I50: =I38*(1+$H$43) -> 0.31340786 | J50: =J38*(1+$H$43) -> 0.36948083 | K50: =K38*(1+$H$43) -> 0.48362938 | L50: =L38*(1+$H$43) -> 0.5907688 | M50: =M38*(1+$H$43) -> 0.39951992 | N50: =N38*(1+$H$43) -> 0.39150949 | O50: =O38*(1+$H$43) -> 0.53970235 | P50: =P38*(1+$H$43) -> 0.10013031 | ... AS50: =AS38*(1+$H$43) -> 0.63182223
E51: Estimated proportion of children who receive the 1st dose of the measles vaccine according to the 2021 MICS survey | F51: % | G51: calc | H51: - | I51: =I39*(1+$H$43) -> 0.30840134 | J51: =J39*(1+$H$43) -> 0.36747822 | K51: =K39*(1+$H$43) -> 0.55972841 | L51: =L39*(1+$H$43) -> 0.56773883 | M51: =M39*(1+$H$43) -> 0.40552774 | N51: =N39*(1+$H$43) -> 0.43756944 | O51: =O39*(1+$H$43) -> 0.63282353 | P51: =P39*(1+$H$43) -> 0.19124888 | ... AS51: =AS39*(1+$H$43) -> 0.71392908
A53: Baseline vaccination coverage among the target population according to the 2017 MICS survey results
C55: Baseline vaccination coverage found in the 2017 MICS coverage survey
E56: Proportion of children reported to have received the BCG vaccine in the 2017 MICS survey | F56: % | G56: input | H56: =Inputs!H67 -> - | I56: =Inputs!I67 -> 0.412 | J56: =Inputs!J67 -> 0.544 | K56: =Inputs!K67 -> 0.256 | L56: =Inputs!L67 -> 0.514 | M56: =Inputs!M67 -> 0.337 | N56: =Inputs!N67 -> 0.285 | O56: =Inputs!O67 -> 0.226 | ... AS56: =Inputs!AS67 -> 0.163
E57: Proportion of children reported to have received the 1st dose of the Penta vaccine in the 2017 MICS survey | F57: % | G57: input | H57: =Inputs!H64 -> - | I57: =Inputs!I64 -> 0.353 | J57: =Inputs!J64 -> 0.447 | K57: =Inputs!K64 -> 0.195 | L57: =Inputs!L64 -> 0.437 | M57: =Inputs!M64 -> 0.279 | N57: =Inputs!N64 -> 0.282 | O57: =Inputs!O64 -> 0.202 | ... AS57: =Inputs!AS64 -> 0.175
E58: Proportion of children reported to have received the 2nd dose of the Penta vaccine in the 2017 MICS survey | F58: % | G58: input | H58: =Inputs!H65 -> - | I58: =Inputs!I65 -> 0.252 | J58: =Inputs!J65 -> 0.291 | K58: =Inputs!K65 -> 0.09 | L58: =Inputs!L65 -> 0.325 | M58: =Inputs!M65 -> 0.209 | N58: =Inputs!N65 -> 0.183 | O58: =Inputs!O65 -> 0.167 | ... AS58: =Inputs!AS65 -> 0.113
E59: Proportion of children reported to have received the 3rd dose of the Penta vaccine in the 2017 MICS survey | F59: % | G59: input | H59: =Inputs!H66 -> - | I59: =Inputs!I66 -> 0.185 | J59: =Inputs!J66 -> 0.25 | K59: =Inputs!K66 -> 0.071 | L59: =Inputs!L66 -> 0.295 | M59: =Inputs!M66 -> 0.159 | N59: =Inputs!N66 -> 0.121 | O59: =Inputs!O66 -> 0.113 | ... AS59: =Inputs!AS66 -> 0.087
E60: Proportion of children reported to have received the 1st dose of the measles vaccine in the 2017 MICS survey | F60: % | G60: input | H60: =Inputs!H68 -> - | I60: =Inputs!I68 -> 0.222 | J60: =Inputs!J68 -> 0.324 | K60: =Inputs!K68 -> 0.104 | L60: =Inputs!L68 -> 0.431 | M60: =Inputs!M68 -> 0.241 | N60: =Inputs!N68 -> 0.211 | O60: =Inputs!O68 -> 0.255 | ... AS60: =Inputs!AS68 -> 0.147
C62: Baseline vaccination coverage based on the 2017 MICS survey, adjusted for self-report bias
E63: Proportion of positive responses that came from self-report in the 2017 MICS survey | F63: % | G63: input | H63: =Inputs!H72 -> 0.4415068 | I63: =Inputs!I72 -> - | J63: =Inputs!J72 -> - | K63: =Inputs!K72 -> - | L63: =Inputs!L72 -> - | M63: =Inputs!M72 -> - | N63: =Inputs!N72 -> - | O63: =Inputs!O72 -> - | ... AS63: =Inputs!AS72 -> -
E64: Adjustment for self-report bias in the 2017 MICS coverage survey | F64: % | G64: calc | H64: =H22*H63 -> 0.0026490408 | I64: - | J64: - | K64: - | L64: - | M64: - | N64: - | O64: - | P64: - | Q64: - | R64: - | S64: - | T64: - | U64: - | V64: - | W64: - | X64: - | Y64: - | Z64: - | AA64: - | AB64: - | AC64: - | AD64: - | AE64: - | AF64: - | AG64: - | AH64: - | AI64: - | AJ64: - | AK64: - | AL64: - | AM64: - | AN64: - | AO64: - | AP64: - | AQ64: - | AR64: - | AS64: -
E65: Estimated proportion of children who receive the BCG vaccine according to the 2017 MICS survey | F65: % | G65: calc | H65: - | I65: =I56*(1+$H$64) -> 0.4130914 | J65: =J56*(1+$H$64) -> 0.54544108 | K65: =K56*(1+$H$64) -> 0.25667815 | L65: =L56*(1+$H$64) -> 0.51536161 | M65: =M56*(1+$H$64) -> 0.33789273 | N65: =N56*(1+$H$64) -> 0.28575498 | O65: =O56*(1+$H$64) -> 0.22659868 | P65: =P56*(1+$H$64) -> 0.16343179 | ... AS65: =AS56*(1+$H$64) -> 0.16343179
E66: Estimated proportion of children who receive the 1st dose of the Penta vaccine according to the 2017 MICS survey | F66: % | G66: calc | H66: - | I66: =I57*(1+$H$64) -> 0.35393511 | J66: =J57*(1+$H$64) -> 0.44818412 | K66: =K57*(1+$H$64) -> 0.19551656 | L66: =L57*(1+$H$64) -> 0.43815763 | M66: =M57*(1+$H$64) -> 0.27973908 | N66: =N57*(1+$H$64) -> 0.28274703 | O66: =O57*(1+$H$64) -> 0.20253511 | P66: =P57*(1+$H$64) -> 0.09424901 | ... AS66: =AS57*(1+$H$64) -> 0.17546358
E67: Estimated proportion of children who receive the 2nd dose of the Penta vaccine according to the 2017 MICS survey | F67: % | G67: calc | H67: - | I67: =I58*(1+$H$64) -> 0.25266756 | J67: =J58*(1+$H$64) -> 0.29177087 | K67: =K58*(1+$H$64) -> 0.090238414 | L67: =L58*(1+$H$64) -> 0.32586094 | M67: =M58*(1+$H$64) -> 0.20955365 | N67: =N58*(1+$H$64) -> 0.18348477 | O67: =O58*(1+$H$64) -> 0.16744239 | P67: =P58*(1+$H$64) -> 0.05213775 | ... AS67: =AS58*(1+$H$64) -> 0.11329934
E68: Estimated proportion of children who receive the 3rd dose of the Penta vaccine according to the 2017 MICS survey | F68: % | G68: calc | H68: - | I68: =I59*(1+$H$64) -> 0.18549007 | J68: =J59*(1+$H$64) -> 0.25066226 | K68: =K59*(1+$H$64) -> 0.071188082 | L68: =L59*(1+$H$64) -> 0.29578147 | M68: =M59*(1+$H$64) -> 0.1594212 | N68: =N59*(1+$H$64) -> 0.12132053 | O68: =O59*(1+$H$64) -> 0.11329934 | P68: =P59*(1+$H$64) -> 0.029076822 | ... AS68: =AS59*(1+$H$64) -> 0.087230467
E69: Estimated proportion of children who receive the 1st dose of the measles vaccine according to the 2017 MICS survey | F69: % | G69: calc | H69: - | I69: =I60*(1+$H$64) -> 0.22258809 | J69: =J60*(1+$H$64) -> 0.32485829 | K69: =K60*(1+$H$64) -> 0.1042755 | L69: =L60*(1+$H$64) -> 0.43214174 | M69: =M60*(1+$H$64) -> 0.24163842 | N69: =N60*(1+$H$64) -> 0.21155895 | O69: =O60*(1+$H$64) -> 0.25567551 | P69: =P60*(1+$H$64) -> 0.098259606 | ... AS69: =AS60*(1+$H$64) -> 0.14738941
C71: Ratio of 2017 MICS coverage results to 2021 MICS coverage results
E72: Ratio of BCG vaccine coverage from the 2017 MICS survey to the 2021 MICS survey | F72: % | G72: calc | H72: - | I72: =I65/I44 -> 0.84023182 | J72: =J65/J44 -> 0.92327333 | K72: =K65/K44 -> 0.40369153 | L72: =L65/L44 -> 0.65901528 | M72: =M65/M44 -> 0.55962356 | N72: =N65/N44 -> 0.50155203 | O72: =O65/O44 -> 0.35582358 | P72: =P65/P44 -> 0.4843297 | ... AS72: =AS65/AS44 -> 0.21704669
E73: Ratio of 1st dose Penta vaccine coverage from the 2017 MICS survey to the 2021 MICS survey | F73: % | G73: calc | H73: - | I73: =I66/I45 -> 0.83563715 | J73: =J66/J45 -> 0.82583187 | K73: =K66/K45 -> 0.31801649 | L73: =L66/L45 -> 0.60273751 | M73: =M66/M45 -> 0.50887986 | N73: =N66/N45 -> 0.53279071 | O73: =O66/O45 -> 0.33995216 | P73: =P66/P45 -> 0.32682763 | ... AS73: =AS66/AS45 -> 0.23744613
E74: Ratio of 2nd dose Penta vaccine coverage from the 2017 MICS survey to the 2021 MICS survey | F74: % | G74: calc | H74: - | I74: =I67/I46 -> 0.67111369 | J74: =J67/J46 -> 0.56912338 | K74: =K67/K46 -> 0.15978897 | L74: =L67/L46 -> 0.48937876 | M74: =M67/M46 -> 0.44527861 | N74: =N67/N46 -> 0.39323175 | O74: =O67/O46 -> 0.2863433 | P74: =P67/P46 -> 0.28298859 | ... AS74: =AS67/AS46 -> 0.15892121
E75: Ratio of 3rd dose Penta vaccine coverage from the 2017 MICS survey to the 2021 MICS survey | F75: % | G75: calc | H75: - | I75: =I68/I47 -> 0.59184883 | J75: =J68/J47 -> 0.6587791 | K75: =K68/K47 -> 0.14568738 | L75: =L68/L47 -> 0.48987819 | M75: =M68/M47 -> 0.37550409 | N75: =N68/N47 -> 0.29408411 | O75: =O68/O47 -> 0.20535735 | P75: =P68/P47 -> 0.25251289 | ... AS75: =AS68/AS47 -> 0.13569618
E76: Ratio of measles vaccine coverage from the 2017 MICS survey to the 2021 MICS survey | F76: % | G76: calc | H76: - | I76: =I69/I51 -> 0.72174812 | J76: =J69/J51 -> 0.88402052 | K76: =K69/K51 -> 0.1862966 | L76: =L69/L51 -> 0.7611629 | M76: =M69/M51 -> 0.59586163 | N76: =N69/N51 -> 0.48348657 | O76: =O69/O51 -> 0.40402339 | P76: =P69/P51 -> 0.51377872 | ... AS76: =AS69/AS51 -> 0.20644825
E77: Average ratio across vaccine doses | F77: % | G77: calc | H77: - | I77: =AVERAGE(I72:I76) -> 0.73211592 | J77: =AVERAGE(J72:J76) -> 0.77220564 | K77: =AVERAGE(K72:K76) -> 0.2426962 | L77: =AVERAGE(L72:L76) -> 0.60043453 | M77: =AVERAGE(M72:M76) -> 0.49702955 | N77: =AVERAGE(N72:N76) -> 0.44102903 | O77: =AVERAGE(O72:O76) -> 0.31829995 | P77: =AVERAGE(P72:P76) -> 0.37208751 | ... AS77: =AVERAGE(AS72:AS76) -> 0.19111169
C79: Extrapolated 2017 vaccination coverage for the PCV vaccine
E80: Extrapolated proportion of children who receive the 1st dose of the PCV vaccine based on the 2017 MICS survey | F80: % | G80: calc | H80: - | I80: =I48*I$77 -> 0.30422401 | J80: =J48*J$77 -> 0.40361659 | K80: =K48*K$77 -> 0.14726554 | L80: =L48*L$77 -> 0.43287619 | M80: =M48*M$77 -> 0.2707364 | N80: =N48*N$77 -> 0.22875073 | O80: =O48*O$77 -> 0.18995397 | P80: =P48*P$77 -> 0.081220774 | ... AS80: =AS48*AS$77 -> 0.13777972
E81: Extrapolated proportion of children who receive the 2nd dose of the PCV vaccine based on the 2017 MICS survey | F81: % | G81: calc | H81: - | I81: =I49*I$77 -> 0.27856657 | J81: =J49*J$77 -> 0.36108994 | K81: =K49*K$77 -> 0.13487191 | L81: =L49*L$77 -> 0.38898735 | M81: =M49*M$77 -> 0.23191758 | N81: =N49*N$77 -> 0.19386403 | O81: =O49*O$77 -> 0.18134867 | P81: =P49*P$77 -> 0.052905275 | ... AS81: =AS49*AS$77 -> 0.13031665
E82: Extrapolated proportion of children who receive the 3rd dose of the PCV vaccine based on the 2017 MICS survey | F82: % | G82: calc | H82: - | I82: =I50*I$77 -> 0.22945088 | J82: =J50*J$77 -> 0.28531518 | K82: =K50*K$77 -> 0.11737501 | L82: =L50*L$77 -> 0.35471799 | M82: =M50*M$77 -> 0.1985732 | N82: =N50*N$77 -> 0.17266705 | O82: =O50*O$77 -> 0.17178723 | P82: =P50*P$77 -> 0.037257236 | ... AS82: =AS50*AS$77 -> 0.12074861
A84: Estimated baseline vaccination coverage among target populations for New Incentives program
C86: Weighting of coverage estimates from different sources for the BCG, Penta, and PCV vaccines
E87: Weight placed on the results of New Incentives' coverage surveys for estimating BCG, Penta, and PCV coverage | F87: % | G87: feed | H87: =H12 -> - | I87: =I12 -> 1 | J87: =J12 -> 1 | K87: =K12 -> 1 | L87: =L12 -> 1 | M87: =M12 -> 1 | N87: =N12 -> 0.52941176 | O87: =O12 -> 1 | ... AS87: =AS12 -> 0
E88: Weight placed on the results of the 2021 MICS survey for estimating BCG, Penta, and PCV coverage | F88: % | G88: calc | H88: - | I88: =1-I87 -> 0 | J88: =1-J87 -> 0 | K88: =1-K87 -> 0 | L88: =1-L87 -> 0 | M88: =1-M87 -> 0 | N88: =1-N87 -> 0.47058824 | O88: =1-O87 -> 0 | P88: =1-P87 -> 0.086956522 | ... AS88: =1-AS87 -> 1
C90: Estimated baseline coverage for the BCG and Penta vaccines
E91: Baseline proportion of children in the target population who receive the BCG vaccine | F91: % | G91: calc | H91: - | I91: =IF(I23="-",I44,(I23*I87)+(I44*I88)) -> 0.55353772 | J91: =IF(J23="-",J44,(J23*J87)+(J44*J88)) -> 0.72328382 | K91: =IF(K23="-",K44,(K23*K87)+(K44*K88)) -> 0.61118826 | L91: =IF(L23="-",L44,(L23*L87)+(L44*L88)) -> 0.77568938 | M91: =IF(M23="-",M44,(M23*M87)+(M44*M88)) -> 0.62892504 | N91: =IF(N23="-",N44,(N23*N87)+(N44*N88)) -> 0.49455416 | O91: =IF(O23="-",O44,(O23*O87)+(O44*O88)) -> 0.39201909 | P91: =IF(P23="-",P44,(P23*P87)+(P44*P88)) -> 0.34815959 | Q91: =IF(Q23="-",Q44,(Q23*Q87)+(Q44*Q88)) -> 0.4767759 | R91: =IF(R23="-",R44,(R23*R$87)+(R44*R$88)) -> 0.90617927 | S91: =IF(S23="-",S44,(S23*S87)+(S44*S88)) -> 0.89699869 | T91: =IF(T23="-",T44,(T23*T87)+(T44*T88)) -> 0.85711542 | U91: =IF(U23="-",U44,(U23*U87)+(U44*U88)) -> 0.84509978 | V91: =IF(V23="-",V44,(V23*V87)+(V44*V88)) -> 0.79002811 | W91: =IF(W23="-",W44,(W23*W87)+(W44*W88)) -> 0.8180646 | X91: =IF(X23="-",X44,(X23*X87)+(X44*X88)) -> 0.64884438 | Y91: =IF(Y23="-",Y44,(Y23*Y87)+(Y44*Y88)) -> 0.93221315 | Z91: =IF(Z23="-",Z44,(Z23*Z87)+(Z44*Z88)) -> 0.83608805 | ... AS91: =IF(AS23="-",AS44,(AS23*AS87)+(AS44*AS88)) -> 0.7529799
E92: Baseline proportion of children in the target population who receive the 1st dose of the Penta vaccine | F92: % | G92: calc | H92: - | I92: =IF(I24="-",I45,(I24*I$87)+(I45*I$88)) -> 0.49558276 | J92: =IF(J24="-",J45,(J24*J$87)+(J45*J$88)) -> 0.67331278 | K92: =IF(K24="-",K45,(K24*K$87)+(K45*K$88)) -> 0.57384453 | L92: =IF(L24="-",L45,(L24*L$87)+(L45*L$88)) -> 0.74159805 | M92: =IF(M24="-",M45,(M24*M$87)+(M45*M$88)) -> 0.57953749 | N92: =IF(N24="-",N45,(N24*N$87)+(N45*N$88)) -> 0.45805759 | O92: =IF(O24="-",O45,(O24*O$87)+(O45*O$88)) -> 0.32588565 | P92: =IF(P24="-",P45,(P24*P$87)+(P45*P$88)) -> 0.27065576 | ... AS92: =IF(AS24="-",AS45,(AS24*AS$87)+(AS45*AS$88)) -> 0.73896166
E93: Baseline proportion of children in the target population who receive the 2nd dose of the Penta vaccine | F93: % | G93: calc | H93: - | I93: =IF(I25="-",I46,(I25*I$87)+(I46*I$88)) -> 0.45193705 | J93: =IF(J25="-",J46,(J25*J$87)+(J46*J$88)) -> 0.63149437 | K93: =IF(K25="-",K46,(K25*K$87)+(K46*K$88)) -> 0.51747533 | L93: =IF(L25="-",L46,(L25*L$87)+(L46*L$88)) -> 0.67035112 | M93: =IF(M25="-",M46,(M25*M$87)+(M46*M$88)) -> 0.49860579 | N93: =IF(N25="-",N46,(N25*N$87)+(N46*N$88)) -> 0.4193159 | O93: =IF(O25="-",O46,(O25*O$87)+(O46*O$88)) -> 0.23438593 | P93: =IF(P25="-",P46,(P25*P$87)+(P46*P$88)) -> 0.25160239 | ... AS93: =IF(AS25="-",AS46,(AS25*AS$87)+(AS46*AS$88)) -> 0.71292778
E94: Baseline proportion of children in the target population who receive the 3rd dose of the Penta vaccine | F94: % | G94: calc | H94: - | I94: =IF(I26="-",I47,(I26*I$87)+(I47*I$88)) -> 0.36136808 | J94: =IF(J26="-",J47,(J26*J$87)+(J47*J$88)) -> 0.50198796 | K94: =IF(K26="-",K47,(K26*K$87)+(K47*K$88)) -> 0.39680563 | L94: =IF(L26="-",L47,(L26*L$87)+(L47*L$88)) -> 0.57935842 | M94: =IF(M26="-",M47,(M26*M$87)+(M47*M$88)) -> 0.38185245 | N94: =IF(N26="-",N47,(N26*N$87)+(N47*N$88)) -> 0.35294269 | O94: =IF(O26="-",O47,(O26*O$87)+(O47*O$88)) -> 0.14129572 | P94: =IF(P26="-",P47,(P26*P$87)+(P47*P$88)) -> 0.17969706 | ... AS94: =IF(AS26="-",AS47,(AS26*AS$87)+(AS47*AS$88)) -> 0.64283656
C96: Estimated baseline coverage for the PCV vaccine
E97: Average coverage rate for the Penta vaccine across doses from the 2021 MICS survey | F97: % | G97: calc | H97: - | I97: =AVERAGE(I45:I47) -> 0.37114967 | J97: =AVERAGE(J45:J47) -> 0.47862286 | K97: =AVERAGE(K45:K47) -> 0.55605696 | L97: =AVERAGE(L45:L47) -> 0.66553276 | M97: =AVERAGE(M45:M47) -> 0.48162677 | N97: =AVERAGE(N45:N47) -> 0.4699449 | O97: =AVERAGE(O45:O47) -> 0.5774181 | P97: =AVERAGE(P45:P47) -> 0.19592163 | ... AS97: =AVERAGE(AS45:AS47) -> 0.698242
E98: Average coverage rate for the PCV vaccine across doses from the 2021 MICS survey | F98: % | G98: calc | H98: - | I98: =AVERAGE(I48:I50) -> 0.3698146 | J98: =AVERAGE(J48:J50) -> 0.45325652 | K98: =AVERAGE(K48:K50) -> 0.54871407 | L98: =AVERAGE(L48:L50) -> 0.65318336 | M98: =AVERAGE(M48:M50) -> 0.47027867 | N98: =AVERAGE(N48:N50) -> 0.44991884 | O98: =AVERAGE(O48:O50) -> 0.56874014 | P98: =AVERAGE(P48:P50) -> 0.15353314 | ... AS98: =AVERAGE(AS48:AS50) -> 0.67821594
E99: Estimated difference between PCV vaccine coverage and Penta vaccine coverage | F99: % | G99: calc | H99: - | I99: =(I98-I97)/I97 -> -0.0035971223 | J99: =(J98-J97)/J97 -> -0.052998605 | K99: =(K98-K97)/K97 -> -0.013205282 | L99: =(L98-L97)/L97 -> -0.018555667 | M99: =(M98-M97)/M97 -> -0.023562024 | N99: =(N98-N97)/N97 -> -0.042613636 | O99: =(O98-O97)/O97 -> -0.015028902 | P99: =(P98-P97)/P97 -> -0.21635434 | ... AS99: =(AS98-AS97)/AS97 -> -0.028680688
E100: Extrapolated proportion of children surveyed in New Incentives' coverage surveys who received the 1st dose of the PCV vaccine | F100: % | G100: calc | H100: - | I100: =IF(I24="-","-",I24*(1+I$99)) -> 0.49380009 | J100: =IF(J24="-","-",J24*(1+J$99)) -> 0.63762814 | K100: =IF(K24="-","-",K24*(1+K$99)) -> 0.56626675 | L100: =IF(L24="-","-",L24*(1+L$99)) -> 0.7278372 | M100: =IF(M24="-","-",M24*(1+M$99)) -> 0.56588241 | N100: =IF(N24="-","-",N24*(1+N$99)) -> 0.37672664 | O100: =IF(O24="-","-",O24*(1+O$99)) -> 0.32098795 | P100: =IF(P24="-","-",P24*(1+P$99)) -> 0.21077575 | ... AS100: =IF(AS24="-","-",AS24*(1+AS$99)) -> -
E101: Extrapolated proportion of children surveyed in New Incentives' coverage surveys who received the 2nd dose of the PCV vaccine | F101: % | G101: calc | H101: - | I101: =IF(I25="-","-",I25*(1+I$99)) -> 0.45031138 | J101: =IF(J25="-","-",J25*(1+J$99)) -> 0.59802605 | K101: =IF(K25="-","-",K25*(1+K$99)) -> 0.51064193 | L101: =IF(L25="-","-",L25*(1+L$99)) -> 0.65791231 | M101: =IF(M25="-","-",M25*(1+M$99)) -> 0.48685763 | N101: =IF(N25="-","-",N25*(1+N$99)) -> 0.36120194 | O101: =IF(O25="-","-",O25*(1+O$99)) -> 0.23086336 | P101: =IF(P25="-","-",P25*(1+P$99)) -> 0.20219459 | ... AS101: =IF(AS25="-","-",AS25*(1+AS$99)) -> -
E102: Extrapolated proportion of children surveyed in New Incentives' coverage surveys who received the 3rd dose of the PCV vaccine | F102: % | G102: calc | H102: - | I102: =IF(I26="-","-",I26*(1+I$99)) -> 0.36006819 | J102: =IF(J26="-","-",J26*(1+J$99)) -> 0.4753833 | K102: =IF(K26="-","-",K26*(1+K$99)) -> 0.3915657 | L102: =IF(L26="-","-",L26*(1+L$99)) -> 0.56860804 | M102: =IF(M26="-","-",M26*(1+M$99)) -> 0.37285523 | N102: =IF(N26="-","-",N26*(1+N$99)) -> 0.28718727 | O102: =IF(O26="-","-",O26*(1+O$99)) -> 0.1391722 | P102: =IF(P26="-","-",P26*(1+P$99)) -> 0.14563617 | ... AS102: =IF(AS26="-","-",AS26*(1+AS$99)) -> -
E103: Baseline proportion of children in the target population who receive the 1st dose of the PCV vaccine | F103: % | G103: calc | H103: - | I103: =IF(I100="-",I48,(I100*I$87)+(I48*I$88)) -> 0.49380009 | J103: =IF(J100="-",J48,(J100*J$87)+(J48*J$88)) -> 0.63762814 | K103: =IF(K100="-",K48,(K100*K$87)+(K48*K$88)) -> 0.56626675 | L103: =IF(L100="-",L48,(L100*L$87)+(L48*L$88)) -> 0.7278372 | M103: =IF(M100="-",M48,(M100*M$87)+(M48*M$88)) -> 0.56588241 | N103: =IF(N100="-",N48,(N100*N$87)+(N48*N$88)) -> 0.44352586 | O103: =IF(O100="-",O48,(O100*O$87)+(O48*O$88)) -> 0.32098795 | P103: =IF(P100="-",P48,(P100*P$87)+(P48*P$88)) -> 0.21142865 | ... AS103: =IF(AS100="-",AS48,(AS100*AS$87)+(AS48*AS$88)) -> 0.7209382
E104: Baseline proportion of children in the target population who receive the 2nd dose of the PCV vaccine | F104: % | G104: calc | H104: - | I104: =IF(I101="-",I49,(I101*I$87)+(I49*I$88)) -> 0.45031138 | J104: =IF(J101="-",J49,(J101*J$87)+(J49*J$88)) -> 0.59802605 | K104: =IF(K101="-",K49,(K101*K$87)+(K49*K$88)) -> 0.51064193 | L104: =IF(L101="-",L49,(L101*L$87)+(L49*L$88)) -> 0.65791231 | M104: =IF(M101="-",M49,(M101*M$87)+(M49*M$88)) -> 0.48685763 | N104: =IF(N101="-",N49,(N101*N$87)+(N49*N$88)) -> 0.39808199 | O104: =IF(O101="-",O49,(O101*O$87)+(O49*O$88)) -> 0.23086336 | P104: =IF(P101="-",P49,(P101*P$87)+(P49*P$88)) -> 0.19697636 | ... AS104: =IF(AS101="-",AS49,(AS101*AS$87)+(AS49*AS$88)) -> 0.68188738
E105: Baseline proportion of children in the target population who receive the 3rd dose of the PCV vaccine | F105: % | G105: calc | H105: - | I105: =IF(I102="-",I50,(I102*I$87)+(I50*I$88)) -> 0.36006819 | J105: =IF(J102="-",J50,(J102*J$87)+(J50*J$88)) -> 0.4753833 | K105: =IF(K102="-",K50,(K102*K$87)+(K50*K$88)) -> 0.3915657 | L105: =IF(L102="-",L50,(L102*L$87)+(L50*L$88)) -> 0.56860804 | M105: =IF(M102="-",M50,(M102*M$87)+(M50*M$88)) -> 0.37285523 | N105: =IF(N102="-",N50,(N102*N$87)+(N50*N$88)) -> 0.33628008 | O105: =IF(O102="-",O50,(O102*O$87)+(O50*O$88)) -> 0.1391722 | P105: =IF(P102="-",P50,(P102*P$87)+(P50*P$88)) -> 0.14167914 | ... AS105: =IF(AS102="-",AS50,(AS102*AS$87)+(AS50*AS$88)) -> 0.63182223
C107: Weighting of coverage estimates from different sources for the rotavirus vaccine
E108: Weight placed on estimated coverage for the Penta vaccine for estimating rotavirus vaccine coverage | F108: % | G108: input | H108: =Inputs!H75 -> 0.5 | I108: =Inputs!I75 -> - | J108: =Inputs!J75 -> - | K108: =Inputs!K75 -> - | L108: =Inputs!L75 -> - | M108: =Inputs!M75 -> - | N108: =Inputs!N75 -> - | O108: =Inputs!O75 -> - | ... AS108: =Inputs!AS75 -> -
E109: Weight placed on estimated coverage for the PCV vaccine for estimating rotavirus vaccine coverage | F109: % | G109: input | H109: =Inputs!H76 -> 0.5 | I109: =Inputs!I76 -> - | J109: =Inputs!J76 -> - | K109: =Inputs!K76 -> - | L109: =Inputs!L76 -> - | M109: =Inputs!M76 -> - | N109: =Inputs!N76 -> - | O109: =Inputs!O76 -> - | ... AS109: =Inputs!AS76 -> -
E110: Baseline proportion of children in the target popullation who receive the 1st dose of the rotavirus vaccine | F110: % | G110: calc | H110: - | I110: =(I92*$H$108)+(I103*$H$109) -> 0.49469143 | J110: =(J92*$H$108)+(J103*$H$109) -> 0.65547046 | K110: =(K92*$H$108)+(K103*$H$109) -> 0.57005564 | L110: =(L92*$H$108)+(L103*$H$109) -> 0.73471763 | M110: =(M92*$H$108)+(M103*$H$109) -> 0.57270995 | N110: =(N92*$H$108)+(N103*$H$109) -> 0.45079172 | O110: =(O92*$H$108)+(O103*$H$109) -> 0.3234368 | P110: =(P92*$H$108)+(P103*$H$109) -> 0.2410422 | ... AS110: =(AS92*$H$108)+(AS103*$H$109) -> 0.72994993
E111: Estimated proportion of children in the target population who receive the 2nd dose of the rotavirus vaccine | F111: % | G111: calc | H111: - | I111: =(I93*$H$108)+(I104*$H$109) -> 0.45112421 | J111: =(J93*$H$108)+(J104*$H$109) -> 0.61476021 | K111: =(K93*$H$108)+(K104*$H$109) -> 0.51405863 | L111: =(L93*$H$108)+(L104*$H$109) -> 0.66413171 | M111: =(M93*$H$108)+(M104*$H$109) -> 0.49273171 | N111: =(N93*$H$108)+(N104*$H$109) -> 0.40869894 | O111: =(O93*$H$108)+(O104*$H$109) -> 0.23262465 | P111: =(P93*$H$108)+(P104*$H$109) -> 0.22428938 | ... AS111: =(AS93*$H$108)+(AS104*$H$109) -> 0.69740758
C113: Weighting of coverage estimates from different sources for the measles vaccine
E114: Weight placed on the results of New Incentives' coverage surveys for estimating measles vaccine coverage | F114: % | G114: input | H114: =Inputs!H83 -> 0 | I114: =Inputs!I83 -> - | J114: =Inputs!J83 -> - | K114: =Inputs!K83 -> - | L114: =Inputs!L83 -> - | M114: =Inputs!M83 -> - | N114: =Inputs!N83 -> - | O114: =Inputs!O83 -> - | ... AS114: =Inputs!AS83 -> -
E115: Weight placed on the results of the 2021 MICS survey for estimating measles vaccine coverage | F115: % | G115: input | H115: =Inputs!H84 -> 1 | I115: =Inputs!I84 -> - | J115: =Inputs!J84 -> - | K115: =Inputs!K84 -> - | L115: =Inputs!L84 -> - | M115: =Inputs!M84 -> - | N115: =Inputs!N84 -> - | O115: =Inputs!O84 -> - | ... AS115: =Inputs!AS84 -> -
C117: Estimated baseline coverage for the measles vaccine
E118: Baseline proportion of children in the target population who receive the 1st dose of the measles vaccine | F118: % | G118: calc | H118: - | I118: =IF(I27="-",I51,(I27*$H114)+(I51*$H115)) -> 0.30840134 | J118: =IF(J27="-",J51,(J27*$H114)+(J51*$H115)) -> 0.36747822 | K118: =IF(K27="-",K51,(K27*$H114)+(K51*$H115)) -> 0.55972841 | L118: =IF(L27="-",L51,(L27*$H114)+(L51*$H115)) -> 0.56773883 | M118: =IF(M27="-",M51,(M27*$H114)+(M51*$H115)) -> 0.40552774 | N118: =IF(N27="-",N51,(N27*$H114)+(N51*$H115)) -> 0.43756944 | O118: =IF(O27="-",O51,(O27*$H114)+(O51*$H115)) -> 0.63282353 | P118: =IF(P27="-",P51,(P27*$H114)+(P51*$H115)) -> 0.19124888 | ... AS118: =IF(AS27="-",AS51,(AS27*$H114)+(AS51*$H115)) -> 0.71392908
...

Sheet Vaccine efficacy
I1: New Incentives – current states of operation | R1: New Incentives – prospective states | AF1: New Incentives – prospective states
I2: Nigeria | J2: Nigeria | K2: Nigeria | L2: Nigeria | M2: Nigeria | N2: Nigeria | O2: Nigeria | P2: Nigeria | Q2: Nigeria | R2: Nigeria | S2: Nigeria | T2: Nigeria | U2: Nigeria | V2: Nigeria | W2: Nigeria | X2: Nigeria | Y2: Nigeria | Z2: Nigeria | AA2: Nigeria | AB2: Nigeria | AC2: Nigeria | AD2: Nigeria | AE2: Nigeria | AF2: Nigeria | AG2: Nigeria | AH2: Nigeria | AI2: Nigeria | AJ2: Nigeria | AK2: Nigeria | AL2: Nigeria | AM2: Nigeria | AN2: Nigeria | AO2: Nigeria | AP2: Nigeria | AQ2: Nigeria | AR2: Nigeria | AS2: Nigeria
A3: Main calculations | F3: unit | G3: type | H3: Overall | I3: Bauchi | J3: Gombe | K3: Jigawa | L3: Kaduna | M3: Kano | N3: Katsina | O3: Kebbi | P3: Sokoto | Q3: Zamfara | R3: Abia | S3: Adamawa | T3: Akwa Ibom | U3: Anambra | V3: Bayelsa | W3: Benue | X3: Borno | Y3: Cross River | Z3: Delta | AA3: Ebonyi | AB3: Edo | AC3: Ekiti | AD3: Enugu | AE3: FCT | AF3: Imo | AG3: Kogi | AH3: Kwara | AI3: Lagos | AJ3: Nasarawa | AK3: Niger | AL3: Ogun | AM3: Ondo | AN3: Osun | AO3: Oyo | AP3: Plateau | AQ3: Rivers | AR3: Taraba | AS3: Yobe
E4: Final cost-effectiveness estimate (pulled from "Main calcs" sheet for visibility) | F4: ='Main CEA'!F241 -> xcash | G4: ='Main CEA'!G241 -> calc | H4: ='Main CEA'!H241 -> - | I4: ='Main CEA'!I241 -> 23.798889 | J4: ='Main CEA'!J241 -> 10.800641 | K4: ='Main CEA'!K241 -> 19.899944 | L4: ='Main CEA'!L241 -> 5.6568275 | M4: ='Main CEA'!M241 -> 13.129176 | ... AS4: ='Main CEA'!AS241 -> 6.7228331
A5: Vaccine efficacy
C7: Vaccine efficacy rates from meta-analyses
E8: BCG vaccine efficacy rate from Mangtani et al. 2014 | F8: =Inputs!F16 -> % | G8: =Inputs!G16 -> input | H8: =Inputs!H16 -> 0.85 | I8: =Inputs!I16 -> - | J8: =Inputs!J16 -> - | K8: =Inputs!K16 -> - | L8: =Inputs!L16 -> - | M8: =Inputs!M16 -> - | ... AS8: =Inputs!AS16 -> -
E9: DTP vaccine efficacy rate from the LiST meta-analysis (part of the Penta vaccine) | F9: =Inputs!F17 -> % | G9: =Inputs!G17 -> input | H9: =Inputs!H17 -> 0.84 | I9: =Inputs!I17 -> - | J9: =Inputs!J17 -> - | K9: =Inputs!K17 -> - | L9: =Inputs!L17 -> - | M9: =Inputs!M17 -> - | ... AS9: =Inputs!AS17 -> -
E10: Hib vaccine efficacy rate from Thumburu et al. 2015 (part of the Penta vaccine) | F10: =Inputs!F18 -> % | G10: =Inputs!G18 -> input | H10: =Inputs!H18 -> 0.82 | I10: =Inputs!I18 -> - | J10: =Inputs!J18 -> - | K10: =Inputs!K18 -> - | L10: =Inputs!L18 -> - | M10: =Inputs!M18 -> - | ... AS10: =Inputs!AS18 -> -
E11: PCV vaccine efficacy rate from the LiST meta-analysis | F11: =Inputs!F19 -> % | G11: =Inputs!G19 -> input | H11: =Inputs!H19 -> 0.58 | I11: =Inputs!I19 -> - | J11: =Inputs!J19 -> - | K11: =Inputs!K19 -> - | L11: =Inputs!L19 -> - | M11: =Inputs!M19 -> - | ... AS11: =Inputs!AS19 -> -
E12: Rotavirus vaccine efficacy rate from the LiST meta-analysis | F12: =Inputs!F20 -> % | G12: =Inputs!G20 -> input | H12: =Inputs!H20 -> 0.46 | I12: =Inputs!I20 -> - | J12: =Inputs!J20 -> - | K12: =Inputs!K20 -> - | L12: =Inputs!L20 -> - | M12: =Inputs!M20 -> - | ... AS12: =Inputs!AS20 -> -
E13: Measles vaccine efficacy rate from the LiST meta-analysis | F13: =Inputs!F21 -> % | G13: =Inputs!G21 -> input | H13: =Inputs!H21 -> 0.85 | I13: =Inputs!I21 -> - | J13: =Inputs!J21 -> - | K13: =Inputs!K21 -> - | L13: =Inputs!L21 -> - | M13: =Inputs!M21 -> - | ... AS13: =Inputs!AS21 -> -
A15: Adjustments for geography-specific vaccine efficacy
C17: Measles vaccine efficacy implied by different data sources
E18: Measles vaccine efficacy rate from the LiST meta-analysis | F18: =F13 -> % | G18: feed | H18: =H13 -> 0.85 | I18: =I13 -> - | J18: =J13 -> - | K18: =K13 -> - | L18: =L13 -> - | M18: =M13 -> - | N18: =N13 -> - | O18: =O13 -> - | ... AS18: =AS13 -> -
E19: Measles vaccine efficacy rate GiveWell infers from the results of IDinsight's biomarkers pilot, assuming the results are entirely explained by vaccine efficacy | F19: =Inputs!F24 -> % | G19: =Inputs!G24 -> input | H19: =Inputs!H24 -> 0.2572674 | I19: =Inputs!I24 -> - | J19: =Inputs!J24 -> - | K19: =Inputs!K24 -> - | L19: =Inputs!L24 -> - | M19: =Inputs!M24 -> - | ... AS19: =Inputs!AS24 -> -
E20: Measles vaccine efficacy rate implied by the results of Fowotade et al. 2015 | F20: =Inputs!F25 -> % | G20: =Inputs!G25 -> input | H20: =Inputs!H25 -> 0.686 | I20: =Inputs!I25 -> - | J20: =Inputs!J25 -> - | K20: =Inputs!K25 -> - | L20: =Inputs!L25 -> - | M20: =Inputs!M25 -> - | ... AS20: =Inputs!AS25 -> -
E21: Measles vaccine efficacy rate from Uzicanin and Zimmerman 2011 | F21: =Inputs!F26 -> % | G21: =Inputs!G26 -> input | H21: =Inputs!H26 -> 0.73 | I21: =Inputs!I26 -> - | J21: =Inputs!J26 -> - | K21: =Inputs!K26 -> - | L21: =Inputs!L26 -> - | M21: =Inputs!M26 -> - | ... AS21: =Inputs!AS26 -> -
C23: Weights assigned to data sources for measles vaccine efficacy
E24: Weight assigned to the vaccine efficacy rate from the LiST meta-analysis | F24: =Inputs!F27 -> % | G24: =Inputs!G27 -> input | H24: =Inputs!H27 -> 0.1 | I24: =Inputs!I27 -> - | J24: =Inputs!J27 -> - | K24: =Inputs!K27 -> - | L24: =Inputs!L27 -> - | M24: =Inputs!M27 -> - | ... AS24: =Inputs!AS27 -> -
E25: Weight assigned to the vaccine efficacy rate GiveWell infers from the results of IDinsight's biomarkers pilot | F25: =Inputs!F28 -> % | G25: =Inputs!G28 -> input | H25: =Inputs!H28 -> 0.2 | I25: =Inputs!I28 -> - | J25: =Inputs!J28 -> - | K25: =Inputs!K28 -> - | L25: =Inputs!L28 -> - | M25: =Inputs!M28 -> - | ... AS25: =Inputs!AS28 -> -
E26: Weight assigned to the vaccine efficacy rate implied by the results of Fowotade et al. 2015 | F26: =Inputs!F29 -> % | G26: =Inputs!G29 -> input | H26: =Inputs!H29 -> 0.35 | I26: =Inputs!I29 -> - | J26: =Inputs!J29 -> - | K26: =Inputs!K29 -> - | L26: =Inputs!L29 -> - | M26: =Inputs!M29 -> - | ... AS26: =Inputs!AS29 -> -
E27: Weight assigned to the vaccine efficacy rate from Uzicanin and Zimmerman 2011 | F27: =Inputs!F30 -> % | G27: =Inputs!G30 -> input | H27: =Inputs!H30 -> 0.35 | I27: =Inputs!I30 -> - | J27: =Inputs!J30 -> - | K27: =Inputs!K30 -> - | L27: =Inputs!L30 -> - | M27: =Inputs!M30 -> - | ... AS27: =Inputs!AS30 -> -
C29: Adjustment for geography-specific vaccine efficacy
E30: Estimated measles vaccine efficacy rate in New Incentives' program areas | F30: % | G30: calc | H30: =SUMPRODUCT(H18:H21,H24:H27) -> 0.63205348 | I30: - | J30: - | K30: - | L30: - | M30: - | N30: - | O30: - | P30: - | Q30: - | R30: - | S30: - | T30: - | U30: - | V30: - | W30: - | X30: - | Y30: - | Z30: - | AA30: - | AB30: - | AC30: - | AD30: - | AE30: - | AF30: - | AG30: - | AH30: - | AI30: - | AJ30: - | AK30: - | AL30: - | AM30: - | AN30: - | AO30: - | AP30: - | AQ30: - | AR30: - | AS30: -
E31: Adjustment for geography-specific measles vaccine efficacy | F31: % | G31: calc | H31: =(H30/H18)-1 -> -0.25640767 | I31: - | J31: - | K31: - | L31: - | M31: - | N31: - | O31: - | P31: - | Q31: - | R31: - | S31: - | T31: - | U31: - | V31: - | W31: - | X31: - | Y31: - | Z31: - | AA31: - | AB31: - | AC31: - | AD31: - | AE31: - | AF31: - | AG31: - | AH31: - | AI31: - | AJ31: - | AK31: - | AL31: - | AM31: - | AN31: - | AO31: - | AP31: - | AQ31: - | AR31: - | AS31: -
E32: Proportion of the adjustment for geography-specific measles vaccine efficacy that applies to other vaccines | F32: =Inputs!F31 -> % | G32: =Inputs!G31 -> input | H32: =Inputs!H31 -> 0.75 | I32: =Inputs!I31 -> - | J32: =Inputs!J31 -> - | K32: =Inputs!K31 -> - | L32: =Inputs!L31 -> - | M32: =Inputs!M31 -> - | ... AS32: =Inputs!AS31 -> -
E33: Adjustment for geography-specific vaccine efficacy for non-measles vaccines | F33: % | G33: calc | H33: =H31*H32 -> -0.19230575 | I33: - | J33: - | K33: - | L33: - | M33: - | N33: - | O33: - | P33: - | Q33: - | R33: - | S33: - | T33: - | U33: - | V33: - | W33: - | X33: - | Y33: - | Z33: - | AA33: - | AB33: - | AC33: - | AD33: - | AE33: - | AF33: - | AG33: - | AH33: - | AI33: - | AJ33: - | AK33: - | AL33: - | AM33: - | AN33: - | AO33: - | AP33: - | AQ33: - | AR33: - | AS33: -
C35: Adjusted vaccine efficacy in program areas
E36: BCG vaccine efficacy rate in program areas | F36: % | G36: calc | H36: =H8*(1+H$33) -> 0.68654011 | I36: - | J36: - | K36: - | L36: - | M36: - | N36: - | O36: - | P36: - | Q36: - | R36: - | S36: - | T36: - | U36: - | V36: - | W36: - | X36: - | Y36: - | Z36: - | AA36: - | AB36: - | AC36: - | AD36: - | AE36: - | AF36: - | AG36: - | AH36: - | AI36: - | AJ36: - | AK36: - | AL36: - | AM36: - | AN36: - | AO36: - | AP36: - | AQ36: - | AR36: - | AS36: -
E37: DTP vaccine efficacy rate in program areas (part of the Penta vaccine) | F37: % | G37: calc | H37: =H9*(1+H$33) -> 0.67846317 | I37: - | J37: - | K37: - | L37: - | M37: - | N37: - | O37: - | P37: - | Q37: - | R37: - | S37: - | T37: - | U37: - | V37: - | W37: - | X37: - | Y37: - | Z37: - | AA37: - | AB37: - | AC37: - | AD37: - | AE37: - | AF37: - | AG37: - | AH37: - | AI37: - | AJ37: - | AK37: - | AL37: - | AM37: - | AN37: - | AO37: - | AP37: - | AQ37: - | AR37: - | AS37: -
E38: Hib vaccine efficacy rate in program areas (part of the Penta vaccine) | F38: % | G38: calc | H38: =H10*(1+H$33) -> 0.66230928 | I38: - | J38: - | K38: - | L38: - | M38: - | N38: - | O38: - | P38: - | Q38: - | R38: - | S38: - | T38: - | U38: - | V38: - | W38: - | X38: - | Y38: - | Z38: - | AA38: - | AB38: - | AC38: - | AD38: - | AE38: - | AF38: - | AG38: - | AH38: - | AI38: - | AJ38: - | AK38: - | AL38: - | AM38: - | AN38: - | AO38: - | AP38: - | AQ38: - | AR38: - | AS38: -
E39: PCV vaccine efficacy rate in program areas | F39: % | G39: calc | H39: =H11*(1+H$33) -> 0.46846266 | I39: - | J39: - | K39: - | L39: - | M39: - | N39: - | O39: - | P39: - | Q39: - | R39: - | S39: - | T39: - | U39: - | V39: - | W39: - | X39: - | Y39: - | Z39: - | AA39: - | AB39: - | AC39: - | AD39: - | AE39: - | AF39: - | AG39: - | AH39: - | AI39: - | AJ39: - | AK39: - | AL39: - | AM39: - | AN39: - | AO39: - | AP39: - | AQ39: - | AR39: - | AS39: -
E40: Rotavirus vaccine efficacy rate in program areas | F40: % | G40: calc | H40: =H12*(1+H$33) -> 0.37153935 | I40: - | J40: - | K40: - | L40: - | M40: - | N40: - | O40: - | P40: - | Q40: - | R40: - | S40: - | T40: - | U40: - | V40: - | W40: - | X40: - | Y40: - | Z40: - | AA40: - | AB40: - | AC40: - | AD40: - | AE40: - | AF40: - | AG40: - | AH40: - | AI40: - | AJ40: - | AK40: - | AL40: - | AM40: - | AN40: - | AO40: - | AP40: - | AQ40: - | AR40: - | AS40: -
